Workbook
Name Payment_Needed: "Pago necesario"
Name Reimbursement: "Reembolso"

Sheet RESUMEN
D2: Capítulo GDL
D3: Real 2025 | E3: Ppto. 2025 | F3: Real 2024 | G3: Variación Real 2024 vs Real 2025 | H3: Variación Ppto. 2025 vs Real 2025
C5: INCOME | D5: =SUM(D6,D9,D11,D13) -> 7429941.9 | E5: =SUM(E6,E9,E11,E13) -> 7988990.8 | F5: =SUM(F6,F9,F11,F13) -> 6768264 | G5: =IF((IFERROR(D5/F5,0))=0,0,(IFERROR(D5/F5,0)-1)) -> 0.097761837 | H5: =IF((IFERROR(D5/E5,0))=0,0,(IFERROR(D5/E5,0)-1)) -> -0.06997741
C6: Membership | D6: =D7+D8 -> 6021827.2 | E6: =E7+E8 -> 5769308.5 | F6: =F7+F8 -> 5730814 | G6: =IF((IFERROR(D6/F6,0))=0,0,(IFERROR(D6/F6,0)-1)) -> 0.050780435 | H6: =IF((IFERROR(D6/E6,0))=0,0,(IFERROR(D6/E6,0)-1)) -> 0.043769323
B7: 4e+20 | C7: Cuotas Netas | D7: =SUMIF('PPvsREal Summary'!$C:$C,RESUMEN!B7,'PPvsREal Summary'!$AD:$AD) -> 5813127.2 | E7: =SUMIF('PPvsREal Summary'!$C:$C,RESUMEN!B7,'PPvsREal Summary'!$AC:$AC) -> 5262808.5 | F7: 5475214 | G7: =IF((IFERROR(D7/F7,0))=0,0,(IFERROR(D7/F7,0)-1)) -> 0.061716899 | H7: =IF((IFERROR(D7/E7,0))=0,0,(IFERROR(D7/E7,0)-1)) -> 0.1045675
B8: 4.01e+20 | C8: Ingresos socios nuevos | D8: =SUMIF('PPvsREal Summary'!$C:$C,RESUMEN!B8,'PPvsREal Summary'!$AD:$AD) -> 208700 | E8: =SUMIF('PPvsREal Summary'!$C:$C,RESUMEN!B8,'PPvsREal Summary'!$AC:$AC) -> 506500 | F8: 255600 | G8: =IF((IFERROR(D8/F8,0))=0,0,(IFERROR(D8/F8,0)-1)) -> -0.18348983 | H8: =IF((IFERROR(D8/E8,0))=0,0,(IFERROR(D8/E8,0)-1)) -> -0.58795656
C9: Events | D9: =D10 -> 468782.76 | E9: =E10 -> 945000 | F9: =F10 -> 453300 | G9: =IF((IFERROR(D9/F9,0))=0,0,(IFERROR(D9/F9,0)-1)) -> 0.034155659 | H9: =IF((IFERROR(D9/E9,0))=0,0,(IFERROR(D9/E9,0)-1)) -> -0.50393359
B10: 4.05e+20 | C10: Eventos | D10: =SUMIF('PPvsREal Summary'!$C:$C,RESUMEN!B10,'PPvsREal Summary'!$AD:$AD) -> 468782.76 | E10: =SUMIF('PPvsREal Summary'!$C:$C,RESUMEN!B10,'PPvsREal Summary'!$AC:$AC) -> 945000 | F10: 453300 | G10: =IF((IFERROR(D10/F10,0))=0,0,(IFERROR(D10/F10,0)-1)) -> 0.034155659 | H10: =IF((IFERROR(D10/E10,0))=0,0,(IFERROR(D10/E10,0)-1)) -> -0.50393359
C11: Committees | D11: =D12 -> 493931.93 | E11: =E12 -> 943800 | F11: =F12 -> 272150 | G11: =IF((IFERROR(D11/F11,0))=0,0,(IFERROR(D11/F11,0)-1)) -> 0.81492534 | H11: =IF((IFERROR(D11/E11,0))=0,0,(IFERROR(D11/E11,0)-1)) -> -0.47665615
B12: 4.04e+20 | C12: Comités | D12: =SUMIF('PPvsREal Summary'!$C:$C,RESUMEN!B12,'PPvsREal Summary'!$AD:$AD) -> 493931.93 | E12: =SUMIF('PPvsREal Summary'!$C:$C,RESUMEN!B12,'PPvsREal Summary'!$AC:$AC) -> 943800 | F12: 272150 | G12: =IF((IFERROR(D12/F12,0))=0,0,(IFERROR(D12/F12,0)-1)) -> 0.81492534 | H12: =IF((IFERROR(D12/E12,0))=0,0,(IFERROR(D12/E12,0)-1)) -> -0.47665615
C13: Services to Members | D13: =D14+D15 -> 445400 | E13: =E14+E15 -> 330882.3 | F13: =F14+F15 -> 312000 | G13: =IF((IFERROR(D13/F13,0))=0,0,(IFERROR(D13/F13,0)-1)) -> 0.4275641 | H13: =IF((IFERROR(D13/E13,0))=0,0,(IFERROR(D13/E13,0)-1)) -> 0.34609799
B14: 4.03e+20 | C14: Venta Publicaciones | D14: =SUMIF('PPvsREal Summary'!$C:$C,RESUMEN!B14,'PPvsREal Summary'!$AD:$AD) -> 445400 | E14: =SUMIF('PPvsREal Summary'!$C:$C,RESUMEN!B14,'PPvsREal Summary'!$AC:$AC) -> 330882.3 | F14: 312000 | G14: =IF((IFERROR(D14/F14,0))=0,0,(IFERROR(D14/F14,0)-1)) -> 0.4275641 | H14: =IF((IFERROR(D14/E14,0))=0,0,(IFERROR(D14/E14,0)-1)) -> 0.34609799
B15: 4.08e+20 | C15: Visas | D15: =SUMIF('PPvsREal Summary'!$C:$C,RESUMEN!B15,'PPvsREal Summary'!$AD:$AD) -> 0 | E15: =SUMIF('PPvsREal Summary'!$C:$C,RESUMEN!B15,'PPvsREal Summary'!$AC:$AC) -> 0 | F15: 0 | G15: =IF((IFERROR(D15/F15,0))=0,0,(IFERROR(D15/F15,0)-1)) -> 0 | H15: =IF((IFERROR(D15/E15,0))=0,0,(IFERROR(D15/E15,0)-1)) -> 0
C16: EXPENSE | D16: =D17+D20+D22+D24+D27+D30+D31 -> 7802832.5 | E16: =E17+E20+E22+E24+E27+E30+E31 -> 8751333.5 | F16: =F17+F20+F22+F24+F27+F30+F31 -> 6326171.9 | G16: =IF((IFERROR(D16/F16,0))=0,0,(IFERROR(D16/F16,0)-1)) -> 0.23342087 | H16: =IF((IFERROR(D16/E16,0))=0,0,(IFERROR(D16/E16,0)-1)) -> -0.10838359
C17: Membership | D17: =D18+D19 -> 261568.57 | E17: =E18+E19 -> 404257.85 | F17: =F18+F19 -> 291669.44 | G17: =IF((IFERROR(D17/F17,0))=0,0,(IFERROR(D17/F17,0)-1)) -> -0.103202 | H17: =IF((IFERROR(D17/E17,0))=0,0,(IFERROR(D17/E17,0)-1)) -> -0.35296601
B18: 7.02e+20 | C18: Gastos Promoción | D18: =SUMIF('PPvsREal Summary'!$C:$C,RESUMEN!B18,'PPvsREal Summary'!$AD:$AD) -> 8094.57 | E18: =SUMIF('PPvsREal Summary'!$C:$C,RESUMEN!B18,'PPvsREal Summary'!$AC:$AC) -> 80000 | F18: 1380.9 | G18: =IF((IFERROR(D18/F18,0))=0,0,(IFERROR(D18/F18,0)-1)) -> 4.8618075 | H18: =IF((IFERROR(D18/E18,0))=0,0,(IFERROR(D18/E18,0)-1)) -> -0.89881787
B19: 5.0100101e+20 | C19: Comisiones por venta de membresías | D19: =SUMIF('PPvsREal Summary'!$C:$C,RESUMEN!B19,'PPvsREal Summary'!$AD:$AD) -> 253474 | E19: =SUMIF('PPvsREal Summary'!$C:$C,RESUMEN!B19,'PPvsREal Summary'!$AC:$AC) -> 324257.85 | F19: 290288.54 | G19: =IF((IFERROR(D19/F19,0))=0,0,(IFERROR(D19/F19,0)-1)) -> -0.12682051 | H19: =IF((IFERROR(D19/E19,0))=0,0,(IFERROR(D19/E19,0)-1)) -> -0.21829495
C20: Events | D20: =D21 -> 316129.15 | E20: =E21 -> 756045 | F20: =F21 -> 207965.48 | G20: =IF((IFERROR(D20/F20,0))=0,0,(IFERROR(D20/F20,0)-1)) -> 0.52010396 | H20: =IF((IFERROR(D20/E20,0))=0,0,(IFERROR(D20/E20,0)-1)) -> -0.58186464
B21: 7.01e+20 | C21: Costo Eventos | D21: =SUMIF('PPvsREal Summary'!$C:$C,RESUMEN!B21,'PPvsREal Summary'!$AD:$AD) -> 316129.15 | E21: =SUMIF('PPvsREal Summary'!$C:$C,RESUMEN!B21,'PPvsREal Summary'!$AC:$AC) -> 756045 | F21: 207965.48 | G21: =IF((IFERROR(D21/F21,0))=0,0,(IFERROR(D21/F21,0)-1)) -> 0.52010396 | H21: =IF((IFERROR(D21/E21,0))=0,0,(IFERROR(D21/E21,0)-1)) -> -0.58186464
C22: Committees | D22: =D23 -> 436752.04 | E22: =E23 -> 485280 | F22: =F23 -> 174406.29 | G22: =IF((IFERROR(D22/F22,0))=0,0,(IFERROR(D22/F22,0)-1)) -> 1.5042218 | H22: =IF((IFERROR(D22/E22,0))=0,0,(IFERROR(D22/E22,0)-1)) -> -0.099999918
B23: 5.02e+20 | C23: Costo comités | D23: =SUMIF('PPvsREal Summary'!$C:$C,RESUMEN!B23,'PPvsREal Summary'!$AD:$AD) -> 436752.04 | E23: =SUMIF('PPvsREal Summary'!$C:$C,RESUMEN!B23,'PPvsREal Summary'!$AC:$AC) -> 485280 | F23: 174406.29 | G23: =IF((IFERROR(D23/F23,0))=0,0,(IFERROR(D23/F23,0)-1)) -> 1.5042218 | H23: =IF((IFERROR(D23/E23,0))=0,0,(IFERROR(D23/E23,0)-1)) -> -0.099999918
C24: Services to Members | D24: =D25+D26 -> 269801.39 | E24: =E25+E26 -> 225941.15 | F24: =F25+F26 -> 188297.04 | G24: =IF((IFERROR(D24/F24,0))=0,0,(IFERROR(D24/F24,0)-1)) -> 0.43284987 | H24: =IF((IFERROR(D24/E24,0))=0,0,(IFERROR(D24/E24,0)-1)) -> 0.19412241
B25: 6.01e+20 | C25: Gastos directos de publicación | D25: =SUMIF('PPvsREal Summary'!$C:$C,RESUMEN!B25,'PPvsREal Summary'!$AD:$AD) -> 222700 | E25: =SUMIF('PPvsREal Summary'!$C:$C,RESUMEN!B25,'PPvsREal Summary'!$AC:$AC) -> 165441.15 | F25: 156000 | G25: =IF((IFERROR(D25/F25,0))=0,0,(IFERROR(D25/F25,0)-1)) -> 0.4275641 | H25: =IF((IFERROR(D25/E25,0))=0,0,(IFERROR(D25/E25,0)-1)) -> 0.34609799
B26: 9.02e+20 | C26: Gtos promoción y juntas de trabajo | D26: =SUMIF('PPvsREal Summary'!$C:$C,RESUMEN!B26,'PPvsREal Summary'!$AD:$AD) -> 47101.39 | E26: =SUMIF('PPvsREal Summary'!$C:$C,RESUMEN!B26,'PPvsREal Summary'!$AC:$AC) -> 60500 | F26: 32297.04 | G26: =IF((IFERROR(D26/F26,0))=0,0,(IFERROR(D26/F26,0)-1)) -> 0.45838102 | H26: =IF((IFERROR(D26/E26,0))=0,0,(IFERROR(D26/E26,0)-1)) -> -0.22146463
C27: Gastos Administrativos | D27: =D28+D29 -> 1078577.2 | E27: =E28+E29 -> 1255838.4 | F27: =F28+F29 -> 773979.89 | G27: =IF((IFERROR(D27/F27,0))=0,0,(IFERROR(D27/F27,0)-1)) -> 0.39354684 | H27: =IF((IFERROR(D27/E27,0))=0,0,(IFERROR(D27/E27,0)-1)) -> -0.14114966
B28: 8.01e+20 | C28: Gasto de local | D28: =SUMIF('PPvsREal Summary'!$C:$C,RESUMEN!B28,'PPvsREal Summary'!$AD:$AD) -> 230633.03 | E28: =SUMIF('PPvsREal Summary'!$C:$C,RESUMEN!B28,'PPvsREal Summary'!$AC:$AC) -> 332625.02 | F28: 109786.66 | G28: =IF((IFERROR(D28/F28,0))=0,0,(IFERROR(D28/F28,0)-1)) -> 1.1007382 | H28: =IF((IFERROR(D28/E28,0))=0,0,(IFERROR(D28/E28,0)-1)) -> -0.30662754
B29: 9.01e+20 | C29: Gastos de Administracion | D29: =SUMIF('PPvsREal Summary'!$C:$C,RESUMEN!B29,'PPvsREal Summary'!$AD:$AD) -> 847944.2 | E29: =SUMIF('PPvsREal Summary'!$C:$C,RESUMEN!B29,'PPvsREal Summary'!$AC:$AC) -> 923213.38 | F29: 664193.23 | G29: =IF((IFERROR(D29/F29,0))=0,0,(IFERROR(D29/F29,0)-1)) -> 0.27665288 | H29: =IF((IFERROR(D29/E29,0))=0,0,(IFERROR(D29/E29,0)-1)) -> -0.081529558
B30: 5.01e+20 | C30: Nómina | D30: =SUMIF('PPvsREal Summary'!$C:$C,RESUMEN!B30,'PPvsREal Summary'!$AD:$AD) -> 3313718.6 | E30: =SUMIF('PPvsREal Summary'!$C:$C,RESUMEN!B30,'PPvsREal Summary'!$AC:$AC) -> 3336915 | F30: 2638976.5 | G30: =IF((IFERROR(D30/F30,0))=0,0,(IFERROR(D30/F30,0)-1)) -> 0.25568328 | H30: =IF((IFERROR(D30/E30,0))=0,0,(IFERROR(D30/E30,0)-1)) -> -0.0069514357
B31: 9.03e+20 | C31: Gastos Corporativos | D31: =SUMIF('PPvsREal Summary'!$C:$C,RESUMEN!B31,'PPvsREal Summary'!$AD:$AD) -> 2126285.5 | E31: =SUMIF('PPvsREal Summary'!$C:$C,RESUMEN!B31,'PPvsREal Summary'!$AC:$AC) -> 2287056.1 | F31: 2050877.3 | G31: =IF((IFERROR(D31/F31,0))=0,0,(IFERROR(D31/F31,0)-1)) -> 0.036768742 | H31: =IF((IFERROR(D31/E31,0))=0,0,(IFERROR(D31/E31,0)-1)) -> -0.070295872 | I31: cuenta de gastos corporativos
C32: OPERATING RESULTS | D32: =+D5-D16 -> -372890.61 | E32: =+E5-E16 -> -762342.7 | F32: =+F5-F16 -> 442092.05 | G32: =IF((IFERROR(D32/F32,0))=0,0,(IFERROR(D32/F32,0)-1)) -> -1.8434683 | H32: =IF((IFERROR(D32/E32,0))=0,0,(IFERROR(D32/E32,0)-1)) -> -0.51086223
B33: 9.04e+20 | C33: Member Centricity | D33: =SUMIF('PPvsREal Summary'!$C:$C,RESUMEN!B33,'PPvsREal Summary'!$AD:$AD) -> 348146.81 | E33: =SUMIF('PPvsREal Summary'!$C:$C,RESUMEN!B33,'PPvsREal Summary'!$AC:$AC) -> 0 | F33: 212205.32 | G33: =IF((IFERROR(D33/F33,0))=0,0,(IFERROR(D33/F33,0)-1)) -> 0.64061302 | H33: =IF((IFERROR(D33/E33,0))=0,0,(IFERROR(D33/E33,0)-1)) -> 0
C34: Other | D34: =D35+D36 -> 128.96 | E34: =E35+E36 -> 0 | F34: =F35+F36 -> 82234.73 | G34: =IF((IFERROR(D34/F34,0))=0,0,(IFERROR(D34/F34,0)-1)) -> -0.99843181 | H34: =IF((IFERROR(D34/E34,0))=0,0,(IFERROR(D34/E34,0)-1)) -> 0
B35: 4.02e+20 | C35: Otros ingresos | D35: =SUMIF('PPvsREal Summary'!$C:$C,RESUMEN!B35,'PPvsREal Summary'!$AD:$AD) -> 128.96 | E35: =SUMIF('PPvsREal Summary'!$C:$C,RESUMEN!B35,'PPvsREal Summary'!$AC:$AC) -> 0 | F35: 81377.88 | G35: =IF((IFERROR(D35/F35,0))=0,0,(IFERROR(D35/F35,0)-1)) -> -0.99841529 | H35: =IF((IFERROR(D35/E35,0))=0,0,(IFERROR(D35/E35,0)-1)) -> 0
B36: 4.1e+20 | C36: Utilidad cambiaria | D36: =SUMIF('PPvsREal Summary'!$C:$C,RESUMEN!B36,'PPvsREal Summary'!$AD:$AD) -> 0 | E36: =SUMIF('PPvsREal Summary'!$C:$C,RESUMEN!B36,'PPvsREal Summary'!$AC:$AC) -> 0 | F36: 856.85 | G36: =IF((IFERROR(D36/F36,0))=0,0,(IFERROR(D36/F36,0)-1)) -> 0 | H36: =IF((IFERROR(D36/E36,0))=0,0,(IFERROR(D36/E36,0)-1)) -> 0
C37: NET RESULTS | D37: =D32-D33+D34 -> -720908.46 | E37: =E32-E33+E34 -> -762342.7 | F37: =F32-F33+F34 -> 312121.46 | G37: =IF((IFERROR(D37/F37,0))=0,0,(IFERROR(D37/F37,0)-1)) -> -3.3097049 | H37: =IF((IFERROR(D37/E37,0))=0,0,(IFERROR(D37/E37,0)-1)) -> -0.054351201

Sheet Gtos. Corporativos
C1: AMERICAN CHAMBER OF COMMERCE OF MEXICO, A.C.
C3: GASTOS CORPORATIVOS 2025 | D3: Real 2024 GDL | E3: Presupuesto 2024 | F3: Presupuesto 2025 | G3: Criterio | H3: Mensual
B5: 903-034-000-00 | C5: Seguro Gtos Médicos Mayores | D5: 446958.48 | E5: 559381.02 | F5: 551169.52 | G5: Costo Directo | H5: =F5/12 -> 45930.793
B6: 903-033-000-00 | C6: Seguro de Vida | D6: 24288.1 | E6: 16419.403 | F6: 25643.5 | G6: Costo Directo | H6: =F6/12 -> 2136.9583
B7: 903-002-000-00 | C7: Seguro Empresarial | D7: 18039.24 | E7: 22058.218 | F7: 20502.54 | G7: Costo Directo | H7: =F7/12 -> 1708.545
B8: 903-003-000-00 | C8: PAE | D8: 7422.69 | E8: 6898.3215 | F8: 8433.3795 | G8: Costo Directo | H8: =F8/12 -> 702.78163
B9: 903-030-000-00 | C9: Hosting /VPS | D9: 23393.39 | E9: 93489.642 | F9: 19500 | G9: 0.13 | H9: =F9/12 -> 1625
B10: 903-032-000-00 | C10: Outsourcing TI | D10: 56537.49 | E10: 63536.256 | F10: 0 | G10: 0.13 | H10: =F10/12 -> 0
B11: 903-032-000-00 | C11: Póliza soporte y mantenimiento SIA | D11: 0 | E11: 0 | F11: 56180.233 | G11: 0.13 | H11: =F11/12 -> 4681.6861
B12: 903-018-000-00 | C12: MCM/Internet/telefonía IP | D12: 117696 | E12: 118909.63 | F12: 100409.4 | G12: 0.13 | H12: =F12/12 -> 8367.45
B13: 903-023-000-00/903-031-000-00/903-035-000-00 | C13: Actualizaciones de software (COI, office, antivirus, licencias, timbres, etc) | D13: 28507.91 | E13: 26082.022 | F13: 30421.601 | G13: 0.13 | H13: =F13/12 -> 2535.1334
B14: 903-028-000-00 | C14: Licencias Google Apps | D14: 52305.06 | E14: 56337.12 | F14: 62162.1 | G14: 0.13 | H14: =F14/12 -> 5180.175
B15: 903-011-000-00 | C15: Estudio actuarial | D15: 3801.42 | E15: 3730.4299 | F15: 3243.1035 | G15: 0.13 | H15: =F15/12 -> 270.25862
B16: 903-012-000-00 | C16: Gtos Notariales | D16: 1884 | E16: 1883.52 | F16: 1606.878 | G16: 0.13 | H16: =F16/12 -> 133.9065
B17: 903-017-000-00 / 903-013-000-00 / 903-004-000-00 | C17: Honorarios Auditoría financiera, seguro social y fiscal | D17: 67863.84 | E17: 67863.814 | F17: 65005.2 | G17: 0.13 | H17: =F17/12 -> 5417.1
B18: 903-014-000-00 | C18: Registro de Marcas | D18: 5436 | E18: 5440 | F18: 6342.83 | G18: 0.13 | H18: =F18/12 -> 528.56917
B19: 903-015-000-00 | C19: Costo Anual AACCLA | D19: 51943.89 | E19: 63504 | F19: 60196.5 | G19: 0.13 | H19: =F19/12 -> 5016.375
B20: 903-022-000-00 | C20: Almacen de Archivos AAA | D20: 7264.44 | E20: 6971.9933 | F20: 4017 | G20: 0.13 | H20: =F20/12 -> 334.75
B21: 903-024-000-00 | C21: Herramientas T&IC (plataformas, créditos, etc.) | D21: 109672.75 | E21: 107635.08 | F21: 108856.37 | G21: 0.13 | H21: =F21/12 -> 9071.3641
B22: 903-005-000-00 | C22: Linkedln | D22: 53586.893 | E22: 61699.226 | F22: 71982.431 | G22: Costo Directo | H22: =F22/12 -> 5998.5359
B23: 903-005-000-00 | C23: ZOOM | D23: 9101.0766 | E23: 8964.648 | F23: 9125.5887 | G23: 0.13 | H23: =F23/12 -> 760.46573
B24: 903-016-000-00 | C24: Sueldos y Salarios VPE/Nacionales | D24: 2436719.4 | E24: 2436719.4 | F24: 2715869.4 | G24: 0.13 | H24: =F24/12 -> 226322.45
C26: TOTAL CARGOS CORPORATIVOS | D26: =SUM(D5:D24) -> 3522422.1 | E26: =SUM(E5:E24) -> 3727523.7 | F26: =SUM(F5:F24) -> 3920667.6 | H26: =SUM(H5:H24) -> 326722.3

Sheet Gtos. Corporativos (P)
C1: AMERICAN CHAMBER OF COMMERCE OF MEXICO, A.C.
C3: GASTOS CORPORATIVOS 2025 | D3: Forecast 11+1 GDL | E3: Presupuesto 2024 | F3: Presupuesto 2025 | G3: Criterio | H3: Mensual | J3: Ene. 25 | K3: Ppto. Ene. 25 | L3: Feb. 25 | M3: Ppto. Feb. 25 | N3: Mar. 25 | O3: Ppto. Mar. 25 | P3: Abr. 25 | Q3: Ppto. Abr. 25 | R3: May. 25 | S3: Ppto. May. 25 | T3: Jun. 25 | U3: Ppto. Jun.. 25 | V3: Jul. 25 | W3: Ppto. Jul. 25 | AB3: Real Acumulado 2025 | AC3: Ppto. Acumulado 2025
B5: 903-034-000-00 | C5: Seguro Gtos Médicos Mayores | D5: 459301.43 | E5: 559381.02 | F5: 551169.52 | G5: Costo Directo | H5: =F5/12 -> 45930.793 | J5: 29024.43 | K5: 45930.793 | L5: 29024.43 | M5: 45930.793 | N5: 36950.92 | O5: 45930.793 | P5: 29024.43 | Q5: 45930.793 | R5: 37048.21 | S5: 45930.793 | T5: 31699.02 | U5: 45930.793 | V5: 31699.02 | W5: =U5 -> 45930.793 | AB5: =J5+L5+N5+P5+R5+T5+V5+X5+Z5 -> 224470.46 | AC5: =K5+M5+O5+Q5+S5+U5+W5+Y5+AA5 -> 321515.55
B6: 903-033-000-00 | C6: Seguro de Vida | D6: 24033.68 | E6: 16419.403 | F6: 25643.5 | G6: Costo Directo | H6: =F6/12 -> 2136.9583 | J6: 2137 | K6: 2136.9583 | L6: 699.32 | M6: 2136.9583 | N6: 2355.08 | O6: 2136.9583 | P6: 1247.95 | Q6: 2136.9583 | R6: 1660.28 | S6: 2136.9583 | T6: 1385.39 | U6: 2136.9583 | V6: 1385.39 | W6: =U6 -> 2136.9583 | AB6: =J6+L6+N6+P6+R6+T6+V6+X6+Z6 -> 10870.41 | AC6: =K6+M6+O6+Q6+S6+U6+W6+Y6+AA6 -> 14958.708
B7: 903-002-000-00 | C7: Seguro Empresarial | D7: 18374.15 | E7: 22058.218 | F7: 20502.54 | G7: Costo Directo | H7: =F7/12 -> 1708.545 | J7: 1457 | K7: 1708.545 | L7: 1457 | M7: 1708.545 | N7: 1457 | O7: 1708.545 | P7: 1457 | Q7: 1708.545 | R7: 1457 | S7: 1708.545 | T7: 1457 | U7: 1708.545 | V7: 1457 | W7: =U7 -> 1708.545 | AB7: =J7+L7+N7+P7+R7+T7+V7+X7+Z7 -> 10199 | AC7: =K7+M7+O7+Q7+S7+U7+W7+Y7+AA7 -> 11959.815
B8: 903-003-000-00 | C8: PAE | D8: 7328.23 | E8: 6898.3215 | F8: 8433.3795 | G8: Costo Directo | H8: =F8/12 -> 702.78163 | J8: 669.32 | K8: 702.78163 | L8: 669.32 | M8: 702.78163 | N8: 669.32 | O8: 702.78163 | P8: 669.32 | Q8: 702.78163 | R8: 669.32 | S8: 702.78163 | T8: 878.08 | U8: 702.78163 | V8: 878.08 | W8: =U8 -> 702.78163 | AB8: =J8+L8+N8+P8+R8+T8+V8+X8+Z8 -> 5102.76 | AC8: =K8+M8+O8+Q8+S8+U8+W8+Y8+AA8 -> 4919.4714
B9: 903-030-000-00 | C9: Hosting /VPS | D9: 31158.5 | E9: 93489.642 | F9: 19500 | G9: 0.13 | H9: =F9/12 -> 1625 | J9: 20.87 | K9: 1625 | L9: 20.87 | M9: 1625 | N9: 20.87 | O9: 1625 | P9: 20.87 | Q9: 1625 | R9: 20.87 | S9: 1625 | T9: 20.87 | U9: 1625 | V9: 20.87 | W9: =U9 -> 1625 | AB9: =J9+L9+N9+P9+R9+T9+V9+X9+Z9 -> 146.09 | AC9: =K9+M9+O9+Q9+S9+U9+W9+Y9+AA9 -> 11375
B10: 903-032-000-00 | C10: Outsourcing TI | D10: 57091.13 | E10: 63536.256 | F10: 0 | G10: 0.13 | H10: =F10/12 -> 0 | J10: 0 | K10: 0 | L10: 0 | M10: 0 | N10: 0 | O10: 0 | P10: 0 | Q10: 0 | R10: 0 | S10: 0 | T10: 0 | U10: 0 | V10: 0 | W10: =U10 -> 0 | AB10: =J10+L10+N10+P10+R10+T10+V10+X10+Z10 -> 0 | AC10: =K10+M10+O10+Q10+S10+U10+W10+Y10+AA10 -> 0
B11: 903-032-000-00 | C11: Póliza soporte y mantenimiento SIA | D11: 0 | E11: 0 | F11: 56180.233 | G11: 0.13 | H11: =F11/12 -> 4681.6861 | J11: 0 | K11: 4681.6861 | L11: 0 | M11: 4681.6861 | N11: 0 | O11: 4681.6861 | P11: 0 | Q11: 4681.6861 | R11: 0 | S11: 4681.6861 | T11: 0 | U11: 4681.6861 | V11: 0 | W11: =U11 -> 4681.6861 | AB11: =J11+L11+N11+P11+R11+T11+V11+X11+Z11 -> 0 | AC11: =K11+M11+O11+Q11+S11+U11+W11+Y11+AA11 -> 32771.803
B12: 903-018-000-00 | C12: MCM/Internet/telefonía IP | D12: 117797.14 | E12: 118909.63 | F12: 100409.4 | G12: 0.13 | H12: =F12/12 -> 8367.45 | J12: 7969 | K12: 8367.45 | L12: 7969 | M12: 8367.45 | N12: 7969 | O12: 8367.45 | P12: 7969 | Q12: 8367.45 | R12: 7969 | S12: 8367.45 | T12: 7969 | U12: 8367.45 | V12: 7969 | W12: =U12 -> 8367.45 | AB12: =J12+L12+N12+P12+R12+T12+V12+X12+Z12 -> 55783 | AC12: =K12+M12+O12+Q12+S12+U12+W12+Y12+AA12 -> 58572.15
B13: 903-023-000-00/903-031-000-00/903-035-000-00 | C13: Actualizaciones de software (COI, office, antivirus, licencias, timbres, etc) | D13: 27997.97 | E13: 26082.022 | F13: 30421.601 | G13: 0.13 | H13: =F13/12 -> 2535.1334 | J13: 2917.4 | K13: 2535.1334 | L13: 2917.4 | M13: 2535.1334 | N13: 3001.43 | O13: 2535.1334 | P13: 3496.17 | Q13: 2535.1334 | R13: 4106.82 | S13: 2535.1334 | T13: 4000.13 | U13: 2535.1334 | V13: 4582.89 | W13: =U13 -> 2535.1334 | AB13: =J13+L13+N13+P13+R13+T13+V13+X13+Z13 -> 25022.24 | AC13: =K13+M13+O13+Q13+S13+U13+W13+Y13+AA13 -> 17745.934
B14: 903-028-000-00 | C14: Licencias Google Apps | D14: 52569.18 | E14: 56337.12 | F14: 62162.1 | G14: 0.13 | H14: =F14/12 -> 5180.175 | J14: 3578.47 | K14: 5180.175 | L14: 3578.47 | M14: 5180.175 | N14: 3578.47 | O14: 5180.175 | P14: 3578.47 | Q14: 5180.175 | R14: 5468.47 | S14: 5180.175 | T14: 3578.43 | U14: 5180.175 | V14: 4328.03 | W14: =U14 -> 5180.175 | AB14: =J14+L14+N14+P14+R14+T14+V14+X14+Z14 -> 27688.81 | AC14: =K14+M14+O14+Q14+S14+U14+W14+Y14+AA14 -> 36261.225
B15: 903-011-000-00 | C15: Estudio actuarial | D15: 3795.56 | E15: 3730.4299 | F15: 3243.1035 | G15: 0.13 | H15: =F15/12 -> 270.25862 | J15: 269.23 | K15: 270.25862 | L15: 269.23 | M15: 270.25862 | N15: 269.23 | O15: 270.25862 | P15: 269.23 | Q15: 270.25862 | R15: 269.23 | S15: 270.25862 | T15: 269.23 | U15: 270.25862 | V15: 269.23 | W15: =U15 -> 270.25862 | AB15: =J15+L15+N15+P15+R15+T15+V15+X15+Z15 -> 1884.61 | AC15: =K15+M15+O15+Q15+S15+U15+W15+Y15+AA15 -> 1891.8104
B16: 903-012-000-00 | C16: Gtos Notariales | D16: 1883.96 | E16: 1883.52 | F16: 1606.878 | G16: 0.13 | H16: =F16/12 -> 133.9065 | J16: 134 | K16: 133.9065 | L16: 134 | M16: 133.9065 | N16: 134 | O16: 133.9065 | P16: 134 | Q16: 133.9065 | R16: 134 | S16: 133.9065 | T16: 134 | U16: 133.9065 | V16: 134 | W16: =U16 -> 133.9065 | AB16: =J16+L16+N16+P16+R16+T16+V16+X16+Z16 -> 938 | AC16: =K16+M16+O16+Q16+S16+U16+W16+Y16+AA16 -> 937.3455
B17: 903-017-000-00 / 903-013-000-00 / 903-004-000-00 | C17: Honorarios Auditoría financiera, seguro social y fiscal | D17: 67863.84 | E17: 67863.814 | F17: 65005.2 | G17: 0.13 | H17: =F17/12 -> 5417.1 | J17: 5417.1 | K17: 5417.1 | L17: 5417.1 | M17: 5417.1 | N17: 5417.1 | O17: 5417.1 | P17: 5417.1 | Q17: 5417.1 | R17: 5417.1 | S17: 5417.1 | T17: 5417.1 | U17: 5417.1 | V17: 5417.1 | W17: =U17 -> 5417.1 | AB17: =J17+L17+N17+P17+R17+T17+V17+X17+Z17 -> 37919.7 | AC17: =K17+M17+O17+Q17+S17+U17+W17+Y17+AA17 -> 37919.7
B18: 903-014-000-00 | C18: Registro de Marcas | D18: 5436.33 | E18: 5440 | F18: 6342.83 | G18: 0.13 | H18: =F18/12 -> 528.56917 | J18: 529 | K18: 528.56917 | L18: 529 | M18: 528.56917 | N18: 529 | O18: 528.56917 | P18: 529 | Q18: 528.56917 | R18: 529 | S18: 528.56917 | T18: 529 | U18: 528.56917 | V18: 529 | W18: =U18 -> 528.56917 | AB18: =J18+L18+N18+P18+R18+T18+V18+X18+Z18 -> 3703 | AC18: =K18+M18+O18+Q18+S18+U18+W18+Y18+AA18 -> 3699.9842
B19: 903-015-000-00 | C19: Costo Anual AACCLA | D19: 52461.14 | E19: 63504 | F19: 60196.5 | G19: 0.13 | H19: =F19/12 -> 5016.375 | J19: 3879.49 | K19: 5016.375 | L19: 3879.49 | M19: 5016.375 | N19: 3879.49 | O19: 5016.375 | P19: 4267.44 | Q19: 5016.375 | R19: 4267.44 | S19: 5016.375 | T19: 4267.44 | U19: 5016.375 | V19: 4267.44 | W19: =U19 -> 5016.375 | AB19: =J19+L19+N19+P19+R19+T19+V19+X19+Z19 -> 28708.23 | AC19: =K19+M19+O19+Q19+S19+U19+W19+Y19+AA19 -> 35114.625
B20: 903-022-000-00 | C20: Almacen de Archivos AAA | D20: 7466.41 | E20: 6971.9933 | F20: 4017 | G20: 0.13 | H20: =F20/12 -> 334.75 | J20: 344.77 | K20: 334.75 | L20: 344.77 | M20: 334.75 | N20: 344.77 | O20: 334.75 | P20: 493.92 | Q20: 334.75 | R20: 521.29 | S20: 334.75 | T20: 305.32 | U20: 334.75 | V20: 305.32 | W20: =U20 -> 334.75 | AB20: =J20+L20+N20+P20+R20+T20+V20+X20+Z20 -> 2660.16 | AC20: =K20+M20+O20+Q20+S20+U20+W20+Y20+AA20 -> 2343.25
B21: 903-024-000-00 | C21: Herramientas T&IC (plataformas, créditos, etc.) | D21: 107191.8 | E21: 107635.08 | F21: 108856.37 | G21: 0.13 | H21: =F21/12 -> 9071.3641 | J21: 9303.57 | K21: 9071.3641 | L21: 9303.57 | M21: 9071.3641 | N21: 9303.57 | O21: 9071.3641 | P21: 9303.57 | Q21: 9071.3641 | R21: 10153.87 | S21: 9071.3641 | T21: 10153.87 | U21: 9071.3641 | V21: 10153.87 | W21: =U21 -> 9071.3641 | AB21: =J21+L21+N21+P21+R21+T21+V21+X21+Z21 -> 67675.89 | AC21: =K21+M21+O21+Q21+S21+U21+W21+Y21+AA21 -> 63499.549
B22: 903-005-000-00 | C22: Linkedln | D22: 53835.4 | E22: 61699.226 | F22: 71982.431 | G22: Costo Directo | H22: =F22/12 -> 5998.5359 | J22: 4893.1 | K22: 5998.5359 | L22: 4893.1 | M22: 5998.5359 | N22: 4893.1 | O22: 5998.5359 | P22: 4893.1 | Q22: 5998.5359 | R22: 4893.1 | S22: 5998.5359 | T22: 4893.1 | U22: 5998.5359 | V22: 4893.1 | W22: =U22 -> 5998.5359 | AB22: =J22+L22+N22+P22+R22+T22+V22+X22+Z22 -> 34251.7 | AC22: =K22+M22+O22+Q22+S22+U22+W22+Y22+AA22 -> 41989.751
B23: 903-005-000-00 | C23: ZOOM | D23: 8967.69 | E23: 8964.648 | F23: 9125.5887 | G23: 0.13 | H23: =F23/12 -> 760.46573 | J23: 715.35 | K23: 760.46573 | L23: 715.35 | M23: 760.46573 | N23: 715.35 | O23: 760.46573 | P23: 715.35 | Q23: 760.46573 | R23: 715.35 | S23: 760.46573 | T23: 715.35 | U23: 760.46573 | V23: 715.35 | W23: =U23 -> 760.46573 | AB23: =J23+L23+N23+P23+R23+T23+V23+X23+Z23 -> 5007.45 | AC23: =K23+M23+O23+Q23+S23+U23+W23+Y23+AA23 -> 5323.2601
B24: 903-016-000-00 | C24: Sueldos y Salarios VPE/Nacionales | D24: 2436719.4 | E24: 2436719.4 | F24: 2715869.4 | G24: 0.13 | H24: =F24/12 -> 226322.45 | J24: 226322 | K24: 226322.45 | L24: 226322 | M24: 226322.45 | N24: 226322 | O24: 226322.45 | P24: 226322 | Q24: 226322.45 | R24: 226322 | S24: 226322.45 | T24: 226322 | U24: 226322.45 | V24: 226322 | W24: =U24 -> 226322.45 | AB24: =J24+L24+N24+P24+R24+T24+V24+X24+Z24 -> 1584254 | AC24: =K24+M24+O24+Q24+S24+U24+W24+Y24+AA24 -> 1584257.2
C26: TOTAL CARGOS CORPORATIVOS | D26: =SUM(D5:D24) -> 3541272.9 | E26: =SUM(E5:E24) -> 3727523.7 | F26: =SUM(F5:F24) -> 3920667.6 | H26: =SUM(H5:H24) -> 326722.3 | J26: =SUM(J5:J24) -> 299581.1 | K26: =SUM(K5:K24) -> 326722.3 | L26: =SUM(L5:L24) -> 298143.42 | M26: =SUM(M5:M24) -> 326722.3 | N26: =SUM(N5:N24) -> 307809.7 | O26: =SUM(O5:O24) -> 326722.3 | P26: =SUM(P5:P24) -> 299807.92 | Q26: =SUM(Q5:Q24) -> 326722.3 | ... W26: =SUM(W5:W24) -> 326722.3 | AB26: =SUM(AB5:AB24) -> 2126285.5 | AC26: =SUM(AC5:AC24) -> 2287056.1

Sheet DN
AD1: Ppto. | AE1: Real
C2: DESARROLLO DE NEGOCIOS | D2: 45658 | E2: 45658 | F2: 45689 | G2: 45689 | H2: 45717 | I2: 45717 | J2: 45748 | K2: 45748 | L2: 45778 | M2: 45778 | N2: 45809 | O2: 45809 | P2: 45839 | Q2: 45839 | R2: 45870 | S2: 45870 | T2: 45901 | U2: 45901 | V2: 45931 | W2: 45931 | X2: 45962 | Y2: 45962 | Z2: 45992 | AA2: 45992 | AB2: 2025 | AD2: Acumulado | AE2: Acumulado
C4: Ingresos Desarrollo de Negocios
B5: 400-000-000-00 | C5: Membresías | D5: =SUM(D6:D8) -> 686830.87 | E5: =SUM(E6:E8) -> 796918.16 | F5: =SUM(F6:F8) -> 703360.05 | G5: =SUM(G6:G8) -> 827529.92 | H5: =SUM(H6:H8) -> 734319.71 | I5: =SUM(I6:I8) -> 835486.43 | J5: =SUM(J6:J8) -> 755012.55 | K5: =SUM(K6:K8) -> 828972.86 | ... R5: =SUM(R6:R8) -> 842496.92 | T5: =SUM(T6:T8) -> 880129.5 | V5: =SUM(V6:V8) -> 925545.42 | X5: =SUM(X6:X8) -> 1032212.1 | Z5: =SUM(Z6:Z8) -> 1108896.7 | AB5: =D5+F5+H5+J5+L5+N5+P5+R5+T5+V5+X5+Z5 -> 10052089 | AD5: =D5+F5+H5+J5+L5+N5+P5 -> 5262808.5 | AE5: =E5+G5+I5+K5+M5+O5+Q5 -> 5813127.2
C6: Renovaciones | D6: 557052.16 | E6: 603047.58 | F6: 571890.92 | G6: 630347.34 | H6: 560844.67 | I6: 632544.59 | J6: 561057.83 | K6: 621674.98 | L6: 547515.67 | M6: 634980.76 | N6: 536928.17 | O6: 622281.79 | P6: 542396.08 | Q6: 613596.86 | R6: 535304.83 | T6: 560153.17 | V6: 579474.42 | X6: 648224.42 | Z6: 694250 | AB6: =D6+F6+H6+J6+L6+N6+P6+R6+T6+V6+X6+Z6 -> 6895092.3 | AD6: =D6+F6+H6+J6+L6+N6+P6 -> 3877685.5 | AE6: =E6+G6+I6+K6+M6+O6+Q6 -> 4358473.9
C7: Descuentos | D7: -10205.539 | E7: -16322.5 | F7: -10222.285 | G7: -16304.42 | H7: -10123.62 | I7: -16285.75 | J7: -10140.537 | K7: -16366.01 | L7: -10148.036 | M7: -17470.17 | N7: -10253.202 | O7: -16275.35 | P7: -10586.202 | Q7: -16285.02 | R7: -10817.083 | T7: -10866.416 | V7: -10845.666 | X7: -10845.666 | Z7: -10853.333 | AB7: =D7+F7+H7+J7+L7+N7+P7+R7+T7+V7+X7+Z7 -> -125907.59 | AD7: =D7+F7+H7+J7+L7+N7+P7 -> -71679.421 | AE7: =E7+G7+I7+K7+M7+O7+Q7 -> -115309.22
C8: Socios Nuevos | D8: 139984.25 | E8: 210193.08 | F8: 141691.42 | G8: 213487 | H8: 183598.67 | I8: 219227.59 | J8: 204095.25 | K8: 223663.89 | L8: 234188.67 | M8: 215840.63 | N8: 264012.58 | O8: 246790.67 | P8: 289231.58 | Q8: 240759.68 | R8: 318009.17 | T8: 330842.75 | V8: 356916.67 | X8: 394833.33 | Z8: 425500 | AB8: =D8+F8+H8+J8+L8+N8+P8+R8+T8+V8+X8+Z8 -> 3282904.3 | AD8: =D8+F8+H8+J8+L8+N8+P8 -> 1456802.4 | AE8: =E8+G8+I8+K8+M8+O8+Q8 -> 1569962.5
B9: 401-001-000-00 | C9: Cuotas Suscripción | D9: 54000 | E9: 37200 | F9: 65000 | G9: 65500 | H9: 72500 | I9: 22500 | J9: 82000 | K9: 24500 | L9: 89500 | M9: 0 | N9: 65000 | O9: 29500 | P9: 78500 | Q9: 29500 | R9: 100500 | T9: 54000 | V9: 60000 | X9: 71000 | Z9: 65000 | AB9: =D9+F9+H9+J9+L9+N9+P9+R9+T9+V9+X9+Z9 -> 857000 | AD9: =D9+F9+H9+J9+L9+N9+P9 -> 506500 | AE9: =E9+G9+I9+K9+M9+O9+Q9 -> 208700
C10: Suma de Ingresos Desarrollo de Negocios | D10: =D5+D9 -> 740830.87 | E10: =E5+E9 -> 834118.16 | F10: =F5+F9 -> 768360.05 | G10: =G5+G9 -> 893029.92 | H10: =H5+H9 -> 806819.71 | I10: =I5+I9 -> 857986.43 | J10: =J5+J9 -> 837012.55 | K10: =K5+K9 -> 853472.86 | ... R10: =R5+R9 -> 942996.92 | T10: =T5+T9 -> 934129.5 | V10: =V5+V9 -> 985545.42 | X10: =X5+X9 -> 1103212.1 | Z10: =Z5+Z9 -> 1173896.7 | AB10: =AB5+AB9 -> 10909089 | AD10: =AD5+AD9 -> 5769308.5 | AE10: =AE5+AE9 -> 6021827.2
C12: Gastos Desarrollo de Negocios
B13: 902-002-000-00 | C13: Herramienta Sales Force | D13: 0 | E13: 0 | F13: 0 | G13: 0 | H13: 0 | I13: 0 | J13: 0 | K13: 0 | L13: 0 | M13: 0 | N13: 0 | O13: 0 | P13: 0 | Q13: 0 | R13: 0 | T13: 0 | V13: 0 | X13: 0 | Z13: 0 | AB13: =D13+F13+H13+J13+L13+N13+P13+R13+T13+V13+X13+Z13 -> 0 | AD13: =D13+F13+H13+J13+L13+N13+P13 -> 0 | AE13: =E13+G13+I13+K13+M13+O13+Q13 -> 0
B14: 501-001-009-00 | C14: Comisiones KAM´s | D14: 46322.55 | E14: 3000 | F14: 46322.55 | G14: 66863 | H14: 46322.55 | I14: 41841 | J14: 46322.55 | K14: 13745 | L14: 46322.55 | M14: 36975 | N14: 46322.55 | O14: 5400 | P14: 46322.55 | Q14: 85650 | R14: 46322.55 | T14: 46322.55 | V14: 46322.55 | X14: 46322.55 | Z14: 46322.55 | AB14: =D14+F14+H14+J14+L14+N14+P14+R14+T14+V14+X14+Z14 -> 555870.6 | AD14: =D14+F14+H14+J14+L14+N14+P14 -> 324257.85 | AE14: =E14+G14+I14+K14+M14+O14+Q14 -> 253474
B15: 702-001-000-00 | C15: Desayunos promoción - On boarding | D15: 20000 | E15: 1563.21 | F15: 0 | G15: 1815.06 | H15: 20000 | I15: 0 | J15: 0 | K15: 811.35 | L15: 20000 | M15: 0 | N15: 0 | O15: 3904.95 | P15: 20000 | Q15: 0 | R15: 0 | T15: 20000 | V15: 0 | X15: 20000 | Z15: 0 | AB15: =D15+F15+H15+J15+L15+N15+P15+R15+T15+V15+X15+Z15 -> 120000 | AD15: =D15+F15+H15+J15+L15+N15+P15 -> 80000 | AE15: =E15+G15+I15+K15+M15+O15+Q15 -> 8094.57
C16: Suma de Gastos Desarrollo de Negocios | D16: =SUM(D13:D15) -> 66322.55 | E16: =SUM(E13:E15) -> 4563.21 | F16: =SUM(F13:F15) -> 46322.55 | G16: =SUM(G13:G15) -> 68678.06 | H16: =SUM(H13:H15) -> 66322.55 | I16: =SUM(I13:I15) -> 41841 | J16: =SUM(J13:J15) -> 46322.55 | K16: =SUM(K13:K15) -> 14556.35 | ... R16: =SUM(R13:R15) -> 46322.55 | T16: =SUM(T13:T15) -> 66322.55 | V16: =SUM(V13:V15) -> 46322.55 | X16: =SUM(X13:X15) -> 66322.55 | Z16: =SUM(Z13:Z15) -> 46322.55 | AB16: =SUM(AB13:AB15) -> 675870.6 | AD16: =SUM(AD13:AD15) -> 404257.85 | AE16: =SUM(AE13:AE15) -> 261568.57
C19: Resultado Desarrollo de Negocios | D19: =+D10-D16 -> 674508.32 | E19: =+E10-E16 -> 829554.95 | F19: =+F10-F16 -> 722037.5 | G19: =+G10-G16 -> 824351.86 | H19: =+H10-H16 -> 740497.16 | I19: =+I10-I16 -> 816145.43 | J19: =+J10-J16 -> 790690 | K19: =+K10-K16 -> 838916.51 | ... R19: =+R10-R16 -> 896674.37 | T19: =+T10-T16 -> 867806.95 | V19: =+V10-V16 -> 939222.87 | X19: =+X10-X16 -> 1036889.5 | Z19: =+Z10-Z16 -> 1127574.1 | AB19: =+AB10-AB16 -> 10233218 | AD19: =+AD10-AD16 -> 5365050.6 | AE19: =+AE10-AE16 -> 5760258.7

Sheet Comités
AD1: Ppto. | AE1: Real
C2: COMITÉS Y RELACIONES EXTERNAS | D2: 45658 | E2: 45658 | F2: 45689 | G2: 45689 | H2: 45717 | I2: 45717 | J2: 45748 | K2: 45748 | L2: 45778 | M2: 45778 | N2: 45809 | O2: 45809 | P2: 45839 | Q2: 45839 | R2: 45870 | S2: 45870 | T2: 45901 | U2: 45901 | V2: 45931 | W2: 45931 | X2: 45962 | Y2: 45962 | Z2: 45992 | AA2: 45992 | AB2: 2025 | AD2: Acumulado | AE2: Acumulado
C4: Ingresos Comités
B5: 404-017-000-00 | C5: Agroindustria (Virtual ) | D5: 0 | E5: 0 | F5: 8400 | G5: 0 | H5: 0 | I5: 0 | J5: 8400 | K5: 0 | L5: 0 | M5: 0 | N5: 8400 | O5: 1120.7 | P5: 0 | Q5: 9525.95 | R5: 8400 | T5: 0 | V5: 8400 | X5: 0 | Z5: 8400 | AB5: =D5+F5+H5+J5+L5+N5+P5+R5+T5+V5+X5+Z5 -> 50400 | AD5: =D5+F5+H5+J5+L5+N5+P5 -> 25200 | AE5: =E5+G5+I5+K5+M5+O5+Q5 -> 10646.65
B6: 404-005-000-00 | C6: Asuntos Fiscales | D6: 11200 | E6: 0 | F6: 11200 | G6: 0 | H6: 11200 | I6: 0 | J6: 11200 | K6: 0 | L6: 11200 | M6: 12006.98 | N6: 11200 | O6: 1120.7 | P6: 11200 | Q6: 0 | R6: 11200 | T6: 11200 | V6: 11200 | X6: 11200 | Z6: 11200 | AB6: =D6+F6+H6+J6+L6+N6+P6+R6+T6+V6+X6+Z6 -> 134400 | AD6: =D6+F6+H6+J6+L6+N6+P6 -> 78400 | AE6: =E6+G6+I6+K6+M6+O6+Q6 -> 13127.68
B7: 404-001-000-00 | C7: Capital Humano y Asuntos Laborales | D7: 19600 | E7: 0 | F7: 19600 | G7: 0 | H7: 19600 | I7: 0 | J7: 19600 | K7: 0 | L7: =560*35 -> 19600 | M7: 5603.5 | N7: =560*35 -> 19600 | O7: 12327.7 | P7: =560*35 -> 19600 | Q7: 3922.45 | R7: =560*35 -> 19600 | T7: =560*35 -> 19600 | V7: =560*35 -> 19600 | X7: =560*35 -> 19600 | Z7: =560*35 -> 19600 | AB7: =D7+F7+H7+J7+L7+N7+P7+R7+T7+V7+X7+Z7 -> 235200 | AD7: =D7+F7+H7+J7+L7+N7+P7 -> 137200 | AE7: =E7+G7+I7+K7+M7+O7+Q7 -> 21853.65
B8: 404-003-000-00 | C8: Comercio Exterior y Logística | D8: 8400 | E8: 0 | F8: 8400 | G8: 0 | H8: 8400 | I8: 0 | J8: 8400 | K8: 0 | L8: 8400 | M8: 6724.2 | N8: 8400 | O8: 1120.7 | P8: 8400 | Q8: 2241.4 | R8: 8400 | T8: 8400 | V8: 8400 | X8: 8400 | Z8: 8400 | AB8: =D8+F8+H8+J8+L8+N8+P8+R8+T8+V8+X8+Z8 -> 100800 | AD8: =D8+F8+H8+J8+L8+N8+P8 -> 58800 | AE8: =E8+G8+I8+K8+M8+O8+Q8 -> 10086.3
B9: 404-013-000-00 | C9: Innovación y TICs | D9: 0 | E9: 0 | F9: 0 | G9: 0 | H9: 0 | I9: 0 | J9: 0 | K9: 0 | L9: 0 | M9: 2094.33 | N9: 0 | O9: 0 | P9: 0 | Q9: 0 | R9: 0 | T9: 0 | V9: 0 | X9: 0 | Z9: 0 | AB9: =D9+F9+H9+J9+L9+N9+P9+R9+T9+V9+X9+Z9 -> 0 | AD9: =D9+F9+H9+J9+L9+N9+P9 -> 0 | AE9: =E9+G9+I9+K9+M9+O9+Q9 -> 2094.33
B10: 404-007-000-00 | C10: Legalidad y Estado de Derecho | D10: 11200 | E10: 0 | F10: 11200 | G10: 0 | H10: 11200 | I10: 0 | J10: 11200 | K10: 0 | L10: 11200 | M10: 0 | N10: 11200 | O10: 0 | P10: 11200 | Q10: 0 | R10: 11200 | T10: 11200 | V10: 11200 | X10: 11200 | Z10: 11200 | AB10: =D10+F10+H10+J10+L10+N10+P10+R10+T10+V10+X10+Z10 -> 134400 | AD10: =D10+F10+H10+J10+L10+N10+P10 -> 78400 | AE10: =E10+G10+I10+K10+M10+O10+Q10 -> 0
B11: 404-016-000-00 | C11: Salud | D11: 0 | E11: 0 | F11: 0 | G11: 0 | H11: 0 | I11: 0 | J11: 0 | K11: 0 | L11: 0 | M11: 0 | N11: 0 | O11: 0 | P11: 0 | Q11: 0 | R11: 0 | T11: 0 | V11: 0 | X11: 0 | Z11: 0 | AB11: =D11+F11+H11+J11+L11+N11+P11+R11+T11+V11+X11+Z11 -> 0 | AD11: =D11+F11+H11+J11+L11+N11+P11 -> 0 | AE11: =E11+G11+I11+K11+M11+O11+Q11 -> 0
B12: 404-004-000-00 | C12: Seguridad | D12: 8400 | E12: 0 | F12: 8400 | G12: 0 | H12: 8400 | I12: 0 | J12: 8400 | K12: 0 | L12: 8400 | M12: 0 | N12: 8400 | O12: 0 | P12: 8400 | Q12: 0 | R12: 8400 | T12: 8400 | V12: 8400 | X12: 8400 | Z12: 8400 | AB12: =D12+F12+H12+J12+L12+N12+P12+R12+T12+V12+X12+Z12 -> 100800 | AD12: =D12+F12+H12+J12+L12+N12+P12 -> 58800 | AE12: =E12+G12+I12+K12+M12+O12+Q12 -> 0
C13: Sustentabilidad y Responsabilidad Social | D13: 0 | E13: 0 | F13: 0 | G13: 0 | H13: 0 | I13: 0 | J13: 0 | K13: 0 | L13: 0 | M13: 0 | N13: 0 | O13: 0 | P13: 0 | Q13: 0 | R13: 0 | T13: 0 | V13: 0 | X13: 0 | Z13: 0 | AB13: =D13+F13+H13+J13+L13+N13+P13+R13+T13+V13+X13+Z13 -> 0 | AD13: =D13+F13+H13+J13+L13+N13+P13 -> 0 | AE13: =E13+G13+I13+K13+M13+O13+Q13 -> 0
B14: 404-009-000-00 | C14: Turismo | D14: 0 | E14: 0 | F14: 0 | G14: 0 | H14: 0 | I14: 0 | J14: 0 | K14: 0 | L14: 0 | M14: 0 | N14: 0 | O14: 0 | P14: 0 | Q14: 0 | R14: 0 | T14: 0 | V14: 0 | X14: 0 | Z14: 0 | AB14: =D14+F14+H14+J14+L14+N14+P14+R14+T14+V14+X14+Z14 -> 0 | AD14: =D14+F14+H14+J14+L14+N14+P14 -> 0 | AE14: =E14+G14+I14+K14+M14+O14+Q14 -> 0
B15: 404-018-000-00 | C15: Programa de Mentoría (EWDP) | D15: 0 | E15: 0 | F15: 0 | G15: 0 | H15: 0 | I15: 0 | J15: 0 | K15: 0 | L15: 0 | M15: 65000 | N15: 162500 | O15: 195833.33 | P15: 162500 | Q15: 152499.99 | R15: 162500 | T15: 162500 | V15: 0 | X15: 0 | Z15: 0 | AB15: =D15+F15+H15+J15+L15+N15+P15+R15+T15+V15+X15+Z15 -> 650000 | AD15: =D15+F15+H15+J15+L15+N15+P15 -> 325000 | AE15: =E15+G15+I15+K15+M15+O15+Q15 -> 413333.32
C16: Suma de Ingresos Comités | D16: =SUM(D5:D15) -> 58800 | E16: =SUM(E5:E15) -> 0 | F16: =SUM(F5:F15) -> 67200 | G16: =SUM(G5:G15) -> 0 | H16: =SUM(H5:H15) -> 58800 | I16: =SUM(I5:I15) -> 0 | J16: =SUM(J5:J15) -> 67200 | K16: =SUM(K5:K15) -> 0 | ... R16: =SUM(R5:R15) -> 229700 | T16: =SUM(T5:T15) -> 221300 | V16: =SUM(V5:V15) -> 67200 | X16: =SUM(X5:X15) -> 58800 | Z16: =SUM(Z5:Z15) -> 67200 | AB16: =SUM(AB5:AB15) -> 1406000 | AD16: =SUM(AD5:AD15) -> 761800 | AE16: =SUM(AE5:AE15) -> 471141.93
C18: Gastos Comités
B19: 502-014-000-00 | C19: Agroindustria | D19: 0 | E19: 0 | F19: 6000 | G19: 0 | H19: 0 | I19: 0 | J19: 6000 | K19: 0 | L19: 0 | M19: 0 | N19: 6000 | O19: 45.56 | P19: 0 | Q19: 5651.27 | R19: 6000 | T19: 0 | V19: 6000 | X19: 0 | Z19: 6000 | AB19: =D19+F19+H19+J19+L19+N19+P19+R19+T19+V19+X19+Z19 -> 36000 | AD19: =D19+F19+H19+J19+L19+N19+P19 -> 18000 | AE19: =E19+G19+I19+K19+M19+O19+Q19 -> 5696.83
B20: 502-005-000-00 | C20: Asuntos Fiscales | D20: 8000 | E20: 0 | F20: 8000 | G20: 0 | H20: 8000 | I20: 0 | J20: 8000 | K20: 0 | L20: 8000 | M20: 10815.12 | N20: 8000 | O20: 0 | P20: 8000 | Q20: 420 | R20: 8000 | T20: 8000 | V20: 8000 | X20: 8000 | Z20: 8000 | AB20: =D20+F20+H20+J20+L20+N20+P20+R20+T20+V20+X20+Z20 -> 96000 | AD20: =D20+F20+H20+J20+L20+N20+P20 -> 56000 | AE20: =E20+G20+I20+K20+M20+O20+Q20 -> 11235.12
B21: 502-001-000-00 | C21: Capital Humano y Asuntos Laborales | D21: 0 | E21: 0 | F21: 0 | G21: 0 | H21: 0 | I21: 0 | J21: 0 | K21: 0 | L21: 0 | M21: 113.9 | N21: 0 | O21: 30001.66 | P21: 0 | Q21: 375.03 | R21: 0 | T21: 0 | V21: 0 | X21: 0 | Z21: 0 | AB21: =D21+F21+H21+J21+L21+N21+P21+R21+T21+V21+X21+Z21 -> 0 | AD21: =D21+F21+H21+J21+L21+N21+P21 -> 0 | AE21: =E21+G21+I21+K21+M21+O21+Q21 -> 30490.59
B22: 502-003-000-00 | C22: Comercio Exterior y Logística | D22: 6000 | E22: 0 | F22: 6000 | G22: 0 | H22: 6000 | I22: 768 | J22: 6000 | K22: 0 | L22: 6000 | M22: 91.12 | N22: 6000 | O22: 11512.78 | P22: 6000 | Q22: 0 | R22: 6000 | T22: 6000 | V22: 6000 | X22: 6000 | Z22: 6000 | AB22: =D22+F22+H22+J22+L22+N22+P22+R22+T22+V22+X22+Z22 -> 72000 | AD22: =D22+F22+H22+J22+L22+N22+P22 -> 42000 | AE22: =E22+G22+I22+K22+M22+O22+Q22 -> 12371.9
B23: 502-013-000-00 | C23: Innovación y TICs | D23: 0 | E23: 0 | F23: 0 | G23: 916 | H23: 0 | I23: 0 | J23: 0 | K23: 0 | L23: 0 | M23: 623.36 | N23: 0 | O23: 0 | P23: 0 | Q23: 0 | R23: 0 | T23: 0 | V23: 0 | X23: 0 | Z23: 0 | AB23: =D23+F23+H23+J23+L23+N23+P23+R23+T23+V23+X23+Z23 -> 0 | AD23: =D23+F23+H23+J23+L23+N23+P23 -> 0 | AE23: =E23+G23+I23+K23+M23+O23+Q23 -> 1539.36
B24: 502-007-000-00 | C24: Legalidad y Estado de Derecho | D24: 11200 | E24: 0 | F24: 11200 | G24: 0 | H24: 11200 | I24: 0 | J24: 11200 | K24: 0 | L24: 11200 | M24: 745.43 | N24: 11200 | O24: 0 | P24: 11200 | Q24: 0 | R24: 11200 | T24: 11200 | V24: 11200 | X24: 11200 | Z24: 11200 | AB24: =D24+F24+H24+J24+L24+N24+P24+R24+T24+V24+X24+Z24 -> 134400 | AD24: =D24+F24+H24+J24+L24+N24+P24 -> 78400 | AE24: =E24+G24+I24+K24+M24+O24+Q24 -> 745.43
B25: 502-016-000-00 | C25: Salud | D25: 0 | E25: 0 | F25: 0 | G25: 0 | H25: 0 | I25: 0 | J25: 0 | K25: 185.01 | L25: 0 | M25: 0 | N25: 0 | O25: 0 | P25: 0 | Q25: 0 | R25: 0 | T25: 0 | V25: 0 | X25: 0 | Z25: 0 | AB25: =D25+F25+H25+J25+L25+N25+P25+R25+T25+V25+X25+Z25 -> 0 | AD25: =D25+F25+H25+J25+L25+N25+P25 -> 0 | AE25: =E25+G25+I25+K25+M25+O25+Q25 -> 185.01
B26: 502-004-000-00 | C26: Seguridad | D26: 6000 | E26: 0 | F26: 6000 | G26: 0 | H26: 6000 | I26: 109.38 | J26: 6000 | K26: 0 | L26: 6000 | M26: 0 | N26: 6000 | O26: 769.91 | P26: 6000 | Q26: 0 | R26: 6000 | T26: 6000 | V26: 6000 | X26: 6000 | Z26: 6000 | AB26: =D26+F26+H26+J26+L26+N26+P26+R26+T26+V26+X26+Z26 -> 72000 | AD26: =D26+F26+H26+J26+L26+N26+P26 -> 42000 | AE26: =E26+G26+I26+K26+M26+O26+Q26 -> 879.29
B27: 502-002-000-00 | C27: Sustentabilidad y Responsabilidad Social | D27: 0 | E27: 0 | F27: 0 | G27: 0 | H27: 0 | I27: 0 | J27: 0 | K27: 0 | L27: 0 | M27: 0 | N27: 0 | O27: 0 | P27: 0 | Q27: 511.66 | R27: 0 | T27: 0 | V27: 0 | X27: 0 | Z27: 0 | AB27: =D27+F27+H27+J27+L27+N27+P27+R27+T27+V27+X27+Z27 -> 0 | AD27: =D27+F27+H27+J27+L27+N27+P27 -> 0 | AE27: =E27+G27+I27+K27+M27+O27+Q27 -> 511.66
B28: 502-009-000-00 | C28: Turismo | D28: 0 | E28: 0 | F28: 0 | G28: 0 | H28: 0 | I28: 0 | J28: 0 | K28: 0 | L28: 0 | M28: 0 | N28: 0 | O28: 0 | P28: 0 | Q28: 0 | R28: 0 | T28: 0 | V28: 0 | X28: 0 | Z28: 0 | AB28: =D28+F28+H28+J28+L28+N28+P28+R28+T28+V28+X28+Z28 -> 0 | AD28: =D28+F28+H28+J28+L28+N28+P28 -> 0 | AE28: =E28+G28+I28+K28+M28+O28+Q28 -> 0
B29: 502-017-000-00 | C29: Programa de Mentoría (EWDP) | D29: 0 | E29: 0 | F29: 0 | G29: 0 | H29: 0 | I29: 0 | J29: 0 | K29: 0 | L29: 0 | M29: 325059 | N29: 36000 | O29: 3047.95 | P29: 32000 | Q29: 3693.21 | R29: 36000 | T29: 32000 | V29: 0 | X29: 0 | Z29: 40000 | AB29: =D29+F29+H29+J29+L29+N29+P29+R29+T29+V29+X29+Z29 -> 176000 | AD29: =D29+F29+H29+J29+L29+N29+P29 -> 68000 | AE29: =E29+G29+I29+K29+M29+O29+Q29 -> 331800.16
C30: Suma de Gastos Comités | D30: =SUM(D19:D29) -> 31200 | E30: =SUM(E19:E29) -> 0 | F30: =SUM(F19:F29) -> 37200 | G30: =SUM(G19:G29) -> 916 | H30: =SUM(H19:H29) -> 31200 | I30: =SUM(I19:I29) -> 877.38 | J30: =SUM(J19:J29) -> 37200 | K30: =SUM(K19:K29) -> 185.01 | ... R30: =SUM(R19:R29) -> 73200 | T30: =SUM(T19:T29) -> 63200 | V30: =SUM(V19:V29) -> 37200 | X30: =SUM(X19:X29) -> 31200 | Z30: =SUM(Z19:Z29) -> 77200 | AB30: =SUM(AB19:AB29) -> 586400 | AD30: =SUM(AD19:AD29) -> 304400 | AE30: =SUM(AE19:AE29) -> 395455.35
C33: Resultado Comités | D33: =+D16-D30 -> 27600 | E33: =+E16-E30 -> 0 | F33: =+F16-F30 -> 30000 | G33: =+G16-G30 -> -916 | H33: =+H16-H30 -> 27600 | I33: =+I16-I30 -> -877.38 | J33: =+J16-J30 -> 30000 | K33: =+K16-K30 -> -185.01 | ... R33: =+R16-R30 -> 156500 | T33: =+T16-T30 -> 158100 | V33: =+V16-V30 -> 30000 | X33: =+X16-X30 -> 27600 | Z33: =+Z16-Z30 -> -10000 | AB33: =+AB16-AB30 -> 819600 | AD33: =+AD16-AD30 -> 457400 | AE33: =+AE16-AE30 -> 75686.58
AB35: 100301.72
C37: Instrucciones: Favor de llenar solo los espacios en blanco, lo que está sombreado en gris será llenado por AYF
C38: Nota: Los eventos y comités deberán presupuestarse al menos en punto de equilibrio.

Sheet Eventos
AD1: Ppto. | AE1: Real
C2: EVENTOS Y SERVICIOS A LA MEMBRESÍA | D2: 45658 | E2: 45658 | F2: 45689 | G2: 45689 | H2: 45717 | I2: 45717 | J2: 45748 | K2: 45748 | L2: 45778 | M2: 45778 | N2: 45809 | O2: 45809 | P2: 45839 | Q2: 45839 | R2: 45870 | S2: 45870 | T2: 45901 | U2: 45901 | V2: 45931 | W2: 45931 | X2: 45962 | Y2: 45962 | Z2: 45992 | AA2: 45992 | AB2: 2025 | AD2: Acumulado | AE2: Acumulado
C4: Ingresos Eventos
C5: Boletaje
B6: 405-012-000-00 | C6: Meet the consulate | D6: 0 | E6: 0 | F6: 0 | G6: 0 | H6: 0 | I6: 0 | J6: 0 | K6: 0 | L6: 0 | M6: 0 | N6: 0 | O6: 0 | P6: 0 | Q6: 0 | R6: 0 | T6: 0 | V6: 0 | X6: 0 | Z6: 0 | AB6: =D6+F6+H6+J6+L6+N6+P6+R6+T6+V6+X6+Z6 -> 0 | AD6: =D6+F6+H6+J6+L6+N6+P6 -> 0 | AE6: =E6+G6+I6+K6+M6+O6+Q6 -> 0
B7: 405-010-000-00 | C7: Empower Your People | D7: 0 | E7: 0 | F7: 35000 | G7: 23800 | H7: 0 | I7: 7650 | J7: 0 | K7: 3400 | L7: 0 | M7: 0 | N7: 0 | O7: 0 | P7: 0 | Q7: 0 | R7: 0 | T7: 0 | V7: 0 | X7: 0 | Z7: 0 | AB7: =D7+F7+H7+J7+L7+N7+P7+R7+T7+V7+X7+Z7 -> 35000 | AD7: =D7+F7+H7+J7+L7+N7+P7 -> 35000 | AE7: =E7+G7+I7+K7+M7+O7+Q7 -> 34850
B8: 405-007-000-00 | C8: Extend Our Reach | D8: 0 | E8: 0 | F8: 0 | G8: 0 | H8: 0 | I8: 0 | J8: 0 | K8: 0 | L8: 0 | M8: 0 | N8: 0 | O8: 0 | P8: 0 | Q8: 0 | R8: 0 | T8: 0 | V8: 0 | X8: 0 | Z8: 0 | AB8: =D8+F8+H8+J8+L8+N8+P8+R8+T8+V8+X8+Z8 -> 0 | AD8: =D8+F8+H8+J8+L8+N8+P8 -> 0 | AE8: =E8+G8+I8+K8+M8+O8+Q8 -> 0
B9: 405-012-000-00 | C9: Punto de encuentro | D9: 0 | E9: 0 | F9: 0 | G9: 0 | H9: 45000 | I9: 0 | J9: 0 | K9: 0 | L9: 0 | M9: 0 | N9: 0 | O9: 0 | P9: 0 | Q9: 0 | R9: 0 | T9: 0 | V9: 0 | X9: 0 | Z9: 0 | AB9: =D9+F9+H9+J9+L9+N9+P9+R9+T9+V9+X9+Z9 -> 45000 | AD9: =D9+F9+H9+J9+L9+N9+P9 -> 45000 | AE9: =E9+G9+I9+K9+M9+O9+Q9 -> 0
B10: 405-013-000-00 | C10: The North America Week | D10: 0 | E10: 0 | F10: 0 | G10: 0 | H10: 0 | I10: 0 | J10: 55000 | K10: 0 | L10: 0 | M10: 0 | N10: 0 | O10: 20200 | P10: 0 | Q10: 6800 | R10: 0 | T10: 0 | V10: 0 | X10: 0 | Z10: 0 | AB10: =D10+F10+H10+J10+L10+N10+P10+R10+T10+V10+X10+Z10 -> 55000 | AD10: =D10+F10+H10+J10+L10+N10+P10 -> 55000 | AE10: =E10+G10+I10+K10+M10+O10+Q10 -> 27000
B11: 405-007-000-00 | C11: Reunion de Directores | D11: 0 | E11: 0 | F11: 0 | G11: 0 | H11: 0 | I11: 0 | J11: 0 | K11: 0 | L11: 50000 | M11: 0 | N11: 0 | O11: 0 | P11: 0 | Q11: 0 | R11: 0 | T11: 0 | V11: 0 | X11: 0 | Z11: 0 | AB11: =D11+F11+H11+J11+L11+N11+P11+R11+T11+V11+X11+Z11 -> 50000 | AD11: =D11+F11+H11+J11+L11+N11+P11 -> 50000 | AE11: =E11+G11+I11+K11+M11+O11+Q11 -> 0
B12: 405-012-000-00 | C12: Jalisco Travel Fest | D12: 0 | E12: 0 | F12: 0 | G12: 0 | H12: 0 | I12: 0 | J12: 0 | K12: 0 | L12: 0 | M12: 0 | N12: 70000 | O12: 0 | P12: 0 | Q12: 0 | R12: 0 | T12: 0 | V12: 0 | X12: 0 | Z12: 0 | AB12: =D12+F12+H12+J12+L12+N12+P12+R12+T12+V12+X12+Z12 -> 70000 | AD12: =D12+F12+H12+J12+L12+N12+P12 -> 70000 | AE12: =E12+G12+I12+K12+M12+O12+Q12 -> 0
B13: 405-008-000-00 | C13: Secretarias | D13: 0 | E13: 0 | F13: 0 | G13: 0 | H13: 0 | I13: 0 | J13: 0 | K13: 0 | L13: 0 | M13: 0 | N13: 0 | O13: 0 | P13: 0 | Q13: 0 | R13: 0 | T13: 0 | V13: 0 | X13: 0 | Z13: 0 | AB13: =D13+F13+H13+J13+L13+N13+P13+R13+T13+V13+X13+Z13 -> 0 | AD13: =D13+F13+H13+J13+L13+N13+P13 -> 0 | AE13: =E13+G13+I13+K13+M13+O13+Q13 -> 0
B14: 405-003-000-00 | C14: Foros (Economico, Jalisco Visión, etc.) | D14: 0 | E14: 42382.76 | F14: 0 | G14: 17850 | H14: 0 | I14: 850 | J14: 0 | K14: 0 | L14: 0 | M14: 0 | N14: 0 | O14: 0 | P14: 0 | Q14: 0 | R14: 45000 | T14: 0 | V14: 0 | X14: 0 | Z14: 0 | AB14: =D14+F14+H14+J14+L14+N14+P14+R14+T14+V14+X14+Z14 -> 45000 | AD14: =D14+F14+H14+J14+L14+N14+P14 -> 0 | AE14: =E14+G14+I14+K14+M14+O14+Q14 -> 61082.76
B15: 405-009-000-00 | C15: Cumbre Empresarios | D15: 0 | E15: 0 | F15: 0 | G15: 0 | H15: 0 | I15: 0 | J15: 0 | K15: 0 | L15: 0 | M15: 0 | N15: 0 | O15: 0 | P15: 0 | Q15: 0 | R15: 0 | T15: 210000 | V15: 0 | X15: 0 | Z15: 0 | AB15: =D15+F15+H15+J15+L15+N15+P15+R15+T15+V15+X15+Z15 -> 210000 | AD15: =D15+F15+H15+J15+L15+N15+P15 -> 0 | AE15: =E15+G15+I15+K15+M15+O15+Q15 -> 0
B16: 405-001-000-00 | C16: Torneo Golf | D16: 0 | E16: 0 | F16: 0 | G16: 0 | H16: 0 | I16: 0 | J16: 0 | K16: 0 | L16: 0 | M16: 0 | N16: 0 | O16: 0 | P16: 0 | Q16: 0 | R16: 0 | T16: 0 | V16: 480000 | X16: 0 | Z16: 0 | AB16: =D16+F16+H16+J16+L16+N16+P16+R16+T16+V16+X16+Z16 -> 480000 | AD16: =D16+F16+H16+J16+L16+N16+P16 -> 0 | AE16: =E16+G16+I16+K16+M16+O16+Q16 -> 0
B17: 405-002-000-00 | C17: Asamblea Anual | D17: 0 | E17: 0 | F17: 0 | G17: 0 | H17: 0 | I17: 0 | J17: 0 | K17: 0 | L17: 0 | M17: 0 | N17: 0 | O17: 0 | P17: 0 | Q17: 0 | R17: 0 | T17: 0 | V17: 0 | X17: 300000 | Z17: 0 | AB17: =D17+F17+H17+J17+L17+N17+P17+R17+T17+V17+X17+Z17 -> 300000 | AD17: =D17+F17+H17+J17+L17+N17+P17 -> 0 | AE17: =E17+G17+I17+K17+M17+O17+Q17 -> 0
C18: Ingresos Boletaje | D18: =SUM(D6:D17) -> 0 | E18: =SUM(E6:E17) -> 42382.76 | F18: =SUM(F6:F17) -> 35000 | G18: =SUM(G6:G17) -> 41650 | H18: =SUM(H6:H17) -> 45000 | I18: =SUM(I6:I17) -> 8500 | J18: =SUM(J6:J17) -> 55000 | K18: =SUM(K6:K17) -> 3400 | ... R18: =SUM(R6:R17) -> 45000 | T18: =SUM(T6:T17) -> 210000 | V18: =SUM(V6:V17) -> 480000 | X18: =SUM(X6:X17) -> 300000 | Z18: =SUM(Z6:Z17) -> 0 | AB18: =SUM(AB6:AB17) -> 1290000 | AD18: =SUM(AD6:AD17) -> 255000 | AE18: =SUM(AE6:AE17) -> 122932.76
C20: Patrocinios
B21: 405-012-000-00 | C21: Meet the consulate | D21: 60000 | E21: 0 | F21: 0 | G21: 0 | H21: 0 | I21: 0 | J21: 0 | K21: 0 | L21: 0 | M21: 0 | N21: 0 | O21: 0 | P21: 0 | Q21: 0 | R21: 0 | T21: 0 | V21: 0 | X21: 0 | Z21: 0 | AB21: =D21+F21+H21+J21+L21+N21+P21+R21+T21+V21+X21+Z21 -> 60000 | AD21: =D21+F21+H21+J21+L21+N21+P21 -> 60000 | AE21: =E21+G21+I21+K21+M21+O21+Q21 -> 0
B22: 405-010-000-00 | C22: Empower Your People | D22: 0 | E22: 0 | F22: 35000 | G22: 50000 | H22: 0 | I22: 0 | J22: 0 | K22: 0 | L22: 0 | M22: 0 | N22: 0 | O22: 850 | P22: 0 | Q22: 0 | R22: 0 | T22: 0 | V22: 0 | X22: 0 | Z22: 0 | AB22: =D22+F22+H22+J22+L22+N22+P22+R22+T22+V22+X22+Z22 -> 35000 | AD22: =D22+F22+H22+J22+L22+N22+P22 -> 35000 | AE22: =E22+G22+I22+K22+M22+O22+Q22 -> 50850
B23: 405-007-000-00 | C23: Extend Our Reach | D23: 0 | E23: 0 | F23: 25000 | G23: 0 | H23: 0 | I23: 0 | J23: 25000 | K23: 0 | L23: 0 | M23: 0 | N23: 25000 | O23: 0 | P23: 0 | Q23: 0 | R23: 0 | T23: 25000 | AB23: =D23+F23+H23+J23+L23+N23+P23+R23+T23+V23+X23+Z23 -> 100000 | AD23: =D23+F23+H23+J23+L23+N23+P23 -> 75000 | AE23: =E23+G23+I23+K23+M23+O23+Q23 -> 0
B24: 405-012-000-00 | C24: Punto de encuentro | D24: 0 | E24: 0 | F24: 0 | G24: 0 | H24: 35000 | I24: 0 | J24: 0 | K24: 0 | L24: 0 | M24: 0 | N24: 0 | O24: 0 | P24: 0 | Q24: 0 | R24: 0 | T24: 0 | V24: 0 | X24: 0 | Z24: 0 | AB24: =D24+F24+H24+J24+L24+N24+P24+R24+T24+V24+X24+Z24 -> 35000 | AD24: =D24+F24+H24+J24+L24+N24+P24 -> 35000 | AE24: =E24+G24+I24+K24+M24+O24+Q24 -> 0
B25: 405-013-000-00 | C25: The North America Week | D25: 0 | E25: 0 | F25: 0 | G25: 0 | H25: 0 | I25: 0 | J25: 180000 | K25: 0 | L25: 0 | M25: 0 | N25: 0 | O25: 140000 | P25: 0 | Q25: 40000 | R25: 0 | T25: 0 | V25: 0 | X25: 0 | Z25: 0 | AB25: =D25+F25+H25+J25+L25+N25+P25+R25+T25+V25+X25+Z25 -> 180000 | AD25: =D25+F25+H25+J25+L25+N25+P25 -> 180000 | AE25: =E25+G25+I25+K25+M25+O25+Q25 -> 180000
B26: 405-007-000-00 | C26: Reunion de Directores | D26: 0 | E26: 0 | F26: 0 | G26: 0 | H26: 0 | I26: 0 | J26: 0 | K26: 0 | L26: 100000 | M26: 0 | N26: 0 | O26: 0 | P26: 0 | Q26: 0 | R26: 0 | T26: 0 | V26: 0 | X26: 0 | Z26: 0 | AB26: =D26+F26+H26+J26+L26+N26+P26+R26+T26+V26+X26+Z26 -> 100000 | AD26: =D26+F26+H26+J26+L26+N26+P26 -> 100000 | AE26: =E26+G26+I26+K26+M26+O26+Q26 -> 0
B27: 405-012-000-00 | C27: Jalisco Travel Fest | D27: 0 | E27: 0 | F27: 0 | G27: 0 | H27: 0 | I27: 0 | J27: 0 | K27: 0 | L27: 0 | M27: 80000 | N27: 120000 | O27: 0 | P27: 0 | Q27: 0 | R27: 0 | T27: 0 | V27: 0 | X27: 0 | Z27: 0 | AB27: =D27+F27+H27+J27+L27+N27+P27+R27+T27+V27+X27+Z27 -> 120000 | AD27: =D27+F27+H27+J27+L27+N27+P27 -> 120000 | AE27: =E27+G27+I27+K27+M27+O27+Q27 -> 80000
B28: 405-008-000-00 | C28: Secretarias | D28: 0 | E28: 0 | F28: 0 | G28: 0 | H28: 0 | I28: 0 | J28: 0 | K28: 0 | L28: 0 | M28: 0 | N28: 0 | O28: 0 | P28: 85000 | Q28: 0 | R28: 0 | T28: 0 | V28: 0 | X28: 0 | Z28: 0 | AB28: =D28+F28+H28+J28+L28+N28+P28+R28+T28+V28+X28+Z28 -> 85000 | AD28: =D28+F28+H28+J28+L28+N28+P28 -> 85000 | AE28: =E28+G28+I28+K28+M28+O28+Q28 -> 0
B29: 405-003-000-00 | C29: Foros (Economico, Jalisco Visión, etc.) | D29: 0 | E29: 0 | F29: 0 | G29: 35000 | H29: 0 | I29: 0 | J29: 0 | K29: 0 | L29: 0 | M29: 0 | N29: 0 | O29: 0 | P29: 0 | Q29: 0 | R29: 95000 | T29: 0 | V29: 0 | X29: 0 | Z29: 0 | AB29: =D29+F29+H29+J29+L29+N29+P29+R29+T29+V29+X29+Z29 -> 95000 | AD29: =D29+F29+H29+J29+L29+N29+P29 -> 0 | AE29: =E29+G29+I29+K29+M29+O29+Q29 -> 35000
B30: 405-009-000-00 | C30: Cumbre Empresarios | D30: 0 | E30: 0 | F30: 0 | G30: 0 | H30: 0 | I30: 0 | J30: 0 | K30: 0 | L30: 0 | M30: 0 | N30: 0 | O30: 0 | P30: 0 | Q30: 0 | R30: 0 | T30: 650000 | V30: 0 | X30: 0 | Z30: 0 | AB30: =D30+F30+H30+J30+L30+N30+P30+R30+T30+V30+X30+Z30 -> 650000 | AD30: =D30+F30+H30+J30+L30+N30+P30 -> 0 | AE30: =E30+G30+I30+K30+M30+O30+Q30 -> 0
B31: 405-001-000-00 | C31: Torneo Golf | D31: 0 | E31: 0 | F31: 0 | G31: 0 | H31: 0 | I31: 0 | J31: 0 | K31: 0 | L31: 0 | M31: 0 | N31: 0 | O31: 0 | P31: 0 | Q31: 0 | R31: 0 | T31: 0 | V31: 550000 | X31: 0 | Z31: 0 | AB31: =D31+F31+H31+J31+L31+N31+P31+R31+T31+V31+X31+Z31 -> 550000 | AD31: =D31+F31+H31+J31+L31+N31+P31 -> 0 | AE31: =E31+G31+I31+K31+M31+O31+Q31 -> 0
B32: 405-002-000-00 | C32: Asamblea Anual | D32: 0 | E32: 0 | F32: 0 | G32: 0 | H32: 0 | I32: 0 | J32: 0 | K32: 0 | L32: 0 | M32: 0 | N32: 0 | O32: 0 | P32: 0 | Q32: 0 | R32: 0 | T32: 0 | V32: 0 | X32: 800000 | Z32: 0 | AB32: =D32+F32+H32+J32+L32+N32+P32+R32+T32+V32+X32+Z32 -> 800000 | AD32: =D32+F32+H32+J32+L32+N32+P32 -> 0 | AE32: =E32+G32+I32+K32+M32+O32+Q32 -> 0
C33: Ingresos Patrocinios | D33: =SUM(D21:D32) -> 60000 | E33: =SUM(E21:E32) -> 0 | F33: =SUM(F21:F32) -> 60000 | G33: =SUM(G21:G32) -> 85000 | H33: =SUM(H21:H32) -> 35000 | I33: =SUM(I21:I32) -> 0 | J33: =SUM(J21:J32) -> 205000 | K33: =SUM(K21:K32) -> 0 | ... R33: =SUM(R21:R32) -> 95000 | T33: =SUM(T21:T32) -> 675000 | V33: =SUM(V21:V32) -> 550000 | X33: =SUM(X21:X32) -> 800000 | Z33: =SUM(Z21:Z32) -> 0 | AB33: =SUM(AB21:AB32) -> 2810000 | AD33: =SUM(AD21:AD32) -> 690000 | AE33: =SUM(AE21:AE32) -> 345850
C35: Suma Ingresos Eventos | D35: =+D18+D33 -> 60000 | E35: =+E18+E33 -> 42382.76 | F35: =+F18+F33 -> 95000 | G35: =+G18+G33 -> 126650 | H35: =+H18+H33 -> 80000 | I35: =+I18+I33 -> 8500 | J35: =+J18+J33 -> 260000 | K35: =+K18+K33 -> 3400 | ... R35: =+R18+R33 -> 140000 | T35: =+T18+T33 -> 885000 | V35: =+V18+V33 -> 1030000 | X35: =+X18+X33 -> 1100000 | Z35: =+Z18+Z33 -> 0 | AB35: =+AB18+AB33 -> 4100000 | AD35: =+AD18+AD33 -> 945000 | AE35: =+AE18+AE33 -> 468782.76
C37: Costos y Gastos Eventos
B38: 701-010-000-00 | C38: Meet the consulate | D38: 40000 | E38: 0 | F38: 53045 | G38: 0 | H38: 0 | I38: 14340 | J38: 0 | K38: 0 | L38: 0 | N38: 0 | O38: 0 | P38: 0 | Q38: 0 | R38: 0 | T38: 0 | V38: 0 | X38: 0 | Z38: 0 | AB38: =D38+F38+H38+J38+L38+N38+P38+R38+T38+V38+X38+Z38 -> 93045 | AD38: =D38+F38+H38+J38+L38+N38+P38 -> 93045 | AE38: =E38+G38+I38+K38+M38+O38+Q38 -> 14340
B39: 701-014-000-00 | C39: Empower Your People | D39: 0 | E39: 0 | F39: 38000 | G39: 46790.9 | H39: 0 | I39: -517.24 | J39: 0 | K39: 0 | L39: 0 | M39: 0 | N39: 0 | O39: 0 | P39: 0 | Q39: 0 | R39: 0 | T39: 0 | V39: 0 | X39: 0 | Z39: 0 | AB39: =D39+F39+H39+J39+L39+N39+P39+R39+T39+V39+X39+Z39 -> 38000 | AD39: =D39+F39+H39+J39+L39+N39+P39 -> 38000 | AE39: =E39+G39+I39+K39+M39+O39+Q39 -> 46273.66
B40: 701-009-000-00 | C40: Extend Our Reach | D40: 0 | E40: 0 | F40: 60000 | G40: 0 | H40: 0 | I40: 0 | J40: 60000 | K40: 0 | L40: 0 | M40: 1419.03 | N40: 60000 | O40: 0 | P40: 0 | Q40: 1857.23 | R40: 0 | T40: 60000 | V40: 0 | X40: 0 | Z40: 0 | AB40: =D40+F40+H40+J40+L40+N40+P40+R40+T40+V40+X40+Z40 -> 240000 | AD40: =D40+F40+H40+J40+L40+N40+P40 -> 180000 | AE40: =E40+G40+I40+K40+M40+O40+Q40 -> 3276.26
B41: 701-010-000-00 | C41: Punto de encuentro | D41: 0 | E41: 0 | G41: 0 | H41: 35000 | I41: 0 | J41: 0 | K41: 0 | L41: 0 | M41: 0 | N41: 0 | O41: 0 | P41: 0 | Q41: 0 | R41: 0 | T41: 0 | V41: 0 | X41: 0 | Z41: 0 | AB41: =D41+F41+H41+J41+L41+N41+P41+R41+T41+V41+X41+Z41 -> 35000 | AD41: =D41+F41+H41+J41+L41+N41+P41 -> 35000 | AE41: =E41+G41+I41+K41+M41+O41+Q41 -> 0
B42: 701-012-000-00 | C42: The North America Week | D42: 0 | E42: 0 | F42: 0 | G42: 0 | H42: 0 | I42: 0 | J42: 130000 | K42: 0 | L42: 0 | M42: 0 | N42: 0 | O42: 67650.68 | P42: 0 | Q42: 68842.52 | R42: 0 | T42: 0 | V42: 0 | X42: 0 | Z42: 0 | AB42: =D42+F42+H42+J42+L42+N42+P42+R42+T42+V42+X42+Z42 -> 130000 | AD42: =D42+F42+H42+J42+L42+N42+P42 -> 130000 | AE42: =E42+G42+I42+K42+M42+O42+Q42 -> 136493.2
B43: 701-009-000-00 | C43: Reunion de Directores | D43: 0 | E43: 0 | F43: 0 | G43: 0 | H43: 0 | I43: 0 | J43: 0 | K43: 0 | L43: 100000 | M43: 0 | N43: 0 | O43: 0 | P43: 0 | Q43: 0 | R43: 0 | T43: 0 | V43: 0 | X43: 0 | Z43: 0 | AB43: =D43+F43+H43+J43+L43+N43+P43+R43+T43+V43+X43+Z43 -> 100000 | AD43: =D43+F43+H43+J43+L43+N43+P43 -> 100000 | AE43: =E43+G43+I43+K43+M43+O43+Q43 -> 0
B44: 701-010-000-00 | C44: Jalisco Travel Fest | D44: 0 | E44: 0 | F44: 0 | G44: 0 | H44: 0 | I44: 0 | J44: 0 | K44: 0 | L44: 0 | M44: 10309.84 | N44: 125000 | O44: 0 | P44: 0 | Q44: 0 | R44: 0 | T44: 0 | V44: 0 | X44: 0 | Z44: 0 | AB44: =D44+F44+H44+J44+L44+N44+P44+R44+T44+V44+X44+Z44 -> 125000 | AD44: =D44+F44+H44+J44+L44+N44+P44 -> 125000 | AE44: =E44+G44+I44+K44+M44+O44+Q44 -> 10309.84
B45: 701-008-000-00 | C45: Secretarias | D45: 0 | E45: 0 | F45: 0 | G45: 0 | H45: 0 | I45: 0 | J45: 0 | K45: 0 | L45: 0 | M45: 0 | N45: 0 | O45: 0 | P45: 55000 | Q45: 0 | R45: 0 | T45: 0 | V45: 0 | X45: 0 | Z45: 0 | AB45: =D45+F45+H45+J45+L45+N45+P45+R45+T45+V45+X45+Z45 -> 55000 | AD45: =D45+F45+H45+J45+L45+N45+P45 -> 55000 | AE45: =E45+G45+I45+K45+M45+O45+Q45 -> 0
B46: 701-007-000-00 | C46: Foros (Economico, Jalisco Visión, etc.) | D46: 0 | E46: 24047.83 | F46: 0 | G46: 56472.77 | H46: 0 | I46: 1118.97 | J46: 0 | K46: 0 | L46: 0 | M46: 0 | N46: 0 | O46: 0 | P46: 0 | Q46: 0 | R46: 110000 | T46: 0 | V46: 0 | X46: 0 | Z46: 0 | AB46: =D46+F46+H46+J46+L46+N46+P46+R46+T46+V46+X46+Z46 -> 110000 | AD46: =D46+F46+H46+J46+L46+N46+P46 -> 0 | AE46: =E46+G46+I46+K46+M46+O46+Q46 -> 81639.57
B47: 701-011-000-00 | C47: Cumbre Empresarios | D47: 0 | E47: 0 | F47: 0 | G47: 0 | H47: 0 | I47: 0 | J47: 0 | K47: 0 | L47: 0 | M47: 0 | N47: 0 | O47: 0 | P47: 0 | Q47: 0 | R47: 0 | T47: 630000 | V47: 0 | X47: 0 | Z47: 0 | AB47: =D47+F47+H47+J47+L47+N47+P47+R47+T47+V47+X47+Z47 -> 630000 | AD47: =D47+F47+H47+J47+L47+N47+P47 -> 0 | AE47: =E47+G47+I47+K47+M47+O47+Q47 -> 0
B48: 701-001-000-00 | C48: Torneo Golf | D48: 0 | E48: 0 | F48: 0 | G48: 0 | H48: 0 | I48: 0 | J48: 0 | K48: 0 | L48: 0 | M48: 0 | N48: 0 | O48: 0 | P48: 0 | Q48: 0 | R48: 0 | T48: 0 | V48: 700000 | X48: 0 | Z48: 0 | AB48: =D48+F48+H48+J48+L48+N48+P48+R48+T48+V48+X48+Z48 -> 700000 | AD48: =D48+F48+H48+J48+L48+N48+P48 -> 0 | AE48: =E48+G48+I48+K48+M48+O48+Q48 -> 0
B49: 701-002-000-00 | C49: Asamblea Anual | D49: 0 | E49: 0 | F49: 0 | G49: 0 | H49: 0 | I49: 0 | J49: 0 | K49: 0 | L49: 0 | M49: 0 | N49: 0 | O49: 0 | P49: 0 | Q49: 0 | R49: 0 | T49: 0 | V49: 0 | X49: 700000 | Z49: 0 | AB49: =D49+F49+H49+J49+L49+N49+P49+R49+T49+V49+X49+Z49 -> 700000 | AD49: =D49+F49+H49+J49+L49+N49+P49 -> 0 | AE49: =E49+G49+I49+K49+M49+O49+Q49 -> 0
B50: 701-004-000-00 | C50: COCTELES | D50: 0 | E50: 0 | F50: 0 | G50: 0 | H50: 0 | I50: 0 | J50: 0 | K50: 0 | L50: 0 | M50: 22332.47 | N50: 0 | O50: 0 | P50: 0 | Q50: 0 | R50: 0 | T50: 0 | V50: 0 | X50: 700000 | Z50: 0 | AB50: 700000 | AD50: =D50+F50+H50+J50+L50+N50+P50 -> 0 | AE50: =E50+G50+I50+K50+M50+O50+Q50 -> 22332.47
B51: 701-013-000-00 | C51: GLOBAL ENTRY | D51: 0 | E51: 0 | F51: 0 | G51: 0 | H51: 0 | I51: 0 | J51: 0 | K51: 1464.15 | L51: 0 | M51: 0 | N51: 0 | O51: 0 | P51: 0 | Q51: 0 | R51: 0 | T51: 0 | V51: 0 | X51: 0 | Z51: 0 | AB51: =D51+F51+H51+J51+L51+N51+P51+R51+T51+V51+X51+Z51 -> 0 | AD51: =D51+F51+H51+J51+L51+N51+P51 -> 0 | AE51: =E51+G51+I51+K51+M51+O51+Q51 -> 1464.15
C52: Suma Costos y Gastos Eventos | D52: =SUM(D38:D51) -> 40000 | E52: =SUM(E38:E51) -> 24047.83 | F52: =SUM(F38:F51) -> 151045 | G52: =SUM(G38:G51) -> 103263.67 | H52: =SUM(H38:H51) -> 35000 | I52: =SUM(I38:I51) -> 14941.73 | J52: =SUM(J38:J51) -> 190000 | K52: =SUM(K38:K51) -> 1464.15 | ... R52: =SUM(R38:R51) -> 110000 | T52: =SUM(T38:T51) -> 690000 | V52: =SUM(V38:V51) -> 700000 | X52: =SUM(X38:X51) -> 1400000 | Z52: =SUM(Z38:Z51) -> 0 | AB52: =SUM(AB38:AB51) -> 3656045 | AD52: =SUM(AD38:AD51) -> 756045 | AE52: =SUM(AE38:AE51) -> 316129.15
C55: Resultado Operativo Eventos | D55: =+D35-D52 -> 20000 | E55: =+E35-E52 -> 18334.93 | F55: =+F35-F52 -> -56045 | G55: =+G35-G52 -> 23386.33 | H55: =+H35-H52 -> 45000 | I55: =+I35-I52 -> -6441.73 | J55: =+J35-J52 -> 70000 | K55: =+K35-K52 -> 1935.85 | ... R55: =+R35-R52 -> 30000 | T55: =+T35-T52 -> 195000 | V55: =+V35-V52 -> 330000 | X55: =+X35-X52 -> -300000 | Z55: =+Z35-Z52 -> 0 | AB55: =+AB35-AB52 -> 443955 | AD55: =+AD35-AD52 -> 188955 | AE55: =+AE35-AE52 -> 152653.61
C59: Ingresos Servicios a la Membresía
B60: 403-002-000-00 | C60: Encuesta de Sueldos y Prestaciones | D60: 47268.9 | E60: 78600 | F60: 47268.9 | G60: 52400 | H60: 47268.9 | I60: 78600 | J60: 47268.9 | K60: 78600 | L60: 47268.9 | M60: 52400 | N60: 47268.9 | O60: 52400 | P60: 47268.9 | Q60: 52400 | R60: 47268.9 | T60: 47268.9 | V60: 47268.9 | X60: 47268.9 | Z60: 47268.9 | AB60: =D60+F60+H60+J60+L60+N60+P60+R60+T60+V60+X60+Z60 -> 567226.8 | AD60: =D60+F60+H60+J60+L60+N60+P60 -> 330882.3 | AE60: =E60+G60+I60+K60+M60+O60+Q60 -> 445400
C61: Suma de Ingresos Servicios a la Membresía | D61: =SUM(D60) -> 47268.9 | E61: =SUM(E60) -> 78600 | F61: =SUM(F60) -> 47268.9 | G61: =SUM(G60) -> 52400 | H61: =SUM(H60) -> 47268.9 | I61: =SUM(I60) -> 78600 | J61: =SUM(J60) -> 47268.9 | K61: =SUM(K60) -> 78600 | ... R61: =SUM(R60) -> 47268.9 | T61: =SUM(T60) -> 47268.9 | V61: =SUM(V60) -> 47268.9 | X61: =SUM(X60) -> 47268.9 | Z61: =SUM(Z60) -> 47268.9 | AB61: =SUM(AB60) -> 567226.8 | AD61: =SUM(AD60) -> 330882.3 | AE61: =SUM(AE60) -> 445400
C63: Gastos Servicios a la Membresía
B64: 601-003-004-00 | C64: Encuesta de Sueldos y Prestaciones | D64: =D60*0.5 -> 23634.45 | E64: 39300 | F64: 23634.45 | G64: 26200 | H64: 23634.45 | I64: 39300 | J64: 23634.45 | K64: 39300 | L64: =L60*0.5 -> 23634.45 | M64: 26200 | N64: =N60*0.5 -> 23634.45 | O64: 26200 | P64: =P60*0.5 -> 23634.45 | Q64: 26200 | R64: =R60*0.5 -> 23634.45 | T64: =T60*0.5 -> 23634.45 | V64: =V60*0.5 -> 23634.45 | X64: =X60*0.5 -> 23634.45 | Z64: =Z60*0.5 -> 23634.45 | AB64: =D64+F64+H64+J64+L64+N64+P64+R64+T64+V64+X64+Z64 -> 283613.4 | AD64: =D64+F64+H64+J64+L64+N64+P64 -> 165441.15 | AE64: =E64+G64+I64+K64+M64+O64+Q64 -> 222700
C65: Suma de Gastos Servicios a la Membresía | D65: =SUM(D64) -> 23634.45 | E65: =SUM(E64) -> 39300 | F65: =SUM(F64) -> 23634.45 | G65: =SUM(G64) -> 26200 | H65: =SUM(H64) -> 23634.45 | I65: =SUM(I64) -> 39300 | J65: =SUM(J64) -> 23634.45 | K65: =SUM(K64) -> 39300 | ... R65: =SUM(R64) -> 23634.45 | T65: =SUM(T64) -> 23634.45 | V65: =SUM(V64) -> 23634.45 | X65: =SUM(X64) -> 23634.45 | Z65: =SUM(Z64) -> 23634.45 | AB65: =SUM(AB64) -> 283613.4 | AD65: =SUM(AD64) -> 165441.15 | AE65: =SUM(AE64) -> 222700
C68: Resultado Eventos y Serv Membresía | D68: =+D61-D65+D55 -> 43634.45 | E68: =+E61-E65+E55 -> 57634.93 | F68: =+F61-F65+F55 -> -32410.55 | G68: =+G61-G65+G55 -> 49586.33 | H68: =+H61-H65+H55 -> 68634.45 | I68: =+I61-I65+I55 -> 32858.27 | J68: =+J61-J65+J55 -> 93634.45 | K68: =+K61-K65+K55 -> 41235.85 | ... R68: =+R61-R65+R55 -> 53634.45 | T68: =+T61-T65+T55 -> 218634.45 | V68: =+V61-V65+V55 -> 353634.45 | X68: =+X61-X65+X55 -> -276365.55 | Z68: =+Z61-Z65+Z55 -> 23634.45 | AB68: =+AB61-AB65+AB55 -> 727568.4 | AD68: =+AD61-AD65+AD55 -> 354396.15 | AE68: =+AE61-AE65+AE55 -> 375353.61
C72: Instrucciones: Favor de llenar solo los espacios en blanco, lo que está sombreado en gris será llenado por AYF
C73: Nota: Los eventos y comités deberán presupuestarse al menos en punto de equilibrio.

Sheet Dirección
AD1: Ppto. | AE1: Real
C2: DIRECCIÓN CAPÍTULO | D2: 45658 | E2: 45658 | F2: 45689 | G2: 45689 | H2: 45717 | I2: 45717 | J2: 45748 | K2: 45748 | L2: 45778 | M2: 45778 | N2: 45809 | O2: 45809 | P2: 45839 | Q2: 45839 | R2: 45870 | S2: 45870 | T2: 45901 | U2: 45901 | V2: 45931 | W2: 45931 | X2: 45962 | Y2: 45962 | Z2: 45992 | AA2: 45992 | AB2: 2025 | AD2: Acumulado | AE2: Acumulado
C4: Ingresos CE/Board
B5: 404-006-000-00 | C5: Board Of Directors | D5: =650*25 -> 16250 | E5: 0 | F5: 16250 | G5: 0 | H5: 16250 | I5: 0 | J5: 16250 | K5: 0 | L5: =650*25 -> 16250 | M5: 0 | N5: =650*25 -> 16250 | O5: 0 | P5: =650*25 -> 16250 | Q5: 0 | R5: =650*25 -> 16250 | T5: =650*25 -> 16250 | V5: =650*25 -> 16250 | X5: =650*25 -> 16250 | Z5: =650*25 -> 16250 | AB5: =D5+F5+H5+J5+L5+N5+P5+R5+T5+V5+X5+Z5 -> 195000 | AD5: =D5+F5+H5+J5+L5+N5+P5 -> 113750 | AE5: =E5+G5+I5+K5+M5+O5+Q5 -> 0
B6: 404-011-000-00 | C6: Executive Committee | D6: =650*15 -> 9750 | E6: 0 | F6: 9750 | G6: 0 | H6: 9750 | I6: 5850 | J6: 9750 | K6: 3600 | L6: =650*15 -> 9750 | M6: 740 | N6: =650*15 -> 9750 | O6: 5850 | P6: =650*15 -> 9750 | Q6: 6750 | R6: =650*15 -> 9750 | T6: =650*15 -> 9750 | V6: =650*15 -> 9750 | X6: =650*15 -> 9750 | Z6: =650*15 -> 9750 | AB6: =D6+F6+H6+J6+L6+N6+P6+R6+T6+V6+X6+Z6 -> 117000 | AD6: =D6+F6+H6+J6+L6+N6+P6 -> 68250 | AE6: =E6+G6+I6+K6+M6+O6+Q6 -> 22790
C7: Suma de Ingresos CE/Board | D7: =SUM(D5:D6) -> 26000 | E7: =SUM(E5:E6) -> 0 | F7: =SUM(F5:F6) -> 26000 | G7: =SUM(G5:G6) -> 0 | H7: =SUM(H5:H6) -> 26000 | I7: =SUM(I5:I6) -> 5850 | J7: =SUM(J5:J6) -> 26000 | K7: =SUM(K5:K6) -> 3600 | ... R7: =SUM(R5:R6) -> 26000 | T7: =SUM(T5:T6) -> 26000 | V7: =SUM(V5:V6) -> 26000 | X7: =SUM(X5:X6) -> 26000 | Z7: =SUM(Z5:Z6) -> 26000 | AB7: =SUM(AB5:AB6) -> 312000 | AD7: =SUM(AD5:AD6) -> 182000 | AE7: =SUM(AE5:AE6) -> 22790
C9: Gastos CE/Board
B10: 502-006-000-00 | C10: Board of Directors | D10: 18000 | E10: 0 | F10: 18000 | G10: 0 | H10: 18000 | I10: 0 | J10: 18000 | K10: 0 | L10: 18000 | M10: 0 | N10: 18000 | O10: 0 | P10: 18000 | Q10: 372.75 | R10: 18000 | T10: 18000 | V10: 18000 | X10: 18000 | Z10: 18000 | AB10: =D10+F10+H10+J10+L10+N10+P10+R10+T10+V10+X10+Z10 -> 216000 | AD10: =D10+F10+H10+J10+L10+N10+P10 -> 126000 | AE10: =E10+G10+I10+K10+M10+O10+Q10 -> 372.75
B11: 502-012-000-00 | C11: Executive Committee | D11: =560*14 -> 7840 | E11: 0 | F11: 7840 | G11: 0 | H11: 7840 | I11: 656.5 | J11: 7840 | K11: 20698.44 | L11: =560*14 -> 7840 | M11: 8908.76 | N11: =560*14 -> 7840 | O11: 8460.24 | P11: =560*14 -> 7840 | Q11: 2200 | R11: =560*14 -> 7840 | T11: =560*14 -> 7840 | V11: =560*14 -> 7840 | X11: =560*14 -> 7840 | Z11: =560*14 -> 7840 | AB11: =D11+F11+H11+J11+L11+N11+P11+R11+T11+V11+X11+Z11 -> 94080 | AD11: =D11+F11+H11+J11+L11+N11+P11 -> 54880 | AE11: =E11+G11+I11+K11+M11+O11+Q11 -> 40923.94
C12: Suma de Gastos CE/Board | D12: =SUM(D10:D11) -> 25840 | E12: =SUM(E10:E11) -> 0 | F12: =SUM(F10:F11) -> 25840 | G12: =SUM(G10:G11) -> 0 | H12: =SUM(H10:H11) -> 25840 | I12: =SUM(I10:I11) -> 656.5 | J12: =SUM(J10:J11) -> 25840 | K12: =SUM(K10:K11) -> 20698.44 | ... R12: =SUM(R10:R11) -> 25840 | T12: =SUM(T10:T11) -> 25840 | V12: =SUM(V10:V11) -> 25840 | X12: =SUM(X10:X11) -> 25840 | Z12: =SUM(Z10:Z11) -> 25840 | AB12: =SUM(AB10:AB11) -> 310080 | AD12: =SUM(AD10:AD11) -> 180880 | AE12: =SUM(AE10:AE11) -> 41296.69
C14: Resultado Board y Executive | D14: =+D7-D12 -> 160 | E14: =+E7-E12 -> 0 | F14: =+F7-F12 -> 160 | G14: =+G7-G12 -> 0 | H14: =+H7-H12 -> 160 | I14: =+I7-I12 -> 5193.5 | J14: =+J7-J12 -> 160 | K14: =+K7-K12 -> -17098.44 | ... R14: =+R7-R12 -> 160 | T14: =+T7-T12 -> 160 | V14: =+V7-V12 -> 160 | X14: =+X7-X12 -> 160 | Z14: =+Z7-Z12 -> 160 | AB14: =+AB7-AB12 -> 1920 | AD14: =+AD7-AD12 -> 1120 | AE14: =+AE7-AE12 -> -18506.69
C17: Gastos de Administración
B19: 901-004-003-00 | C19: Gastos de Viaje | D19: =SUM(D20) -> 0 | E19: 0 | F19: 14500 | G19: 0 | H19: 14500 | I19: 4093.19 | J19: 0 | K19: -232 | L19: =SUM(L20) -> 0 | M19: 33715.3 | N19: =SUM(N20) -> 14500 | O19: 0 | P19: =SUM(P20) -> 0 | Q19: 11069.43 | R19: =SUM(R20) -> 0 | T19: =SUM(T20) -> 0 | V19: =SUM(V20) -> 14500 | X19: =SUM(X20) -> 0 | Z19: =SUM(Z20) -> 0 | AB19: =D19+F19+H19+J19+L19+N19+P19+R19+T19+V19+X19+Z19 -> 58000 | AD19: =D19+F19+H19+J19+L19+N19+P19 -> 43500 | AE19: =E19+G19+I19+K19+M19+O19+Q19 -> 48645.92
C20: Dirección | D20: 0 | E20: 0 | F20: 14500 | G20: 0 | H20: 14500 | I20: 4093.19 | J20: 0 | K20: -232 | L20: 0 | M20: 33715.3 | N20: 14500 | O20: 0 | P20: 0 | Q20: 11069.43 | R20: 0 | T20: 0 | V20: 14500 | X20: 0 | Z20: 0 | AB20: =D20+F20+H20+J20+L20+N20+P20+R20+T20+V20+X20+Z20 -> 58000 | AD20: =D20+F20+H20+J20+L20+N20+P20 -> 43500 | AE20: =E20+G20+I20+K20+M20+O20+Q20 -> 48645.92
B21: 901-007-000-00 | C21: Viajes Presidente Capítulo | D21: 0 | E21: 0 | F21: 0 | G21: 0 | H21: 15000 | I21: 9472.26 | J21: 0 | K21: 0 | L21: 0 | M21: 0 | N21: 0 | O21: 0 | P21: 15000 | Q21: 9570.15 | R21: 0 | T21: 0 | V21: 0 | X21: 0 | Z21: 0 | AB21: =D21+F21+H21+J21+L21+N21+P21+R21+T21+V21+X21+Z21 -> 30000 | AD21: =D21+F21+H21+J21+L21+N21+P21 -> 30000 | AE21: =E21+G21+I21+K21+M21+O21+Q21 -> 19042.41
B22: 902-003-000-00 | C22: Gasolina Administración | D22: =2500+(1500*2) -> 5500 | E22: 8000 | F22: 5500 | G22: 3000 | H22: 5500 | I22: 5500 | J22: 5500 | K22: 5000 | L22: =2500+(1500*2) -> 5500 | M22: 3000 | N22: =2500+(1500*2) -> 5500 | O22: 5333.5 | P22: =2500+(1500*2) -> 5500 | Q22: 5500 | R22: =2500+(1500*2) -> 5500 | T22: =2500+(1500*2) -> 5500 | V22: =2500+(1500*2) -> 5500 | X22: =2500+(1500*2) -> 5500 | Z22: =2500+(1500*2) -> 5500 | AB22: =D22+F22+H22+J22+L22+N22+P22+R22+T22+V22+X22+Z22 -> 66000 | AD22: =D22+F22+H22+J22+L22+N22+P22 -> 38500 | AE22: =E22+G22+I22+K22+M22+O22+Q22 -> 35333.5
B23: 901-014-004-00 | C23: Mtto. Equipo de Transporte | D23: 0 | E23: 0 | F23: 0 | G23: 0 | H23: 6750 | I23: 0 | J23: 0 | K23: 0 | L23: 0 | M23: 0 | N23: 0 | O23: 0 | P23: 0 | Q23: 0 | R23: 0 | T23: =13500/2 -> 6750 | V23: 0 | X23: 0 | Z23: 0 | AB23: =D23+F23+H23+J23+L23+N23+P23+R23+T23+V23+X23+Z23 -> 13500 | AD23: =D23+F23+H23+J23+L23+N23+P23 -> 6750 | AE23: =E23+G23+I23+K23+M23+O23+Q23 -> 0
B24: 902-002-001-00 | C24: Gastos de representacion | D24: 3500 | E24: 0 | F24: 0 | G24: 993.97 | H24: 0 | I24: -256.04 | J24: 0 | K24: 0 | L24: 0 | M24: 0 | N24: 3500 | O24: 0 | P24: 0 | Q24: 0 | R24: 0 | T24: 0 | V24: 0 | X24: 3500 | Z24: 0 | AB24: =D24+F24+H24+J24+L24+N24+P24+R24+T24+V24+X24+Z24 -> 10500 | AD24: =D24+F24+H24+J24+L24+N24+P24 -> 7000 | AE24: =E24+G24+I24+K24+M24+O24+Q24 -> 737.93
B25: 902-002-003-00 | C25: Cuotas CCI | D25: 500 | E25: 0 | F25: 500 | G25: 0 | H25: 500 | I25: 0 | J25: 500 | K25: 0 | L25: 500 | M25: 0 | N25: 500 | O25: 431.04 | P25: 500 | Q25: 0 | R25: 500 | T25: 500 | V25: 500 | X25: 500 | Z25: 500 | AB25: =D25+F25+H25+J25+L25+N25+P25+R25+T25+V25+X25+Z25 -> 6000 | AD25: =D25+F25+H25+J25+L25+N25+P25 -> 3500 | AE25: =E25+G25+I25+K25+M25+O25+Q25 -> 431.04
B26: 902-002-003-00 | C26: Cuotas CCJEJ | D26: 0 | E26: 0 | F26: 7500 | G26: 0 | H26: 0 | I26: 0 | J26: 0 | K26: 0 | L26: 0 | M26: 0 | N26: 0 | O26: 0 | P26: 0 | Q26: 0 | R26: 0 | T26: 0 | V26: 0 | X26: 0 | Z26: 0 | AB26: =D26+F26+H26+J26+L26+N26+P26+R26+T26+V26+X26+Z26 -> 7500 | AD26: =D26+F26+H26+J26+L26+N26+P26 -> 7500 | AE26: =E26+G26+I26+K26+M26+O26+Q26 -> 0
C27: Suma Gastos Administrativos | D27: =D19+D22+D24+D25+D23+D26+D21 -> 9500 | E27: =E19+E22+E24+E25+E23+E26+E21 -> 8000 | F27: =F19+F22+F24+F25+F23+F26+F21 -> 28000 | G27: =G19+G22+G24+G25+G23+G26+G21 -> 3993.97 | H27: =H19+H22+H24+H25+H23+H26+H21 -> 42250 | I27: =I19+I22+I24+I25+I23+I26+I21 -> 18809.41 | J27: =J19+J22+J24+J25+J23+J26+J21 -> 6000 | K27: =K19+K22+K24+K25+K23+K26+K21 -> 4768 | ... R27: =R19+R22+R24+R25+R23+R26+R21 -> 6000 | T27: =T19+T22+T24+T25+T23+T26+T21 -> 12750 | V27: =V19+V22+V24+V25+V23+V26+V21 -> 20500 | X27: =X19+X22+X24+X25+X23+X26+X21 -> 9500 | Z27: =Z19+Z22+Z24+Z25+Z23+Z26+Z21 -> 6000 | AB27: =AB19+AB22+AB24+AB25+AB23+AB26+AB21 -> 191500 | AD27: =AD19+AD22+AD24+AD25+AD23+AD26+AD21 -> 136750 | AE27: =AE19+AE22+AE24+AE25+AE23+AE26+AE21 -> 104190.8
C29: Resultado Director Capítulo | D29: =D14-D27 -> -9340 | E29: =E14-E27 -> -8000 | F29: =F14-F27 -> -27840 | G29: =G14-G27 -> -3993.97 | H29: =H14-H27 -> -42090 | I29: =I14-I27 -> -13615.91 | J29: =J14-J27 -> -5840 | K29: =K14-K27 -> -21866.44 | ... R29: =R14-R27 -> -5840 | T29: =T14-T27 -> -12590 | V29: =V14-V27 -> -20340 | X29: =X14-X27 -> -9340 | Z29: =Z14-Z27 -> -5840 | AB29: =AB14-AB27 -> -189580 | AD29: =AD14-AD27 -> -135630 | AE29: =AE14-AE27 -> -122697.49
C32: Instrucciones: Favor de llenar solo los espacios en blanco, lo que está sombreado en gris será llenado por AYF

Sheet Gastos Generales
AD1: Ppto. | AE1: Real
C2: GASTOS GENERALES | D2: 45658 | E2: 45658 | F2: 45689 | G2: 45689 | H2: 45717 | I2: 45717 | J2: 45748 | K2: 45748 | L2: 45778 | M2: 45778 | N2: 45809 | O2: 45809 | P2: 45839 | Q2: 45839 | R2: 45870 | S2: 45870 | T2: 45901 | U2: 45901 | V2: 45931 | W2: 45931 | X2: 45962 | Y2: 45962 | Z2: 45992 | AA2: 45992 | AB2: 2025 | AD2: Acumulado | AE2: Acumulado
C4: Otros ingresos
B5: 402-000-000-00 | C5: Otros Ingresos | D5: 0 | E5: 29.04 | F5: 0 | G5: 32.87 | H5: 0 | I5: 10.89 | J5: 0 | K5: 20.27 | L5: 0 | M5: 13.92 | N5: 0 | O5: 21.96 | P5: 0 | Q5: 0.01 | R5: 0 | T5: 0 | V5: 0 | X5: 0 | Z5: 0 | AB5: =D5+F5+H5+J5+L5+N5+P5+R5+T5+V5+X5+Z5 -> 0 | AD5: =D5+F5+H5+J5+L5+N5+P5 -> 0 | AE5: =E5+G5+I5+K5+M5+O5+Q5 -> 128.96
C6: Suma Otros Ingresos | D6: =D5 -> 0 | E6: =E5 -> 29.04 | F6: =F5 -> 0 | G6: =G5 -> 32.87 | H6: =H5 -> 0 | I6: =I5 -> 10.89 | J6: =J5 -> 0 | K6: =K5 -> 20.27 | ... R6: =R5 -> 0 | T6: =T5 -> 0 | V6: =V5 -> 0 | X6: =X5 -> 0 | Z6: =Z5 -> 0 | AB6: =AB5 -> 0 | AD6: =AD5 -> 0 | AE6: =AE5 -> 128.96
C8: Gastos Financieros
B9: 410-000-000-00 | C9: Utilidad Cambiaria | D9: 0 | E9: 0 | F9: 0 | G9: 0 | H9: 0 | I9: 0 | J9: 0 | K9: 0 | L9: 0 | M9: 0 | N9: 0 | O9: 0 | P9: 0 | Q9: 0 | R9: 0 | T9: 0 | V9: 0 | X9: 0 | Z9: 0 | AB9: =D9+F9+H9+J9+L9+N9+P9+R9+T9+V9+X9+Z9 -> 0 | AD9: =D9+F9+H9+J9+L9+N9+P9 -> 0 | AE9: =E9+G9+I9+K9+M9+O9+Q9 -> 0
B10: 901-019-000-00 | C10: Perdida Cambiaria | D10: 0 | E10: 0 | F10: 0 | G10: 0 | H10: 0 | I10: 0 | J10: 0 | K10: 0 | L10: 0 | M10: 0 | N10: 0 | O10: 0 | P10: 0 | Q10: 0 | R10: 0 | T10: 0 | V10: 0 | X10: 0 | Z10: 0 | AB10: =D10+F10+H10+J10+L10+N10+P10+R10+T10+V10+X10+Z10 -> 0 | AD10: =D10+F10+H10+J10+L10+N10+P10 -> 0 | AE10: =E10+G10+I10+K10+M10+O10+Q10 -> 0
B11: 901-020-000-00 | C11: Gtos Financieros (comisiones) | D11: 3750 | E11: 6394.13 | F11: 3750 | G11: 1455.07 | H11: 3750 | I11: 1405.74 | J11: 3750 | K11: 3853.96 | L11: 3750 | M11: 3054.68 | N11: 3750 | O11: 6965.99 | P11: 3750 | Q11: 3326.66 | R11: 3750 | T11: 3750 | V11: 3750 | X11: 3750 | Z11: 3750 | AB11: =D11+F11+H11+J11+L11+N11+P11+R11+T11+V11+X11+Z11 -> 45000 | AD11: =D11+F11+H11+J11+L11+N11+P11 -> 26250 | AE11: =E11+G11+I11+K11+M11+O11+Q11 -> 26456.23
C12: Suma Gastos Financieros | D12: =D11+D10-D9 -> 3750 | E12: =E11+E10-E9 -> 6394.13 | F12: =F11+F10-F9 -> 3750 | G12: =G11+G10-G9 -> 1455.07 | H12: =H11+H10-H9 -> 3750 | I12: =I11+I10-I9 -> 1405.74 | J12: =J11+J10-J9 -> 3750 | K12: =K11+K10-K9 -> 3853.96 | ... R12: =R11+R10-R9 -> 3750 | T12: =T11+T10-T9 -> 3750 | V12: =V11+V10-V9 -> 3750 | X12: =X11+X10-X9 -> 3750 | Z12: =Z11+Z10-Z9 -> 3750 | AB12: =AB11+AB10-AB9 -> 45000 | AD12: =AD11+AD10-AD9 -> 26250 | AE12: =AE11+AE10-AE9 -> 26456.23
C14: Otros Ingresos vs Gastos | D14: =D6-D12 -> -3750 | E14: =E6-E12 -> -6365.09 | F14: =F6-F12 -> -3750 | G14: =G6-G12 -> -1422.2 | H14: =H6-H12 -> -3750 | I14: =I6-I12 -> -1394.85 | J14: =J6-J12 -> -3750 | K14: =K6-K12 -> -3833.69 | ... R14: =R6-R12 -> -3750 | T14: =T6-T12 -> -3750 | V14: =V6-V12 -> -3750 | X14: =X6-X12 -> -3750 | Z14: =Z6-Z12 -> -3750 | AB14: =AB6-AB12 -> -45000 | AD14: =AD6-AD12 -> -26250 | AE14: =AE6-AE12 -> -26327.27
C16: Gastos Generales
B17: 801-004-000-00 | C17: MONITOREO ALARMA | D17: =996*1.06 -> 1055.76 | E17: 1317 | F17: 1055.76 | G17: 450 | H17: 1055.76 | I17: 2998 | J17: 1055.76 | K17: 900 | L17: =996*1.06 -> 1055.76 | M17: 450 | N17: =996*1.06 -> 1055.76 | O17: 2937 | P17: =996*1.06 -> 1055.76 | Q17: 450 | R17: =996*1.06 -> 1055.76 | T17: =996*1.06 -> 1055.76 | V17: =996*1.06 -> 1055.76 | X17: =996*1.06 -> 1055.76 | Z17: =996*1.06 -> 1055.76 | AB17: =D17+F17+H17+J17+L17+N17+P17+R17+T17+V17+X17+Z17 -> 12669.12 | AD17: =D17+F17+H17+J17+L17+N17+P17 -> 7390.32 | AE17: =E17+G17+I17+K17+M17+O17+Q17 -> 9502
B18: 801-001-000-00 | C18: ENERGIA ELECTRICA | D18: 9500 | E18: 0 | F18: 0 | G18: 3899.96 | H18: 9500 | I18: 0 | J18: 0 | K18: 5018.08 | L18: 9500 | M18: 0 | N18: 0 | O18: 9280.15 | P18: 9500 | Q18: 0 | R18: 0 | T18: 9500 | V18: 0 | X18: 9500 | Z18: 0 | AB18: =D18+F18+H18+J18+L18+N18+P18+R18+T18+V18+X18+Z18 -> 57000 | AD18: =D18+F18+H18+J18+L18+N18+P18 -> 38000 | AE18: =E18+G18+I18+K18+M18+O18+Q18 -> 18198.19
B19: 801-002-000-00 | C19: AGUA POTABLE | D19: 800 | E19: 143 | F19: 800 | G19: 372 | H19: 800 | I19: 197 | J19: 800 | K19: 150 | L19: 800 | M19: 168 | N19: 800 | O19: 138 | P19: 800 | Q19: 114 | R19: 800 | T19: 800 | V19: 800 | X19: 800 | Z19: 800 | AB19: =D19+F19+H19+J19+L19+N19+P19+R19+T19+V19+X19+Z19 -> 9600 | AD19: =D19+F19+H19+J19+L19+N19+P19 -> 5600 | AE19: =E19+G19+I19+K19+M19+O19+Q19 -> 1282
B20: 801-003-000-00 | C20: PREDIAL | D20: =12657+(12657*0.1) -> 13922.7 | E20: 13185 | F20: 0 | G20: 0 | H20: 0 | I20: 0 | J20: 0 | K20: 0 | L20: 0 | M20: 0 | N20: 0 | O20: 0 | P20: 0 | Q20: 0 | R20: 0 | T20: 0 | V20: 0 | X20: 0 | Z20: 0 | AB20: =D20+F20+H20+J20+L20+N20+P20+R20+T20+V20+X20+Z20 -> 13922.7 | AD20: =D20+F20+H20+J20+L20+N20+P20 -> 13922.7 | AE20: =E20+G20+I20+K20+M20+O20+Q20 -> 13185
B21: 901-011-013-00 | C21: ASEO OFICINAS | D21: =9990+(9990*0.1) -> 10989 | E21: 11190 | F21: 10989 | G21: 11190 | H21: 10989 | I21: 11190 | J21: 10989 | K21: 11190 | L21: =9990+(9990*0.1) -> 10989 | M21: 11190 | N21: =9990+(9990*0.1) -> 10989 | O21: 14990 | P21: =9990+(9990*0.1) -> 10989 | Q21: 14990 | R21: =9990+(9990*0.1) -> 10989 | T21: =9990+(9990*0.1) -> 10989 | V21: =9990+(9990*0.1) -> 10989 | X21: =9990+(9990*0.1) -> 10989 | Z21: =9990+(9990*0.1) -> 10989 | AB21: =D21+F21+H21+J21+L21+N21+P21+R21+T21+V21+X21+Z21 -> 131868 | AD21: =D21+F21+H21+J21+L21+N21+P21 -> 76923 | AE21: =E21+G21+I21+K21+M21+O21+Q21 -> 85930
B22: 901-011-006-00 | C22: MANTTO LAVANDERIA, TINTORERIA | D22: 1100 | E22: 0 | F22: 0 | G22: 651.76 | H22: 0 | I22: 15500 | J22: 1100 | K22: 0 | L22: 0 | M22: 0 | N22: 0 | O22: 0 | P22: 1100 | Q22: 0 | R22: 0 | T22: 0 | V22: 1100 | X22: 0 | Z22: 0 | AB22: =D22+F22+H22+J22+L22+N22+P22+R22+T22+V22+X22+Z22 -> 4400 | AD22: =D22+F22+H22+J22+L22+N22+P22 -> 3300 | AE22: =E22+G22+I22+K22+M22+O22+Q22 -> 16151.76
C23: Poda de jardín | D23: 1740 | E23: 0 | F23: 1740 | G23: 0 | H23: 1740 | I23: 0 | J23: 1740 | K23: 0 | L23: 1740 | M23: 0 | N23: 1740 | O23: 0 | P23: 1740 | Q23: 0 | R23: 1740 | T23: 1740 | V23: 1740 | X23: 1740 | Z23: 1740 | AB23: =D23+F23+H23+J23+L23+N23+P23+R23+T23+V23+X23+Z23 -> 20880 | AD23: =D23+F23+H23+J23+L23+N23+P23 -> 12180 | AE23: =E23+G23+I23+K23+M23+O23+Q23 -> 0
C24: Recolección de basura | D24: 0 | E24: 0 | F24: 0 | G24: 0 | H24: 0 | I24: 0 | J24: 0 | K24: 0 | L24: 0 | M24: 0 | N24: 0 | O24: 0 | P24: 0 | Q24: 0 | R24: 0 | T24: 0 | V24: 0 | X24: 0 | Z24: 0 | AB24: =D24+F24+H24+J24+L24+N24+P24+R24+T24+V24+X24+Z24 -> 0 | AD24: =D24+F24+H24+J24+L24+N24+P24 -> 0 | AE24: =E24+G24+I24+K24+M24+O24+Q24 -> 0
B25: 901-014-001-00 | C25: MANTTO EQ DE OFICINA | D25: =SUM(D23:D24) -> 1740 | E25: =SUM(E23:E24) -> 0 | F25: =SUM(F23:F24) -> 1740 | G25: =SUM(G23:G24) -> 0 | H25: =SUM(H23:H24) -> 1740 | I25: =SUM(I23:I24) -> 0 | J25: =SUM(J23:J24) -> 1740 | K25: =SUM(K23:K24) -> 0 | ... R25: =SUM(R23:R24) -> 1740 | T25: =SUM(T23:T24) -> 1740 | V25: =SUM(V23:V24) -> 1740 | X25: =SUM(X23:X24) -> 1740 | Z25: =SUM(Z23:Z24) -> 1740 | AB25: =D25+F25+H25+J25+L25+N25+P25+R25+T25+V25+X25+Z25 -> 20880 | AD25: =D25+F25+H25+J25+L25+N25+P25 -> 12180 | AE25: =E25+G25+I25+K25+M25+O25+Q25 -> 0
B26: 901-014-002-00 | C26: MANTTO EQ DE COMPUTO | D26: 0 | E26: 0 | F26: 28000 | G26: 21444.52 | H26: 0 | I26: 4256.22 | J26: 16000 | K26: 2102.07 | L26: 0 | M26: 0 | N26: 0 | O26: 1425 | P26: 16000 | Q26: 7995 | R26: 0 | T26: 0 | V26: 16000 | X26: 0 | Z26: 0 | AB26: =D26+F26+H26+J26+L26+N26+P26+R26+T26+V26+X26+Z26 -> 76000 | AD26: =D26+F26+H26+J26+L26+N26+P26 -> 60000 | AE26: =E26+G26+I26+K26+M26+O26+Q26 -> 37222.81
C27: Recarga Extintores | D27: 0 | E27: 0 | F27: 0 | G27: 0 | H27: 2695 | I27: 2500 | J27: 0 | K27: 0 | L27: 0 | M27: 0 | N27: 0 | O27: 0 | P27: 0 | Q27: 0 | R27: 0 | T27: 2695 | V27: 0 | X27: 0 | Z27: 0 | AB27: =D27+F27+H27+J27+L27+N27+P27+R27+T27+V27+X27+Z27 -> 5390 | AD27: =D27+F27+H27+J27+L27+N27+P27 -> 2695 | AE27: =E27+G27+I27+K27+M27+O27+Q27 -> 2500
C28: Fumigaciones y sanitización | D28: =3150*1.06 -> 3339 | E28: 0 | F28: 0 | G28: 0 | H28: 0 | I28: 0 | J28: 3339 | K28: 0 | L28: 0 | M28: 1400 | N28: 0 | O28: 0 | P28: =3150*1.06 -> 3339 | Q28: 1600 | R28: 0 | T28: 0 | V28: =3150*1.06 -> 3339 | X28: 0 | Z28: 0 | AB28: =D28+F28+H28+J28+L28+N28+P28+R28+T28+V28+X28+Z28 -> 13356 | AD28: =D28+F28+H28+J28+L28+N28+P28 -> 10017 | AE28: =E28+G28+I28+K28+M28+O28+Q28 -> 3000
C29: Mantenimiento Portón Electrico | D29: 7500 | E29: 0 | F29: 0 | G29: 0 | H29: 0 | I29: 0 | J29: 0 | K29: 0 | L29: 0 | M29: 0 | N29: 0 | O29: 0 | P29: 7500 | Q29: 0 | R29: 0 | T29: 0 | V29: 0 | X29: 0 | Z29: 0 | AB29: =D29+F29+H29+J29+L29+N29+P29+R29+T29+V29+X29+Z29 -> 15000 | AD29: =D29+F29+H29+J29+L29+N29+P29 -> 15000 | AE29: =E29+G29+I29+K29+M29+O29+Q29 -> 0
C30: Mantenimiento aire acondicionado | D30: 0 | E30: 0 | F30: 0 | G30: 0 | H30: 20000 | I30: 0 | J30: 0 | K30: 55800 | L30: 0 | M30: 9100 | N30: 20000 | O30: 19650 | P30: 0 | Q30: 0 | R30: 0 | T30: 20000 | V30: 0 | X30: 0 | Z30: 0 | AB30: =D30+F30+H30+J30+L30+N30+P30+R30+T30+V30+X30+Z30 -> 60000 | AD30: =D30+F30+H30+J30+L30+N30+P30 -> 40000 | AE30: =E30+G30+I30+K30+M30+O30+Q30 -> 84550
C31: Diversos (reparaciones mayores, pintura, toldo para jardín, etc.) | D31: 10000 | E31: 600 | F31: 10000 | G31: 4129.35 | H31: 80000 | I31: 41836.74 | J31: 50000 | K31: 2150 | L31: 30000 | M31: 24521.75 | N31: 10000 | O31: 11378 | P31: 10000 | Q31: 13800 | R31: 10000 | T31: 10000 | V31: 10000 | X31: 10000 | Z31: 10000 | AB31: =D31+F31+H31+J31+L31+N31+P31+R31+T31+V31+X31+Z31 -> 250000 | AD31: =D31+F31+H31+J31+L31+N31+P31 -> 200000 | AE31: =E31+G31+I31+K31+M31+O31+Q31 -> 98415.84
B32: 801-005-001-00 | C32: MANTTO.Y GTOS DEL LOCAL | D32: =SUM(D27:D31) -> 20839 | E32: =SUM(E27:E31) -> 600 | F32: =SUM(F27:F31) -> 10000 | G32: =SUM(G27:G31) -> 4129.35 | H32: =SUM(H27:H31) -> 102695 | I32: =SUM(I27:I31) -> 44336.74 | J32: =SUM(J27:J31) -> 53339 | K32: =SUM(K27:K31) -> 57950 | ... R32: =SUM(R27:R31) -> 10000 | T32: =SUM(T27:T31) -> 32695 | V32: =SUM(V27:V31) -> 13339 | X32: =SUM(X27:X31) -> 10000 | Z32: =SUM(Z27:Z31) -> 10000 | AB32: =D32+F32+H32+J32+L32+N32+P32+R32+T32+V32+X32+Z32 -> 343746 | AD32: =D32+F32+H32+J32+L32+N32+P32 -> 267712 | AE32: =E32+G32+I32+K32+M32+O32+Q32 -> 188465.84
B33: 901-003-000-00 | C33: RENTA IMPRESORAS / COPIADORAS | D33: =1700*1.06 -> 1802 | E33: 1700 | F33: 1802 | G33: 1700 | H33: 1802 | I33: 1700 | J33: 1802 | K33: 1700 | L33: =1700*1.06 -> 1802 | M33: 1700 | N33: =1700*1.06 -> 1802 | O33: 1700 | P33: =1700*1.06 -> 1802 | Q33: 1700 | R33: =1700*1.06 -> 1802 | T33: =1700*1.06 -> 1802 | V33: =1700*1.06 -> 1802 | X33: =1700*1.06 -> 1802 | Z33: =1700*1.06 -> 1802 | AB33: =D33+F33+H33+J33+L33+N33+P33+R33+T33+V33+X33+Z33 -> 21624 | AD33: =D33+F33+H33+J33+L33+N33+P33 -> 12614 | AE33: =E33+G33+I33+K33+M33+O33+Q33 -> 11900
B34: 901-006-001-00 | C34: TELCEL / WHATSAPP | D34: 3200 | E34: 3192 | F34: 0 | G34: 0 | H34: 0 | I34: 0 | J34: 0 | K34: 0 | L34: 0 | M34: 0 | N34: 0 | O34: 0 | P34: 0 | Q34: 0 | R34: 0 | T34: 0 | V34: 0 | X34: 0 | Z34: 0 | AB34: =D34+F34+H34+J34+L34+N34+P34+R34+T34+V34+X34+Z34 -> 3200 | AD34: =D34+F34+H34+J34+L34+N34+P34 -> 3200 | AE34: =E34+G34+I34+K34+M34+O34+Q34 -> 3192
B35: 901-006-003-00 | C35: TELEFONOS DE MEXICO | D35: =799+(799*0.1) -> 878.9 | E35: 799 | F35: 878.9 | G35: 799 | H35: 878.9 | I35: 799 | J35: 878.9 | K35: 799 | L35: =799+(799*0.1) -> 878.9 | M35: 799 | N35: =799+(799*0.1) -> 878.9 | O35: 799 | P35: =799+(799*0.1) -> 878.9 | Q35: 799 | R35: =799+(799*0.1) -> 878.9 | T35: =799+(799*0.1) -> 878.9 | V35: =799+(799*0.1) -> 878.9 | X35: =799+(799*0.1) -> 878.9 | Z35: =799+(799*0.1) -> 878.9 | AB35: =D35+F35+H35+J35+L35+N35+P35+R35+T35+V35+X35+Z35 -> 10546.8 | AD35: =D35+F35+H35+J35+L35+N35+P35 -> 6152.3 | AE35: =E35+G35+I35+K35+M35+O35+Q35 -> 5593
C36: TELEFONOS | D36: =SUM(D34:D35) -> 4078.9 | E36: =SUM(E34:E35) -> 3991 | F36: =SUM(F34:F35) -> 878.9 | G36: =SUM(G34:G35) -> 799 | H36: =SUM(H34:H35) -> 878.9 | I36: =SUM(I34:I35) -> 799 | J36: =SUM(J34:J35) -> 878.9 | K36: =SUM(K34:K35) -> 799 | ... R36: =SUM(R34:R35) -> 878.9 | T36: =SUM(T34:T35) -> 878.9 | V36: =SUM(V34:V35) -> 878.9 | X36: =SUM(X34:X35) -> 878.9 | Z36: =SUM(Z34:Z35) -> 878.9 | AB36: =D36+F36+H36+J36+L36+N36+P36+R36+T36+V36+X36+Z36 -> 13746.8 | AD36: =D36+F36+H36+J36+L36+N36+P36 -> 9352.3 | AE36: =E36+G36+I36+K36+M36+O36+Q36 -> 8785
C37: FEDEX, SEPOMEX, Etc. | D37: 500 | E37: 0 | F37: 400 | G37: 0 | H37: 500 | I37: 700.24 | J37: 400 | K37: 0 | L37: 500 | M37: 1587.52 | N37: 0 | O37: 533.98 | P37: 500 | Q37: 0 | R37: 400 | T37: 500 | V37: 400 | X37: 500 | Z37: 400 | AB37: =D37+F37+H37+J37+L37+N37+P37+R37+T37+V37+X37+Z37 -> 5000 | AD37: =D37+F37+H37+J37+L37+N37+P37 -> 2800 | AE37: =E37+G37+I37+K37+M37+O37+Q37 -> 2821.74
B38: 901-011-002-00 | C38: PAQUETERIA Y MENSAJERIA | D38: =SUM(D37) -> 500 | E38: 0 | F38: 400 | G38: 0 | H38: 500 | I38: 700.24 | J38: 400 | K38: 0 | L38: =SUM(L37) -> 500 | M38: 1587.52 | N38: =SUM(N37) -> 0 | O38: 533.98 | P38: =SUM(P37) -> 500 | Q38: =SUM(Q37) -> 0 | R38: =SUM(R37) -> 400 | T38: =SUM(T37) -> 500 | V38: =SUM(V37) -> 400 | X38: =SUM(X37) -> 500 | Z38: =SUM(Z37) -> 400 | AB38: =D38+F38+H38+J38+L38+N38+P38+R38+T38+V38+X38+Z38 -> 5000 | AD38: =D38+F38+H38+J38+L38+N38+P38 -> 2800 | AE38: =E38+G38+I38+K38+M38+O38+Q38 -> 2821.74
B39: 901-011-011-00 | C39: GTOS EXP PERMISO LICENCIA | D39: 0 | E39: 0 | F39: 0 | G39: 0 | H39: 25000 | I39: 0 | J39: 0 | K39: 0 | L39: 0 | M39: 7000 | N39: 0 | O39: 7000 | P39: 25000 | Q39: 0 | R39: 0 | T39: 0 | V39: 0 | X39: 25000 | Z39: 0 | AB39: =D39+F39+H39+J39+L39+N39+P39+R39+T39+V39+X39+Z39 -> 75000 | AD39: =D39+F39+H39+J39+L39+N39+P39 -> 50000 | AE39: =E39+G39+I39+K39+M39+O39+Q39 -> 14000
B40: 901-011-012-00 | C40: GASTOS EXTRAORDINARIOS | D40: 0 | E40: 7755.58 | F40: 20000 | G40: 0 | H40: 0 | I40: -748.09 | J40: 20000 | K40: 701.1 | L40: 0 | M40: 123021.26 | N40: 20000 | O40: 93000 | P40: 0 | Q40: 0 | R40: 20000 | T40: 0 | V40: 20000 | X40: 0 | Z40: 20000 | AB40: =D40+F40+H40+J40+L40+N40+P40+R40+T40+V40+X40+Z40 -> 120000 | AD40: =D40+F40+H40+J40+L40+N40+P40 -> 60000 | AE40: =E40+G40+I40+K40+M40+O40+Q40 -> 223729.85
B41: 901-011-015-00 | C41: Administración Fideicomiso | D41: 20000 | E41: 0 | F41: 50000 | G41: 0 | I41: 0 | J41: 50000 | K41: 0 | L41: 0 | M41: 0 | N41: 0 | O41: 0 | P41: 0 | Q41: 15003.21 | R41: 0 | T41: 0 | V41: 0 | X41: 0 | Z41: 0 | AB41: =D41+F41+H41+J41+L41+N41+P41+R41+T41+V41+X41+Z41 -> 120000 | AD41: =D41+F41+H41+J41+L41+N41+P41 -> 120000 | AE41: =E41+G41+I41+K41+M41+O41+Q41 -> 15003.21
B42: 901-011-005-00 | C42: No deducibles (PODA, BASURA, AGUA ESTACIONAMIENTOS) | D42: =600+300+150 -> 1050 | E42: 3370 | F42: 1050 | G42: 600 | H42: 1050 | I42: 600 | J42: 1050 | K42: 600 | L42: =600+300+150 -> 1050 | M42: 754.99 | N42: =600+300+150 -> 1050 | O42: 923 | P42: =600+300+150 -> 1050 | Q42: 1149.99 | R42: =600+300+150 -> 1050 | T42: =600+300+150 -> 1050 | V42: =600+300+150 -> 1050 | X42: =600+300+150 -> 1050 | Z42: =600+300+150 -> 1050 | AB42: =D42+F42+H42+J42+L42+N42+P42+R42+T42+V42+X42+Z42 -> 12600 | AD42: =D42+F42+H42+J42+L42+N42+P42 -> 7350 | AE42: =E42+G42+I42+K42+M42+O42+Q42 -> 7997.98
B43: 901-011-004-00 | C43: Varios | D43: 1000 | E43: 0 | F43: 1000 | G43: 0 | H43: 1000 | I43: 0 | J43: 1000 | K43: 0 | L43: 1000 | M43: 0 | N43: 1000 | O43: 0 | P43: 1000 | Q43: 0 | R43: 1000 | T43: 1000 | V43: 1000 | X43: 1000 | Z43: 1000 | AB43: =D43+F43+H43+J43+L43+N43+P43+R43+T43+V43+X43+Z43 -> 12000 | AD43: =D43+F43+H43+J43+L43+N43+P43 -> 7000 | AE43: =E43+G43+I43+K43+M43+O43+Q43 -> 0
C44: OTROS GASTOS | D44: =SUM(D41:D43) -> 22050 | E44: =SUM(E41:E43) -> 3370 | F44: =SUM(F41:F43) -> 52050 | G44: =SUM(G41:G43) -> 600 | H44: =SUM(H41:H43) -> 2050 | I44: =SUM(I41:I43) -> 600 | J44: =SUM(J41:J43) -> 52050 | K44: =SUM(K41:K43) -> 600 | ... R44: =SUM(R41:R43) -> 2050 | T44: =SUM(T41:T43) -> 2050 | V44: =SUM(V41:V43) -> 2050 | X44: =SUM(X41:X43) -> 2050 | Z44: =SUM(Z41:Z43) -> 2050 | AB44: =D44+F44+H44+J44+L44+N44+P44+R44+T44+V44+X44+Z44 -> 144600 | AD44: =D44+F44+H44+J44+L44+N44+P44 -> 134350 | AE44: =E44+G44+I44+K44+M44+O44+Q44 -> 23001.19
B45: 901-024-000-00 | C45: REUNION FIN DE AÑO | D45: 0 | E45: 0 | F45: 0 | G45: 0 | H45: 0 | I45: 0 | J45: 0 | K45: 0 | L45: 0 | M45: 0 | N45: 0 | O45: 0 | P45: 0 | Q45: 0 | R45: 0 | T45: 0 | V45: 0 | X45: 17750 | Z45: 17750 | AB45: =D45+F45+H45+J45+L45+N45+P45+R45+T45+V45+X45+Z45 -> 35500 | AD45: =D45+F45+H45+J45+L45+N45+P45 -> 0 | AE45: =E45+G45+I45+K45+M45+O45+Q45 -> 0
B46: 901-022-000-00 | C46: IVA A PRORRATA NO ACREDITABLE | D46: 7583.33 | E46: 6300.83 | F46: 7583.33 | G46: 4300.65 | H46: 7583.33 | I46: 5488.08 | J46: 7583.33 | K46: 8205.68 | L46: 7583.33 | M46: 4527.89 | N46: 7583.33 | O46: 4660.03 | P46: 7583.33 | Q46: 5873.59 | R46: 7583.33 | T46: 7583.33 | V46: 7583.33 | X46: 7583.33 | Z46: 7583.33 | AB46: =D46+F46+H46+J46+L46+N46+P46+R46+T46+V46+X46+Z46 -> 90999.96 | AD46: =D46+F46+H46+J46+L46+N46+P46 -> 53083.31 | AE46: =E46+G46+I46+K46+M46+O46+Q46 -> 39356.75
B47: 901-099-000-00 | C47: AJUSTES Y DIFERENCIAS | D47: 0 | E47: -0.01 | F47: 0 | G47: -10.01 | H47: 0 | I47: -0.01 | J47: 0 | K47: 0 | L47: 0 | M47: -19.91 | N47: 0 | O47: 0.01 | P47: 0 | Q47: 0.01 | R47: 0 | T47: 0 | V47: 0 | X47: 0 | Z47: 0 | AB47: =D47+F47+H47+J47+L47+N47+P47+R47+T47+V47+X47+Z47 -> 0 | AD47: =D47+F47+H47+J47+L47+N47+P47 -> 0 | AE47: =E47+G47+I47+K47+M47+O47+Q47 -> -29.92
C48: Cuota vecinal | D48: 0 | E48: 2700 | F48: 0 | H48: =2800+(2800*0.1) -> 3080 | I48: 0 | J48: 0 | K48: 0 | L48: 0 | M48: 0 | N48: 0 | O48: 0 | P48: 0 | Q48: 0 | R48: 0 | T48: 0 | V48: 0 | X48: 0 | Z48: 0 | AB48: =D48+F48+H48+J48+L48+N48+P48+R48+T48+V48+X48+Z48 -> 3080 | AD48: =D48+F48+H48+J48+L48+N48+P48 -> 3080 | AE48: =E48+G48+I48+K48+M48+O48+Q48 -> 2700
C49: Cuota Asociación Femenil de Ejecutivas de Empresas | D49: 0 | E49: 0 | F49: 0 | H49: 0 | I49: 0 | J49: 0 | K49: 0 | L49: 0 | M49: 0 | N49: =5600+(5600*0.1) -> 6160 | O49: 0 | P49: 0 | Q49: 0 | R49: 0 | T49: 0 | V49: 0 | X49: 0 | Z49: 0 | AB49: =D49+F49+H49+J49+L49+N49+P49+R49+T49+V49+X49+Z49 -> 6160 | AD49: =D49+F49+H49+J49+L49+N49+P49 -> 6160 | AE49: =E49+G49+I49+K49+M49+O49+Q49 -> 0
C50: Otras cuotas y suscripciones | D50: 400 | E50: 0 | F50: 400 | H50: 400 | I50: 0 | J50: 400 | K50: 0 | L50: 400 | M50: 0 | N50: 400 | O50: 0 | P50: 400 | Q50: 0 | R50: 400 | T50: 400 | V50: 400 | X50: 400 | Z50: 400 | AB50: =D50+F50+H50+J50+L50+N50+P50+R50+T50+V50+X50+Z50 -> 4800 | AD50: =D50+F50+H50+J50+L50+N50+P50 -> 2800 | AE50: =E50+G50+I50+K50+M50+O50+Q50 -> 0
B51: 901-002-000-00 | C51: CUOTAS y SUSCRIPCIONES | D51: =SUM(D48:D50) -> 400 | E51: 2700 | F51: 400 | G51: 0 | H51: 3480 | I51: 0 | J51: 400 | K51: 0 | L51: =SUM(L48:L50) -> 400 | M51: 0 | N51: =SUM(N48:N50) -> 6560 | O51: 0 | P51: =SUM(P48:P50) -> 400 | Q51: =SUM(Q48:Q50) -> 0 | R51: =SUM(R48:R50) -> 400 | T51: =SUM(T48:T50) -> 400 | V51: =SUM(V48:V50) -> 400 | X51: =SUM(X48:X50) -> 400 | Z51: =SUM(Z48:Z50) -> 400 | AB51: =D51+F51+H51+J51+L51+N51+P51+R51+T51+V51+X51+Z51 -> 14040 | AD51: =D51+F51+H51+J51+L51+N51+P51 -> 12040 | AE51: =E51+G51+I51+K51+M51+O51+Q51 -> 2700
B52: 901-009-000-00 | C52: DESPENSA, ARTS. CAFETERIA | D52: 2032.11 | E52: 1348.06 | F52: 2032.11 | G52: 2525 | H52: 2032.11 | I52: 1769.82 | J52: 2032.11 | K52: 800.69 | L52: 2032.11 | M52: 2196.34 | N52: 2032.11 | O52: 1238.76 | P52: 2032.11 | Q52: 2484.47 | R52: 2032.11 | T52: 2032.11 | V52: 2032.11 | X52: 2032.11 | Z52: 2032.11 | AB52: =D52+F52+H52+J52+L52+N52+P52+R52+T52+V52+X52+Z52 -> 24385.32 | AD52: =D52+F52+H52+J52+L52+N52+P52 -> 14224.77 | AE52: =E52+G52+I52+K52+M52+O52+Q52 -> 12363.14
B53: 902-002-001-00 | C53: GASTOS PROMOCIONALES (ROLL UP, termos, libretas, plumas) | D53: 0 | E53: 0 | F53: 0 | G53: 0 | H53: 0 | I53: 0 | J53: 0 | K53: 0 | L53: 0 | M53: 0 | N53: 0 | O53: 0 | P53: 0 | Q53: 10220.69 | R53: 0 | T53: 0 | V53: 0 | X53: 0 | Z53: 0 | AB53: =D53+F53+H53+J53+L53+N53+P53+R53+T53+V53+X53+Z53 -> 0 | AD53: =D53+F53+H53+J53+L53+N53+P53 -> 0 | AE53: =E53+G53+I53+K53+M53+O53+Q53 -> 10220.69
B54: 901-013-000-00 | C54: SERVICIOS DE CONSULTORIA EN COMUNICACIÓN | D54: =15734.32*1.05 -> 16521.036 | E54: 15734.32 | F54: 16521.036 | G54: 15734.32 | H54: 16521.036 | I54: 15734.32 | J54: 16521.036 | K54: 15734.32 | L54: =15734.32*1.05 -> 16521.036 | M54: 15734.32 | N54: =15734.32*1.05 -> 16521.036 | O54: 15734.32 | P54: =15734.32*1.05 -> 16521.036 | Q54: 15734.32 | R54: =15734.32*1.05 -> 16521.036 | T54: =15734.32*1.05 -> 16521.036 | V54: =15734.32*1.05 -> 16521.036 | X54: =15734.32*1.05 -> 16521.036 | Z54: =15734.32*1.05 -> 16521.036 | AB54: =D54+F54+H54+J54+L54+N54+P54+R54+T54+V54+X54+Z54 -> 198252.43 | AD54: =D54+F54+H54+J54+L54+N54+P54 -> 115647.25 | AE54: =E54+G54+I54+K54+M54+O54+Q54 -> 110140.24
B55: 901-011-010-00 | C55: CONSUMOS REUNIONES | D55: 0 | E55: 0 | F55: 1000 | G55: 0 | H55: 0 | I55: 0 | J55: 1000 | K55: 0 | L55: 0 | M55: 0 | N55: 1000 | O55: 0 | P55: 0 | Q55: 0 | R55: 1000 | T55: 0 | V55: 1000 | X55: 0 | Z55: 0 | AB55: =D55+F55+H55+J55+L55+N55+P55+R55+T55+V55+X55+Z55 -> 5000 | AD55: =D55+F55+H55+J55+L55+N55+P55 -> 3000 | AE55: =E55+G55+I55+K55+M55+O55+Q55 -> 0
B56: 901-001-000-00 | C56: PAPELERIA Y ARTS OFICINA | D56: 0 | E56: 0 | F56: 1666.67 | G56: 0 | H56: 0 | I56: 2850 | J56: 1666.67 | K56: 850 | L56: 0 | M56: 5126.18 | N56: 1666.67 | O56: 4978.45 | P56: 0 | Q56: 2194.83 | R56: 1666.67 | T56: 0 | V56: 1666.67 | X56: 0 | Z56: 1666.65 | AB56: =D56+F56+H56+J56+L56+N56+P56+R56+T56+V56+X56+Z56 -> 10000 | AD56: =D56+F56+H56+J56+L56+N56+P56 -> 5000.01 | AE56: =E56+G56+I56+K56+M56+O56+Q56 -> 15999.46
B57: 902-001-000-00 | C57: PASAJES y ESTACIONAMIENTOS (KAM´S) | D57: 1000 | E57: 0 | F57: 0 | G57: 80 | H57: 1000 | I57: 156 | J57: 0 | K57: 142.23 | L57: 1000 | M57: 0 | N57: 0 | O57: 0 | P57: 1000 | Q57: 0 | R57: 0 | T57: 1000 | V57: 0 | X57: 1000 | Z57: 0 | AB57: =D57+F57+H57+J57+L57+N57+P57+R57+T57+V57+X57+Z57 -> 6000 | AD57: =D57+F57+H57+J57+L57+N57+P57 -> 4000 | AE57: =E57+G57+I57+K57+M57+O57+Q57 -> 378.23
B58: 901-004-000-00 | C58: PASAJES y ESTACIONAMIENTOS (AMCHAM) | D58: 0 | E58: 44 | F58: 0 | G58: 102.59 | H58: 0 | I58: 0 | J58: 0 | K58: 0 | L58: 0 | M58: 0 | N58: 0 | O58: 0 | P58: 0 | Q58: 0 | R58: 0 | T58: 0 | V58: 0 | X58: 0 | Z58: 0 | AB58: =D58+F58+H58+J58+L58+N58+P58+R58+T58+V58+X58+Z58 -> 0 | AD58: =D58+F58+H58+J58+L58+N58+P58 -> 0 | AE58: =E58+G58+I58+K58+M58+O58+Q58 -> 146.59
B59: 501-000-000-00 | C59: NOMINA GDL | D59: =470484.14+6218 -> 476702.14 | E59: 374295.29 | F59: 476702.14 | G59: 454221.51 | H59: 476702.14 | I59: 464140.67 | J59: 476702.14 | K59: 456208.07 | L59: =470484.14+6218 -> 476702.14 | M59: 683954.99 | N59: =470484.14+6218 -> 476702.14 | O59: 454501.14 | P59: =470484.14+6218 -> 476702.14 | Q59: 426396.96 | R59: =470484.14+6218 -> 476702.14 | T59: =470484.14+6218 -> 476702.14 | V59: =470484.14+6218 -> 476702.14 | X59: =470484.14+6218 -> 476702.14 | Z59: =470484.14+6218 -> 476702.14 | AB59: =D59+F59+H59+J59+L59+N59+P59+R59+T59+V59+X59+Z59 -> 5720425.7 | AD59: =D59+F59+H59+J59+L59+N59+P59 -> 3336915 | AE59: =E59+G59+I59+K59+M59+O59+Q59 -> 3313718.6
B60: 901-005-000-00 | C60: GASOLINA KAM´S | D60: =2000*3 -> 6000 | E60: 2000 | F60: 6000 | G60: 0 | H60: 6000 | I60: 2550 | J60: 6000 | K60: 3867 | L60: =2000*3 -> 6000 | M60: 7068 | N60: =2000*3 -> 6000 | O60: 6000 | P60: =2000*3 -> 6000 | Q60: 4000 | R60: =2000*3 -> 6000 | T60: =2000*3 -> 6000 | V60: =2000*3 -> 6000 | X60: =2000*3 -> 6000 | Z60: =2000*3 -> 6000 | AB60: =D60+F60+H60+J60+L60+N60+P60+R60+T60+V60+X60+Z60 -> 72000 | AD60: =D60+F60+H60+J60+L60+N60+P60 -> 42000 | AE60: =E60+G60+I60+K60+M60+O60+Q60 -> 25485
B61: 901-006-002-00 | C61: REEMBOLSO TELEFONO | D61: =800*6 -> 4800 | E61: 1239 | F61: 4800 | G61: 2188.83 | H61: 4800 | I61: 3195.16 | J61: 4800 | K61: 2394 | L61: =800*6 -> 4800 | M61: 2308 | N61: =800*6 -> 4800 | O61: 3303.54 | P61: =800*6 -> 4800 | Q61: 2794 | R61: =800*6 -> 4800 | T61: =800*6 -> 4800 | V61: =800*6 -> 4800 | X61: =800*6 -> 4800 | Z61: =800*6 -> 4800 | AB61: =D61+F61+H61+J61+L61+N61+P61+R61+T61+V61+X61+Z61 -> 57600 | AD61: =D61+F61+H61+J61+L61+N61+P61 -> 33600 | AE61: =E61+G61+I61+K61+M61+O61+Q61 -> 17422.53
B62: 901-011-008-00 | C62: HERRAMIENTAS TELE-TRABAJO | D62: =700*10 -> 7000 | E62: 5797 | F62: 7000 | G62: 6230 | H62: 7000 | I62: 6953.52 | J62: 7000 | K62: 5600 | L62: =700*10 -> 7000 | M62: 6673 | N62: =700*10 -> 7000 | O62: 6953.33 | P62: =700*10 -> 7000 | Q62: 6300 | R62: =700*10 -> 7000 | T62: =700*10 -> 7000 | V62: =700*10 -> 7000 | X62: =700*10 -> 7000 | Z62: =700*10 -> 7000 | AB62: =D62+F62+H62+J62+L62+N62+P62+R62+T62+V62+X62+Z62 -> 84000 | AD62: =D62+F62+H62+J62+L62+N62+P62 -> 49000 | AE62: =E62+G62+I62+K62+M62+O62+Q62 -> 44506.85
C63: Suma de Gastos Generales | D63: =SUM(D17:D22)+D25+D26+D32+D33+D36+SUM(D38:D40)+SUM(D44:D47)+SUM(D51:D55)+SUM(D56:D62) -> 610415.98 | E63: =SUM(E17:E22)+E25+E26+E32+E33+E36+SUM(E38:E40)+SUM(E44:E47)+SUM(E51:E55)+SUM(E56:E62) -> 452710.07 | F63: =SUM(F17:F22)+F25+F26+F32+F33+F36+SUM(F38:F40)+SUM(F44:F47)+SUM(F51:F55)+SUM(F56:F62) -> 651420.95 | G63: =SUM(G17:G22)+G25+G26+G32+G33+G36+SUM(G38:G40)+SUM(G44:G47)+SUM(G51:G55)+SUM(G56:G62) -> 530609.48 | H63: =SUM(H17:H22)+H25+H26+H32+H33+H36+SUM(H38:H40)+SUM(H44:H47)+SUM(H51:H55)+SUM(H56:H62) -> 682129.28 | I63: =SUM(I17:I22)+I25+I26+I32+I33+I36+SUM(I38:I40)+SUM(I44:I47)+SUM(I51:I55)+SUM(I56:I62) -> 584366.67 | J63: =SUM(J17:J22)+J25+J26+J32+J33+J36+SUM(J38:J40)+SUM(J44:J47)+SUM(J51:J55)+SUM(J56:J62) -> 683859.95 | K63: =SUM(K17:K22)+K25+K26+K32+K33+K36+SUM(K38:K40)+SUM(K44:K47)+SUM(K51:K55)+SUM(K56:K62) -> 574912.24 | ... R63: =SUM(R17:R22)+R25+R26+R32+R33+R36+SUM(R38:R40)+SUM(R44:R47)+SUM(R51:R55)+SUM(R56:R62) -> 573420.95 | T63: =SUM(T17:T22)+T25+T26+T32+T33+T36+SUM(T38:T40)+SUM(T44:T47)+SUM(T51:T55)+SUM(T56:T62) -> 584049.28 | V63: =SUM(V17:V22)+V25+V26+V32+V33+V36+SUM(V38:V40)+SUM(V44:V47)+SUM(V51:V55)+SUM(V56:V62) -> 593859.95 | X63: =SUM(X17:X22)+X25+X26+X32+X33+X36+SUM(X38:X40)+SUM(X44:X47)+SUM(X51:X55)+SUM(X56:X62) -> 604104.28 | Z63: =SUM(Z17:Z22)+Z25+Z26+Z32+Z33+Z36+SUM(Z38:Z40)+SUM(Z44:Z47)+SUM(Z51:Z55)+SUM(Z56:Z62) -> 590170.93 | AB63: =SUM(AB17:AB22)+AB25+AB26+AB32+AB33+AB36+SUM(AB38:AB40)+SUM(AB44:AB47)+SUM(AB51:AB55)+SUM(AB56:AB62) -> 7368260 | AD63: =SUM(AD17:AD22)+AD25+AD26+AD32+AD33+AD36+SUM(AD38:AD40)+SUM(AD44:AD47)+SUM(AD51:AD55)+SUM(AD56:AD62) -> 4422654.6 | AE63: =SUM(AE17:AE22)+AE25+AE26+AE32+AE33+AE36+SUM(AE38:AE40)+SUM(AE44:AE47)+SUM(AE51:AE55)+SUM(AE56:AE62) -> 4246583.6
C65: Depreciaciones y Amortizaciones
B66: 901-008-000-00 | C66: Depreciaciones de equipo | D66: =SUM(D67:D68) -> 6339.3557 | E66: 5563.34 | F66: 6339.3557 | G66: 5563.34 | H66: 6339.3557 | I66: 5563.34 | J66: 6339.3557 | K66: 5563.34 | L66: =SUM(L67:L68) -> 6339.3557 | M66: 5563.34 | N66: =SUM(N67:N68) -> 6339.3557 | O66: 5563.34 | P66: =SUM(P67:P68) -> 6339.3557 | Q66: 5563.34 | R66: =SUM(R67:R68) -> 6339.3557 | T66: =SUM(T67:T68) -> 6339.3557 | V66: =SUM(V67:V68) -> 6339.3557 | X66: =SUM(X67:X68) -> 6339.3557 | Z66: =SUM(Z67:Z68) -> 6339.3557 | AB66: =D66+F66+H66+J66+L66+N66+P66+R66+T66+V66+X66+Z66 -> 76072.268 | AD66: =D66+F66+H66+J66+L66+N66+P66 -> 44375.49 | AE66: =E66+G66+I66+K66+M66+O66+Q66 -> 38943.38
C67: Depreciación actual | D67: 5563.35 | F67: 5563.35 | H67: 5563.35 | J67: 5563.35 | L67: 5563.35 | N67: 5563.35 | P67: 5563.35 | R67: 5563.35 | T67: 5563.35 | V67: 5563.35 | X67: 5563.35 | Z67: 5563.35 | AB67: =D67+F67+H67+J67+L67+N67+P67+R67+T67+V67+X67+Z67 -> 66760.2 | AD67: =D67+F67+H67+J67+L67+N67+P67 -> 38943.45 | AE67: =E67+G67+I67+K67+M67+O67+Q67 -> 0
C68: 2 Equipos de Computo | D68: =(((14781.06*2)*1.05)*0.3)/12 -> 776.00565 | F68: =(((14781.06*2)*1.05)*0.3)/12 -> 776.00565 | H68: =(((14781.06*2)*1.05)*0.3)/12 -> 776.00565 | J68: =(((14781.06*2)*1.05)*0.3)/12 -> 776.00565 | L68: =(((14781.06*2)*1.05)*0.3)/12 -> 776.00565 | N68: =(((14781.06*2)*1.05)*0.3)/12 -> 776.00565 | P68: =(((14781.06*2)*1.05)*0.3)/12 -> 776.00565 | R68: =(((14781.06*2)*1.05)*0.3)/12 -> 776.00565 | T68: =(((14781.06*2)*1.05)*0.3)/12 -> 776.00565 | V68: =(((14781.06*2)*1.05)*0.3)/12 -> 776.00565 | X68: =(((14781.06*2)*1.05)*0.3)/12 -> 776.00565 | Z68: =(((14781.06*2)*1.05)*0.3)/12 -> 776.00565 | AB68: =D68+F68+H68+J68+L68+N68+P68+R68+T68+V68+X68+Z68 -> 9312.0678 | AD68: =D68+F68+H68+J68+L68+N68+P68 -> 5432.0395 | AE68: =E68+G68+I68+K68+M68+O68+Q68 -> 0
B69: 901-008-007-00 | C69: Amortizaciones | D69: 3317.6067 | E69: 3317.61 | F69: 3317.6067 | G69: 3317.61 | H69: 3317.6067 | I69: 3317.61 | J69: 3317.6067 | K69: 3317.61 | L69: 3317.6067 | M69: 3317.61 | N69: 3317.6067 | O69: 3317.61 | P69: 3317.6067 | Q69: 3317.61 | R69: 3317.6067 | T69: 3317.6067 | V69: 3317.6067 | X69: 3317.6067 | Z69: 3317.6067 | AB69: =D69+F69+H69+J69+L69+N69+P69+R69+T69+V69+X69+Z69 -> 39811.28 | AD69: =D69+F69+H69+J69+L69+N69+P69 -> 23223.247 | AE69: =E69+G69+I69+K69+M69+O69+Q69 -> 23223.27
C70: Suma Depreciaciones y Amortizaciones | D70: =D66+D69 -> 9656.9623 | E70: =E66+E69 -> 8880.95 | F70: =F66+F69 -> 9656.9623 | G70: =G66+G69 -> 8880.95 | H70: =H66+H69 -> 9656.9623 | I70: =I66+I69 -> 8880.95 | J70: =J66+J69 -> 9656.9623 | K70: =K66+K69 -> 8880.95 | ... R70: =R66+R69 -> 9656.9623 | T70: =T66+T69 -> 9656.9623 | V70: =V66+V69 -> 9656.9623 | X70: =X66+X69 -> 9656.9623 | Z70: =Z66+Z69 -> 9656.9623 | AB70: =AB66+AB69 -> 115883.55 | AD70: =AD66+AD69 -> 67598.736 | AE70: =AE66+AE69 -> 62166.65
B72: 903-000-000-00 | C72: Gastos Corporativos Gdl | D72: ='Gtos. Corporativos'!H26 -> 326722.3 | E72: ='Gtos. Corporativos (P)'!J26 -> 299581.1 | F72: =D72 -> 326722.3 | G72: ='Gtos. Corporativos (P)'!L26 -> 298143.42 | H72: =F72 -> 326722.3 | I72: ='Gtos. Corporativos (P)'!N26 -> 307809.7 | J72: =H72 -> 326722.3 | K72: ='Gtos. Corporativos (P)'!P26 -> 299807.92 | L72: =J72 -> 326722.3 | M72: 311622.35 | N72: =L72 -> 326722.3 | O72: 303994.33 | P72: =N72 -> 326722.3 | Q72: 305326.69 | R72: =P72 -> 326722.3 | T72: =R72 -> 326722.3 | V72: =T72 -> 326722.3 | X72: =V72 -> 326722.3 | Z72: =X72 -> 326722.3 | AB72: =D72+F72+H72+J72+L72+N72+P72+R72+T72+V72+X72+Z72 -> 3920667.6 | AD72: =D72+F72+H72+J72+L72+N72+P72 -> 2287056.1 | AE72: =E72+G72+I72+K72+M72+O72+Q72 -> 2126285.5
B74: 904-000-000-00 | C74: Member Centricity | D74: 0 | E74: 41606.6 | F74: 0 | G74: 17657.62 | H74: 0 | I74: 58913.76 | J74: 0 | K74: 34155.83 | L74: 0 | M74: 35336.78 | N74: 0 | O74: 59646.77 | P74: 0 | Q74: 100829.45 | R74: 0 | T74: 0 | V74: 0 | X74: 0 | Z74: 0 | AB74: =D74+F74+H74+J74+L74+N74+P74+R74+T74+V74+X74+Z74 -> 0 | AD74: =D74+F74+H74+J74+L74+N74+P74 -> 0 | AE74: =E74+G74+I74+K74+M74+O74+Q74 -> 348146.81
C76: Total GA Gdl | D76: =+D14-D63-D70-D72-D74 -> -950545.24 | E76: =+E14-E63-E70-E72-E74 -> -809143.81 | F76: =+F14-F63-F70-F72-F74 -> -991550.21 | G76: =+G14-G63-G70-G72-G74 -> -856713.67 | H76: =+H14-H63-H70-H72-H74 -> -1022258.5 | I76: =+I14-I63-I70-I72-I74 -> -961365.93 | J76: =+J14-J63-J70-J72-J74 -> -1023989.2 | K76: =+K14-K63-K70-K72-K74 -> -921590.63 | ... R76: =+R14-R63-R70-R72-R74 -> -913550.21 | T76: =+T14-T63-T70-T72-T74 -> -924178.54 | V76: =+V14-V63-V70-V72-V74 -> -933989.21 | X76: =+X14-X63-X70-X72-X74 -> -944233.54 | Z76: =+Z14-Z63-Z70-Z72-Z74 -> -930300.19 | AB76: =+AB14-AB63-AB70-AB72-AB74 -> -11449811 | AD76: =+AD14-AD63-AD70-AD72-AD74 -> -6803559.5 | AE76: =+AE14-AE63-AE70-AE72-AE74 -> -6809509.8
AB78: =DN!AB19+Comités!AB33+Eventos!AB68+#REF!+Dirección!AB29+'Gastos Generales'!AB76 -> #REF!
AB79: =AB78-RESUMEN!D37 -> #REF!
C81: Nota: Se pueden adicionar conceptos para los gastos generales, en caso de ser necesario.

Sheet PPvsREal
D2: Ppto. | E2: Real | F2: Ppto. | G2: Real | H2: Ppto. | I2: Real | J2: Ppto. | K2: Real | L2: Ppto. | M2: Real | N2: Ppto. | O2: Real | P2: Ppto. | Q2: Real | R2: Ppto. | S2: Real | T2: Ppto. | U2: Real | V2: Ppto. | W2: Real | X2: Ppto. | Y2: Real | Z2: Ppto. | AA2: Real
B3: Departamento | C3: Cta | D3: Ene | E3: Ene | F3: Feb | G3: Feb | H3: Mar | I3: Mar | J3: Abr | K3: Abr | L3: May | M3: May | N3: Jun | O3: Jun | P3: Jul | Q3: Jul | R3: Ago | S3: Ago | T3: Sep | U3: Sep | V3: Oct | W3: Oct | X3: Nov | Y3: Nov | Z3: Dic | AA3: Dic
B4: DN | C4: 400-000-000-00 | D4: =SUMIF(DN!$B:$B,PPvsREal!$C$4,DN!D:D) -> 686830.87 | E4: =SUMIF(DN!$B:$B,PPvsREal!$C$4,DN!E:E) -> 796918.16 | F4: =SUMIF(DN!$B:$B,PPvsREal!$C$4,DN!F:F) -> 703360.05 | G4: =SUMIF(DN!$B:$B,PPvsREal!$C$4,DN!G:G) -> 827529.92 | H4: =SUMIF(DN!$B:$B,PPvsREal!$C$4,DN!H:H) -> 734319.71 | I4: =SUMIF(DN!$B:$B,PPvsREal!$C$4,DN!I:I) -> 835486.43 | J4: =SUMIF(DN!$B:$B,PPvsREal!$C$4,DN!J:J) -> 755012.55 | K4: =SUMIF(DN!$B:$B,PPvsREal!$C$4,DN!K:K) -> 828972.86 | L4: =SUMIF(DN!$B:$B,PPvsREal!$C$4,DN!L:L) -> 771556.3 | M4: =SUMIF(DN!$B:$B,PPvsREal!$C$4,DN!M:M) -> 833351.22 | N4: =SUMIF(DN!$B:$B,PPvsREal!$C$4,DN!N:N) -> 790687.55 | O4: =SUMIF(DN!$B:$B,PPvsREal!$C$4,DN!O:O) -> 852797.11 | P4: =SUMIF(DN!$B:$B,PPvsREal!$C$4,DN!P:P) -> 821041.46 | Q4: =SUMIF(DN!$B:$B,PPvsREal!$C$4,DN!Q:Q) -> 838071.52 | R4: =SUMIF(DN!$B:$B,PPvsREal!$C$4,DN!R:R) -> 842496.92 | S4: =SUMIF(DN!$B:$B,PPvsREal!$C$4,DN!S:S) -> 0 | T4: =SUMIF(DN!$B:$B,PPvsREal!$C$4,DN!T:T) -> 880129.5 | U4: =SUMIF(DN!$B:$B,PPvsREal!$C$4,DN!U:U) -> 0 | V4: =SUMIF(DN!$B:$B,PPvsREal!$C$4,DN!V:V) -> 925545.42 | W4: =SUMIF(DN!$B:$B,PPvsREal!$C$4,DN!W:W) -> 0 | X4: =SUMIF(DN!$B:$B,PPvsREal!$C$4,DN!X:X) -> 1032212.1 | Y4: =SUMIF(DN!$B:$B,PPvsREal!$C$4,DN!Y:Y) -> 0 | Z4: =SUMIF(DN!$B:$B,PPvsREal!$C$4,DN!Z:Z) -> 1108896.7 | AA4: =SUMIF(DN!$B:$B,PPvsREal!$C$4,DN!AA:AA) -> 0
B5: DN | C5: 401-001-000-00 | D5: =SUMIF(DN!$B:$B,PPvsREal!$C$5,DN!D:D) -> 54000 | E5: =SUMIF(DN!$B:$B,PPvsREal!$C$5,DN!E:E) -> 37200 | F5: =SUMIF(DN!$B:$B,PPvsREal!$C$5,DN!F:F) -> 65000 | G5: =SUMIF(DN!$B:$B,PPvsREal!$C$5,DN!G:G) -> 65500 | H5: =SUMIF(DN!$B:$B,PPvsREal!$C$5,DN!H:H) -> 72500 | I5: =SUMIF(DN!$B:$B,PPvsREal!$C$5,DN!I:I) -> 22500 | J5: =SUMIF(DN!$B:$B,PPvsREal!$C$5,DN!J:J) -> 82000 | K5: =SUMIF(DN!$B:$B,PPvsREal!$C$5,DN!K:K) -> 24500 | L5: =SUMIF(DN!$B:$B,PPvsREal!$C$5,DN!L:L) -> 89500 | M5: =SUMIF(DN!$B:$B,PPvsREal!$C$5,DN!M:M) -> 0 | N5: =SUMIF(DN!$B:$B,PPvsREal!$C$5,DN!N:N) -> 65000 | O5: =SUMIF(DN!$B:$B,PPvsREal!$C$5,DN!O:O) -> 29500 | P5: =SUMIF(DN!$B:$B,PPvsREal!$C$5,DN!P:P) -> 78500 | Q5: =SUMIF(DN!$B:$B,PPvsREal!$C$5,DN!Q:Q) -> 29500 | R5: =SUMIF(DN!$B:$B,PPvsREal!$C$5,DN!R:R) -> 100500 | S5: =SUMIF(DN!$B:$B,PPvsREal!$C$5,DN!S:S) -> 0 | T5: =SUMIF(DN!$B:$B,PPvsREal!$C$5,DN!T:T) -> 54000 | U5: =SUMIF(DN!$B:$B,PPvsREal!$C$5,DN!U:U) -> 0 | V5: =SUMIF(DN!$B:$B,PPvsREal!$C$5,DN!V:V) -> 60000 | W5: =SUMIF(DN!$B:$B,PPvsREal!$C$5,DN!W:W) -> 0 | X5: =SUMIF(DN!$B:$B,PPvsREal!$C$5,DN!X:X) -> 71000 | Y5: =SUMIF(DN!$B:$B,PPvsREal!$C$5,DN!Y:Y) -> 0 | Z5: =SUMIF(DN!$B:$B,PPvsREal!$C$5,DN!Z:Z) -> 65000 | AA5: =SUMIF(DN!$B:$B,PPvsREal!$C$5,DN!AA:AA) -> 0
B6: DN | C6: 902-002-000-00 | D6: =SUMIF(DN!$B:$B,PPvsREal!$C$6,DN!D:D) -> 0 | E6: =SUMIF(DN!$B:$B,PPvsREal!$C$6,DN!E:E) -> 0 | F6: =SUMIF(DN!$B:$B,PPvsREal!$C$6,DN!F:F) -> 0 | G6: =SUMIF(DN!$B:$B,PPvsREal!$C$6,DN!G:G) -> 0 | H6: =SUMIF(DN!$B:$B,PPvsREal!$C$6,DN!H:H) -> 0 | I6: =SUMIF(DN!$B:$B,PPvsREal!$C$6,DN!I:I) -> 0 | J6: =SUMIF(DN!$B:$B,PPvsREal!$C$6,DN!J:J) -> 0 | K6: =SUMIF(DN!$B:$B,PPvsREal!$C$6,DN!K:K) -> 0 | L6: =SUMIF(DN!$B:$B,PPvsREal!$C$6,DN!L:L) -> 0 | M6: =SUMIF(DN!$B:$B,PPvsREal!$C$6,DN!M:M) -> 0 | N6: =SUMIF(DN!$B:$B,PPvsREal!$C$6,DN!N:N) -> 0 | O6: =SUMIF(DN!$B:$B,PPvsREal!$C$6,DN!O:O) -> 0 | P6: =SUMIF(DN!$B:$B,PPvsREal!$C$6,DN!P:P) -> 0 | Q6: =SUMIF(DN!$B:$B,PPvsREal!$C$6,DN!Q:Q) -> 0 | R6: =SUMIF(DN!$B:$B,PPvsREal!$C$6,DN!R:R) -> 0 | S6: =SUMIF(DN!$B:$B,PPvsREal!$C$6,DN!S:S) -> 0 | T6: =SUMIF(DN!$B:$B,PPvsREal!$C$6,DN!T:T) -> 0 | U6: =SUMIF(DN!$B:$B,PPvsREal!$C$6,DN!U:U) -> 0 | V6: =SUMIF(DN!$B:$B,PPvsREal!$C$6,DN!V:V) -> 0 | W6: =SUMIF(DN!$B:$B,PPvsREal!$C$6,DN!W:W) -> 0 | X6: =SUMIF(DN!$B:$B,PPvsREal!$C$6,DN!X:X) -> 0 | Y6: =SUMIF(DN!$B:$B,PPvsREal!$C$6,DN!Y:Y) -> 0 | Z6: =SUMIF(DN!$B:$B,PPvsREal!$C$6,DN!Z:Z) -> 0 | AA6: =SUMIF(DN!$B:$B,PPvsREal!$C$6,DN!AA:AA) -> 0
B7: DN | C7: 501-001-009-00 | D7: =SUMIF(DN!$B:$B,PPvsREal!$C$7,DN!D:D) -> 46322.55 | E7: =SUMIF(DN!$B:$B,PPvsREal!$C$7,DN!E:E) -> 3000 | F7: =SUMIF(DN!$B:$B,PPvsREal!$C$7,DN!F:F) -> 46322.55 | G7: =SUMIF(DN!$B:$B,PPvsREal!$C$7,DN!G:G) -> 66863 | H7: =SUMIF(DN!$B:$B,PPvsREal!$C$7,DN!H:H) -> 46322.55 | I7: =SUMIF(DN!$B:$B,PPvsREal!$C$7,DN!I:I) -> 41841 | J7: =SUMIF(DN!$B:$B,PPvsREal!$C$7,DN!J:J) -> 46322.55 | K7: =SUMIF(DN!$B:$B,PPvsREal!$C$7,DN!K:K) -> 13745 | L7: =SUMIF(DN!$B:$B,PPvsREal!$C$7,DN!L:L) -> 46322.55 | M7: =SUMIF(DN!$B:$B,PPvsREal!$C$7,DN!M:M) -> 36975 | N7: =SUMIF(DN!$B:$B,PPvsREal!$C$7,DN!N:N) -> 46322.55 | O7: =SUMIF(DN!$B:$B,PPvsREal!$C$7,DN!O:O) -> 5400 | P7: =SUMIF(DN!$B:$B,PPvsREal!$C$7,DN!P:P) -> 46322.55 | Q7: =SUMIF(DN!$B:$B,PPvsREal!$C$7,DN!Q:Q) -> 85650 | R7: =SUMIF(DN!$B:$B,PPvsREal!$C$7,DN!R:R) -> 46322.55 | S7: =SUMIF(DN!$B:$B,PPvsREal!$C$7,DN!S:S) -> 0 | T7: =SUMIF(DN!$B:$B,PPvsREal!$C$7,DN!T:T) -> 46322.55 | U7: =SUMIF(DN!$B:$B,PPvsREal!$C$7,DN!U:U) -> 0 | V7: =SUMIF(DN!$B:$B,PPvsREal!$C$7,DN!V:V) -> 46322.55 | W7: =SUMIF(DN!$B:$B,PPvsREal!$C$7,DN!W:W) -> 0 | X7: =SUMIF(DN!$B:$B,PPvsREal!$C$7,DN!X:X) -> 46322.55 | Y7: =SUMIF(DN!$B:$B,PPvsREal!$C$7,DN!Y:Y) -> 0 | Z7: =SUMIF(DN!$B:$B,PPvsREal!$C$7,DN!Z:Z) -> 46322.55 | AA7: =SUMIF(DN!$B:$B,PPvsREal!$C$7,DN!AA:AA) -> 0
B8: DN | C8: 702-001-000-00 | D8: =SUMIF(DN!$B:$B,PPvsREal!$C$8,DN!D:D) -> 20000 | E8: =SUMIF(DN!$B:$B,PPvsREal!$C$8,DN!E:E) -> 1563.21 | F8: =SUMIF(DN!$B:$B,PPvsREal!$C$8,DN!F:F) -> 0 | G8: =SUMIF(DN!$B:$B,PPvsREal!$C$8,DN!G:G) -> 1815.06 | H8: =SUMIF(DN!$B:$B,PPvsREal!$C$8,DN!H:H) -> 20000 | I8: =SUMIF(DN!$B:$B,PPvsREal!$C$8,DN!I:I) -> 0 | J8: =SUMIF(DN!$B:$B,PPvsREal!$C$8,DN!J:J) -> 0 | K8: =SUMIF(DN!$B:$B,PPvsREal!$C$8,DN!K:K) -> 811.35 | L8: =SUMIF(DN!$B:$B,PPvsREal!$C$8,DN!L:L) -> 20000 | M8: =SUMIF(DN!$B:$B,PPvsREal!$C$8,DN!M:M) -> 0 | N8: =SUMIF(DN!$B:$B,PPvsREal!$C$8,DN!N:N) -> 0 | O8: =SUMIF(DN!$B:$B,PPvsREal!$C$8,DN!O:O) -> 3904.95 | P8: =SUMIF(DN!$B:$B,PPvsREal!$C$8,DN!P:P) -> 20000 | Q8: =SUMIF(DN!$B:$B,PPvsREal!$C$8,DN!Q:Q) -> 0 | R8: =SUMIF(DN!$B:$B,PPvsREal!$C$8,DN!R:R) -> 0 | S8: =SUMIF(DN!$B:$B,PPvsREal!$C$8,DN!S:S) -> 0 | T8: =SUMIF(DN!$B:$B,PPvsREal!$C$8,DN!T:T) -> 20000 | U8: =SUMIF(DN!$B:$B,PPvsREal!$C$8,DN!U:U) -> 0 | V8: =SUMIF(DN!$B:$B,PPvsREal!$C$8,DN!V:V) -> 0 | W8: =SUMIF(DN!$B:$B,PPvsREal!$C$8,DN!W:W) -> 0 | X8: =SUMIF(DN!$B:$B,PPvsREal!$C$8,DN!X:X) -> 20000 | Y8: =SUMIF(DN!$B:$B,PPvsREal!$C$8,DN!Y:Y) -> 0 | Z8: =SUMIF(DN!$B:$B,PPvsREal!$C$8,DN!Z:Z) -> 0 | AA8: =SUMIF(DN!$B:$B,PPvsREal!$C$8,DN!AA:AA) -> 0
B9: Comités | C9: 404-017-000-00 | D9: =SUMIF(Comités!$B:$B,PPvsREal!$C$9,Comités!D:D) -> 0 | E9: =SUMIF(Comités!$B:$B,PPvsREal!$C$9,Comités!E:E) -> 0 | F9: =SUMIF(Comités!$B:$B,PPvsREal!$C$9,Comités!F:F) -> 8400 | G9: =SUMIF(Comités!$B:$B,PPvsREal!$C$9,Comités!G:G) -> 0 | H9: =SUMIF(Comités!$B:$B,PPvsREal!$C$9,Comités!H:H) -> 0 | I9: =SUMIF(Comités!$B:$B,PPvsREal!$C$9,Comités!I:I) -> 0 | J9: =SUMIF(Comités!$B:$B,PPvsREal!$C$9,Comités!J:J) -> 8400 | K9: =SUMIF(Comités!$B:$B,PPvsREal!$C$9,Comités!K:K) -> 0 | L9: =SUMIF(Comités!$B:$B,PPvsREal!$C$9,Comités!L:L) -> 0 | M9: =SUMIF(Comités!$B:$B,PPvsREal!$C$9,Comités!M:M) -> 0 | N9: =SUMIF(Comités!$B:$B,PPvsREal!$C$9,Comités!N:N) -> 8400 | O9: =SUMIF(Comités!$B:$B,PPvsREal!$C$9,Comités!O:O) -> 1120.7 | P9: =SUMIF(Comités!$B:$B,PPvsREal!$C$9,Comités!P:P) -> 0 | Q9: =SUMIF(Comités!$B:$B,PPvsREal!$C$9,Comités!Q:Q) -> 9525.95 | R9: =SUMIF(Comités!$B:$B,PPvsREal!$C$9,Comités!R:R) -> 8400 | S9: =SUMIF(Comités!$B:$B,PPvsREal!$C$9,Comités!S:S) -> 0 | T9: =SUMIF(Comités!$B:$B,PPvsREal!$C$9,Comités!T:T) -> 0 | U9: =SUMIF(Comités!$B:$B,PPvsREal!$C$9,Comités!U:U) -> 0 | V9: =SUMIF(Comités!$B:$B,PPvsREal!$C$9,Comités!V:V) -> 8400 | W9: =SUMIF(Comités!$B:$B,PPvsREal!$C$9,Comités!W:W) -> 0 | X9: =SUMIF(Comités!$B:$B,PPvsREal!$C$9,Comités!X:X) -> 0 | Y9: =SUMIF(Comités!$B:$B,PPvsREal!$C$9,Comités!Y:Y) -> 0 | Z9: =SUMIF(Comités!$B:$B,PPvsREal!$C$9,Comités!Z:Z) -> 8400 | AA9: =SUMIF(Comités!$B:$B,PPvsREal!$C$9,Comités!AA:AA) -> 0
B10: Comités | C10: 404-005-000-00 | D10: =SUMIF(Comités!$B:$B,PPvsREal!$C$10,Comités!D:D) -> 11200 | E10: =SUMIF(Comités!$B:$B,PPvsREal!$C$10,Comités!E:E) -> 0 | F10: =SUMIF(Comités!$B:$B,PPvsREal!$C$10,Comités!F:F) -> 11200 | G10: =SUMIF(Comités!$B:$B,PPvsREal!$C$10,Comités!G:G) -> 0 | H10: =SUMIF(Comités!$B:$B,PPvsREal!$C$10,Comités!H:H) -> 11200 | I10: =SUMIF(Comités!$B:$B,PPvsREal!$C$10,Comités!I:I) -> 0 | J10: =SUMIF(Comités!$B:$B,PPvsREal!$C$10,Comités!J:J) -> 11200 | K10: =SUMIF(Comités!$B:$B,PPvsREal!$C$10,Comités!K:K) -> 0 | L10: =SUMIF(Comités!$B:$B,PPvsREal!$C$10,Comités!L:L) -> 11200 | M10: =SUMIF(Comités!$B:$B,PPvsREal!$C$10,Comités!M:M) -> 12006.98 | N10: =SUMIF(Comités!$B:$B,PPvsREal!$C$10,Comités!N:N) -> 11200 | O10: =SUMIF(Comités!$B:$B,PPvsREal!$C$10,Comités!O:O) -> 1120.7 | P10: =SUMIF(Comités!$B:$B,PPvsREal!$C$10,Comités!P:P) -> 11200 | Q10: =SUMIF(Comités!$B:$B,PPvsREal!$C$10,Comités!Q:Q) -> 0 | R10: =SUMIF(Comités!$B:$B,PPvsREal!$C$10,Comités!R:R) -> 11200 | S10: =SUMIF(Comités!$B:$B,PPvsREal!$C$10,Comités!S:S) -> 0 | T10: =SUMIF(Comités!$B:$B,PPvsREal!$C$10,Comités!T:T) -> 11200 | U10: =SUMIF(Comités!$B:$B,PPvsREal!$C$10,Comités!U:U) -> 0 | V10: =SUMIF(Comités!$B:$B,PPvsREal!$C$10,Comités!V:V) -> 11200 | W10: =SUMIF(Comités!$B:$B,PPvsREal!$C$10,Comités!W:W) -> 0 | X10: =SUMIF(Comités!$B:$B,PPvsREal!$C$10,Comités!X:X) -> 11200 | Y10: =SUMIF(Comités!$B:$B,PPvsREal!$C$10,Comités!Y:Y) -> 0 | Z10: =SUMIF(Comités!$B:$B,PPvsREal!$C$10,Comités!Z:Z) -> 11200 | AA10: =SUMIF(Comités!$B:$B,PPvsREal!$C$10,Comités!AA:AA) -> 0
B11: Comités | C11: 404-001-000-00 | D11: =SUMIF(Comités!$B:$B,PPvsREal!$C$11,Comités!D:D) -> 19600 | E11: =SUMIF(Comités!$B:$B,PPvsREal!$C$11,Comités!E:E) -> 0 | F11: =SUMIF(Comités!$B:$B,PPvsREal!$C$11,Comités!F:F) -> 19600 | G11: =SUMIF(Comités!$B:$B,PPvsREal!$C$11,Comités!G:G) -> 0 | H11: =SUMIF(Comités!$B:$B,PPvsREal!$C$11,Comités!H:H) -> 19600 | I11: =SUMIF(Comités!$B:$B,PPvsREal!$C$11,Comités!I:I) -> 0 | J11: =SUMIF(Comités!$B:$B,PPvsREal!$C$11,Comités!J:J) -> 19600 | K11: =SUMIF(Comités!$B:$B,PPvsREal!$C$11,Comités!K:K) -> 0 | L11: =SUMIF(Comités!$B:$B,PPvsREal!$C$11,Comités!L:L) -> 19600 | M11: =SUMIF(Comités!$B:$B,PPvsREal!$C$11,Comités!M:M) -> 5603.5 | N11: =SUMIF(Comités!$B:$B,PPvsREal!$C$11,Comités!N:N) -> 19600 | O11: =SUMIF(Comités!$B:$B,PPvsREal!$C$11,Comités!O:O) -> 12327.7 | P11: =SUMIF(Comités!$B:$B,PPvsREal!$C$11,Comités!P:P) -> 19600 | Q11: =SUMIF(Comités!$B:$B,PPvsREal!$C$11,Comités!Q:Q) -> 3922.45 | R11: =SUMIF(Comités!$B:$B,PPvsREal!$C$11,Comités!R:R) -> 19600 | S11: =SUMIF(Comités!$B:$B,PPvsREal!$C$11,Comités!S:S) -> 0 | T11: =SUMIF(Comités!$B:$B,PPvsREal!$C$11,Comités!T:T) -> 19600 | U11: =SUMIF(Comités!$B:$B,PPvsREal!$C$11,Comités!U:U) -> 0 | V11: =SUMIF(Comités!$B:$B,PPvsREal!$C$11,Comités!V:V) -> 19600 | W11: =SUMIF(Comités!$B:$B,PPvsREal!$C$11,Comités!W:W) -> 0 | X11: =SUMIF(Comités!$B:$B,PPvsREal!$C$11,Comités!X:X) -> 19600 | Y11: =SUMIF(Comités!$B:$B,PPvsREal!$C$11,Comités!Y:Y) -> 0 | Z11: =SUMIF(Comités!$B:$B,PPvsREal!$C$11,Comités!Z:Z) -> 19600 | AA11: =SUMIF(Comités!$B:$B,PPvsREal!$C$11,Comités!AA:AA) -> 0
B12: Comités | C12: 404-003-000-00 | D12: =SUMIF(Comités!$B:$B,PPvsREal!$C$12,Comités!D:D) -> 8400 | E12: =SUMIF(Comités!$B:$B,PPvsREal!$C$12,Comités!E:E) -> 0 | F12: =SUMIF(Comités!$B:$B,PPvsREal!$C$12,Comités!F:F) -> 8400 | G12: =SUMIF(Comités!$B:$B,PPvsREal!$C$12,Comités!G:G) -> 0 | H12: =SUMIF(Comités!$B:$B,PPvsREal!$C$12,Comités!H:H) -> 8400 | I12: =SUMIF(Comités!$B:$B,PPvsREal!$C$12,Comités!I:I) -> 0 | J12: =SUMIF(Comités!$B:$B,PPvsREal!$C$12,Comités!J:J) -> 8400 | K12: =SUMIF(Comités!$B:$B,PPvsREal!$C$12,Comités!K:K) -> 0 | L12: =SUMIF(Comités!$B:$B,PPvsREal!$C$12,Comités!L:L) -> 8400 | M12: =SUMIF(Comités!$B:$B,PPvsREal!$C$12,Comités!M:M) -> 6724.2 | N12: =SUMIF(Comités!$B:$B,PPvsREal!$C$12,Comités!N:N) -> 8400 | O12: =SUMIF(Comités!$B:$B,PPvsREal!$C$12,Comités!O:O) -> 1120.7 | P12: =SUMIF(Comités!$B:$B,PPvsREal!$C$12,Comités!P:P) -> 8400 | Q12: =SUMIF(Comités!$B:$B,PPvsREal!$C$12,Comités!Q:Q) -> 2241.4 | R12: =SUMIF(Comités!$B:$B,PPvsREal!$C$12,Comités!R:R) -> 8400 | S12: =SUMIF(Comités!$B:$B,PPvsREal!$C$12,Comités!S:S) -> 0 | T12: =SUMIF(Comités!$B:$B,PPvsREal!$C$12,Comités!T:T) -> 8400 | U12: =SUMIF(Comités!$B:$B,PPvsREal!$C$12,Comités!U:U) -> 0 | V12: =SUMIF(Comités!$B:$B,PPvsREal!$C$12,Comités!V:V) -> 8400 | W12: =SUMIF(Comités!$B:$B,PPvsREal!$C$12,Comités!W:W) -> 0 | X12: =SUMIF(Comités!$B:$B,PPvsREal!$C$12,Comités!X:X) -> 8400 | Y12: =SUMIF(Comités!$B:$B,PPvsREal!$C$12,Comités!Y:Y) -> 0 | Z12: =SUMIF(Comités!$B:$B,PPvsREal!$C$12,Comités!Z:Z) -> 8400 | AA12: =SUMIF(Comités!$B:$B,PPvsREal!$C$12,Comités!AA:AA) -> 0
B13: Comités | C13: 404-013-000-00 | D13: =SUMIF(Comités!$B:$B,PPvsREal!$C$13,Comités!D:D) -> 0 | E13: =SUMIF(Comités!$B:$B,PPvsREal!$C$13,Comités!E:E) -> 0 | F13: =SUMIF(Comités!$B:$B,PPvsREal!$C$13,Comités!F:F) -> 0 | G13: =SUMIF(Comités!$B:$B,PPvsREal!$C$13,Comités!G:G) -> 0 | H13: =SUMIF(Comités!$B:$B,PPvsREal!$C$13,Comités!H:H) -> 0 | I13: =SUMIF(Comités!$B:$B,PPvsREal!$C$13,Comités!I:I) -> 0 | J13: =SUMIF(Comités!$B:$B,PPvsREal!$C$13,Comités!J:J) -> 0 | K13: =SUMIF(Comités!$B:$B,PPvsREal!$C$13,Comités!K:K) -> 0 | L13: =SUMIF(Comités!$B:$B,PPvsREal!$C$13,Comités!L:L) -> 0 | M13: =SUMIF(Comités!$B:$B,PPvsREal!$C$13,Comités!M:M) -> 2094.33 | N13: =SUMIF(Comités!$B:$B,PPvsREal!$C$13,Comités!N:N) -> 0 | O13: =SUMIF(Comités!$B:$B,PPvsREal!$C$13,Comités!O:O) -> 0 | P13: =SUMIF(Comités!$B:$B,PPvsREal!$C$13,Comités!P:P) -> 0 | Q13: =SUMIF(Comités!$B:$B,PPvsREal!$C$13,Comités!Q:Q) -> 0 | R13: =SUMIF(Comités!$B:$B,PPvsREal!$C$13,Comités!R:R) -> 0 | S13: =SUMIF(Comités!$B:$B,PPvsREal!$C$13,Comités!S:S) -> 0 | T13: =SUMIF(Comités!$B:$B,PPvsREal!$C$13,Comités!T:T) -> 0 | U13: =SUMIF(Comités!$B:$B,PPvsREal!$C$13,Comités!U:U) -> 0 | V13: =SUMIF(Comités!$B:$B,PPvsREal!$C$13,Comités!V:V) -> 0 | W13: =SUMIF(Comités!$B:$B,PPvsREal!$C$13,Comités!W:W) -> 0 | X13: =SUMIF(Comités!$B:$B,PPvsREal!$C$13,Comités!X:X) -> 0 | Y13: =SUMIF(Comités!$B:$B,PPvsREal!$C$13,Comités!Y:Y) -> 0 | Z13: =SUMIF(Comités!$B:$B,PPvsREal!$C$13,Comités!Z:Z) -> 0 | AA13: =SUMIF(Comités!$B:$B,PPvsREal!$C$13,Comités!AA:AA) -> 0
B14: Comités | C14: 404-007-000-00 | D14: =SUMIF(Comités!$B:$B,PPvsREal!$C$14,Comités!D:D) -> 11200 | E14: =SUMIF(Comités!$B:$B,PPvsREal!$C$14,Comités!E:E) -> 0 | F14: =SUMIF(Comités!$B:$B,PPvsREal!$C$14,Comités!F:F) -> 11200 | G14: =SUMIF(Comités!$B:$B,PPvsREal!$C$14,Comités!G:G) -> 0 | H14: =SUMIF(Comités!$B:$B,PPvsREal!$C$14,Comités!H:H) -> 11200 | I14: =SUMIF(Comités!$B:$B,PPvsREal!$C$14,Comités!I:I) -> 0 | J14: =SUMIF(Comités!$B:$B,PPvsREal!$C$14,Comités!J:J) -> 11200 | K14: =SUMIF(Comités!$B:$B,PPvsREal!$C$14,Comités!K:K) -> 0 | L14: =SUMIF(Comités!$B:$B,PPvsREal!$C$14,Comités!L:L) -> 11200 | M14: =SUMIF(Comités!$B:$B,PPvsREal!$C$14,Comités!M:M) -> 0 | N14: =SUMIF(Comités!$B:$B,PPvsREal!$C$14,Comités!N:N) -> 11200 | O14: =SUMIF(Comités!$B:$B,PPvsREal!$C$14,Comités!O:O) -> 0 | P14: =SUMIF(Comités!$B:$B,PPvsREal!$C$14,Comités!P:P) -> 11200 | Q14: =SUMIF(Comités!$B:$B,PPvsREal!$C$14,Comités!Q:Q) -> 0 | R14: =SUMIF(Comités!$B:$B,PPvsREal!$C$14,Comités!R:R) -> 11200 | S14: =SUMIF(Comités!$B:$B,PPvsREal!$C$14,Comités!S:S) -> 0 | T14: =SUMIF(Comités!$B:$B,PPvsREal!$C$14,Comités!T:T) -> 11200 | U14: =SUMIF(Comités!$B:$B,PPvsREal!$C$14,Comités!U:U) -> 0 | V14: =SUMIF(Comités!$B:$B,PPvsREal!$C$14,Comités!V:V) -> 11200 | W14: =SUMIF(Comités!$B:$B,PPvsREal!$C$14,Comités!W:W) -> 0 | X14: =SUMIF(Comités!$B:$B,PPvsREal!$C$14,Comités!X:X) -> 11200 | Y14: =SUMIF(Comités!$B:$B,PPvsREal!$C$14,Comités!Y:Y) -> 0 | Z14: =SUMIF(Comités!$B:$B,PPvsREal!$C$14,Comités!Z:Z) -> 11200 | AA14: =SUMIF(Comités!$B:$B,PPvsREal!$C$14,Comités!AA:AA) -> 0
B15: Comités | C15: 404-016-000-00 | D15: =SUMIF(Comités!$B:$B,PPvsREal!$C$15,Comités!D:D) -> 0 | E15: =SUMIF(Comités!$B:$B,PPvsREal!$C$15,Comités!E:E) -> 0 | F15: =SUMIF(Comités!$B:$B,PPvsREal!$C$15,Comités!F:F) -> 0 | G15: =SUMIF(Comités!$B:$B,PPvsREal!$C$15,Comités!G:G) -> 0 | H15: =SUMIF(Comités!$B:$B,PPvsREal!$C$15,Comités!H:H) -> 0 | I15: =SUMIF(Comités!$B:$B,PPvsREal!$C$15,Comités!I:I) -> 0 | J15: =SUMIF(Comités!$B:$B,PPvsREal!$C$15,Comités!J:J) -> 0 | K15: =SUMIF(Comités!$B:$B,PPvsREal!$C$15,Comités!K:K) -> 0 | L15: =SUMIF(Comités!$B:$B,PPvsREal!$C$15,Comités!L:L) -> 0 | M15: =SUMIF(Comités!$B:$B,PPvsREal!$C$15,Comités!M:M) -> 0 | N15: =SUMIF(Comités!$B:$B,PPvsREal!$C$15,Comités!N:N) -> 0 | O15: =SUMIF(Comités!$B:$B,PPvsREal!$C$15,Comités!O:O) -> 0 | P15: =SUMIF(Comités!$B:$B,PPvsREal!$C$15,Comités!P:P) -> 0 | Q15: =SUMIF(Comités!$B:$B,PPvsREal!$C$15,Comités!Q:Q) -> 0 | R15: =SUMIF(Comités!$B:$B,PPvsREal!$C$15,Comités!R:R) -> 0 | S15: =SUMIF(Comités!$B:$B,PPvsREal!$C$15,Comités!S:S) -> 0 | T15: =SUMIF(Comités!$B:$B,PPvsREal!$C$15,Comités!T:T) -> 0 | U15: =SUMIF(Comités!$B:$B,PPvsREal!$C$15,Comités!U:U) -> 0 | V15: =SUMIF(Comités!$B:$B,PPvsREal!$C$15,Comités!V:V) -> 0 | W15: =SUMIF(Comités!$B:$B,PPvsREal!$C$15,Comités!W:W) -> 0 | X15: =SUMIF(Comités!$B:$B,PPvsREal!$C$15,Comités!X:X) -> 0 | Y15: =SUMIF(Comités!$B:$B,PPvsREal!$C$15,Comités!Y:Y) -> 0 | Z15: =SUMIF(Comités!$B:$B,PPvsREal!$C$15,Comités!Z:Z) -> 0 | AA15: =SUMIF(Comités!$B:$B,PPvsREal!$C$15,Comités!AA:AA) -> 0
B16: Comités | C16: 404-004-000-00 | D16: =SUMIF(Comités!$B:$B,PPvsREal!$C$16,Comités!D:D) -> 8400 | E16: =SUMIF(Comités!$B:$B,PPvsREal!$C$16,Comités!E:E) -> 0 | F16: =SUMIF(Comités!$B:$B,PPvsREal!$C$16,Comités!F:F) -> 8400 | G16: =SUMIF(Comités!$B:$B,PPvsREal!$C$16,Comités!G:G) -> 0 | H16: =SUMIF(Comités!$B:$B,PPvsREal!$C$16,Comités!H:H) -> 8400 | I16: =SUMIF(Comités!$B:$B,PPvsREal!$C$16,Comités!I:I) -> 0 | J16: =SUMIF(Comités!$B:$B,PPvsREal!$C$16,Comités!J:J) -> 8400 | K16: =SUMIF(Comités!$B:$B,PPvsREal!$C$16,Comités!K:K) -> 0 | L16: =SUMIF(Comités!$B:$B,PPvsREal!$C$16,Comités!L:L) -> 8400 | M16: =SUMIF(Comités!$B:$B,PPvsREal!$C$16,Comités!M:M) -> 0 | N16: =SUMIF(Comités!$B:$B,PPvsREal!$C$16,Comités!N:N) -> 8400 | O16: =SUMIF(Comités!$B:$B,PPvsREal!$C$16,Comités!O:O) -> 0 | P16: =SUMIF(Comités!$B:$B,PPvsREal!$C$16,Comités!P:P) -> 8400 | Q16: =SUMIF(Comités!$B:$B,PPvsREal!$C$16,Comités!Q:Q) -> 0 | R16: =SUMIF(Comités!$B:$B,PPvsREal!$C$16,Comités!R:R) -> 8400 | S16: =SUMIF(Comités!$B:$B,PPvsREal!$C$16,Comités!S:S) -> 0 | T16: =SUMIF(Comités!$B:$B,PPvsREal!$C$16,Comités!T:T) -> 8400 | U16: =SUMIF(Comités!$B:$B,PPvsREal!$C$16,Comités!U:U) -> 0 | V16: =SUMIF(Comités!$B:$B,PPvsREal!$C$16,Comités!V:V) -> 8400 | W16: =SUMIF(Comités!$B:$B,PPvsREal!$C$16,Comités!W:W) -> 0 | X16: =SUMIF(Comités!$B:$B,PPvsREal!$C$16,Comités!X:X) -> 8400 | Y16: =SUMIF(Comités!$B:$B,PPvsREal!$C$16,Comités!Y:Y) -> 0 | Z16: =SUMIF(Comités!$B:$B,PPvsREal!$C$16,Comités!Z:Z) -> 8400 | AA16: =SUMIF(Comités!$B:$B,PPvsREal!$C$16,Comités!AA:AA) -> 0
B17: Comités | C17: 404-009-000-00 | D17: =SUMIF(Comités!$B:$B,PPvsREal!$C$17,Comités!D:D) -> 0 | E17: =SUMIF(Comités!$B:$B,PPvsREal!$C$17,Comités!E:E) -> 0 | F17: =SUMIF(Comités!$B:$B,PPvsREal!$C$17,Comités!F:F) -> 0 | G17: =SUMIF(Comités!$B:$B,PPvsREal!$C$17,Comités!G:G) -> 0 | H17: =SUMIF(Comités!$B:$B,PPvsREal!$C$17,Comités!H:H) -> 0 | I17: =SUMIF(Comités!$B:$B,PPvsREal!$C$17,Comités!I:I) -> 0 | J17: =SUMIF(Comités!$B:$B,PPvsREal!$C$17,Comités!J:J) -> 0 | K17: =SUMIF(Comités!$B:$B,PPvsREal!$C$17,Comités!K:K) -> 0 | L17: =SUMIF(Comités!$B:$B,PPvsREal!$C$17,Comités!L:L) -> 0 | M17: =SUMIF(Comités!$B:$B,PPvsREal!$C$17,Comités!M:M) -> 0 | N17: =SUMIF(Comités!$B:$B,PPvsREal!$C$17,Comités!N:N) -> 0 | O17: =SUMIF(Comités!$B:$B,PPvsREal!$C$17,Comités!O:O) -> 0 | P17: =SUMIF(Comités!$B:$B,PPvsREal!$C$17,Comités!P:P) -> 0 | Q17: =SUMIF(Comités!$B:$B,PPvsREal!$C$17,Comités!Q:Q) -> 0 | R17: =SUMIF(Comités!$B:$B,PPvsREal!$C$17,Comités!R:R) -> 0 | S17: =SUMIF(Comités!$B:$B,PPvsREal!$C$17,Comités!S:S) -> 0 | T17: =SUMIF(Comités!$B:$B,PPvsREal!$C$17,Comités!T:T) -> 0 | U17: =SUMIF(Comités!$B:$B,PPvsREal!$C$17,Comités!U:U) -> 0 | V17: =SUMIF(Comités!$B:$B,PPvsREal!$C$17,Comités!V:V) -> 0 | W17: =SUMIF(Comités!$B:$B,PPvsREal!$C$17,Comités!W:W) -> 0 | X17: =SUMIF(Comités!$B:$B,PPvsREal!$C$17,Comités!X:X) -> 0 | Y17: =SUMIF(Comités!$B:$B,PPvsREal!$C$17,Comités!Y:Y) -> 0 | Z17: =SUMIF(Comités!$B:$B,PPvsREal!$C$17,Comités!Z:Z) -> 0 | AA17: =SUMIF(Comités!$B:$B,PPvsREal!$C$17,Comités!AA:AA) -> 0
B18: Comités | C18: 404-018-000-00 | D18: =SUMIF(Comités!$B:$B,PPvsREal!$C$18,Comités!D:D) -> 0 | E18: =SUMIF(Comités!$B:$B,PPvsREal!$C$18,Comités!E:E) -> 0 | F18: =SUMIF(Comités!$B:$B,PPvsREal!$C$18,Comités!F:F) -> 0 | G18: =SUMIF(Comités!$B:$B,PPvsREal!$C$18,Comités!G:G) -> 0 | H18: =SUMIF(Comités!$B:$B,PPvsREal!$C$18,Comités!H:H) -> 0 | I18: =SUMIF(Comités!$B:$B,PPvsREal!$C$18,Comités!I:I) -> 0 | J18: =SUMIF(Comités!$B:$B,PPvsREal!$C$18,Comités!J:J) -> 0 | K18: =SUMIF(Comités!$B:$B,PPvsREal!$C$18,Comités!K:K) -> 0 | L18: =SUMIF(Comités!$B:$B,PPvsREal!$C$18,Comités!L:L) -> 0 | M18: =SUMIF(Comités!$B:$B,PPvsREal!$C$18,Comités!M:M) -> 65000 | N18: =SUMIF(Comités!$B:$B,PPvsREal!$C$18,Comités!N:N) -> 162500 | O18: =SUMIF(Comités!$B:$B,PPvsREal!$C$18,Comités!O:O) -> 195833.33 | P18: =SUMIF(Comités!$B:$B,PPvsREal!$C$18,Comités!P:P) -> 162500 | Q18: =SUMIF(Comités!$B:$B,PPvsREal!$C$18,Comités!Q:Q) -> 152499.99 | R18: =SUMIF(Comités!$B:$B,PPvsREal!$C$18,Comités!R:R) -> 162500 | S18: =SUMIF(Comités!$B:$B,PPvsREal!$C$18,Comités!S:S) -> 0 | T18: =SUMIF(Comités!$B:$B,PPvsREal!$C$18,Comités!T:T) -> 162500 | U18: =SUMIF(Comités!$B:$B,PPvsREal!$C$18,Comités!U:U) -> 0 | V18: =SUMIF(Comités!$B:$B,PPvsREal!$C$18,Comités!V:V) -> 0 | W18: =SUMIF(Comités!$B:$B,PPvsREal!$C$18,Comités!W:W) -> 0 | X18: =SUMIF(Comités!$B:$B,PPvsREal!$C$18,Comités!X:X) -> 0 | Y18: =SUMIF(Comités!$B:$B,PPvsREal!$C$18,Comités!Y:Y) -> 0 | Z18: =SUMIF(Comités!$B:$B,PPvsREal!$C$18,Comités!Z:Z) -> 0 | AA18: =SUMIF(Comités!$B:$B,PPvsREal!$C$18,Comités!AA:AA) -> 0
B19: Comités | C19: 502-014-000-00 | D19: =SUMIF(Comités!$B:$B,PPvsREal!$C$19,Comités!D:D) -> 0 | E19: =SUMIF(Comités!$B:$B,PPvsREal!$C$19,Comités!E:E) -> 0 | F19: =SUMIF(Comités!$B:$B,PPvsREal!$C$19,Comités!F:F) -> 6000 | G19: =SUMIF(Comités!$B:$B,PPvsREal!$C$19,Comités!G:G) -> 0 | H19: =SUMIF(Comités!$B:$B,PPvsREal!$C$19,Comités!H:H) -> 0 | I19: =SUMIF(Comités!$B:$B,PPvsREal!$C$19,Comités!I:I) -> 0 | J19: =SUMIF(Comités!$B:$B,PPvsREal!$C$19,Comités!J:J) -> 6000 | K19: =SUMIF(Comités!$B:$B,PPvsREal!$C$19,Comités!K:K) -> 0 | L19: =SUMIF(Comités!$B:$B,PPvsREal!$C$19,Comités!L:L) -> 0 | M19: =SUMIF(Comités!$B:$B,PPvsREal!$C$19,Comités!M:M) -> 0 | N19: =SUMIF(Comités!$B:$B,PPvsREal!$C$19,Comités!N:N) -> 6000 | O19: =SUMIF(Comités!$B:$B,PPvsREal!$C$19,Comités!O:O) -> 45.56 | P19: =SUMIF(Comités!$B:$B,PPvsREal!$C$19,Comités!P:P) -> 0 | Q19: =SUMIF(Comités!$B:$B,PPvsREal!$C$19,Comités!Q:Q) -> 5651.27 | R19: =SUMIF(Comités!$B:$B,PPvsREal!$C$19,Comités!R:R) -> 6000 | S19: =SUMIF(Comités!$B:$B,PPvsREal!$C$19,Comités!S:S) -> 0 | T19: =SUMIF(Comités!$B:$B,PPvsREal!$C$19,Comités!T:T) -> 0 | U19: =SUMIF(Comités!$B:$B,PPvsREal!$C$19,Comités!U:U) -> 0 | V19: =SUMIF(Comités!$B:$B,PPvsREal!$C$19,Comités!V:V) -> 6000 | W19: =SUMIF(Comités!$B:$B,PPvsREal!$C$19,Comités!W:W) -> 0 | X19: =SUMIF(Comités!$B:$B,PPvsREal!$C$19,Comités!X:X) -> 0 | Y19: =SUMIF(Comités!$B:$B,PPvsREal!$C$19,Comités!Y:Y) -> 0 | Z19: =SUMIF(Comités!$B:$B,PPvsREal!$C$19,Comités!Z:Z) -> 6000 | AA19: =SUMIF(Comités!$B:$B,PPvsREal!$C$19,Comités!AA:AA) -> 0
B20: Comités | C20: 502-005-000-00 | D20: =SUMIF(Comités!$B:$B,PPvsREal!$C$20,Comités!D:D) -> 8000 | E20: =SUMIF(Comités!$B:$B,PPvsREal!$C$20,Comités!E:E) -> 0 | F20: =SUMIF(Comités!$B:$B,PPvsREal!$C$20,Comités!F:F) -> 8000 | G20: =SUMIF(Comités!$B:$B,PPvsREal!$C$20,Comités!G:G) -> 0 | H20: =SUMIF(Comités!$B:$B,PPvsREal!$C$20,Comités!H:H) -> 8000 | I20: =SUMIF(Comités!$B:$B,PPvsREal!$C$20,Comités!I:I) -> 0 | J20: =SUMIF(Comités!$B:$B,PPvsREal!$C$20,Comités!J:J) -> 8000 | K20: =SUMIF(Comités!$B:$B,PPvsREal!$C$20,Comités!K:K) -> 0 | L20: =SUMIF(Comités!$B:$B,PPvsREal!$C$20,Comités!L:L) -> 8000 | M20: =SUMIF(Comités!$B:$B,PPvsREal!$C$20,Comités!M:M) -> 10815.12 | N20: =SUMIF(Comités!$B:$B,PPvsREal!$C$20,Comités!N:N) -> 8000 | O20: =SUMIF(Comités!$B:$B,PPvsREal!$C$20,Comités!O:O) -> 0 | P20: =SUMIF(Comités!$B:$B,PPvsREal!$C$20,Comités!P:P) -> 8000 | Q20: =SUMIF(Comités!$B:$B,PPvsREal!$C$20,Comités!Q:Q) -> 420 | R20: =SUMIF(Comités!$B:$B,PPvsREal!$C$20,Comités!R:R) -> 8000 | S20: =SUMIF(Comités!$B:$B,PPvsREal!$C$20,Comités!S:S) -> 0 | T20: =SUMIF(Comités!$B:$B,PPvsREal!$C$20,Comités!T:T) -> 8000 | U20: =SUMIF(Comités!$B:$B,PPvsREal!$C$20,Comités!U:U) -> 0 | V20: =SUMIF(Comités!$B:$B,PPvsREal!$C$20,Comités!V:V) -> 8000 | W20: =SUMIF(Comités!$B:$B,PPvsREal!$C$20,Comités!W:W) -> 0 | X20: =SUMIF(Comités!$B:$B,PPvsREal!$C$20,Comités!X:X) -> 8000 | Y20: =SUMIF(Comités!$B:$B,PPvsREal!$C$20,Comités!Y:Y) -> 0 | Z20: =SUMIF(Comités!$B:$B,PPvsREal!$C$20,Comités!Z:Z) -> 8000 | AA20: =SUMIF(Comités!$B:$B,PPvsREal!$C$20,Comités!AA:AA) -> 0
B21: Comités | C21: 502-001-000-00 | D21: =SUMIF(Comités!$B:$B,PPvsREal!$C$21,Comités!D:D) -> 0 | E21: =SUMIF(Comités!$B:$B,PPvsREal!$C$21,Comités!E:E) -> 0 | F21: =SUMIF(Comités!$B:$B,PPvsREal!$C$21,Comités!F:F) -> 0 | G21: =SUMIF(Comités!$B:$B,PPvsREal!$C$21,Comités!G:G) -> 0 | H21: =SUMIF(Comités!$B:$B,PPvsREal!$C$21,Comités!H:H) -> 0 | I21: =SUMIF(Comités!$B:$B,PPvsREal!$C$21,Comités!I:I) -> 0 | J21: =SUMIF(Comités!$B:$B,PPvsREal!$C$21,Comités!J:J) -> 0 | K21: =SUMIF(Comités!$B:$B,PPvsREal!$C$21,Comités!K:K) -> 0 | L21: =SUMIF(Comités!$B:$B,PPvsREal!$C$21,Comités!L:L) -> 0 | M21: =SUMIF(Comités!$B:$B,PPvsREal!$C$21,Comités!M:M) -> 113.9 | N21: =SUMIF(Comités!$B:$B,PPvsREal!$C$21,Comités!N:N) -> 0 | O21: =SUMIF(Comités!$B:$B,PPvsREal!$C$21,Comités!O:O) -> 30001.66 | P21: =SUMIF(Comités!$B:$B,PPvsREal!$C$21,Comités!P:P) -> 0 | Q21: =SUMIF(Comités!$B:$B,PPvsREal!$C$21,Comités!Q:Q) -> 375.03 | R21: =SUMIF(Comités!$B:$B,PPvsREal!$C$21,Comités!R:R) -> 0 | S21: =SUMIF(Comités!$B:$B,PPvsREal!$C$21,Comités!S:S) -> 0 | T21: =SUMIF(Comités!$B:$B,PPvsREal!$C$21,Comités!T:T) -> 0 | U21: =SUMIF(Comités!$B:$B,PPvsREal!$C$21,Comités!U:U) -> 0 | V21: =SUMIF(Comités!$B:$B,PPvsREal!$C$21,Comités!V:V) -> 0 | W21: =SUMIF(Comités!$B:$B,PPvsREal!$C$21,Comités!W:W) -> 0 | X21: =SUMIF(Comités!$B:$B,PPvsREal!$C$21,Comités!X:X) -> 0 | Y21: =SUMIF(Comités!$B:$B,PPvsREal!$C$21,Comités!Y:Y) -> 0 | Z21: =SUMIF(Comités!$B:$B,PPvsREal!$C$21,Comités!Z:Z) -> 0 | AA21: =SUMIF(Comités!$B:$B,PPvsREal!$C$21,Comités!AA:AA) -> 0
B22: Comités | C22: 502-003-000-00 | D22: =SUMIF(Comités!$B:$B,PPvsREal!$C$22,Comités!D:D) -> 6000 | E22: =SUMIF(Comités!$B:$B,PPvsREal!$C$22,Comités!E:E) -> 0 | F22: =SUMIF(Comités!$B:$B,PPvsREal!$C$22,Comités!F:F) -> 6000 | G22: =SUMIF(Comités!$B:$B,PPvsREal!$C$22,Comités!G:G) -> 0 | H22: =SUMIF(Comités!$B:$B,PPvsREal!$C$22,Comités!H:H) -> 6000 | I22: =SUMIF(Comités!$B:$B,PPvsREal!$C$22,Comités!I:I) -> 768 | J22: =SUMIF(Comités!$B:$B,PPvsREal!$C$22,Comités!J:J) -> 6000 | K22: =SUMIF(Comités!$B:$B,PPvsREal!$C$22,Comités!K:K) -> 0 | L22: =SUMIF(Comités!$B:$B,PPvsREal!$C$22,Comités!L:L) -> 6000 | M22: =SUMIF(Comités!$B:$B,PPvsREal!$C$22,Comités!M:M) -> 91.12 | N22: =SUMIF(Comités!$B:$B,PPvsREal!$C$22,Comités!N:N) -> 6000 | O22: =SUMIF(Comités!$B:$B,PPvsREal!$C$22,Comités!O:O) -> 11512.78 | P22: =SUMIF(Comités!$B:$B,PPvsREal!$C$22,Comités!P:P) -> 6000 | Q22: =SUMIF(Comités!$B:$B,PPvsREal!$C$22,Comités!Q:Q) -> 0 | R22: =SUMIF(Comités!$B:$B,PPvsREal!$C$22,Comités!R:R) -> 6000 | S22: =SUMIF(Comités!$B:$B,PPvsREal!$C$22,Comités!S:S) -> 0 | T22: =SUMIF(Comités!$B:$B,PPvsREal!$C$22,Comités!T:T) -> 6000 | U22: =SUMIF(Comités!$B:$B,PPvsREal!$C$22,Comités!U:U) -> 0 | V22: =SUMIF(Comités!$B:$B,PPvsREal!$C$22,Comités!V:V) -> 6000 | W22: =SUMIF(Comités!$B:$B,PPvsREal!$C$22,Comités!W:W) -> 0 | X22: =SUMIF(Comités!$B:$B,PPvsREal!$C$22,Comités!X:X) -> 6000 | Y22: =SUMIF(Comités!$B:$B,PPvsREal!$C$22,Comités!Y:Y) -> 0 | Z22: =SUMIF(Comités!$B:$B,PPvsREal!$C$22,Comités!Z:Z) -> 6000 | AA22: =SUMIF(Comités!$B:$B,PPvsREal!$C$22,Comités!AA:AA) -> 0
B23: Comités | C23: 502-013-000-00 | D23: =SUMIF(Comités!$B:$B,PPvsREal!$C$23,Comités!D:D) -> 0 | E23: =SUMIF(Comités!$B:$B,PPvsREal!$C$23,Comités!E:E) -> 0 | F23: =SUMIF(Comités!$B:$B,PPvsREal!$C$23,Comités!F:F) -> 0 | G23: =SUMIF(Comités!$B:$B,PPvsREal!$C$23,Comités!G:G) -> 916 | H23: =SUMIF(Comités!$B:$B,PPvsREal!$C$23,Comités!H:H) -> 0 | I23: =SUMIF(Comités!$B:$B,PPvsREal!$C$23,Comités!I:I) -> 0 | J23: =SUMIF(Comités!$B:$B,PPvsREal!$C$23,Comités!J:J) -> 0 | K23: =SUMIF(Comités!$B:$B,PPvsREal!$C$23,Comités!K:K) -> 0 | L23: =SUMIF(Comités!$B:$B,PPvsREal!$C$23,Comités!L:L) -> 0 | M23: =SUMIF(Comités!$B:$B,PPvsREal!$C$23,Comités!M:M) -> 623.36 | N23: =SUMIF(Comités!$B:$B,PPvsREal!$C$23,Comités!N:N) -> 0 | O23: =SUMIF(Comités!$B:$B,PPvsREal!$C$23,Comités!O:O) -> 0 | P23: =SUMIF(Comités!$B:$B,PPvsREal!$C$23,Comités!P:P) -> 0 | Q23: =SUMIF(Comités!$B:$B,PPvsREal!$C$23,Comités!Q:Q) -> 0 | R23: =SUMIF(Comités!$B:$B,PPvsREal!$C$23,Comités!R:R) -> 0 | S23: =SUMIF(Comités!$B:$B,PPvsREal!$C$23,Comités!S:S) -> 0 | T23: =SUMIF(Comités!$B:$B,PPvsREal!$C$23,Comités!T:T) -> 0 | U23: =SUMIF(Comités!$B:$B,PPvsREal!$C$23,Comités!U:U) -> 0 | V23: =SUMIF(Comités!$B:$B,PPvsREal!$C$23,Comités!V:V) -> 0 | W23: =SUMIF(Comités!$B:$B,PPvsREal!$C$23,Comités!W:W) -> 0 | X23: =SUMIF(Comités!$B:$B,PPvsREal!$C$23,Comités!X:X) -> 0 | Y23: =SUMIF(Comités!$B:$B,PPvsREal!$C$23,Comités!Y:Y) -> 0 | Z23: =SUMIF(Comités!$B:$B,PPvsREal!$C$23,Comités!Z:Z) -> 0 | AA23: =SUMIF(Comités!$B:$B,PPvsREal!$C$23,Comités!AA:AA) -> 0
B24: Comités | C24: 502-007-000-00 | D24: =SUMIF(Comités!$B:$B,PPvsREal!$C$24,Comités!D:D) -> 11200 | E24: =SUMIF(Comités!$B:$B,PPvsREal!$C$24,Comités!E:E) -> 0 | F24: =SUMIF(Comités!$B:$B,PPvsREal!$C$24,Comités!F:F) -> 11200 | G24: =SUMIF(Comités!$B:$B,PPvsREal!$C$24,Comités!G:G) -> 0 | H24: =SUMIF(Comités!$B:$B,PPvsREal!$C$24,Comités!H:H) -> 11200 | I24: =SUMIF(Comités!$B:$B,PPvsREal!$C$24,Comités!I:I) -> 0 | J24: =SUMIF(Comités!$B:$B,PPvsREal!$C$24,Comités!J:J) -> 11200 | K24: =SUMIF(Comités!$B:$B,PPvsREal!$C$24,Comités!K:K) -> 0 | L24: =SUMIF(Comités!$B:$B,PPvsREal!$C$24,Comités!L:L) -> 11200 | M24: =SUMIF(Comités!$B:$B,PPvsREal!$C$24,Comités!M:M) -> 745.43 | N24: =SUMIF(Comités!$B:$B,PPvsREal!$C$24,Comités!N:N) -> 11200 | O24: =SUMIF(Comités!$B:$B,PPvsREal!$C$24,Comités!O:O) -> 0 | P24: =SUMIF(Comités!$B:$B,PPvsREal!$C$24,Comités!P:P) -> 11200 | Q24: =SUMIF(Comités!$B:$B,PPvsREal!$C$24,Comités!Q:Q) -> 0 | R24: =SUMIF(Comités!$B:$B,PPvsREal!$C$24,Comités!R:R) -> 11200 | S24: =SUMIF(Comités!$B:$B,PPvsREal!$C$24,Comités!S:S) -> 0 | T24: =SUMIF(Comités!$B:$B,PPvsREal!$C$24,Comités!T:T) -> 11200 | U24: =SUMIF(Comités!$B:$B,PPvsREal!$C$24,Comités!U:U) -> 0 | V24: =SUMIF(Comités!$B:$B,PPvsREal!$C$24,Comités!V:V) -> 11200 | W24: =SUMIF(Comités!$B:$B,PPvsREal!$C$24,Comités!W:W) -> 0 | X24: =SUMIF(Comités!$B:$B,PPvsREal!$C$24,Comités!X:X) -> 11200 | Y24: =SUMIF(Comités!$B:$B,PPvsREal!$C$24,Comités!Y:Y) -> 0 | Z24: =SUMIF(Comités!$B:$B,PPvsREal!$C$24,Comités!Z:Z) -> 11200 | AA24: =SUMIF(Comités!$B:$B,PPvsREal!$C$24,Comités!AA:AA) -> 0
B25: Comités | C25: 502-016-000-00 | D25: =SUMIF(Comités!$B:$B,PPvsREal!$C$25,Comités!D:D) -> 0 | E25: =SUMIF(Comités!$B:$B,PPvsREal!$C$25,Comités!E:E) -> 0 | F25: =SUMIF(Comités!$B:$B,PPvsREal!$C$25,Comités!F:F) -> 0 | G25: =SUMIF(Comités!$B:$B,PPvsREal!$C$25,Comités!G:G) -> 0 | H25: =SUMIF(Comités!$B:$B,PPvsREal!$C$25,Comités!H:H) -> 0 | I25: =SUMIF(Comités!$B:$B,PPvsREal!$C$25,Comités!I:I) -> 0 | J25: =SUMIF(Comités!$B:$B,PPvsREal!$C$25,Comités!J:J) -> 0 | K25: =SUMIF(Comités!$B:$B,PPvsREal!$C$25,Comités!K:K) -> 185.01 | L25: =SUMIF(Comités!$B:$B,PPvsREal!$C$25,Comités!L:L) -> 0 | M25: =SUMIF(Comités!$B:$B,PPvsREal!$C$25,Comités!M:M) -> 0 | N25: =SUMIF(Comités!$B:$B,PPvsREal!$C$25,Comités!N:N) -> 0 | O25: =SUMIF(Comités!$B:$B,PPvsREal!$C$25,Comités!O:O) -> 0 | P25: =SUMIF(Comités!$B:$B,PPvsREal!$C$25,Comités!P:P) -> 0 | Q25: =SUMIF(Comités!$B:$B,PPvsREal!$C$25,Comités!Q:Q) -> 0 | R25: =SUMIF(Comités!$B:$B,PPvsREal!$C$25,Comités!R:R) -> 0 | S25: =SUMIF(Comités!$B:$B,PPvsREal!$C$25,Comités!S:S) -> 0 | T25: =SUMIF(Comités!$B:$B,PPvsREal!$C$25,Comités!T:T) -> 0 | U25: =SUMIF(Comités!$B:$B,PPvsREal!$C$25,Comités!U:U) -> 0 | V25: =SUMIF(Comités!$B:$B,PPvsREal!$C$25,Comités!V:V) -> 0 | W25: =SUMIF(Comités!$B:$B,PPvsREal!$C$25,Comités!W:W) -> 0 | X25: =SUMIF(Comités!$B:$B,PPvsREal!$C$25,Comités!X:X) -> 0 | Y25: =SUMIF(Comités!$B:$B,PPvsREal!$C$25,Comités!Y:Y) -> 0 | Z25: =SUMIF(Comités!$B:$B,PPvsREal!$C$25,Comités!Z:Z) -> 0 | AA25: =SUMIF(Comités!$B:$B,PPvsREal!$C$25,Comités!AA:AA) -> 0
B26: Comités | C26: 502-004-000-00 | D26: =SUMIF(Comités!$B:$B,PPvsREal!$C$26,Comités!D:D) -> 6000 | E26: =SUMIF(Comités!$B:$B,PPvsREal!$C$26,Comités!E:E) -> 0 | F26: =SUMIF(Comités!$B:$B,PPvsREal!$C$26,Comités!F:F) -> 6000 | G26: =SUMIF(Comités!$B:$B,PPvsREal!$C$26,Comités!G:G) -> 0 | H26: =SUMIF(Comités!$B:$B,PPvsREal!$C$26,Comités!H:H) -> 6000 | I26: =SUMIF(Comités!$B:$B,PPvsREal!$C$26,Comités!I:I) -> 109.38 | J26: =SUMIF(Comités!$B:$B,PPvsREal!$C$26,Comités!J:J) -> 6000 | K26: =SUMIF(Comités!$B:$B,PPvsREal!$C$26,Comités!K:K) -> 0 | L26: =SUMIF(Comités!$B:$B,PPvsREal!$C$26,Comités!L:L) -> 6000 | M26: =SUMIF(Comités!$B:$B,PPvsREal!$C$26,Comités!M:M) -> 0 | N26: =SUMIF(Comités!$B:$B,PPvsREal!$C$26,Comités!N:N) -> 6000 | O26: =SUMIF(Comités!$B:$B,PPvsREal!$C$26,Comités!O:O) -> 769.91 | P26: =SUMIF(Comités!$B:$B,PPvsREal!$C$26,Comités!P:P) -> 6000 | Q26: =SUMIF(Comités!$B:$B,PPvsREal!$C$26,Comités!Q:Q) -> 0 | R26: =SUMIF(Comités!$B:$B,PPvsREal!$C$26,Comités!R:R) -> 6000 | S26: =SUMIF(Comités!$B:$B,PPvsREal!$C$26,Comités!S:S) -> 0 | T26: =SUMIF(Comités!$B:$B,PPvsREal!$C$26,Comités!T:T) -> 6000 | U26: =SUMIF(Comités!$B:$B,PPvsREal!$C$26,Comités!U:U) -> 0 | V26: =SUMIF(Comités!$B:$B,PPvsREal!$C$26,Comités!V:V) -> 6000 | W26: =SUMIF(Comités!$B:$B,PPvsREal!$C$26,Comités!W:W) -> 0 | X26: =SUMIF(Comités!$B:$B,PPvsREal!$C$26,Comités!X:X) -> 6000 | Y26: =SUMIF(Comités!$B:$B,PPvsREal!$C$26,Comités!Y:Y) -> 0 | Z26: =SUMIF(Comités!$B:$B,PPvsREal!$C$26,Comités!Z:Z) -> 6000 | AA26: =SUMIF(Comités!$B:$B,PPvsREal!$C$26,Comités!AA:AA) -> 0
B27: Comités | C27: 502-002-000-00 | D27: =SUMIF(Comités!$B:$B,PPvsREal!$C$27,Comités!D:D) -> 0 | E27: =SUMIF(Comités!$B:$B,PPvsREal!$C$27,Comités!E:E) -> 0 | F27: =SUMIF(Comités!$B:$B,PPvsREal!$C$27,Comités!F:F) -> 0 | G27: =SUMIF(Comités!$B:$B,PPvsREal!$C$27,Comités!G:G) -> 0 | H27: =SUMIF(Comités!$B:$B,PPvsREal!$C$27,Comités!H:H) -> 0 | I27: =SUMIF(Comités!$B:$B,PPvsREal!$C$27,Comités!I:I) -> 0 | J27: =SUMIF(Comités!$B:$B,PPvsREal!$C$27,Comités!J:J) -> 0 | K27: =SUMIF(Comités!$B:$B,PPvsREal!$C$27,Comités!K:K) -> 0 | L27: =SUMIF(Comités!$B:$B,PPvsREal!$C$27,Comités!L:L) -> 0 | M27: =SUMIF(Comités!$B:$B,PPvsREal!$C$27,Comités!M:M) -> 0 | N27: =SUMIF(Comités!$B:$B,PPvsREal!$C$27,Comités!N:N) -> 0 | O27: =SUMIF(Comités!$B:$B,PPvsREal!$C$27,Comités!O:O) -> 0 | P27: =SUMIF(Comités!$B:$B,PPvsREal!$C$27,Comités!P:P) -> 0 | Q27: =SUMIF(Comités!$B:$B,PPvsREal!$C$27,Comités!Q:Q) -> 511.66 | R27: =SUMIF(Comités!$B:$B,PPvsREal!$C$27,Comités!R:R) -> 0 | S27: =SUMIF(Comités!$B:$B,PPvsREal!$C$27,Comités!S:S) -> 0 | T27: =SUMIF(Comités!$B:$B,PPvsREal!$C$27,Comités!T:T) -> 0 | U27: =SUMIF(Comités!$B:$B,PPvsREal!$C$27,Comités!U:U) -> 0 | V27: =SUMIF(Comités!$B:$B,PPvsREal!$C$27,Comités!V:V) -> 0 | W27: =SUMIF(Comités!$B:$B,PPvsREal!$C$27,Comités!W:W) -> 0 | X27: =SUMIF(Comités!$B:$B,PPvsREal!$C$27,Comités!X:X) -> 0 | Y27: =SUMIF(Comités!$B:$B,PPvsREal!$C$27,Comités!Y:Y) -> 0 | Z27: =SUMIF(Comités!$B:$B,PPvsREal!$C$27,Comités!Z:Z) -> 0 | AA27: =SUMIF(Comités!$B:$B,PPvsREal!$C$27,Comités!AA:AA) -> 0
B28: Comités | C28: 502-009-000-00 | D28: =SUMIF(Comités!$B:$B,PPvsREal!$C$28,Comités!D:D) -> 0 | E28: =SUMIF(Comités!$B:$B,PPvsREal!$C$28,Comités!E:E) -> 0 | F28: =SUMIF(Comités!$B:$B,PPvsREal!$C$28,Comités!F:F) -> 0 | G28: =SUMIF(Comités!$B:$B,PPvsREal!$C$28,Comités!G:G) -> 0 | H28: =SUMIF(Comités!$B:$B,PPvsREal!$C$28,Comités!H:H) -> 0 | I28: =SUMIF(Comités!$B:$B,PPvsREal!$C$28,Comités!I:I) -> 0 | J28: =SUMIF(Comités!$B:$B,PPvsREal!$C$28,Comités!J:J) -> 0 | K28: =SUMIF(Comités!$B:$B,PPvsREal!$C$28,Comités!K:K) -> 0 | L28: =SUMIF(Comités!$B:$B,PPvsREal!$C$28,Comités!L:L) -> 0 | M28: =SUMIF(Comités!$B:$B,PPvsREal!$C$28,Comités!M:M) -> 0 | N28: =SUMIF(Comités!$B:$B,PPvsREal!$C$28,Comités!N:N) -> 0 | O28: =SUMIF(Comités!$B:$B,PPvsREal!$C$28,Comités!O:O) -> 0 | P28: =SUMIF(Comités!$B:$B,PPvsREal!$C$28,Comités!P:P) -> 0 | Q28: =SUMIF(Comités!$B:$B,PPvsREal!$C$28,Comités!Q:Q) -> 0 | R28: =SUMIF(Comités!$B:$B,PPvsREal!$C$28,Comités!R:R) -> 0 | S28: =SUMIF(Comités!$B:$B,PPvsREal!$C$28,Comités!S:S) -> 0 | T28: =SUMIF(Comités!$B:$B,PPvsREal!$C$28,Comités!T:T) -> 0 | U28: =SUMIF(Comités!$B:$B,PPvsREal!$C$28,Comités!U:U) -> 0 | V28: =SUMIF(Comités!$B:$B,PPvsREal!$C$28,Comités!V:V) -> 0 | W28: =SUMIF(Comités!$B:$B,PPvsREal!$C$28,Comités!W:W) -> 0 | X28: =SUMIF(Comités!$B:$B,PPvsREal!$C$28,Comités!X:X) -> 0 | Y28: =SUMIF(Comités!$B:$B,PPvsREal!$C$28,Comités!Y:Y) -> 0 | Z28: =SUMIF(Comités!$B:$B,PPvsREal!$C$28,Comités!Z:Z) -> 0 | AA28: =SUMIF(Comités!$B:$B,PPvsREal!$C$28,Comités!AA:AA) -> 0
B29: Comités | C29: 502-017-000-00 | D29: =SUMIF(Comités!$B:$B,PPvsREal!$C$29,Comités!D:D) -> 0 | E29: =SUMIF(Comités!$B:$B,PPvsREal!$C$29,Comités!E:E) -> 0 | F29: =SUMIF(Comités!$B:$B,PPvsREal!$C$29,Comités!F:F) -> 0 | G29: =SUMIF(Comités!$B:$B,PPvsREal!$C$29,Comités!G:G) -> 0 | H29: =SUMIF(Comités!$B:$B,PPvsREal!$C$29,Comités!H:H) -> 0 | I29: =SUMIF(Comités!$B:$B,PPvsREal!$C$29,Comités!I:I) -> 0 | J29: =SUMIF(Comités!$B:$B,PPvsREal!$C$29,Comités!J:J) -> 0 | K29: =SUMIF(Comités!$B:$B,PPvsREal!$C$29,Comités!K:K) -> 0 | L29: =SUMIF(Comités!$B:$B,PPvsREal!$C$29,Comités!L:L) -> 0 | M29: =SUMIF(Comités!$B:$B,PPvsREal!$C$29,Comités!M:M) -> 325059 | N29: =SUMIF(Comités!$B:$B,PPvsREal!$C$29,Comités!N:N) -> 36000 | O29: =SUMIF(Comités!$B:$B,PPvsREal!$C$29,Comités!O:O) -> 3047.95 | P29: =SUMIF(Comités!$B:$B,PPvsREal!$C$29,Comités!P:P) -> 32000 | Q29: =SUMIF(Comités!$B:$B,PPvsREal!$C$29,Comités!Q:Q) -> 3693.21 | R29: =SUMIF(Comités!$B:$B,PPvsREal!$C$29,Comités!R:R) -> 36000 | S29: =SUMIF(Comités!$B:$B,PPvsREal!$C$29,Comités!S:S) -> 0 | T29: =SUMIF(Comités!$B:$B,PPvsREal!$C$29,Comités!T:T) -> 32000 | U29: =SUMIF(Comités!$B:$B,PPvsREal!$C$29,Comités!U:U) -> 0 | V29: =SUMIF(Comités!$B:$B,PPvsREal!$C$29,Comités!V:V) -> 0 | W29: =SUMIF(Comités!$B:$B,PPvsREal!$C$29,Comités!W:W) -> 0 | X29: =SUMIF(Comités!$B:$B,PPvsREal!$C$29,Comités!X:X) -> 0 | Y29: =SUMIF(Comités!$B:$B,PPvsREal!$C$29,Comités!Y:Y) -> 0 | Z29: =SUMIF(Comités!$B:$B,PPvsREal!$C$29,Comités!Z:Z) -> 40000 | AA29: =SUMIF(Comités!$B:$B,PPvsREal!$C$29,Comités!AA:AA) -> 0
B30: Eventos | C30: 405-012-000-00 | D30: =SUMIF(Eventos!$B:$B,PPvsREal!$C$30,Eventos!D:D) -> 60000 | E30: =SUMIF(Eventos!$B:$B,PPvsREal!$C$30,Eventos!E:E) -> 0 | F30: =SUMIF(Eventos!$B:$B,PPvsREal!$C$30,Eventos!F:F) -> 0 | G30: =SUMIF(Eventos!$B:$B,PPvsREal!$C$30,Eventos!G:G) -> 0 | H30: =SUMIF(Eventos!$B:$B,PPvsREal!$C$30,Eventos!H:H) -> 80000 | I30: =SUMIF(Eventos!$B:$B,PPvsREal!$C$30,Eventos!I:I) -> 0 | J30: =SUMIF(Eventos!$B:$B,PPvsREal!$C$30,Eventos!J:J) -> 0 | K30: =SUMIF(Eventos!$B:$B,PPvsREal!$C$30,Eventos!K:K) -> 0 | L30: =SUMIF(Eventos!$B:$B,PPvsREal!$C$30,Eventos!L:L) -> 0 | M30: =SUMIF(Eventos!$B:$B,PPvsREal!$C$30,Eventos!M:M) -> 80000 | N30: =SUMIF(Eventos!$B:$B,PPvsREal!$C$30,Eventos!N:N) -> 190000 | O30: =SUMIF(Eventos!$B:$B,PPvsREal!$C$30,Eventos!O:O) -> 0 | P30: =SUMIF(Eventos!$B:$B,PPvsREal!$C$30,Eventos!P:P) -> 0 | Q30: =SUMIF(Eventos!$B:$B,PPvsREal!$C$30,Eventos!Q:Q) -> 0 | R30: =SUMIF(Eventos!$B:$B,PPvsREal!$C$30,Eventos!R:R) -> 0 | S30: =SUMIF(Eventos!$B:$B,PPvsREal!$C$30,Eventos!S:S) -> 0 | T30: =SUMIF(Eventos!$B:$B,PPvsREal!$C$30,Eventos!T:T) -> 0 | U30: =SUMIF(Eventos!$B:$B,PPvsREal!$C$30,Eventos!U:U) -> 0 | V30: =SUMIF(Eventos!$B:$B,PPvsREal!$C$30,Eventos!V:V) -> 0 | W30: =SUMIF(Eventos!$B:$B,PPvsREal!$C$30,Eventos!W:W) -> 0 | X30: =SUMIF(Eventos!$B:$B,PPvsREal!$C$30,Eventos!X:X) -> 0 | Y30: =SUMIF(Eventos!$B:$B,PPvsREal!$C$30,Eventos!Y:Y) -> 0 | Z30: =SUMIF(Eventos!$B:$B,PPvsREal!$C$30,Eventos!Z:Z) -> 0 | AA30: =SUMIF(Eventos!$B:$B,PPvsREal!$C$30,Eventos!AA:AA) -> 0
B31: Eventos | C31: 405-010-000-00 | D31: =SUMIF(Eventos!$B:$B,PPvsREal!$C$31,Eventos!D:D) -> 0 | E31: =SUMIF(Eventos!$B:$B,PPvsREal!$C$31,Eventos!E:E) -> 0 | F31: =SUMIF(Eventos!$B:$B,PPvsREal!$C$31,Eventos!F:F) -> 70000 | G31: =SUMIF(Eventos!$B:$B,PPvsREal!$C$31,Eventos!G:G) -> 73800 | H31: =SUMIF(Eventos!$B:$B,PPvsREal!$C$31,Eventos!H:H) -> 0 | I31: =SUMIF(Eventos!$B:$B,PPvsREal!$C$31,Eventos!I:I) -> 7650 | J31: =SUMIF(Eventos!$B:$B,PPvsREal!$C$31,Eventos!J:J) -> 0 | K31: =SUMIF(Eventos!$B:$B,PPvsREal!$C$31,Eventos!K:K) -> 3400 | L31: =SUMIF(Eventos!$B:$B,PPvsREal!$C$31,Eventos!L:L) -> 0 | M31: =SUMIF(Eventos!$B:$B,PPvsREal!$C$31,Eventos!M:M) -> 0 | N31: =SUMIF(Eventos!$B:$B,PPvsREal!$C$31,Eventos!N:N) -> 0 | O31: =SUMIF(Eventos!$B:$B,PPvsREal!$C$31,Eventos!O:O) -> 850 | P31: =SUMIF(Eventos!$B:$B,PPvsREal!$C$31,Eventos!P:P) -> 0 | Q31: =SUMIF(Eventos!$B:$B,PPvsREal!$C$31,Eventos!Q:Q) -> 0 | R31: =SUMIF(Eventos!$B:$B,PPvsREal!$C$31,Eventos!R:R) -> 0 | S31: =SUMIF(Eventos!$B:$B,PPvsREal!$C$31,Eventos!S:S) -> 0 | T31: =SUMIF(Eventos!$B:$B,PPvsREal!$C$31,Eventos!T:T) -> 0 | U31: =SUMIF(Eventos!$B:$B,PPvsREal!$C$31,Eventos!U:U) -> 0 | V31: =SUMIF(Eventos!$B:$B,PPvsREal!$C$31,Eventos!V:V) -> 0 | W31: =SUMIF(Eventos!$B:$B,PPvsREal!$C$31,Eventos!W:W) -> 0 | X31: =SUMIF(Eventos!$B:$B,PPvsREal!$C$31,Eventos!X:X) -> 0 | Y31: =SUMIF(Eventos!$B:$B,PPvsREal!$C$31,Eventos!Y:Y) -> 0 | Z31: =SUMIF(Eventos!$B:$B,PPvsREal!$C$31,Eventos!Z:Z) -> 0 | AA31: =SUMIF(Eventos!$B:$B,PPvsREal!$C$31,Eventos!AA:AA) -> 0
B32: Eventos | C32: 405-007-000-00 | D32: =SUMIF(Eventos!$B:$B,PPvsREal!$C$32,Eventos!D:D) -> 0 | E32: =SUMIF(Eventos!$B:$B,PPvsREal!$C$32,Eventos!E:E) -> 0 | F32: =SUMIF(Eventos!$B:$B,PPvsREal!$C$32,Eventos!F:F) -> 25000 | G32: =SUMIF(Eventos!$B:$B,PPvsREal!$C$32,Eventos!G:G) -> 0 | H32: =SUMIF(Eventos!$B:$B,PPvsREal!$C$32,Eventos!H:H) -> 0 | I32: =SUMIF(Eventos!$B:$B,PPvsREal!$C$32,Eventos!I:I) -> 0 | J32: =SUMIF(Eventos!$B:$B,PPvsREal!$C$32,Eventos!J:J) -> 25000 | K32: =SUMIF(Eventos!$B:$B,PPvsREal!$C$32,Eventos!K:K) -> 0 | L32: =SUMIF(Eventos!$B:$B,PPvsREal!$C$32,Eventos!L:L) -> 150000 | M32: =SUMIF(Eventos!$B:$B,PPvsREal!$C$32,Eventos!M:M) -> 0 | N32: =SUMIF(Eventos!$B:$B,PPvsREal!$C$32,Eventos!N:N) -> 25000 | O32: =SUMIF(Eventos!$B:$B,PPvsREal!$C$32,Eventos!O:O) -> 0 | P32: =SUMIF(Eventos!$B:$B,PPvsREal!$C$32,Eventos!P:P) -> 0 | Q32: =SUMIF(Eventos!$B:$B,PPvsREal!$C$32,Eventos!Q:Q) -> 0 | R32: =SUMIF(Eventos!$B:$B,PPvsREal!$C$32,Eventos!R:R) -> 0 | S32: =SUMIF(Eventos!$B:$B,PPvsREal!$C$32,Eventos!S:S) -> 0 | T32: =SUMIF(Eventos!$B:$B,PPvsREal!$C$32,Eventos!T:T) -> 25000 | U32: =SUMIF(Eventos!$B:$B,PPvsREal!$C$32,Eventos!U:U) -> 0 | V32: =SUMIF(Eventos!$B:$B,PPvsREal!$C$32,Eventos!V:V) -> 0 | W32: =SUMIF(Eventos!$B:$B,PPvsREal!$C$32,Eventos!W:W) -> 0 | X32: =SUMIF(Eventos!$B:$B,PPvsREal!$C$32,Eventos!X:X) -> 0 | Y32: =SUMIF(Eventos!$B:$B,PPvsREal!$C$32,Eventos!Y:Y) -> 0 | Z32: =SUMIF(Eventos!$B:$B,PPvsREal!$C$32,Eventos!Z:Z) -> 0 | AA32: =SUMIF(Eventos!$B:$B,PPvsREal!$C$32,Eventos!AA:AA) -> 0
B33: Eventos | C33: 405-014-000-00 | D33: =SUMIF(Eventos!$B:$B,PPvsREal!$C$33,Eventos!D:D) -> 0 | E33: =SUMIF(Eventos!$B:$B,PPvsREal!$C$33,Eventos!E:E) -> 0 | F33: =SUMIF(Eventos!$B:$B,PPvsREal!$C$33,Eventos!F:F) -> 0 | G33: =SUMIF(Eventos!$B:$B,PPvsREal!$C$33,Eventos!G:G) -> 0 | H33: =SUMIF(Eventos!$B:$B,PPvsREal!$C$33,Eventos!H:H) -> 0 | I33: =SUMIF(Eventos!$B:$B,PPvsREal!$C$33,Eventos!I:I) -> 0 | J33: =SUMIF(Eventos!$B:$B,PPvsREal!$C$33,Eventos!J:J) -> 0 | K33: =SUMIF(Eventos!$B:$B,PPvsREal!$C$33,Eventos!K:K) -> 0 | L33: =SUMIF(Eventos!$B:$B,PPvsREal!$C$33,Eventos!L:L) -> 0 | M33: =SUMIF(Eventos!$B:$B,PPvsREal!$C$33,Eventos!M:M) -> 0 | N33: =SUMIF(Eventos!$B:$B,PPvsREal!$C$33,Eventos!N:N) -> 0 | O33: =SUMIF(Eventos!$B:$B,PPvsREal!$C$33,Eventos!O:O) -> 0 | P33: =SUMIF(Eventos!$B:$B,PPvsREal!$C$33,Eventos!P:P) -> 0 | Q33: =SUMIF(Eventos!$B:$B,PPvsREal!$C$33,Eventos!Q:Q) -> 0 | R33: =SUMIF(Eventos!$B:$B,PPvsREal!$C$33,Eventos!R:R) -> 0 | S33: =SUMIF(Eventos!$B:$B,PPvsREal!$C$33,Eventos!S:S) -> 0 | T33: =SUMIF(Eventos!$B:$B,PPvsREal!$C$33,Eventos!T:T) -> 0 | U33: =SUMIF(Eventos!$B:$B,PPvsREal!$C$33,Eventos!U:U) -> 0 | V33: =SUMIF(Eventos!$B:$B,PPvsREal!$C$33,Eventos!V:V) -> 0 | W33: =SUMIF(Eventos!$B:$B,PPvsREal!$C$33,Eventos!W:W) -> 0 | X33: =SUMIF(Eventos!$B:$B,PPvsREal!$C$33,Eventos!X:X) -> 0 | Y33: =SUMIF(Eventos!$B:$B,PPvsREal!$C$33,Eventos!Y:Y) -> 0 | Z33: =SUMIF(Eventos!$B:$B,PPvsREal!$C$33,Eventos!Z:Z) -> 0 | AA33: =SUMIF(Eventos!$B:$B,PPvsREal!$C$33,Eventos!AA:AA) -> 0
B34: Eventos | C34: 405-013-000-00 | D34: =SUMIF(Eventos!$B:$B,PPvsREal!$C$34,Eventos!D:D) -> 0 | E34: =SUMIF(Eventos!$B:$B,PPvsREal!$C$34,Eventos!E:E) -> 0 | F34: =SUMIF(Eventos!$B:$B,PPvsREal!$C$34,Eventos!F:F) -> 0 | G34: =SUMIF(Eventos!$B:$B,PPvsREal!$C$34,Eventos!G:G) -> 0 | H34: =SUMIF(Eventos!$B:$B,PPvsREal!$C$34,Eventos!H:H) -> 0 | I34: =SUMIF(Eventos!$B:$B,PPvsREal!$C$34,Eventos!I:I) -> 0 | J34: =SUMIF(Eventos!$B:$B,PPvsREal!$C$34,Eventos!J:J) -> 235000 | K34: =SUMIF(Eventos!$B:$B,PPvsREal!$C$34,Eventos!K:K) -> 0 | L34: =SUMIF(Eventos!$B:$B,PPvsREal!$C$34,Eventos!L:L) -> 0 | M34: =SUMIF(Eventos!$B:$B,PPvsREal!$C$34,Eventos!M:M) -> 0 | N34: =SUMIF(Eventos!$B:$B,PPvsREal!$C$34,Eventos!N:N) -> 0 | O34: =SUMIF(Eventos!$B:$B,PPvsREal!$C$34,Eventos!O:O) -> 160200 | P34: =SUMIF(Eventos!$B:$B,PPvsREal!$C$34,Eventos!P:P) -> 0 | Q34: =SUMIF(Eventos!$B:$B,PPvsREal!$C$34,Eventos!Q:Q) -> 46800 | R34: =SUMIF(Eventos!$B:$B,PPvsREal!$C$34,Eventos!R:R) -> 0 | S34: =SUMIF(Eventos!$B:$B,PPvsREal!$C$34,Eventos!S:S) -> 0 | T34: =SUMIF(Eventos!$B:$B,PPvsREal!$C$34,Eventos!T:T) -> 0 | U34: =SUMIF(Eventos!$B:$B,PPvsREal!$C$34,Eventos!U:U) -> 0 | V34: =SUMIF(Eventos!$B:$B,PPvsREal!$C$34,Eventos!V:V) -> 0 | W34: =SUMIF(Eventos!$B:$B,PPvsREal!$C$34,Eventos!W:W) -> 0 | X34: =SUMIF(Eventos!$B:$B,PPvsREal!$C$34,Eventos!X:X) -> 0 | Y34: =SUMIF(Eventos!$B:$B,PPvsREal!$C$34,Eventos!Y:Y) -> 0 | Z34: =SUMIF(Eventos!$B:$B,PPvsREal!$C$34,Eventos!Z:Z) -> 0 | AA34: =SUMIF(Eventos!$B:$B,PPvsREal!$C$34,Eventos!AA:AA) -> 0
B35: Eventos | C35: 405-008-000-00 | D35: =SUMIF(Eventos!$B:$B,PPvsREal!$C$35,Eventos!D:D) -> 0 | E35: =SUMIF(Eventos!$B:$B,PPvsREal!$C$35,Eventos!E:E) -> 0 | F35: =SUMIF(Eventos!$B:$B,PPvsREal!$C$35,Eventos!F:F) -> 0 | G35: =SUMIF(Eventos!$B:$B,PPvsREal!$C$35,Eventos!G:G) -> 0 | H35: =SUMIF(Eventos!$B:$B,PPvsREal!$C$35,Eventos!H:H) -> 0 | I35: =SUMIF(Eventos!$B:$B,PPvsREal!$C$35,Eventos!I:I) -> 0 | J35: =SUMIF(Eventos!$B:$B,PPvsREal!$C$35,Eventos!J:J) -> 0 | K35: =SUMIF(Eventos!$B:$B,PPvsREal!$C$35,Eventos!K:K) -> 0 | L35: =SUMIF(Eventos!$B:$B,PPvsREal!$C$35,Eventos!L:L) -> 0 | M35: =SUMIF(Eventos!$B:$B,PPvsREal!$C$35,Eventos!M:M) -> 0 | N35: =SUMIF(Eventos!$B:$B,PPvsREal!$C$35,Eventos!N:N) -> 0 | O35: =SUMIF(Eventos!$B:$B,PPvsREal!$C$35,Eventos!O:O) -> 0 | P35: =SUMIF(Eventos!$B:$B,PPvsREal!$C$35,Eventos!P:P) -> 85000 | Q35: =SUMIF(Eventos!$B:$B,PPvsREal!$C$35,Eventos!Q:Q) -> 0 | R35: =SUMIF(Eventos!$B:$B,PPvsREal!$C$35,Eventos!R:R) -> 0 | S35: =SUMIF(Eventos!$B:$B,PPvsREal!$C$35,Eventos!S:S) -> 0 | T35: =SUMIF(Eventos!$B:$B,PPvsREal!$C$35,Eventos!T:T) -> 0 | U35: =SUMIF(Eventos!$B:$B,PPvsREal!$C$35,Eventos!U:U) -> 0 | V35: =SUMIF(Eventos!$B:$B,PPvsREal!$C$35,Eventos!V:V) -> 0 | W35: =SUMIF(Eventos!$B:$B,PPvsREal!$C$35,Eventos!W:W) -> 0 | X35: =SUMIF(Eventos!$B:$B,PPvsREal!$C$35,Eventos!X:X) -> 0 | Y35: =SUMIF(Eventos!$B:$B,PPvsREal!$C$35,Eventos!Y:Y) -> 0 | Z35: =SUMIF(Eventos!$B:$B,PPvsREal!$C$35,Eventos!Z:Z) -> 0 | AA35: =SUMIF(Eventos!$B:$B,PPvsREal!$C$35,Eventos!AA:AA) -> 0
B36: Eventos | C36: 405-003-000-00 | D36: =SUMIF(Eventos!$B:$B,PPvsREal!$C$36,Eventos!D:D) -> 0 | E36: =SUMIF(Eventos!$B:$B,PPvsREal!$C$36,Eventos!E:E) -> 42382.76 | F36: =SUMIF(Eventos!$B:$B,PPvsREal!$C$36,Eventos!F:F) -> 0 | G36: =SUMIF(Eventos!$B:$B,PPvsREal!$C$36,Eventos!G:G) -> 52850 | H36: =SUMIF(Eventos!$B:$B,PPvsREal!$C$36,Eventos!H:H) -> 0 | I36: =SUMIF(Eventos!$B:$B,PPvsREal!$C$36,Eventos!I:I) -> 850 | J36: =SUMIF(Eventos!$B:$B,PPvsREal!$C$36,Eventos!J:J) -> 0 | K36: =SUMIF(Eventos!$B:$B,PPvsREal!$C$36,Eventos!K:K) -> 0 | L36: =SUMIF(Eventos!$B:$B,PPvsREal!$C$36,Eventos!L:L) -> 0 | M36: =SUMIF(Eventos!$B:$B,PPvsREal!$C$36,Eventos!M:M) -> 0 | N36: =SUMIF(Eventos!$B:$B,PPvsREal!$C$36,Eventos!N:N) -> 0 | O36: =SUMIF(Eventos!$B:$B,PPvsREal!$C$36,Eventos!O:O) -> 0 | P36: =SUMIF(Eventos!$B:$B,PPvsREal!$C$36,Eventos!P:P) -> 0 | Q36: =SUMIF(Eventos!$B:$B,PPvsREal!$C$36,Eventos!Q:Q) -> 0 | R36: =SUMIF(Eventos!$B:$B,PPvsREal!$C$36,Eventos!R:R) -> 140000 | S36: =SUMIF(Eventos!$B:$B,PPvsREal!$C$36,Eventos!S:S) -> 0 | T36: =SUMIF(Eventos!$B:$B,PPvsREal!$C$36,Eventos!T:T) -> 0 | U36: =SUMIF(Eventos!$B:$B,PPvsREal!$C$36,Eventos!U:U) -> 0 | V36: =SUMIF(Eventos!$B:$B,PPvsREal!$C$36,Eventos!V:V) -> 0 | W36: =SUMIF(Eventos!$B:$B,PPvsREal!$C$36,Eventos!W:W) -> 0 | X36: =SUMIF(Eventos!$B:$B,PPvsREal!$C$36,Eventos!X:X) -> 0 | Y36: =SUMIF(Eventos!$B:$B,PPvsREal!$C$36,Eventos!Y:Y) -> 0 | Z36: =SUMIF(Eventos!$B:$B,PPvsREal!$C$36,Eventos!Z:Z) -> 0 | AA36: =SUMIF(Eventos!$B:$B,PPvsREal!$C$36,Eventos!AA:AA) -> 0
B37: Eventos | C37: 405-009-000-00 | D37: =SUMIF(Eventos!$B:$B,PPvsREal!$C$37,Eventos!D:D) -> 0 | E37: =SUMIF(Eventos!$B:$B,PPvsREal!$C$37,Eventos!E:E) -> 0 | F37: =SUMIF(Eventos!$B:$B,PPvsREal!$C$37,Eventos!F:F) -> 0 | G37: =SUMIF(Eventos!$B:$B,PPvsREal!$C$37,Eventos!G:G) -> 0 | H37: =SUMIF(Eventos!$B:$B,PPvsREal!$C$37,Eventos!H:H) -> 0 | I37: =SUMIF(Eventos!$B:$B,PPvsREal!$C$37,Eventos!I:I) -> 0 | J37: =SUMIF(Eventos!$B:$B,PPvsREal!$C$37,Eventos!J:J) -> 0 | K37: =SUMIF(Eventos!$B:$B,PPvsREal!$C$37,Eventos!K:K) -> 0 | L37: =SUMIF(Eventos!$B:$B,PPvsREal!$C$37,Eventos!L:L) -> 0 | M37: =SUMIF(Eventos!$B:$B,PPvsREal!$C$37,Eventos!M:M) -> 0 | N37: =SUMIF(Eventos!$B:$B,PPvsREal!$C$37,Eventos!N:N) -> 0 | O37: =SUMIF(Eventos!$B:$B,PPvsREal!$C$37,Eventos!O:O) -> 0 | P37: =SUMIF(Eventos!$B:$B,PPvsREal!$C$37,Eventos!P:P) -> 0 | Q37: =SUMIF(Eventos!$B:$B,PPvsREal!$C$37,Eventos!Q:Q) -> 0 | R37: =SUMIF(Eventos!$B:$B,PPvsREal!$C$37,Eventos!R:R) -> 0 | S37: =SUMIF(Eventos!$B:$B,PPvsREal!$C$37,Eventos!S:S) -> 0 | T37: =SUMIF(Eventos!$B:$B,PPvsREal!$C$37,Eventos!T:T) -> 860000 | U37: =SUMIF(Eventos!$B:$B,PPvsREal!$C$37,Eventos!U:U) -> 0 | V37: =SUMIF(Eventos!$B:$B,PPvsREal!$C$37,Eventos!V:V) -> 0 | W37: =SUMIF(Eventos!$B:$B,PPvsREal!$C$37,Eventos!W:W) -> 0 | X37: =SUMIF(Eventos!$B:$B,PPvsREal!$C$37,Eventos!X:X) -> 0 | Y37: =SUMIF(Eventos!$B:$B,PPvsREal!$C$37,Eventos!Y:Y) -> 0 | Z37: =SUMIF(Eventos!$B:$B,PPvsREal!$C$37,Eventos!Z:Z) -> 0 | AA37: =SUMIF(Eventos!$B:$B,PPvsREal!$C$37,Eventos!AA:AA) -> 0
B38: Eventos | C38: 405-001-000-00 | D38: =SUMIF(Eventos!$B:$B,PPvsREal!$C$38,Eventos!D:D) -> 0 | E38: =SUMIF(Eventos!$B:$B,PPvsREal!$C$38,Eventos!E:E) -> 0 | F38: =SUMIF(Eventos!$B:$B,PPvsREal!$C$38,Eventos!F:F) -> 0 | G38: =SUMIF(Eventos!$B:$B,PPvsREal!$C$38,Eventos!G:G) -> 0 | H38: =SUMIF(Eventos!$B:$B,PPvsREal!$C$38,Eventos!H:H) -> 0 | I38: =SUMIF(Eventos!$B:$B,PPvsREal!$C$38,Eventos!I:I) -> 0 | J38: =SUMIF(Eventos!$B:$B,PPvsREal!$C$38,Eventos!J:J) -> 0 | K38: =SUMIF(Eventos!$B:$B,PPvsREal!$C$38,Eventos!K:K) -> 0 | L38: =SUMIF(Eventos!$B:$B,PPvsREal!$C$38,Eventos!L:L) -> 0 | M38: =SUMIF(Eventos!$B:$B,PPvsREal!$C$38,Eventos!M:M) -> 0 | N38: =SUMIF(Eventos!$B:$B,PPvsREal!$C$38,Eventos!N:N) -> 0 | O38: =SUMIF(Eventos!$B:$B,PPvsREal!$C$38,Eventos!O:O) -> 0 | P38: =SUMIF(Eventos!$B:$B,PPvsREal!$C$38,Eventos!P:P) -> 0 | Q38: =SUMIF(Eventos!$B:$B,PPvsREal!$C$38,Eventos!Q:Q) -> 0 | R38: =SUMIF(Eventos!$B:$B,PPvsREal!$C$38,Eventos!R:R) -> 0 | S38: =SUMIF(Eventos!$B:$B,PPvsREal!$C$38,Eventos!S:S) -> 0 | T38: =SUMIF(Eventos!$B:$B,PPvsREal!$C$38,Eventos!T:T) -> 0 | U38: =SUMIF(Eventos!$B:$B,PPvsREal!$C$38,Eventos!U:U) -> 0 | V38: =SUMIF(Eventos!$B:$B,PPvsREal!$C$38,Eventos!V:V) -> 1030000 | W38: =SUMIF(Eventos!$B:$B,PPvsREal!$C$38,Eventos!W:W) -> 0 | X38: =SUMIF(Eventos!$B:$B,PPvsREal!$C$38,Eventos!X:X) -> 0 | Y38: =SUMIF(Eventos!$B:$B,PPvsREal!$C$38,Eventos!Y:Y) -> 0 | Z38: =SUMIF(Eventos!$B:$B,PPvsREal!$C$38,Eventos!Z:Z) -> 0 | AA38: =SUMIF(Eventos!$B:$B,PPvsREal!$C$38,Eventos!AA:AA) -> 0
B39: Eventos | C39: 405-002-000-00 | D39: =SUMIF(Eventos!$B:$B,PPvsREal!$C$39,Eventos!D:D) -> 0 | E39: =SUMIF(Eventos!$B:$B,PPvsREal!$C$39,Eventos!E:E) -> 0 | F39: =SUMIF(Eventos!$B:$B,PPvsREal!$C$39,Eventos!F:F) -> 0 | G39: =SUMIF(Eventos!$B:$B,PPvsREal!$C$39,Eventos!G:G) -> 0 | H39: =SUMIF(Eventos!$B:$B,PPvsREal!$C$39,Eventos!H:H) -> 0 | I39: =SUMIF(Eventos!$B:$B,PPvsREal!$C$39,Eventos!I:I) -> 0 | J39: =SUMIF(Eventos!$B:$B,PPvsREal!$C$39,Eventos!J:J) -> 0 | K39: =SUMIF(Eventos!$B:$B,PPvsREal!$C$39,Eventos!K:K) -> 0 | L39: =SUMIF(Eventos!$B:$B,PPvsREal!$C$39,Eventos!L:L) -> 0 | M39: =SUMIF(Eventos!$B:$B,PPvsREal!$C$39,Eventos!M:M) -> 0 | N39: =SUMIF(Eventos!$B:$B,PPvsREal!$C$39,Eventos!N:N) -> 0 | O39: =SUMIF(Eventos!$B:$B,PPvsREal!$C$39,Eventos!O:O) -> 0 | P39: =SUMIF(Eventos!$B:$B,PPvsREal!$C$39,Eventos!P:P) -> 0 | Q39: =SUMIF(Eventos!$B:$B,PPvsREal!$C$39,Eventos!Q:Q) -> 0 | R39: =SUMIF(Eventos!$B:$B,PPvsREal!$C$39,Eventos!R:R) -> 0 | S39: =SUMIF(Eventos!$B:$B,PPvsREal!$C$39,Eventos!S:S) -> 0 | T39: =SUMIF(Eventos!$B:$B,PPvsREal!$C$39,Eventos!T:T) -> 0 | U39: =SUMIF(Eventos!$B:$B,PPvsREal!$C$39,Eventos!U:U) -> 0 | V39: =SUMIF(Eventos!$B:$B,PPvsREal!$C$39,Eventos!V:V) -> 0 | W39: =SUMIF(Eventos!$B:$B,PPvsREal!$C$39,Eventos!W:W) -> 0 | X39: =SUMIF(Eventos!$B:$B,PPvsREal!$C$39,Eventos!X:X) -> 1100000 | Y39: =SUMIF(Eventos!$B:$B,PPvsREal!$C$39,Eventos!Y:Y) -> 0 | Z39: =SUMIF(Eventos!$B:$B,PPvsREal!$C$39,Eventos!Z:Z) -> 0 | AA39: =SUMIF(Eventos!$B:$B,PPvsREal!$C$39,Eventos!AA:AA) -> 0
B40: Eventos | C40: 701-010-000-00 | D40: =SUMIF(Eventos!$B:$B,PPvsREal!$C$40,Eventos!D:D) -> 40000 | E40: =SUMIF(Eventos!$B:$B,PPvsREal!$C$40,Eventos!E:E) -> 0 | F40: =SUMIF(Eventos!$B:$B,PPvsREal!$C$40,Eventos!F:F) -> 53045 | G40: =SUMIF(Eventos!$B:$B,PPvsREal!$C$40,Eventos!G:G) -> 0 | H40: =SUMIF(Eventos!$B:$B,PPvsREal!$C$40,Eventos!H:H) -> 35000 | I40: =SUMIF(Eventos!$B:$B,PPvsREal!$C$40,Eventos!I:I) -> 14340 | J40: =SUMIF(Eventos!$B:$B,PPvsREal!$C$40,Eventos!J:J) -> 0 | K40: =SUMIF(Eventos!$B:$B,PPvsREal!$C$40,Eventos!K:K) -> 0 | L40: =SUMIF(Eventos!$B:$B,PPvsREal!$C$40,Eventos!L:L) -> 0 | M40: =SUMIF(Eventos!$B:$B,PPvsREal!$C$40,Eventos!M:M) -> 10309.84 | N40: =SUMIF(Eventos!$B:$B,PPvsREal!$C$40,Eventos!N:N) -> 125000 | O40: =SUMIF(Eventos!$B:$B,PPvsREal!$C$40,Eventos!O:O) -> 0 | P40: =SUMIF(Eventos!$B:$B,PPvsREal!$C$40,Eventos!P:P) -> 0 | Q40: =SUMIF(Eventos!$B:$B,PPvsREal!$C$40,Eventos!Q:Q) -> 0 | R40: =SUMIF(Eventos!$B:$B,PPvsREal!$C$40,Eventos!R:R) -> 0 | S40: =SUMIF(Eventos!$B:$B,PPvsREal!$C$40,Eventos!S:S) -> 0 | T40: =SUMIF(Eventos!$B:$B,PPvsREal!$C$40,Eventos!T:T) -> 0 | U40: =SUMIF(Eventos!$B:$B,PPvsREal!$C$40,Eventos!U:U) -> 0 | V40: =SUMIF(Eventos!$B:$B,PPvsREal!$C$40,Eventos!V:V) -> 0 | W40: =SUMIF(Eventos!$B:$B,PPvsREal!$C$40,Eventos!W:W) -> 0 | X40: =SUMIF(Eventos!$B:$B,PPvsREal!$C$40,Eventos!X:X) -> 0 | Y40: =SUMIF(Eventos!$B:$B,PPvsREal!$C$40,Eventos!Y:Y) -> 0 | Z40: =SUMIF(Eventos!$B:$B,PPvsREal!$C$40,Eventos!Z:Z) -> 0 | AA40: =SUMIF(Eventos!$B:$B,PPvsREal!$C$40,Eventos!AA:AA) -> 0
B41: Eventos | C41: 701-014-000-00 | D41: =SUMIF(Eventos!$B:$B,PPvsREal!$C$41,Eventos!D:D) -> 0 | E41: =SUMIF(Eventos!$B:$B,PPvsREal!$C$41,Eventos!E:E) -> 0 | F41: =SUMIF(Eventos!$B:$B,PPvsREal!$C$41,Eventos!F:F) -> 38000 | G41: =SUMIF(Eventos!$B:$B,PPvsREal!$C$41,Eventos!G:G) -> 46790.9 | H41: =SUMIF(Eventos!$B:$B,PPvsREal!$C$41,Eventos!H:H) -> 0 | I41: =SUMIF(Eventos!$B:$B,PPvsREal!$C$41,Eventos!I:I) -> -517.24 | J41: =SUMIF(Eventos!$B:$B,PPvsREal!$C$41,Eventos!J:J) -> 0 | K41: =SUMIF(Eventos!$B:$B,PPvsREal!$C$41,Eventos!K:K) -> 0 | L41: =SUMIF(Eventos!$B:$B,PPvsREal!$C$41,Eventos!L:L) -> 0 | M41: =SUMIF(Eventos!$B:$B,PPvsREal!$C$41,Eventos!M:M) -> 0 | N41: =SUMIF(Eventos!$B:$B,PPvsREal!$C$41,Eventos!N:N) -> 0 | O41: =SUMIF(Eventos!$B:$B,PPvsREal!$C$41,Eventos!O:O) -> 0 | P41: =SUMIF(Eventos!$B:$B,PPvsREal!$C$41,Eventos!P:P) -> 0 | Q41: =SUMIF(Eventos!$B:$B,PPvsREal!$C$41,Eventos!Q:Q) -> 0 | R41: =SUMIF(Eventos!$B:$B,PPvsREal!$C$41,Eventos!R:R) -> 0 | S41: =SUMIF(Eventos!$B:$B,PPvsREal!$C$41,Eventos!S:S) -> 0 | T41: =SUMIF(Eventos!$B:$B,PPvsREal!$C$41,Eventos!T:T) -> 0 | U41: =SUMIF(Eventos!$B:$B,PPvsREal!$C$41,Eventos!U:U) -> 0 | V41: =SUMIF(Eventos!$B:$B,PPvsREal!$C$41,Eventos!V:V) -> 0 | W41: =SUMIF(Eventos!$B:$B,PPvsREal!$C$41,Eventos!W:W) -> 0 | X41: =SUMIF(Eventos!$B:$B,PPvsREal!$C$41,Eventos!X:X) -> 0 | Y41: =SUMIF(Eventos!$B:$B,PPvsREal!$C$41,Eventos!Y:Y) -> 0 | Z41: =SUMIF(Eventos!$B:$B,PPvsREal!$C$41,Eventos!Z:Z) -> 0 | AA41: =SUMIF(Eventos!$B:$B,PPvsREal!$C$41,Eventos!AA:AA) -> 0
B42: Eventos | C42: 701-009-000-00 | D42: =SUMIF(Eventos!$B:$B,PPvsREal!$C$42,Eventos!D:D) -> 0 | E42: =SUMIF(Eventos!$B:$B,PPvsREal!$C$42,Eventos!E:E) -> 0 | F42: =SUMIF(Eventos!$B:$B,PPvsREal!$C$42,Eventos!F:F) -> 60000 | G42: =SUMIF(Eventos!$B:$B,PPvsREal!$C$42,Eventos!G:G) -> 0 | H42: =SUMIF(Eventos!$B:$B,PPvsREal!$C$42,Eventos!H:H) -> 0 | I42: =SUMIF(Eventos!$B:$B,PPvsREal!$C$42,Eventos!I:I) -> 0 | J42: =SUMIF(Eventos!$B:$B,PPvsREal!$C$42,Eventos!J:J) -> 60000 | K42: =SUMIF(Eventos!$B:$B,PPvsREal!$C$42,Eventos!K:K) -> 0 | L42: =SUMIF(Eventos!$B:$B,PPvsREal!$C$42,Eventos!L:L) -> 100000 | M42: =SUMIF(Eventos!$B:$B,PPvsREal!$C$42,Eventos!M:M) -> 1419.03 | N42: =SUMIF(Eventos!$B:$B,PPvsREal!$C$42,Eventos!N:N) -> 60000 | O42: =SUMIF(Eventos!$B:$B,PPvsREal!$C$42,Eventos!O:O) -> 0 | P42: =SUMIF(Eventos!$B:$B,PPvsREal!$C$42,Eventos!P:P) -> 0 | Q42: =SUMIF(Eventos!$B:$B,PPvsREal!$C$42,Eventos!Q:Q) -> 1857.23 | R42: =SUMIF(Eventos!$B:$B,PPvsREal!$C$42,Eventos!R:R) -> 0 | S42: =SUMIF(Eventos!$B:$B,PPvsREal!$C$42,Eventos!S:S) -> 0 | T42: =SUMIF(Eventos!$B:$B,PPvsREal!$C$42,Eventos!T:T) -> 60000 | U42: =SUMIF(Eventos!$B:$B,PPvsREal!$C$42,Eventos!U:U) -> 0 | V42: =SUMIF(Eventos!$B:$B,PPvsREal!$C$42,Eventos!V:V) -> 0 | W42: =SUMIF(Eventos!$B:$B,PPvsREal!$C$42,Eventos!W:W) -> 0 | X42: =SUMIF(Eventos!$B:$B,PPvsREal!$C$42,Eventos!X:X) -> 0 | Y42: =SUMIF(Eventos!$B:$B,PPvsREal!$C$42,Eventos!Y:Y) -> 0 | Z42: =SUMIF(Eventos!$B:$B,PPvsREal!$C$42,Eventos!Z:Z) -> 0 | AA42: =SUMIF(Eventos!$B:$B,PPvsREal!$C$42,Eventos!AA:AA) -> 0
B43: Eventos | C43: 701-015-000-00 | D43: =SUMIF(Eventos!$B:$B,PPvsREal!$C$43,Eventos!D:D) -> 0 | E43: =SUMIF(Eventos!$B:$B,PPvsREal!$C$43,Eventos!E:E) -> 0 | F43: =SUMIF(Eventos!$B:$B,PPvsREal!$C$43,Eventos!F:F) -> 0 | G43: =SUMIF(Eventos!$B:$B,PPvsREal!$C$43,Eventos!G:G) -> 0 | H43: =SUMIF(Eventos!$B:$B,PPvsREal!$C$43,Eventos!H:H) -> 0 | I43: =SUMIF(Eventos!$B:$B,PPvsREal!$C$43,Eventos!I:I) -> 0 | J43: =SUMIF(Eventos!$B:$B,PPvsREal!$C$43,Eventos!J:J) -> 0 | K43: =SUMIF(Eventos!$B:$B,PPvsREal!$C$43,Eventos!K:K) -> 0 | L43: =SUMIF(Eventos!$B:$B,PPvsREal!$C$43,Eventos!L:L) -> 0 | M43: =SUMIF(Eventos!$B:$B,PPvsREal!$C$43,Eventos!M:M) -> 0 | N43: =SUMIF(Eventos!$B:$B,PPvsREal!$C$43,Eventos!N:N) -> 0 | O43: =SUMIF(Eventos!$B:$B,PPvsREal!$C$43,Eventos!O:O) -> 0 | P43: =SUMIF(Eventos!$B:$B,PPvsREal!$C$43,Eventos!P:P) -> 0 | Q43: =SUMIF(Eventos!$B:$B,PPvsREal!$C$43,Eventos!Q:Q) -> 0 | R43: =SUMIF(Eventos!$B:$B,PPvsREal!$C$43,Eventos!R:R) -> 0 | S43: =SUMIF(Eventos!$B:$B,PPvsREal!$C$43,Eventos!S:S) -> 0 | T43: =SUMIF(Eventos!$B:$B,PPvsREal!$C$43,Eventos!T:T) -> 0 | U43: =SUMIF(Eventos!$B:$B,PPvsREal!$C$43,Eventos!U:U) -> 0 | V43: =SUMIF(Eventos!$B:$B,PPvsREal!$C$43,Eventos!V:V) -> 0 | W43: =SUMIF(Eventos!$B:$B,PPvsREal!$C$43,Eventos!W:W) -> 0 | X43: =SUMIF(Eventos!$B:$B,PPvsREal!$C$43,Eventos!X:X) -> 0 | Y43: =SUMIF(Eventos!$B:$B,PPvsREal!$C$43,Eventos!Y:Y) -> 0 | Z43: =SUMIF(Eventos!$B:$B,PPvsREal!$C$43,Eventos!Z:Z) -> 0 | AA43: =SUMIF(Eventos!$B:$B,PPvsREal!$C$43,Eventos!AA:AA) -> 0
B44: Eventos | C44: 701-012-000-00 | D44: =SUMIF(Eventos!$B:$B,PPvsREal!$C$44,Eventos!D:D) -> 0 | E44: =SUMIF(Eventos!$B:$B,PPvsREal!$C$44,Eventos!E:E) -> 0 | F44: =SUMIF(Eventos!$B:$B,PPvsREal!$C$44,Eventos!F:F) -> 0 | G44: =SUMIF(Eventos!$B:$B,PPvsREal!$C$44,Eventos!G:G) -> 0 | H44: =SUMIF(Eventos!$B:$B,PPvsREal!$C$44,Eventos!H:H) -> 0 | I44: =SUMIF(Eventos!$B:$B,PPvsREal!$C$44,Eventos!I:I) -> 0 | J44: =SUMIF(Eventos!$B:$B,PPvsREal!$C$44,Eventos!J:J) -> 130000 | K44: =SUMIF(Eventos!$B:$B,PPvsREal!$C$44,Eventos!K:K) -> 0 | L44: =SUMIF(Eventos!$B:$B,PPvsREal!$C$44,Eventos!L:L) -> 0 | M44: =SUMIF(Eventos!$B:$B,PPvsREal!$C$44,Eventos!M:M) -> 0 | N44: =SUMIF(Eventos!$B:$B,PPvsREal!$C$44,Eventos!N:N) -> 0 | O44: =SUMIF(Eventos!$B:$B,PPvsREal!$C$44,Eventos!O:O) -> 67650.68 | P44: =SUMIF(Eventos!$B:$B,PPvsREal!$C$44,Eventos!P:P) -> 0 | Q44: =SUMIF(Eventos!$B:$B,PPvsREal!$C$44,Eventos!Q:Q) -> 68842.52 | R44: =SUMIF(Eventos!$B:$B,PPvsREal!$C$44,Eventos!R:R) -> 0 | S44: =SUMIF(Eventos!$B:$B,PPvsREal!$C$44,Eventos!S:S) -> 0 | T44: =SUMIF(Eventos!$B:$B,PPvsREal!$C$44,Eventos!T:T) -> 0 | U44: =SUMIF(Eventos!$B:$B,PPvsREal!$C$44,Eventos!U:U) -> 0 | V44: =SUMIF(Eventos!$B:$B,PPvsREal!$C$44,Eventos!V:V) -> 0 | W44: =SUMIF(Eventos!$B:$B,PPvsREal!$C$44,Eventos!W:W) -> 0 | X44: =SUMIF(Eventos!$B:$B,PPvsREal!$C$44,Eventos!X:X) -> 0 | Y44: =SUMIF(Eventos!$B:$B,PPvsREal!$C$44,Eventos!Y:Y) -> 0 | Z44: =SUMIF(Eventos!$B:$B,PPvsREal!$C$44,Eventos!Z:Z) -> 0 | AA44: =SUMIF(Eventos!$B:$B,PPvsREal!$C$44,Eventos!AA:AA) -> 0
B45: Eventos | C45: 701-008-000-00 | D45: =SUMIF(Eventos!$B:$B,PPvsREal!$C$45,Eventos!D:D) -> 0 | E45: =SUMIF(Eventos!$B:$B,PPvsREal!$C$45,Eventos!E:E) -> 0 | F45: =SUMIF(Eventos!$B:$B,PPvsREal!$C$45,Eventos!F:F) -> 0 | G45: =SUMIF(Eventos!$B:$B,PPvsREal!$C$45,Eventos!G:G) -> 0 | H45: =SUMIF(Eventos!$B:$B,PPvsREal!$C$45,Eventos!H:H) -> 0 | I45: =SUMIF(Eventos!$B:$B,PPvsREal!$C$45,Eventos!I:I) -> 0 | J45: =SUMIF(Eventos!$B:$B,PPvsREal!$C$45,Eventos!J:J) -> 0 | K45: =SUMIF(Eventos!$B:$B,PPvsREal!$C$45,Eventos!K:K) -> 0 | L45: =SUMIF(Eventos!$B:$B,PPvsREal!$C$45,Eventos!L:L) -> 0 | M45: =SUMIF(Eventos!$B:$B,PPvsREal!$C$45,Eventos!M:M) -> 0 | N45: =SUMIF(Eventos!$B:$B,PPvsREal!$C$45,Eventos!N:N) -> 0 | O45: =SUMIF(Eventos!$B:$B,PPvsREal!$C$45,Eventos!O:O) -> 0 | P45: =SUMIF(Eventos!$B:$B,PPvsREal!$C$45,Eventos!P:P) -> 55000 | Q45: =SUMIF(Eventos!$B:$B,PPvsREal!$C$45,Eventos!Q:Q) -> 0 | R45: =SUMIF(Eventos!$B:$B,PPvsREal!$C$45,Eventos!R:R) -> 0 | S45: =SUMIF(Eventos!$B:$B,PPvsREal!$C$45,Eventos!S:S) -> 0 | T45: =SUMIF(Eventos!$B:$B,PPvsREal!$C$45,Eventos!T:T) -> 0 | U45: =SUMIF(Eventos!$B:$B,PPvsREal!$C$45,Eventos!U:U) -> 0 | V45: =SUMIF(Eventos!$B:$B,PPvsREal!$C$45,Eventos!V:V) -> 0 | W45: =SUMIF(Eventos!$B:$B,PPvsREal!$C$45,Eventos!W:W) -> 0 | X45: =SUMIF(Eventos!$B:$B,PPvsREal!$C$45,Eventos!X:X) -> 0 | Y45: =SUMIF(Eventos!$B:$B,PPvsREal!$C$45,Eventos!Y:Y) -> 0 | Z45: =SUMIF(Eventos!$B:$B,PPvsREal!$C$45,Eventos!Z:Z) -> 0 | AA45: =SUMIF(Eventos!$B:$B,PPvsREal!$C$45,Eventos!AA:AA) -> 0
B46: Eventos | C46: 701-007-000-00 | D46: =SUMIF(Eventos!$B:$B,PPvsREal!$C$46,Eventos!D:D) -> 0 | E46: =SUMIF(Eventos!$B:$B,PPvsREal!$C$46,Eventos!E:E) -> 24047.83 | F46: =SUMIF(Eventos!$B:$B,PPvsREal!$C$46,Eventos!F:F) -> 0 | G46: =SUMIF(Eventos!$B:$B,PPvsREal!$C$46,Eventos!G:G) -> 56472.77 | H46: =SUMIF(Eventos!$B:$B,PPvsREal!$C$46,Eventos!H:H) -> 0 | I46: =SUMIF(Eventos!$B:$B,PPvsREal!$C$46,Eventos!I:I) -> 1118.97 | J46: =SUMIF(Eventos!$B:$B,PPvsREal!$C$46,Eventos!J:J) -> 0 | K46: =SUMIF(Eventos!$B:$B,PPvsREal!$C$46,Eventos!K:K) -> 0 | L46: =SUMIF(Eventos!$B:$B,PPvsREal!$C$46,Eventos!L:L) -> 0 | M46: =SUMIF(Eventos!$B:$B,PPvsREal!$C$46,Eventos!M:M) -> 0 | N46: =SUMIF(Eventos!$B:$B,PPvsREal!$C$46,Eventos!N:N) -> 0 | O46: =SUMIF(Eventos!$B:$B,PPvsREal!$C$46,Eventos!O:O) -> 0 | P46: =SUMIF(Eventos!$B:$B,PPvsREal!$C$46,Eventos!P:P) -> 0 | Q46: =SUMIF(Eventos!$B:$B,PPvsREal!$C$46,Eventos!Q:Q) -> 0 | R46: =SUMIF(Eventos!$B:$B,PPvsREal!$C$46,Eventos!R:R) -> 110000 | S46: =SUMIF(Eventos!$B:$B,PPvsREal!$C$46,Eventos!S:S) -> 0 | T46: =SUMIF(Eventos!$B:$B,PPvsREal!$C$46,Eventos!T:T) -> 0 | U46: =SUMIF(Eventos!$B:$B,PPvsREal!$C$46,Eventos!U:U) -> 0 | V46: =SUMIF(Eventos!$B:$B,PPvsREal!$C$46,Eventos!V:V) -> 0 | W46: =SUMIF(Eventos!$B:$B,PPvsREal!$C$46,Eventos!W:W) -> 0 | X46: =SUMIF(Eventos!$B:$B,PPvsREal!$C$46,Eventos!X:X) -> 0 | Y46: =SUMIF(Eventos!$B:$B,PPvsREal!$C$46,Eventos!Y:Y) -> 0 | Z46: =SUMIF(Eventos!$B:$B,PPvsREal!$C$46,Eventos!Z:Z) -> 0 | AA46: =SUMIF(Eventos!$B:$B,PPvsREal!$C$46,Eventos!AA:AA) -> 0
B47: Eventos | C47: 701-011-000-00 | D47: =SUMIF(Eventos!$B:$B,PPvsREal!$C$47,Eventos!D:D) -> 0 | E47: =SUMIF(Eventos!$B:$B,PPvsREal!$C$47,Eventos!E:E) -> 0 | F47: =SUMIF(Eventos!$B:$B,PPvsREal!$C$47,Eventos!F:F) -> 0 | G47: =SUMIF(Eventos!$B:$B,PPvsREal!$C$47,Eventos!G:G) -> 0 | H47: =SUMIF(Eventos!$B:$B,PPvsREal!$C$47,Eventos!H:H) -> 0 | I47: =SUMIF(Eventos!$B:$B,PPvsREal!$C$47,Eventos!I:I) -> 0 | J47: =SUMIF(Eventos!$B:$B,PPvsREal!$C$47,Eventos!J:J) -> 0 | K47: =SUMIF(Eventos!$B:$B,PPvsREal!$C$47,Eventos!K:K) -> 0 | L47: =SUMIF(Eventos!$B:$B,PPvsREal!$C$47,Eventos!L:L) -> 0 | M47: =SUMIF(Eventos!$B:$B,PPvsREal!$C$47,Eventos!M:M) -> 0 | N47: =SUMIF(Eventos!$B:$B,PPvsREal!$C$47,Eventos!N:N) -> 0 | O47: =SUMIF(Eventos!$B:$B,PPvsREal!$C$47,Eventos!O:O) -> 0 | P47: =SUMIF(Eventos!$B:$B,PPvsREal!$C$47,Eventos!P:P) -> 0 | Q47: =SUMIF(Eventos!$B:$B,PPvsREal!$C$47,Eventos!Q:Q) -> 0 | R47: =SUMIF(Eventos!$B:$B,PPvsREal!$C$47,Eventos!R:R) -> 0 | S47: =SUMIF(Eventos!$B:$B,PPvsREal!$C$47,Eventos!S:S) -> 0 | T47: =SUMIF(Eventos!$B:$B,PPvsREal!$C$47,Eventos!T:T) -> 630000 | U47: =SUMIF(Eventos!$B:$B,PPvsREal!$C$47,Eventos!U:U) -> 0 | V47: =SUMIF(Eventos!$B:$B,PPvsREal!$C$47,Eventos!V:V) -> 0 | W47: =SUMIF(Eventos!$B:$B,PPvsREal!$C$47,Eventos!W:W) -> 0 | X47: =SUMIF(Eventos!$B:$B,PPvsREal!$C$47,Eventos!X:X) -> 0 | Y47: =SUMIF(Eventos!$B:$B,PPvsREal!$C$47,Eventos!Y:Y) -> 0 | Z47: =SUMIF(Eventos!$B:$B,PPvsREal!$C$47,Eventos!Z:Z) -> 0 | AA47: =SUMIF(Eventos!$B:$B,PPvsREal!$C$47,Eventos!AA:AA) -> 0
B48: Eventos | C48: 701-001-000-00 | D48: =SUMIF(Eventos!$B:$B,PPvsREal!$C$48,Eventos!D:D) -> 0 | E48: =SUMIF(Eventos!$B:$B,PPvsREal!$C$48,Eventos!E:E) -> 0 | F48: =SUMIF(Eventos!$B:$B,PPvsREal!$C$48,Eventos!F:F) -> 0 | G48: =SUMIF(Eventos!$B:$B,PPvsREal!$C$48,Eventos!G:G) -> 0 | H48: =SUMIF(Eventos!$B:$B,PPvsREal!$C$48,Eventos!H:H) -> 0 | I48: =SUMIF(Eventos!$B:$B,PPvsREal!$C$48,Eventos!I:I) -> 0 | J48: =SUMIF(Eventos!$B:$B,PPvsREal!$C$48,Eventos!J:J) -> 0 | K48: =SUMIF(Eventos!$B:$B,PPvsREal!$C$48,Eventos!K:K) -> 0 | L48: =SUMIF(Eventos!$B:$B,PPvsREal!$C$48,Eventos!L:L) -> 0 | M48: =SUMIF(Eventos!$B:$B,PPvsREal!$C$48,Eventos!M:M) -> 0 | N48: =SUMIF(Eventos!$B:$B,PPvsREal!$C$48,Eventos!N:N) -> 0 | O48: =SUMIF(Eventos!$B:$B,PPvsREal!$C$48,Eventos!O:O) -> 0 | P48: =SUMIF(Eventos!$B:$B,PPvsREal!$C$48,Eventos!P:P) -> 0 | Q48: =SUMIF(Eventos!$B:$B,PPvsREal!$C$48,Eventos!Q:Q) -> 0 | R48: =SUMIF(Eventos!$B:$B,PPvsREal!$C$48,Eventos!R:R) -> 0 | S48: =SUMIF(Eventos!$B:$B,PPvsREal!$C$48,Eventos!S:S) -> 0 | T48: =SUMIF(Eventos!$B:$B,PPvsREal!$C$48,Eventos!T:T) -> 0 | U48: =SUMIF(Eventos!$B:$B,PPvsREal!$C$48,Eventos!U:U) -> 0 | V48: =SUMIF(Eventos!$B:$B,PPvsREal!$C$48,Eventos!V:V) -> 700000 | W48: =SUMIF(Eventos!$B:$B,PPvsREal!$C$48,Eventos!W:W) -> 0 | X48: =SUMIF(Eventos!$B:$B,PPvsREal!$C$48,Eventos!X:X) -> 0 | Y48: =SUMIF(Eventos!$B:$B,PPvsREal!$C$48,Eventos!Y:Y) -> 0 | Z48: =SUMIF(Eventos!$B:$B,PPvsREal!$C$48,Eventos!Z:Z) -> 0 | AA48: =SUMIF(Eventos!$B:$B,PPvsREal!$C$48,Eventos!AA:AA) -> 0
B49: Eventos | C49: 701-002-000-00 | D49: =SUMIF(Eventos!$B:$B,PPvsREal!$C$49,Eventos!D:D) -> 0 | E49: =SUMIF(Eventos!$B:$B,PPvsREal!$C$49,Eventos!E:E) -> 0 | F49: =SUMIF(Eventos!$B:$B,PPvsREal!$C$49,Eventos!F:F) -> 0 | G49: =SUMIF(Eventos!$B:$B,PPvsREal!$C$49,Eventos!G:G) -> 0 | H49: =SUMIF(Eventos!$B:$B,PPvsREal!$C$49,Eventos!H:H) -> 0 | I49: =SUMIF(Eventos!$B:$B,PPvsREal!$C$49,Eventos!I:I) -> 0 | J49: =SUMIF(Eventos!$B:$B,PPvsREal!$C$49,Eventos!J:J) -> 0 | K49: =SUMIF(Eventos!$B:$B,PPvsREal!$C$49,Eventos!K:K) -> 0 | L49: =SUMIF(Eventos!$B:$B,PPvsREal!$C$49,Eventos!L:L) -> 0 | M49: =SUMIF(Eventos!$B:$B,PPvsREal!$C$49,Eventos!M:M) -> 0 | N49: =SUMIF(Eventos!$B:$B,PPvsREal!$C$49,Eventos!N:N) -> 0 | O49: =SUMIF(Eventos!$B:$B,PPvsREal!$C$49,Eventos!O:O) -> 0 | P49: =SUMIF(Eventos!$B:$B,PPvsREal!$C$49,Eventos!P:P) -> 0 | Q49: =SUMIF(Eventos!$B:$B,PPvsREal!$C$49,Eventos!Q:Q) -> 0 | R49: =SUMIF(Eventos!$B:$B,PPvsREal!$C$49,Eventos!R:R) -> 0 | S49: =SUMIF(Eventos!$B:$B,PPvsREal!$C$49,Eventos!S:S) -> 0 | T49: =SUMIF(Eventos!$B:$B,PPvsREal!$C$49,Eventos!T:T) -> 0 | U49: =SUMIF(Eventos!$B:$B,PPvsREal!$C$49,Eventos!U:U) -> 0 | V49: =SUMIF(Eventos!$B:$B,PPvsREal!$C$49,Eventos!V:V) -> 0 | W49: =SUMIF(Eventos!$B:$B,PPvsREal!$C$49,Eventos!W:W) -> 0 | X49: =SUMIF(Eventos!$B:$B,PPvsREal!$C$49,Eventos!X:X) -> 700000 | Y49: =SUMIF(Eventos!$B:$B,PPvsREal!$C$49,Eventos!Y:Y) -> 0 | Z49: =SUMIF(Eventos!$B:$B,PPvsREal!$C$49,Eventos!Z:Z) -> 0 | AA49: =SUMIF(Eventos!$B:$B,PPvsREal!$C$49,Eventos!AA:AA) -> 0
B50: Eventos | C50: 701-004-000-00 | D50: =SUMIF(Eventos!$B:$B,PPvsREal!$C$50,Eventos!D:D) -> 0 | E50: =SUMIF(Eventos!$B:$B,PPvsREal!$C$50,Eventos!E:E) -> 0 | F50: =SUMIF(Eventos!$B:$B,PPvsREal!$C$50,Eventos!F:F) -> 0 | G50: =SUMIF(Eventos!$B:$B,PPvsREal!$C$50,Eventos!G:G) -> 0 | H50: =SUMIF(Eventos!$B:$B,PPvsREal!$C$50,Eventos!H:H) -> 0 | I50: =SUMIF(Eventos!$B:$B,PPvsREal!$C$50,Eventos!I:I) -> 0 | J50: =SUMIF(Eventos!$B:$B,PPvsREal!$C$50,Eventos!J:J) -> 0 | K50: =SUMIF(Eventos!$B:$B,PPvsREal!$C$50,Eventos!K:K) -> 0 | L50: =SUMIF(Eventos!$B:$B,PPvsREal!$C$50,Eventos!L:L) -> 0 | M50: =SUMIF(Eventos!$B:$B,PPvsREal!$C$50,Eventos!M:M) -> 22332.47 | N50: =SUMIF(Eventos!$B:$B,PPvsREal!$C$50,Eventos!N:N) -> 0 | O50: =SUMIF(Eventos!$B:$B,PPvsREal!$C$50,Eventos!O:O) -> 0 | P50: =SUMIF(Eventos!$B:$B,PPvsREal!$C$50,Eventos!P:P) -> 0 | Q50: =SUMIF(Eventos!$B:$B,PPvsREal!$C$50,Eventos!Q:Q) -> 0 | R50: =SUMIF(Eventos!$B:$B,PPvsREal!$C$50,Eventos!R:R) -> 0 | S50: =SUMIF(Eventos!$B:$B,PPvsREal!$C$50,Eventos!S:S) -> 0 | T50: =SUMIF(Eventos!$B:$B,PPvsREal!$C$50,Eventos!T:T) -> 0 | U50: =SUMIF(Eventos!$B:$B,PPvsREal!$C$50,Eventos!U:U) -> 0 | V50: =SUMIF(Eventos!$B:$B,PPvsREal!$C$50,Eventos!V:V) -> 0 | W50: =SUMIF(Eventos!$B:$B,PPvsREal!$C$50,Eventos!W:W) -> 0 | X50: =SUMIF(Eventos!$B:$B,PPvsREal!$C$50,Eventos!X:X) -> 700000 | Y50: =SUMIF(Eventos!$B:$B,PPvsREal!$C$50,Eventos!Y:Y) -> 0 | Z50: =SUMIF(Eventos!$B:$B,PPvsREal!$C$50,Eventos!Z:Z) -> 0 | AA50: =SUMIF(Eventos!$B:$B,PPvsREal!$C$50,Eventos!AA:AA) -> 0
B51: Eventos | C51: 701-013-000-00 | D51: =SUMIF(Eventos!$B:$B,PPvsREal!$C$51,Eventos!D:D) -> 0 | E51: =SUMIF(Eventos!$B:$B,PPvsREal!$C$51,Eventos!E:E) -> 0 | F51: =SUMIF(Eventos!$B:$B,PPvsREal!$C$51,Eventos!F:F) -> 0 | G51: =SUMIF(Eventos!$B:$B,PPvsREal!$C$51,Eventos!G:G) -> 0 | H51: =SUMIF(Eventos!$B:$B,PPvsREal!$C$51,Eventos!H:H) -> 0 | I51: =SUMIF(Eventos!$B:$B,PPvsREal!$C$51,Eventos!I:I) -> 0 | J51: =SUMIF(Eventos!$B:$B,PPvsREal!$C$51,Eventos!J:J) -> 0 | K51: =SUMIF(Eventos!$B:$B,PPvsREal!$C$51,Eventos!K:K) -> 1464.15 | L51: =SUMIF(Eventos!$B:$B,PPvsREal!$C$51,Eventos!L:L) -> 0 | M51: =SUMIF(Eventos!$B:$B,PPvsREal!$C$51,Eventos!M:M) -> 0 | N51: =SUMIF(Eventos!$B:$B,PPvsREal!$C$51,Eventos!N:N) -> 0 | O51: =SUMIF(Eventos!$B:$B,PPvsREal!$C$51,Eventos!O:O) -> 0 | P51: =SUMIF(Eventos!$B:$B,PPvsREal!$C$51,Eventos!P:P) -> 0 | Q51: =SUMIF(Eventos!$B:$B,PPvsREal!$C$51,Eventos!Q:Q) -> 0 | R51: =SUMIF(Eventos!$B:$B,PPvsREal!$C$51,Eventos!R:R) -> 0 | S51: =SUMIF(Eventos!$B:$B,PPvsREal!$C$51,Eventos!S:S) -> 0 | T51: =SUMIF(Eventos!$B:$B,PPvsREal!$C$51,Eventos!T:T) -> 0 | U51: =SUMIF(Eventos!$B:$B,PPvsREal!$C$51,Eventos!U:U) -> 0 | V51: =SUMIF(Eventos!$B:$B,PPvsREal!$C$51,Eventos!V:V) -> 0 | W51: =SUMIF(Eventos!$B:$B,PPvsREal!$C$51,Eventos!W:W) -> 0 | X51: =SUMIF(Eventos!$B:$B,PPvsREal!$C$51,Eventos!X:X) -> 0 | Y51: =SUMIF(Eventos!$B:$B,PPvsREal!$C$51,Eventos!Y:Y) -> 0 | Z51: =SUMIF(Eventos!$B:$B,PPvsREal!$C$51,Eventos!Z:Z) -> 0 | AA51: =SUMIF(Eventos!$B:$B,PPvsREal!$C$51,Eventos!AA:AA) -> 0
B52: Eventos | C52: 403-002-000-00 | D52: =SUMIF(Eventos!$B:$B,PPvsREal!$C$52,Eventos!D:D) -> 47268.9 | E52: =SUMIF(Eventos!$B:$B,PPvsREal!$C$52,Eventos!E:E) -> 78600 | F52: =SUMIF(Eventos!$B:$B,PPvsREal!$C$52,Eventos!F:F) -> 47268.9 | G52: =SUMIF(Eventos!$B:$B,PPvsREal!$C$52,Eventos!G:G) -> 52400 | H52: =SUMIF(Eventos!$B:$B,PPvsREal!$C$52,Eventos!H:H) -> 47268.9 | I52: =SUMIF(Eventos!$B:$B,PPvsREal!$C$52,Eventos!I:I) -> 78600 | J52: =SUMIF(Eventos!$B:$B,PPvsREal!$C$52,Eventos!J:J) -> 47268.9 | K52: =SUMIF(Eventos!$B:$B,PPvsREal!$C$52,Eventos!K:K) -> 78600 | L52: =SUMIF(Eventos!$B:$B,PPvsREal!$C$52,Eventos!L:L) -> 47268.9 | M52: =SUMIF(Eventos!$B:$B,PPvsREal!$C$52,Eventos!M:M) -> 52400 | N52: =SUMIF(Eventos!$B:$B,PPvsREal!$C$52,Eventos!N:N) -> 47268.9 | O52: =SUMIF(Eventos!$B:$B,PPvsREal!$C$52,Eventos!O:O) -> 52400 | P52: =SUMIF(Eventos!$B:$B,PPvsREal!$C$52,Eventos!P:P) -> 47268.9 | Q52: =SUMIF(Eventos!$B:$B,PPvsREal!$C$52,Eventos!Q:Q) -> 52400 | R52: =SUMIF(Eventos!$B:$B,PPvsREal!$C$52,Eventos!R:R) -> 47268.9 | S52: =SUMIF(Eventos!$B:$B,PPvsREal!$C$52,Eventos!S:S) -> 0 | T52: =SUMIF(Eventos!$B:$B,PPvsREal!$C$52,Eventos!T:T) -> 47268.9 | U52: =SUMIF(Eventos!$B:$B,PPvsREal!$C$52,Eventos!U:U) -> 0 | V52: =SUMIF(Eventos!$B:$B,PPvsREal!$C$52,Eventos!V:V) -> 47268.9 | W52: =SUMIF(Eventos!$B:$B,PPvsREal!$C$52,Eventos!W:W) -> 0 | X52: =SUMIF(Eventos!$B:$B,PPvsREal!$C$52,Eventos!X:X) -> 47268.9 | Y52: =SUMIF(Eventos!$B:$B,PPvsREal!$C$52,Eventos!Y:Y) -> 0 | Z52: =SUMIF(Eventos!$B:$B,PPvsREal!$C$52,Eventos!Z:Z) -> 47268.9 | AA52: =SUMIF(Eventos!$B:$B,PPvsREal!$C$52,Eventos!AA:AA) -> 0
B53: Eventos | C53: 601-003-004-00 | D53: =SUMIF(Eventos!$B:$B,PPvsREal!$C$53,Eventos!D:D) -> 23634.45 | E53: =SUMIF(Eventos!$B:$B,PPvsREal!$C$53,Eventos!E:E) -> 39300 | F53: =SUMIF(Eventos!$B:$B,PPvsREal!$C$53,Eventos!F:F) -> 23634.45 | G53: =SUMIF(Eventos!$B:$B,PPvsREal!$C$53,Eventos!G:G) -> 26200 | H53: =SUMIF(Eventos!$B:$B,PPvsREal!$C$53,Eventos!H:H) -> 23634.45 | I53: =SUMIF(Eventos!$B:$B,PPvsREal!$C$53,Eventos!I:I) -> 39300 | J53: =SUMIF(Eventos!$B:$B,PPvsREal!$C$53,Eventos!J:J) -> 23634.45 | K53: =SUMIF(Eventos!$B:$B,PPvsREal!$C$53,Eventos!K:K) -> 39300 | L53: =SUMIF(Eventos!$B:$B,PPvsREal!$C$53,Eventos!L:L) -> 23634.45 | M53: =SUMIF(Eventos!$B:$B,PPvsREal!$C$53,Eventos!M:M) -> 26200 | N53: =SUMIF(Eventos!$B:$B,PPvsREal!$C$53,Eventos!N:N) -> 23634.45 | O53: =SUMIF(Eventos!$B:$B,PPvsREal!$C$53,Eventos!O:O) -> 26200 | P53: =SUMIF(Eventos!$B:$B,PPvsREal!$C$53,Eventos!P:P) -> 23634.45 | Q53: =SUMIF(Eventos!$B:$B,PPvsREal!$C$53,Eventos!Q:Q) -> 26200 | R53: =SUMIF(Eventos!$B:$B,PPvsREal!$C$53,Eventos!R:R) -> 23634.45 | S53: =SUMIF(Eventos!$B:$B,PPvsREal!$C$53,Eventos!S:S) -> 0 | T53: =SUMIF(Eventos!$B:$B,PPvsREal!$C$53,Eventos!T:T) -> 23634.45 | U53: =SUMIF(Eventos!$B:$B,PPvsREal!$C$53,Eventos!U:U) -> 0 | V53: =SUMIF(Eventos!$B:$B,PPvsREal!$C$53,Eventos!V:V) -> 23634.45 | W53: =SUMIF(Eventos!$B:$B,PPvsREal!$C$53,Eventos!W:W) -> 0 | X53: =SUMIF(Eventos!$B:$B,PPvsREal!$C$53,Eventos!X:X) -> 23634.45 | Y53: =SUMIF(Eventos!$B:$B,PPvsREal!$C$53,Eventos!Y:Y) -> 0 | Z53: =SUMIF(Eventos!$B:$B,PPvsREal!$C$53,Eventos!Z:Z) -> 23634.45 | AA53: =SUMIF(Eventos!$B:$B,PPvsREal!$C$53,Eventos!AA:AA) -> 0
B54: RH | C54: 901-011-003-00 | D54: 0 | E54: 0 | F54: 0 | G54: 0 | H54: 0 | I54: 0 | J54: 0 | K54: 0 | L54: 0 | M54: 0 | N54: 0 | O54: 0 | P54: 0 | Q54: 0 | R54: 0 | S54: 0 | T54: 0 | U54: 0 | V54: 0 | W54: 0 | X54: 0 | Y54: 0 | Z54: 0 | AA54: 0
B55: Dirección | C55: 404-006-000-00 | D55: =SUMIF(Dirección!$B:$B,PPvsREal!$C$55,Dirección!D:D) -> 16250 | E55: =SUMIF(Dirección!$B:$B,PPvsREal!$C$55,Dirección!E:E) -> 0 | F55: =SUMIF(Dirección!$B:$B,PPvsREal!$C$55,Dirección!F:F) -> 16250 | G55: =SUMIF(Dirección!$B:$B,PPvsREal!$C$55,Dirección!G:G) -> 0 | H55: =SUMIF(Dirección!$B:$B,PPvsREal!$C$55,Dirección!H:H) -> 16250 | I55: =SUMIF(Dirección!$B:$B,PPvsREal!$C$55,Dirección!I:I) -> 0 | J55: =SUMIF(Dirección!$B:$B,PPvsREal!$C$55,Dirección!J:J) -> 16250 | K55: =SUMIF(Dirección!$B:$B,PPvsREal!$C$55,Dirección!K:K) -> 0 | L55: =SUMIF(Dirección!$B:$B,PPvsREal!$C$55,Dirección!L:L) -> 16250 | M55: =SUMIF(Dirección!$B:$B,PPvsREal!$C$55,Dirección!M:M) -> 0 | N55: =SUMIF(Dirección!$B:$B,PPvsREal!$C$55,Dirección!N:N) -> 16250 | O55: =SUMIF(Dirección!$B:$B,PPvsREal!$C$55,Dirección!O:O) -> 0 | P55: =SUMIF(Dirección!$B:$B,PPvsREal!$C$55,Dirección!P:P) -> 16250 | Q55: =SUMIF(Dirección!$B:$B,PPvsREal!$C$55,Dirección!Q:Q) -> 0 | R55: =SUMIF(Dirección!$B:$B,PPvsREal!$C$55,Dirección!R:R) -> 16250 | S55: =SUMIF(Dirección!$B:$B,PPvsREal!$C$55,Dirección!S:S) -> 0 | T55: =SUMIF(Dirección!$B:$B,PPvsREal!$C$55,Dirección!T:T) -> 16250 | U55: =SUMIF(Dirección!$B:$B,PPvsREal!$C$55,Dirección!U:U) -> 0 | V55: =SUMIF(Dirección!$B:$B,PPvsREal!$C$55,Dirección!V:V) -> 16250 | W55: =SUMIF(Dirección!$B:$B,PPvsREal!$C$55,Dirección!W:W) -> 0 | X55: =SUMIF(Dirección!$B:$B,PPvsREal!$C$55,Dirección!X:X) -> 16250 | Y55: =SUMIF(Dirección!$B:$B,PPvsREal!$C$55,Dirección!Y:Y) -> 0 | Z55: =SUMIF(Dirección!$B:$B,PPvsREal!$C$55,Dirección!Z:Z) -> 16250 | AA55: =SUMIF(Dirección!$B:$B,PPvsREal!$C$55,Dirección!AA:AA) -> 0
B56: Dirección | C56: 404-011-000-00 | D56: =SUMIF(Dirección!$B:$B,PPvsREal!$C$56,Dirección!D:D) -> 9750 | E56: =SUMIF(Dirección!$B:$B,PPvsREal!$C$56,Dirección!E:E) -> 0 | F56: =SUMIF(Dirección!$B:$B,PPvsREal!$C$56,Dirección!F:F) -> 9750 | G56: =SUMIF(Dirección!$B:$B,PPvsREal!$C$56,Dirección!G:G) -> 0 | H56: =SUMIF(Dirección!$B:$B,PPvsREal!$C$56,Dirección!H:H) -> 9750 | I56: =SUMIF(Dirección!$B:$B,PPvsREal!$C$56,Dirección!I:I) -> 5850 | J56: =SUMIF(Dirección!$B:$B,PPvsREal!$C$56,Dirección!J:J) -> 9750 | K56: =SUMIF(Dirección!$B:$B,PPvsREal!$C$56,Dirección!K:K) -> 3600 | L56: =SUMIF(Dirección!$B:$B,PPvsREal!$C$56,Dirección!L:L) -> 9750 | M56: =SUMIF(Dirección!$B:$B,PPvsREal!$C$56,Dirección!M:M) -> 740 | N56: =SUMIF(Dirección!$B:$B,PPvsREal!$C$56,Dirección!N:N) -> 9750 | O56: =SUMIF(Dirección!$B:$B,PPvsREal!$C$56,Dirección!O:O) -> 5850 | P56: =SUMIF(Dirección!$B:$B,PPvsREal!$C$56,Dirección!P:P) -> 9750 | Q56: =SUMIF(Dirección!$B:$B,PPvsREal!$C$56,Dirección!Q:Q) -> 6750 | R56: =SUMIF(Dirección!$B:$B,PPvsREal!$C$56,Dirección!R:R) -> 9750 | S56: =SUMIF(Dirección!$B:$B,PPvsREal!$C$56,Dirección!S:S) -> 0 | T56: =SUMIF(Dirección!$B:$B,PPvsREal!$C$56,Dirección!T:T) -> 9750 | U56: =SUMIF(Dirección!$B:$B,PPvsREal!$C$56,Dirección!U:U) -> 0 | V56: =SUMIF(Dirección!$B:$B,PPvsREal!$C$56,Dirección!V:V) -> 9750 | W56: =SUMIF(Dirección!$B:$B,PPvsREal!$C$56,Dirección!W:W) -> 0 | X56: =SUMIF(Dirección!$B:$B,PPvsREal!$C$56,Dirección!X:X) -> 9750 | Y56: =SUMIF(Dirección!$B:$B,PPvsREal!$C$56,Dirección!Y:Y) -> 0 | Z56: =SUMIF(Dirección!$B:$B,PPvsREal!$C$56,Dirección!Z:Z) -> 9750 | AA56: =SUMIF(Dirección!$B:$B,PPvsREal!$C$56,Dirección!AA:AA) -> 0
B57: Dirección | C57: 502-006-000-00 | D57: =SUMIF(Dirección!$B:$B,PPvsREal!$C$57,Dirección!D:D) -> 18000 | E57: =SUMIF(Dirección!$B:$B,PPvsREal!$C$57,Dirección!E:E) -> 0 | F57: =SUMIF(Dirección!$B:$B,PPvsREal!$C$57,Dirección!F:F) -> 18000 | G57: =SUMIF(Dirección!$B:$B,PPvsREal!$C$57,Dirección!G:G) -> 0 | H57: =SUMIF(Dirección!$B:$B,PPvsREal!$C$57,Dirección!H:H) -> 18000 | I57: =SUMIF(Dirección!$B:$B,PPvsREal!$C$57,Dirección!I:I) -> 0 | J57: =SUMIF(Dirección!$B:$B,PPvsREal!$C$57,Dirección!J:J) -> 18000 | K57: =SUMIF(Dirección!$B:$B,PPvsREal!$C$57,Dirección!K:K) -> 0 | L57: =SUMIF(Dirección!$B:$B,PPvsREal!$C$57,Dirección!L:L) -> 18000 | M57: =SUMIF(Dirección!$B:$B,PPvsREal!$C$57,Dirección!M:M) -> 0 | N57: =SUMIF(Dirección!$B:$B,PPvsREal!$C$57,Dirección!N:N) -> 18000 | O57: =SUMIF(Dirección!$B:$B,PPvsREal!$C$57,Dirección!O:O) -> 0 | P57: =SUMIF(Dirección!$B:$B,PPvsREal!$C$57,Dirección!P:P) -> 18000 | Q57: =SUMIF(Dirección!$B:$B,PPvsREal!$C$57,Dirección!Q:Q) -> 372.75 | R57: =SUMIF(Dirección!$B:$B,PPvsREal!$C$57,Dirección!R:R) -> 18000 | S57: =SUMIF(Dirección!$B:$B,PPvsREal!$C$57,Dirección!S:S) -> 0 | T57: =SUMIF(Dirección!$B:$B,PPvsREal!$C$57,Dirección!T:T) -> 18000 | U57: =SUMIF(Dirección!$B:$B,PPvsREal!$C$57,Dirección!U:U) -> 0 | V57: =SUMIF(Dirección!$B:$B,PPvsREal!$C$57,Dirección!V:V) -> 18000 | W57: =SUMIF(Dirección!$B:$B,PPvsREal!$C$57,Dirección!W:W) -> 0 | X57: =SUMIF(Dirección!$B:$B,PPvsREal!$C$57,Dirección!X:X) -> 18000 | Y57: =SUMIF(Dirección!$B:$B,PPvsREal!$C$57,Dirección!Y:Y) -> 0 | Z57: =SUMIF(Dirección!$B:$B,PPvsREal!$C$57,Dirección!Z:Z) -> 18000 | AA57: =SUMIF(Dirección!$B:$B,PPvsREal!$C$57,Dirección!AA:AA) -> 0
B58: Dirección | C58: 502-012-000-00 | D58: =SUMIF(Dirección!$B:$B,PPvsREal!$C$58,Dirección!D:D) -> 7840 | E58: =SUMIF(Dirección!$B:$B,PPvsREal!$C$58,Dirección!E:E) -> 0 | F58: =SUMIF(Dirección!$B:$B,PPvsREal!$C$58,Dirección!F:F) -> 7840 | G58: =SUMIF(Dirección!$B:$B,PPvsREal!$C$58,Dirección!G:G) -> 0 | H58: =SUMIF(Dirección!$B:$B,PPvsREal!$C$58,Dirección!H:H) -> 7840 | I58: =SUMIF(Dirección!$B:$B,PPvsREal!$C$58,Dirección!I:I) -> 656.5 | J58: =SUMIF(Dirección!$B:$B,PPvsREal!$C$58,Dirección!J:J) -> 7840 | K58: =SUMIF(Dirección!$B:$B,PPvsREal!$C$58,Dirección!K:K) -> 20698.44 | L58: =SUMIF(Dirección!$B:$B,PPvsREal!$C$58,Dirección!L:L) -> 7840 | M58: =SUMIF(Dirección!$B:$B,PPvsREal!$C$58,Dirección!M:M) -> 8908.76 | N58: =SUMIF(Dirección!$B:$B,PPvsREal!$C$58,Dirección!N:N) -> 7840 | O58: =SUMIF(Dirección!$B:$B,PPvsREal!$C$58,Dirección!O:O) -> 8460.24 | P58: =SUMIF(Dirección!$B:$B,PPvsREal!$C$58,Dirección!P:P) -> 7840 | Q58: =SUMIF(Dirección!$B:$B,PPvsREal!$C$58,Dirección!Q:Q) -> 2200 | R58: =SUMIF(Dirección!$B:$B,PPvsREal!$C$58,Dirección!R:R) -> 7840 | S58: =SUMIF(Dirección!$B:$B,PPvsREal!$C$58,Dirección!S:S) -> 0 | T58: =SUMIF(Dirección!$B:$B,PPvsREal!$C$58,Dirección!T:T) -> 7840 | U58: =SUMIF(Dirección!$B:$B,PPvsREal!$C$58,Dirección!U:U) -> 0 | V58: =SUMIF(Dirección!$B:$B,PPvsREal!$C$58,Dirección!V:V) -> 7840 | W58: =SUMIF(Dirección!$B:$B,PPvsREal!$C$58,Dirección!W:W) -> 0 | X58: =SUMIF(Dirección!$B:$B,PPvsREal!$C$58,Dirección!X:X) -> 7840 | Y58: =SUMIF(Dirección!$B:$B,PPvsREal!$C$58,Dirección!Y:Y) -> 0 | Z58: =SUMIF(Dirección!$B:$B,PPvsREal!$C$58,Dirección!Z:Z) -> 7840 | AA58: =SUMIF(Dirección!$B:$B,PPvsREal!$C$58,Dirección!AA:AA) -> 0
B59: Dirección | C59: 901-004-003-00 | D59: =SUMIF(Dirección!$B:$B,PPvsREal!$C$59,Dirección!D:D) -> 0 | E59: =SUMIF(Dirección!$B:$B,PPvsREal!$C$59,Dirección!E:E) -> 0 | F59: =SUMIF(Dirección!$B:$B,PPvsREal!$C$59,Dirección!F:F) -> 14500 | G59: =SUMIF(Dirección!$B:$B,PPvsREal!$C$59,Dirección!G:G) -> 0 | H59: =SUMIF(Dirección!$B:$B,PPvsREal!$C$59,Dirección!H:H) -> 14500 | I59: =SUMIF(Dirección!$B:$B,PPvsREal!$C$59,Dirección!I:I) -> 4093.19 | J59: =SUMIF(Dirección!$B:$B,PPvsREal!$C$59,Dirección!J:J) -> 0 | K59: =SUMIF(Dirección!$B:$B,PPvsREal!$C$59,Dirección!K:K) -> -232 | L59: =SUMIF(Dirección!$B:$B,PPvsREal!$C$59,Dirección!L:L) -> 0 | M59: =SUMIF(Dirección!$B:$B,PPvsREal!$C$59,Dirección!M:M) -> 33715.3 | N59: =SUMIF(Dirección!$B:$B,PPvsREal!$C$59,Dirección!N:N) -> 14500 | O59: =SUMIF(Dirección!$B:$B,PPvsREal!$C$59,Dirección!O:O) -> 0 | P59: =SUMIF(Dirección!$B:$B,PPvsREal!$C$59,Dirección!P:P) -> 0 | Q59: =SUMIF(Dirección!$B:$B,PPvsREal!$C$59,Dirección!Q:Q) -> 11069.43 | R59: =SUMIF(Dirección!$B:$B,PPvsREal!$C$59,Dirección!R:R) -> 0 | S59: =SUMIF(Dirección!$B:$B,PPvsREal!$C$59,Dirección!S:S) -> 0 | T59: =SUMIF(Dirección!$B:$B,PPvsREal!$C$59,Dirección!T:T) -> 0 | U59: =SUMIF(Dirección!$B:$B,PPvsREal!$C$59,Dirección!U:U) -> 0 | V59: =SUMIF(Dirección!$B:$B,PPvsREal!$C$59,Dirección!V:V) -> 14500 | W59: =SUMIF(Dirección!$B:$B,PPvsREal!$C$59,Dirección!W:W) -> 0 | X59: =SUMIF(Dirección!$B:$B,PPvsREal!$C$59,Dirección!X:X) -> 0 | Y59: =SUMIF(Dirección!$B:$B,PPvsREal!$C$59,Dirección!Y:Y) -> 0 | Z59: =SUMIF(Dirección!$B:$B,PPvsREal!$C$59,Dirección!Z:Z) -> 0 | AA59: =SUMIF(Dirección!$B:$B,PPvsREal!$C$59,Dirección!AA:AA) -> 0
B60: Dirección | C60: 901-007-000-00 | D60: =SUMIF(Dirección!$B:$B,PPvsREal!$C$60,Dirección!D:D) -> 0 | E60: =SUMIF(Dirección!$B:$B,PPvsREal!$C$60,Dirección!E:E) -> 0 | F60: =SUMIF(Dirección!$B:$B,PPvsREal!$C$60,Dirección!F:F) -> 0 | G60: =SUMIF(Dirección!$B:$B,PPvsREal!$C$60,Dirección!G:G) -> 0 | H60: =SUMIF(Dirección!$B:$B,PPvsREal!$C$60,Dirección!H:H) -> 15000 | I60: =SUMIF(Dirección!$B:$B,PPvsREal!$C$60,Dirección!I:I) -> 9472.26 | J60: =SUMIF(Dirección!$B:$B,PPvsREal!$C$60,Dirección!J:J) -> 0 | K60: =SUMIF(Dirección!$B:$B,PPvsREal!$C$60,Dirección!K:K) -> 0 | L60: =SUMIF(Dirección!$B:$B,PPvsREal!$C$60,Dirección!L:L) -> 0 | M60: =SUMIF(Dirección!$B:$B,PPvsREal!$C$60,Dirección!M:M) -> 0 | N60: =SUMIF(Dirección!$B:$B,PPvsREal!$C$60,Dirección!N:N) -> 0 | O60: =SUMIF(Dirección!$B:$B,PPvsREal!$C$60,Dirección!O:O) -> 0 | P60: =SUMIF(Dirección!$B:$B,PPvsREal!$C$60,Dirección!P:P) -> 15000 | Q60: =SUMIF(Dirección!$B:$B,PPvsREal!$C$60,Dirección!Q:Q) -> 9570.15 | R60: =SUMIF(Dirección!$B:$B,PPvsREal!$C$60,Dirección!R:R) -> 0 | S60: =SUMIF(Dirección!$B:$B,PPvsREal!$C$60,Dirección!S:S) -> 0 | T60: =SUMIF(Dirección!$B:$B,PPvsREal!$C$60,Dirección!T:T) -> 0 | U60: =SUMIF(Dirección!$B:$B,PPvsREal!$C$60,Dirección!U:U) -> 0 | V60: =SUMIF(Dirección!$B:$B,PPvsREal!$C$60,Dirección!V:V) -> 0 | W60: =SUMIF(Dirección!$B:$B,PPvsREal!$C$60,Dirección!W:W) -> 0 | X60: =SUMIF(Dirección!$B:$B,PPvsREal!$C$60,Dirección!X:X) -> 0 | Y60: =SUMIF(Dirección!$B:$B,PPvsREal!$C$60,Dirección!Y:Y) -> 0 | Z60: =SUMIF(Dirección!$B:$B,PPvsREal!$C$60,Dirección!Z:Z) -> 0 | AA60: =SUMIF(Dirección!$B:$B,PPvsREal!$C$60,Dirección!AA:AA) -> 0
B61: Dirección | C61: 902-003-000-00 | D61: =SUMIF(Dirección!$B:$B,PPvsREal!$C$61,Dirección!D:D) -> 5500 | E61: =SUMIF(Dirección!$B:$B,PPvsREal!$C$61,Dirección!E:E) -> 8000 | F61: =SUMIF(Dirección!$B:$B,PPvsREal!$C$61,Dirección!F:F) -> 5500 | G61: =SUMIF(Dirección!$B:$B,PPvsREal!$C$61,Dirección!G:G) -> 3000 | H61: =SUMIF(Dirección!$B:$B,PPvsREal!$C$61,Dirección!H:H) -> 5500 | I61: =SUMIF(Dirección!$B:$B,PPvsREal!$C$61,Dirección!I:I) -> 5500 | J61: =SUMIF(Dirección!$B:$B,PPvsREal!$C$61,Dirección!J:J) -> 5500 | K61: =SUMIF(Dirección!$B:$B,PPvsREal!$C$61,Dirección!K:K) -> 5000 | L61: =SUMIF(Dirección!$B:$B,PPvsREal!$C$61,Dirección!L:L) -> 5500 | M61: =SUMIF(Dirección!$B:$B,PPvsREal!$C$61,Dirección!M:M) -> 3000 | N61: =SUMIF(Dirección!$B:$B,PPvsREal!$C$61,Dirección!N:N) -> 5500 | O61: =SUMIF(Dirección!$B:$B,PPvsREal!$C$61,Dirección!O:O) -> 5333.5 | P61: =SUMIF(Dirección!$B:$B,PPvsREal!$C$61,Dirección!P:P) -> 5500 | Q61: =SUMIF(Dirección!$B:$B,PPvsREal!$C$61,Dirección!Q:Q) -> 5500 | R61: =SUMIF(Dirección!$B:$B,PPvsREal!$C$61,Dirección!R:R) -> 5500 | S61: =SUMIF(Dirección!$B:$B,PPvsREal!$C$61,Dirección!S:S) -> 0 | T61: =SUMIF(Dirección!$B:$B,PPvsREal!$C$61,Dirección!T:T) -> 5500 | U61: =SUMIF(Dirección!$B:$B,PPvsREal!$C$61,Dirección!U:U) -> 0 | V61: =SUMIF(Dirección!$B:$B,PPvsREal!$C$61,Dirección!V:V) -> 5500 | W61: =SUMIF(Dirección!$B:$B,PPvsREal!$C$61,Dirección!W:W) -> 0 | X61: =SUMIF(Dirección!$B:$B,PPvsREal!$C$61,Dirección!X:X) -> 5500 | Y61: =SUMIF(Dirección!$B:$B,PPvsREal!$C$61,Dirección!Y:Y) -> 0 | Z61: =SUMIF(Dirección!$B:$B,PPvsREal!$C$61,Dirección!Z:Z) -> 5500 | AA61: =SUMIF(Dirección!$B:$B,PPvsREal!$C$61,Dirección!AA:AA) -> 0
B62: Dirección | C62: 901-014-004-00 | D62: =SUMIF(Dirección!$B:$B,PPvsREal!$C$62,Dirección!D:D) -> 0 | E62: =SUMIF(Dirección!$B:$B,PPvsREal!$C$62,Dirección!E:E) -> 0 | F62: =SUMIF(Dirección!$B:$B,PPvsREal!$C$62,Dirección!F:F) -> 0 | G62: =SUMIF(Dirección!$B:$B,PPvsREal!$C$62,Dirección!G:G) -> 0 | H62: =SUMIF(Dirección!$B:$B,PPvsREal!$C$62,Dirección!H:H) -> 6750 | I62: =SUMIF(Dirección!$B:$B,PPvsREal!$C$62,Dirección!I:I) -> 0 | J62: =SUMIF(Dirección!$B:$B,PPvsREal!$C$62,Dirección!J:J) -> 0 | K62: =SUMIF(Dirección!$B:$B,PPvsREal!$C$62,Dirección!K:K) -> 0 | L62: =SUMIF(Dirección!$B:$B,PPvsREal!$C$62,Dirección!L:L) -> 0 | M62: =SUMIF(Dirección!$B:$B,PPvsREal!$C$62,Dirección!M:M) -> 0 | N62: =SUMIF(Dirección!$B:$B,PPvsREal!$C$62,Dirección!N:N) -> 0 | O62: =SUMIF(Dirección!$B:$B,PPvsREal!$C$62,Dirección!O:O) -> 0 | P62: =SUMIF(Dirección!$B:$B,PPvsREal!$C$62,Dirección!P:P) -> 0 | Q62: =SUMIF(Dirección!$B:$B,PPvsREal!$C$62,Dirección!Q:Q) -> 0 | R62: =SUMIF(Dirección!$B:$B,PPvsREal!$C$62,Dirección!R:R) -> 0 | S62: =SUMIF(Dirección!$B:$B,PPvsREal!$C$62,Dirección!S:S) -> 0 | T62: =SUMIF(Dirección!$B:$B,PPvsREal!$C$62,Dirección!T:T) -> 6750 | U62: =SUMIF(Dirección!$B:$B,PPvsREal!$C$62,Dirección!U:U) -> 0 | V62: =SUMIF(Dirección!$B:$B,PPvsREal!$C$62,Dirección!V:V) -> 0 | W62: =SUMIF(Dirección!$B:$B,PPvsREal!$C$62,Dirección!W:W) -> 0 | X62: =SUMIF(Dirección!$B:$B,PPvsREal!$C$62,Dirección!X:X) -> 0 | Y62: =SUMIF(Dirección!$B:$B,PPvsREal!$C$62,Dirección!Y:Y) -> 0 | Z62: =SUMIF(Dirección!$B:$B,PPvsREal!$C$62,Dirección!Z:Z) -> 0 | AA62: =SUMIF(Dirección!$B:$B,PPvsREal!$C$62,Dirección!AA:AA) -> 0
B63: Dirección | C63: 902-002-001-00 | D63: =SUMIF(Dirección!$B:$B,PPvsREal!$C$63,Dirección!D:D) -> 3500 | E63: =SUMIF(Dirección!$B:$B,PPvsREal!$C$63,Dirección!E:E) -> 0 | F63: =SUMIF(Dirección!$B:$B,PPvsREal!$C$63,Dirección!F:F) -> 0 | G63: =SUMIF(Dirección!$B:$B,PPvsREal!$C$63,Dirección!G:G) -> 993.97 | H63: =SUMIF(Dirección!$B:$B,PPvsREal!$C$63,Dirección!H:H) -> 0 | I63: =SUMIF(Dirección!$B:$B,PPvsREal!$C$63,Dirección!I:I) -> -256.04 | J63: =SUMIF(Dirección!$B:$B,PPvsREal!$C$63,Dirección!J:J) -> 0 | K63: =SUMIF(Dirección!$B:$B,PPvsREal!$C$63,Dirección!K:K) -> 0 | L63: =SUMIF(Dirección!$B:$B,PPvsREal!$C$63,Dirección!L:L) -> 0 | M63: =SUMIF(Dirección!$B:$B,PPvsREal!$C$63,Dirección!M:M) -> 0 | N63: =SUMIF(Dirección!$B:$B,PPvsREal!$C$63,Dirección!N:N) -> 3500 | O63: =SUMIF(Dirección!$B:$B,PPvsREal!$C$63,Dirección!O:O) -> 0 | P63: =SUMIF(Dirección!$B:$B,PPvsREal!$C$63,Dirección!P:P) -> 0 | Q63: =SUMIF(Dirección!$B:$B,PPvsREal!$C$63,Dirección!Q:Q) -> 0 | R63: =SUMIF(Dirección!$B:$B,PPvsREal!$C$63,Dirección!R:R) -> 0 | S63: =SUMIF(Dirección!$B:$B,PPvsREal!$C$63,Dirección!S:S) -> 0 | T63: =SUMIF(Dirección!$B:$B,PPvsREal!$C$63,Dirección!T:T) -> 0 | U63: =SUMIF(Dirección!$B:$B,PPvsREal!$C$63,Dirección!U:U) -> 0 | V63: =SUMIF(Dirección!$B:$B,PPvsREal!$C$63,Dirección!V:V) -> 0 | W63: =SUMIF(Dirección!$B:$B,PPvsREal!$C$63,Dirección!W:W) -> 0 | X63: =SUMIF(Dirección!$B:$B,PPvsREal!$C$63,Dirección!X:X) -> 3500 | Y63: =SUMIF(Dirección!$B:$B,PPvsREal!$C$63,Dirección!Y:Y) -> 0 | Z63: =SUMIF(Dirección!$B:$B,PPvsREal!$C$63,Dirección!Z:Z) -> 0 | AA63: =SUMIF(Dirección!$B:$B,PPvsREal!$C$63,Dirección!AA:AA) -> 0
B64: Dirección | C64: 902-002-003-00 | D64: =SUMIF(Dirección!$B:$B,PPvsREal!$C$64,Dirección!D:D) -> 500 | E64: =SUMIF(Dirección!$B:$B,PPvsREal!$C$64,Dirección!E:E) -> 0 | F64: =SUMIF(Dirección!$B:$B,PPvsREal!$C$64,Dirección!F:F) -> 8000 | G64: =SUMIF(Dirección!$B:$B,PPvsREal!$C$64,Dirección!G:G) -> 0 | H64: =SUMIF(Dirección!$B:$B,PPvsREal!$C$64,Dirección!H:H) -> 500 | I64: =SUMIF(Dirección!$B:$B,PPvsREal!$C$64,Dirección!I:I) -> 0 | J64: =SUMIF(Dirección!$B:$B,PPvsREal!$C$64,Dirección!J:J) -> 500 | K64: =SUMIF(Dirección!$B:$B,PPvsREal!$C$64,Dirección!K:K) -> 0 | L64: =SUMIF(Dirección!$B:$B,PPvsREal!$C$64,Dirección!L:L) -> 500 | M64: =SUMIF(Dirección!$B:$B,PPvsREal!$C$64,Dirección!M:M) -> 0 | N64: =SUMIF(Dirección!$B:$B,PPvsREal!$C$64,Dirección!N:N) -> 500 | O64: =SUMIF(Dirección!$B:$B,PPvsREal!$C$64,Dirección!O:O) -> 431.04 | P64: =SUMIF(Dirección!$B:$B,PPvsREal!$C$64,Dirección!P:P) -> 500 | Q64: =SUMIF(Dirección!$B:$B,PPvsREal!$C$64,Dirección!Q:Q) -> 0 | R64: =SUMIF(Dirección!$B:$B,PPvsREal!$C$64,Dirección!R:R) -> 500 | S64: =SUMIF(Dirección!$B:$B,PPvsREal!$C$64,Dirección!S:S) -> 0 | T64: =SUMIF(Dirección!$B:$B,PPvsREal!$C$64,Dirección!T:T) -> 500 | U64: =SUMIF(Dirección!$B:$B,PPvsREal!$C$64,Dirección!U:U) -> 0 | V64: =SUMIF(Dirección!$B:$B,PPvsREal!$C$64,Dirección!V:V) -> 500 | W64: =SUMIF(Dirección!$B:$B,PPvsREal!$C$64,Dirección!W:W) -> 0 | X64: =SUMIF(Dirección!$B:$B,PPvsREal!$C$64,Dirección!X:X) -> 500 | Y64: =SUMIF(Dirección!$B:$B,PPvsREal!$C$64,Dirección!Y:Y) -> 0 | Z64: =SUMIF(Dirección!$B:$B,PPvsREal!$C$64,Dirección!Z:Z) -> 500 | AA64: =SUMIF(Dirección!$B:$B,PPvsREal!$C$64,Dirección!AA:AA) -> 0
B65: Gastos Generales | C65: 402-000-000-00 | D65: =SUMIF('Gastos Generales'!$B:$B,PPvsREal!$C$65,'Gastos Generales'!D:D) -> 0 | E65: =SUMIF('Gastos Generales'!$B:$B,PPvsREal!$C$65,'Gastos Generales'!E:E) -> 29.04 | F65: =SUMIF('Gastos Generales'!$B:$B,PPvsREal!$C$65,'Gastos Generales'!F:F) -> 0 | G65: =SUMIF('Gastos Generales'!$B:$B,PPvsREal!$C$65,'Gastos Generales'!G:G) -> 32.87 | H65: =SUMIF('Gastos Generales'!$B:$B,PPvsREal!$C$65,'Gastos Generales'!H:H) -> 0 | I65: =SUMIF('Gastos Generales'!$B:$B,PPvsREal!$C$65,'Gastos Generales'!I:I) -> 10.89 | J65: =SUMIF('Gastos Generales'!$B:$B,PPvsREal!$C$65,'Gastos Generales'!J:J) -> 0 | K65: =SUMIF('Gastos Generales'!$B:$B,PPvsREal!$C$65,'Gastos Generales'!K:K) -> 20.27 | L65: =SUMIF('Gastos Generales'!$B:$B,PPvsREal!$C$65,'Gastos Generales'!L:L) -> 0 | M65: =SUMIF('Gastos Generales'!$B:$B,PPvsREal!$C$65,'Gastos Generales'!M:M) -> 13.92 | N65: =SUMIF('Gastos Generales'!$B:$B,PPvsREal!$C$65,'Gastos Generales'!N:N) -> 0 | O65: =SUMIF('Gastos Generales'!$B:$B,PPvsREal!$C$65,'Gastos Generales'!O:O) -> 21.96 | P65: =SUMIF('Gastos Generales'!$B:$B,PPvsREal!$C$65,'Gastos Generales'!P:P) -> 0 | Q65: =SUMIF('Gastos Generales'!$B:$B,PPvsREal!$C$65,'Gastos Generales'!Q:Q) -> 0.01 | R65: =SUMIF('Gastos Generales'!$B:$B,PPvsREal!$C$65,'Gastos Generales'!R:R) -> 0 | S65: =SUMIF('Gastos Generales'!$B:$B,PPvsREal!$C$65,'Gastos Generales'!S:S) -> 0 | T65: =SUMIF('Gastos Generales'!$B:$B,PPvsREal!$C$65,'Gastos Generales'!T:T) -> 0 | U65: =SUMIF('Gastos Generales'!$B:$B,PPvsREal!$C$65,'Gastos Generales'!U:U) -> 0 | V65: =SUMIF('Gastos Generales'!$B:$B,PPvsREal!$C$65,'Gastos Generales'!V:V) -> 0 | W65: =SUMIF('Gastos Generales'!$B:$B,PPvsREal!$C$65,'Gastos Generales'!W:W) -> 0 | X65: =SUMIF('Gastos Generales'!$B:$B,PPvsREal!$C$65,'Gastos Generales'!X:X) -> 0 | Y65: =SUMIF('Gastos Generales'!$B:$B,PPvsREal!$C$65,'Gastos Generales'!Y:Y) -> 0 | Z65: =SUMIF('Gastos Generales'!$B:$B,PPvsREal!$C$65,'Gastos Generales'!Z:Z) -> 0 | AA65: =SUMIF('Gastos Generales'!$B:$B,PPvsREal!$C$65,'Gastos Generales'!AA:AA) -> 0
B66: Gastos Generales | C66: 410-000-000-00 | D66: =SUMIF('Gastos Generales'!$B:$B,PPvsREal!$C$66,'Gastos Generales'!D:D) -> 0 | E66: =SUMIF('Gastos Generales'!$B:$B,PPvsREal!$C$66,'Gastos Generales'!E:E) -> 0 | F66: =SUMIF('Gastos Generales'!$B:$B,PPvsREal!$C$66,'Gastos Generales'!F:F) -> 0 | G66: =SUMIF('Gastos Generales'!$B:$B,PPvsREal!$C$66,'Gastos Generales'!G:G) -> 0 | H66: =SUMIF('Gastos Generales'!$B:$B,PPvsREal!$C$66,'Gastos Generales'!H:H) -> 0 | I66: =SUMIF('Gastos Generales'!$B:$B,PPvsREal!$C$66,'Gastos Generales'!I:I) -> 0 | J66: =SUMIF('Gastos Generales'!$B:$B,PPvsREal!$C$66,'Gastos Generales'!J:J) -> 0 | K66: =SUMIF('Gastos Generales'!$B:$B,PPvsREal!$C$66,'Gastos Generales'!K:K) -> 0 | L66: =SUMIF('Gastos Generales'!$B:$B,PPvsREal!$C$66,'Gastos Generales'!L:L) -> 0 | M66: =SUMIF('Gastos Generales'!$B:$B,PPvsREal!$C$66,'Gastos Generales'!M:M) -> 0 | N66: =SUMIF('Gastos Generales'!$B:$B,PPvsREal!$C$66,'Gastos Generales'!N:N) -> 0 | O66: =SUMIF('Gastos Generales'!$B:$B,PPvsREal!$C$66,'Gastos Generales'!O:O) -> 0 | P66: =SUMIF('Gastos Generales'!$B:$B,PPvsREal!$C$66,'Gastos Generales'!P:P) -> 0 | Q66: =SUMIF('Gastos Generales'!$B:$B,PPvsREal!$C$66,'Gastos Generales'!Q:Q) -> 0 | R66: =SUMIF('Gastos Generales'!$B:$B,PPvsREal!$C$66,'Gastos Generales'!R:R) -> 0 | S66: =SUMIF('Gastos Generales'!$B:$B,PPvsREal!$C$66,'Gastos Generales'!S:S) -> 0 | T66: =SUMIF('Gastos Generales'!$B:$B,PPvsREal!$C$66,'Gastos Generales'!T:T) -> 0 | U66: =SUMIF('Gastos Generales'!$B:$B,PPvsREal!$C$66,'Gastos Generales'!U:U) -> 0 | V66: =SUMIF('Gastos Generales'!$B:$B,PPvsREal!$C$66,'Gastos Generales'!V:V) -> 0 | W66: =SUMIF('Gastos Generales'!$B:$B,PPvsREal!$C$66,'Gastos Generales'!W:W) -> 0 | X66: =SUMIF('Gastos Generales'!$B:$B,PPvsREal!$C$66,'Gastos Generales'!X:X) -> 0 | Y66: =SUMIF('Gastos Generales'!$B:$B,PPvsREal!$C$66,'Gastos Generales'!Y:Y) -> 0 | Z66: =SUMIF('Gastos Generales'!$B:$B,PPvsREal!$C$66,'Gastos Generales'!Z:Z) -> 0 | AA66: =SUMIF('Gastos Generales'!$B:$B,PPvsREal!$C$66,'Gastos Generales'!AA:AA) -> 0
B67: Gastos Generales | C67: 901-019-000-00 | D67: =SUMIF('Gastos Generales'!$B:$B,PPvsREal!$C$67,'Gastos Generales'!D:D) -> 0 | E67: =SUMIF('Gastos Generales'!$B:$B,PPvsREal!$C$67,'Gastos Generales'!E:E) -> 0 | F67: =SUMIF('Gastos Generales'!$B:$B,PPvsREal!$C$67,'Gastos Generales'!F:F) -> 0 | G67: =SUMIF('Gastos Generales'!$B:$B,PPvsREal!$C$67,'Gastos Generales'!G:G) -> 0 | H67: =SUMIF('Gastos Generales'!$B:$B,PPvsREal!$C$67,'Gastos Generales'!H:H) -> 0 | I67: =SUMIF('Gastos Generales'!$B:$B,PPvsREal!$C$67,'Gastos Generales'!I:I) -> 0 | J67: =SUMIF('Gastos Generales'!$B:$B,PPvsREal!$C$67,'Gastos Generales'!J:J) -> 0 | K67: =SUMIF('Gastos Generales'!$B:$B,PPvsREal!$C$67,'Gastos Generales'!K:K) -> 0 | L67: =SUMIF('Gastos Generales'!$B:$B,PPvsREal!$C$67,'Gastos Generales'!L:L) -> 0 | M67: =SUMIF('Gastos Generales'!$B:$B,PPvsREal!$C$67,'Gastos Generales'!M:M) -> 0 | N67: =SUMIF('Gastos Generales'!$B:$B,PPvsREal!$C$67,'Gastos Generales'!N:N) -> 0 | O67: =SUMIF('Gastos Generales'!$B:$B,PPvsREal!$C$67,'Gastos Generales'!O:O) -> 0 | P67: =SUMIF('Gastos Generales'!$B:$B,PPvsREal!$C$67,'Gastos Generales'!P:P) -> 0 | Q67: =SUMIF('Gastos Generales'!$B:$B,PPvsREal!$C$67,'Gastos Generales'!Q:Q) -> 0 | R67: =SUMIF('Gastos Generales'!$B:$B,PPvsREal!$C$67,'Gastos Generales'!R:R) -> 0 | S67: =SUMIF('Gastos Generales'!$B:$B,PPvsREal!$C$67,'Gastos Generales'!S:S) -> 0 | T67: =SUMIF('Gastos Generales'!$B:$B,PPvsREal!$C$67,'Gastos Generales'!T:T) -> 0 | U67: =SUMIF('Gastos Generales'!$B:$B,PPvsREal!$C$67,'Gastos Generales'!U:U) -> 0 | V67: =SUMIF('Gastos Generales'!$B:$B,PPvsREal!$C$67,'Gastos Generales'!V:V) -> 0 | W67: =SUMIF('Gastos Generales'!$B:$B,PPvsREal!$C$67,'Gastos Generales'!W:W) -> 0 | X67: =SUMIF('Gastos Generales'!$B:$B,PPvsREal!$C$67,'Gastos Generales'!X:X) -> 0 | Y67: =SUMIF('Gastos Generales'!$B:$B,PPvsREal!$C$67,'Gastos Generales'!Y:Y) -> 0 | Z67: =SUMIF('Gastos Generales'!$B:$B,PPvsREal!$C$67,'Gastos Generales'!Z:Z) -> 0 | AA67: =SUMIF('Gastos Generales'!$B:$B,PPvsREal!$C$67,'Gastos Generales'!AA:AA) -> 0
