Workbook
Name Payment_Needed: "Pago necesario"
Name Reimbursement: "Reembolso"

Sheet OneAmCham
A1: CONCEPTO | B1: Real 2025 | C1: Ppto. 2026 | D1: Ppto. 2025 | E1: Variación Ppto. 2026 vs Real 2025 | F1: Variación Ppto. 2025 vs Ppto. 2026
A3: CDMX Income | B3: ='Resumen (Caps)'!D4 -> 64619514 | C3: ='Resumen (Caps)'!E4 -> 71683976 | D3: ='Resumen (Caps)'!F4 -> 62529782 | E3: =IF((IFERROR(C3/B3,0))=0,0,(IFERROR(C3/B3,0)-1)) -> 0.10932398 | F3: =IF((IFERROR(C3/D3,0))=0,0,(IFERROR(C3/D3,0)-1)) -> 0.14639734
A4: Guadalajara Income | B4: ='Resumen (Caps)'!J4 -> 14195973 | C4: ='Resumen (Caps)'!K4 -> 17961606 | D4: ='Resumen (Caps)'!L4 -> 17294316 | E4: =IF((IFERROR(C4/B4,0))=0,0,(IFERROR(C4/B4,0)-1)) -> 0.26526067 | F4: =IF((IFERROR(C4/D4,0))=0,0,(IFERROR(C4/D4,0)-1)) -> 0.038584369
A5: Northeast Income | B5: ='Resumen (Caps)'!P4 -> 32744833 | C5: ='Resumen (Caps)'!Q4 -> 36605251 | D5: ='Resumen (Caps)'!R4 -> 34972433 | E5: =IF((IFERROR(C5/B5,0))=0,0,(IFERROR(C5/B5,0)-1)) -> 0.11789396 | F5: =IF((IFERROR(C5/D5,0))=0,0,(IFERROR(C5/D5,0)-1)) -> 0.046688705
A6: Northwests Income | B6: ='Resumen (Caps)'!V4 -> 5116359.8 | C6: ='Resumen (Caps)'!W4 -> 6765685 | D6: ='Resumen (Caps)'!X4 -> 8173413.7 | E6: =IF((IFERROR(C6/B6,0))=0,0,(IFERROR(C6/B6,0)-1)) -> 0.32236303 | F6: =IF((IFERROR(C6/D6,0))=0,0,(IFERROR(C6/D6,0)-1)) -> -0.17223265
A7: CONSOLIDATED INCOME | B7: =B3+B4+B5+B6 -> 1.1667668e+08 | C7: =C3+C4+C5+C6 -> 133016518 | D7: =D3+D4+D5+D6 -> 1.2296994e+08 | E7: =IF((IFERROR(C7/B7,0))=0,0,(IFERROR(C7/B7,0)-1)) -> 0.14004374 | F7: =IF((IFERROR(C7/D7,0))=0,0,(IFERROR(C7/D7,0)-1)) -> 0.08169942
A8: CDMX Expense | B8: ='Resumen (Caps)'!D24 -> 61247285 | C8: ='Resumen (Caps)'!E24 -> 69120006 | D8: ='Resumen (Caps)'!F24 -> 61625391 | E8: =IF((IFERROR(C8/B8,0))=0,0,(IFERROR(C8/B8,0)-1)) -> 0.12853991 | F8: =IF((IFERROR(C8/D8,0))=0,0,(IFERROR(C8/D8,0)-1)) -> 0.12161569
A9: Guadalajara Expense | B9: ='Resumen (Caps)'!J24 -> 14658996 | C9: ='Resumen (Caps)'!K24 -> 17851585 | D9: ='Resumen (Caps)'!L24 -> 16453320 | E9: =IF((IFERROR(C9/B9,0))=0,0,(IFERROR(C9/B9,0)-1)) -> 0.21779036 | F9: =IF((IFERROR(C9/D9,0))=0,0,(IFERROR(C9/D9,0)-1)) -> 0.084983721
A10: Northeast Expense | B10: ='Resumen (Caps)'!P24 -> 32320735 | C10: ='Resumen (Caps)'!Q24 -> 35744174 | D10: ='Resumen (Caps)'!R24 -> 33410428 | E10: =IF((IFERROR(C10/B10,0))=0,0,(IFERROR(C10/B10,0)-1)) -> 0.10592082 | F10: =IF((IFERROR(C10/D10,0))=0,0,(IFERROR(C10/D10,0)-1)) -> 0.069850825
A11: Northwests Expense | B11: ='Resumen (Caps)'!V24 -> 4574611.7 | C11: ='Resumen (Caps)'!W24 -> 6026890 | D11: ='Resumen (Caps)'!X24 -> 5864476.4 | E11: =IF((IFERROR(C11/B11,0))=0,0,(IFERROR(C11/B11,0)-1)) -> 0.31746482 | F11: =IF((IFERROR(C11/D11,0))=0,0,(IFERROR(C11/D11,0)-1)) -> 0.027694472
A12: CONSOLIDATED EXPENSES | B12: =B8+B9+B10+B11 -> 1.1280163e+08 | C12: =C8+C9+C10+C11 -> 1.2874265e+08 | D12: =D8+D9+D10+D11 -> 1.1735362e+08 | E12: =IF((IFERROR(C12/B12,0))=0,0,(IFERROR(C12/B12,0)-1)) -> 0.14131911 | F12: =IF((IFERROR(C12/D12,0))=0,0,(IFERROR(C12/D12,0)-1)) -> 0.097048894
A13: OPERATING RESULTS CDMX | B13: =+B3-B8 -> 3372228.3 | C13: =+C3-C8 -> 2563969.8 | D13: =+D3-D8 -> 904390.62 | E13: =IF((IFERROR(C13/B13,0))=0,0,(IFERROR(C13/B13,0)-1)) -> -0.23968085 | F13: =IF((IFERROR(C13/D13,0))=0,0,(IFERROR(C13/D13,0)-1)) -> 1.8350247
A14: OPERATING RESULTS Guadalajara | B14: =+B4-B9 -> -463023.6 | C14: =+C4-C9 -> 110021.59 | D14: =+D4-D9 -> 840995.7 | E14: =IF((IFERROR(C14/B14,0))=0,0,(IFERROR(C14/B14,0)-1))*-1 -> 1.2376155 | F14: =IF((IFERROR(C14/D14,0))=0,0,(IFERROR(C14/D14,0)-1))*-1 -> 0.86917699
A15: OPERATING RESULTS Northeast | B15: =+B5-B10 -> 424098.19 | C15: =+C5-C10 -> 861077.45 | D15: =+D5-D10 -> 1562005.8 | E15: =IF((IFERROR(C15/B15,0))=0,0,(IFERROR(C15/B15,0)-1)) -> 1.0303728 | F15: =IF((IFERROR(C15/D15,0))=0,0,(IFERROR(C15/D15,0)-1)) -> -0.44873606
A16: OPERATING RESULTS Northwests | B16: =+B6-B11 -> 541748.02 | C16: =+C6-C11 -> 738794.98 | D16: =+D6-D11 -> 2308937.2 | E16: =IF((IFERROR(C16/B16,0))=0,0,(IFERROR(C16/B16,0)-1)) -> 0.36372437 | F16: =IF((IFERROR(C16/D16,0))=0,0,(IFERROR(C16/D16,0)-1)) -> -0.68002812
A17: CONSOLIDATED OPERATING RESULTS | B17: =B13+B14+B15+B16 -> 3875050.9 | C17: =C13+C14+C15+C16 -> 4273863.8 | D17: =D13+D14+D15+D16 -> 5616329.3 | E17: =IF((IFERROR(C17/B17,0))=0,0,(IFERROR(C17/B17,0)-1)) -> 0.10291809 | F17: =IF((IFERROR(C17/D17,0))=0,0,(IFERROR(C17/D17,0)-1)) -> -0.23902899
A18: México Member Centricity | B18: ='Resumen (Caps)'!D75 -> 0 | C18: ='Resumen (Caps)'!E75 -> 0 | D18: ='Resumen (Caps)'!F75 -> 0 | E18: =IF((IFERROR(C18/B18,0))=0,0,(IFERROR(C18/B18,0)-1)) -> 0 | F18: =IF((IFERROR(C18/D18,0))=0,0,(IFERROR(C18/D18,0)-1)) -> 0
A19: Guadalajara Member Centricity | B19: ='Resumen (Caps)'!J75 -> 0 | C19: ='Resumen (Caps)'!K75 -> 0 | D19: ='Resumen (Caps)'!L75 -> 0 | E19: =IF((IFERROR(C19/B19,0))=0,0,(IFERROR(C19/B19,0)-1)) -> 0 | F19: =IF((IFERROR(C19/D19,0))=0,0,(IFERROR(C19/D19,0)-1)) -> 0
A20: Northeast Member Centricity | B20: ='Resumen (Caps)'!P75 -> 0 | C20: ='Resumen (Caps)'!Q75 -> 0 | D20: ='Resumen (Caps)'!R75 -> 0 | E20: =IF((IFERROR(C20/B20,0))=0,0,(IFERROR(C20/B20,0)-1)) -> 0 | F20: =IF((IFERROR(C20/D20,0))=0,0,(IFERROR(C20/D20,0)-1)) -> 0
A21: Northwests Member Centricity | B21: ='Resumen (Caps)'!V75 -> 0 | C21: ='Resumen (Caps)'!W75 -> 0 | D21: ='Resumen (Caps)'!X75 -> 0 | E21: =IF((IFERROR(C21/B21,0))=0,0,(IFERROR(C21/B21,0)-1)) -> 0 | F21: =IF((IFERROR(C21/D21,0))=0,0,(IFERROR(C21/D21,0)-1)) -> 0
A22: México Other Income | B22: ='Resumen (Caps)'!D77 -> 6005514 | C22: ='Resumen (Caps)'!E77 -> 0 | D22: ='Resumen (Caps)'!F77 -> 0 | E22: =IF((IFERROR(C22/B22,0))=0,0,(IFERROR(C22/B22,0)-1)) -> 0 | F22: =IF((IFERROR(C22/D22,0))=0,0,(IFERROR(C22/D22,0)-1)) -> 0
A23: Guadalajara Other Income | B23: ='Resumen (Caps)'!J77 -> 215.81 | C23: ='Resumen (Caps)'!K77 -> 0 | D23: ='Resumen (Caps)'!L77 -> 0 | E23: =IF((IFERROR(C23/B23,0))=0,0,(IFERROR(C23/B23,0)-1)) -> 0 | F23: =IF((IFERROR(C23/D23,0))=0,0,(IFERROR(C23/D23,0)-1)) -> 0
A24: Northeast Other Income | B24: ='Resumen (Caps)'!P77 -> 150141.67 | C24: ='Resumen (Caps)'!Q77 -> 0 | D24: ='Resumen (Caps)'!R77 -> 0 | E24: =IF((IFERROR(C24/B24,0))=0,0,(IFERROR(C24/B24,0)-1)) -> 0 | F24: =IF((IFERROR(C24/D24,0))=0,0,(IFERROR(C24/D24,0)-1)) -> 0
A25: Northwests Other Income | B25: ='Resumen (Caps)'!V77 -> 0 | C25: ='Resumen (Caps)'!W77 -> 0 | D25: ='Resumen (Caps)'!X77 -> 0 | E25: =IF((IFERROR(C25/B25,0))=0,0,(IFERROR(C25/B25,0)-1)) -> 0 | F25: =IF((IFERROR(C25/D25,0))=0,0,(IFERROR(C25/D25,0)-1)) -> 0
A26: NET RESULTS CDMX | B26: =B13-B18+B22 -> 9377742.4 | C26: =C13-C18+C22 -> 2563969.8 | D26: =D13-D18+D22 -> 904390.62 | E26: =IF((IFERROR(C26/B26,0))=0,0,(IFERROR(C26/B26,0)-1)) -> -0.72658987 | F26: =IF((IFERROR(C26/D26,0))=0,0,(IFERROR(C26/D26,0)-1)) -> 1.8350247
A27: NET RESULTS Guadalajara | B27: =B14-B19+B23 -> -462807.79 | C27: =C14-C19+C23 -> 110021.59 | D27: =D14-D19+D23 -> 840995.7 | E27: =IF((IFERROR(C27/B27,0))=0,0,(IFERROR(C27/B27,0)-1))*-1 -> 1.2377263 | F27: =IF((IFERROR(C27/D27,0))=0,0,(IFERROR(C27/D27,0)-1))*-1 -> 0.86917699
A28: NET RESULTS Northeast | B28: =B15-B20+B24 -> 574239.86 | C28: =C15-C20+C24 -> 861077.45 | D28: =D15-D20+D24 -> 1562005.8 | E28: =IF((IFERROR(C28/B28,0))=0,0,(IFERROR(C28/B28,0)-1)) -> 0.49950832 | F28: =IF((IFERROR(C28/D28,0))=0,0,(IFERROR(C28/D28,0)-1)) -> -0.44873606
A29: NET RESULTS Northwests | B29: =B16-B21+B25 -> 541748.02 | C29: =C16-C21+C25 -> 738794.98 | D29: =D16-D21+D25 -> 2308937.2 | E29: =IF((IFERROR(C29/B29,0))=0,0,(IFERROR(C29/B29,0)-1)) -> 0.36372437 | F29: =IF((IFERROR(C29/D29,0))=0,0,(IFERROR(C29/D29,0)-1)) -> -0.68002812
A30: CONSOLIDATED NET RESULTS | B30: =SUM(B26:B29) -> 10030922 | C30: =SUM(C26:C29) -> 4273863.8 | D30: =SUM(D26:D29) -> 5616329.3 | E30: =IF((IFERROR(C30/B30,0))=0,0,(IFERROR(C30/B30,0)-1)) -> -0.57393113 | F30: =IF((IFERROR(C30/D30,0))=0,0,(IFERROR(C30/D30,0)-1)) -> -0.23902899
B33: ='Resumen (Caps)'!D87 -> 9377742.4 | C33: ='Resumen (Caps)'!E87 -> 2563969.8 | D33: ='Resumen (Caps)'!F87 -> 904390.62
B34: ='Resumen (Caps)'!J87 -> -462807.79 | C34: ='Resumen (Caps)'!K87 -> 110021.59 | D34: ='Resumen (Caps)'!L87 -> 840995.7
B35: ='Resumen (Caps)'!P87 -> 574239.86 | C35: ='Resumen (Caps)'!Q87 -> 861077.45 | D35: ='Resumen (Caps)'!R87 -> 1562005.8
B36: ='Resumen (Caps)'!V87 -> 541748.02 | C36: ='Resumen (Caps)'!W87 -> 738794.98 | D36: ='Resumen (Caps)'!X87 -> 2308937.2
B37: =B26-B33 -> 0 | C37: =C26-C33 -> 0 | D37: =D26-D33 -> 0
B38: =B27-B34 -> 0 | C38: =C27-C34 -> 0 | D38: =D27-D34 -> 0
B39: =B28-B35 -> 0 | C39: =C28-C35 -> 0 | D39: =D28-D35 -> 0
B40: =B29-B36 -> 0 | C40: =C29-C36 -> 0 | D40: =D29-D36 -> 0

Sheet Resumen (Caps)
D1: MX | J1: GDL | P1: NE | V1: NO
D2: Real 2025 | E2: Ppto. 2026 | F2: Ppto. 2025 | G2: Variación Ppto. 2026 vs Real 2025 | H2: Variación Ppto. 2025 vs Ppto. 2026 | J2: Real 2025 | K2: Ppto. 2026 | L2: Ppto. 2025 | M2: Variación Ppto. 2026 vs Real 2025 | N2: Variación Ppto. 2025 vs Ppto. 2026 | P2: Real 2025 | Q2: Ppto. 2026 | R2: Ppto. 2025 | S2: Variación Ppto. 2026 vs Real 2025 | T2: Variación Ppto. 2025 vs Ppto. 2026 | V2: Real 2025 | W2: Ppto. 2026 | X2: Ppto. 2025 | Y2: Variación Ppto. 2026 vs Real 2025 | Z2: Variación Ppto. 2025 vs Ppto. 2026
C4: INCOME | D4: =SUM(D5,D8,D11,D16,D14) -> 64619514 | E4: =SUM(E5,E8,E11,E16,E14) -> 71683976 | F4: =SUM(F5,F8,F11,F16,F14) -> 62529782 | G4: =IF((IFERROR(E4/D4,0))=0,0,(IFERROR(E4/D4,0)-1)) -> 0.10932398 | H4: =IF((IFERROR(E4/F4,0))=0,0,(IFERROR(E4/F4,0)-1)) -> 0.14639734 | J4: =J5+J8+J11+J14+J16 -> 14195973 | K4: =K5+K8+K11+K14+K16 -> 17961606 | L4: =L5+L8+L11+L14+L16 -> 17294316 | M4: =IF((IFERROR(K4/J4,0))=0,0,(IFERROR(K4/J4,0)-1)) -> 0.26526067 | N4: =IF((IFERROR(K4/L4,0))=0,0,(IFERROR(K4/L4,0)-1)) -> 0.038584369 | P4: =P5+P8+P11+P14+P16 -> 32744833 | Q4: =Q5+Q8+Q11+Q14+Q16 -> 36605251 | R4: =R5+R8+R11+R14+R16 -> 34972433 | S4: =IF((IFERROR(Q4/P4,0))=0,0,(IFERROR(Q4/P4,0)-1)) -> 0.11789396 | T4: =IF((IFERROR(Q4/R4,0))=0,0,(IFERROR(Q4/R4,0)-1)) -> 0.046688705 | V4: =V5+V8+V11+V14+V16 -> 5116359.8 | W4: =W5+W8+W11+W14+W16 -> 6765685 | X4: =X5+X8+X11+X14+X16 -> 8173413.7 | Y4: =IF((IFERROR(W4/V4,0))=0,0,(IFERROR(W4/V4,0)-1)) -> 0.32236303 | Z4: =IF((IFERROR(W4/X4,0))=0,0,(IFERROR(W4/X4,0)-1)) -> -0.17223265
C5: Membership | D5: =D6+D7 -> 42611318 | E5: =E6+E7 -> 46872450 | F5: =F6+F7 -> 37282030 | G5: =IF((IFERROR(E5/D5,0))=0,0,(IFERROR(E5/D5,0)-1)) -> 0.1 | H5: =IF((IFERROR(E5/F5,0))=0,0,(IFERROR(E5/F5,0)-1)) -> 0.25723974 | J5: 10543077 | K5: 11782798 | L5: 10909089 | M5: =IF((IFERROR(K5/J5,0))=0,0,(IFERROR(K5/J5,0)-1)) -> 0.11758631 | N5: =IF((IFERROR(K5/L5,0))=0,0,(IFERROR(K5/L5,0)-1)) -> 0.080090036 | P5: 25323170 | Q5: 28947770 | R5: =24786483.33 -> 24786483 | S5: =IF((IFERROR(Q5/P5,0))=0,0,(IFERROR(Q5/P5,0)-1)) -> 0.14313377 | T5: =IF((IFERROR(Q5/R5,0))=0,0,(IFERROR(Q5/R5,0)-1)) -> 0.16788533 | V5: 4754009.8 | W5: 5828618 | X5: 7502413.7 | Y5: =IF((IFERROR(W5/V5,0))=0,0,(IFERROR(W5/V5,0)-1)) -> 0.2260425 | Z5: =IF((IFERROR(W5/X5,0))=0,0,(IFERROR(W5/X5,0)-1)) -> -0.22310096
B6: 401-000-000-00 | C6: Cuotas Netas | D6: =Resumen!I7 -> 41346034 | E6: =SUMIF('México Summary'!$C:$C,'Resumen (Caps)'!B6,'México Summary'!$AC:$AC) -> 45370058 | F6: 36117362 | G6: =IF((IFERROR(E6/D6,0))=0,0,(IFERROR(E6/D6,0)-1)) -> 0.097325506 | H6: =IF((IFERROR(E6/F6,0))=0,0,(IFERROR(E6/F6,0)-1)) -> 0.25618416 | P6: 24416653 | Q6: 28705760 | R6: 22877983 | V6: 4420176.4 | W6: 6426568.2 | X6: 6677913.7
B7: 402-000-000-00 | C7: Ingresos socios nuevos | D7: =Resumen!I8 -> 1265283.3 | E7: =SUMIF('México Summary'!$C:$C,'Resumen (Caps)'!B7,'México Summary'!$AC:$AC) -> 1502391.4 | F7: 1164667.8 | G7: =IF((IFERROR(E7/D7,0))=0,0,(IFERROR(E7/D7,0)-1)) -> 0.18739523 | H7: =IF((IFERROR(E7/F7,0))=0,0,(IFERROR(E7/F7,0)-1)) -> 0.2899742 | P7: 906516.99 | Q7: 1242010 | R7: 1908500 | V7: 333833.33 | W7: 402050 | X7: 824500
C8: Events | D8: =D9+D10 -> 12859605 | E8: =E9+E10 -> 11511191 | F8: =F9+F10 -> 12957002 | G8: =IF((IFERROR(E8/D8,0))=0,0,(IFERROR(E8/D8,0)-1)) -> -0.10485653 | H8: =IF((IFERROR(E8/F8,0))=0,0,(IFERROR(E8/F8,0)-1)) -> -0.1115853 | J8: 2311332.8 | K8: 3820000 | L8: 4100000 | M8: =IF((IFERROR(K8/J8,0))=0,0,(IFERROR(K8/J8,0)-1)) -> 0.65272611 | N8: =IF((IFERROR(K8/L8,0))=0,0,(IFERROR(K8/L8,0)-1)) -> -0.068292683 | P8: 3788994.6 | Q8: 4070000 | R8: 5632000 | S8: =IF((IFERROR(Q8/P8,0))=0,0,(IFERROR(Q8/P8,0)-1)) -> 0.074163579 | T8: =IF((IFERROR(Q8/R8,0))=0,0,(IFERROR(Q8/R8,0)-1)) -> -0.27734375 | V8: 294450 | W8: 710000 | X8: 440000 | Y8: =IF((IFERROR(W8/V8,0))=0,0,(IFERROR(W8/V8,0)-1)) -> 1.4112753 | Z8: =IF((IFERROR(W8/X8,0))=0,0,(IFERROR(W8/X8,0)-1)) -> 0.61363636
B9: 407-000-000-00 | C9: Eventos | D9: =Resumen!I10 -> 1856490.2 | E9: =SUMIF('México Summary'!$C:$C,'Resumen (Caps)'!B9,'México Summary'!$AC:$AC) -> 1460000 | F9: 2250000 | G9: =IF((IFERROR(E9/D9,0))=0,0,(IFERROR(E9/D9,0)-1)) -> -0.21356976 | H9: =IF((IFERROR(E9/F9,0))=0,0,(IFERROR(E9/F9,0)-1)) -> -0.35111111 | P9: 3788994.6 | Q9: 1476239.8 | R9: 5632000 | V9: 294450 | W9: 208395 | X9: 440000
B10: 408-000-000-00 | C10: Patrocinios | D10: =Resumen!I11 -> 11003115 | E10: =SUMIF('México Summary'!$C:$C,'Resumen (Caps)'!B10,'México Summary'!$AC:$AC) -> 10051191 | F10: 10707002 | G10: =IF((IFERROR(E10/D10,0))=0,0,(IFERROR(E10/D10,0)-1)) -> -0.086513996 | H10: =IF((IFERROR(E10/F10,0))=0,0,(IFERROR(E10/F10,0)-1)) -> -0.061250657 | P10: 0 | Q10: 4898758.1 | R10: 0 | V10: 0 | W10: 352000 | X10: 0
C11: Committees | D11: =D12+D13 -> 6702991 | E11: =E12+E13 -> 9775090 | F11: =F12+F13 -> 11450750 | G11: =IF((IFERROR(E11/D11,0))=0,0,(IFERROR(E11/D11,0)-1)) -> 0.45831765 | H11: =IF((IFERROR(E11/F11,0))=0,0,(IFERROR(E11/F11,0)-1)) -> -0.14633627 | J11: 756663.16 | K11: 1594590.7 | L11: 1718000 | M11: =IF((IFERROR(K11/J11,0))=0,0,(IFERROR(K11/J11,0)-1)) -> 1.1073983 | N11: =IF((IFERROR(K11/L11,0))=0,0,(IFERROR(K11/L11,0)-1)) -> -0.071833132 | P11: 1740806.7 | Q11: 2209360.8 | R11: 2593050 | S11: =IF((IFERROR(Q11/P11,0))=0,0,(IFERROR(Q11/P11,0)-1)) -> 0.26915913 | T11: =IF((IFERROR(Q11/R11,0))=0,0,(IFERROR(Q11/R11,0)-1)) -> -0.14796832 | V11: 0 | W11: 48000 | X11: 100000 | Y11: =IF((IFERROR(W11/V11,0))=0,0,(IFERROR(W11/V11,0)-1)) -> 0 | Z11: =IF((IFERROR(W11/X11,0))=0,0,(IFERROR(W11/X11,0)-1)) -> -0.52
B12: 417-000-000-00 | C12: Comités | D12: =Resumen!I13 -> 5748342.6 | E12: =SUMIF('México Summary'!$C:$C,'Resumen (Caps)'!B12,'México Summary'!$AC:$AC) -> 8675090 | F12: 10800750 | G12: =IF((IFERROR(E12/D12,0))=0,0,(IFERROR(E12/D12,0)-1)) -> 0.5091463 | H12: =IF((IFERROR(E12/F12,0))=0,0,(IFERROR(E12/F12,0)-1)) -> -0.1968067 | P12: 1740806.7 | Q12: 1663666.9 | R12: 2593050 | V12: 0 | W12: 22000 | X12: 100000
B13: 412-000-000-00 | C13: Economex | D13: =Resumen!I14 -> 954648.32 | E13: =SUMIF('México Summary'!$C:$C,'Resumen (Caps)'!B13,'México Summary'!$AC:$AC) -> 1100000 | F13: 650000 | G13: =IF((IFERROR(E13/D13,0))=0,0,(IFERROR(E13/D13,0)-1)) -> 0.15225678 | H13: =IF((IFERROR(E13/F13,0))=0,0,(IFERROR(E13/F13,0)-1)) -> 0.69230769 | P13: 1001862.1 | Q13: 403754 | R13: 1450000 | V13: 0 | W13: 74539.2 | X13: 0
C14: T&IC | D14: =D15 -> 0 | E14: =E15 -> 840000 | F14: =F15 -> 0 | G14: =IF((IFERROR(E14/D14,0))=0,0,(IFERROR(E14/D14,0)-1)) -> 0 | H14: =IF((IFERROR(E14/F14,0))=0,0,(IFERROR(E14/F14,0)-1)) -> 0 | J14: 0 | K14: 50000 | L14: 0 | M14: 1 | N14: =IF((IFERROR(K14/L14,0))=0,0,(IFERROR(K14/L14,0)-1)) -> 0 | P14: 1001862 | Q14: 460000 | R14: 1450000 | S14: =IF((IFERROR(Q14/P14,0))=0,0,(IFERROR(Q14/P14,0)-1)) -> -0.54085493 | T14: =IF((IFERROR(Q14/R14,0))=0,0,(IFERROR(Q14/R14,0)-1)) -> -0.68275862 | V14: 0 | W14: 80000 | X14: 0 | Y14: =IF((IFERROR(W14/V14,0))=0,0,(IFERROR(W14/V14,0)-1)) -> 0 | Z14: =IF((IFERROR(W14/X14,0))=0,0,(IFERROR(W14/X14,0)-1)) -> 0
B15: 405-000-000-00 | C15: Trade & Investment Center | D15: =Resumen!I16 -> 0 | E15: =SUMIF('México Summary'!$C:$C,'Resumen (Caps)'!B15,'México Summary'!$AC:$AC) -> 840000 | F15: 0 | G15: =IF((IFERROR(E15/D15,0))=0,0,(IFERROR(E15/D15,0)-1)) -> 0 | H15: =IF((IFERROR(E15/F15,0))=0,0,(IFERROR(E15/F15,0)-1)) -> 0
C16: Services to Members | D16: =D17+D19+D18 -> 2445600 | E16: =E17+E19+E18 -> 2685245 | F16: =F17+F19+F18 -> 840000 | G16: =IF((IFERROR(E16/D16,0))=0,0,(IFERROR(E16/D16,0)-1)) -> 0.097990268 | H16: =IF((IFERROR(E16/F16,0))=0,0,(IFERROR(E16/F16,0)-1)) -> 2.1967202 | J16: 584900 | K16: 714217.04 | L16: 567226.8 | M16: =IF((IFERROR(K16/J16,0))=0,0,(IFERROR(K16/J16,0)-1)) -> 0.22109256 | N16: =IF((IFERROR(K16/L16,0))=0,0,(IFERROR(K16/L16,0)-1)) -> 0.25913839 | P16: 890000 | Q16: 918120 | R16: 510900 | S16: =IF((IFERROR(Q16/P16,0))=0,0,(IFERROR(Q16/P16,0)-1)) -> 0.031595506 | T16: =IF((IFERROR(Q16/R16,0))=0,0,(IFERROR(Q16/R16,0)-1)) -> 0.797064 | V16: 67900 | W16: 99067 | X16: 131000 | Y16: =IF((IFERROR(W16/V16,0))=0,0,(IFERROR(W16/V16,0)-1)) -> 0.45901325 | Z16: =IF((IFERROR(W16/X16,0))=0,0,(IFERROR(W16/X16,0)-1)) -> -0.24376336
B17: 406-001-000-00 | C17: Venta Publicaciones | D17: =Resumen!I18 -> 1292600 | E17: =SUMIF('México Summary'!$C:$C,'Resumen (Caps)'!B17,'México Summary'!$AC:$AC) -> 1232595 | F17: 840000 | G17: =IF((IFERROR(E17/D17,0))=0,0,(IFERROR(E17/D17,0)-1)) -> -0.04642194 | H17: =IF((IFERROR(E17/F17,0))=0,0,(IFERROR(E17/F17,0)-1)) -> 0.467375
B18: 406-002-000-00 | C18: Digital Training | D18: =Resumen!I19 -> 1153000 | E18: =SUMIF('México Summary'!$C:$C,'Resumen (Caps)'!B18,'México Summary'!$AC:$AC) -> 1452650 | F18: 0 | G18: =IF((IFERROR(E18/D18,0))=0,0,(IFERROR(E18/D18,0)-1)) -> 0.25988725 | H18: =IF((IFERROR(E18/F18,0))=0,0,(IFERROR(E18/F18,0)-1)) -> 0
B19: 409-000-000-00 | C19: Visas | D19: =Resumen!I20 -> 0 | E19: =SUMIF('México Summary'!$C:$C,'Resumen (Caps)'!B19,'México Summary'!$AC:$AC) -> 0 | F19: 0 | G19: =IF((IFERROR(E19/D19,0))=0,0,(IFERROR(E19/D19,0)-1)) -> 0 | H19: =IF((IFERROR(E19/F19,0))=0,0,(IFERROR(E19/F19,0)-1)) -> 0
B20: 450-001-000-00 | C20: Guadalajara Income | D20: =Resumen!I21 -> 14196189 | E20: =SUMIF('México Summary'!$C:$C,'Resumen (Caps)'!B20,'México Summary'!$AC:$AC) -> 0 | F20: 0 | G20: =IF((IFERROR(E20/D20,0))=0,0,(IFERROR(E20/D20,0)-1)) -> 0 | H20: =IF((IFERROR(E20/F20,0))=0,0,(IFERROR(E20/F20,0)-1)) -> 0
B21: 450-002-000-00 | C21: Monterrey Income | D21: =Resumen!I22 -> 32894975 | E21: =SUMIF('México Summary'!$C:$C,'Resumen (Caps)'!B21,'México Summary'!$AC:$AC) -> 0 | F21: 0 | G21: =IF((IFERROR(E21/D21,0))=0,0,(IFERROR(E21/D21,0)-1)) -> 0 | H21: =IF((IFERROR(E21/F21,0))=0,0,(IFERROR(E21/F21,0)-1)) -> 0
B22: 450-003-000-00 | C22: Northwest Income | D22: =Resumen!I23 -> 5116359.8 | E22: =SUMIF('México Summary'!$C:$C,'Resumen (Caps)'!B22,'México Summary'!$AC:$AC) -> 0 | F22: 0 | G22: =IF((IFERROR(E22/D22,0))=0,0,(IFERROR(E22/D22,0)-1)) -> 0 | H22: =IF((IFERROR(E22/F22,0))=0,0,(IFERROR(E22/F22,0)-1)) -> 0
C23: CONSOLIDATED INCOME | D23: =D22+D21+D20+D4 -> 1.1682704e+08 | E23: =E22+E21+E20+E4 -> 71683976 | F23: =F22+F21+F20+F4 -> 62529782 | G23: =IF((IFERROR(E23/D23,0))=0,0,(IFERROR(E23/D23,0)-1)) -> -0.38640936 | H23: =IF((IFERROR(E23/F23,0))=0,0,(IFERROR(E23/F23,0)-1)) -> 0.14639734
C24: EXPENSE | D24: =D25+D28+D30+D36+D39+D53+D54+D62 -> 61247285 | E24: =E25+E28+E30+E36+E39+E53+E54+E62+E34 -> 69120006 | F24: =F25+F28+F30+F36+F39+F53+F54+F62 -> 61625391 | G24: =IF((IFERROR(E24/D24,0))=0,0,(IFERROR(E24/D24,0)-1)) -> 0.12853991 | H24: =IF((IFERROR(E24/F24,0))=0,0,(IFERROR(E24/F24,0)-1)) -> 0.12161569 | J24: =J25+J28+J30+J34+J36+J39+J53+J54+J62 -> 14658996 | K24: =K25+K28+K30+K34+K36+K39+K53+K54+K62 -> 17851585 | L24: =L25+L28+L30+L34+L36+L39+L53+L54+L62 -> 16453320 | M24: =IF((IFERROR(K24/J24,0))=0,0,(IFERROR(K24/J24,0)-1)) -> 0.21779036 | N24: =IF((IFERROR(K24/L24,0))=0,0,(IFERROR(K24/L24,0)-1)) -> 0.084983721 | P24: =P25+P28+P30+P34+P36+P39+P53+P54+P62 -> 32320735 | Q24: =Q25+Q28+Q30+Q34+Q36+Q39+Q53+Q54+Q62 -> 35744174 | R24: =R25+R28+R30+R34+R36+R39+R53+R54+R62 -> 33410428 | S24: =IF((IFERROR(Q24/P24,0))=0,0,(IFERROR(Q24/P24,0)-1)) -> 0.10592082 | T24: =IF((IFERROR(Q24/R24,0))=0,0,(IFERROR(Q24/R24,0)-1)) -> 0.069850825 | V24: =V25+V28+V30+V34+V36+V39+V53+V54+V62 -> 4574611.7 | W24: =W25+W28+W30+W34+W36+W39+W53+W54+W62 -> 6026890 | X24: =X25+X28+X30+X34+X36+X39+X53+X54+X62 -> 5864476.4 | Y24: =IF((IFERROR(W24/V24,0))=0,0,(IFERROR(W24/V24,0)-1)) -> 0.31746482 | Z24: =IF((IFERROR(W24/X24,0))=0,0,(IFERROR(W24/X24,0)-1)) -> 0.027694472
C25: Membership | D25: =D26+D27 -> 2207503.3 | E25: =E26+E27 -> 2949107.9 | F25: =F26+F27 -> 2584139.3 | G25: =IF((IFERROR(E25/D25,0))=0,0,(IFERROR(E25/D25,0)-1)) -> 0.33594723 | H25: =IF((IFERROR(E25/F25,0))=0,0,(IFERROR(E25/F25,0)-1)) -> 0.14123409 | J25: 567446.96 | K25: 493042.52 | L25: 675870.6 | M25: =IF((IFERROR(K25/J25,0))=0,0,(IFERROR(K25/J25,0)-1)) -> -0.1311214 | N25: =IF((IFERROR(K25/L25,0))=0,0,(IFERROR(K25/L25,0)-1)) -> -0.27050752 | P25: 1650853.2 | Q25: 1901079.6 | R25: 2224320 | S25: =IF((IFERROR(Q25/P25,0))=0,0,(IFERROR(Q25/P25,0)-1)) -> 0.15157401 | T25: =IF((IFERROR(Q25/R25,0))=0,0,(IFERROR(Q25/R25,0)-1)) -> -0.14532097 | V25: 398459.21 | W25: 369485.92 | X25: 618375 | Y25: =IF((IFERROR(W25/V25,0))=0,0,(IFERROR(W25/V25,0)-1)) -> -0.072713315 | Z25: =IF((IFERROR(W25/X25,0))=0,0,(IFERROR(W25/X25,0)-1)) -> -0.40248891
B26: 705-000-000-00 | C26: Gastos Promoción | D26: =Resumen!I27 -> 225000 | E26: =SUMIF('México Summary'!$C:$C,'Resumen (Caps)'!B26,'México Summary'!$AC:$AC) -> 887380 | F26: 863500 | G26: =IF((IFERROR(E26/D26,0))=0,0,(IFERROR(E26/D26,0)-1)) -> 2.9439111 | H26: =IF((IFERROR(E26/F26,0))=0,0,(IFERROR(E26/F26,0)-1)) -> 0.027654893 | P26: 1215514.1 | Q26: 1447993.8 | R26: 1804320
B27: 520-000-000-00 | C27: Comsiones por venta de membresía | D27: =Resumen!I28 -> 1982503.3 | E27: =SUMIF('México Summary'!$C:$C,'Resumen (Caps)'!B27,'México Summary'!$AC:$AC) -> 2061727.9 | F27: 1720639.3 | G27: =IF((IFERROR(E27/D27,0))=0,0,(IFERROR(E27/D27,0)-1)) -> 0.039961902 | H27: =IF((IFERROR(E27/F27,0))=0,0,(IFERROR(E27/F27,0)-1)) -> 0.19823362 | P27: 435339.09 | Q27: 453085.89 | R27: 420000
C28: Events | D28: =D29 -> 8546422.2 | E28: =E29 -> 6727036.8 | F28: =F29 -> 9107000 | G28: =IF((IFERROR(E28/D28,0))=0,0,(IFERROR(E28/D28,0)-1)) -> -0.21288269 | H28: =IF((IFERROR(E28/F28,0))=0,0,(IFERROR(E28/F28,0)-1)) -> -0.26133339 | J28: 1496260.2 | K28: 2660000 | L28: 2956045 | M28: =IF((IFERROR(K28/J28,0))=0,0,(IFERROR(K28/J28,0)-1)) -> 0.7777656 | N28: =IF((IFERROR(K28/L28,0))=0,0,(IFERROR(K28/L28,0)-1)) -> -0.10014902 | P28: 3151924.3 | Q28: 3015000 | R28: 4450000 | S28: =IF((IFERROR(Q28/P28,0))=0,0,(IFERROR(Q28/P28,0)-1)) -> -0.0434415 | T28: =IF((IFERROR(Q28/R28,0))=0,0,(IFERROR(Q28/R28,0)-1)) -> -0.32247191 | V28: 129166.8 | W28: 442000 | X28: 270000 | Y28: =IF((IFERROR(W28/V28,0))=0,0,(IFERROR(W28/V28,0)-1)) -> 2.421932 | Z28: =IF((IFERROR(W28/X28,0))=0,0,(IFERROR(W28/X28,0)-1)) -> 0.63703704
B29: 701-000-000-00 | C29: Costo Eventos | D29: =Resumen!I30 -> 8546422.2 | E29: =SUMIF('México Summary'!$C:$C,'Resumen (Caps)'!B29,'México Summary'!$AC:$AC) -> 6727036.8 | F29: 9107000 | G29: =IF((IFERROR(E29/D29,0))=0,0,(IFERROR(E29/D29,0)-1)) -> -0.21288269 | H29: =IF((IFERROR(E29/F29,0))=0,0,(IFERROR(E29/F29,0)-1)) -> -0.26133339 | P29: 3151924.3 | Q29: 4244536.5 | R29: 4450000
C30: Committees | D30: =SUM(D31:D33) -> 4258755.3 | E30: =SUM(E31:E33) -> 6940491.4 | F30: =SUM(F31:F33) -> 8604867.1 | G30: =IF((IFERROR(E30/D30,0))=0,0,(IFERROR(E30/D30,0)-1)) -> 0.6296995 | H30: =IF((IFERROR(E30/F30,0))=0,0,(IFERROR(E30/F30,0)-1)) -> -0.19342258 | J30: 644237.57 | K30: 1004784.9 | L30: 896480 | M30: =IF((IFERROR(K30/J30,0))=0,0,(IFERROR(K30/J30,0)-1)) -> 0.55964962 | N30: =IF((IFERROR(K30/L30,0))=0,0,(IFERROR(K30/L30,0)-1)) -> 0.12081126 | P30: 1200608.4 | Q30: 1537330.2 | R30: 1744550 | S30: =IF((IFERROR(Q30/P30,0))=0,0,(IFERROR(Q30/P30,0)-1)) -> 0.28045936 | T30: =IF((IFERROR(Q30/R30,0))=0,0,(IFERROR(Q30/R30,0)-1)) -> -0.11878121 | V30: 0 | W30: 24000 | X30: 60000 | Y30: =IF((IFERROR(W30/V30,0))=0,0,(IFERROR(W30/V30,0)-1)) -> 0 | Z30: =IF((IFERROR(W30/X30,0))=0,0,(IFERROR(W30/X30,0)-1)) -> -0.6
B31: 702-000-000-00 | C31: Costo Comités | D31: =Resumen!I32 -> 3073058.1 | E31: =SUMIF('México Summary'!$C:$C,'Resumen (Caps)'!B31,'México Summary'!$AC:$AC) -> 5438618.2 | F31: 7363267.1 | G31: =IF((IFERROR(E31/D31,0))=0,0,(IFERROR(E31/D31,0)-1)) -> 0.76977395 | H31: =IF((IFERROR(E31/F31,0))=0,0,(IFERROR(E31/F31,0)-1)) -> -0.26138517 | P31: 1200608.4 | Q31: 1495707.2 | R31: 1744550
B32: 704-000-000-00 | C32: Costo Economex | D32: =Resumen!I33 -> 1050317.2 | E32: =SUMIF('México Summary'!$C:$C,'Resumen (Caps)'!B32,'México Summary'!$AC:$AC) -> 1299254 | F32: 1081600 | G32: =IF((IFERROR(E32/D32,0))=0,0,(IFERROR(E32/D32,0)-1)) -> 0.23701111 | H32: =IF((IFERROR(E32/F32,0))=0,0,(IFERROR(E32/F32,0)-1)) -> 0.20123336 | P32: 0 | Q32: 0 | R32: 0
B33: 521-000-000-00 | C33: Comisiones EWDP y Economex | D33: =Resumen!I34 -> 135380.03 | E33: =SUMIF('México Summary'!$C:$C,'Resumen (Caps)'!B33,'México Summary'!$AC:$AC) -> 202619.2 | F33: 160000 | G33: =IF((IFERROR(E33/D33,0))=0,0,(IFERROR(E33/D33,0)-1)) -> 0.49666978 | H33: =IF((IFERROR(E33/F33,0))=0,0,(IFERROR(E33/F33,0)-1)) -> 0.26637 | P33: 412057.39 | Q33: 144690 | R33: 1250000
C34: T&IC | D34: =D35 -> 0 | E34: =E35 -> 340000 | F34: =F35 -> 0 | G34: =IF((IFERROR(E34/D34,0))=0,0,(IFERROR(E34/D34,0)-1)) -> 0 | H34: =IF((IFERROR(E34/F34,0))=0,0,(IFERROR(E34/F34,0)-1)) -> 0 | J34: 0 | K34: 25000 | L34: 0 | M34: 1 | N34: =IF((IFERROR(K34/L34,0))=0,0,(IFERROR(K34/L34,0)-1)) -> 0 | P34: 412057.39 | Q34: 230000 | R34: 1250000 | S34: =IF((IFERROR(Q34/P34,0))=0,0,(IFERROR(Q34/P34,0)-1)) -> -0.44182532 | T34: =IF((IFERROR(Q34/R34,0))=0,0,(IFERROR(Q34/R34,0)-1)) -> -0.816 | V34: 0 | W34: 40000 | X34: 0 | Y34: =IF((IFERROR(W34/V34,0))=0,0,(IFERROR(W34/V34,0)-1)) -> 0 | Z34: =IF((IFERROR(W34/X34,0))=0,0,(IFERROR(W34/X34,0)-1)) -> 0
B35: 703-000-000-00 | C35: Costo Trade & Investment Center | D35: =Resumen!I36 -> 0 | E35: =SUMIF('México Summary'!$C:$C,'Resumen (Caps)'!B35,'México Summary'!$AC:$AC) -> 340000 | F35: 0 | G35: =IF((IFERROR(E35/D35,0))=0,0,(IFERROR(E35/D35,0)-1)) -> 0 | H35: =IF((IFERROR(E35/F35,0))=0,0,(IFERROR(E35/F35,0)-1)) -> 0 | P35: 440250 | Q35: 459060 | R35: 286104
C36: Services to Members | D36: =D37+D38 -> 1151300.3 | E36: =E37+E38 -> 1268666.8 | F36: =F37+F38 -> 420000 | G36: =IF((IFERROR(E36/D36,0))=0,0,(IFERROR(E36/D36,0)-1)) -> 0.10194259 | H36: =IF((IFERROR(E36/F36,0))=0,0,(IFERROR(E36/F36,0)-1)) -> 2.0206352 | J36: 292450 | K36: 357108.52 | L36: 283613.4 | M36: =IF((IFERROR(K36/J36,0))=0,0,(IFERROR(K36/J36,0)-1)) -> 0.22109256 | N36: =IF((IFERROR(K36/L36,0))=0,0,(IFERROR(K36/L36,0)-1)) -> 0.25913839 | P36: 440250 | Q36: 459060 | R36: 286104 | S36: =IF((IFERROR(Q36/P36,0))=0,0,(IFERROR(Q36/P36,0)-1)) -> 0.042725724 | T36: =IF((IFERROR(Q36/R36,0))=0,0,(IFERROR(Q36/R36,0)-1)) -> 0.60452143 | V36: 33950 | W36: 49533.5 | X36: 65500 | Y36: =IF((IFERROR(W36/V36,0))=0,0,(IFERROR(W36/V36,0)-1)) -> 0.45901325 | Z36: =IF((IFERROR(W36/X36,0))=0,0,(IFERROR(W36/X36,0)-1)) -> -0.24376336
B37: 601-002-003-00 | C37: Costo Venta Publicaciones | D37: =Resumen!I38 -> 574300 | E37: =SUMIF('México Summary'!$C:$C,'Resumen (Caps)'!B37,'México Summary'!$AC:$AC) -> 542341.8 | F37: 420000 | G37: =IF((IFERROR(E37/D37,0))=0,0,(IFERROR(E37/D37,0)-1)) -> -0.055647223 | H37: =IF((IFERROR(E37/F37,0))=0,0,(IFERROR(E37/F37,0)-1)) -> 0.29129
B38: 601-003-001-00 | C38: Costo Digital Training | D38: =Resumen!I39 -> 577000.27 | E38: =SUMIF('México Summary'!$C:$C,'Resumen (Caps)'!B38,'México Summary'!$AC:$AC) -> 726325 | F38: 0 | G38: =IF((IFERROR(E38/D38,0))=0,0,(IFERROR(E38/D38,0)-1)) -> 0.2587949 | H38: =IF((IFERROR(E38/F38,0))=0,0,(IFERROR(E38/F38,0)-1)) -> 0
C39: Gastos Administrativos | D39: =SUM(D40:D52) -> 4160868.6 | E39: =SUM(E40:E52) -> 4705358 | F39: =SUM(F40:F52) -> 5070086.1 | G39: =IF((IFERROR(E39/D39,0))=0,0,(IFERROR(E39/D39,0)-1)) -> 0.13085955 | H39: =IF((IFERROR(E39/F39,0))=0,0,(IFERROR(E39/F39,0)-1)) -> -0.071937258 | J39: 302430.6 | K39: 496408.94 | L39: 532937.82 | M39: =IF((IFERROR(K39/J39,0))=0,0,(IFERROR(K39/J39,0)-1)) -> 0.64139786 | N39: =IF((IFERROR(K39/L39,0))=0,0,(IFERROR(K39/L39,0)-1)) -> -0.06854248 | P39: 791370.32 | Q39: 995988.15 | R39: 935209.05 | S39: =IF((IFERROR(Q39/P39,0))=0,0,(IFERROR(Q39/P39,0)-1)) -> 0.25856142 | T39: =IF((IFERROR(Q39/R39,0))=0,0,(IFERROR(Q39/R39,0)-1)) -> 0.064989854 | V39: 346977.56 | W39: 1117643.7 | X39: 1615380.4 | Y39: =IF((IFERROR(W39/V39,0))=0,0,(IFERROR(W39/V39,0)-1)) -> 2.2210835 | Z39: =IF((IFERROR(W39/X39,0))=0,0,(IFERROR(W39/X39,0)-1)) -> -0.30812351
B40: 801-001-000-00 | C40: Desarrollo de Negocios | D40: =Resumen!I41 -> 448434.14 | E40: =SUMIF('México Summary'!$C:$C,'Resumen (Caps)'!B40,'México Summary'!$AC:$AC) -> 656495.11 | F40: 579831.32 | G40: =IF((IFERROR(E40/D40,0))=0,0,(IFERROR(E40/D40,0)-1)) -> 0.46397219 | H40: =IF((IFERROR(E40/F40,0))=0,0,(IFERROR(E40/F40,0)-1)) -> 0.1322174 | P40: 3082099.9 | Q40: 4240697.9 | R40: 3404584.7
B41: 801-002-000-00 | C41: Relaciones Externas | D41: =Resumen!I42 -> 0 | E41: =SUMIF('México Summary'!$C:$C,'Resumen (Caps)'!B41,'México Summary'!$AC:$AC) -> 0 | F41: 0 | G41: =IF((IFERROR(E41/D41,0))=0,0,(IFERROR(E41/D41,0)-1)) -> 0 | H41: =IF((IFERROR(E41/F41,0))=0,0,(IFERROR(E41/F41,0)-1)) -> 0
B42: 801-003-000-00 | C42: Servicios a las membresia | D42: =Resumen!I43 -> 0 | E42: =SUMIF('México Summary'!$C:$C,'Resumen (Caps)'!B42,'México Summary'!$AC:$AC) -> 0 | F42: 0 | G42: =IF((IFERROR(E42/D42,0))=0,0,(IFERROR(E42/D42,0)-1)) -> 0 | H42: =IF((IFERROR(E42/F42,0))=0,0,(IFERROR(E42/F42,0)-1)) -> 0
B43: 801-004-000-00 | C43: Vicepresidencia | D43: =Resumen!I44 -> 705009.98 | E43: =SUMIF('México Summary'!$C:$C,'Resumen (Caps)'!B43,'México Summary'!$AC:$AC) -> 924190.86 | F43: 1145597.2 | G43: =IF((IFERROR(E43/D43,0))=0,0,(IFERROR(E43/D43,0)-1)) -> 0.31089046 | H43: =IF((IFERROR(E43/F43,0))=0,0,(IFERROR(E43/F43,0)-1)) -> -0.19326718
B44: 801-005-000-00 | C44: Finanzas | D44: =Resumen!I45 -> 351191.16 | E44: =SUMIF('México Summary'!$C:$C,'Resumen (Caps)'!B44,'México Summary'!$AC:$AC) -> 467017.59 | F44: 747879.2 | G44: =IF((IFERROR(E44/D44,0))=0,0,(IFERROR(E44/D44,0)-1)) -> 0.32981021 | H44: =IF((IFERROR(E44/F44,0))=0,0,(IFERROR(E44/F44,0)-1)) -> -0.37554408
B45: 801-006-000-00 | C45: Administración | D45: =Resumen!I46 -> 150603.26 | E45: =SUMIF('México Summary'!$C:$C,'Resumen (Caps)'!B45,'México Summary'!$AC:$AC) -> 395072.91 | F45: 158700 | G45: =IF((IFERROR(E45/D45,0))=0,0,(IFERROR(E45/D45,0)-1)) -> 1.6232693 | H45: =IF((IFERROR(E45/F45,0))=0,0,(IFERROR(E45/F45,0)-1)) -> 1.4894323
B46: 801-007-000-00 | C46: Sistemas | D46: =Resumen!I47 -> 0 | E46: =SUMIF('México Summary'!$C:$C,'Resumen (Caps)'!B46,'México Summary'!$AC:$AC) -> 0 | F46: 0 | G46: =IF((IFERROR(E46/D46,0))=0,0,(IFERROR(E46/D46,0)-1)) -> 0 | H46: =IF((IFERROR(E46/F46,0))=0,0,(IFERROR(E46/F46,0)-1)) -> 0
B47: 801-008-000-00 | C47: Empleos | D47: =Resumen!I48 -> 0 | E47: =SUMIF('México Summary'!$C:$C,'Resumen (Caps)'!B47,'México Summary'!$AC:$AC) -> 0 | F47: 0 | G47: =IF((IFERROR(E47/D47,0))=0,0,(IFERROR(E47/D47,0)-1)) -> 0 | H47: =IF((IFERROR(E47/F47,0))=0,0,(IFERROR(E47/F47,0)-1)) -> 0
B48: 801-009-000-00 | C48: Servicios Generales (Almacén) | D48: =Resumen!I49 -> 0 | E48: =SUMIF('México Summary'!$C:$C,'Resumen (Caps)'!B48,'México Summary'!$AC:$AC) -> 0 | F48: 0 | G48: =IF((IFERROR(E48/D48,0))=0,0,(IFERROR(E48/D48,0)-1)) -> 0 | H48: =IF((IFERROR(E48/F48,0))=0,0,(IFERROR(E48/F48,0)-1)) -> 0
B49: 801-010-000-00 | C49: Eventos | D49: =Resumen!I50 -> 404903.39 | E49: =SUMIF('México Summary'!$C:$C,'Resumen (Caps)'!B49,'México Summary'!$AC:$AC) -> 625945.18 | F49: 452700 | G49: =IF((IFERROR(E49/D49,0))=0,0,(IFERROR(E49/D49,0)-1)) -> 0.54591242 | H49: =IF((IFERROR(E49/F49,0))=0,0,(IFERROR(E49/F49,0)-1)) -> 0.38269313
B50: 801-011-000-00 | C50: Comites | D50: =Resumen!I51 -> 618233.64 | E50: =SUMIF('México Summary'!$C:$C,'Resumen (Caps)'!B50,'México Summary'!$AC:$AC) -> 781454.96 | F50: 493958.4 | G50: =IF((IFERROR(E50/D50,0))=0,0,(IFERROR(E50/D50,0)-1)) -> 0.26401235 | H50: =IF((IFERROR(E50/F50,0))=0,0,(IFERROR(E50/F50,0)-1)) -> 0.58202585
B51: 801-012-000-00 | C51: Renta de Salas | D51: =Resumen!I52 -> 0 | E51: =SUMIF('México Summary'!$C:$C,'Resumen (Caps)'!B51,'México Summary'!$AC:$AC) -> 0 | F51: 0 | G51: =IF((IFERROR(E51/D51,0))=0,0,(IFERROR(E51/D51,0)-1)) -> 0 | H51: =IF((IFERROR(E51/F51,0))=0,0,(IFERROR(E51/F51,0)-1)) -> 0
B52: 801-013-000-00 | C52: Comunicación | D52: =Resumen!I53 -> 1482493.1 | E52: =SUMIF('México Summary'!$C:$C,'Resumen (Caps)'!B52,'México Summary'!$AC:$AC) -> 855181.42 | F52: 1491420 | G52: =IF((IFERROR(E52/D52,0))=0,0,(IFERROR(E52/D52,0)-1)) -> -0.42314643 | H52: =IF((IFERROR(E52/F52,0))=0,0,(IFERROR(E52/F52,0)-1)) -> -0.4265992
B53: 901-000-000-00 | C53: Gastos Generales | D53: =Resumen!I54 -> 7935477.4 | E53: =SUMIF('México Summary'!$C:$C,'Resumen (Caps)'!B53,'México Summary'!$AC:$AC) -> 8506216.4 | F53: 8413203.5 | G53: =IF((IFERROR(E53/D53,0))=0,0,(IFERROR(E53/D53,0)-1)) -> 0.071922446 | H53: =IF((IFERROR(E53/F53,0))=0,0,(IFERROR(E53/F53,0)-1)) -> 0.011055585 | J53: 1477901.2 | K53: 1774271.9 | L53: 1467280.1 | M53: =IF((IFERROR(K53/J53,0))=0,0,(IFERROR(K53/J53,0)-1)) -> 0.20053485 | N53: =IF((IFERROR(K53/L53,0))=0,0,(IFERROR(K53/L53,0)-1)) -> 0.20922509 | P53: 3082100 | Q53: 4329365.6 | R53: 3404585 | S53: =IF((IFERROR(Q53/P53,0))=0,0,(IFERROR(Q53/P53,0)-1)) -> 0.40468044 | T53: =IF((IFERROR(Q53/R53,0))=0,0,(IFERROR(Q53/R53,0)-1)) -> 0.27162799 | V53: 166257.16 | W53: 311397.45 | X53: 213513.03 | Y53: =IF((IFERROR(W53/V53,0))=0,0,(IFERROR(W53/V53,0)-1)) -> 0.8729867 | Z53: =IF((IFERROR(W53/X53,0))=0,0,(IFERROR(W53/X53,0)-1)) -> 0.45844706
C54: Nómina | D54: =SUM(D55:D61) -> 17959246 | E54: =SUM(E55:E61) -> 18493809 | F54: =SUM(F55:F61) -> 13119015 | G54: =IF((IFERROR(E54/D54,0))=0,0,(IFERROR(E54/D54,0)-1)) -> 0.029765345 | H54: =IF((IFERROR(E54/F54,0))=0,0,(IFERROR(E54/F54,0)-1)) -> 0.40969495 | J54: 5850740.2 | K54: 6711987.8 | L54: 5720425.7 | M54: =IF((IFERROR(K54/J54,0))=0,0,(IFERROR(K54/J54,0)-1)) -> 0.1472032 | N54: =IF((IFERROR(K54/L54,0))=0,0,(IFERROR(K54/L54,0)-1)) -> 0.17333713 | P54: 13272267 | Q54: 13206772 | R54: 10606138 | S54: =IF((IFERROR(Q54/P54,0))=0,0,(IFERROR(Q54/P54,0)-1)) -> -0.0049347606 | T54: =IF((IFERROR(Q54/R54,0))=0,0,(IFERROR(Q54/R54,0)-1)) -> 0.24520086 | V54: 2011347.6 | W54: 2292372.1 | X54: 1655980 | Y54: =IF((IFERROR(W54/V54,0))=0,0,(IFERROR(W54/V54,0)-1)) -> 0.13971954 | Z54: =IF((IFERROR(W54/X54,0))=0,0,(IFERROR(W54/X54,0)-1)) -> 0.38429943
B55: 513-000-000-00 | C55: Nomina Vicepresidencia | D55: =Resumen!I56 -> 601991.89 | E55: =SUMIF('México Summary'!$C:$C,'Resumen (Caps)'!B55,'México Summary'!$AC:$AC) -> 542438.28 | F55: 334036.73 | G55: =IF((IFERROR(E55/D55,0))=0,0,(IFERROR(E55/D55,0)-1)) -> -0.098927595 | H55: =IF((IFERROR(E55/F55,0))=0,0,(IFERROR(E55/F55,0)-1)) -> 0.62388814 | P55: 8319303.9 | Q55: 10069578 | R55: 8509522.2
B56: 517-000-000-00 | C56: Nomina Desarrollo de Negocios | D56: =Resumen!I57 -> 4517285.5 | E56: =SUMIF('México Summary'!$C:$C,'Resumen (Caps)'!B56,'México Summary'!$AC:$AC) -> 4883189.3 | F56: 3385754.8 | G56: =IF((IFERROR(E56/D56,0))=0,0,(IFERROR(E56/D56,0)-1)) -> 0.081000797 | H56: =IF((IFERROR(E56/F56,0))=0,0,(IFERROR(E56/F56,0)-1)) -> 0.44227492
B57: 516-000-000-00 | C57: Nomina Comites y Relaciones Externas | D57: =Resumen!I58 -> 5327063.1 | E57: =SUMIF('México Summary'!$C:$C,'Resumen (Caps)'!B57,'México Summary'!$AC:$AC) -> 5213492.5 | F57: 4088183.5 | G57: =IF((IFERROR(E57/D57,0))=0,0,(IFERROR(E57/D57,0)-1)) -> -0.02131955 | H57: =IF((IFERROR(E57/F57,0))=0,0,(IFERROR(E57/F57,0)-1)) -> 0.27525892
B58: 519-000-000-00 | C58: Nomina Comunicación | D58: =Resumen!I59 -> 1285252.2 | E58: =SUMIF('México Summary'!$C:$C,'Resumen (Caps)'!B58,'México Summary'!$AC:$AC) -> 1448842.1 | F58: 876475.57 | G58: =IF((IFERROR(E58/D58,0))=0,0,(IFERROR(E58/D58,0)-1)) -> 0.12728233 | H58: =IF((IFERROR(E58/F58,0))=0,0,(IFERROR(E58/F58,0)-1)) -> 0.6530319
B59: 515-000-000-00 | C59: Nomina Servicios a la Membresia | D59: =Resumen!I60 -> 1798050.7 | E59: =SUMIF('México Summary'!$C:$C,'Resumen (Caps)'!B59,'México Summary'!$AC:$AC) -> 1925404.1 | F59: 1506952.1 | G59: =IF((IFERROR(E59/D59,0))=0,0,(IFERROR(E59/D59,0)-1)) -> 0.070828575 | H59: =IF((IFERROR(E59/F59,0))=0,0,(IFERROR(E59/F59,0)-1)) -> 0.27768101
B60: 518-000-000-00 | C60: Nomina Eventos y Mercadotecnia | D60: =Resumen!I61 -> 876357.8 | E60: =SUMIF('México Summary'!$C:$C,'Resumen (Caps)'!B60,'México Summary'!$AC:$AC) -> 566664.36 | F60: 672955.21 | G60: =IF((IFERROR(E60/D60,0))=0,0,(IFERROR(E60/D60,0)-1)) -> -0.35338698 | H60: =IF((IFERROR(E60/F60,0))=0,0,(IFERROR(E60/F60,0)-1)) -> -0.1579464
B61: 514-000-000-00 | C61: Nomina Administración y Fiananzas | D61: =Resumen!I62 -> 3553244.7 | E61: =SUMIF('México Summary'!$C:$C,'Resumen (Caps)'!B61,'México Summary'!$AC:$AC) -> 3913778.5 | F61: 2254657 | G61: =IF((IFERROR(E61/D61,0))=0,0,(IFERROR(E61/D61,0)-1)) -> 0.10146608 | H61: =IF((IFERROR(E61/F61,0))=0,0,(IFERROR(E61/F61,0)-1)) -> 0.73586425
B62: 903-000-000-00 | C62: Gastos Corporativos | D62: =Resumen!I63 -> 15027712 | E62: =SUMIF('México Summary'!$C:$C,'Resumen (Caps)'!B62,'México Summary'!$AC:$AC) -> 19189320 | F62: 14307080 | G62: =IF((IFERROR(E62/D62,0))=0,0,(IFERROR(E62/D62,0)-1)) -> 0.27692888 | H62: =IF((IFERROR(E62/F62,0))=0,0,(IFERROR(E62/F62,0)-1)) -> 0.34124637 | J62: 4027529.7 | K62: 4328980 | L62: 3920667.6 | M62: =IF((IFERROR(K62/J62,0))=0,0,(IFERROR(K62/J62,0)-1)) -> 0.07484743 | N62: =IF((IFERROR(K62/L62,0))=0,0,(IFERROR(K62/L62,0)-1)) -> 0.10414358 | P62: 8319304 | Q62: 10069578 | R62: 8509522 | S62: =IF((IFERROR(Q62/P62,0))=0,0,(IFERROR(Q62/P62,0)-1)) -> 0.2103871 | T62: =IF((IFERROR(Q62/R62,0))=0,0,(IFERROR(Q62/R62,0)-1)) -> 0.18333066 | V62: 1488453.4 | W62: 1380457.3 | X62: 1365728.1 | Y62: =IF((IFERROR(W62/V62,0))=0,0,(IFERROR(W62/V62,0)-1)) -> -0.072555921 | Z62: =IF((IFERROR(W62/X62,0))=0,0,(IFERROR(W62/X62,0)-1)) -> 0.010784899
B63: 950-001-000-00 | C63: Guadalajara Expense | D63: =Resumen!I64 -> 14658996 | E63: =SUMIF('México Summary'!$C:$C,'Resumen (Caps)'!B63,'México Summary'!$AC:$AC) -> 0 | F63: 0 | G63: =IF((IFERROR(E63/D63,0))=0,0,(IFERROR(E63/D63,0)-1)) -> 0 | H63: =IF((IFERROR(E63/F63,0))=0,0,(IFERROR(E63/F63,0)-1)) -> 0
B64: 950-002-000-00 | C64: Monterrey Expense | D64: =Resumen!I65 -> 32320734 | E64: =SUMIF('México Summary'!$C:$C,'Resumen (Caps)'!B64,'México Summary'!$AC:$AC) -> 0 | F64: 0 | G64: =IF((IFERROR(E64/D64,0))=0,0,(IFERROR(E64/D64,0)-1)) -> 0 | H64: =IF((IFERROR(E64/F64,0))=0,0,(IFERROR(E64/F64,0)-1)) -> 0
B65: 950-003-000-00 | C65: Northwest Expense | D65: =Resumen!I66 -> 4574611.7 | E65: =SUMIF('México Summary'!$C:$C,'Resumen (Caps)'!B65,'México Summary'!$AC:$AC) -> 0 | F65: 0 | G65: =IF((IFERROR(E65/D65,0))=0,0,(IFERROR(E65/D65,0)-1)) -> 0 | H65: =IF((IFERROR(E65/F65,0))=0,0,(IFERROR(E65/F65,0)-1)) -> 0
C66: CONSOLIDATED EXPENSES | D66: =D65+D64+D63+D24 -> 1.1280163e+08 | E66: =E65+E64+E63+E24 -> 69120006 | F66: =F65+F64+F63+F24 -> 61625391 | G66: =IF((IFERROR(E66/D66,0))=0,0,(IFERROR(E66/D66,0)-1)) -> -0.38724283 | H66: =IF((IFERROR(E66/F66,0))=0,0,(IFERROR(E66/F66,0)-1)) -> 0.12161569
C68: OPERATING RESULTS MEXICO | D68: =D4-D24 -> 3372228.3 | E68: =E4-E24 -> 2563969.8 | F68: =F4-F24 -> 904390.62 | G68: =IF((IFERROR(E68/D68,0))=0,0,(IFERROR(E68/D68,0)-1)) -> -0.23968085 | H68: =IF((IFERROR(E68/F68,0))=0,0,(IFERROR(E68/F68,0)-1)) -> 1.8350247 | J68: =J4-J24 -> -463023.6 | K68: =K4-K24 -> 110021.59 | L68: =L4-L24 -> 840995.7 | M68: =IF((IFERROR(K68/J68,0))=0,0,(IFERROR(K68/J68,0)-1))*-1 -> 1.2376155 | N68: =IF((IFERROR(K68/L68,0))=0,0,(IFERROR(K68/L68,0)-1)) -> -0.86917699 | P68: =P4-P24 -> 424098.19 | Q68: =Q4-Q24 -> 861077.45 | R68: =R4-R24 -> 1562005.8 | S68: =IF((IFERROR(Q68/P68,0))=0,0,(IFERROR(Q68/P68,0)-1)) -> 1.0303728 | T68: =IF((IFERROR(Q68/R68,0))=0,0,(IFERROR(Q68/R68,0)-1)) -> -0.44873606 | V68: =V4-V24 -> 541748.02 | W68: =W4-W24 -> 738794.98 | X68: =X4-X24 -> 2308937.2 | Y68: =IF((IFERROR(W68/V68,0))=0,0,(IFERROR(W68/V68,0)-1)) -> 0.36372437 | Z68: =IF((IFERROR(W68/X68,0))=0,0,(IFERROR(W68/X68,0)-1)) -> -0.68002812
C69: OPERATING RESULTS GUADALAJARA | D69: =D20-D63 -> -462807.79 | E69: =E20-E63 -> 0 | F69: =F20-F63 -> 0 | G69: =IF((IFERROR(E69/D69,0))=0,0,(IFERROR(E69/D69,0)-1)) -> 0 | H69: =IF((IFERROR(E69/F69,0))=0,0,(IFERROR(E69/F69,0)-1)) -> 0
C70: OPERATING RESULTS MONTERREY | D70: =D21-D64 -> 574240.16 | E70: =E21-E64 -> 0 | F70: =F21-F64 -> 0 | G70: =IF((IFERROR(E70/D70,0))=0,0,(IFERROR(E70/D70,0)-1)) -> 0 | H70: =IF((IFERROR(E70/F70,0))=0,0,(IFERROR(E70/F70,0)-1)) -> 0
C71: OPERATING RESULTS NORTHWEST | D71: =D22-D65 -> 541748.02 | E71: =E22-E65 -> 0 | F71: =F22-F65 -> 0 | G71: =IF((IFERROR(E71/D71,0))=0,0,(IFERROR(E71/D71,0)-1)) -> 0 | H71: =IF((IFERROR(E71/F71,0))=0,0,(IFERROR(E71/F71,0)-1)) -> 0
C73: CONSOLIDATED OPERATING RESULTS | D73: =SUM(D68:D72) -> 4025408.7 | E73: =SUM(E68:E72) -> 2563969.8 | F73: =SUM(F68:F72) -> 904390.62 | G73: =IF((IFERROR(E73/D73,0))=0,0,(IFERROR(E73/D73,0)-1)) -> -0.36305356 | H73: =IF((IFERROR(E73/F73,0))=0,0,(IFERROR(E73/F73,0)-1)) -> 1.8350247
B75: 902-000-000-00 | C75: Member Centricity | D75: =Resumen!I76 -> 0 | E75: =SUMIF('México Summary'!$C:$C,'Resumen (Caps)'!B75,'México Summary'!$AC:$AC) -> 0 | F75: 0 | G75: =IF((IFERROR(E75/D75,0))=0,0,(IFERROR(E75/D75,0)-1)) -> 0 | H75: =IF((IFERROR(E75/F75,0))=0,0,(IFERROR(E75/F75,0)-1)) -> 0 | J75: 0 | K75: 0 | L75: 0 | M75: =IF((IFERROR(K75/J75,0))=0,0,(IFERROR(K75/J75,0)-1)) -> 0 | N75: =IF((IFERROR(K75/L75,0))=0,0,(IFERROR(K75/L75,0)-1)) -> 0 | P75: 0 | Q75: 0 | R75: 0 | S75: =IF((IFERROR(Q75/P75,0))=0,0,(IFERROR(Q75/P75,0)-1)) -> 0 | T75: =IF((IFERROR(Q75/R75,0))=0,0,(IFERROR(Q75/R75,0)-1)) -> 0 | V75: 0 | W75: 0 | X75: 0 | Y75: =IF((IFERROR(W75/V75,0))=0,0,(IFERROR(W75/V75,0)-1)) -> 0 | Z75: =IF((IFERROR(W75/X75,0))=0,0,(IFERROR(W75/X75,0)-1)) -> 0
C77: Other | D77: =SUM(D78:D81) -> 6005514 | E77: =SUM(E78:E81) -> 0 | F77: =SUM(F78:F81) -> 0 | G77: =IF((IFERROR(E77/D77,0))=0,0,(IFERROR(E77/D77,0)-1)) -> 0 | H77: =IF((IFERROR(E77/F77,0))=0,0,(IFERROR(E77/F77,0)-1)) -> 0 | J77: 215.81 | K77: 0 | L77: 0 | M77: =IF((IFERROR(K77/J77,0))=0,0,(IFERROR(K77/J77,0)-1)) -> 0 | N77: =IF((IFERROR(K77/L77,0))=0,0,(IFERROR(K77/L77,0)-1)) -> 0 | P77: 150141.67 | Q77: 0 | R77: 0 | S77: =IF((IFERROR(Q77/P77,0))=0,0,(IFERROR(Q77/P77,0)-1)) -> 0 | T77: =IF((IFERROR(Q77/R77,0))=0,0,(IFERROR(Q77/R77,0)-1)) -> 0 | V77: 0 | W77: 0 | X77: 0 | Y77: =IF((IFERROR(W77/V77,0))=0,0,(IFERROR(W77/V77,0)-1)) -> 0 | Z77: =IF((IFERROR(W77/X77,0))=0,0,(IFERROR(W77/X77,0)-1)) -> 0
B78: 413-000-000-00 | C78: Otros Ingresos | D78: =Resumen!I79 -> 53815.53 | E78: =SUMIF('México Summary'!$C:$C,'Resumen (Caps)'!B78,'México Summary'!$AC:$AC) -> 0 | F78: 0 | G78: =IF((IFERROR(E78/D78,0))=0,0,(IFERROR(E78/D78,0)-1)) -> 0 | H78: =IF((IFERROR(E78/F78,0))=0,0,(IFERROR(E78/F78,0)-1)) -> 0
B79: 414-000-000-00 | C79: Intereses Bancos | D79: =Resumen!I80 -> 7263697.4 | E79: =SUMIF('México Summary'!$C:$C,'Resumen (Caps)'!B79,'México Summary'!$AC:$AC) -> 0 | F79: 0 | G79: =IF((IFERROR(E79/D79,0))=0,0,(IFERROR(E79/D79,0)-1)) -> 0 | H79: =IF((IFERROR(E79/F79,0))=0,0,(IFERROR(E79/F79,0)-1)) -> 0
B80: 416-000-000-00 | C80: Utilidad Cambiaria Inversiones | D80: =Resumen!I81 -> -9880326.4 | E80: =SUMIF('México Summary'!$C:$C,'Resumen (Caps)'!B80,'México Summary'!$AC:$AC) -> 0 | F80: 0 | G80: =IF((IFERROR(E80/D80,0))=0,0,(IFERROR(E80/D80,0)-1)) -> 0 | H80: =IF((IFERROR(E80/F80,0))=0,0,(IFERROR(E80/F80,0)-1)) -> 0
B81: 418-000-000-00 | C81: Plusvalia/Minusvalia Portafolio Inversiones | D81: =Resumen!I82 -> 8568327.5 | E81: =SUMIF('México Summary'!$C:$C,'Resumen (Caps)'!B81,'México Summary'!$AC:$AC) -> 0 | F81: 0 | G81: =IF((IFERROR(E81/D81,0))=0,0,(IFERROR(E81/D81,0)-1)) -> 0 | H81: =IF((IFERROR(E81/F81,0))=0,0,(IFERROR(E81/F81,0)-1)) -> 0
C83: Guadalajara Other Income | D83: 0 | E83: 0 | F83: 0 | G83: =IF((IFERROR(E83/D83,0))=0,0,(IFERROR(E83/D83,0)-1)) -> 0 | H83: =IF((IFERROR(E83/F83,0))=0,0,(IFERROR(E83/F83,0)-1)) -> 0
C84: Monterrey Other Income | D84: 0 | E84: 0 | F84: 0 | G84: =IF((IFERROR(E84/D84,0))=0,0,(IFERROR(E84/D84,0)-1)) -> 0 | H84: =IF((IFERROR(E84/F84,0))=0,0,(IFERROR(E84/F84,0)-1)) -> 0
C85: Northwest Other Income | D85: 0 | E85: 0 | F85: 0 | G85: =IF((IFERROR(E85/D85,0))=0,0,(IFERROR(E85/D85,0)-1)) -> 0 | H85: =IF((IFERROR(E85/F85,0))=0,0,(IFERROR(E85/F85,0)-1)) -> 0
C87: NET RESULTS MEXICO | D87: =D68-D75+D77 -> 9377742.4 | E87: =E68-E75+E77 -> 2563969.8 | F87: =F68-F75+F77 -> 904390.62 | G87: =IF((IFERROR(E87/D87,0))=0,0,(IFERROR(E87/D87,0)-1)) -> -0.72658987 | H87: =IF((IFERROR(E87/F87,0))=0,0,(IFERROR(E87/F87,0)-1)) -> 1.8350247 | J87: =J68-J75+J77 -> -462807.79 | K87: =K68-K75+K77 -> 110021.59 | L87: =L68-L75+L77 -> 840995.7 | M87: =IF((IFERROR(K87/J87,0))=0,0,(IFERROR(K87/J87,0)-1))*-1 -> 1.2377263 | N87: =IF((IFERROR(K87/L87,0))=0,0,(IFERROR(K87/L87,0)-1)) -> -0.86917699 | P87: =P68-P75+P77 -> 574239.86 | Q87: =Q68-Q75+Q77 -> 861077.45 | R87: =R68-R75+R77 -> 1562005.8 | S87: =IF((IFERROR(Q87/P87,0))=0,0,(IFERROR(Q87/P87,0)-1)) -> 0.49950832 | T87: =IF((IFERROR(Q87/R87,0))=0,0,(IFERROR(Q87/R87,0)-1)) -> -0.44873606 | V87: =V68-V75+V77 -> 541748.02 | W87: =W68-W75+W77 -> 738794.98 | X87: =X68-X75+X77 -> 2308937.2 | Y87: =IF((IFERROR(W87/V87,0))=0,0,(IFERROR(W87/V87,0)-1)) -> 0.36372437 | Z87: =IF((IFERROR(W87/X87,0))=0,0,(IFERROR(W87/X87,0)-1)) -> -0.68002812
C88: NET RESULTS GUADALAJARA | D88: =D69+D83 -> -462807.79 | E88: =E69+E83 -> 0 | F88: =F69+F83 -> 0 | G88: =IF((IFERROR(E88/D88,0))=0,0,(IFERROR(E88/D88,0)-1)) -> 0 | H88: =IF((IFERROR(E88/F88,0))=0,0,(IFERROR(E88/F88,0)-1)) -> 0
C89: NET RESULTS MONTERREY | D89: =D70+D84 -> 574240.16 | E89: =E70+E84 -> 0 | F89: =F70+F84 -> 0 | G89: =IF((IFERROR(E89/D89,0))=0,0,(IFERROR(E89/D89,0)-1)) -> 0 | H89: =IF((IFERROR(E89/F89,0))=0,0,(IFERROR(E89/F89,0)-1)) -> 0
C90: NET RESULTS NORTHWEST | D90: =D71+D85 -> 541748.02 | E90: =E71+E85 -> 0 | F90: =F71+F85 -> 0 | G90: =IF((IFERROR(E90/D90,0))=0,0,(IFERROR(E90/D90,0)-1)) -> 0 | H90: =IF((IFERROR(E90/F90,0))=0,0,(IFERROR(E90/F90,0)-1)) -> 0
C92: CONSOLIDATED NET RESULTS | D92: =SUM(D87:D91) -> 10030923 | E92: =SUM(E87:E91) -> 2563969.8 | F92: =SUM(F87:F91) -> 904390.62 | G92: =IF((IFERROR(E92/D92,0))=0,0,(IFERROR(E92/D92,0)-1)) -> -0.74439343 | H92: =IF((IFERROR(E92/F92,0))=0,0,(IFERROR(E92/F92,0)-1)) -> 1.8350247
E104: =E5-D5 -> 4261131.8 | F104: =E104/130000 -> 32.777937 | G104: 0.1 | J104: Dif Membresía | K104: =K5-J5 -> 1239721.5 | L104: =K104/106000 -> 11.695486 | Q104: =Q5-P5 -> 3624600.7 | R104: =Q104/106000 -> 34.194346 | W104: =W5-V5 -> 1074608.2 | X104: =W104/100000 -> 10.746082
J105: -350794.95 | K105: 574806.45 | L105: 840995.69 | P105: -17946.91 | Q105: 566088.82 | R105: 1562005.9 | V105: 1417862.9 | W105: 1247378.9 | X105: 2308937.2
J106: =J87-J105 -> -112012.84 | K106: =K87-K105 -> -464784.86 | L106: =L87-L105 -> 0.0066995267 | P106: =P87-P105 -> 592186.77 | Q106: =Q87-Q105 -> 294988.63 | R106: =R87-R105 -> -0.12693841 | V106: =V87-V105 -> -876114.87 | W106: =W87-W105 -> -508583.89 | X106: =X87-X105 -> 0.0065747155
C107: Bono 2026 - Sueldos NO corporativos: | D107: 1366439
C108: Sueldos Corporativos: | D108: 373963.62
C110: Bono 2026 - Sueldos NO corporativos: | D110: 886066.64
C111: Sueldos Corporativos: | D111: 242495.76
J113: Dif Nómina | K113: =K54-J54 -> 861247.67 | L113: 705 | M113: PROVISIÓN 2027
C114: NOTA: | K114: 50% bono 2026 + PCA | L114: =288+130 -> 418
C115: Ingresos por devengar:
C116: CDMX | D116: 25.6M | E116: 6M
C117: GDL | D117: 7.1M | E117: 600K
C118: NE | D118: 11.1M
C119: NO | D119: 2.2M

Sheet Copia de Resumen (Caps)
D1: MX | J1: GDL | P1: NE | V1: NO
D2: Forecast 9+3 | E2: Ppto. 2026 | F2: Ppto. 2025 | G2: Variación Ppto. 2026 vs Forecast 2025 | H2: Variación Ppto. 2025 vs Ppto. 2026 | J2: Forecast 9+3 | K2: Ppto. 2026 | L2: Ppto. 2025 | M2: Variación Ppto. 2026 vs Forecast 2025 | N2: Variación Ppto. 2025 vs Ppto. 2026 | P2: Forecast 9+3 | Q2: Ppto. 2026 | R2: Ppto. 2025 | S2: Variación Ppto. 2026 vs Forecast 2025 | T2: Variación Ppto. 2025 vs Ppto. 2026 | V2: Forecast 9+3 | W2: Ppto. 2026 | X2: Ppto. 2025 | Y2: Variación Ppto. 2026 vs Forecast 2025 | Z2: Variación Ppto. 2025 vs Ppto. 2026
C4: INCOME | D4: =SUM(D5,D8,D11,D16,D14) -> 63870318 | E4: =SUM(E5,E8,E11,E16,E14) -> 71683976 | F4: =SUM(F5,F8,F11,F16,F14) -> 62529782 | G4: =IF((IFERROR(E4/D4,0))=0,0,(IFERROR(E4/D4,0)-1)) -> 0.1223363 | H4: =IF((IFERROR(E4/F4,0))=0,0,(IFERROR(E4/F4,0)-1)) -> 0.14639734 | J4: =J5+J8+J11+J14+J16 -> 15701008 | K4: =K5+K8+K11+K14+K16 -> 18595805 | L4: =L5+L8+L11+L14+L16 -> 17294316 | M4: =IF((IFERROR(K4/J4,0))=0,0,(IFERROR(K4/J4,0)-1)) -> 0.18437017 | N4: =IF((IFERROR(K4/L4,0))=0,0,(IFERROR(K4/L4,0)-1)) -> 0.075255328 | P4: =P5+P8+P11+P14+P16 -> 34776476 | Q4: =Q5+Q8+Q11+Q14+Q16 -> 39308309 | R4: =R5+R8+R11+R14+R16 -> 34972433 | S4: =IF((IFERROR(Q4/P4,0))=0,0,(IFERROR(Q4/P4,0)-1)) -> 0.13031318 | T4: =IF((IFERROR(Q4/R4,0))=0,0,(IFERROR(Q4/R4,0)-1)) -> 0.12397981 | V4: =V5+V8+V11+V14+V16 -> 6305605.7 | W4: =W5+W8+W11+W14+W16 -> 7584619.4 | X4: =X5+X8+X11+X14+X16 -> 8173413.7 | Y4: =IF((IFERROR(W4/V4,0))=0,0,(IFERROR(W4/V4,0)-1)) -> 0.20283756 | Z4: =IF((IFERROR(W4/X4,0))=0,0,(IFERROR(W4/X4,0)-1)) -> -0.072037743
C5: Membership | D5: =D6+D7 -> 41169436 | E5: =E6+E7 -> 46872450 | F5: =F6+F7 -> 37282030 | G5: =IF((IFERROR(E5/D5,0))=0,0,(IFERROR(E5/D5,0)-1)) -> 0.13852542 | H5: =IF((IFERROR(E5/F5,0))=0,0,(IFERROR(E5/F5,0)-1)) -> 0.25723974 | J5: 11002476 | K5: 12582798 | L5: 10909089 | M5: =IF((IFERROR(K5/J5,0))=0,0,(IFERROR(K5/J5,0)-1)) -> 0.1436333 | N5: =IF((IFERROR(K5/L5,0))=0,0,(IFERROR(K5/L5,0)-1)) -> 0.15342338 | P5: 25760437 | Q5: 29947770 | R5: 24786483 | S5: =IF((IFERROR(Q5/P5,0))=0,0,(IFERROR(Q5/P5,0)-1)) -> 0.16254899 | T5: =IF((IFERROR(Q5/R5,0))=0,0,(IFERROR(Q5/R5,0)-1)) -> 0.2082299 | V5: 5682055.7 | W5: 6828618.2 | X5: 7502413.7 | Y5: =IF((IFERROR(W5/V5,0))=0,0,(IFERROR(W5/V5,0)-1)) -> 0.20178656 | Z5: =IF((IFERROR(W5/X5,0))=0,0,(IFERROR(W5/X5,0)-1)) -> -0.089810493
B6: 401-000-000-00 | C6: Cuotas Netas | D6: 39828015 | E6: =SUMIF('México Summary'!$C:$C,'Copia de Resumen (Caps)'!B6,'México Summary'!$AC:$AC) -> 45370058 | F6: 36117362 | G6: =IF((IFERROR(E6/D6,0))=0,0,(IFERROR(E6/D6,0)-1)) -> 0.13914937 | H6: =IF((IFERROR(E6/F6,0))=0,0,(IFERROR(E6/F6,0)-1)) -> 0.25618416
B7: 402-000-000-00 | C7: Ingresos socios nuevos | D7: 1341420.9 | E7: =SUMIF('México Summary'!$C:$C,'Copia de Resumen (Caps)'!B7,'México Summary'!$AC:$AC) -> 1502391.4 | F7: 1164667.8 | G7: =IF((IFERROR(E7/D7,0))=0,0,(IFERROR(E7/D7,0)-1)) -> 0.12 | H7: =IF((IFERROR(E7/F7,0))=0,0,(IFERROR(E7/F7,0)-1)) -> 0.2899742
C8: Events | D8: =D9+D10 -> 13199629 | E8: =E9+E10 -> 11511191 | F8: =F9+F10 -> 12957002 | G8: =IF((IFERROR(E8/D8,0))=0,0,(IFERROR(E8/D8,0)-1)) -> -0.12791558 | H8: =IF((IFERROR(E8/F8,0))=0,0,(IFERROR(E8/F8,0)-1)) -> -0.1115853 | J8: 3199282.8 | K8: 3901776 | L8: 4100000 | M8: =IF((IFERROR(K8/J8,0))=0,0,(IFERROR(K8/J8,0)-1)) -> 0.21957836 | N8: =IF((IFERROR(K8/L8,0))=0,0,(IFERROR(K8/L8,0)-1)) -> -0.048347308 | P8: 5581851.8 | Q8: 6374997.9 | R8: 5632000 | S8: =IF((IFERROR(Q8/P8,0))=0,0,(IFERROR(Q8/P8,0)-1)) -> 0.14209372 | T8: =IF((IFERROR(Q8/R8,0))=0,0,(IFERROR(Q8/R8,0)-1)) -> 0.13192435 | V8: 509450 | W8: 560395 | X8: 440000 | Y8: =IF((IFERROR(W8/V8,0))=0,0,(IFERROR(W8/V8,0)-1)) -> 0.1 | Z8: =IF((IFERROR(W8/X8,0))=0,0,(IFERROR(W8/X8,0)-1)) -> 0.273625
B9: 407-000-000-00 | C9: Eventos | D9: 2649840.2 | E9: =SUMIF('México Summary'!$C:$C,'Copia de Resumen (Caps)'!B9,'México Summary'!$AC:$AC) -> 1460000 | F9: 2250000 | G9: =IF((IFERROR(E9/D9,0))=0,0,(IFERROR(E9/D9,0)-1)) -> -0.44902337 | H9: =IF((IFERROR(E9/F9,0))=0,0,(IFERROR(E9/F9,0)-1)) -> -0.35111111
B10: 408-000-000-00 | C10: Patrocinios | D10: 10549789 | E10: =SUMIF('México Summary'!$C:$C,'Copia de Resumen (Caps)'!B10,'México Summary'!$AC:$AC) -> 10051191 | F10: 10707002 | G10: =IF((IFERROR(E10/D10,0))=0,0,(IFERROR(E10/D10,0)-1)) -> -0.047261423 | H10: =IF((IFERROR(E10/F10,0))=0,0,(IFERROR(E10/F10,0)-1)) -> -0.061250657
C11: Committees | D11: =D12+D13 -> 8327352.3 | E11: =E12+E13 -> 9775090 | F11: =F12+F13 -> 11450750 | G11: =IF((IFERROR(E11/D11,0))=0,0,(IFERROR(E11/D11,0)-1)) -> 0.1738533 | H11: =IF((IFERROR(E11/F11,0))=0,0,(IFERROR(E11/F11,0)-1)) -> -0.14633627 | J11: 819041.89 | K11: 1347321.1 | L11: 1718000 | M11: =IF((IFERROR(K11/J11,0))=0,0,(IFERROR(K11/J11,0)-1)) -> 0.64499652 | N11: =IF((IFERROR(K11/L11,0))=0,0,(IFERROR(K11/L11,0)-1)) -> -0.2157619 | P11: 1518924.9 | Q11: 1663666.9 | R11: 2593050 | S11: =IF((IFERROR(Q11/P11,0))=0,0,(IFERROR(Q11/P11,0)-1)) -> 0.095292386 | T11: =IF((IFERROR(Q11/R11,0))=0,0,(IFERROR(Q11/R11,0)-1)) -> -0.35841311 | V11: 20000 | W11: 22000 | X11: 100000 | Y11: =IF((IFERROR(W11/V11,0))=0,0,(IFERROR(W11/V11,0)-1)) -> 0.1 | Z11: =IF((IFERROR(W11/X11,0))=0,0,(IFERROR(W11/X11,0)-1)) -> -0.78
B12: 417-000-000-00 | C12: Comités | D12: 7451647.3 | E12: =SUMIF('México Summary'!$C:$C,'Copia de Resumen (Caps)'!B12,'México Summary'!$AC:$AC) -> 8675090 | F12: 10800750 | G12: =IF((IFERROR(E12/D12,0))=0,0,(IFERROR(E12/D12,0)-1)) -> 0.16418419 | H12: =IF((IFERROR(E12/F12,0))=0,0,(IFERROR(E12/F12,0)-1)) -> -0.1968067
B13: 412-000-000-00 | C13: Economex | D13: 875704.99 | E13: =SUMIF('México Summary'!$C:$C,'Copia de Resumen (Caps)'!B13,'México Summary'!$AC:$AC) -> 1100000 | F13: 650000 | G13: =IF((IFERROR(E13/D13,0))=0,0,(IFERROR(E13/D13,0)-1)) -> 0.25613079 | H13: =IF((IFERROR(E13/F13,0))=0,0,(IFERROR(E13/F13,0)-1)) -> 0.69230769
C14: T&IC | D14: =D15 -> 0 | E14: =E15 -> 840000 | F14: =F15 -> 0 | G14: =IF((IFERROR(E14/D14,0))=0,0,(IFERROR(E14/D14,0)-1)) -> 0 | H14: =IF((IFERROR(E14/F14,0))=0,0,(IFERROR(E14/F14,0)-1)) -> 0 | J14: 0 | K14: 49692.8 | L14: 0 | M14: =IF((IFERROR(K14/J14,0))=0,0,(IFERROR(K14/J14,0)-1)) -> 0 | N14: =IF((IFERROR(K14/L14,0))=0,0,(IFERROR(K14/L14,0)-1)) -> 0 | P14: 1040862.1 | Q14: 403754 | R14: 1450000 | S14: =IF((IFERROR(Q14/P14,0))=0,0,(IFERROR(Q14/P14,0)-1)) -> -0.61209654 | T14: =IF((IFERROR(Q14/R14,0))=0,0,(IFERROR(Q14/R14,0)-1)) -> -0.72154897 | V14: 0 | W14: 74539.2 | X14: 0 | Y14: =IF((IFERROR(W14/V14,0))=0,0,(IFERROR(W14/V14,0)-1)) -> 0 | Z14: =IF((IFERROR(W14/X14,0))=0,0,(IFERROR(W14/X14,0)-1)) -> 0
B15: 405-000-000-00 | C15: Trade & Investment Center | D15: 0 | E15: =SUMIF('México Summary'!$C:$C,'Copia de Resumen (Caps)'!B15,'México Summary'!$AC:$AC) -> 840000 | F15: 0 | G15: =IF((IFERROR(E15/D15,0))=0,0,(IFERROR(E15/D15,0)-1)) -> 0 | H15: =IF((IFERROR(E15/F15,0))=0,0,(IFERROR(E15/F15,0)-1)) -> 0
C16: Services to Members | D16: =D17+D19+D18 -> 1173900 | E16: =E17+E19+E18 -> 2685245 | F16: =F17+F19+F18 -> 840000 | G16: =IF((IFERROR(E16/D16,0))=0,0,(IFERROR(E16/D16,0)-1)) -> 1.2874563 | H16: =IF((IFERROR(E16/F16,0))=0,0,(IFERROR(E16/F16,0)-1)) -> 2.1967202 | J16: 680206.7 | K16: 714217.03 | L16: 567226.8 | M16: =IF((IFERROR(K16/J16,0))=0,0,(IFERROR(K16/J16,0)-1)) -> 0.05 | N16: =IF((IFERROR(K16/L16,0))=0,0,(IFERROR(K16/L16,0)-1)) -> 0.25913838 | P16: 874400 | Q16: 918120 | R16: 510900 | S16: =IF((IFERROR(Q16/P16,0))=0,0,(IFERROR(Q16/P16,0)-1)) -> 0.05 | T16: =IF((IFERROR(Q16/R16,0))=0,0,(IFERROR(Q16/R16,0)-1)) -> 0.797064 | V16: 94100 | W16: 99067 | X16: 131000 | Y16: =IF((IFERROR(W16/V16,0))=0,0,(IFERROR(W16/V16,0)-1)) -> 0.052784272 | Z16: =IF((IFERROR(W16/X16,0))=0,0,(IFERROR(W16/X16,0)-1)) -> -0.24376336
B17: 406-001-000-00 | C17: Venta Publicaciones | D17: 1173900 | E17: =SUMIF('México Summary'!$C:$C,'Copia de Resumen (Caps)'!B17,'México Summary'!$AC:$AC) -> 1232595 | F17: 840000 | G17: =IF((IFERROR(E17/D17,0))=0,0,(IFERROR(E17/D17,0)-1)) -> 0.05 | H17: =IF((IFERROR(E17/F17,0))=0,0,(IFERROR(E17/F17,0)-1)) -> 0.467375
B18: 406-002-000-00 | C18: Digital Training | D18: 0 | E18: =SUMIF('México Summary'!$C:$C,'Copia de Resumen (Caps)'!B18,'México Summary'!$AC:$AC) -> 1452650 | F18: 0 | G18: =IF((IFERROR(E18/D18,0))=0,0,(IFERROR(E18/D18,0)-1)) -> 0 | H18: =IF((IFERROR(E18/F18,0))=0,0,(IFERROR(E18/F18,0)-1)) -> 0
B19: 409-000-000-00 | C19: Visas | D19: 0 | E19: =SUMIF('México Summary'!$C:$C,'Copia de Resumen (Caps)'!B19,'México Summary'!$AC:$AC) -> 0 | F19: 0 | G19: =IF((IFERROR(E19/D19,0))=0,0,(IFERROR(E19/D19,0)-1)) -> 0 | H19: =IF((IFERROR(E19/F19,0))=0,0,(IFERROR(E19/F19,0)-1)) -> 0
B20: 450-001-000-00 | C20: Guadalajara Income | D20: 0 | E20: =SUMIF('México Summary'!$C:$C,'Copia de Resumen (Caps)'!B20,'México Summary'!$AC:$AC) -> 0 | F20: 0 | G20: =IF((IFERROR(E20/D20,0))=0,0,(IFERROR(E20/D20,0)-1)) -> 0 | H20: =IF((IFERROR(E20/F20,0))=0,0,(IFERROR(E20/F20,0)-1)) -> 0
B21: 450-002-000-00 | C21: Monterrey Income | D21: 0 | E21: =SUMIF('México Summary'!$C:$C,'Copia de Resumen (Caps)'!B21,'México Summary'!$AC:$AC) -> 0 | F21: 0 | G21: =IF((IFERROR(E21/D21,0))=0,0,(IFERROR(E21/D21,0)-1)) -> 0 | H21: =IF((IFERROR(E21/F21,0))=0,0,(IFERROR(E21/F21,0)-1)) -> 0
B22: 450-003-000-00 | C22: Northwest Income | D22: 0 | E22: =SUMIF('México Summary'!$C:$C,'Copia de Resumen (Caps)'!B22,'México Summary'!$AC:$AC) -> 0 | F22: 0 | G22: =IF((IFERROR(E22/D22,0))=0,0,(IFERROR(E22/D22,0)-1)) -> 0 | H22: =IF((IFERROR(E22/F22,0))=0,0,(IFERROR(E22/F22,0)-1)) -> 0
C23: CONSOLIDATED INCOME | D23: =D22+D21+D20+D4 -> 63870318 | E23: =E22+E21+E20+E4 -> 71683976 | F23: =F22+F21+F20+F4 -> 62529782 | G23: =IF((IFERROR(E23/D23,0))=0,0,(IFERROR(E23/D23,0)-1)) -> 0.1223363 | H23: =IF((IFERROR(E23/F23,0))=0,0,(IFERROR(E23/F23,0)-1)) -> 0.14639734
C24: EXPENSE | D24: =D25+D28+D30+D36+D39+D53+D54+D62 -> 61514669 | E24: =E25+E28+E30+E36+E39+E53+E54+E62+E34 -> 71775247 | F24: =F25+F28+F30+F36+F39+F53+F54+F62 -> 61625391 | G24: =IF((IFERROR(E24/D24,0))=0,0,(IFERROR(E24/D24,0)-1)) -> 0.16679888 | H24: =IF((IFERROR(E24/F24,0))=0,0,(IFERROR(E24/F24,0)-1)) -> 0.1647025 | J24: =J25+J28+J30+J34+J36+J39+J53+J54+J62 -> 15592230 | K24: =K25+K28+K30+K34+K36+K39+K53+K54+K62 -> 18020999 | L24: =L25+L28+L30+L34+L36+L39+L53+L54+L62 -> 16453320 | M24: =IF((IFERROR(K24/J24,0))=0,0,(IFERROR(K24/J24,0)-1)) -> 0.15576791 | N24: =IF((IFERROR(K24/L24,0))=0,0,(IFERROR(K24/L24,0)-1)) -> 0.095280383 | P24: =P25+P28+P30+P34+P36+P39+P53+P54+P62 -> 33952718 | Q24: =Q25+Q28+Q30+Q34+Q36+Q39+Q53+Q54+Q62 -> 38742220 | R24: =R25+R28+R30+R34+R36+R39+R53+R54+R62 -> 33410427 | S24: =IF((IFERROR(Q24/P24,0))=0,0,(IFERROR(Q24/P24,0)-1)) -> 0.14106389 | T24: =IF((IFERROR(Q24/R24,0))=0,0,(IFERROR(Q24/R24,0)-1)) -> 0.15958469 | V24: =V25+V28+V30+V34+V36+V39+V53+V54+V62 -> 4887742.8 | W24: =W25+W28+W30+W34+W36+W39+W53+W54+W62 -> 6337240.5 | X24: =X25+X28+X30+X34+X36+X39+X53+X54+X62 -> 5864476.4 | Y24: =IF((IFERROR(W24/V24,0))=0,0,(IFERROR(W24/V24,0)-1)) -> 0.29655768 | Z24: =IF((IFERROR(W24/X24,0))=0,0,(IFERROR(W24/X24,0)-1)) -> 0.080614883
C25: Membership | D25: =D26+D27 -> 2777026.4 | E25: =E26+E27 -> 2949107.9 | F25: =F26+F27 -> 2584139.3 | G25: =IF((IFERROR(E25/D25,0))=0,0,(IFERROR(E25/D25,0)-1)) -> 0.061966102 | H25: =IF((IFERROR(E25/F25,0))=0,0,(IFERROR(E25/F25,0)-1)) -> 0.14123409 | J25: 482307.62 | K25: 522373.81 | L25: 675870.6 | M25: =IF((IFERROR(K25/J25,0))=0,0,(IFERROR(K25/J25,0)-1)) -> 0.083071863 | N25: =IF((IFERROR(K25/L25,0))=0,0,(IFERROR(K25/L25,0)-1)) -> -0.22710973 | P25: 1793471.4 | Q25: 1901079.7 | R25: 2224320 | S25: =IF((IFERROR(Q25/P25,0))=0,0,(IFERROR(Q25/P25,0)-1)) -> 0.06 | T25: =IF((IFERROR(Q25/R25,0))=0,0,(IFERROR(Q25/R25,0)-1)) -> -0.14532097 | V25: 318541 | W25: 369485.92 | X25: 618375 | Y25: =IF((IFERROR(W25/V25,0))=0,0,(IFERROR(W25/V25,0)-1)) -> 0.15993207 | Z25: =IF((IFERROR(W25/X25,0))=0,0,(IFERROR(W25/X25,0)-1)) -> -0.40248891
B26: 705-000-000-00 | C26: Gastos Promoción | D26: 832000 | E26: =SUMIF('México Summary'!$C:$C,'Copia de Resumen (Caps)'!B26,'México Summary'!$AC:$AC) -> 887380 | F26: 863500 | G26: =IF((IFERROR(E26/D26,0))=0,0,(IFERROR(E26/D26,0)-1)) -> 0.0665625 | H26: =IF((IFERROR(E26/F26,0))=0,0,(IFERROR(E26/F26,0)-1)) -> 0.027654893
B27: 520-000-000-00 | C27: Comsiones por venta de membresía | D27: 1945026.4 | E27: =SUMIF('México Summary'!$C:$C,'Copia de Resumen (Caps)'!B27,'México Summary'!$AC:$AC) -> 2061727.9 | F27: 1720639.3 | G27: =IF((IFERROR(E27/D27,0))=0,0,(IFERROR(E27/D27,0)-1)) -> 0.059999958 | H27: =IF((IFERROR(E27/F27,0))=0,0,(IFERROR(E27/F27,0)-1)) -> 0.19823362
C28: Events | D28: =D29 -> 8552654.8 | E28: =E29 -> 6727036.8 | F28: =F29 -> 9107000 | G28: =IF((IFERROR(E28/D28,0))=0,0,(IFERROR(E28/D28,0)-1)) -> -0.21345629 | H28: =IF((IFERROR(E28/F28,0))=0,0,(IFERROR(E28/F28,0)-1)) -> -0.26133339 | J28: 2341278.1 | K28: 2042171.9 | L28: 2956045 | M28: =IF((IFERROR(K28/J28,0))=0,0,(IFERROR(K28/J28,0)-1)) -> -0.12775339 | N28: =IF((IFERROR(K28/L28,0))=0,0,(IFERROR(K28/L28,0)-1)) -> -0.30915398 | P28: 4183139.5 | Q28: 4244536.5 | R28: 4450000 | S28: =IF((IFERROR(Q28/P28,0))=0,0,(IFERROR(Q28/P28,0)-1)) -> 0.014677242 | T28: =IF((IFERROR(Q28/R28,0))=0,0,(IFERROR(Q28/R28,0)-1)) -> -0.046171573 | V28: 234008.52 | W28: 218797.96 | X28: 270000 | Y28: =IF((IFERROR(W28/V28,0))=0,0,(IFERROR(W28/V28,0)-1)) -> -0.065000026 | Z28: =IF((IFERROR(W28/X28,0))=0,0,(IFERROR(W28/X28,0)-1)) -> -0.18963719
B29: 701-000-000-00 | C29: Costo Eventos | D29: 8552654.8 | E29: =SUMIF('México Summary'!$C:$C,'Copia de Resumen (Caps)'!B29,'México Summary'!$AC:$AC) -> 6727036.8 | F29: 9107000 | G29: =IF((IFERROR(E29/D29,0))=0,0,(IFERROR(E29/D29,0)-1)) -> -0.21345629 | H29: =IF((IFERROR(E29/F29,0))=0,0,(IFERROR(E29/F29,0)-1)) -> -0.26133339
C30: Committees | D30: =SUM(D31:D33) -> 5477932.2 | E30: =SUM(E31:E33) -> 6940491.4 | F30: =SUM(F31:F33) -> 8604867.1 | G30: =IF((IFERROR(E30/D30,0))=0,0,(IFERROR(E30/D30,0)-1)) -> 0.26699111 | H30: =IF((IFERROR(E30/F30,0))=0,0,(IFERROR(E30/F30,0)-1)) -> -0.19342258 | J30: 776370.91 | K30: 776297.49 | L30: 896480 | M30: =IF((IFERROR(K30/J30,0))=0,0,(IFERROR(K30/J30,0)-1)) -> -9.4569489e-05 | N30: =IF((IFERROR(K30/L30,0))=0,0,(IFERROR(K30/L30,0)-1)) -> -0.13406045 | P30: 1413380.4 | Q30: 1495707.2 | R30: 1744550 | S30: =IF((IFERROR(Q30/P30,0))=0,0,(IFERROR(Q30/P30,0)-1)) -> 0.058248158 | T30: =IF((IFERROR(Q30/R30,0))=0,0,(IFERROR(Q30/R30,0)-1)) -> -0.14264008 | V30: 12000 | W30: 13200 | X30: 60000 | Y30: =IF((IFERROR(W30/V30,0))=0,0,(IFERROR(W30/V30,0)-1)) -> 0.1 | Z30: =IF((IFERROR(W30/X30,0))=0,0,(IFERROR(W30/X30,0)-1)) -> -0.78
B31: 702-000-000-00 | C31: Costo Comités | D31: 4236122.3 | E31: =SUMIF('México Summary'!$C:$C,'Copia de Resumen (Caps)'!B31,'México Summary'!$AC:$AC) -> 5438618.2 | F31: 7363267.1 | G31: =IF((IFERROR(E31/D31,0))=0,0,(IFERROR(E31/D31,0)-1)) -> 0.28386715 | H31: =IF((IFERROR(E31/F31,0))=0,0,(IFERROR(E31/F31,0)-1)) -> -0.26138517
B32: 704-000-000-00 | C32: Costo Economex | D32: 1060899.9 | E32: =SUMIF('México Summary'!$C:$C,'Copia de Resumen (Caps)'!B32,'México Summary'!$AC:$AC) -> 1299254 | F32: 1081600 | G32: =IF((IFERROR(E32/D32,0))=0,0,(IFERROR(E32/D32,0)-1)) -> 0.22467156 | H32: =IF((IFERROR(E32/F32,0))=0,0,(IFERROR(E32/F32,0)-1)) -> 0.20123336
B33: 521-000-000-00 | C33: Comisiones EWDP y Economex | D33: 180910 | E33: =SUMIF('México Summary'!$C:$C,'Copia de Resumen (Caps)'!B33,'México Summary'!$AC:$AC) -> 202619.2 | F33: 160000 | G33: =IF((IFERROR(E33/D33,0))=0,0,(IFERROR(E33/D33,0)-1)) -> 0.12 | H33: =IF((IFERROR(E33/F33,0))=0,0,(IFERROR(E33/F33,0)-1)) -> 0.26637
C34: T&IC | D34: =D35 -> 0 | E34: =E35 -> 340000 | F34: =F35 -> 0 | G34: =IF((IFERROR(E34/D34,0))=0,0,(IFERROR(E34/D34,0)-1)) -> 0 | H34: =IF((IFERROR(E34/F34,0))=0,0,(IFERROR(E34/F34,0)-1)) -> 0 | J34: 0 | K34: 17808 | L34: 0 | M34: =IF((IFERROR(K34/J34,0))=0,0,(IFERROR(K34/J34,0)-1)) -> 0 | N34: =IF((IFERROR(K34/L34,0))=0,0,(IFERROR(K34/L34,0)-1)) -> 0 | P34: 723930.21 | Q34: 144690 | R34: 1250000 | S34: =IF((IFERROR(Q34/P34,0))=0,0,(IFERROR(Q34/P34,0)-1)) -> -0.80013267 | T34: =IF((IFERROR(Q34/R34,0))=0,0,(IFERROR(Q34/R34,0)-1)) -> -0.884248 | V34: 0 | W34: 26712 | X34: 0 | Y34: =IF((IFERROR(W34/V34,0))=0,0,(IFERROR(W34/V34,0)-1)) -> 0 | Z34: =IF((IFERROR(W34/X34,0))=0,0,(IFERROR(W34/X34,0)-1)) -> 0
B35: 703-000-000-00 | C35: Costo Trade & Investment Center | D35: 0 | E35: =SUMIF('México Summary'!$C:$C,'Copia de Resumen (Caps)'!B35,'México Summary'!$AC:$AC) -> 340000 | F35: 0 | G35: =IF((IFERROR(E35/D35,0))=0,0,(IFERROR(E35/D35,0)-1)) -> 0 | H35: =IF((IFERROR(E35/F35,0))=0,0,(IFERROR(E35/F35,0)-1)) -> 0
C36: Services to Members | D36: =D37+D38 -> 557700 | E36: =E37+E38 -> 1268666.8 | F36: =F37+F38 -> 420000 | G36: =IF((IFERROR(E36/D36,0))=0,0,(IFERROR(E36/D36,0)-1)) -> 1.2748194 | H36: =IF((IFERROR(E36/F36,0))=0,0,(IFERROR(E36/F36,0)-1)) -> 2.0206352 | J36: 340103.35 | K36: 357108.52 | L36: 283613.4 | M36: =IF((IFERROR(K36/J36,0))=0,0,(IFERROR(K36/J36,0)-1)) -> 0.05 | N36: =IF((IFERROR(K36/L36,0))=0,0,(IFERROR(K36/L36,0)-1)) -> 0.25913838 | P36: 444274 | Q36: 459060 | R36: 286104 | S36: =IF((IFERROR(Q36/P36,0))=0,0,(IFERROR(Q36/P36,0)-1)) -> 0.033281263 | T36: =IF((IFERROR(Q36/R36,0))=0,0,(IFERROR(Q36/R36,0)-1)) -> 0.60452143 | V36: 47050 | W36: 49533.5 | X36: 65500 | Y36: =IF((IFERROR(W36/V36,0))=0,0,(IFERROR(W36/V36,0)-1)) -> 0.052784272 | Z36: =IF((IFERROR(W36/X36,0))=0,0,(IFERROR(W36/X36,0)-1)) -> -0.24376336
B37: 601-002-003-00 | C37: Costo Venta Publicaciones | D37: 557700 | E37: =SUMIF('México Summary'!$C:$C,'Copia de Resumen (Caps)'!B37,'México Summary'!$AC:$AC) -> 542341.8 | F37: 420000 | G37: =IF((IFERROR(E37/D37,0))=0,0,(IFERROR(E37/D37,0)-1)) -> -0.027538462 | H37: =IF((IFERROR(E37/F37,0))=0,0,(IFERROR(E37/F37,0)-1)) -> 0.29129
B38: 601-003-001-00 | C38: Costo Digital Training | D38: 0 | E38: =SUMIF('México Summary'!$C:$C,'Copia de Resumen (Caps)'!B38,'México Summary'!$AC:$AC) -> 726325 | F38: 0 | G38: =IF((IFERROR(E38/D38,0))=0,0,(IFERROR(E38/D38,0)-1)) -> 0 | H38: =IF((IFERROR(E38/F38,0))=0,0,(IFERROR(E38/F38,0)-1)) -> 0
C39: Gastos Administrativos | D39: =SUM(D40:D52) -> 4141199.2 | E39: =SUM(E40:E52) -> 4705358 | F39: =SUM(F40:F52) -> 5070086.1 | G39: =IF((IFERROR(E39/D39,0))=0,0,(IFERROR(E39/D39,0)-1)) -> 0.13623078 | H39: =IF((IFERROR(E39/F39,0))=0,0,(IFERROR(E39/F39,0)-1)) -> -0.071937258 | J39: 402867.07 | K39: 496408.94 | L39: 532937.82 | M39: =IF((IFERROR(K39/J39,0))=0,0,(IFERROR(K39/J39,0)-1)) -> 0.23219042 | N39: =IF((IFERROR(K39/L39,0))=0,0,(IFERROR(K39/L39,0)-1)) -> -0.068542472 | P39: 976028.67 | Q39: 995988.15 | R39: 935209.05 | S39: =IF((IFERROR(Q39/P39,0))=0,0,(IFERROR(Q39/P39,0)-1)) -> 0.020449687 | T39: =IF((IFERROR(Q39/R39,0))=0,0,(IFERROR(Q39/R39,0)-1)) -> 0.064989855 | V39: 703279.36 | W39: 1393114.2 | X39: 1615380.4 | Y39: =IF((IFERROR(W39/V39,0))=0,0,(IFERROR(W39/V39,0)-1)) -> 0.98088316 | Z39: =IF((IFERROR(W39/X39,0))=0,0,(IFERROR(W39/X39,0)-1)) -> -0.13759367
B40: 801-001-000-00 | C40: Desarrollo de Negocios | D40: 477398.26 | E40: =SUMIF('México Summary'!$C:$C,'Copia de Resumen (Caps)'!B40,'México Summary'!$AC:$AC) -> 656495.11 | F40: 579831.32 | G40: =IF((IFERROR(E40/D40,0))=0,0,(IFERROR(E40/D40,0)-1)) -> 0.37515187 | H40: =IF((IFERROR(E40/F40,0))=0,0,(IFERROR(E40/F40,0)-1)) -> 0.1322174
B41: 801-002-000-00 | C41: Relaciones Externas | D41: 0 | E41: =SUMIF('México Summary'!$C:$C,'Copia de Resumen (Caps)'!B41,'México Summary'!$AC:$AC) -> 0 | F41: 0 | G41: =IF((IFERROR(E41/D41,0))=0,0,(IFERROR(E41/D41,0)-1)) -> 0 | H41: =IF((IFERROR(E41/F41,0))=0,0,(IFERROR(E41/F41,0)-1)) -> 0
B42: 801-003-000-00 | C42: Servicios a las membresia | D42: 0 | E42: =SUMIF('México Summary'!$C:$C,'Copia de Resumen (Caps)'!B42,'México Summary'!$AC:$AC) -> 0 | F42: 0 | G42: =IF((IFERROR(E42/D42,0))=0,0,(IFERROR(E42/D42,0)-1)) -> 0 | H42: =IF((IFERROR(E42/F42,0))=0,0,(IFERROR(E42/F42,0)-1)) -> 0
B43: 801-004-000-00 | C43: Vicepresidencia | D43: 734096.11 | E43: =SUMIF('México Summary'!$C:$C,'Copia de Resumen (Caps)'!B43,'México Summary'!$AC:$AC) -> 924190.86 | F43: 1145597.2 | G43: =IF((IFERROR(E43/D43,0))=0,0,(IFERROR(E43/D43,0)-1)) -> 0.25895076 | H43: =IF((IFERROR(E43/F43,0))=0,0,(IFERROR(E43/F43,0)-1)) -> -0.19326718
B44: 801-005-000-00 | C44: Finanzas | D44: 424267.54 | E44: =SUMIF('México Summary'!$C:$C,'Copia de Resumen (Caps)'!B44,'México Summary'!$AC:$AC) -> 467017.59 | F44: 747879.2 | G44: =IF((IFERROR(E44/D44,0))=0,0,(IFERROR(E44/D44,0)-1)) -> 0.10076201 | H44: =IF((IFERROR(E44/F44,0))=0,0,(IFERROR(E44/F44,0)-1)) -> -0.37554408
B45: 801-006-000-00 | C45: Administración | D45: 173620.58 | E45: =SUMIF('México Summary'!$C:$C,'Copia de Resumen (Caps)'!B45,'México Summary'!$AC:$AC) -> 395072.91 | F45: 158700 | G45: =IF((IFERROR(E45/D45,0))=0,0,(IFERROR(E45/D45,0)-1)) -> 1.2754959 | H45: =IF((IFERROR(E45/F45,0))=0,0,(IFERROR(E45/F45,0)-1)) -> 1.4894323
B46: 801-007-000-00 | C46: Sistemas | D46: 0 | E46: =SUMIF('México Summary'!$C:$C,'Copia de Resumen (Caps)'!B46,'México Summary'!$AC:$AC) -> 0 | F46: 0 | G46: =IF((IFERROR(E46/D46,0))=0,0,(IFERROR(E46/D46,0)-1)) -> 0 | H46: =IF((IFERROR(E46/F46,0))=0,0,(IFERROR(E46/F46,0)-1)) -> 0
B47: 801-008-000-00 | C47: Empleos | D47: 0 | E47: =SUMIF('México Summary'!$C:$C,'Copia de Resumen (Caps)'!B47,'México Summary'!$AC:$AC) -> 0 | F47: 0 | G47: =IF((IFERROR(E47/D47,0))=0,0,(IFERROR(E47/D47,0)-1)) -> 0 | H47: =IF((IFERROR(E47/F47,0))=0,0,(IFERROR(E47/F47,0)-1)) -> 0
B48: 801-009-000-00 | C48: Servicios Generales (Almacén) | D48: 0 | E48: =SUMIF('México Summary'!$C:$C,'Copia de Resumen (Caps)'!B48,'México Summary'!$AC:$AC) -> 0 | F48: 0 | G48: =IF((IFERROR(E48/D48,0))=0,0,(IFERROR(E48/D48,0)-1)) -> 0 | H48: =IF((IFERROR(E48/F48,0))=0,0,(IFERROR(E48/F48,0)-1)) -> 0
B49: 801-010-000-00 | C49: Eventos | D49: 398515.05 | E49: =SUMIF('México Summary'!$C:$C,'Copia de Resumen (Caps)'!B49,'México Summary'!$AC:$AC) -> 625945.18 | F49: 452700 | G49: =IF((IFERROR(E49/D49,0))=0,0,(IFERROR(E49/D49,0)-1)) -> 0.57069395 | H49: =IF((IFERROR(E49/F49,0))=0,0,(IFERROR(E49/F49,0)-1)) -> 0.38269313
B50: 801-011-000-00 | C50: Comites | D50: 520549.57 | E50: =SUMIF('México Summary'!$C:$C,'Copia de Resumen (Caps)'!B50,'México Summary'!$AC:$AC) -> 781454.96 | F50: 493958.4 | G50: =IF((IFERROR(E50/D50,0))=0,0,(IFERROR(E50/D50,0)-1)) -> 0.50121142 | H50: =IF((IFERROR(E50/F50,0))=0,0,(IFERROR(E50/F50,0)-1)) -> 0.58202585
B51: 801-012-000-00 | C51: Renta de Salas | D51: 0 | E51: =SUMIF('México Summary'!$C:$C,'Copia de Resumen (Caps)'!B51,'México Summary'!$AC:$AC) -> 0 | F51: 0 | G51: =IF((IFERROR(E51/D51,0))=0,0,(IFERROR(E51/D51,0)-1)) -> 0 | H51: =IF((IFERROR(E51/F51,0))=0,0,(IFERROR(E51/F51,0)-1)) -> 0
B52: 801-013-000-00 | C52: Comunicación | D52: 1412752.1 | E52: =SUMIF('México Summary'!$C:$C,'Copia de Resumen (Caps)'!B52,'México Summary'!$AC:$AC) -> 855181.42 | F52: 1491420 | G52: =IF((IFERROR(E52/D52,0))=0,0,(IFERROR(E52/D52,0)-1)) -> -0.39466986 | H52: =IF((IFERROR(E52/F52,0))=0,0,(IFERROR(E52/F52,0)-1)) -> -0.4265992
B53: 901-000-000-00 | C53: Gastos Generales | D53: 7939704.1 | E53: =SUMIF('México Summary'!$C:$C,'Copia de Resumen (Caps)'!B53,'México Summary'!$AC:$AC) -> 8506216.4 | F53: 8413203.5 | G53: =IF((IFERROR(E53/D53,0))=0,0,(IFERROR(E53/D53,0)-1)) -> 0.071351818 | H53: =IF((IFERROR(E53/F53,0))=0,0,(IFERROR(E53/F53,0)-1)) -> 0.011055585 | J53: 1372892.7 | K53: 1809100.7 | L53: 1467280.1 | M53: =IF((IFERROR(K53/J53,0))=0,0,(IFERROR(K53/J53,0)-1)) -> 0.31772906 | N53: =IF((IFERROR(K53/L53,0))=0,0,(IFERROR(K53/L53,0)-1)) -> 0.23296207 | P53: 2638864.7 | Q53: 4410097.8 | R53: 3404584.7 | S53: =IF((IFERROR(Q53/P53,0))=0,0,(IFERROR(Q53/P53,0)-1)) -> 0.67121026 | T53: =IF((IFERROR(Q53/R53,0))=0,0,(IFERROR(Q53/R53,0)-1)) -> 0.29534089 | V53: 195609.04 | W53: 323135.62 | X53: 213513.03 | Y53: =IF((IFERROR(W53/V53,0))=0,0,(IFERROR(W53/V53,0)-1)) -> 0.65194627 | Z53: =IF((IFERROR(W53/X53,0))=0,0,(IFERROR(W53/X53,0)-1)) -> 0.51342342
C54: Nómina | D54: =SUM(D55:D61)+1366439+886066.64 -> 17347185 | E54: 21149050 | F54: =SUM(F55:F61) -> 13119015 | G54: =IF((IFERROR(E54/D54,0))=0,0,(IFERROR(E54/D54,0)-1)) -> 0.21916327 | H54: =IF((IFERROR(E54/F54,0))=0,0,(IFERROR(E54/F54,0)-1)) -> 0.61209133 | J54: 5848248.4 | K54: 7550054.4 | L54: 5720425.7 | M54: =IF((IFERROR(K54/J54,0))=0,0,(IFERROR(K54/J54,0)-1)) -> 0.29099414 | N54: =IF((IFERROR(K54/L54,0))=0,0,(IFERROR(K54/L54,0)-1)) -> 0.31984136 | P54: 13233035 | Q54: 15709723 | R54: 10606138 | S54: =IF((IFERROR(Q54/P54,0))=0,0,(IFERROR(Q54/P54,0)-1)) -> 0.1871595 | T54: =IF((IFERROR(Q54/R54,0))=0,0,(IFERROR(Q54/R54,0)-1)) -> 0.48119171 | V54: 1883615.9 | W54: 2117554.4 | X54: 1655980 | Y54: =IF((IFERROR(W54/V54,0))=0,0,(IFERROR(W54/V54,0)-1)) -> 0.12419653 | Z54: =IF((IFERROR(W54/X54,0))=0,0,(IFERROR(W54/X54,0)-1)) -> 0.27873192
B55: 513-000-000-00 | C55: Nomina Vicepresidencia | D55: 576330.22 | E55: =SUMIF('México Summary'!$C:$C,'Copia de Resumen (Caps)'!B55,'México Summary'!$AC:$AC) -> 542438.28 | F55: 334036.73 | G55: =IF((IFERROR(E55/D55,0))=0,0,(IFERROR(E55/D55,0)-1)) -> -0.058806463 | H55: =IF((IFERROR(E55/F55,0))=0,0,(IFERROR(E55/F55,0)-1)) -> 0.62388814
B56: 517-000-000-00 | C56: Nomina Desarrollo de Negocios | D56: 3856950.5 | E56: =SUMIF('México Summary'!$C:$C,'Copia de Resumen (Caps)'!B56,'México Summary'!$AC:$AC) -> 4883189.3 | F56: 3385754.8 | G56: =IF((IFERROR(E56/D56,0))=0,0,(IFERROR(E56/D56,0)-1)) -> 0.26607518 | H56: =IF((IFERROR(E56/F56,0))=0,0,(IFERROR(E56/F56,0)-1)) -> 0.44227492
B57: 516-000-000-00 | C57: Nomina Comites y Relaciones Externas | D57: 4593443.9 | E57: =SUMIF('México Summary'!$C:$C,'Copia de Resumen (Caps)'!B57,'México Summary'!$AC:$AC) -> 5213492.5 | F57: 4088183.5 | G57: =IF((IFERROR(E57/D57,0))=0,0,(IFERROR(E57/D57,0)-1)) -> 0.13498557 | H57: =IF((IFERROR(E57/F57,0))=0,0,(IFERROR(E57/F57,0)-1)) -> 0.27525892
B58: 519-000-000-00 | C58: Nomina Comunicación | D58: 1003603 | E58: =SUMIF('México Summary'!$C:$C,'Copia de Resumen (Caps)'!B58,'México Summary'!$AC:$AC) -> 1448842.1 | F58: 876475.57 | G58: =IF((IFERROR(E58/D58,0))=0,0,(IFERROR(E58/D58,0)-1)) -> 0.44364065 | H58: =IF((IFERROR(E58/F58,0))=0,0,(IFERROR(E58/F58,0)-1)) -> 0.6530319
B59: 515-000-000-00 | C59: Nomina Servicios a la Membresia | D59: 1649823.9 | E59: =SUMIF('México Summary'!$C:$C,'Copia de Resumen (Caps)'!B59,'México Summary'!$AC:$AC) -> 1925404.1 | F59: 1506952.1 | G59: =IF((IFERROR(E59/D59,0))=0,0,(IFERROR(E59/D59,0)-1)) -> 0.1670361 | H59: =IF((IFERROR(E59/F59,0))=0,0,(IFERROR(E59/F59,0)-1)) -> 0.27768101
B60: 518-000-000-00 | C60: Nomina Eventos y Mercadotecnia | D60: 764166.04 | E60: =SUMIF('México Summary'!$C:$C,'Copia de Resumen (Caps)'!B60,'México Summary'!$AC:$AC) -> 566664.36 | F60: 672955.21 | G60: =IF((IFERROR(E60/D60,0))=0,0,(IFERROR(E60/D60,0)-1)) -> -0.25845389 | H60: =IF((IFERROR(E60/F60,0))=0,0,(IFERROR(E60/F60,0)-1)) -> -0.1579464
B61: 514-000-000-00 | C61: Nomina Administración y Fiananzas | D61: 2650361.4 | E61: =SUMIF('México Summary'!$C:$C,'Copia de Resumen (Caps)'!B61,'México Summary'!$AC:$AC) -> 3913778.5 | F61: 2254657 | G61: =IF((IFERROR(E61/D61,0))=0,0,(IFERROR(E61/D61,0)-1)) -> 0.47669615 | H61: =IF((IFERROR(E61/F61,0))=0,0,(IFERROR(E61/F61,0)-1)) -> 0.73586425
B62: 903-000-000-00 | C62: Gastos Corporativos | D62: =14104808.71+373963.62+242495.76 -> 14721268 | E62: =SUMIF('México Summary'!$C:$C,'Copia de Resumen (Caps)'!B62,'México Summary'!$AC:$AC) -> 19189320 | F62: 14307080 | G62: =IF((IFERROR(E62/D62,0))=0,0,(IFERROR(E62/D62,0)-1)) -> 0.30350997 | H62: =IF((IFERROR(E62/F62,0))=0,0,(IFERROR(E62/F62,0)-1)) -> 0.34124637 | J62: 4028161.6 | K62: 4449675.1 | L62: 3920667.6 | M62: =IF((IFERROR(K62/J62,0))=0,0,(IFERROR(K62/J62,0)-1)) -> 0.10464166 | N62: =IF((IFERROR(K62/L62,0))=0,0,(IFERROR(K62/L62,0)-1)) -> 0.13492791 | P62: 8546594.2 | Q62: 9381338 | R62: 8509522.2 | S62: =IF((IFERROR(Q62/P62,0))=0,0,(IFERROR(Q62/P62,0)-1)) -> 0.097669757 | T62: =IF((IFERROR(Q62/R62,0))=0,0,(IFERROR(Q62/R62,0)-1)) -> 0.10245179 | V62: 1493639 | W62: 1825706.8 | X62: 1365728.1 | Y62: =IF((IFERROR(W62/V62,0))=0,0,(IFERROR(W62/V62,0)-1)) -> 0.22232131 | Z62: =IF((IFERROR(W62/X62,0))=0,0,(IFERROR(W62/X62,0)-1)) -> 0.33680112
B63: 950-001-000-00 | C63: Guadalajara Expense | D63: 0 | E63: =SUMIF('México Summary'!$C:$C,'Copia de Resumen (Caps)'!B63,'México Summary'!$AC:$AC) -> 0 | F63: 0 | G63: =IF((IFERROR(E63/D63,0))=0,0,(IFERROR(E63/D63,0)-1)) -> 0 | H63: =IF((IFERROR(E63/F63,0))=0,0,(IFERROR(E63/F63,0)-1)) -> 0
B64: 950-002-000-00 | C64: Monterrey Expense | D64: 0 | E64: =SUMIF('México Summary'!$C:$C,'Copia de Resumen (Caps)'!B64,'México Summary'!$AC:$AC) -> 0 | F64: 0 | G64: =IF((IFERROR(E64/D64,0))=0,0,(IFERROR(E64/D64,0)-1)) -> 0 | H64: =IF((IFERROR(E64/F64,0))=0,0,(IFERROR(E64/F64,0)-1)) -> 0
B65: 950-003-000-00 | C65: Northwest Expense | D65: 0 | E65: =SUMIF('México Summary'!$C:$C,'Copia de Resumen (Caps)'!B65,'México Summary'!$AC:$AC) -> 0 | F65: 0 | G65: =IF((IFERROR(E65/D65,0))=0,0,(IFERROR(E65/D65,0)-1)) -> 0 | H65: =IF((IFERROR(E65/F65,0))=0,0,(IFERROR(E65/F65,0)-1)) -> 0
C66: CONSOLIDATED EXPENSES | D66: =D65+D64+D63+D24 -> 61514669 | E66: =E65+E64+E63+E24 -> 71775247 | F66: =F65+F64+F63+F24 -> 61625391 | G66: =IF((IFERROR(E66/D66,0))=0,0,(IFERROR(E66/D66,0)-1)) -> 0.16679888 | H66: =IF((IFERROR(E66/F66,0))=0,0,(IFERROR(E66/F66,0)-1)) -> 0.1647025
C68: OPERATING RESULTS MEXICO | D68: =D4-D24 -> 2355648.5 | E68: =E4-E24 -> -91271.429 | F68: =F4-F24 -> 904390.62 | G68: =IF((IFERROR(E68/D68,0))=0,0,(IFERROR(E68/D68,0)-1)) -> -1.0387458 | H68: =IF((IFERROR(E68/F68,0))=0,0,(IFERROR(E68/F68,0)-1)) -> -1.1009204 | J68: =J4-J24 -> 108778 | K68: =K4-K24 -> 574806.45 | L68: =L4-L24 -> 840995.69 | M68: =IF((IFERROR(K68/J68,0))=0,0,(IFERROR(K68/J68,0)-1)) -> 4.2842159 | N68: =IF((IFERROR(K68/L68,0))=0,0,(IFERROR(K68/L68,0)-1)) -> -0.31651677 | P68: =P4-P24 -> 823758.16 | Q68: =Q4-Q24 -> 566088.82 | R68: =R4-R24 -> 1562005.9 | S68: =IF((IFERROR(Q68/P68,0))=0,0,(IFERROR(Q68/P68,0)-1)) -> -0.31279732 | T68: =IF((IFERROR(Q68/R68,0))=0,0,(IFERROR(Q68/R68,0)-1)) -> -0.63758855 | V68: =V4-V24 -> 1417862.9 | W68: =W4-W24 -> 1247378.9 | X68: =X4-X24 -> 2308937.2 | Y68: =IF((IFERROR(W68/V68,0))=0,0,(IFERROR(W68/V68,0)-1)) -> -0.12024013 | Z68: =IF((IFERROR(W68/X68,0))=0,0,(IFERROR(W68/X68,0)-1)) -> -0.4597606
C69: OPERATING RESULTS GUADALAJARA | D69: =D20-D63 -> 0 | E69: =E20-E63 -> 0 | F69: =F20-F63 -> 0 | G69: =IF((IFERROR(E69/D69,0))=0,0,(IFERROR(E69/D69,0)-1)) -> 0 | H69: =IF((IFERROR(E69/F69,0))=0,0,(IFERROR(E69/F69,0)-1)) -> 0
C70: OPERATING RESULTS MONTERREY | D70: =D21-D64 -> 0 | E70: =E21-E64 -> 0 | F70: =F21-F64 -> 0 | G70: =IF((IFERROR(E70/D70,0))=0,0,(IFERROR(E70/D70,0)-1)) -> 0 | H70: =IF((IFERROR(E70/F70,0))=0,0,(IFERROR(E70/F70,0)-1)) -> 0
C71: OPERATING RESULTS NORTHWEST | D71: =D22-D65 -> 0 | E71: =E22-E65 -> 0 | F71: =F22-F65 -> 0 | G71: =IF((IFERROR(E71/D71,0))=0,0,(IFERROR(E71/D71,0)-1)) -> 0 | H71: =IF((IFERROR(E71/F71,0))=0,0,(IFERROR(E71/F71,0)-1)) -> 0
C73: CONSOLIDATED OPERATING RESULTS | D73: =SUM(D68:D72) -> 2355648.5 | E73: =SUM(E68:E72) -> -91271.429 | F73: =SUM(F68:F72) -> 904390.62 | G73: =IF((IFERROR(E73/D73,0))=0,0,(IFERROR(E73/D73,0)-1)) -> -1.0387458 | H73: =IF((IFERROR(E73/F73,0))=0,0,(IFERROR(E73/F73,0)-1)) -> -1.1009204
B75: 902-000-000-00 | C75: Member Centricity | D75: 1808869.4 | E75: =SUMIF('México Summary'!$C:$C,'Copia de Resumen (Caps)'!B75,'México Summary'!$AC:$AC) -> 0 | F75: 0 | G75: =IF((IFERROR(E75/D75,0))=0,0,(IFERROR(E75/D75,0)-1)) -> 0 | H75: =IF((IFERROR(E75/F75,0))=0,0,(IFERROR(E75/F75,0)-1)) -> 0 | J75: 459718.4 | K75: 0 | L75: 0 | M75: =IF((IFERROR(K75/J75,0))=0,0,(IFERROR(K75/J75,0)-1)) -> 0 | N75: =IF((IFERROR(K75/L75,0))=0,0,(IFERROR(K75/L75,0)-1)) -> 0 | P75: 991831.01 | Q75: 0 | R75: 0 | S75: =IF((IFERROR(Q75/P75,0))=0,0,(IFERROR(Q75/P75,0)-1)) -> 0 | T75: =IF((IFERROR(Q75/R75,0))=0,0,(IFERROR(Q75/R75,0)-1)) -> 0 | V75: 0 | W75: 0 | X75: 0 | Y75: =IF((IFERROR(W75/V75,0))=0,0,(IFERROR(W75/V75,0)-1)) -> 0 | Z75: =IF((IFERROR(W75/X75,0))=0,0,(IFERROR(W75/X75,0)-1)) -> 0
C77: Other | D77: =SUM(D78:D81) -> 3230204.5 | E77: =SUM(E78:E81) -> 0 | F77: =SUM(F78:F81) -> 0 | G77: =IF((IFERROR(E77/D77,0))=0,0,(IFERROR(E77/D77,0)-1)) -> 0 | H77: =IF((IFERROR(E77/F77,0))=0,0,(IFERROR(E77/F77,0)-1)) -> 0 | J77: 145.45 | K77: 0 | L77: 0 | M77: =IF((IFERROR(K77/J77,0))=0,0,(IFERROR(K77/J77,0)-1)) -> 0 | N77: =IF((IFERROR(K77/L77,0))=0,0,(IFERROR(K77/L77,0)-1)) -> 0 | P77: 150125.94 | Q77: 0 | R77: 0 | S77: =IF((IFERROR(Q77/P77,0))=0,0,(IFERROR(Q77/P77,0)-1)) -> 0 | T77: =IF((IFERROR(Q77/R77,0))=0,0,(IFERROR(Q77/R77,0)-1)) -> 0 | V77: 0 | W77: 0 | X77: 0 | Y77: =IF((IFERROR(W77/V77,0))=0,0,(IFERROR(W77/V77,0)-1)) -> 0 | Z77: =IF((IFERROR(W77/X77,0))=0,0,(IFERROR(W77/X77,0)-1)) -> 0
B78: 413-000-000-00 | C78: Otros Ingresos | D78: 53602.71 | E78: =SUMIF('México Summary'!$C:$C,'Copia de Resumen (Caps)'!B78,'México Summary'!$AC:$AC) -> 0 | F78: 0 | G78: =IF((IFERROR(E78/D78,0))=0,0,(IFERROR(E78/D78,0)-1)) -> 0 | H78: =IF((IFERROR(E78/F78,0))=0,0,(IFERROR(E78/F78,0)-1)) -> 0
B79: 414-000-000-00 | C79: Intereses Bancos | D79: 5495278.6 | E79: =SUMIF('México Summary'!$C:$C,'Copia de Resumen (Caps)'!B79,'México Summary'!$AC:$AC) -> 0 | F79: 0 | G79: =IF((IFERROR(E79/D79,0))=0,0,(IFERROR(E79/D79,0)-1)) -> 0 | H79: =IF((IFERROR(E79/F79,0))=0,0,(IFERROR(E79/F79,0)-1)) -> 0
B80: 416-000-000-00 | C80: Utilidad Cambiaria Inversiones | D80: -8589913.5 | E80: =SUMIF('México Summary'!$C:$C,'Copia de Resumen (Caps)'!B80,'México Summary'!$AC:$AC) -> 0 | F80: 0 | G80: =IF((IFERROR(E80/D80,0))=0,0,(IFERROR(E80/D80,0)-1)) -> 0 | H80: =IF((IFERROR(E80/F80,0))=0,0,(IFERROR(E80/F80,0)-1)) -> 0
B81: 418-000-000-00 | C81: Plusvalia/Minusvalia Portafolio Inversiones | D81: 6271236.7 | E81: =SUMIF('México Summary'!$C:$C,'Copia de Resumen (Caps)'!B81,'México Summary'!$AC:$AC) -> 0 | F81: 0 | G81: =IF((IFERROR(E81/D81,0))=0,0,(IFERROR(E81/D81,0)-1)) -> 0 | H81: =IF((IFERROR(E81/F81,0))=0,0,(IFERROR(E81/F81,0)-1)) -> 0
C83: Guadalajara Other Income | D83: 0 | E83: 0 | F83: 0 | G83: =IF((IFERROR(E83/D83,0))=0,0,(IFERROR(E83/D83,0)-1)) -> 0 | H83: =IF((IFERROR(E83/F83,0))=0,0,(IFERROR(E83/F83,0)-1)) -> 0
C84: Monterrey Other Income | D84: 0 | E84: 0 | F84: 0 | G84: =IF((IFERROR(E84/D84,0))=0,0,(IFERROR(E84/D84,0)-1)) -> 0 | H84: =IF((IFERROR(E84/F84,0))=0,0,(IFERROR(E84/F84,0)-1)) -> 0
C85: Northwest Other Income | D85: 0 | E85: 0 | F85: 0 | G85: =IF((IFERROR(E85/D85,0))=0,0,(IFERROR(E85/D85,0)-1)) -> 0 | H85: =IF((IFERROR(E85/F85,0))=0,0,(IFERROR(E85/F85,0)-1)) -> 0
C87: NET RESULTS MEXICO | D87: =D68-D75+D77 -> 3776983.6 | E87: =E68-E75+E77 -> -91271.429 | F87: =F68-F75+F77 -> 904390.62 | G87: =IF((IFERROR(E87/D87,0))=0,0,(IFERROR(E87/D87,0)-1)) -> -1.0241652 | H87: =IF((IFERROR(E87/F87,0))=0,0,(IFERROR(E87/F87,0)-1)) -> -1.1009204 | J87: =J68-J75+J77 -> -350794.95 | K87: =K68-K75+K77 -> 574806.45 | L87: =L68-L75+L77 -> 840995.69 | M87: =IF((IFERROR(K87/J87,0))=0,0,(IFERROR(K87/J87,0)-1)) -> -2.6385825 | N87: =IF((IFERROR(K87/L87,0))=0,0,(IFERROR(K87/L87,0)-1)) -> -0.31651677 | P87: =P68-P75+P77 -> -17946.91 | Q87: =Q68-Q75+Q77 -> 566088.82 | R87: =R68-R75+R77 -> 1562005.9 | S87: =IF((IFERROR(Q87/P87,0))=0,0,(IFERROR(Q87/P87,0)-1)) -> -32.542412 | T87: =IF((IFERROR(Q87/R87,0))=0,0,(IFERROR(Q87/R87,0)-1)) -> -0.63758855 | V87: =V68-V75+V77 -> 1417862.9 | W87: =W68-W75+W77 -> 1247378.9 | X87: =X68-X75+X77 -> 2308937.2 | Y87: =IF((IFERROR(W87/V87,0))=0,0,(IFERROR(W87/V87,0)-1)) -> -0.12024013 | Z87: =IF((IFERROR(W87/X87,0))=0,0,(IFERROR(W87/X87,0)-1)) -> -0.4597606
C88: NET RESULTS GUADALAJARA | D88: =D69+D83 -> 0 | E88: =E69+E83 -> 0 | F88: =F69+F83 -> 0 | G88: =IF((IFERROR(E88/D88,0))=0,0,(IFERROR(E88/D88,0)-1)) -> 0 | H88: =IF((IFERROR(E88/F88,0))=0,0,(IFERROR(E88/F88,0)-1)) -> 0
C89: NET RESULTS MONTERREY | D89: =D70+D84 -> 0 | E89: =E70+E84 -> 0 | F89: =F70+F84 -> 0 | G89: =IF((IFERROR(E89/D89,0))=0,0,(IFERROR(E89/D89,0)-1)) -> 0 | H89: =IF((IFERROR(E89/F89,0))=0,0,(IFERROR(E89/F89,0)-1)) -> 0
C90: NET RESULTS NORTHWEST | D90: =D71+D85 -> 0 | E90: =E71+E85 -> 0 | F90: =F71+F85 -> 0 | G90: =IF((IFERROR(E90/D90,0))=0,0,(IFERROR(E90/D90,0)-1)) -> 0 | H90: =IF((IFERROR(E90/F90,0))=0,0,(IFERROR(E90/F90,0)-1)) -> 0
C92: CONSOLIDATED NET RESULTS | D92: =SUM(D87:D91) -> 3776983.6 | E92: =SUM(E87:E91) -> -91271.429 | F92: =SUM(F87:F91) -> 904390.62 | G92: =IF((IFERROR(E92/D92,0))=0,0,(IFERROR(E92/D92,0)-1)) -> -1.0241652 | H92: =IF((IFERROR(E92/F92,0))=0,0,(IFERROR(E92/F92,0)-1)) -> -1.1009204
E94: =Resumen!J93 -> 2563969.8 | J94: -350794.95 | K94: 574806.45 | L94: 840995.69 | P94: -17946.91 | Q94: 566088.82 | R94: 1562005.9 | V94: 1417862.9 | W94: 1247378.9 | X94: 2308937.2
E95: =E87-E94 -> -2655241.2 | J95: =J87-J94 -> 0 | K95: =K87-K94 -> 0 | L95: =L87-L94 -> 0 | P95: =P87-P94 -> -1.4842954e-08 | Q95: =Q87-Q94 -> 0 | R95: =R87-R94 -> 0 | V95: =V87-V94 -> 0 | W95: =W87-W94 -> 0 | X95: =X87-X94 -> 0
C96: Bono 2026 - Sueldos NO corporativos: | D96: 1366439
C97: Sueldos Corporativos: | D97: 373963.62
C99: Bono 2026 - Sueldos NO corporativos: | D99: 886066.64
C100: Sueldos Corporativos: | D100: 242495.76

Sheet Copia de Copia de Resumen (Caps
D1: MX | J1: GDL | P1: NE | V1: NO
D2: Forecast 9+3 | E2: Ppto. 2026 | F2: Ppto. 2025 | G2: Variación Ppto. 2026 vs Forecast 2025 | H2: Variación Ppto. 2025 vs Ppto. 2026 | J2: Forecast 9+3 | K2: Ppto. 2026 | L2: Ppto. 2025 | M2: Variación Ppto. 2026 vs Forecast 2025 | N2: Variación Ppto. 2025 vs Ppto. 2026 | P2: Forecast 9+3 | Q2: Ppto. 2026 | R2: Ppto. 2025 | S2: Variación Ppto. 2026 vs Forecast 2025 | T2: Variación Ppto. 2025 vs Ppto. 2026 | V2: Forecast 9+3 | W2: Ppto. 2026 | X2: Ppto. 2025 | Y2: Variación Ppto. 2026 vs Forecast 2025 | Z2: Variación Ppto. 2025 vs Ppto. 2026
C4: INCOME | D4: =SUM(D5,D8,D11,D16,D14) -> 63870318 | E4: =SUM(E5,E8,E11,E16,E14) -> 71683976 | F4: =SUM(F5,F8,F11,F16,F14) -> 62529782 | G4: =IF((IFERROR(E4/D4,0))=0,0,(IFERROR(E4/D4,0)-1)) -> 0.1223363 | H4: =IF((IFERROR(E4/F4,0))=0,0,(IFERROR(E4/F4,0)-1)) -> 0.14639734 | J4: =J5+J8+J11+J14+J16 -> 15701008 | K4: =K5+K8+K11+K14+K16 -> 18595805 | L4: =L5+L8+L11+L14+L16 -> 17294316 | M4: =IF((IFERROR(K4/J4,0))=0,0,(IFERROR(K4/J4,0)-1)) -> 0.18437017 | N4: =IF((IFERROR(K4/L4,0))=0,0,(IFERROR(K4/L4,0)-1)) -> 0.075255328 | P4: =P5+P8+P11+P14+P16 -> 34776476 | Q4: =Q5+Q8+Q11+Q14+Q16 -> 39308309 | R4: =R5+R8+R11+R14+R16 -> 34972433 | S4: =IF((IFERROR(Q4/P4,0))=0,0,(IFERROR(Q4/P4,0)-1)) -> 0.13031318 | T4: =IF((IFERROR(Q4/R4,0))=0,0,(IFERROR(Q4/R4,0)-1)) -> 0.12397981 | V4: =V5+V8+V11+V14+V16 -> 6305605.7 | W4: =W5+W8+W11+W14+W16 -> 7584619.4 | X4: =X5+X8+X11+X14+X16 -> 8173413.7 | Y4: =IF((IFERROR(W4/V4,0))=0,0,(IFERROR(W4/V4,0)-1)) -> 0.20283756 | Z4: =IF((IFERROR(W4/X4,0))=0,0,(IFERROR(W4/X4,0)-1)) -> -0.072037743
C5: Membership | D5: =D6+D7 -> 41169436 | E5: =E6+E7 -> 46872450 | F5: =F6+F7 -> 37282030 | G5: =IF((IFERROR(E5/D5,0))=0,0,(IFERROR(E5/D5,0)-1)) -> 0.13852542 | H5: =IF((IFERROR(E5/F5,0))=0,0,(IFERROR(E5/F5,0)-1)) -> 0.25723974 | J5: 11002476 | K5: 12582798 | L5: 10909089 | M5: =IF((IFERROR(K5/J5,0))=0,0,(IFERROR(K5/J5,0)-1)) -> 0.1436333 | N5: =IF((IFERROR(K5/L5,0))=0,0,(IFERROR(K5/L5,0)-1)) -> 0.15342338 | P5: 25760437 | Q5: 29947770 | R5: 24786483 | S5: =IF((IFERROR(Q5/P5,0))=0,0,(IFERROR(Q5/P5,0)-1)) -> 0.16254899 | T5: =IF((IFERROR(Q5/R5,0))=0,0,(IFERROR(Q5/R5,0)-1)) -> 0.2082299 | V5: 5682055.7 | W5: 6828618.2 | X5: 7502413.7 | Y5: =IF((IFERROR(W5/V5,0))=0,0,(IFERROR(W5/V5,0)-1)) -> 0.20178656 | Z5: =IF((IFERROR(W5/X5,0))=0,0,(IFERROR(W5/X5,0)-1)) -> -0.089810493
B6: 401-000-000-00 | C6: Cuotas Netas | D6: 39828015 | E6: =SUMIF('México Summary'!$C:$C,'Copia de Copia de Resumen (Caps'!B6,'México Summary'!$AC:$AC) -> 45370058 | F6: 36117362 | G6: =IF((IFERROR(E6/D6,0))=0,0,(IFERROR(E6/D6,0)-1)) -> 0.13914937 | H6: =IF((IFERROR(E6/F6,0))=0,0,(IFERROR(E6/F6,0)-1)) -> 0.25618416
B7: 402-000-000-00 | C7: Ingresos socios nuevos | D7: 1341420.9 | E7: =SUMIF('México Summary'!$C:$C,'Copia de Copia de Resumen (Caps'!B7,'México Summary'!$AC:$AC) -> 1502391.4 | F7: 1164667.8 | G7: =IF((IFERROR(E7/D7,0))=0,0,(IFERROR(E7/D7,0)-1)) -> 0.12 | H7: =IF((IFERROR(E7/F7,0))=0,0,(IFERROR(E7/F7,0)-1)) -> 0.2899742
C8: Events | D8: =D9+D10 -> 13199629 | E8: =E9+E10 -> 11511191 | F8: =F9+F10 -> 12957002 | G8: =IF((IFERROR(E8/D8,0))=0,0,(IFERROR(E8/D8,0)-1)) -> -0.12791558 | H8: =IF((IFERROR(E8/F8,0))=0,0,(IFERROR(E8/F8,0)-1)) -> -0.1115853 | J8: 3199282.8 | K8: 3901776 | L8: 4100000 | M8: =IF((IFERROR(K8/J8,0))=0,0,(IFERROR(K8/J8,0)-1)) -> 0.21957836 | N8: =IF((IFERROR(K8/L8,0))=0,0,(IFERROR(K8/L8,0)-1)) -> -0.048347308 | P8: 5581851.8 | Q8: 6374997.9 | R8: 5632000 | S8: =IF((IFERROR(Q8/P8,0))=0,0,(IFERROR(Q8/P8,0)-1)) -> 0.14209372 | T8: =IF((IFERROR(Q8/R8,0))=0,0,(IFERROR(Q8/R8,0)-1)) -> 0.13192435 | V8: 509450 | W8: 560395 | X8: 440000 | Y8: =IF((IFERROR(W8/V8,0))=0,0,(IFERROR(W8/V8,0)-1)) -> 0.1 | Z8: =IF((IFERROR(W8/X8,0))=0,0,(IFERROR(W8/X8,0)-1)) -> 0.273625
B9: 407-000-000-00 | C9: Eventos | D9: 2649840.2 | E9: =SUMIF('México Summary'!$C:$C,'Copia de Copia de Resumen (Caps'!B9,'México Summary'!$AC:$AC) -> 1460000 | F9: 2250000 | G9: =IF((IFERROR(E9/D9,0))=0,0,(IFERROR(E9/D9,0)-1)) -> -0.44902337 | H9: =IF((IFERROR(E9/F9,0))=0,0,(IFERROR(E9/F9,0)-1)) -> -0.35111111
B10: 408-000-000-00 | C10: Patrocinios | D10: 10549789 | E10: =SUMIF('México Summary'!$C:$C,'Copia de Copia de Resumen (Caps'!B10,'México Summary'!$AC:$AC) -> 10051191 | F10: 10707002 | G10: =IF((IFERROR(E10/D10,0))=0,0,(IFERROR(E10/D10,0)-1)) -> -0.047261423 | H10: =IF((IFERROR(E10/F10,0))=0,0,(IFERROR(E10/F10,0)-1)) -> -0.061250657
C11: Committees | D11: =D12+D13 -> 8327352.3 | E11: =E12+E13 -> 9775090 | F11: =F12+F13 -> 11450750 | G11: =IF((IFERROR(E11/D11,0))=0,0,(IFERROR(E11/D11,0)-1)) -> 0.1738533 | H11: =IF((IFERROR(E11/F11,0))=0,0,(IFERROR(E11/F11,0)-1)) -> -0.14633627 | J11: 819041.89 | K11: 1347321.1 | L11: 1718000 | M11: =IF((IFERROR(K11/J11,0))=0,0,(IFERROR(K11/J11,0)-1)) -> 0.64499652 | N11: =IF((IFERROR(K11/L11,0))=0,0,(IFERROR(K11/L11,0)-1)) -> -0.2157619 | P11: 1518924.9 | Q11: 1663666.9 | R11: 2593050 | S11: =IF((IFERROR(Q11/P11,0))=0,0,(IFERROR(Q11/P11,0)-1)) -> 0.095292386 | T11: =IF((IFERROR(Q11/R11,0))=0,0,(IFERROR(Q11/R11,0)-1)) -> -0.35841311 | V11: 20000 | W11: 22000 | X11: 100000 | Y11: =IF((IFERROR(W11/V11,0))=0,0,(IFERROR(W11/V11,0)-1)) -> 0.1 | Z11: =IF((IFERROR(W11/X11,0))=0,0,(IFERROR(W11/X11,0)-1)) -> -0.78
B12: 417-000-000-00 | C12: Comités | D12: 7451647.3 | E12: =SUMIF('México Summary'!$C:$C,'Copia de Copia de Resumen (Caps'!B12,'México Summary'!$AC:$AC) -> 8675090 | F12: 10800750 | G12: =IF((IFERROR(E12/D12,0))=0,0,(IFERROR(E12/D12,0)-1)) -> 0.16418419 | H12: =IF((IFERROR(E12/F12,0))=0,0,(IFERROR(E12/F12,0)-1)) -> -0.1968067
B13: 412-000-000-00 | C13: Economex | D13: 875704.99 | E13: =SUMIF('México Summary'!$C:$C,'Copia de Copia de Resumen (Caps'!B13,'México Summary'!$AC:$AC) -> 1100000 | F13: 650000 | G13: =IF((IFERROR(E13/D13,0))=0,0,(IFERROR(E13/D13,0)-1)) -> 0.25613079 | H13: =IF((IFERROR(E13/F13,0))=0,0,(IFERROR(E13/F13,0)-1)) -> 0.69230769
C14: T&IC | D14: =D15 -> 0 | E14: =E15 -> 840000 | F14: =F15 -> 0 | G14: =IF((IFERROR(E14/D14,0))=0,0,(IFERROR(E14/D14,0)-1)) -> 0 | H14: =IF((IFERROR(E14/F14,0))=0,0,(IFERROR(E14/F14,0)-1)) -> 0 | J14: 0 | K14: 49692.8 | L14: 0 | M14: =IF((IFERROR(K14/J14,0))=0,0,(IFERROR(K14/J14,0)-1)) -> 0 | N14: =IF((IFERROR(K14/L14,0))=0,0,(IFERROR(K14/L14,0)-1)) -> 0 | P14: 1040862.1 | Q14: 403754 | R14: 1450000 | S14: =IF((IFERROR(Q14/P14,0))=0,0,(IFERROR(Q14/P14,0)-1)) -> -0.61209654 | T14: =IF((IFERROR(Q14/R14,0))=0,0,(IFERROR(Q14/R14,0)-1)) -> -0.72154897 | V14: 0 | W14: 74539.2 | X14: 0 | Y14: =IF((IFERROR(W14/V14,0))=0,0,(IFERROR(W14/V14,0)-1)) -> 0 | Z14: =IF((IFERROR(W14/X14,0))=0,0,(IFERROR(W14/X14,0)-1)) -> 0
B15: 405-000-000-00 | C15: Trade & Investment Center | D15: 0 | E15: =SUMIF('México Summary'!$C:$C,'Copia de Copia de Resumen (Caps'!B15,'México Summary'!$AC:$AC) -> 840000 | F15: 0 | G15: =IF((IFERROR(E15/D15,0))=0,0,(IFERROR(E15/D15,0)-1)) -> 0 | H15: =IF((IFERROR(E15/F15,0))=0,0,(IFERROR(E15/F15,0)-1)) -> 0
C16: Services to Members | D16: =D17+D19+D18 -> 1173900 | E16: =E17+E19+E18 -> 2685245 | F16: =F17+F19+F18 -> 840000 | G16: =IF((IFERROR(E16/D16,0))=0,0,(IFERROR(E16/D16,0)-1)) -> 1.2874563 | H16: =IF((IFERROR(E16/F16,0))=0,0,(IFERROR(E16/F16,0)-1)) -> 2.1967202 | J16: 680206.7 | K16: 714217.03 | L16: 567226.8 | M16: =IF((IFERROR(K16/J16,0))=0,0,(IFERROR(K16/J16,0)-1)) -> 0.05 | N16: =IF((IFERROR(K16/L16,0))=0,0,(IFERROR(K16/L16,0)-1)) -> 0.25913838 | P16: 874400 | Q16: 918120 | R16: 510900 | S16: =IF((IFERROR(Q16/P16,0))=0,0,(IFERROR(Q16/P16,0)-1)) -> 0.05 | T16: =IF((IFERROR(Q16/R16,0))=0,0,(IFERROR(Q16/R16,0)-1)) -> 0.797064 | V16: 94100 | W16: 99067 | X16: 131000 | Y16: =IF((IFERROR(W16/V16,0))=0,0,(IFERROR(W16/V16,0)-1)) -> 0.052784272 | Z16: =IF((IFERROR(W16/X16,0))=0,0,(IFERROR(W16/X16,0)-1)) -> -0.24376336
B17: 406-001-000-00 | C17: Venta Publicaciones | D17: 1173900 | E17: =SUMIF('México Summary'!$C:$C,'Copia de Copia de Resumen (Caps'!B17,'México Summary'!$AC:$AC) -> 1232595 | F17: 840000 | G17: =IF((IFERROR(E17/D17,0))=0,0,(IFERROR(E17/D17,0)-1)) -> 0.05 | H17: =IF((IFERROR(E17/F17,0))=0,0,(IFERROR(E17/F17,0)-1)) -> 0.467375
B18: 406-002-000-00 | C18: Digital Training | D18: 0 | E18: =SUMIF('México Summary'!$C:$C,'Copia de Copia de Resumen (Caps'!B18,'México Summary'!$AC:$AC) -> 1452650 | F18: 0 | G18: =IF((IFERROR(E18/D18,0))=0,0,(IFERROR(E18/D18,0)-1)) -> 0 | H18: =IF((IFERROR(E18/F18,0))=0,0,(IFERROR(E18/F18,0)-1)) -> 0
B19: 409-000-000-00 | C19: Visas | D19: 0 | E19: =SUMIF('México Summary'!$C:$C,'Copia de Copia de Resumen (Caps'!B19,'México Summary'!$AC:$AC) -> 0 | F19: 0 | G19: =IF((IFERROR(E19/D19,0))=0,0,(IFERROR(E19/D19,0)-1)) -> 0 | H19: =IF((IFERROR(E19/F19,0))=0,0,(IFERROR(E19/F19,0)-1)) -> 0
B20: 450-001-000-00 | C20: Guadalajara Income | D20: 0 | E20: =SUMIF('México Summary'!$C:$C,'Copia de Copia de Resumen (Caps'!B20,'México Summary'!$AC:$AC) -> 0 | F20: 0 | G20: =IF((IFERROR(E20/D20,0))=0,0,(IFERROR(E20/D20,0)-1)) -> 0 | H20: =IF((IFERROR(E20/F20,0))=0,0,(IFERROR(E20/F20,0)-1)) -> 0
B21: 450-002-000-00 | C21: Monterrey Income | D21: 0 | E21: =SUMIF('México Summary'!$C:$C,'Copia de Copia de Resumen (Caps'!B21,'México Summary'!$AC:$AC) -> 0 | F21: 0 | G21: =IF((IFERROR(E21/D21,0))=0,0,(IFERROR(E21/D21,0)-1)) -> 0 | H21: =IF((IFERROR(E21/F21,0))=0,0,(IFERROR(E21/F21,0)-1)) -> 0
B22: 450-003-000-00 | C22: Northwest Income | D22: 0 | E22: =SUMIF('México Summary'!$C:$C,'Copia de Copia de Resumen (Caps'!B22,'México Summary'!$AC:$AC) -> 0 | F22: 0 | G22: =IF((IFERROR(E22/D22,0))=0,0,(IFERROR(E22/D22,0)-1)) -> 0 | H22: =IF((IFERROR(E22/F22,0))=0,0,(IFERROR(E22/F22,0)-1)) -> 0
C23: CONSOLIDATED INCOME | D23: =D22+D21+D20+D4 -> 63870318 | E23: =E22+E21+E20+E4 -> 71683976 | F23: =F22+F21+F20+F4 -> 62529782 | G23: =IF((IFERROR(E23/D23,0))=0,0,(IFERROR(E23/D23,0)-1)) -> 0.1223363 | H23: =IF((IFERROR(E23/F23,0))=0,0,(IFERROR(E23/F23,0)-1)) -> 0.14639734
C24: EXPENSE | D24: =D25+D28+D30+D36+D39+D53+D54+D62 -> 61514669 | E24: =E25+E28+E30+E36+E39+E53+E54+E62+E34 -> 71775247 | F24: =F25+F28+F30+F36+F39+F53+F54+F62 -> 61625391 | G24: =IF((IFERROR(E24/D24,0))=0,0,(IFERROR(E24/D24,0)-1)) -> 0.16679888 | H24: =IF((IFERROR(E24/F24,0))=0,0,(IFERROR(E24/F24,0)-1)) -> 0.1647025 | J24: =J25+J28+J30+J34+J36+J39+J53+J54+J62 -> 15592230 | K24: =K25+K28+K30+K34+K36+K39+K53+K54+K62 -> 18020999 | L24: =L25+L28+L30+L34+L36+L39+L53+L54+L62 -> 16453320 | M24: =IF((IFERROR(K24/J24,0))=0,0,(IFERROR(K24/J24,0)-1)) -> 0.15576791 | N24: =IF((IFERROR(K24/L24,0))=0,0,(IFERROR(K24/L24,0)-1)) -> 0.095280383 | P24: =P25+P28+P30+P34+P36+P39+P53+P54+P62 -> 33952718 | Q24: =Q25+Q28+Q30+Q34+Q36+Q39+Q53+Q54+Q62 -> 38742220 | R24: =R25+R28+R30+R34+R36+R39+R53+R54+R62 -> 33410427 | S24: =IF((IFERROR(Q24/P24,0))=0,0,(IFERROR(Q24/P24,0)-1)) -> 0.14106389 | T24: =IF((IFERROR(Q24/R24,0))=0,0,(IFERROR(Q24/R24,0)-1)) -> 0.15958469 | V24: =V25+V28+V30+V34+V36+V39+V53+V54+V62 -> 4887742.8 | W24: =W25+W28+W30+W34+W36+W39+W53+W54+W62 -> 6337240.5 | X24: =X25+X28+X30+X34+X36+X39+X53+X54+X62 -> 5864476.4 | Y24: =IF((IFERROR(W24/V24,0))=0,0,(IFERROR(W24/V24,0)-1)) -> 0.29655768 | Z24: =IF((IFERROR(W24/X24,0))=0,0,(IFERROR(W24/X24,0)-1)) -> 0.080614883
C25: Membership | D25: =D26+D27 -> 2777026.4 | E25: =E26+E27 -> 2949107.9 | F25: =F26+F27 -> 2584139.3 | G25: =IF((IFERROR(E25/D25,0))=0,0,(IFERROR(E25/D25,0)-1)) -> 0.061966102 | H25: =IF((IFERROR(E25/F25,0))=0,0,(IFERROR(E25/F25,0)-1)) -> 0.14123409 | J25: 482307.62 | K25: 522373.81 | L25: 675870.6 | M25: =IF((IFERROR(K25/J25,0))=0,0,(IFERROR(K25/J25,0)-1)) -> 0.083071863 | N25: =IF((IFERROR(K25/L25,0))=0,0,(IFERROR(K25/L25,0)-1)) -> -0.22710973 | P25: 1793471.4 | Q25: 1901079.7 | R25: 2224320 | S25: =IF((IFERROR(Q25/P25,0))=0,0,(IFERROR(Q25/P25,0)-1)) -> 0.06 | T25: =IF((IFERROR(Q25/R25,0))=0,0,(IFERROR(Q25/R25,0)-1)) -> -0.14532097 | V25: 318541 | W25: 369485.92 | X25: 618375 | Y25: =IF((IFERROR(W25/V25,0))=0,0,(IFERROR(W25/V25,0)-1)) -> 0.15993207 | Z25: =IF((IFERROR(W25/X25,0))=0,0,(IFERROR(W25/X25,0)-1)) -> -0.40248891
B26: 705-000-000-00 | C26: Gastos Promoción | D26: 832000 | E26: =SUMIF('México Summary'!$C:$C,'Copia de Copia de Resumen (Caps'!B26,'México Summary'!$AC:$AC) -> 887380 | F26: 863500 | G26: =IF((IFERROR(E26/D26,0))=0,0,(IFERROR(E26/D26,0)-1)) -> 0.0665625 | H26: =IF((IFERROR(E26/F26,0))=0,0,(IFERROR(E26/F26,0)-1)) -> 0.027654893
B27: 520-000-000-00 | C27: Comsiones por venta de membresía | D27: 1945026.4 | E27: =SUMIF('México Summary'!$C:$C,'Copia de Copia de Resumen (Caps'!B27,'México Summary'!$AC:$AC) -> 2061727.9 | F27: 1720639.3 | G27: =IF((IFERROR(E27/D27,0))=0,0,(IFERROR(E27/D27,0)-1)) -> 0.059999958 | H27: =IF((IFERROR(E27/F27,0))=0,0,(IFERROR(E27/F27,0)-1)) -> 0.19823362
C28: Events | D28: =D29 -> 8552654.8 | E28: =E29 -> 6727036.8 | F28: =F29 -> 9107000 | G28: =IF((IFERROR(E28/D28,0))=0,0,(IFERROR(E28/D28,0)-1)) -> -0.21345629 | H28: =IF((IFERROR(E28/F28,0))=0,0,(IFERROR(E28/F28,0)-1)) -> -0.26133339 | J28: 2341278.1 | K28: 2042171.9 | L28: 2956045 | M28: =IF((IFERROR(K28/J28,0))=0,0,(IFERROR(K28/J28,0)-1)) -> -0.12775339 | N28: =IF((IFERROR(K28/L28,0))=0,0,(IFERROR(K28/L28,0)-1)) -> -0.30915398 | P28: 4183139.5 | Q28: 4244536.5 | R28: 4450000 | S28: =IF((IFERROR(Q28/P28,0))=0,0,(IFERROR(Q28/P28,0)-1)) -> 0.014677242 | T28: =IF((IFERROR(Q28/R28,0))=0,0,(IFERROR(Q28/R28,0)-1)) -> -0.046171573 | V28: 234008.52 | W28: 218797.96 | X28: 270000 | Y28: =IF((IFERROR(W28/V28,0))=0,0,(IFERROR(W28/V28,0)-1)) -> -0.065000026 | Z28: =IF((IFERROR(W28/X28,0))=0,0,(IFERROR(W28/X28,0)-1)) -> -0.18963719
B29: 701-000-000-00 | C29: Costo Eventos | D29: 8552654.8 | E29: =SUMIF('México Summary'!$C:$C,'Copia de Copia de Resumen (Caps'!B29,'México Summary'!$AC:$AC) -> 6727036.8 | F29: 9107000 | G29: =IF((IFERROR(E29/D29,0))=0,0,(IFERROR(E29/D29,0)-1)) -> -0.21345629 | H29: =IF((IFERROR(E29/F29,0))=0,0,(IFERROR(E29/F29,0)-1)) -> -0.26133339
C30: Committees | D30: =SUM(D31:D33) -> 5477932.2 | E30: =SUM(E31:E33) -> 6940491.4 | F30: =SUM(F31:F33) -> 8604867.1 | G30: =IF((IFERROR(E30/D30,0))=0,0,(IFERROR(E30/D30,0)-1)) -> 0.26699111 | H30: =IF((IFERROR(E30/F30,0))=0,0,(IFERROR(E30/F30,0)-1)) -> -0.19342258 | J30: 776370.91 | K30: 776297.49 | L30: 896480 | M30: =IF((IFERROR(K30/J30,0))=0,0,(IFERROR(K30/J30,0)-1)) -> -9.4569489e-05 | N30: =IF((IFERROR(K30/L30,0))=0,0,(IFERROR(K30/L30,0)-1)) -> -0.13406045 | P30: 1413380.4 | Q30: 1495707.2 | R30: 1744550 | S30: =IF((IFERROR(Q30/P30,0))=0,0,(IFERROR(Q30/P30,0)-1)) -> 0.058248158 | T30: =IF((IFERROR(Q30/R30,0))=0,0,(IFERROR(Q30/R30,0)-1)) -> -0.14264008 | V30: 12000 | W30: 13200 | X30: 60000 | Y30: =IF((IFERROR(W30/V30,0))=0,0,(IFERROR(W30/V30,0)-1)) -> 0.1 | Z30: =IF((IFERROR(W30/X30,0))=0,0,(IFERROR(W30/X30,0)-1)) -> -0.78
B31: 702-000-000-00 | C31: Costo Comités | D31: 4236122.3 | E31: =SUMIF('México Summary'!$C:$C,'Copia de Copia de Resumen (Caps'!B31,'México Summary'!$AC:$AC) -> 5438618.2 | F31: 7363267.1 | G31: =IF((IFERROR(E31/D31,0))=0,0,(IFERROR(E31/D31,0)-1)) -> 0.28386715 | H31: =IF((IFERROR(E31/F31,0))=0,0,(IFERROR(E31/F31,0)-1)) -> -0.26138517
B32: 704-000-000-00 | C32: Costo Economex | D32: 1060899.9 | E32: =SUMIF('México Summary'!$C:$C,'Copia de Copia de Resumen (Caps'!B32,'México Summary'!$AC:$AC) -> 1299254 | F32: 1081600 | G32: =IF((IFERROR(E32/D32,0))=0,0,(IFERROR(E32/D32,0)-1)) -> 0.22467156 | H32: =IF((IFERROR(E32/F32,0))=0,0,(IFERROR(E32/F32,0)-1)) -> 0.20123336
B33: 521-000-000-00 | C33: Comisiones EWDP y Economex | D33: 180910 | E33: =SUMIF('México Summary'!$C:$C,'Copia de Copia de Resumen (Caps'!B33,'México Summary'!$AC:$AC) -> 202619.2 | F33: 160000 | G33: =IF((IFERROR(E33/D33,0))=0,0,(IFERROR(E33/D33,0)-1)) -> 0.12 | H33: =IF((IFERROR(E33/F33,0))=0,0,(IFERROR(E33/F33,0)-1)) -> 0.26637
C34: T&IC | D34: =D35 -> 0 | E34: =E35 -> 340000 | F34: =F35 -> 0 | G34: =IF((IFERROR(E34/D34,0))=0,0,(IFERROR(E34/D34,0)-1)) -> 0 | H34: =IF((IFERROR(E34/F34,0))=0,0,(IFERROR(E34/F34,0)-1)) -> 0 | J34: 0 | K34: 17808 | L34: 0 | M34: =IF((IFERROR(K34/J34,0))=0,0,(IFERROR(K34/J34,0)-1)) -> 0 | N34: =IF((IFERROR(K34/L34,0))=0,0,(IFERROR(K34/L34,0)-1)) -> 0 | P34: 723930.21 | Q34: 144690 | R34: 1250000 | S34: =IF((IFERROR(Q34/P34,0))=0,0,(IFERROR(Q34/P34,0)-1)) -> -0.80013267 | T34: =IF((IFERROR(Q34/R34,0))=0,0,(IFERROR(Q34/R34,0)-1)) -> -0.884248 | V34: 0 | W34: 26712 | X34: 0 | Y34: =IF((IFERROR(W34/V34,0))=0,0,(IFERROR(W34/V34,0)-1)) -> 0 | Z34: =IF((IFERROR(W34/X34,0))=0,0,(IFERROR(W34/X34,0)-1)) -> 0
B35: 703-000-000-00 | C35: Costo Trade & Investment Center | D35: 0 | E35: =SUMIF('México Summary'!$C:$C,'Copia de Copia de Resumen (Caps'!B35,'México Summary'!$AC:$AC) -> 340000 | F35: 0 | G35: =IF((IFERROR(E35/D35,0))=0,0,(IFERROR(E35/D35,0)-1)) -> 0 | H35: =IF((IFERROR(E35/F35,0))=0,0,(IFERROR(E35/F35,0)-1)) -> 0
C36: Services to Members | D36: =D37+D38 -> 557700 | E36: =E37+E38 -> 1268666.8 | F36: =F37+F38 -> 420000 | G36: =IF((IFERROR(E36/D36,0))=0,0,(IFERROR(E36/D36,0)-1)) -> 1.2748194 | H36: =IF((IFERROR(E36/F36,0))=0,0,(IFERROR(E36/F36,0)-1)) -> 2.0206352 | J36: 340103.35 | K36: 357108.52 | L36: 283613.4 | M36: =IF((IFERROR(K36/J36,0))=0,0,(IFERROR(K36/J36,0)-1)) -> 0.05 | N36: =IF((IFERROR(K36/L36,0))=0,0,(IFERROR(K36/L36,0)-1)) -> 0.25913838 | P36: 444274 | Q36: 459060 | R36: 286104 | S36: =IF((IFERROR(Q36/P36,0))=0,0,(IFERROR(Q36/P36,0)-1)) -> 0.033281263 | T36: =IF((IFERROR(Q36/R36,0))=0,0,(IFERROR(Q36/R36,0)-1)) -> 0.60452143 | V36: 47050 | W36: 49533.5 | X36: 65500 | Y36: =IF((IFERROR(W36/V36,0))=0,0,(IFERROR(W36/V36,0)-1)) -> 0.052784272 | Z36: =IF((IFERROR(W36/X36,0))=0,0,(IFERROR(W36/X36,0)-1)) -> -0.24376336
B37: 601-002-003-00 | C37: Costo Venta Publicaciones | D37: 557700 | E37: =SUMIF('México Summary'!$C:$C,'Copia de Copia de Resumen (Caps'!B37,'México Summary'!$AC:$AC) -> 542341.8 | F37: 420000 | G37: =IF((IFERROR(E37/D37,0))=0,0,(IFERROR(E37/D37,0)-1)) -> -0.027538462 | H37: =IF((IFERROR(E37/F37,0))=0,0,(IFERROR(E37/F37,0)-1)) -> 0.29129
B38: 601-003-001-00 | C38: Costo Digital Training | D38: 0 | E38: =SUMIF('México Summary'!$C:$C,'Copia de Copia de Resumen (Caps'!B38,'México Summary'!$AC:$AC) -> 726325 | F38: 0 | G38: =IF((IFERROR(E38/D38,0))=0,0,(IFERROR(E38/D38,0)-1)) -> 0 | H38: =IF((IFERROR(E38/F38,0))=0,0,(IFERROR(E38/F38,0)-1)) -> 0
C39: Gastos Administrativos | D39: =SUM(D40:D52) -> 4141199.2 | E39: =SUM(E40:E52) -> 4705358 | F39: =SUM(F40:F52) -> 5070086.1 | G39: =IF((IFERROR(E39/D39,0))=0,0,(IFERROR(E39/D39,0)-1)) -> 0.13623078 | H39: =IF((IFERROR(E39/F39,0))=0,0,(IFERROR(E39/F39,0)-1)) -> -0.071937258 | J39: 402867.07 | K39: 496408.94 | L39: 532937.82 | M39: =IF((IFERROR(K39/J39,0))=0,0,(IFERROR(K39/J39,0)-1)) -> 0.23219042 | N39: =IF((IFERROR(K39/L39,0))=0,0,(IFERROR(K39/L39,0)-1)) -> -0.068542472 | P39: 976028.67 | Q39: 995988.15 | R39: 935209.05 | S39: =IF((IFERROR(Q39/P39,0))=0,0,(IFERROR(Q39/P39,0)-1)) -> 0.020449687 | T39: =IF((IFERROR(Q39/R39,0))=0,0,(IFERROR(Q39/R39,0)-1)) -> 0.064989855 | V39: 703279.36 | W39: 1393114.2 | X39: 1615380.4 | Y39: =IF((IFERROR(W39/V39,0))=0,0,(IFERROR(W39/V39,0)-1)) -> 0.98088316 | Z39: =IF((IFERROR(W39/X39,0))=0,0,(IFERROR(W39/X39,0)-1)) -> -0.13759367
B40: 801-001-000-00 | C40: Desarrollo de Negocios | D40: 477398.26 | E40: =SUMIF('México Summary'!$C:$C,'Copia de Copia de Resumen (Caps'!B40,'México Summary'!$AC:$AC) -> 656495.11 | F40: 579831.32 | G40: =IF((IFERROR(E40/D40,0))=0,0,(IFERROR(E40/D40,0)-1)) -> 0.37515187 | H40: =IF((IFERROR(E40/F40,0))=0,0,(IFERROR(E40/F40,0)-1)) -> 0.1322174
B41: 801-002-000-00 | C41: Relaciones Externas | D41: 0 | E41: =SUMIF('México Summary'!$C:$C,'Copia de Copia de Resumen (Caps'!B41,'México Summary'!$AC:$AC) -> 0 | F41: 0 | G41: =IF((IFERROR(E41/D41,0))=0,0,(IFERROR(E41/D41,0)-1)) -> 0 | H41: =IF((IFERROR(E41/F41,0))=0,0,(IFERROR(E41/F41,0)-1)) -> 0
B42: 801-003-000-00 | C42: Servicios a las membresia | D42: 0 | E42: =SUMIF('México Summary'!$C:$C,'Copia de Copia de Resumen (Caps'!B42,'México Summary'!$AC:$AC) -> 0 | F42: 0 | G42: =IF((IFERROR(E42/D42,0))=0,0,(IFERROR(E42/D42,0)-1)) -> 0 | H42: =IF((IFERROR(E42/F42,0))=0,0,(IFERROR(E42/F42,0)-1)) -> 0
B43: 801-004-000-00 | C43: Vicepresidencia | D43: 734096.11 | E43: =SUMIF('México Summary'!$C:$C,'Copia de Copia de Resumen (Caps'!B43,'México Summary'!$AC:$AC) -> 924190.86 | F43: 1145597.2 | G43: =IF((IFERROR(E43/D43,0))=0,0,(IFERROR(E43/D43,0)-1)) -> 0.25895076 | H43: =IF((IFERROR(E43/F43,0))=0,0,(IFERROR(E43/F43,0)-1)) -> -0.19326718
B44: 801-005-000-00 | C44: Finanzas | D44: 424267.54 | E44: =SUMIF('México Summary'!$C:$C,'Copia de Copia de Resumen (Caps'!B44,'México Summary'!$AC:$AC) -> 467017.59 | F44: 747879.2 | G44: =IF((IFERROR(E44/D44,0))=0,0,(IFERROR(E44/D44,0)-1)) -> 0.10076201 | H44: =IF((IFERROR(E44/F44,0))=0,0,(IFERROR(E44/F44,0)-1)) -> -0.37554408
B45: 801-006-000-00 | C45: Administración | D45: 173620.58 | E45: =SUMIF('México Summary'!$C:$C,'Copia de Copia de Resumen (Caps'!B45,'México Summary'!$AC:$AC) -> 395072.91 | F45: 158700 | G45: =IF((IFERROR(E45/D45,0))=0,0,(IFERROR(E45/D45,0)-1)) -> 1.2754959 | H45: =IF((IFERROR(E45/F45,0))=0,0,(IFERROR(E45/F45,0)-1)) -> 1.4894323
B46: 801-007-000-00 | C46: Sistemas | D46: 0 | E46: =SUMIF('México Summary'!$C:$C,'Copia de Copia de Resumen (Caps'!B46,'México Summary'!$AC:$AC) -> 0 | F46: 0 | G46: =IF((IFERROR(E46/D46,0))=0,0,(IFERROR(E46/D46,0)-1)) -> 0 | H46: =IF((IFERROR(E46/F46,0))=0,0,(IFERROR(E46/F46,0)-1)) -> 0
B47: 801-008-000-00 | C47: Empleos | D47: 0 | E47: =SUMIF('México Summary'!$C:$C,'Copia de Copia de Resumen (Caps'!B47,'México Summary'!$AC:$AC) -> 0 | F47: 0 | G47: =IF((IFERROR(E47/D47,0))=0,0,(IFERROR(E47/D47,0)-1)) -> 0 | H47: =IF((IFERROR(E47/F47,0))=0,0,(IFERROR(E47/F47,0)-1)) -> 0
B48: 801-009-000-00 | C48: Servicios Generales (Almacén) | D48: 0 | E48: =SUMIF('México Summary'!$C:$C,'Copia de Copia de Resumen (Caps'!B48,'México Summary'!$AC:$AC) -> 0 | F48: 0 | G48: =IF((IFERROR(E48/D48,0))=0,0,(IFERROR(E48/D48,0)-1)) -> 0 | H48: =IF((IFERROR(E48/F48,0))=0,0,(IFERROR(E48/F48,0)-1)) -> 0
B49: 801-010-000-00 | C49: Eventos | D49: 398515.05 | E49: =SUMIF('México Summary'!$C:$C,'Copia de Copia de Resumen (Caps'!B49,'México Summary'!$AC:$AC) -> 625945.18 | F49: 452700 | G49: =IF((IFERROR(E49/D49,0))=0,0,(IFERROR(E49/D49,0)-1)) -> 0.57069395 | H49: =IF((IFERROR(E49/F49,0))=0,0,(IFERROR(E49/F49,0)-1)) -> 0.38269313
B50: 801-011-000-00 | C50: Comites | D50: 520549.57 | E50: =SUMIF('México Summary'!$C:$C,'Copia de Copia de Resumen (Caps'!B50,'México Summary'!$AC:$AC) -> 781454.96 | F50: 493958.4 | G50: =IF((IFERROR(E50/D50,0))=0,0,(IFERROR(E50/D50,0)-1)) -> 0.50121142 | H50: =IF((IFERROR(E50/F50,0))=0,0,(IFERROR(E50/F50,0)-1)) -> 0.58202585
B51: 801-012-000-00 | C51: Renta de Salas | D51: 0 | E51: =SUMIF('México Summary'!$C:$C,'Copia de Copia de Resumen (Caps'!B51,'México Summary'!$AC:$AC) -> 0 | F51: 0 | G51: =IF((IFERROR(E51/D51,0))=0,0,(IFERROR(E51/D51,0)-1)) -> 0 | H51: =IF((IFERROR(E51/F51,0))=0,0,(IFERROR(E51/F51,0)-1)) -> 0
B52: 801-013-000-00 | C52: Comunicación | D52: 1412752.1 | E52: =SUMIF('México Summary'!$C:$C,'Copia de Copia de Resumen (Caps'!B52,'México Summary'!$AC:$AC) -> 855181.42 | F52: 1491420 | G52: =IF((IFERROR(E52/D52,0))=0,0,(IFERROR(E52/D52,0)-1)) -> -0.39466986 | H52: =IF((IFERROR(E52/F52,0))=0,0,(IFERROR(E52/F52,0)-1)) -> -0.4265992
B53: 901-000-000-00 | C53: Gastos Generales | D53: 7939704.1 | E53: =SUMIF('México Summary'!$C:$C,'Copia de Copia de Resumen (Caps'!B53,'México Summary'!$AC:$AC) -> 8506216.4 | F53: 8413203.5 | G53: =IF((IFERROR(E53/D53,0))=0,0,(IFERROR(E53/D53,0)-1)) -> 0.071351818 | H53: =IF((IFERROR(E53/F53,0))=0,0,(IFERROR(E53/F53,0)-1)) -> 0.011055585 | J53: 1372892.7 | K53: 1809100.7 | L53: 1467280.1 | M53: =IF((IFERROR(K53/J53,0))=0,0,(IFERROR(K53/J53,0)-1)) -> 0.31772906 | N53: =IF((IFERROR(K53/L53,0))=0,0,(IFERROR(K53/L53,0)-1)) -> 0.23296207 | P53: 2638864.7 | Q53: 4410097.8 | R53: 3404584.7 | S53: =IF((IFERROR(Q53/P53,0))=0,0,(IFERROR(Q53/P53,0)-1)) -> 0.67121026 | T53: =IF((IFERROR(Q53/R53,0))=0,0,(IFERROR(Q53/R53,0)-1)) -> 0.29534089 | V53: 195609.04 | W53: 323135.62 | X53: 213513.03 | Y53: =IF((IFERROR(W53/V53,0))=0,0,(IFERROR(W53/V53,0)-1)) -> 0.65194627 | Z53: =IF((IFERROR(W53/X53,0))=0,0,(IFERROR(W53/X53,0)-1)) -> 0.51342342
C54: Nómina | D54: =SUM(D55:D61)+1366439+886066.64 -> 17347185 | E54: 21149050 | F54: =SUM(F55:F61) -> 13119015 | G54: =IF((IFERROR(E54/D54,0))=0,0,(IFERROR(E54/D54,0)-1)) -> 0.21916327 | H54: =IF((IFERROR(E54/F54,0))=0,0,(IFERROR(E54/F54,0)-1)) -> 0.61209133 | J54: 5848248.4 | K54: 7550054.4 | L54: 5720425.7 | M54: =IF((IFERROR(K54/J54,0))=0,0,(IFERROR(K54/J54,0)-1)) -> 0.29099414 | N54: =IF((IFERROR(K54/L54,0))=0,0,(IFERROR(K54/L54,0)-1)) -> 0.31984136 | P54: 13233035 | Q54: 15709723 | R54: 10606138 | S54: =IF((IFERROR(Q54/P54,0))=0,0,(IFERROR(Q54/P54,0)-1)) -> 0.1871595 | T54: =IF((IFERROR(Q54/R54,0))=0,0,(IFERROR(Q54/R54,0)-1)) -> 0.48119171 | V54: 1883615.9 | W54: 2117554.4 | X54: 1655980 | Y54: =IF((IFERROR(W54/V54,0))=0,0,(IFERROR(W54/V54,0)-1)) -> 0.12419653 | Z54: =IF((IFERROR(W54/X54,0))=0,0,(IFERROR(W54/X54,0)-1)) -> 0.27873192
B55: 513-000-000-00 | C55: Nomina Vicepresidencia | D55: 576330.22 | E55: =SUMIF('México Summary'!$C:$C,'Copia de Copia de Resumen (Caps'!B55,'México Summary'!$AC:$AC) -> 542438.28 | F55: 334036.73 | G55: =IF((IFERROR(E55/D55,0))=0,0,(IFERROR(E55/D55,0)-1)) -> -0.058806463 | H55: =IF((IFERROR(E55/F55,0))=0,0,(IFERROR(E55/F55,0)-1)) -> 0.62388814
B56: 517-000-000-00 | C56: Nomina Desarrollo de Negocios | D56: 3856950.5 | E56: =SUMIF('México Summary'!$C:$C,'Copia de Copia de Resumen (Caps'!B56,'México Summary'!$AC:$AC) -> 4883189.3 | F56: 3385754.8 | G56: =IF((IFERROR(E56/D56,0))=0,0,(IFERROR(E56/D56,0)-1)) -> 0.26607518 | H56: =IF((IFERROR(E56/F56,0))=0,0,(IFERROR(E56/F56,0)-1)) -> 0.44227492
B57: 516-000-000-00 | C57: Nomina Comites y Relaciones Externas | D57: 4593443.9 | E57: =SUMIF('México Summary'!$C:$C,'Copia de Copia de Resumen (Caps'!B57,'México Summary'!$AC:$AC) -> 5213492.5 | F57: 4088183.5 | G57: =IF((IFERROR(E57/D57,0))=0,0,(IFERROR(E57/D57,0)-1)) -> 0.13498557 | H57: =IF((IFERROR(E57/F57,0))=0,0,(IFERROR(E57/F57,0)-1)) -> 0.27525892
B58: 519-000-000-00 | C58: Nomina Comunicación | D58: 1003603 | E58: =SUMIF('México Summary'!$C:$C,'Copia de Copia de Resumen (Caps'!B58,'México Summary'!$AC:$AC) -> 1448842.1 | F58: 876475.57 | G58: =IF((IFERROR(E58/D58,0))=0,0,(IFERROR(E58/D58,0)-1)) -> 0.44364065 | H58: =IF((IFERROR(E58/F58,0))=0,0,(IFERROR(E58/F58,0)-1)) -> 0.6530319
B59: 515-000-000-00 | C59: Nomina Servicios a la Membresia | D59: 1649823.9 | E59: =SUMIF('México Summary'!$C:$C,'Copia de Copia de Resumen (Caps'!B59,'México Summary'!$AC:$AC) -> 1925404.1 | F59: 1506952.1 | G59: =IF((IFERROR(E59/D59,0))=0,0,(IFERROR(E59/D59,0)-1)) -> 0.1670361 | H59: =IF((IFERROR(E59/F59,0))=0,0,(IFERROR(E59/F59,0)-1)) -> 0.27768101
B60: 518-000-000-00 | C60: Nomina Eventos y Mercadotecnia | D60: 764166.04 | E60: =SUMIF('México Summary'!$C:$C,'Copia de Copia de Resumen (Caps'!B60,'México Summary'!$AC:$AC) -> 566664.36 | F60: 672955.21 | G60: =IF((IFERROR(E60/D60,0))=0,0,(IFERROR(E60/D60,0)-1)) -> -0.25845389 | H60: =IF((IFERROR(E60/F60,0))=0,0,(IFERROR(E60/F60,0)-1)) -> -0.1579464
B61: 514-000-000-00 | C61: Nomina Administración y Fiananzas | D61: 2650361.4 | E61: =SUMIF('México Summary'!$C:$C,'Copia de Copia de Resumen (Caps'!B61,'México Summary'!$AC:$AC) -> 3913778.5 | F61: 2254657 | G61: =IF((IFERROR(E61/D61,0))=0,0,(IFERROR(E61/D61,0)-1)) -> 0.47669615 | H61: =IF((IFERROR(E61/F61,0))=0,0,(IFERROR(E61/F61,0)-1)) -> 0.73586425
B62: 903-000-000-00 | C62: Gastos Corporativos | D62: =14104808.71+373963.62+242495.76 -> 14721268 | E62: =SUMIF('México Summary'!$C:$C,'Copia de Copia de Resumen (Caps'!B62,'México Summary'!$AC:$AC) -> 19189320 | F62: 14307080 | G62: =IF((IFERROR(E62/D62,0))=0,0,(IFERROR(E62/D62,0)-1)) -> 0.30350997 | H62: =IF((IFERROR(E62/F62,0))=0,0,(IFERROR(E62/F62,0)-1)) -> 0.34124637 | J62: 4028161.6 | K62: 4449675.1 | L62: 3920667.6 | M62: =IF((IFERROR(K62/J62,0))=0,0,(IFERROR(K62/J62,0)-1)) -> 0.10464166 | N62: =IF((IFERROR(K62/L62,0))=0,0,(IFERROR(K62/L62,0)-1)) -> 0.13492791 | P62: 8546594.2 | Q62: 9381338 | R62: 8509522.2 | S62: =IF((IFERROR(Q62/P62,0))=0,0,(IFERROR(Q62/P62,0)-1)) -> 0.097669757 | T62: =IF((IFERROR(Q62/R62,0))=0,0,(IFERROR(Q62/R62,0)-1)) -> 0.10245179 | V62: 1493639 | W62: 1825706.8 | X62: 1365728.1 | Y62: =IF((IFERROR(W62/V62,0))=0,0,(IFERROR(W62/V62,0)-1)) -> 0.22232131 | Z62: =IF((IFERROR(W62/X62,0))=0,0,(IFERROR(W62/X62,0)-1)) -> 0.33680112
B63: 950-001-000-00 | C63: Guadalajara Expense | D63: 0 | E63: =SUMIF('México Summary'!$C:$C,'Copia de Copia de Resumen (Caps'!B63,'México Summary'!$AC:$AC) -> 0 | F63: 0 | G63: =IF((IFERROR(E63/D63,0))=0,0,(IFERROR(E63/D63,0)-1)) -> 0 | H63: =IF((IFERROR(E63/F63,0))=0,0,(IFERROR(E63/F63,0)-1)) -> 0
B64: 950-002-000-00 | C64: Monterrey Expense | D64: 0 | E64: =SUMIF('México Summary'!$C:$C,'Copia de Copia de Resumen (Caps'!B64,'México Summary'!$AC:$AC) -> 0 | F64: 0 | G64: =IF((IFERROR(E64/D64,0))=0,0,(IFERROR(E64/D64,0)-1)) -> 0 | H64: =IF((IFERROR(E64/F64,0))=0,0,(IFERROR(E64/F64,0)-1)) -> 0
B65: 950-003-000-00 | C65: Northwest Expense | D65: 0 | E65: =SUMIF('México Summary'!$C:$C,'Copia de Copia de Resumen (Caps'!B65,'México Summary'!$AC:$AC) -> 0 | F65: 0 | G65: =IF((IFERROR(E65/D65,0))=0,0,(IFERROR(E65/D65,0)-1)) -> 0 | H65: =IF((IFERROR(E65/F65,0))=0,0,(IFERROR(E65/F65,0)-1)) -> 0
C66: CONSOLIDATED EXPENSES | D66: =D65+D64+D63+D24 -> 61514669 | E66: =E65+E64+E63+E24 -> 71775247 | F66: =F65+F64+F63+F24 -> 61625391 | G66: =IF((IFERROR(E66/D66,0))=0,0,(IFERROR(E66/D66,0)-1)) -> 0.16679888 | H66: =IF((IFERROR(E66/F66,0))=0,0,(IFERROR(E66/F66,0)-1)) -> 0.1647025
C68: OPERATING RESULTS MEXICO | D68: =D4-D24 -> 2355648.5 | E68: =E4-E24 -> -91271.429 | F68: =F4-F24 -> 904390.62 | G68: =IF((IFERROR(E68/D68,0))=0,0,(IFERROR(E68/D68,0)-1)) -> -1.0387458 | H68: =IF((IFERROR(E68/F68,0))=0,0,(IFERROR(E68/F68,0)-1)) -> -1.1009204 | J68: =J4-J24 -> 108778 | K68: =K4-K24 -> 574806.45 | L68: =L4-L24 -> 840995.69 | M68: =IF((IFERROR(K68/J68,0))=0,0,(IFERROR(K68/J68,0)-1)) -> 4.2842159 | N68: =IF((IFERROR(K68/L68,0))=0,0,(IFERROR(K68/L68,0)-1)) -> -0.31651677 | P68: =P4-P24 -> 823758.16 | Q68: =Q4-Q24 -> 566088.82 | R68: =R4-R24 -> 1562005.9 | S68: =IF((IFERROR(Q68/P68,0))=0,0,(IFERROR(Q68/P68,0)-1)) -> -0.31279732 | T68: =IF((IFERROR(Q68/R68,0))=0,0,(IFERROR(Q68/R68,0)-1)) -> -0.63758855 | V68: =V4-V24 -> 1417862.9 | W68: =W4-W24 -> 1247378.9 | X68: =X4-X24 -> 2308937.2 | Y68: =IF((IFERROR(W68/V68,0))=0,0,(IFERROR(W68/V68,0)-1)) -> -0.12024013 | Z68: =IF((IFERROR(W68/X68,0))=0,0,(IFERROR(W68/X68,0)-1)) -> -0.4597606
C69: OPERATING RESULTS GUADALAJARA | D69: =D20-D63 -> 0 | E69: =E20-E63 -> 0 | F69: =F20-F63 -> 0 | G69: =IF((IFERROR(E69/D69,0))=0,0,(IFERROR(E69/D69,0)-1)) -> 0 | H69: =IF((IFERROR(E69/F69,0))=0,0,(IFERROR(E69/F69,0)-1)) -> 0
C70: OPERATING RESULTS MONTERREY | D70: =D21-D64 -> 0 | E70: =E21-E64 -> 0 | F70: =F21-F64 -> 0 | G70: =IF((IFERROR(E70/D70,0))=0,0,(IFERROR(E70/D70,0)-1)) -> 0 | H70: =IF((IFERROR(E70/F70,0))=0,0,(IFERROR(E70/F70,0)-1)) -> 0
C71: OPERATING RESULTS NORTHWEST | D71: =D22-D65 -> 0 | E71: =E22-E65 -> 0 | F71: =F22-F65 -> 0 | G71: =IF((IFERROR(E71/D71,0))=0,0,(IFERROR(E71/D71,0)-1)) -> 0 | H71: =IF((IFERROR(E71/F71,0))=0,0,(IFERROR(E71/F71,0)-1)) -> 0
C73: CONSOLIDATED OPERATING RESULTS | D73: =SUM(D68:D72) -> 2355648.5 | E73: =SUM(E68:E72) -> -91271.429 | F73: =SUM(F68:F72) -> 904390.62 | G73: =IF((IFERROR(E73/D73,0))=0,0,(IFERROR(E73/D73,0)-1)) -> -1.0387458 | H73: =IF((IFERROR(E73/F73,0))=0,0,(IFERROR(E73/F73,0)-1)) -> -1.1009204
B75: 902-000-000-00 | C75: Member Centricity | D75: 1808869.4 | E75: =SUMIF('México Summary'!$C:$C,'Copia de Copia de Resumen (Caps'!B75,'México Summary'!$AC:$AC) -> 0 | F75: 0 | G75: =IF((IFERROR(E75/D75,0))=0,0,(IFERROR(E75/D75,0)-1)) -> 0 | H75: =IF((IFERROR(E75/F75,0))=0,0,(IFERROR(E75/F75,0)-1)) -> 0 | J75: 459718.4 | K75: 0 | L75: 0 | M75: =IF((IFERROR(K75/J75,0))=0,0,(IFERROR(K75/J75,0)-1)) -> 0 | N75: =IF((IFERROR(K75/L75,0))=0,0,(IFERROR(K75/L75,0)-1)) -> 0 | P75: 991831.01 | Q75: 0 | R75: 0 | S75: =IF((IFERROR(Q75/P75,0))=0,0,(IFERROR(Q75/P75,0)-1)) -> 0 | T75: =IF((IFERROR(Q75/R75,0))=0,0,(IFERROR(Q75/R75,0)-1)) -> 0 | V75: 0 | W75: 0 | X75: 0 | Y75: =IF((IFERROR(W75/V75,0))=0,0,(IFERROR(W75/V75,0)-1)) -> 0 | Z75: =IF((IFERROR(W75/X75,0))=0,0,(IFERROR(W75/X75,0)-1)) -> 0
C77: Other | D77: =SUM(D78:D81) -> 3230204.5 | E77: =SUM(E78:E81) -> 0 | F77: =SUM(F78:F81) -> 0 | G77: =IF((IFERROR(E77/D77,0))=0,0,(IFERROR(E77/D77,0)-1)) -> 0 | H77: =IF((IFERROR(E77/F77,0))=0,0,(IFERROR(E77/F77,0)-1)) -> 0 | J77: 145.45 | K77: 0 | L77: 0 | M77: =IF((IFERROR(K77/J77,0))=0,0,(IFERROR(K77/J77,0)-1)) -> 0 | N77: =IF((IFERROR(K77/L77,0))=0,0,(IFERROR(K77/L77,0)-1)) -> 0 | P77: 150125.94 | Q77: 0 | R77: 0 | S77: =IF((IFERROR(Q77/P77,0))=0,0,(IFERROR(Q77/P77,0)-1)) -> 0 | T77: =IF((IFERROR(Q77/R77,0))=0,0,(IFERROR(Q77/R77,0)-1)) -> 0 | V77: 0 | W77: 0 | X77: 0 | Y77: =IF((IFERROR(W77/V77,0))=0,0,(IFERROR(W77/V77,0)-1)) -> 0 | Z77: =IF((IFERROR(W77/X77,0))=0,0,(IFERROR(W77/X77,0)-1)) -> 0
B78: 413-000-000-00 | C78: Otros Ingresos | D78: 53602.71 | E78: =SUMIF('México Summary'!$C:$C,'Copia de Copia de Resumen (Caps'!B78,'México Summary'!$AC:$AC) -> 0 | F78: 0 | G78: =IF((IFERROR(E78/D78,0))=0,0,(IFERROR(E78/D78,0)-1)) -> 0 | H78: =IF((IFERROR(E78/F78,0))=0,0,(IFERROR(E78/F78,0)-1)) -> 0
B79: 414-000-000-00 | C79: Intereses Bancos | D79: 5495278.6 | E79: =SUMIF('México Summary'!$C:$C,'Copia de Copia de Resumen (Caps'!B79,'México Summary'!$AC:$AC) -> 0 | F79: 0 | G79: =IF((IFERROR(E79/D79,0))=0,0,(IFERROR(E79/D79,0)-1)) -> 0 | H79: =IF((IFERROR(E79/F79,0))=0,0,(IFERROR(E79/F79,0)-1)) -> 0
B80: 416-000-000-00 | C80: Utilidad Cambiaria Inversiones | D80: -8589913.5 | E80: =SUMIF('México Summary'!$C:$C,'Copia de Copia de Resumen (Caps'!B80,'México Summary'!$AC:$AC) -> 0 | F80: 0 | G80: =IF((IFERROR(E80/D80,0))=0,0,(IFERROR(E80/D80,0)-1)) -> 0 | H80: =IF((IFERROR(E80/F80,0))=0,0,(IFERROR(E80/F80,0)-1)) -> 0
B81: 418-000-000-00 | C81: Plusvalia/Minusvalia Portafolio Inversiones | D81: 6271236.7 | E81: =SUMIF('México Summary'!$C:$C,'Copia de Copia de Resumen (Caps'!B81,'México Summary'!$AC:$AC) -> 0 | F81: 0 | G81: =IF((IFERROR(E81/D81,0))=0,0,(IFERROR(E81/D81,0)-1)) -> 0 | H81: =IF((IFERROR(E81/F81,0))=0,0,(IFERROR(E81/F81,0)-1)) -> 0
C83: Guadalajara Other Income | D83: 0 | E83: 0 | F83: 0 | G83: =IF((IFERROR(E83/D83,0))=0,0,(IFERROR(E83/D83,0)-1)) -> 0 | H83: =IF((IFERROR(E83/F83,0))=0,0,(IFERROR(E83/F83,0)-1)) -> 0
C84: Monterrey Other Income | D84: 0 | E84: 0 | F84: 0 | G84: =IF((IFERROR(E84/D84,0))=0,0,(IFERROR(E84/D84,0)-1)) -> 0 | H84: =IF((IFERROR(E84/F84,0))=0,0,(IFERROR(E84/F84,0)-1)) -> 0
C85: Northwest Other Income | D85: 0 | E85: 0 | F85: 0 | G85: =IF((IFERROR(E85/D85,0))=0,0,(IFERROR(E85/D85,0)-1)) -> 0 | H85: =IF((IFERROR(E85/F85,0))=0,0,(IFERROR(E85/F85,0)-1)) -> 0
C87: NET RESULTS MEXICO | D87: =D68-D75+D77 -> 3776983.6 | E87: =E68-E75+E77 -> -91271.429 | F87: =F68-F75+F77 -> 904390.62 | G87: =IF((IFERROR(E87/D87,0))=0,0,(IFERROR(E87/D87,0)-1)) -> -1.0241652 | H87: =IF((IFERROR(E87/F87,0))=0,0,(IFERROR(E87/F87,0)-1)) -> -1.1009204 | J87: =J68-J75+J77 -> -350794.95 | K87: =K68-K75+K77 -> 574806.45 | L87: =L68-L75+L77 -> 840995.69 | M87: =IF((IFERROR(K87/J87,0))=0,0,(IFERROR(K87/J87,0)-1)) -> -2.6385825 | N87: =IF((IFERROR(K87/L87,0))=0,0,(IFERROR(K87/L87,0)-1)) -> -0.31651677 | P87: =P68-P75+P77 -> -17946.91 | Q87: =Q68-Q75+Q77 -> 566088.82 | R87: =R68-R75+R77 -> 1562005.9 | S87: =IF((IFERROR(Q87/P87,0))=0,0,(IFERROR(Q87/P87,0)-1)) -> -32.542412 | T87: =IF((IFERROR(Q87/R87,0))=0,0,(IFERROR(Q87/R87,0)-1)) -> -0.63758855 | V87: =V68-V75+V77 -> 1417862.9 | W87: =W68-W75+W77 -> 1247378.9 | X87: =X68-X75+X77 -> 2308937.2 | Y87: =IF((IFERROR(W87/V87,0))=0,0,(IFERROR(W87/V87,0)-1)) -> -0.12024013 | Z87: =IF((IFERROR(W87/X87,0))=0,0,(IFERROR(W87/X87,0)-1)) -> -0.4597606
C88: NET RESULTS GUADALAJARA | D88: =D69+D83 -> 0 | E88: =E69+E83 -> 0 | F88: =F69+F83 -> 0 | G88: =IF((IFERROR(E88/D88,0))=0,0,(IFERROR(E88/D88,0)-1)) -> 0 | H88: =IF((IFERROR(E88/F88,0))=0,0,(IFERROR(E88/F88,0)-1)) -> 0
C89: NET RESULTS MONTERREY | D89: =D70+D84 -> 0 | E89: =E70+E84 -> 0 | F89: =F70+F84 -> 0 | G89: =IF((IFERROR(E89/D89,0))=0,0,(IFERROR(E89/D89,0)-1)) -> 0 | H89: =IF((IFERROR(E89/F89,0))=0,0,(IFERROR(E89/F89,0)-1)) -> 0
C90: NET RESULTS NORTHWEST | D90: =D71+D85 -> 0 | E90: =E71+E85 -> 0 | F90: =F71+F85 -> 0 | G90: =IF((IFERROR(E90/D90,0))=0,0,(IFERROR(E90/D90,0)-1)) -> 0 | H90: =IF((IFERROR(E90/F90,0))=0,0,(IFERROR(E90/F90,0)-1)) -> 0
C92: CONSOLIDATED NET RESULTS | D92: =SUM(D87:D91) -> 3776983.6 | E92: =SUM(E87:E91) -> -91271.429 | F92: =SUM(F87:F91) -> 904390.62 | G92: =IF((IFERROR(E92/D92,0))=0,0,(IFERROR(E92/D92,0)-1)) -> -1.0241652 | H92: =IF((IFERROR(E92/F92,0))=0,0,(IFERROR(E92/F92,0)-1)) -> -1.1009204
E94: =Resumen!J93 -> 2563969.8 | J94: -350794.95 | K94: 574806.45 | L94: 840995.69 | P94: -17946.91 | Q94: 566088.82 | R94: 1562005.9 | V94: 1417862.9 | W94: 1247378.9 | X94: 2308937.2
E95: =E87-E94 -> -2655241.2 | J95: =J87-J94 -> 0 | K95: =K87-K94 -> 0 | L95: =L87-L94 -> 0 | P95: =P87-P94 -> -1.4842954e-08 | Q95: =Q87-Q94 -> 0 | R95: =R87-R94 -> 0 | V95: =V87-V94 -> 0 | W95: =W87-W94 -> 0 | X95: =X87-X94 -> 0
C96: Bono 2026 - Sueldos NO corporativos: | D96: 1366439
C97: Sueldos Corporativos: | D97: 373963.62
C99: Bono 2026 - Sueldos NO corporativos: | D99: 886066.64
C100: Sueldos Corporativos: | D100: 242495.76

Sheet Resumen
C3: Real 2026 | D3: Ppto. 2026 | E3: Real 2025 | F3: Variación Ppto. 2026 vs Real 2026 | G3: Variación Real 2025 vs Real 2026 | H3: Sep 24 | I3: Real 2025 | J3: Ppto. 2026 | K3: Ppto. 2025 | L3: Variación Ppto. 2026 vs Forecast 2025 | M3: Variación Ppto. 2025 vs Ppto. 2026 | O3: Forecast 2026 | P3: Ppto. 2026 | Q3: Real 2025 | R3: Variación Ppto. 2026 vs Real 2026 | S3: Variación Real 2025 vs Real 2026 | U3: Proyectado 2026 | V3: Diferencia
C5: =SUM(C6,C9,C12,C17,C15) -> 0 | D5: =SUM(D6,D9,D12,D17,D15) -> 0 | E5: =SUM(E6,E9,E12,E17,E15) -> 0 | F5: =IF((IFERROR(C5/D5,0))=0,0,(IFERROR(C5/D5,0)-1)) -> 0 | G5: =IF((IFERROR(C5/E5,0))=0,0,(IFERROR(C5/E5,0)-1)) -> 0 | H5: INCOME | I5: =SUM(I6,I9,I12,I17,I15) -> 64619514 | J5: =SUM(J6,J9,J12,J17,J15) -> 71683976 | K5: =SUM(K6,K9,K12,K17,K15) -> 62529782 | L5: =IF((IFERROR(J5/I5,0))=0,0,(IFERROR(J5/I5,0)-1)) -> 0.10932398 | M5: =IF((IFERROR(J5/K5,0))=0,0,(IFERROR(J5/K5,0)-1)) -> 0.14639734 | O5: =SUM(O6,O9,O12,O17,O15) -> 0 | P5: =SUM(P6,P9,P12,P17,P15) -> 0 | Q5: =SUM(Q6,Q9,Q12,Q17,Q15) -> 0 | R5: =IF((IFERROR(O5/P5,0))=0,0,(IFERROR(O5/P5,0)-1)) -> 0 | S5: =IF((IFERROR(O5/Q5,0))=0,0,(IFERROR(O5/Q5,0)-1)) -> 0 | U5: =SUM(U6,U9,U12,U17,U15) -> 70785994 | V5: =SUM(V6,V9,V12,V17,V15) -> 897981.49 | W5: =(J5/U5)-1 -> 0.012685864
C6: =C7+C8 -> 0 | D6: =D7+D8 -> 0 | E6: =E7+E8 -> 0 | F6: =IF((IFERROR(C6/D6,0))=0,0,(IFERROR(C6/D6,0)-1)) -> 0 | G6: =IF((IFERROR(C6/E6,0))=0,0,(IFERROR(C6/E6,0)-1)) -> 0 | H6: Membership | I6: =I7+I8 -> 42611318 | J6: =J7+J8 -> 46872450 | K6: =K7+K8 -> 37282030 | L6: =IF((IFERROR(J6/I6,0))=0,0,(IFERROR(J6/I6,0)-1)) -> 0.1 | M6: =IF((IFERROR(J6/K6,0))=0,0,(IFERROR(J6/K6,0)-1)) -> 0.25723974 | O6: =O7+O8 -> 0 | P6: =P7+P8 -> 0 | Q6: =Q7+Q8 -> 0 | R6: =IF((IFERROR(O6/P6,0))=0,0,(IFERROR(O6/P6,0)-1)) -> 0 | S6: =IF((IFERROR(O6/Q6,0))=0,0,(IFERROR(O6/Q6,0)-1)) -> 0 | U6: 45480253 | V6: =J6-U6 -> 1392196.4 | W6: =(J6/U6)-1 -> 0.030611007
B7: 401-000-000-00 | C7: 0 | D7: 0 | E7: 0 | F7: =IF((IFERROR(C7/D7,0))=0,0,(IFERROR(C7/D7,0)-1)) -> 0 | G7: =IF((IFERROR(C7/E7,0))=0,0,(IFERROR(C7/E7,0)-1)) -> 0 | H7: Cuotas Netas | I7: 41346034 | J7: =SUMIF('México Summary'!$C:$C,Resumen!B7,'México Summary'!$AC:$AC) -> 45370058 | K7: 36117362 | L7: =IF((IFERROR(J7/I7,0))=0,0,(IFERROR(J7/I7,0)-1)) -> 0.097325506 | M7: =IF((IFERROR(J7/K7,0))=0,0,(IFERROR(J7/K7,0)-1)) -> 0.25618416 | O7: 0 | P7: 0 | Q7: 0 | R7: =IF((IFERROR(O7/P7,0))=0,0,(IFERROR(O7/P7,0)-1)) -> 0 | S7: =IF((IFERROR(O7/Q7,0))=0,0,(IFERROR(O7/Q7,0)-1)) -> 0
B8: 402-000-000-00 | C8: 0 | D8: 0 | E8: 0 | F8: =IF((IFERROR(C8/D8,0))=0,0,(IFERROR(C8/D8,0)-1)) -> 0 | G8: =IF((IFERROR(C8/E8,0))=0,0,(IFERROR(C8/E8,0)-1)) -> 0 | H8: Ingresos socios nuevos | I8: 1265283.3 | J8: =SUMIF('México Summary'!$C:$C,Resumen!B8,'México Summary'!$AC:$AC) -> 1502391.4 | K8: 1164667.8 | L8: =IF((IFERROR(J8/I8,0))=0,0,(IFERROR(J8/I8,0)-1)) -> 0.18739523 | M8: =IF((IFERROR(J8/K8,0))=0,0,(IFERROR(J8/K8,0)-1)) -> 0.2899742 | O8: 0 | P8: 0 | Q8: 0 | R8: =IF((IFERROR(O8/P8,0))=0,0,(IFERROR(O8/P8,0)-1)) -> 0 | S8: =IF((IFERROR(O8/Q8,0))=0,0,(IFERROR(O8/Q8,0)-1)) -> 0
C9: =C10+C11 -> 0 | D9: =D10+D11 -> 0 | E9: =E10+E11 -> 0 | F9: =IF((IFERROR(C9/D9,0))=0,0,(IFERROR(C9/D9,0)-1)) -> 0 | G9: =IF((IFERROR(C9/E9,0))=0,0,(IFERROR(C9/E9,0)-1)) -> 0 | H9: Events | I9: =I10+I11 -> 12859605 | J9: =J10+J11 -> 11511191 | K9: =K10+K11 -> 12957002 | L9: =IF((IFERROR(J9/I9,0))=0,0,(IFERROR(J9/I9,0)-1)) -> -0.10485653 | M9: =IF((IFERROR(J9/K9,0))=0,0,(IFERROR(J9/K9,0)-1)) -> -0.1115853 | O9: =O10+O11 -> 0 | P9: =P10+P11 -> 0 | Q9: =Q10+Q11 -> 0 | R9: =IF((IFERROR(O9/P9,0))=0,0,(IFERROR(O9/P9,0)-1)) -> 0 | S9: =IF((IFERROR(O9/Q9,0))=0,0,(IFERROR(O9/Q9,0)-1)) -> 0 | U9: 13157480 | V9: =J9-U9 -> -1646289.2 | W9: =(J9/U9)-1 -> -0.12512192
B10: 407-000-000-00 | C10: 0 | D10: 0 | E10: 0 | F10: =IF((IFERROR(C10/D10,0))=0,0,(IFERROR(C10/D10,0)-1)) -> 0 | G10: =IF((IFERROR(C10/E10,0))=0,0,(IFERROR(C10/E10,0)-1)) -> 0 | H10: Eventos | I10: 1856490.2 | J10: =SUMIF('México Summary'!$C:$C,Resumen!B10,'México Summary'!$AC:$AC) -> 1460000 | K10: 2250000 | L10: =IF((IFERROR(J10/I10,0))=0,0,(IFERROR(J10/I10,0)-1)) -> -0.21356976 | M10: =IF((IFERROR(J10/K10,0))=0,0,(IFERROR(J10/K10,0)-1)) -> -0.35111111 | O10: 0 | P10: 0 | Q10: 0 | R10: =IF((IFERROR(O10/P10,0))=0,0,(IFERROR(O10/P10,0)-1)) -> 0 | S10: =IF((IFERROR(O10/Q10,0))=0,0,(IFERROR(O10/Q10,0)-1)) -> 0 | U10: 13157480
B11: 408-000-000-00 | C11: 0 | D11: 0 | E11: 0 | F11: =IF((IFERROR(C11/D11,0))=0,0,(IFERROR(C11/D11,0)-1)) -> 0 | G11: =IF((IFERROR(C11/E11,0))=0,0,(IFERROR(C11/E11,0)-1)) -> 0 | H11: Patrocinios | I11: 11003115 | J11: =SUMIF('México Summary'!$C:$C,Resumen!B11,'México Summary'!$AC:$AC) -> 10051191 | K11: 10707002 | L11: =IF((IFERROR(J11/I11,0))=0,0,(IFERROR(J11/I11,0)-1)) -> -0.086513996 | M11: =IF((IFERROR(J11/K11,0))=0,0,(IFERROR(J11/K11,0)-1)) -> -0.061250657 | O11: 0 | P11: 0 | Q11: 0 | R11: =IF((IFERROR(O11/P11,0))=0,0,(IFERROR(O11/P11,0)-1)) -> 0 | S11: =IF((IFERROR(O11/Q11,0))=0,0,(IFERROR(O11/Q11,0)-1)) -> 0
C12: =C13+C14 -> 0 | D12: =D13+D14 -> 0 | E12: =E13+E14 -> 0 | F12: =IF((IFERROR(C12/D12,0))=0,0,(IFERROR(C12/D12,0)-1)) -> 0 | G12: =IF((IFERROR(C12/E12,0))=0,0,(IFERROR(C12/E12,0)-1)) -> 0 | H12: Committees | I12: =I13+I14 -> 6702991 | J12: =J13+J14 -> 9775090 | K12: =K13+K14 -> 11450750 | L12: =IF((IFERROR(J12/I12,0))=0,0,(IFERROR(J12/I12,0)-1)) -> 0.45831765 | M12: =IF((IFERROR(J12/K12,0))=0,0,(IFERROR(J12/K12,0)-1)) -> -0.14633627 | O12: =O13+O14 -> 0 | P12: =P13+P14 -> 0 | Q12: =Q13+Q14 -> 0 | R12: =IF((IFERROR(O12/P12,0))=0,0,(IFERROR(O12/P12,0)-1)) -> 0 | S12: =IF((IFERROR(O12/Q12,0))=0,0,(IFERROR(O12/Q12,0)-1)) -> 0 | U12: 11196646 | V12: =J12-U12 -> -1421555.7 | W12: =(J12/U12)-1 -> -0.12696264
B13: 417-000-000-00 | C13: 0 | D13: 0 | E13: 0 | F13: =IF((IFERROR(C13/D13,0))=0,0,(IFERROR(C13/D13,0)-1)) -> 0 | G13: =IF((IFERROR(C13/E13,0))=0,0,(IFERROR(C13/E13,0)-1)) -> 0 | H13: Comités | I13: 5748342.6 | J13: =SUMIF('México Summary'!$C:$C,Resumen!B13,'México Summary'!$AC:$AC) -> 8675090 | K13: 10800750 | L13: =IF((IFERROR(J13/I13,0))=0,0,(IFERROR(J13/I13,0)-1)) -> 0.5091463 | M13: =IF((IFERROR(J13/K13,0))=0,0,(IFERROR(J13/K13,0)-1)) -> -0.1968067 | O13: 0 | P13: 0 | Q13: 0 | R13: =IF((IFERROR(O13/P13,0))=0,0,(IFERROR(O13/P13,0)-1)) -> 0 | S13: =IF((IFERROR(O13/Q13,0))=0,0,(IFERROR(O13/Q13,0)-1)) -> 0
B14: 412-000-000-00 | C14: 0 | D14: 0 | E14: 0 | F14: =IF((IFERROR(C14/D14,0))=0,0,(IFERROR(C14/D14,0)-1)) -> 0 | G14: =IF((IFERROR(C14/E14,0))=0,0,(IFERROR(C14/E14,0)-1)) -> 0 | H14: Economex | I14: 954648.32 | J14: =SUMIF('México Summary'!$C:$C,Resumen!B14,'México Summary'!$AC:$AC) -> 1100000 | K14: 650000 | L14: =IF((IFERROR(J14/I14,0))=0,0,(IFERROR(J14/I14,0)-1)) -> 0.15225678 | M14: =IF((IFERROR(J14/K14,0))=0,0,(IFERROR(J14/K14,0)-1)) -> 0.69230769 | O14: 0 | P14: 0 | Q14: 0 | R14: =IF((IFERROR(O14/P14,0))=0,0,(IFERROR(O14/P14,0)-1)) -> 0 | S14: =IF((IFERROR(O14/Q14,0))=0,0,(IFERROR(O14/Q14,0)-1)) -> 0
C15: =C16 -> 0 | D15: =D16 -> 0 | E15: =E16 -> 0 | F15: =IF((IFERROR(C15/D15,0))=0,0,(IFERROR(C15/D15,0)-1)) -> 0 | G15: =IF((IFERROR(C15/E15,0))=0,0,(IFERROR(C15/E15,0)-1)) -> 0 | H15: T&IC | I15: =I16 -> 0 | J15: =J16 -> 840000 | K15: =K16 -> 0 | L15: =IF((IFERROR(J15/I15,0))=0,0,(IFERROR(J15/I15,0)-1)) -> 0 | M15: =IF((IFERROR(J15/K15,0))=0,0,(IFERROR(J15/K15,0)-1)) -> 0 | O15: =O16 -> 0 | P15: =P16 -> 0 | Q15: =Q16 -> 0 | R15: =IF((IFERROR(O15/P15,0))=0,0,(IFERROR(O15/P15,0)-1)) -> 0 | S15: =IF((IFERROR(O15/Q15,0))=0,0,(IFERROR(O15/Q15,0)-1)) -> 0 | U15: 0 | V15: =J15-U15 -> 840000 | W15: =(J15/U15)-1 -> #DIV/0!
B16: 405-000-000-00 | C16: 0 | D16: 0 | E16: 0 | F16: =IF((IFERROR(C16/D16,0))=0,0,(IFERROR(C16/D16,0)-1)) -> 0 | G16: =IF((IFERROR(C16/E16,0))=0,0,(IFERROR(C16/E16,0)-1)) -> 0 | H16: Trade & Investment Center | I16: 0 | J16: =SUMIF('México Summary'!$C:$C,Resumen!B16,'México Summary'!$AC:$AC) -> 840000 | K16: 0 | L16: =IF((IFERROR(J16/I16,0))=0,0,(IFERROR(J16/I16,0)-1)) -> 0 | M16: =IF((IFERROR(J16/K16,0))=0,0,(IFERROR(J16/K16,0)-1)) -> 0 | O16: 0 | P16: 0 | Q16: 0 | R16: =IF((IFERROR(O16/P16,0))=0,0,(IFERROR(O16/P16,0)-1)) -> 0 | S16: =IF((IFERROR(O16/Q16,0))=0,0,(IFERROR(O16/Q16,0)-1)) -> 0
C17: =C18+C20+C19 -> 0 | D17: =D18+D20+D19 -> 0 | E17: =E18+E20+E19 -> 0 | F17: =IF((IFERROR(C17/D17,0))=0,0,(IFERROR(C17/D17,0)-1)) -> 0 | G17: =IF((IFERROR(C17/E17,0))=0,0,(IFERROR(C17/E17,0)-1)) -> 0 | H17: Services to Members | I17: =I18+I20+I19 -> 2445600 | J17: =J18+J20+J19 -> 2685245 | K17: =K18+K20+K19 -> 840000 | L17: =IF((IFERROR(J17/I17,0))=0,0,(IFERROR(J17/I17,0)-1)) -> 0.097990268 | M17: =IF((IFERROR(J17/K17,0))=0,0,(IFERROR(J17/K17,0)-1)) -> 2.1967202 | O17: =O18+O20 -> 0 | P17: =P18+P20 -> 0 | Q17: =Q18+Q20 -> 0 | R17: =IF((IFERROR(O17/P17,0))=0,0,(IFERROR(O17/P17,0)-1)) -> 0 | S17: =IF((IFERROR(O17/Q17,0))=0,0,(IFERROR(O17/Q17,0)-1)) -> 0 | U17: 951615 | V17: =J17-U17 -> 1733630 | W17: =(J17/U17)-1 -> 1.8217767
B18: 406-001-000-00 | C18: 0 | D18: 0 | E18: 0 | F18: =IF((IFERROR(C18/D18,0))=0,0,(IFERROR(C18/D18,0)-1)) -> 0 | G18: =IF((IFERROR(C18/E18,0))=0,0,(IFERROR(C18/E18,0)-1)) -> 0 | H18: Venta Publicaciones | I18: 1292600 | J18: =SUMIF('México Summary'!$C:$C,Resumen!B18,'México Summary'!$AC:$AC) -> 1232595 | K18: 840000 | L18: =IF((IFERROR(J18/I18,0))=0,0,(IFERROR(J18/I18,0)-1)) -> -0.04642194 | M18: =IF((IFERROR(J18/K18,0))=0,0,(IFERROR(J18/K18,0)-1)) -> 0.467375 | O18: 0 | P18: 0 | Q18: 0 | R18: =IF((IFERROR(O18/P18,0))=0,0,(IFERROR(O18/P18,0)-1)) -> 0 | S18: =IF((IFERROR(O18/Q18,0))=0,0,(IFERROR(O18/Q18,0)-1)) -> 0
B19: 406-002-000-00 | C19: 0 | D19: 0 | E19: 0 | F19: =IF((IFERROR(C19/D19,0))=0,0,(IFERROR(C19/D19,0)-1)) -> 0 | G19: =IF((IFERROR(C19/E19,0))=0,0,(IFERROR(C19/E19,0)-1)) -> 0 | H19: Digital Training | I19: 1153000 | J19: =SUMIF('México Summary'!$C:$C,Resumen!B19,'México Summary'!$AC:$AC) -> 1452650 | K19: 0 | L19: =IF((IFERROR(J19/I19,0))=0,0,(IFERROR(J19/I19,0)-1)) -> 0.25988725 | M19: =IF((IFERROR(J19/K19,0))=0,0,(IFERROR(J19/K19,0)-1)) -> 0 | O19: 0 | P19: 0 | Q19: 0 | R19: =IF((IFERROR(O19/P19,0))=0,0,(IFERROR(O19/P19,0)-1)) -> 0 | S19: =IF((IFERROR(O19/Q19,0))=0,0,(IFERROR(O19/Q19,0)-1)) -> 0
B20: 409-000-000-00 | C20: 0 | D20: 0 | E20: 0 | F20: =IF((IFERROR(C20/D20,0))=0,0,(IFERROR(C20/D20,0)-1)) -> 0 | G20: =IF((IFERROR(C20/E20,0))=0,0,(IFERROR(C20/E20,0)-1)) -> 0 | H20: Visas | I20: 0 | J20: =SUMIF('México Summary'!$C:$C,Resumen!B20,'México Summary'!$AC:$AC) -> 0 | K20: 0 | L20: =IF((IFERROR(J20/I20,0))=0,0,(IFERROR(J20/I20,0)-1)) -> 0 | M20: =IF((IFERROR(J20/K20,0))=0,0,(IFERROR(J20/K20,0)-1)) -> 0 | O20: 0 | P20: 0 | Q20: 0 | R20: =IF((IFERROR(O20/P20,0))=0,0,(IFERROR(O20/P20,0)-1)) -> 0 | S20: =IF((IFERROR(O20/Q20,0))=0,0,(IFERROR(O20/Q20,0)-1)) -> 0
B21: 450-001-000-00 | C21: 0 | D21: 0 | E21: 0 | F21: =IF((IFERROR(C21/D21,0))=0,0,(IFERROR(C21/D21,0)-1)) -> 0 | G21: =IF((IFERROR(C21/E21,0))=0,0,(IFERROR(C21/E21,0)-1)) -> 0 | H21: Guadalajara Income | I21: 14196189 | J21: =SUMIF('México Summary'!$C:$C,Resumen!B21,'México Summary'!$AC:$AC) -> 0 | K21: 0 | L21: =IF((IFERROR(J21/I21,0))=0,0,(IFERROR(J21/I21,0)-1)) -> 0 | M21: =IF((IFERROR(J21/K21,0))=0,0,(IFERROR(J21/K21,0)-1)) -> 0 | O21: 0 | P21: 0 | Q21: 0 | R21: =IF((IFERROR(O21/P21,0))=0,0,(IFERROR(O21/P21,0)-1)) -> 0 | S21: =IF((IFERROR(O21/Q21,0))=0,0,(IFERROR(O21/Q21,0)-1)) -> 0
B22: 450-002-000-00 | C22: 0 | D22: 0 | E22: 0 | F22: =IF((IFERROR(C22/D22,0))=0,0,(IFERROR(C22/D22,0)-1)) -> 0 | G22: =IF((IFERROR(C22/E22,0))=0,0,(IFERROR(C22/E22,0)-1)) -> 0 | H22: Monterrey Income | I22: 32894975 | J22: =SUMIF('México Summary'!$C:$C,Resumen!B22,'México Summary'!$AC:$AC) -> 0 | K22: 0 | L22: =IF((IFERROR(J22/I22,0))=0,0,(IFERROR(J22/I22,0)-1)) -> 0 | M22: =IF((IFERROR(J22/K22,0))=0,0,(IFERROR(J22/K22,0)-1)) -> 0 | O22: 0 | P22: 0 | Q22: 0 | R22: =IF((IFERROR(O22/P22,0))=0,0,(IFERROR(O22/P22,0)-1)) -> 0 | S22: =IF((IFERROR(O22/Q22,0))=0,0,(IFERROR(O22/Q22,0)-1)) -> 0
B23: 450-003-000-00 | C23: 0 | D23: 0 | E23: 0 | F23: =IF((IFERROR(C23/D23,0))=0,0,(IFERROR(C23/D23,0)-1)) -> 0 | G23: =IF((IFERROR(C23/E23,0))=0,0,(IFERROR(C23/E23,0)-1)) -> 0 | H23: Northwest Income | I23: 5116359.8 | J23: =SUMIF('México Summary'!$C:$C,Resumen!B23,'México Summary'!$AC:$AC) -> 0 | K23: 0 | L23: =IF((IFERROR(J23/I23,0))=0,0,(IFERROR(J23/I23,0)-1)) -> 0 | M23: =IF((IFERROR(J23/K23,0))=0,0,(IFERROR(J23/K23,0)-1)) -> 0 | O23: 0 | P23: 0 | Q23: 0 | R23: =IF((IFERROR(O23/P23,0))=0,0,(IFERROR(O23/P23,0)-1)) -> 0 | S23: =IF((IFERROR(O23/Q23,0))=0,0,(IFERROR(O23/Q23,0)-1)) -> 0
C24: =C23+C22+C21+C5 -> 0 | D24: =D23+D22+D21+D5 -> 0 | E24: =E23+E22+E21+E5 -> 0 | F24: =IF((IFERROR(C24/D24,0))=0,0,(IFERROR(C24/D24,0)-1)) -> 0 | G24: =IF((IFERROR(C24/E24,0))=0,0,(IFERROR(C24/E24,0)-1)) -> 0 | H24: CONSOLIDATED INCOME | I24: =I23+I22+I21+I5 -> 1.1682704e+08 | J24: =J23+J22+J21+J5 -> 71683976 | K24: =K23+K22+K21+K5 -> 62529782 | L24: =IF((IFERROR(J24/I24,0))=0,0,(IFERROR(J24/I24,0)-1)) -> -0.38640936 | M24: =IF((IFERROR(J24/K24,0))=0,0,(IFERROR(J24/K24,0)-1)) -> 0.14639734 | O24: =O23+O22+O21+O5 -> 0 | P24: =P23+P22+P21+P5 -> 0 | Q24: =Q23+Q22+Q21+Q5 -> 0 | R24: =IF((IFERROR(O24/P24,0))=0,0,(IFERROR(O24/P24,0)-1)) -> 0 | S24: =IF((IFERROR(O24/Q24,0))=0,0,(IFERROR(O24/Q24,0)-1)) -> 0
C25: =C26+C29+C31+C37+C40+C54+C55+C63 -> 0 | D25: =D26+D29+D31+D37+D40+D54+D55+D63 -> 0 | E25: =E26+E29+E31+E37+E40+E54+E55+E63 -> 0 | F25: =IF((IFERROR(C25/D25,0))=0,0,(IFERROR(C25/D25,0)-1)) -> 0 | G25: =IF((IFERROR(C25/E25,0))=0,0,(IFERROR(C25/E25,0)-1)) -> 0 | H25: EXPENSE | I25: =I26+I29+I31+I37+I40+I54+I55+I63 -> 61247285 | J25: =J26+J29+J31+J37+J40+J54+J55+J63+J35 -> 69120006 | K25: =K26+K29+K31+K37+K40+K54+K55+K63 -> 61625391 | L25: =IF((IFERROR(J25/I25,0))=0,0,(IFERROR(J25/I25,0)-1)) -> 0.12853991 | M25: =IF((IFERROR(J25/K25,0))=0,0,(IFERROR(J25/K25,0)-1)) -> 0.12161569 | O25: =O26+O29+O31+O37+O40+O54+O55+O63 -> 0 | P25: =P26+P29+P31+P37+P40+P54+P55+P63 -> 0 | Q25: =Q26+Q29+Q31+Q37+Q40+Q54+Q55+Q63 -> 0 | R25: =IF((IFERROR(O25/P25,0))=0,0,(IFERROR(O25/P25,0)-1)) -> 0 | S25: =IF((IFERROR(O25/Q25,0))=0,0,(IFERROR(O25/Q25,0)-1)) -> 0 | U25: =U26+U29+U31+U37+U40+U54+U55+U63+U35 -> 68675899 | V25: =V26+V29+V31+V37+V40+V54+V55+V63+V35 -> 444106.74 | W25: =(J25/U25)-1 -> 0.0064667044
C26: =C27+C28 -> 0 | D26: =D27+D28 -> 0 | E26: =E27+E28 -> 0 | F26: =IF((IFERROR(C26/D26,0))=0,0,(IFERROR(C26/D26,0)-1)) -> 0 | G26: =IF((IFERROR(C26/E26,0))=0,0,(IFERROR(C26/E26,0)-1)) -> 0 | H26: Membership | I26: =I27+I28 -> 2207503.3 | J26: =J27+J28 -> 2949107.9 | K26: =K27+K28 -> 2584139.3 | L26: =IF((IFERROR(J26/I26,0))=0,0,(IFERROR(J26/I26,0)-1)) -> 0.33594723 | M26: =IF((IFERROR(J26/K26,0))=0,0,(IFERROR(J26/K26,0)-1)) -> 0.14123409 | O26: =O27+O28 -> 0 | P26: =P27+P28 -> 0 | Q26: =Q27+Q28 -> 0 | R26: =IF((IFERROR(O26/P26,0))=0,0,(IFERROR(O26/P26,0)-1)) -> 0 | S26: =IF((IFERROR(O26/Q26,0))=0,0,(IFERROR(O26/Q26,0)-1)) -> 0 | U26: 2768796.2 | V26: =J26-U26 -> 180311.72 | W26: =(J26/U26)-1 -> 0.065122786
B27: 705-000-000-00 | C27: 0 | D27: 0 | E27: 0 | F27: =IF((IFERROR(C27/D27,0))=0,0,(IFERROR(C27/D27,0)-1)) -> 0 | G27: =IF((IFERROR(C27/E27,0))=0,0,(IFERROR(C27/E27,0)-1)) -> 0 | H27: Gastos Promoción | I27: 225000 | J27: =SUMIF('México Summary'!$C:$C,Resumen!B27,'México Summary'!$AC:$AC) -> 887380 | K27: 863500 | L27: =IF((IFERROR(J27/I27,0))=0,0,(IFERROR(J27/I27,0)-1)) -> 2.9439111 | M27: =IF((IFERROR(J27/K27,0))=0,0,(IFERROR(J27/K27,0)-1)) -> 0.027654893 | O27: 0 | P27: 0 | Q27: 0 | R27: =IF((IFERROR(O27/P27,0))=0,0,(IFERROR(O27/P27,0)-1)) -> 0 | S27: =IF((IFERROR(O27/Q27,0))=0,0,(IFERROR(O27/Q27,0)-1)) -> 0
B28: 520-000-000-00 | C28: 0 | D28: 0 | E28: 0 | F28: =IF((IFERROR(C28/D28,0))=0,0,(IFERROR(C28/D28,0)-1)) -> 0 | G28: =IF((IFERROR(C28/E28,0))=0,0,(IFERROR(C28/E28,0)-1)) -> 0 | H28: Comsiones por venta de membresía | I28: 1982503.3 | J28: =SUMIF('México Summary'!$C:$C,Resumen!B28,'México Summary'!$AC:$AC) -> 2061727.9 | K28: 1720639.3 | L28: =IF((IFERROR(J28/I28,0))=0,0,(IFERROR(J28/I28,0)-1)) -> 0.039961902 | M28: =IF((IFERROR(J28/K28,0))=0,0,(IFERROR(J28/K28,0)-1)) -> 0.19823362 | O28: 0 | P28: 0 | Q28: 0 | R28: =IF((IFERROR(O28/P28,0))=0,0,(IFERROR(O28/P28,0)-1)) -> 0 | S28: =IF((IFERROR(O28/Q28,0))=0,0,(IFERROR(O28/Q28,0)-1)) -> 0
C29: =C30 -> 0 | D29: =D30 -> 0 | E29: =E30 -> 0 | F29: =IF((IFERROR(C29/D29,0))=0,0,(IFERROR(C29/D29,0)-1)) -> 0 | G29: =IF((IFERROR(C29/E29,0))=0,0,(IFERROR(C29/E29,0)-1)) -> 0 | H29: Events | I29: =I30 -> 8546422.2 | J29: =J30 -> 6727036.8 | K29: =K30 -> 9107000 | L29: =IF((IFERROR(J29/I29,0))=0,0,(IFERROR(J29/I29,0)-1)) -> -0.21288269 | M29: =IF((IFERROR(J29/K29,0))=0,0,(IFERROR(J29/K29,0)-1)) -> -0.26133339 | O29: =O30 -> 0 | P29: =P30 -> 0 | Q29: =Q30 -> 0 | R29: =IF((IFERROR(O29/P29,0))=0,0,(IFERROR(O29/P29,0)-1)) -> 0 | S29: =IF((IFERROR(O29/Q29,0))=0,0,(IFERROR(O29/Q29,0)-1)) -> 0 | U29: 7361729.1 | V29: =J29-U29 -> -634692.27 | W29: =(J29/U29)-1 -> -0.086215108 | AD29: =J29-Eventos!AB53 -> 0
B30: 701-000-000-00 | C30: 0 | D30: 0 | E30: 0 | F30: =IF((IFERROR(C30/D30,0))=0,0,(IFERROR(C30/D30,0)-1)) -> 0 | G30: =IF((IFERROR(C30/E30,0))=0,0,(IFERROR(C30/E30,0)-1)) -> 0 | H30: Costo Eventos | I30: 8546422.2 | J30: =SUMIF('México Summary'!$C:$C,Resumen!B30,'México Summary'!$AC:$AC) -> 6727036.8 | K30: 9107000 | L30: =IF((IFERROR(J30/I30,0))=0,0,(IFERROR(J30/I30,0)-1)) -> -0.21288269 | M30: =IF((IFERROR(J30/K30,0))=0,0,(IFERROR(J30/K30,0)-1)) -> -0.26133339 | O30: 0 | P30: 0 | Q30: 0 | R30: =IF((IFERROR(O30/P30,0))=0,0,(IFERROR(O30/P30,0)-1)) -> 0 | S30: =IF((IFERROR(O30/Q30,0))=0,0,(IFERROR(O30/Q30,0)-1)) -> 0
C31: =SUM(C32:C34) -> 0 | D31: =SUM(D32:D34) -> 0 | E31: =SUM(E32:E34) -> 0 | F31: =IF((IFERROR(C31/D31,0))=0,0,(IFERROR(C31/D31,0)-1)) -> 0 | G31: =IF((IFERROR(C31/E31,0))=0,0,(IFERROR(C31/E31,0)-1)) -> 0 | H31: Committees | I31: =SUM(I32:I34) -> 4258755.3 | J31: =SUM(J32:J34) -> 6940491.4 | K31: =SUM(K32:K34) -> 8604867.1 | L31: =IF((IFERROR(J31/I31,0))=0,0,(IFERROR(J31/I31,0)-1)) -> 0.6296995 | M31: =IF((IFERROR(J31/K31,0))=0,0,(IFERROR(J31/K31,0)-1)) -> -0.19342258 | O31: =SUM(O32:O34) -> 0 | P31: =SUM(P32:P34) -> 0 | Q31: =SUM(Q32:Q34) -> 0 | R31: =IF((IFERROR(O31/P31,0))=0,0,(IFERROR(O31/P31,0)-1)) -> 0 | S31: =IF((IFERROR(O31/Q31,0))=0,0,(IFERROR(O31/Q31,0)-1)) -> 0 | U31: 6179958.5 | V31: =J31-U31 -> 760532.98 | W31: =(J31/U31)-1 -> 0.12306442
B32: 702-000-000-00 | C32: 0 | D32: 0 | E32: 0 | F32: =IF((IFERROR(C32/D32,0))=0,0,(IFERROR(C32/D32,0)-1)) -> 0 | G32: =IF((IFERROR(C32/E32,0))=0,0,(IFERROR(C32/E32,0)-1)) -> 0 | H32: Costo Comités | I32: 3073058.1 | J32: =SUMIF('México Summary'!$C:$C,Resumen!B32,'México Summary'!$AC:$AC) -> 5438618.2 | K32: 7363267.1 | L32: =IF((IFERROR(J32/I32,0))=0,0,(IFERROR(J32/I32,0)-1)) -> 0.76977395 | M32: =IF((IFERROR(J32/K32,0))=0,0,(IFERROR(J32/K32,0)-1)) -> -0.26138517 | O32: 0 | P32: 0 | Q32: 0 | R32: =IF((IFERROR(O32/P32,0))=0,0,(IFERROR(O32/P32,0)-1)) -> 0 | S32: =IF((IFERROR(O32/Q32,0))=0,0,(IFERROR(O32/Q32,0)-1)) -> 0
B33: 704-000-000-00 | C33: 0 | D33: 0 | E33: 0 | F33: =IF((IFERROR(C33/D33,0))=0,0,(IFERROR(C33/D33,0)-1)) -> 0 | G33: =IF((IFERROR(C33/E33,0))=0,0,(IFERROR(C33/E33,0)-1)) -> 0 | H33: Costo Economex | I33: 1050317.2 | J33: =SUMIF('México Summary'!$C:$C,Resumen!B33,'México Summary'!$AC:$AC) -> 1299254 | K33: 1081600 | L33: =IF((IFERROR(J33/I33,0))=0,0,(IFERROR(J33/I33,0)-1)) -> 0.23701111 | M33: =IF((IFERROR(J33/K33,0))=0,0,(IFERROR(J33/K33,0)-1)) -> 0.20123336 | O33: 0 | P33: 0 | Q33: 0 | R33: =IF((IFERROR(O33/P33,0))=0,0,(IFERROR(O33/P33,0)-1)) -> 0 | S33: =IF((IFERROR(O33/Q33,0))=0,0,(IFERROR(O33/Q33,0)-1)) -> 0
B34: 521-000-000-00 | C34: 0 | D34: 0 | E34: 0 | F34: =IF((IFERROR(C34/D34,0))=0,0,(IFERROR(C34/D34,0)-1)) -> 0 | G34: =IF((IFERROR(C34/E34,0))=0,0,(IFERROR(C34/E34,0)-1)) -> 0 | H34: Comisiones EWDP y Economex | I34: 135380.03 | J34: =SUMIF('México Summary'!$C:$C,Resumen!B34,'México Summary'!$AC:$AC) -> 202619.2 | K34: 160000 | L34: =IF((IFERROR(J34/I34,0))=0,0,(IFERROR(J34/I34,0)-1)) -> 0.49666978 | M34: =IF((IFERROR(J34/K34,0))=0,0,(IFERROR(J34/K34,0)-1)) -> 0.26637 | O34: 0 | P34: 0 | Q34: 0 | R34: =IF((IFERROR(O34/P34,0))=0,0,(IFERROR(O34/P34,0)-1)) -> 0 | S34: =IF((IFERROR(O34/Q34,0))=0,0,(IFERROR(O34/Q34,0)-1)) -> 0
C35: =C36 -> 0 | D35: =D36 -> 0 | E35: =E36 -> 0 | F35: =IF((IFERROR(C35/D35,0))=0,0,(IFERROR(C35/D35,0)-1)) -> 0 | G35: =IF((IFERROR(C35/E35,0))=0,0,(IFERROR(C35/E35,0)-1)) -> 0 | H35: T&IC | I35: =I36 -> 0 | J35: =J36 -> 340000 | K35: =K36 -> 0 | L35: =IF((IFERROR(J35/I35,0))=0,0,(IFERROR(J35/I35,0)-1)) -> 0 | M35: =IF((IFERROR(J35/K35,0))=0,0,(IFERROR(J35/K35,0)-1)) -> 0 | O35: =O36 -> 0 | P35: =P36 -> 0 | Q35: =Q36 -> 0 | R35: =IF((IFERROR(O35/P35,0))=0,0,(IFERROR(O35/P35,0)-1)) -> 0 | S35: =IF((IFERROR(O35/Q35,0))=0,0,(IFERROR(O35/Q35,0)-1)) -> 0 | U35: 0 | V35: =J35-U35 -> 340000 | W35: =(J35/U35)-1 -> #DIV/0!
B36: 703-000-000-00 | C36: 0 | D36: 0 | E36: 0 | F36: =IF((IFERROR(C36/D36,0))=0,0,(IFERROR(C36/D36,0)-1)) -> 0 | G36: =IF((IFERROR(C36/E36,0))=0,0,(IFERROR(C36/E36,0)-1)) -> 0 | H36: Costo Trade & Investment Center | I36: 0 | J36: =SUMIF('México Summary'!$C:$C,Resumen!B36,'México Summary'!$AC:$AC) -> 340000 | K36: 0 | L36: =IF((IFERROR(J36/I36,0))=0,0,(IFERROR(J36/I36,0)-1)) -> 0 | M36: =IF((IFERROR(J36/K36,0))=0,0,(IFERROR(J36/K36,0)-1)) -> 0 | O36: 0 | P36: 0 | Q36: 0 | R36: =IF((IFERROR(O36/P36,0))=0,0,(IFERROR(O36/P36,0)-1)) -> 0 | S36: =IF((IFERROR(O36/Q36,0))=0,0,(IFERROR(O36/Q36,0)-1)) -> 0
C37: =C38+C39 -> 0 | D37: =D38+D39 -> 0 | E37: =E38+E39 -> 0 | F37: =IF((IFERROR(C37/D37,0))=0,0,(IFERROR(C37/D37,0)-1)) -> 0 | G37: =IF((IFERROR(C37/E37,0))=0,0,(IFERROR(C37/E37,0)-1)) -> 0 | H37: Services to Members | I37: =I38+I39 -> 1151300.3 | J37: =J38+J39 -> 1268666.8 | K37: =K38+K39 -> 420000 | L37: =IF((IFERROR(J37/I37,0))=0,0,(IFERROR(J37/I37,0)-1)) -> 0.10194259 | M37: =IF((IFERROR(J37/K37,0))=0,0,(IFERROR(J37/K37,0)-1)) -> 2.0206352 | O37: =O38+O39 -> 0 | P37: =P38+P39 -> 0 | Q37: =Q38+Q39 -> 0 | R37: =IF((IFERROR(O37/P37,0))=0,0,(IFERROR(O37/P37,0)-1)) -> 0 | S37: =IF((IFERROR(O37/Q37,0))=0,0,(IFERROR(O37/Q37,0)-1)) -> 0 | U37: 445095 | V37: =J37-U37 -> 823571.8 | W37: =(J37/U37)-1 -> 1.8503281
B38: 601-002-003-00 | C38: 0 | D38: 0 | E38: 0 | F38: =IF((IFERROR(C38/D38,0))=0,0,(IFERROR(C38/D38,0)-1)) -> 0 | G38: =IF((IFERROR(C38/E38,0))=0,0,(IFERROR(C38/E38,0)-1)) -> 0 | H38: Costo Venta Publicaciones | I38: 574300 | J38: =SUMIF('México Summary'!$C:$C,Resumen!B38,'México Summary'!$AC:$AC) -> 542341.8 | K38: 420000 | L38: =IF((IFERROR(J38/I38,0))=0,0,(IFERROR(J38/I38,0)-1)) -> -0.055647223 | M38: =IF((IFERROR(J38/K38,0))=0,0,(IFERROR(J38/K38,0)-1)) -> 0.29129 | O38: 0 | P38: 0 | Q38: 0 | R38: =IF((IFERROR(O38/P38,0))=0,0,(IFERROR(O38/P38,0)-1)) -> 0 | S38: =IF((IFERROR(O38/Q38,0))=0,0,(IFERROR(O38/Q38,0)-1)) -> 0
B39: 601-003-001-00 | C39: 0 | D39: 0 | E39: 0 | F39: =IF((IFERROR(C39/D39,0))=0,0,(IFERROR(C39/D39,0)-1)) -> 0 | G39: =IF((IFERROR(C39/E39,0))=0,0,(IFERROR(C39/E39,0)-1)) -> 0 | H39: Costo Digital Training | I39: 577000.27 | J39: =SUMIF('México Summary'!$C:$C,Resumen!B39,'México Summary'!$AC:$AC) -> 726325 | K39: 0 | L39: =IF((IFERROR(J39/I39,0))=0,0,(IFERROR(J39/I39,0)-1)) -> 0.2587949 | M39: =IF((IFERROR(J39/K39,0))=0,0,(IFERROR(J39/K39,0)-1)) -> 0 | O39: 0 | P39: 0 | Q39: 0 | R39: =IF((IFERROR(O39/P39,0))=0,0,(IFERROR(O39/P39,0)-1)) -> 0 | S39: =IF((IFERROR(O39/Q39,0))=0,0,(IFERROR(O39/Q39,0)-1)) -> 0
C40: =SUM(C41:C53) -> 0 | D40: =SUM(D41:D53) -> 0 | E40: =SUM(E41:E53) -> 0 | F40: =IF((IFERROR(C40/D40,0))=0,0,(IFERROR(C40/D40,0)-1)) -> 0 | G40: =IF((IFERROR(C40/E40,0))=0,0,(IFERROR(C40/E40,0)-1)) -> 0 | H40: Gastos Administrativos | I40: =SUM(I41:I53) -> 4160868.6 | J40: =SUM(J41:J53) -> 4705358 | K40: =SUM(K41:K53) -> 5070086.1 | L40: =IF((IFERROR(J40/I40,0))=0,0,(IFERROR(J40/I40,0)-1)) -> 0.13085955 | M40: =IF((IFERROR(J40/K40,0))=0,0,(IFERROR(J40/K40,0)-1)) -> -0.071937258 | O40: =SUM(O41:O53) -> 0 | P40: =SUM(P41:P53) -> 0 | Q40: =SUM(Q41:Q53) -> 0 | R40: =IF((IFERROR(O40/P40,0))=0,0,(IFERROR(O40/P40,0)-1)) -> 0 | S40: =IF((IFERROR(O40/Q40,0))=0,0,(IFERROR(O40/Q40,0)-1)) -> 0 | U40: 13319501 | V40: =J40-U40+J54 -> -107926.53 | W40: =(J40/U40)-1 -> -0.64673166
B41: 801-001-000-00 | C41: 0 | D41: 0 | E41: 0 | F41: =IF((IFERROR(C41/D41,0))=0,0,(IFERROR(C41/D41,0)-1)) -> 0 | G41: =IF((IFERROR(C41/E41,0))=0,0,(IFERROR(C41/E41,0)-1)) -> 0 | H41: Desarrollo de Negocios | I41: 448434.14 | J41: =SUMIF('México Summary'!$C:$C,Resumen!B41,'México Summary'!$AC:$AC) -> 656495.11 | K41: 579831.32 | L41: =IF((IFERROR(J41/I41,0))=0,0,(IFERROR(J41/I41,0)-1)) -> 0.46397219 | M41: =IF((IFERROR(J41/K41,0))=0,0,(IFERROR(J41/K41,0)-1)) -> 0.1322174 | O41: 0 | P41: 0 | Q41: 0 | R41: =IF((IFERROR(O41/P41,0))=0,0,(IFERROR(O41/P41,0)-1)) -> 0 | S41: =IF((IFERROR(O41/Q41,0))=0,0,(IFERROR(O41/Q41,0)-1)) -> 0
B42: 801-002-000-00 | C42: 0 | D42: 0 | E42: 0 | F42: =IF((IFERROR(C42/D42,0))=0,0,(IFERROR(C42/D42,0)-1)) -> 0 | G42: =IF((IFERROR(C42/E42,0))=0,0,(IFERROR(C42/E42,0)-1)) -> 0 | H42: Relaciones Externas | I42: 0 | J42: =SUMIF('México Summary'!$C:$C,Resumen!B42,'México Summary'!$AC:$AC) -> 0 | K42: 0 | L42: =IF((IFERROR(J42/I42,0))=0,0,(IFERROR(J42/I42,0)-1)) -> 0 | M42: =IF((IFERROR(J42/K42,0))=0,0,(IFERROR(J42/K42,0)-1)) -> 0 | O42: 0 | P42: 0 | Q42: 0 | R42: =IF((IFERROR(O42/P42,0))=0,0,(IFERROR(O42/P42,0)-1)) -> 0 | S42: =IF((IFERROR(O42/Q42,0))=0,0,(IFERROR(O42/Q42,0)-1)) -> 0
B43: 801-003-000-00 | C43: 0 | D43: 0 | E43: 0 | F43: =IF((IFERROR(C43/D43,0))=0,0,(IFERROR(C43/D43,0)-1)) -> 0 | G43: =IF((IFERROR(C43/E43,0))=0,0,(IFERROR(C43/E43,0)-1)) -> 0 | H43: Servicios a las membresia | I43: 0 | J43: =SUMIF('México Summary'!$C:$C,Resumen!B43,'México Summary'!$AC:$AC) -> 0 | K43: 0 | L43: =IF((IFERROR(J43/I43,0))=0,0,(IFERROR(J43/I43,0)-1)) -> 0 | M43: =IF((IFERROR(J43/K43,0))=0,0,(IFERROR(J43/K43,0)-1)) -> 0 | O43: 0 | P43: 0 | Q43: 0 | R43: =IF((IFERROR(O43/P43,0))=0,0,(IFERROR(O43/P43,0)-1)) -> 0 | S43: =IF((IFERROR(O43/Q43,0))=0,0,(IFERROR(O43/Q43,0)-1)) -> 0
B44: 801-004-000-00 | C44: 0 | D44: 0 | E44: 0 | F44: =IF((IFERROR(C44/D44,0))=0,0,(IFERROR(C44/D44,0)-1)) -> 0 | G44: =IF((IFERROR(C44/E44,0))=0,0,(IFERROR(C44/E44,0)-1)) -> 0 | H44: Vicepresidencia | I44: 705009.98 | J44: =SUMIF('México Summary'!$C:$C,Resumen!B44,'México Summary'!$AC:$AC) -> 924190.86 | K44: 1145597.2 | L44: =IF((IFERROR(J44/I44,0))=0,0,(IFERROR(J44/I44,0)-1)) -> 0.31089046 | M44: =IF((IFERROR(J44/K44,0))=0,0,(IFERROR(J44/K44,0)-1)) -> -0.19326718 | O44: 0 | P44: 0 | Q44: 0 | R44: =IF((IFERROR(O44/P44,0))=0,0,(IFERROR(O44/P44,0)-1)) -> 0 | S44: =IF((IFERROR(O44/Q44,0))=0,0,(IFERROR(O44/Q44,0)-1)) -> 0
B45: 801-005-000-00 | C45: 0 | D45: 0 | E45: 0 | F45: =IF((IFERROR(C45/D45,0))=0,0,(IFERROR(C45/D45,0)-1)) -> 0 | G45: =IF((IFERROR(C45/E45,0))=0,0,(IFERROR(C45/E45,0)-1)) -> 0 | H45: Finanzas | I45: 351191.16 | J45: =SUMIF('México Summary'!$C:$C,Resumen!B45,'México Summary'!$AC:$AC) -> 467017.59 | K45: 747879.2 | L45: =IF((IFERROR(J45/I45,0))=0,0,(IFERROR(J45/I45,0)-1)) -> 0.32981021 | M45: =IF((IFERROR(J45/K45,0))=0,0,(IFERROR(J45/K45,0)-1)) -> -0.37554408 | O45: 0 | P45: 0 | Q45: 0 | R45: =IF((IFERROR(O45/P45,0))=0,0,(IFERROR(O45/P45,0)-1)) -> 0 | S45: =IF((IFERROR(O45/Q45,0))=0,0,(IFERROR(O45/Q45,0)-1)) -> 0
B46: 801-006-000-00 | C46: 0 | D46: 0 | E46: 0 | F46: =IF((IFERROR(C46/D46,0))=0,0,(IFERROR(C46/D46,0)-1)) -> 0 | G46: =IF((IFERROR(C46/E46,0))=0,0,(IFERROR(C46/E46,0)-1)) -> 0 | H46: Administración | I46: 150603.26 | J46: =SUMIF('México Summary'!$C:$C,Resumen!B46,'México Summary'!$AC:$AC) -> 395072.91 | K46: 158700 | L46: =IF((IFERROR(J46/I46,0))=0,0,(IFERROR(J46/I46,0)-1)) -> 1.6232693 | M46: =IF((IFERROR(J46/K46,0))=0,0,(IFERROR(J46/K46,0)-1)) -> 1.4894323 | O46: 0 | P46: 0 | Q46: 0 | R46: =IF((IFERROR(O46/P46,0))=0,0,(IFERROR(O46/P46,0)-1)) -> 0 | S46: =IF((IFERROR(O46/Q46,0))=0,0,(IFERROR(O46/Q46,0)-1)) -> 0
B47: 801-007-000-00 | C47: 0 | D47: 0 | E47: 0 | F47: =IF((IFERROR(C47/D47,0))=0,0,(IFERROR(C47/D47,0)-1)) -> 0 | G47: =IF((IFERROR(C47/E47,0))=0,0,(IFERROR(C47/E47,0)-1)) -> 0 | H47: Sistemas | I47: 0 | J47: =SUMIF('México Summary'!$C:$C,Resumen!B47,'México Summary'!$AC:$AC) -> 0 | K47: 0 | L47: =IF((IFERROR(J47/I47,0))=0,0,(IFERROR(J47/I47,0)-1)) -> 0 | M47: =IF((IFERROR(J47/K47,0))=0,0,(IFERROR(J47/K47,0)-1)) -> 0 | O47: 0 | P47: 0 | Q47: 0 | R47: =IF((IFERROR(O47/P47,0))=0,0,(IFERROR(O47/P47,0)-1)) -> 0 | S47: =IF((IFERROR(O47/Q47,0))=0,0,(IFERROR(O47/Q47,0)-1)) -> 0
B48: 801-008-000-00 | C48: 0 | D48: 0 | E48: 0 | F48: =IF((IFERROR(C48/D48,0))=0,0,(IFERROR(C48/D48,0)-1)) -> 0 | G48: =IF((IFERROR(C48/E48,0))=0,0,(IFERROR(C48/E48,0)-1)) -> 0 | H48: Empleos | I48: 0 | J48: =SUMIF('México Summary'!$C:$C,Resumen!B48,'México Summary'!$AC:$AC) -> 0 | K48: 0 | L48: =IF((IFERROR(J48/I48,0))=0,0,(IFERROR(J48/I48,0)-1)) -> 0 | M48: =IF((IFERROR(J48/K48,0))=0,0,(IFERROR(J48/K48,0)-1)) -> 0 | O48: 0 | P48: 0 | Q48: 0 | R48: =IF((IFERROR(O48/P48,0))=0,0,(IFERROR(O48/P48,0)-1)) -> 0 | S48: =IF((IFERROR(O48/Q48,0))=0,0,(IFERROR(O48/Q48,0)-1)) -> 0
B49: 801-009-000-00 | C49: 0 | D49: 0 | E49: 0 | F49: =IF((IFERROR(C49/D49,0))=0,0,(IFERROR(C49/D49,0)-1)) -> 0 | G49: =IF((IFERROR(C49/E49,0))=0,0,(IFERROR(C49/E49,0)-1)) -> 0 | H49: Servicios Generales (Almacén) | I49: 0 | J49: =SUMIF('México Summary'!$C:$C,Resumen!B49,'México Summary'!$AC:$AC) -> 0 | K49: 0 | L49: =IF((IFERROR(J49/I49,0))=0,0,(IFERROR(J49/I49,0)-1)) -> 0 | M49: =IF((IFERROR(J49/K49,0))=0,0,(IFERROR(J49/K49,0)-1)) -> 0 | O49: 0 | P49: 0 | Q49: 0 | R49: =IF((IFERROR(O49/P49,0))=0,0,(IFERROR(O49/P49,0)-1)) -> 0 | S49: =IF((IFERROR(O49/Q49,0))=0,0,(IFERROR(O49/Q49,0)-1)) -> 0
B50: 801-010-000-00 | C50: 0 | D50: 0 | E50: 0 | F50: =IF((IFERROR(C50/D50,0))=0,0,(IFERROR(C50/D50,0)-1)) -> 0 | G50: =IF((IFERROR(C50/E50,0))=0,0,(IFERROR(C50/E50,0)-1)) -> 0 | H50: Eventos | I50: 404903.39 | J50: =SUMIF('México Summary'!$C:$C,Resumen!B50,'México Summary'!$AC:$AC) -> 625945.18 | K50: 452700 | L50: =IF((IFERROR(J50/I50,0))=0,0,(IFERROR(J50/I50,0)-1)) -> 0.54591242 | M50: =IF((IFERROR(J50/K50,0))=0,0,(IFERROR(J50/K50,0)-1)) -> 0.38269313 | O50: 0 | P50: 0 | Q50: 0 | R50: =IF((IFERROR(O50/P50,0))=0,0,(IFERROR(O50/P50,0)-1)) -> 0 | S50: =IF((IFERROR(O50/Q50,0))=0,0,(IFERROR(O50/Q50,0)-1)) -> 0
B51: 801-011-000-00 | C51: 0 | D51: 0 | E51: 0 | F51: =IF((IFERROR(C51/D51,0))=0,0,(IFERROR(C51/D51,0)-1)) -> 0 | G51: =IF((IFERROR(C51/E51,0))=0,0,(IFERROR(C51/E51,0)-1)) -> 0 | H51: Comites | I51: 618233.64 | J51: =SUMIF('México Summary'!$C:$C,Resumen!B51,'México Summary'!$AC:$AC) -> 781454.96 | K51: 493958.4 | L51: =IF((IFERROR(J51/I51,0))=0,0,(IFERROR(J51/I51,0)-1)) -> 0.26401235 | M51: =IF((IFERROR(J51/K51,0))=0,0,(IFERROR(J51/K51,0)-1)) -> 0.58202585 | O51: 0 | P51: 0 | Q51: 0 | R51: =IF((IFERROR(O51/P51,0))=0,0,(IFERROR(O51/P51,0)-1)) -> 0 | S51: =IF((IFERROR(O51/Q51,0))=0,0,(IFERROR(O51/Q51,0)-1)) -> 0
B52: 801-012-000-00 | C52: 0 | D52: 0 | E52: 0 | F52: =IF((IFERROR(C52/D52,0))=0,0,(IFERROR(C52/D52,0)-1)) -> 0 | G52: =IF((IFERROR(C52/E52,0))=0,0,(IFERROR(C52/E52,0)-1)) -> 0 | H52: Renta de Salas | I52: 0 | J52: =SUMIF('México Summary'!$C:$C,Resumen!B52,'México Summary'!$AC:$AC) -> 0 | K52: 0 | L52: =IF((IFERROR(J52/I52,0))=0,0,(IFERROR(J52/I52,0)-1)) -> 0 | M52: =IF((IFERROR(J52/K52,0))=0,0,(IFERROR(J52/K52,0)-1)) -> 0 | O52: 0 | P52: 0 | Q52: 0 | R52: =IF((IFERROR(O52/P52,0))=0,0,(IFERROR(O52/P52,0)-1)) -> 0 | S52: =IF((IFERROR(O52/Q52,0))=0,0,(IFERROR(O52/Q52,0)-1)) -> 0
B53: 801-013-000-00 | C53: 0 | D53: 0 | E53: 0 | F53: =IF((IFERROR(C53/D53,0))=0,0,(IFERROR(C53/D53,0)-1)) -> 0 | G53: =IF((IFERROR(C53/E53,0))=0,0,(IFERROR(C53/E53,0)-1)) -> 0 | H53: Comunicación | I53: 1482493.1 | J53: =SUMIF('México Summary'!$C:$C,Resumen!B53,'México Summary'!$AC:$AC) -> 855181.42 | K53: 1491420 | L53: =IF((IFERROR(J53/I53,0))=0,0,(IFERROR(J53/I53,0)-1)) -> -0.42314643 | M53: =IF((IFERROR(J53/K53,0))=0,0,(IFERROR(J53/K53,0)-1)) -> -0.4265992 | O53: 0 | P53: 0 | Q53: 0 | R53: =IF((IFERROR(O53/P53,0))=0,0,(IFERROR(O53/P53,0)-1)) -> 0 | S53: =IF((IFERROR(O53/Q53,0))=0,0,(IFERROR(O53/Q53,0)-1)) -> 0
B54: 901-000-000-00 | C54: 0 | D54: 0 | E54: 0 | F54: =IF((IFERROR(C54/D54,0))=0,0,(IFERROR(C54/D54,0)-1)) -> 0 | G54: =IF((IFERROR(C54/E54,0))=0,0,(IFERROR(C54/E54,0)-1)) -> 0 | H54: Gastos Generales | I54: 7935477.4 | J54: =SUMIF('México Summary'!$C:$C,Resumen!B54,'México Summary'!$AC:$AC) -> 8506216.4 | K54: 8413203.5 | L54: =IF((IFERROR(J54/I54,0))=0,0,(IFERROR(J54/I54,0)-1)) -> 0.071922446 | M54: =IF((IFERROR(J54/K54,0))=0,0,(IFERROR(J54/K54,0)-1)) -> 0.011055585 | O54: 0 | P54: 0 | Q54: 0 | R54: =IF((IFERROR(O54/P54,0))=0,0,(IFERROR(O54/P54,0)-1)) -> 0 | S54: =IF((IFERROR(O54/Q54,0))=0,0,(IFERROR(O54/Q54,0)-1)) -> 0 | W54: =(J54/U54)-1 -> #DIV/0!
C55: =SUM(C56:C62) -> 0 | D55: =SUM(D56:D62) -> 0 | E55: =SUM(E56:E62) -> 0 | F55: =IF((IFERROR(C55/D55,0))=0,0,(IFERROR(C55/D55,0)-1)) -> 0 | G55: =IF((IFERROR(C55/E55,0))=0,0,(IFERROR(C55/E55,0)-1)) -> 0 | H55: Nómina | I55: =SUM(I56:I62) -> 17959246 | J55: =SUM(J56:J62) -> 18493809 | K55: =SUM(K56:K62) -> 13119015 | L55: =IF((IFERROR(J55/I55,0))=0,0,(IFERROR(J55/I55,0)-1)) -> 0.029765345 | M55: =IF((IFERROR(J55/K55,0))=0,0,(IFERROR(J55/K55,0)-1)) -> 0.40969495 | O55: =SUM(O56:O62) -> 0 | P55: =SUM(P56:P62) -> 0 | Q55: =SUM(Q56:Q62) -> 0 | R55: =IF((IFERROR(O55/P55,0))=0,0,(IFERROR(O55/P55,0)-1)) -> 0 | S55: =IF((IFERROR(O55/Q55,0))=0,0,(IFERROR(O55/Q55,0)-1)) -> 0 | U55: 21149050 | V55: =J55-U55 -> -2655241.2 | W55: =(J55/U55)-1 -> -0.12554896 | AA55: 2026
B56: 513-000-000-00 | C56: 0 | D56: 0 | E56: 0 | F56: =IF((IFERROR(C56/D56,0))=0,0,(IFERROR(C56/D56,0)-1)) -> 0 | G56: =IF((IFERROR(C56/E56,0))=0,0,(IFERROR(C56/E56,0)-1)) -> 0 | H56: Nomina Vicepresidencia | I56: 601991.89 | J56: =SUMIF('México Summary'!$C:$C,Resumen!B56,'México Summary'!$AC:$AC) -> 542438.28 | K56: 334036.73 | L56: =IF((IFERROR(J56/I56,0))=0,0,(IFERROR(J56/I56,0)-1)) -> -0.098927595 | M56: =IF((IFERROR(J56/K56,0))=0,0,(IFERROR(J56/K56,0)-1)) -> 0.62388814 | O56: 0 | P56: 0 | Q56: 0 | R56: =IF((IFERROR(O56/P56,0))=0,0,(IFERROR(O56/P56,0)-1)) -> 0 | S56: =IF((IFERROR(O56/Q56,0))=0,0,(IFERROR(O56/Q56,0)-1)) -> 0
B57: 517-000-000-00 | C57: 0 | D57: 0 | E57: 0 | F57: =IF((IFERROR(C57/D57,0))=0,0,(IFERROR(C57/D57,0)-1)) -> 0 | G57: =IF((IFERROR(C57/E57,0))=0,0,(IFERROR(C57/E57,0)-1)) -> 0 | H57: Nomina Desarrollo de Negocios | I57: 4517285.5 | J57: =SUMIF('México Summary'!$C:$C,Resumen!B57,'México Summary'!$AC:$AC) -> 4883189.3 | K57: 3385754.8 | L57: =IF((IFERROR(J57/I57,0))=0,0,(IFERROR(J57/I57,0)-1)) -> 0.081000797 | M57: =IF((IFERROR(J57/K57,0))=0,0,(IFERROR(J57/K57,0)-1)) -> 0.44227492 | O57: 0 | P57: 0 | Q57: 0 | R57: =IF((IFERROR(O57/P57,0))=0,0,(IFERROR(O57/P57,0)-1)) -> 0 | S57: =IF((IFERROR(O57/Q57,0))=0,0,(IFERROR(O57/Q57,0)-1)) -> 0
B58: 516-000-000-00 | C58: 0 | D58: 0 | E58: 0 | F58: =IF((IFERROR(C58/D58,0))=0,0,(IFERROR(C58/D58,0)-1)) -> 0 | G58: =IF((IFERROR(C58/E58,0))=0,0,(IFERROR(C58/E58,0)-1)) -> 0 | H58: Nomina Comites y Relaciones Externas | I58: 5327063.1 | J58: =SUMIF('México Summary'!$C:$C,Resumen!B58,'México Summary'!$AC:$AC) -> 5213492.5 | K58: 4088183.5 | L58: =IF((IFERROR(J58/I58,0))=0,0,(IFERROR(J58/I58,0)-1)) -> -0.02131955 | M58: =IF((IFERROR(J58/K58,0))=0,0,(IFERROR(J58/K58,0)-1)) -> 0.27525892 | O58: 0 | P58: 0 | Q58: 0 | R58: =IF((IFERROR(O58/P58,0))=0,0,(IFERROR(O58/P58,0)-1)) -> 0 | S58: =IF((IFERROR(O58/Q58,0))=0,0,(IFERROR(O58/Q58,0)-1)) -> 0
B59: 519-000-000-00 | C59: 0 | D59: 0 | E59: 0 | F59: =IF((IFERROR(C59/D59,0))=0,0,(IFERROR(C59/D59,0)-1)) -> 0 | G59: =IF((IFERROR(C59/E59,0))=0,0,(IFERROR(C59/E59,0)-1)) -> 0 | H59: Nomina Comunicación | I59: 1285252.2 | J59: =SUMIF('México Summary'!$C:$C,Resumen!B59,'México Summary'!$AC:$AC) -> 1448842.1 | K59: 876475.57 | L59: =IF((IFERROR(J59/I59,0))=0,0,(IFERROR(J59/I59,0)-1)) -> 0.12728233 | M59: =IF((IFERROR(J59/K59,0))=0,0,(IFERROR(J59/K59,0)-1)) -> 0.6530319 | O59: 0 | P59: 0 | Q59: 0 | R59: =IF((IFERROR(O59/P59,0))=0,0,(IFERROR(O59/P59,0)-1)) -> 0 | S59: =IF((IFERROR(O59/Q59,0))=0,0,(IFERROR(O59/Q59,0)-1)) -> 0
B60: 515-000-000-00 | C60: 0 | D60: 0 | E60: 0 | F60: =IF((IFERROR(C60/D60,0))=0,0,(IFERROR(C60/D60,0)-1)) -> 0 | G60: =IF((IFERROR(C60/E60,0))=0,0,(IFERROR(C60/E60,0)-1)) -> 0 | H60: Nomina Servicios a la Membresia | I60: 1798050.7 | J60: =SUMIF('México Summary'!$C:$C,Resumen!B60,'México Summary'!$AC:$AC) -> 1925404.1 | K60: 1506952.1 | L60: =IF((IFERROR(J60/I60,0))=0,0,(IFERROR(J60/I60,0)-1)) -> 0.070828575 | M60: =IF((IFERROR(J60/K60,0))=0,0,(IFERROR(J60/K60,0)-1)) -> 0.27768101 | O60: 0 | P60: 0 | Q60: 0 | R60: =IF((IFERROR(O60/P60,0))=0,0,(IFERROR(O60/P60,0)-1)) -> 0 | S60: =IF((IFERROR(O60/Q60,0))=0,0,(IFERROR(O60/Q60,0)-1)) -> 0
B61: 518-000-000-00 | C61: 0 | D61: 0 | E61: 0 | F61: =IF((IFERROR(C61/D61,0))=0,0,(IFERROR(C61/D61,0)-1)) -> 0 | G61: =IF((IFERROR(C61/E61,0))=0,0,(IFERROR(C61/E61,0)-1)) -> 0 | H61: Nomina Eventos y Mercadotecnia | I61: 876357.8 | J61: =SUMIF('México Summary'!$C:$C,Resumen!B61,'México Summary'!$AC:$AC) -> 566664.36 | K61: 672955.21 | L61: =IF((IFERROR(J61/I61,0))=0,0,(IFERROR(J61/I61,0)-1)) -> -0.35338698 | M61: =IF((IFERROR(J61/K61,0))=0,0,(IFERROR(J61/K61,0)-1)) -> -0.1579464 | O61: 0 | P61: 0 | Q61: 0 | R61: =IF((IFERROR(O61/P61,0))=0,0,(IFERROR(O61/P61,0)-1)) -> 0 | S61: =IF((IFERROR(O61/Q61,0))=0,0,(IFERROR(O61/Q61,0)-1)) -> 0
B62: 514-000-000-00 | C62: 0 | D62: 0 | E62: 0 | F62: =IF((IFERROR(C62/D62,0))=0,0,(IFERROR(C62/D62,0)-1)) -> 0 | G62: =IF((IFERROR(C62/E62,0))=0,0,(IFERROR(C62/E62,0)-1)) -> 0 | H62: Nomina Administración y Fiananzas | I62: 3553244.7 | J62: =SUMIF('México Summary'!$C:$C,Resumen!B62,'México Summary'!$AC:$AC) -> 3913778.5 | K62: 2254657 | L62: =IF((IFERROR(J62/I62,0))=0,0,(IFERROR(J62/I62,0)-1)) -> 0.10146608 | M62: =IF((IFERROR(J62/K62,0))=0,0,(IFERROR(J62/K62,0)-1)) -> 0.73586425 | O62: 0 | P62: 0 | Q62: 0 | R62: =IF((IFERROR(O62/P62,0))=0,0,(IFERROR(O62/P62,0)-1)) -> 0 | S62: =IF((IFERROR(O62/Q62,0))=0,0,(IFERROR(O62/Q62,0)-1)) -> 0
B63: 903-000-000-00 | C63: 0 | D63: 0 | E63: 0 | F63: =IF((IFERROR(C63/D63,0))=0,0,(IFERROR(C63/D63,0)-1)) -> 0 | G63: =IF((IFERROR(C63/E63,0))=0,0,(IFERROR(C63/E63,0)-1)) -> 0 | H63: Gastos Corporativos | I63: 15027712 | J63: =SUMIF('México Summary'!$C:$C,Resumen!B63,'México Summary'!$AC:$AC) -> 19189320 | K63: 14307080 | L63: =IF((IFERROR(J63/I63,0))=0,0,(IFERROR(J63/I63,0)-1)) -> 0.27692888 | M63: =IF((IFERROR(J63/K63,0))=0,0,(IFERROR(J63/K63,0)-1)) -> 0.34124637 | O63: 0 | P63: 0 | Q63: 0 | R63: =IF((IFERROR(O63/P63,0))=0,0,(IFERROR(O63/P63,0)-1)) -> 0 | S63: =IF((IFERROR(O63/Q63,0))=0,0,(IFERROR(O63/Q63,0)-1)) -> 0 | U63: 17451769 | V63: =J63-U63 -> 1737550.2 | W63: =(J63/U63)-1 -> 0.099562984 | Y63: MX | Z63: Gdl | AA63: NE | AB63: NO
B64: 950-001-000-00 | C64: 0 | D64: 0 | E64: 0 | F64: =IF((IFERROR(C64/D64,0))=0,0,(IFERROR(C64/D64,0)-1)) -> 0 | G64: =IF((IFERROR(C64/E64,0))=0,0,(IFERROR(C64/E64,0)-1)) -> 0 | H64: Guadalajara Expense | I64: 14658996 | J64: =SUMIF('México Summary'!$C:$C,Resumen!B64,'México Summary'!$AC:$AC) -> 0 | K64: 0 | L64: =IF((IFERROR(J64/I64,0))=0,0,(IFERROR(J64/I64,0)-1)) -> 0 | M64: =IF((IFERROR(J64/K64,0))=0,0,(IFERROR(J64/K64,0)-1)) -> 0 | O64: 0 | P64: 0 | Q64: 0 | R64: =IF((IFERROR(O64/P64,0))=0,0,(IFERROR(O64/P64,0)-1)) -> 0 | S64: =IF((IFERROR(O64/Q64,0))=0,0,(IFERROR(O64/Q64,0)-1)) -> 0
B65: 950-002-000-00 | C65: 0 | D65: 0 | E65: 0 | F65: =IF((IFERROR(C65/D65,0))=0,0,(IFERROR(C65/D65,0)-1)) -> 0 | G65: =IF((IFERROR(C65/E65,0))=0,0,(IFERROR(C65/E65,0)-1)) -> 0 | H65: Monterrey Expense | I65: 32320734 | J65: =SUMIF('México Summary'!$C:$C,Resumen!B65,'México Summary'!$AC:$AC) -> 0 | K65: 0 | L65: =IF((IFERROR(J65/I65,0))=0,0,(IFERROR(J65/I65,0)-1)) -> 0 | M65: =IF((IFERROR(J65/K65,0))=0,0,(IFERROR(J65/K65,0)-1)) -> 0 | O65: 0 | P65: 0 | Q65: 0 | R65: =IF((IFERROR(O65/P65,0))=0,0,(IFERROR(O65/P65,0)-1)) -> 0 | S65: =IF((IFERROR(O65/Q65,0))=0,0,(IFERROR(O65/Q65,0)-1)) -> 0
B66: 950-003-000-00 | C66: 0 | D66: 0 | E66: 0 | F66: =IF((IFERROR(C66/D66,0))=0,0,(IFERROR(C66/D66,0)-1)) -> 0 | G66: =IF((IFERROR(C66/E66,0))=0,0,(IFERROR(C66/E66,0)-1)) -> 0 | H66: Northwest Expense | I66: 4574611.7 | J66: =SUMIF('México Summary'!$C:$C,Resumen!B66,'México Summary'!$AC:$AC) -> 0 | K66: 0 | L66: =IF((IFERROR(J66/I66,0))=0,0,(IFERROR(J66/I66,0)-1)) -> 0 | M66: =IF((IFERROR(J66/K66,0))=0,0,(IFERROR(J66/K66,0)-1)) -> 0 | O66: 0 | P66: 0 | Q66: 0 | R66: =IF((IFERROR(O66/P66,0))=0,0,(IFERROR(O66/P66,0)-1)) -> 0 | S66: =IF((IFERROR(O66/Q66,0))=0,0,(IFERROR(O66/Q66,0)-1)) -> 0
C67: =C66+C65+C64+C25 -> 0 | D67: =D66+D65+D64+D25 -> 0 | E67: =E66+E65+E64+E25 -> 0 | F67: =IF((IFERROR(C67/D67,0))=0,0,(IFERROR(C67/D67,0)-1)) -> 0 | G67: =IF((IFERROR(C67/E67,0))=0,0,(IFERROR(C67/E67,0)-1)) -> 0 | H67: CONSOLIDATED EXPENSES | I67: =I66+I65+I64+I25 -> 1.1280163e+08 | J67: =J66+J65+J64+J25 -> 69120006 | K67: =K66+K65+K64+K25 -> 61625391 | L67: =IF((IFERROR(J67/I67,0))=0,0,(IFERROR(J67/I67,0)-1)) -> -0.38724283 | M67: =IF((IFERROR(J67/K67,0))=0,0,(IFERROR(J67/K67,0)-1)) -> 0.12161569 | O67: =O66+O65+O64+O25 -> 0 | P67: =P66+P65+P64+P25 -> 0 | Q67: =Q66+Q65+Q64+Q25 -> 0 | R67: =IF((IFERROR(O67/P67,0))=0,0,(IFERROR(O67/P67,0)-1)) -> 0 | S67: =IF((IFERROR(O67/Q67,0))=0,0,(IFERROR(O67/Q67,0)-1)) -> 0
C69: =C5-C25 -> 0 | D69: =D5-D25 -> 0 | E69: =E5-E25 -> 0 | F69: =IF((IFERROR(C69/D69,0))=0,0,(IFERROR(C69/D69,0)-1)) -> 0 | G69: =IF((IFERROR(C69/E69,0))=0,0,(IFERROR(C69/E69,0)-1)) -> 0 | H69: OPERATING RESULTS MEXICO | I69: =I5-I25 -> 3372228.3 | J69: =J5-J25 -> 2563969.8 | K69: =K5-K25 -> 904390.62 | L69: =IF((IFERROR(J69/I69,0))=0,0,(IFERROR(J69/I69,0)-1)) -> -0.23968085 | M69: =IF((IFERROR(J69/K69,0))=0,0,(IFERROR(J69/K69,0)-1)) -> 1.8350247 | O69: =O5-O25 -> 0 | P69: =P5-P25 -> 0 | Q69: =Q5-Q25 -> 0 | R69: =IF((IFERROR(O69/P69,0))=0,0,(IFERROR(O69/P69,0)-1)) -> 0 | S69: =IF((IFERROR(O69/Q69,0))=0,0,(IFERROR(O69/Q69,0)-1)) -> 0 | U69: =U5-U25 -> 2110095 | V69: =V5-V25 -> 453874.75 | W69: =(J69/U69)-1 -> 0.21509683 | Y69: =J69 -> 2563969.8 | Z69: 574806.45 | AA69: 566088.74 | AB69: 1247378.9 | AC69: =SUM(Y69:AB69) -> 4952243.8
C70: =C21-C64 -> 0 | D70: =D21-D64 -> 0 | E70: =E21-E64 -> 0 | F70: =IF((IFERROR(C70/D70,0))=0,0,(IFERROR(C70/D70,0)-1)) -> 0 | G70: =IF((IFERROR(C70/E70,0))=0,0,(IFERROR(C70/E70,0)-1)) -> 0 | H70: OPERATING RESULTS GUADALAJARA | I70: =I21-I64 -> -462807.79 | J70: =J21-J64 -> 0 | K70: =K21-K64 -> 0 | L70: =IF((IFERROR(J70/I70,0))=0,0,(IFERROR(J70/I70,0)-1)) -> 0 | M70: =IF((IFERROR(J70/K70,0))=0,0,(IFERROR(J70/K70,0)-1)) -> 0 | O70: =O21-O64 -> 0 | P70: =P21-P64 -> 0 | Q70: =Q21-Q64 -> 0 | R70: =IF((IFERROR(O70/P70,0))=0,0,(IFERROR(O70/P70,0)-1)) -> 0 | S70: =IF((IFERROR(O70/Q70,0))=0,0,(IFERROR(O70/Q70,0)-1)) -> 0
C71: =C22-C65 -> 0 | D71: =D22-D65 -> 0 | E71: =E22-E65 -> 0 | F71: =IF((IFERROR(C71/D71,0))=0,0,(IFERROR(C71/D71,0)-1)) -> 0 | G71: =IF((IFERROR(C71/E71,0))=0,0,(IFERROR(C71/E71,0)-1)) -> 0 | H71: OPERATING RESULTS MONTERREY | I71: =I22-I65 -> 574240.16 | J71: =J22-J65 -> 0 | K71: =K22-K65 -> 0 | L71: =IF((IFERROR(J71/I71,0))=0,0,(IFERROR(J71/I71,0)-1)) -> 0 | M71: =IF((IFERROR(J71/K71,0))=0,0,(IFERROR(J71/K71,0)-1)) -> 0 | O71: =O22-O65 -> 0 | P71: =P22-P65 -> 0 | Q71: =Q22-Q65 -> 0 | R71: =IF((IFERROR(O71/P71,0))=0,0,(IFERROR(O71/P71,0)-1)) -> 0 | S71: =IF((IFERROR(O71/Q71,0))=0,0,(IFERROR(O71/Q71,0)-1)) -> 0
C72: =C23-C66 -> 0 | D72: =D23-D66 -> 0 | E72: =E23-E66 -> 0 | F72: =IF((IFERROR(C72/D72,0))=0,0,(IFERROR(C72/D72,0)-1)) -> 0 | G72: =IF((IFERROR(C72/E72,0))=0,0,(IFERROR(C72/E72,0)-1)) -> 0 | H72: OPERATING RESULTS NORTHWEST | I72: =I23-I66 -> 541748.02 | J72: =J23-J66 -> 0 | K72: =K23-K66 -> 0 | L72: =IF((IFERROR(J72/I72,0))=0,0,(IFERROR(J72/I72,0)-1)) -> 0 | M72: =IF((IFERROR(J72/K72,0))=0,0,(IFERROR(J72/K72,0)-1)) -> 0 | O72: =O23-O66 -> 0 | P72: =P23-P66 -> 0 | Q72: =Q23-Q66 -> 0 | R72: =IF((IFERROR(O72/P72,0))=0,0,(IFERROR(O72/P72,0)-1)) -> 0 | S72: =IF((IFERROR(O72/Q72,0))=0,0,(IFERROR(O72/Q72,0)-1)) -> 0
C74: =SUM(C69:C73) -> 0 | D74: =SUM(D69:D73) -> 0 | E74: =SUM(E69:E73) -> 0 | F74: =IF((IFERROR(C74/D74,0))=0,0,(IFERROR(C74/D74,0)-1)) -> 0 | G74: =IF((IFERROR(C74/E74,0))=0,0,(IFERROR(C74/E74,0)-1)) -> 0 | H74: CONSOLIDATED OPERATING RESULTS | I74: =SUM(I69:I73) -> 4025408.7 | J74: =SUM(J69:J73) -> 2563969.8 | K74: =SUM(K69:K73) -> 904390.62 | L74: =IF((IFERROR(J74/I74,0))=0,0,(IFERROR(J74/I74,0)-1)) -> -0.36305356 | M74: =IF((IFERROR(J74/K74,0))=0,0,(IFERROR(J74/K74,0)-1)) -> 1.8350247 | O74: =SUM(O69:O73) -> 0 | P74: =SUM(P69:P73) -> 0 | Q74: =SUM(Q69:Q73) -> 0 | R74: =IF((IFERROR(O74/P74,0))=0,0,(IFERROR(O74/P74,0)-1)) -> 0 | S74: =IF((IFERROR(O74/Q74,0))=0,0,(IFERROR(O74/Q74,0)-1)) -> 0
B76: 902-000-000-00 | C76: 0 | D76: 0 | E76: 0 | F76: =IF((IFERROR(C76/D76,0))=0,0,(IFERROR(C76/D76,0)-1)) -> 0 | G76: =IF((IFERROR(C76/E76,0))=0,0,(IFERROR(C76/E76,0)-1)) -> 0 | H76: Member Centricity | I76: 0 | J76: =SUMIF('México Summary'!$C:$C,Resumen!B76,'México Summary'!$AC:$AC) -> 0 | K76: 0 | L76: =IF((IFERROR(J76/I76,0))=0,0,(IFERROR(J76/I76,0)-1)) -> 0 | M76: =IF((IFERROR(J76/K76,0))=0,0,(IFERROR(J76/K76,0)-1)) -> 0 | O76: 0 | P76: 0 | Q76: 0 | R76: =IF((IFERROR(O76/P76,0))=0,0,(IFERROR(O76/P76,0)-1)) -> 0 | S76: =IF((IFERROR(O76/Q76,0))=0,0,(IFERROR(O76/Q76,0)-1)) -> 0 | U76: 0 | V76: =J76-U76 -> 0 | W76: =(J76/U76)-1 -> #DIV/0!
C78: =SUM(C79:C82) -> 0 | D78: =SUM(D79:D82) -> 0 | E78: =SUM(E79:E82) -> 0 | F78: =IF((IFERROR(C78/D78,0))=0,0,(IFERROR(C78/D78,0)-1)) -> 0 | G78: =IF((IFERROR(C78/E78,0))=0,0,(IFERROR(C78/E78,0)-1)) -> 0 | H78: Other | I78: =SUM(I79:I82) -> 6005514 | J78: =SUM(J79:J82) -> 0 | K78: =SUM(K79:K82) -> 0 | L78: =IF((IFERROR(J78/I78,0))=0,0,(IFERROR(J78/I78,0)-1)) -> 0 | M78: =IF((IFERROR(J78/K78,0))=0,0,(IFERROR(J78/K78,0)-1)) -> 0 | O78: =SUM(O79:O82) -> 0 | P78: =SUM(P79:P82) -> 0 | Q78: =SUM(Q79:Q82) -> 0 | R78: =IF((IFERROR(O78/P78,0))=0,0,(IFERROR(O78/P78,0)-1)) -> 0 | S78: =IF((IFERROR(O78/Q78,0))=0,0,(IFERROR(O78/Q78,0)-1)) -> 0 | U78: 0 | V78: =J78-U78 -> 0 | W78: =(J78/U78)-1 -> #DIV/0!
B79: 413-000-000-00 | C79: 0 | D79: 0 | E79: 0 | F79: =IF((IFERROR(C79/D79,0))=0,0,(IFERROR(C79/D79,0)-1)) -> 0 | G79: =IF((IFERROR(C79/E79,0))=0,0,(IFERROR(C79/E79,0)-1)) -> 0 | H79: Otros Ingresos | I79: 53815.53 | J79: =SUMIF('México Summary'!$C:$C,Resumen!B79,'México Summary'!$AC:$AC) -> 0 | K79: 0 | L79: =IF((IFERROR(J79/I79,0))=0,0,(IFERROR(J79/I79,0)-1)) -> 0 | M79: =IF((IFERROR(J79/K79,0))=0,0,(IFERROR(J79/K79,0)-1)) -> 0 | O79: 0 | P79: 0 | Q79: 0 | R79: =IF((IFERROR(O79/P79,0))=0,0,(IFERROR(O79/P79,0)-1)) -> 0 | S79: =IF((IFERROR(O79/Q79,0))=0,0,(IFERROR(O79/Q79,0)-1)) -> 0
B80: 414-000-000-00 | C80: 0 | D80: 0 | E80: 0 | F80: =IF((IFERROR(C80/D80,0))=0,0,(IFERROR(C80/D80,0)-1)) -> 0 | G80: =IF((IFERROR(C80/E80,0))=0,0,(IFERROR(C80/E80,0)-1)) -> 0 | H80: Intereses Bancos | I80: 7263697.4 | J80: =SUMIF('México Summary'!$C:$C,Resumen!B80,'México Summary'!$AC:$AC) -> 0 | K80: 0 | L80: =IF((IFERROR(J80/I80,0))=0,0,(IFERROR(J80/I80,0)-1)) -> 0 | M80: =IF((IFERROR(J80/K80,0))=0,0,(IFERROR(J80/K80,0)-1)) -> 0 | O80: 0 | P80: 0 | Q80: 0 | R80: =IF((IFERROR(O80/P80,0))=0,0,(IFERROR(O80/P80,0)-1)) -> 0 | S80: =IF((IFERROR(O80/Q80,0))=0,0,(IFERROR(O80/Q80,0)-1)) -> 0
B81: 416-000-000-00 | C81: 0 | D81: 0 | E81: 0 | F81: =IF((IFERROR(C81/D81,0))=0,0,(IFERROR(C81/D81,0)-1)) -> 0 | G81: =IF((IFERROR(C81/E81,0))=0,0,(IFERROR(C81/E81,0)-1)) -> 0 | H81: Utilidad Cambiaria Inversiones | I81: -9880326.4 | J81: =SUMIF('México Summary'!$C:$C,Resumen!B81,'México Summary'!$AC:$AC) -> 0 | K81: 0 | L81: =IF((IFERROR(J81/I81,0))=0,0,(IFERROR(J81/I81,0)-1)) -> 0 | M81: =IF((IFERROR(J81/K81,0))=0,0,(IFERROR(J81/K81,0)-1)) -> 0 | O81: 0 | P81: 0 | Q81: 0 | R81: =IF((IFERROR(O81/P81,0))=0,0,(IFERROR(O81/P81,0)-1)) -> 0 | S81: =IF((IFERROR(O81/Q81,0))=0,0,(IFERROR(O81/Q81,0)-1)) -> 0
B82: 418-000-000-00 | C82: 0 | D82: 0 | E82: 0 | F82: =IF((IFERROR(C82/D82,0))=0,0,(IFERROR(C82/D82,0)-1)) -> 0 | G82: =IF((IFERROR(C82/E82,0))=0,0,(IFERROR(C82/E82,0)-1)) -> 0 | H82: Plusvalia/Minusvalia Portafolio Inversiones | I82: 8568327.5 | J82: =SUMIF('México Summary'!$C:$C,Resumen!B82,'México Summary'!$AC:$AC) -> 0 | K82: 0 | L82: =IF((IFERROR(J82/I82,0))=0,0,(IFERROR(J82/I82,0)-1)) -> 0 | M82: =IF((IFERROR(J82/K82,0))=0,0,(IFERROR(J82/K82,0)-1)) -> 0 | O82: 0 | P82: 0 | Q82: 0 | R82: =IF((IFERROR(O82/P82,0))=0,0,(IFERROR(O82/P82,0)-1)) -> 0 | S82: =IF((IFERROR(O82/Q82,0))=0,0,(IFERROR(O82/Q82,0)-1)) -> 0
C84: 0 | D84: 0 | E84: 0 | F84: =IF((IFERROR(C84/D84,0))=0,0,(IFERROR(C84/D84,0)-1)) -> 0 | G84: =IF((IFERROR(C84/E84,0))=0,0,(IFERROR(C84/E84,0)-1)) -> 0 | H84: Guadalajara Other Income | I84: 0 | J84: 0 | K84: 0 | L84: =IF((IFERROR(J84/I84,0))=0,0,(IFERROR(J84/I84,0)-1)) -> 0 | M84: =IF((IFERROR(J84/K84,0))=0,0,(IFERROR(J84/K84,0)-1)) -> 0 | O84: 0 | P84: 0 | Q84: 0 | R84: =IF((IFERROR(O84/P84,0))=0,0,(IFERROR(O84/P84,0)-1)) -> 0 | S84: =IF((IFERROR(O84/Q84,0))=0,0,(IFERROR(O84/Q84,0)-1)) -> 0
C85: 0 | D85: 0 | E85: 0 | F85: =IF((IFERROR(C85/D85,0))=0,0,(IFERROR(C85/D85,0)-1)) -> 0 | G85: =IF((IFERROR(C85/E85,0))=0,0,(IFERROR(C85/E85,0)-1)) -> 0 | H85: Monterrey Other Income | I85: 0 | J85: 0 | K85: 0 | L85: =IF((IFERROR(J85/I85,0))=0,0,(IFERROR(J85/I85,0)-1)) -> 0 | M85: =IF((IFERROR(J85/K85,0))=0,0,(IFERROR(J85/K85,0)-1)) -> 0 | O85: 0 | P85: 0 | Q85: 0 | R85: =IF((IFERROR(O85/P85,0))=0,0,(IFERROR(O85/P85,0)-1)) -> 0 | S85: =IF((IFERROR(O85/Q85,0))=0,0,(IFERROR(O85/Q85,0)-1)) -> 0
C86: 0 | D86: 0 | E86: 0 | F86: =IF((IFERROR(C86/D86,0))=0,0,(IFERROR(C86/D86,0)-1)) -> 0 | G86: =IF((IFERROR(C86/E86,0))=0,0,(IFERROR(C86/E86,0)-1)) -> 0 | H86: Northwest Other Income | I86: 0 | J86: 0 | K86: 0 | L86: =IF((IFERROR(J86/I86,0))=0,0,(IFERROR(J86/I86,0)-1)) -> 0 | M86: =IF((IFERROR(J86/K86,0))=0,0,(IFERROR(J86/K86,0)-1)) -> 0 | O86: 0 | P86: 0 | Q86: 0 | R86: =IF((IFERROR(O86/P86,0))=0,0,(IFERROR(O86/P86,0)-1)) -> 0 | S86: =IF((IFERROR(O86/Q86,0))=0,0,(IFERROR(O86/Q86,0)-1)) -> 0
C88: =C69-C76+C78 -> 0 | D88: =D69-D76+D78 -> 0 | E88: =E69-E76+E78 -> 0 | F88: =IF((IFERROR(C88/D88,0))=0,0,(IFERROR(C88/D88,0)-1)) -> 0 | G88: =IF((IFERROR(C88/E88,0))=0,0,(IFERROR(C88/E88,0)-1)) -> 0 | H88: NET RESULTS MEXICO | I88: =I69-I76+I78 -> 9377742.4 | J88: =J69-J76+J78 -> 2563969.8 | K88: =K69-K76+K78 -> 904390.62 | L88: =IF((IFERROR(J88/I88,0))=0,0,(IFERROR(J88/I88,0)-1)) -> -0.72658987 | M88: =IF((IFERROR(J88/K88,0))=0,0,(IFERROR(J88/K88,0)-1)) -> 1.8350247 | O88: =O69-O76+O78 -> 0 | P88: =P69-P76+P78 -> 0 | Q88: =Q69-Q76+Q78 -> 0 | R88: =IF((IFERROR(O88/P88,0))=0,0,(IFERROR(O88/P88,0)-1)) -> 0 | S88: =IF((IFERROR(O88/Q88,0))=0,0,(IFERROR(O88/Q88,0)-1)) -> 0 | U88: =U69-U76+U78 -> 2110095 | V88: =V69-V76+V78 -> 453874.75 | W88: =(J88/U88)-1 -> 0.21509683
C89: =C70+C84 -> 0 | D89: =D70+D84 -> 0 | E89: =E70+E84 -> 0 | F89: =IF((IFERROR(C89/D89,0))=0,0,(IFERROR(C89/D89,0)-1)) -> 0 | G89: =IF((IFERROR(C89/E89,0))=0,0,(IFERROR(C89/E89,0)-1)) -> 0 | H89: NET RESULTS GUADALAJARA | I89: =I70+I84 -> -462807.79 | J89: =J70+J84 -> 0 | K89: =K70+K84 -> 0 | L89: =IF((IFERROR(J89/I89,0))=0,0,(IFERROR(J89/I89,0)-1)) -> 0 | M89: =IF((IFERROR(J89/K89,0))=0,0,(IFERROR(J89/K89,0)-1)) -> 0 | O89: =O70+O84 -> 0 | P89: =P70+P84 -> 0 | Q89: =Q70+Q84 -> 0 | R89: =IF((IFERROR(O89/P89,0))=0,0,(IFERROR(O89/P89,0)-1)) -> 0 | S89: =IF((IFERROR(O89/Q89,0))=0,0,(IFERROR(O89/Q89,0)-1)) -> 0
C90: =C71+C85 -> 0 | D90: =D71+D85 -> 0 | E90: =E71+E85 -> 0 | F90: =IF((IFERROR(C90/D90,0))=0,0,(IFERROR(C90/D90,0)-1)) -> 0 | G90: =IF((IFERROR(C90/E90,0))=0,0,(IFERROR(C90/E90,0)-1)) -> 0 | H90: NET RESULTS MONTERREY | I90: =I71+I85 -> 574240.16 | J90: =J71+J85 -> 0 | K90: =K71+K85 -> 0 | L90: =IF((IFERROR(J90/I90,0))=0,0,(IFERROR(J90/I90,0)-1)) -> 0 | M90: =IF((IFERROR(J90/K90,0))=0,0,(IFERROR(J90/K90,0)-1)) -> 0 | O90: =O71+O85 -> 0 | P90: =P71+P85 -> 0 | Q90: =Q71+Q85 -> 0 | R90: =IF((IFERROR(O90/P90,0))=0,0,(IFERROR(O90/P90,0)-1)) -> 0 | S90: =IF((IFERROR(O90/Q90,0))=0,0,(IFERROR(O90/Q90,0)-1)) -> 0
C91: =C72+C86 -> 0 | D91: =D72+D86 -> 0 | E91: =E72+E86 -> 0 | F91: =IF((IFERROR(C91/D91,0))=0,0,(IFERROR(C91/D91,0)-1)) -> 0 | G91: =IF((IFERROR(C91/E91,0))=0,0,(IFERROR(C91/E91,0)-1)) -> 0 | H91: NET RESULTS NORTHWEST | I91: =I72+I86 -> 541748.02 | J91: =J72+J86 -> 0 | K91: =K72+K86 -> 0 | L91: =IF((IFERROR(J91/I91,0))=0,0,(IFERROR(J91/I91,0)-1)) -> 0 | M91: =IF((IFERROR(J91/K91,0))=0,0,(IFERROR(J91/K91,0)-1)) -> 0 | O91: =O72+O86 -> 0 | P91: =P72+P86 -> 0 | Q91: =Q72+Q86 -> 0 | R91: =IF((IFERROR(O91/P91,0))=0,0,(IFERROR(O91/P91,0)-1)) -> 0 | S91: =IF((IFERROR(O91/Q91,0))=0,0,(IFERROR(O91/Q91,0)-1)) -> 0
C93: =SUM(C88:C92) -> 0 | D93: =SUM(D88:D92) -> 0 | E93: =SUM(E88:E92) -> 0 | F93: =IF((IFERROR(C93/D93,0))=0,0,(IFERROR(C93/D93,0)-1)) -> 0 | G93: =IF((IFERROR(C93/E93,0))=0,0,(IFERROR(C93/E93,0)-1)) -> 0 | H93: CONSOLIDATED NET RESULTS | I93: =SUM(I88:I92) -> 10030923 | J93: =SUM(J88:J92) -> 2563969.8 | K93: =SUM(K88:K92) -> 904390.62 | L93: =IF((IFERROR(J93/I93,0))=0,0,(IFERROR(J93/I93,0)-1)) -> -0.74439343 | M93: =IF((IFERROR(J93/K93,0))=0,0,(IFERROR(J93/K93,0)-1)) -> 1.8350247 | O93: =SUM(O88:O92) -> 0 | P93: =SUM(P88:P92) -> 0 | Q93: =SUM(Q88:Q92) -> 0 | R93: =IF((IFERROR(O93/P93,0))=0,0,(IFERROR(O93/P93,0)-1)) -> 0 | S93: =IF((IFERROR(O93/Q93,0))=0,0,(IFERROR(O93/Q93,0)-1)) -> 0
AA95: Proyectado 2026
Y96: 2110095 | Z96: 158553.44 | AA96: 691304.62 | AB96: 1165188.3 | AC96: =SUM(Y96:AB96)+J96 -> 4125141.4
H97: Bono 2026 - Sueldos NO corporativos: | I97: 1366439
H98: Sueldos Corporativos: | I98: 373963.62
H100: Bono 2026 - Sueldos NO corporativos: | I100: 886066.64 | Y100: =Y96-Y69 -> -453874.75 | Z100: =Z96-Z69 -> -416253.01 | AA100: =AA96-AA69 -> 125215.88 | AB100: =AB96-AB69 -> -82190.524 | AC100: =AC96-AC69 -> -827102.4
H101: Sueldos Corporativos: | I101: 242495.76

Sheet Prorrateo
G2: Criterios de Distribución | K2: Cargo Anual | O2: Cargo Mensual
C3: GASTOS CORPORATIVOS 2026 | D3: Real 2025 | E3: Ppto. 2026 | F3: Criterio | G3: CDMX | H3: GDL | I3: MTY | J3: NO | K3: CDMX | L3: GDL | M3: MTY | N3: NO | O3: CDMX | P3: GDL | Q3: MTY | R3: NO
B4: 903-002-000-00 | C4: Seguro Gtos Médicos Mayores | D4: 2403570.5 | E4: 2700000 | F4: Costo Directo | G4: =$E$4*0.41 -> 1107000 | H4: =$E$4*0.16 -> 432000 | I4: =$E$4*0.39 -> 1053000 | J4: =$E$4*0.04 -> 108000 | K4: =G4 -> 1107000 | L4: =H4 -> 432000 | M4: =I4 -> 1053000 | N4: =J4 -> 108000 | O4: =K4/12 -> 92250 | P4: =L4/12 -> 36000 | Q4: =M4/12 -> 87750 | R4: =N4/12 -> 9000
B5: 903-003-000-00 | C5: Seguro de Vida | D5: 139972.77 | E5: =D5*1.06 -> 148371.14 | F5: Costo Directo | G5: =$E$5*0.62 -> 91990.104 | H5: =$E$5*0.13 -> 19288.248 | I5: =$E$5*0.23 -> 34125.361 | J5: =$E$5*0.02 -> 2967.4227 | K5: =G5 -> 91990.104 | L5: =H5 -> 19288.248 | M5: =I5 -> 34125.361 | N5: =J5 -> 2967.4227 | O5: =K5/12 -> 7665.842 | P5: =L5/12 -> 1607.354 | Q5: =M5/12 -> 2843.7801 | R5: =N5/12 -> 247.28523
B6: 903-004-000-00 | C6: Seguro Empresarial | D6: 213247.42 | E6: =D6*1.06 -> 226042.27 | F6: Costo Directo | G6: =$E$6*0.87 -> 196656.77 | H6: =$E$6*0.08 -> 18083.381 | I6: =$E$6*0.05 -> 11302.113 | J6: =$E$6*0 -> 0 | K6: =G6 -> 196656.77 | L6: =H6 -> 18083.381 | M6: =I6 -> 11302.113 | N6: =J6 -> 0 | O6: =K6/12 -> 16388.064 | P6: =L6/12 -> 1506.9484 | Q6: =M6/12 -> 941.84277 | R6: =N6/12 -> 0
B7: 903-005-000-00 | C7: Seguro Gobierno Corporativo | D7: 0 | E7: =70000*1.06 -> 74200 | F7: Ingresos | G7: 0.56 | H7: 0.12 | I7: 0.28 | J7: 0.04 | K7: =E7*G7 -> 41552 | L7: =E7*H7 -> 8904 | M7: =E7*I7 -> 20776 | N7: =E7*J7 -> 2968 | O7: =K7/12 -> 3462.6667 | P7: =L7/12 -> 742 | Q7: =M7/12 -> 1731.3333 | R7: =N7/12 -> 247.33333
B8: 903-006-000-00 | C8: Programa de Asistencia Empresarial (PAE) | D8: 69132.76 | E8: =76920.1*1.06 -> 81535.306 | F8: Costo Directo | G8: =$E$8*0.53 -> 43213.712 | H8: =$E$8*0.14 -> 11414.943 | I8: =$E$8*0.31 -> 25275.945 | J8: =$E$8*0.02 -> 1630.7061 | K8: =G8 -> 43213.712 | L8: =H8 -> 11414.943 | M8: =I8 -> 25275.945 | N8: =J8 -> 1630.7061 | O8: =K8/12 -> 3601.1427 | P8: =L8/12 -> 951.24524 | Q8: =M8/12 -> 2106.3287 | R8: =N8/12 -> 135.89218
B9: 903-007-000-00 | C9: Dominios | D9: 1925.6 | E9: =D9*1.06 -> 2041.136 | F9: Ingresos | G9: 0.56 | H9: 0.12 | I9: 0.28 | J9: 0.04 | K9: =E9*G9 -> 1143.0362 | L9: =E9*H9 -> 244.93632 | M9: =E9*I9 -> 571.51808 | N9: =E9*J9 -> 81.64544 | O9: =K9/12 -> 95.253013 | P9: =L9/12 -> 20.41136 | Q9: =M9/12 -> 47.626507 | R9: =N9/12 -> 6.8037867
B10: 903-008-000-00 | C10: CRM | D10: 0 | E10: =377280*1.06+74460*1.06 -> 478844.4 | F10: Ingresos | G10: 0.56 | H10: 0.12 | I10: 0.28 | J10: 0.04 | K10: =E10*G10 -> 268152.86 | L10: =E10*H10 -> 57461.328 | M10: =E10*I10 -> 134076.43 | N10: =E10*J10 -> 19153.776 | O10: =K10/12 -> 22346.072 | P10: =L10/12 -> 4788.444 | Q10: =M10/12 -> 11173.036 | R10: =N10/12 -> 1596.148
B11: 903-009-000-00 | C11: Servicios de Telecomunicaciones | D11: 735600 | E11: =D11*1.06 -> 779736 | F11: Ingresos | G11: 0.56 | H11: 0.12 | I11: 0.28 | J11: 0.04 | K11: =E11*G11 -> 436652.16 | L11: =E11*H11 -> 93568.32 | M11: =E11*I11 -> 218326.08 | N11: =E11*J11 -> 31189.44 | O11: =K11/12 -> 36387.68 | P11: =L11/12 -> 7797.36 | Q11: =M11/12 -> 18193.84 | R11: =N11/12 -> 2599.12
B12: 903-010-000-00 | C12: Licencias Generales | D12: 326237.08 | E12: =D12*1.06+(30000*1.06)+(144480.82*1.06)+(51000*1.06)+(13880+108000)+83400 -> 790100.97 | F12: Ingresos | G12: 0.56 | H12: 0.12 | I12: 0.28 | J12: 0.04 | K12: =E12*G12 -> 442456.55 | L12: =E12*H12 -> 94812.117 | M12: =E12*I12 -> 221228.27 | N12: =E12*J12 -> 31604.039 | O12: =K12/12 -> 36871.379 | P12: =L12/12 -> 7901.0097 | Q12: =M12/12 -> 18435.689 | R12: =N12/12 -> 2633.6699
B13: 903-011-000-00 | C13: Licencias Correos Corporativos | D13: 370585.42 | E13: =399510*1.06 -> 423480.6 | F13: Ingresos | G13: 0.56 | H13: 0.12 | I13: 0.28 | J13: 0.04 | K13: =E13*G13 -> 237149.14 | L13: =E13*H13 -> 50817.672 | M13: =E13*I13 -> 118574.57 | N13: =E13*J13 -> 16939.224 | O13: =K13/12 -> 19762.428 | P13: =L13/12 -> 4234.806 | Q13: =M13/12 -> 9881.214 | R13: =N13/12 -> 1411.602
B14: 903-012-000-00 | C14: Estudio Actuarial | D14: 24852.6 | E14: =D14*1.06 -> 26343.756 | F14: Ingresos | G14: 0.56 | H14: 0.12 | I14: 0.28 | J14: 0.04 | K14: =E14*G14 -> 14752.503 | L14: =E14*H14 -> 3161.2507 | M14: =E14*I14 -> 7376.2517 | N14: =E14*J14 -> 1053.7502 | O14: =K14/12 -> 1229.3753 | P14: =L14/12 -> 263.43756 | Q14: =M14/12 -> 614.68764 | R14: =N14/12 -> 87.81252
B15: 903-013-000-00 | C15: Gastos Notariales | D15: 12372 | E15: =D15*1.06 -> 13114.32 | F15: Ingresos | G15: 0.56 | H15: 0.12 | I15: 0.28 | J15: 0.04 | K15: =E15*G15 -> 7344.0192 | L15: =E15*H15 -> 1573.7184 | M15: =E15*I15 -> 3672.0096 | N15: =E15*J15 -> 524.5728 | O15: =K15/12 -> 612.0016 | P15: =L15/12 -> 131.1432 | Q15: =M15/12 -> 306.0008 | R15: =N15/12 -> 43.7144
B16: 903-014-000-00 | C16: Auditorías Externas | D16: 500040 | E16: =D16*1.06 -> 530042.4 | F16: Ingresos | G16: 0.56 | H16: 0.12 | I16: 0.28 | J16: 0.04 | K16: =E16*G16 -> 296823.74 | L16: =E16*H16 -> 63605.088 | M16: =E16*I16 -> 148411.87 | N16: =E16*J16 -> 21201.696 | O16: =K16/12 -> 24735.312 | P16: =L16/12 -> 5300.424 | Q16: =M16/12 -> 12367.656 | R16: =N16/12 -> 1766.808
B17: 903-015-000-00 | C17: Registro de Marcas | D17: 48792 | E17: =D17*1.06 -> 51719.52 | F17: Ingresos | G17: 0.56 | H17: 0.12 | I17: 0.28 | J17: 0.04 | K17: =E17*G17 -> 28962.931 | L17: =E17*H17 -> 6206.3424 | M17: =E17*I17 -> 14481.466 | N17: =E17*J17 -> 2068.7808 | O17: =K17/12 -> 2413.5776 | P17: =L17/12 -> 517.1952 | Q17: =M17/12 -> 1206.7888 | R17: =N17/12 -> 172.3984
B18: 903-016-000-00 | C18: Membresía AACCLA | D18: 389046.74 | E18: =D18*1.06 -> 412389.54 | F18: Ingresos | G18: 0.56 | H18: 0.12 | I18: 0.28 | J18: 0.04 | K18: =E18*G18 -> 230938.14 | L18: =E18*H18 -> 49486.745 | M18: =E18*I18 -> 115469.07 | N18: =E18*J18 -> 16495.582 | O18: =K18/12 -> 19244.845 | P18: =L18/12 -> 4123.8954 | Q18: =M18/12 -> 9622.4227 | R18: =N18/12 -> 1374.6318
C19: Almacen de Archivos AAA | D19: 52171.08 | E19: 0 | F19: Ingresos | G19: 0.56 | H19: 0.12 | I19: 0.28 | J19: 0.04
B20: 903-017-000-00 | C20: T&IC Licencias | D20: 820228.05 | E20: =D20*1.09 -> 894048.57 | F20: Ingresos | G20: 0.56 | H20: 0.12 | I20: 0.28 | J20: 0.04 | K20: =E20*G20 -> 500667.2 | L20: =E20*H20 -> 107285.83 | M20: =E20*I20 -> 250333.6 | N20: =E20*J20 -> 35761.943 | O20: =K20/12 -> 41722.267 | P20: =L20/12 -> 8940.4857 | Q20: =M20/12 -> 20861.133 | R20: =N20/12 -> 2980.1619
B21: 903-018-000-00 | C21: LinkedIn Herramienta | D21: 241392.77 | E21: =D21*1.06 -> 255876.34 | F21: Costo Directo | G21: =$E$21*0.34 -> 86997.954 | H21: =$E$21*0.23 -> 58851.557 | I21: =$E$21*0.41 -> 104909.3 | J21: =$E$21*0.02 -> 5117.5267 | K21: =G21 -> 86997.954 | L21: =H21 -> 58851.557 | M21: =I21 -> 104909.3 | N21: =J21 -> 5117.5267 | O21: =K21/12 -> 7249.8295 | P21: =L21/12 -> 4904.2964 | Q21: =M21/12 -> 8742.4415 | R21: =N21/12 -> 426.46056
B22: 903-019-000-00 | C22: Zoom Herramienta | D22: 72289.22 | E22: =D22*1.06 -> 76626.573 | F22: Ingresos | G22: 0.56 | H22: 0.12 | I22: 0.28 | J22: 0.04 | K22: =E22*G22 -> 42910.881 | L22: =E22*H22 -> 9195.1888 | M22: =E22*I22 -> 21455.441 | N22: =E22*J22 -> 3065.0629 | O22: =K22/12 -> 3575.9067 | P22: =L22/12 -> 766.26573 | Q22: =M22/12 -> 1787.9534 | R22: =N22/12 -> 255.42191
B23: 903-020-000-00 | C23: NarwhalHub Herramienta | D23: 0 | E23: =722743.2*1.06 -> 766107.79 | F23: Ingresos | G23: 0.56 | H23: 0.12 | I23: 0.28 | J23: 0.04 | K23: =E23*G23 -> 429020.36 | L23: =E23*H23 -> 91932.935 | M23: =E23*I23 -> 214510.18 | N23: =E23*J23 -> 30644.312 | O23: =K23/12 -> 35751.697 | P23: =L23/12 -> 7661.0779 | Q23: =M23/12 -> 17875.848 | R23: =N23/12 -> 2553.6926
B24: 903-021-000-00 | C24: Posicionamiento | D24: 0 | E24: =(48000*1.06*12)+(23000*1.06*12) -> 903120 | F24: Ingresos | G24: 0.56 | H24: 0.12 | I24: 0.28 | J24: 0.04 | K24: =E24*G24 -> 505747.2 | L24: =E24*H24 -> 108374.4 | M24: =E24*I24 -> 252873.6 | N24: =E24*J24 -> 36124.8 | O24: =K24/12 -> 42145.6 | P24: =L24/12 -> 9031.2 | Q24: =M24/12 -> 21072.8 | R24: =N24/12 -> 3010.4
B25: 903-001-000-00 | C25: Sueldos y Salarios VPE/Nacionales | D25: 22441543 | E25: =SUM(K25:N25) -> 25319979 | F25: Proyectado | K25: 14179188 | L25: 3038397.5 | M25: 7089594.2 | N25: 1012799.2 | O25: =K25/12 -> 1181599 | P25: =L25/12 -> 253199.79 | Q25: =M25/12 -> 590799.52 | R25: =N25/12 -> 84399.931
C26: TOTAL CARGOS CORPORATIVOS | D26: =SUM(D4:D25) -> 28862999 | E26: =SUM(E4:E25) -> 34953720 | K26: =SUM(K4:K25) -> 19189320 | L26: =SUM(L4:L25) -> 4324665.5 | M26: =SUM(M4:M25) -> 10060343 | N26: =SUM(N4:N25) -> 1379391.4 | O26: =SUM(O4:O25) -> 1599110 | P26: =SUM(P4:P25) -> 360388.79 | Q26: =SUM(Q4:Q25) -> 838361.94 | R26: =SUM(R4:R25) -> 114949.29
E29: INGRESOS: | F29: 45930 | G29: % | H29: 9+3 | I29: %
E30: CDMX | F30: 47208158 | G30: =ROUND(F30/$F$34,2) -> 0.56 | H30: 63870318 | I30: =ROUND(H30/$H$34,2) -> 0.53
E31: GDL | F31: 9895346.9 | G31: =ROUND(F31/$F$34,2) -> 0.12 | H31: 15701008 | I31: =ROUND(H31/$H$34,2) -> 0.13
E32: MTY | F32: 23108739 | G32: =ROUND(F32/$F$34,2) -> 0.28 | H32: 34776476 | I32: =ROUND(H32/$H$34,2) -> 0.29
E33: NO | F33: 3719892.4 | G33: =ROUND(F33/$F$34,2) -> 0.04 | H33: 6305605.7 | I33: =ROUND(H33/$H$34,2) -> 0.05
F34: =SUM(F30:F33) -> 83932136 | G34: =SUM(G30:G33) -> 1 | H34: =SUM(H30:H33) -> 1.2065341e+08 | I34: =SUM(I30:I33) -> 1
D47: Real Gastos corporativos 2025 (MX,GDL,MTY y NO)
D48: 955456.49 | E48: 448492 | F48: 909803 | G48: 89819 | H48: =D48+E48+F48+G48 -> 2403570.5
D49: 87741.77 | E49: 17797 | F49: 31815 | G49: 2619 | H49: =D49+E49+F49+G49 -> 139972.77
D50: 184835.42 | E50: 17484 | F50: 10928 | G50: 0 | H50: =D50+E50+F50+G50 -> 213247.42
D51: 0 | E51: 0 | F51: 0 | G51: 0 | H51: =D51+E51+F51+G51 -> 0
D52: 37972.76 | E52: 9493 | F52: 21667 | G52: 0 | H52: =D52+E52+F52+G52 -> 69132.76
D53: 1059.6 | E53: 250 | F53: 616 | G53: 0 | H53: =D53+E53+F53+G53 -> 1925.6
D54: 0 | E54: 0 | F54: 0 | G54: 0 | H54: =D54+E54+F54+G54 -> 0
D55: 404580 | E55: 95628 | F55: 235392 | G55: 0 | H55: =D55+E55+F55+G55 -> 735600
D56: 149527.08 | E56: 57882 | F56: 118828 | G56: 0 | H56: =D56+E56+F56+G56 -> 326237.08
D57: 200703.42 | E57: 49329 | F57: 120553 | G57: 0 | H57: =D57+E57+F57+G57 -> 370585.42
D58: 13668.6 | E58: 3231 | F58: 7953 | G58: 0 | H58: =D58+E58+F58+G58 -> 24852.6
D59: 6804 | E59: 1608 | F59: 3960 | G59: 0 | H59: =D59+E59+F59+G59 -> 12372
... D69: 11866101 | E69: 3024688 | F69: 6154739 | G69: 1396015 | H69: =D69+E69+F69+G69 -> 22441543

Sheet Gtos. Corporativos
C2: GASTOS CORPORATIVOS 2026 | D2: Real 2025 | E2: Ppto. 2026 | F2: Mensual | H2: 46023 | I2: 46023 | J2: 46054 | K2: 46054 | L2: 46082 | M2: 46082 | N2: 46113 | O2: 46113 | P2: 46143 | Q2: 46143 | R2: 46174 | S2: 46174 | T2: 46204 | U2: 46204 | V2: 46235 | W2: 46235 | X2: 46266 | Y2: 46266 | Z2: 46296 | AA2: 46296 | AB2: 46327 | AC2: 46327 | AD2: 46357 | AE2: 46357
B3: 903-002-000-00 | C3: Seguro Gtos Médicos Mayores | D3: 955456.49 | E3: =Prorrateo!K4 -> 1107000 | F3: =E3/12 -> 92250 | H3: =F3 -> 92250 | J3: =H3 -> 92250 | L3: =J3 -> 92250 | N3: =L3 -> 92250 | P3: =N3 -> 92250 | R3: =P3 -> 92250 | T3: =R3 -> 92250 | V3: =T3 -> 92250 | X3: =V3 -> 92250 | Z3: =X3 -> 92250 | AB3: =Z3 -> 92250 | AD3: =AB3 -> 92250
B4: 903-003-000-00 | C4: Seguro de Vida | D4: 87741.77 | E4: =Prorrateo!K5 -> 91990.104 | F4: =E4/12 -> 7665.842 | H4: =F4 -> 7665.842 | J4: =H4 -> 7665.842 | L4: =J4 -> 7665.842 | N4: =L4 -> 7665.842 | P4: =N4 -> 7665.842 | R4: =P4 -> 7665.842 | T4: =R4 -> 7665.842 | V4: =T4 -> 7665.842 | X4: =V4 -> 7665.842 | Z4: =X4 -> 7665.842 | AB4: =Z4 -> 7665.842 | AD4: =AB4 -> 7665.842
B5: 903-004-000-00 | C5: Seguro Empresarial | D5: 184835.42 | E5: =Prorrateo!K6 -> 196656.77 | F5: =E5/12 -> 16388.064 | H5: =F5 -> 16388.064 | J5: =H5 -> 16388.064 | L5: =J5 -> 16388.064 | N5: =L5 -> 16388.064 | P5: =N5 -> 16388.064 | R5: =P5 -> 16388.064 | T5: =R5 -> 16388.064 | V5: =T5 -> 16388.064 | X5: =V5 -> 16388.064 | Z5: =X5 -> 16388.064 | AB5: =Z5 -> 16388.064 | AD5: =AB5 -> 16388.064
B6: 903-005-000-00 | C6: Seguro Gobierno Corporativo | D6: 0 | E6: =Prorrateo!K7 -> 41552 | F6: =E6/12 -> 3462.6667 | H6: =F6 -> 3462.6667 | J6: =H6 -> 3462.6667 | L6: =J6 -> 3462.6667 | N6: =L6 -> 3462.6667 | P6: =N6 -> 3462.6667 | R6: =P6 -> 3462.6667 | T6: =R6 -> 3462.6667 | V6: =T6 -> 3462.6667 | X6: =V6 -> 3462.6667 | Z6: =X6 -> 3462.6667 | AB6: =Z6 -> 3462.6667 | AD6: =AB6 -> 3462.6667
B7: 903-006-000-00 | C7: Programa de Asistencia Empresarial (PAE) | D7: 37972.76 | E7: =Prorrateo!K8 -> 43213.712 | F7: =E7/12 -> 3601.1427 | H7: =F7 -> 3601.1427 | J7: =H7 -> 3601.1427 | L7: =J7 -> 3601.1427 | N7: =L7 -> 3601.1427 | P7: =N7 -> 3601.1427 | R7: =P7 -> 3601.1427 | T7: =R7 -> 3601.1427 | V7: =T7 -> 3601.1427 | X7: =V7 -> 3601.1427 | Z7: =X7 -> 3601.1427 | AB7: =Z7 -> 3601.1427 | AD7: =AB7 -> 3601.1427
B8: 903-007-000-00 | C8: Dominios | D8: 1059.6 | E8: =Prorrateo!K9 -> 1143.0362 | F8: =E8/12 -> 95.253013 | H8: =F8 -> 95.253013 | J8: =H8 -> 95.253013 | L8: =J8 -> 95.253013 | N8: =L8 -> 95.253013 | P8: =N8 -> 95.253013 | R8: =P8 -> 95.253013 | T8: =R8 -> 95.253013 | V8: =T8 -> 95.253013 | X8: =V8 -> 95.253013 | Z8: =X8 -> 95.253013 | AB8: =Z8 -> 95.253013 | AD8: =AB8 -> 95.253013
B9: 903-008-000-00 | C9: CRM | D9: 0 | E9: =Prorrateo!K10 -> 268152.86 | F9: =E9/12 -> 22346.072 | H9: =F9 -> 22346.072 | J9: =H9 -> 22346.072 | L9: =J9 -> 22346.072 | N9: =L9 -> 22346.072 | P9: =N9 -> 22346.072 | R9: =P9 -> 22346.072 | T9: =R9 -> 22346.072 | V9: =T9 -> 22346.072 | X9: =V9 -> 22346.072 | Z9: =X9 -> 22346.072 | AB9: =Z9 -> 22346.072 | AD9: =AB9 -> 22346.072
B10: 903-009-000-00 | C10: Servicios de Telecomunicaciones | D10: 404580 | E10: =Prorrateo!K11 -> 436652.16 | F10: =E10/12 -> 36387.68 | H10: =F10 -> 36387.68 | J10: =H10 -> 36387.68 | L10: =J10 -> 36387.68 | N10: =L10 -> 36387.68 | P10: =N10 -> 36387.68 | R10: =P10 -> 36387.68 | T10: =R10 -> 36387.68 | V10: =T10 -> 36387.68 | X10: =V10 -> 36387.68 | Z10: =X10 -> 36387.68 | AB10: =Z10 -> 36387.68 | AD10: =AB10 -> 36387.68
B11: 903-010-000-00 | C11: Licencias Generales | D11: 149527.08 | E11: =Prorrateo!K12 -> 442456.55 | F11: =E11/12 -> 36871.379 | H11: =F11 -> 36871.379 | J11: =H11 -> 36871.379 | L11: =J11 -> 36871.379 | N11: =L11 -> 36871.379 | P11: =N11 -> 36871.379 | R11: =P11 -> 36871.379 | T11: =R11 -> 36871.379 | V11: =T11 -> 36871.379 | X11: =V11 -> 36871.379 | Z11: =X11 -> 36871.379 | AB11: =Z11 -> 36871.379 | AD11: =AB11 -> 36871.379
B12: 903-011-000-00 | C12: Licencias Correos Corporativos | D12: 200703.42 | E12: =Prorrateo!K13 -> 237149.14 | F12: =E12/12 -> 19762.428 | H12: =F12 -> 19762.428 | J12: =H12 -> 19762.428 | L12: =J12 -> 19762.428 | N12: =L12 -> 19762.428 | P12: =N12 -> 19762.428 | R12: =P12 -> 19762.428 | T12: =R12 -> 19762.428 | V12: =T12 -> 19762.428 | X12: =V12 -> 19762.428 | Z12: =X12 -> 19762.428 | AB12: =Z12 -> 19762.428 | AD12: =AB12 -> 19762.428
B13: 903-012-000-00 | C13: Estudio Actuarial | D13: 13668.6 | E13: =Prorrateo!K14 -> 14752.503 | F13: =E13/12 -> 1229.3753 | H13: =F13 -> 1229.3753 | J13: =H13 -> 1229.3753 | L13: =J13 -> 1229.3753 | N13: =L13 -> 1229.3753 | P13: =N13 -> 1229.3753 | R13: =P13 -> 1229.3753 | T13: =R13 -> 1229.3753 | V13: =T13 -> 1229.3753 | X13: =V13 -> 1229.3753 | Z13: =X13 -> 1229.3753 | AB13: =Z13 -> 1229.3753 | AD13: =AB13 -> 1229.3753
B14: 903-013-000-00 | C14: Gastos Notariales | D14: 6804 | E14: =Prorrateo!K15 -> 7344.0192 | F14: =E14/12 -> 612.0016 | H14: =F14 -> 612.0016 | J14: =H14 -> 612.0016 | L14: =J14 -> 612.0016 | N14: =L14 -> 612.0016 | P14: =N14 -> 612.0016 | R14: =P14 -> 612.0016 | T14: =R14 -> 612.0016 | V14: =T14 -> 612.0016 | X14: =V14 -> 612.0016 | Z14: =X14 -> 612.0016 | AB14: =Z14 -> 612.0016 | AD14: =AB14 -> 612.0016
... B17: 903-016-000-00 | C17: Membresía AACCLA | D17: 213975.74 | E17: =Prorrateo!K18 -> 230938.14 | F17: =E17/12 -> 19244.845 | H17: =F17 -> 19244.845 | J17: =H17 -> 19244.845 | L17: =J17 -> 19244.845 | N17: =L17 -> 19244.845 | P17: =N17 -> 19244.845 | R17: =P17 -> 19244.845 | T17: =R17 -> 19244.845 | V17: =T17 -> 19244.845 | X17: =V17 -> 19244.845 | Z17: =X17 -> 19244.845 | AB17: =Z17 -> 19244.845 | AD17: =AB17 -> 19244.845
C18: Almacen de Archivos AAA | D18: 28694.08 | E18: 0 | F18: =E18/12 -> 0
B19: 903-017-000-00 | C19: T&IC Licencias | D19: 451125.05 | E19: =Prorrateo!K20 -> 500667.2 | F19: =E19/12 -> 41722.267 | H19: =F19 -> 41722.267 | J19: =H19 -> 41722.267 | L19: =J19 -> 41722.267 | N19: =L19 -> 41722.267 | P19: =N19 -> 41722.267 | R19: =P19 -> 41722.267 | T19: =R19 -> 41722.267 | V19: =T19 -> 41722.267 | X19: =V19 -> 41722.267 | Z19: =X19 -> 41722.267 | AB19: =Z19 -> 41722.267 | AD19: =AB19 -> 41722.267
B20: 903-018-000-00 | C20: LinkedIn Herramienta | D20: 87262.77 | E20: =Prorrateo!K21 -> 86997.954 | F20: =E20/12 -> 7249.8295 | H20: =F20 -> 7249.8295 | J20: =H20 -> 7249.8295 | L20: =J20 -> 7249.8295 | N20: =L20 -> 7249.8295 | P20: =N20 -> 7249.8295 | R20: =P20 -> 7249.8295 | T20: =R20 -> 7249.8295 | V20: =T20 -> 7249.8295 | X20: =V20 -> 7249.8295 | Z20: =X20 -> 7249.8295 | AB20: =Z20 -> 7249.8295 | AD20: =AB20 -> 7249.8295
B21: 903-019-000-00 | C21: Zoom Herramienta | D21: 36350.22 | E21: =Prorrateo!K22 -> 42910.881 | F21: =E21/12 -> 3575.9067 | H21: =F21 -> 3575.9067 | J21: =H21 -> 3575.9067 | L21: =J21 -> 3575.9067 | N21: =L21 -> 3575.9067 | P21: =N21 -> 3575.9067 | R21: =P21 -> 3575.9067 | T21: =R21 -> 3575.9067 | V21: =T21 -> 3575.9067 | X21: =V21 -> 3575.9067 | Z21: =X21 -> 3575.9067 | AB21: =Z21 -> 3575.9067 | AD21: =AB21 -> 3575.9067
B22: 903-020-000-00 | C22: NarwhalHub Herramienta | D22: 0 | E22: =Prorrateo!K23 -> 429020.36 | F22: =E22/12 -> 35751.697 | H22: =F22 -> 35751.697 | J22: =H22 -> 35751.697 | L22: =J22 -> 35751.697 | N22: =L22 -> 35751.697 | P22: =N22 -> 35751.697 | R22: =P22 -> 35751.697 | T22: =R22 -> 35751.697 | V22: =T22 -> 35751.697 | X22: =V22 -> 35751.697 | Z22: =X22 -> 35751.697 | AB22: =Z22 -> 35751.697 | AD22: =AB22 -> 35751.697
B23: 903-021-000-00 | C23: Posicionamiento | D23: 0 | E23: =Prorrateo!K24 -> 505747.2 | F23: =E23/12 -> 42145.6 | H23: =F23 -> 42145.6 | J23: =H23 -> 42145.6 | L23: =J23 -> 42145.6 | N23: =L23 -> 42145.6 | P23: =N23 -> 42145.6 | R23: =P23 -> 42145.6 | T23: =R23 -> 42145.6 | V23: =T23 -> 42145.6 | X23: =V23 -> 42145.6 | Z23: =X23 -> 42145.6 | AB23: =Z23 -> 42145.6 | AD23: =AB23 -> 42145.6
B24: 903-001-000-00 | C24: Sueldos y Salarios VPE/Nacionales | D24: 11866101 | E24: =Prorrateo!K25 -> 14179188 | F24: =E24/12 -> 1181599 | H24: =F24 -> 1181599 | J24: =H24 -> 1181599 | L24: =J24 -> 1181599 | N24: =L24 -> 1181599 | P24: =N24 -> 1181599 | R24: =P24 -> 1181599 | T24: =R24 -> 1181599 | V24: =T24 -> 1181599 | X24: =V24 -> 1181599 | Z24: =X24 -> 1181599 | AB24: =Z24 -> 1181599 | AD24: =AB24 -> 1181599
C25: TOTAL CARGOS CORPORATIVOS | D25: =SUM(D3:D24) -> 15027712 | E25: =SUM(E3:E24) -> 19189320 | F25: =SUM(F3:F24) -> 1599110 | H25: =SUM(H3:H24) -> 1599110 | I25: =SUM(I3:I24) -> 0 | J25: =SUM(J3:J24) -> 1599110 | K25: =SUM(K3:K24) -> 0 | L25: =SUM(L3:L24) -> 1599110 | M25: =SUM(M3:M24) -> 0 | N25: =SUM(N3:N24) -> 1599110 | O25: =SUM(O3:O24) -> 0 | ... AE25: =SUM(AE3:AE24) -> 0

Sheet Membresía
C3: MEMBRESIA | D3: 46023 | E3: 46023 | F3: 46054 | G3: 46054 | H3: 46082 | I3: 46082 | J3: 46113 | K3: 46113 | L3: 46143 | M3: 46143 | N3: 46174 | O3: 46174 | P3: 46204 | Q3: 46204 | R3: 46235 | S3: 46235 | T3: 46266 | U3: 46266 | V3: 46296 | W3: 46296 | X3: 46327 | Y3: 46327 | Z3: 46357 | AA3: 46357 | AB3: 2026
C6: Ingresos Membresía
B7: 401-004-000-00 | C7: Renovaciones | D7: 2940966.8 | E7: 0 | F7: 2940966.8 | G7: 0 | H7: 2940966.8 | I7: 0 | J7: 2940966.8 | K7: 0 | L7: 2940966.8 | M7: 0 | N7: 2940966.8 | O7: 0 | P7: 2940966.8 | Q7: 0 | R7: 2940966.8 | S7: 0 | T7: 2940966.8 | U7: 0 | V7: 2940966.8 | W7: 0 | X7: 2940966.8 | Y7: 0 | Z7: 2940966.8 | AA7: 0 | AB7: =D7+F7+H7+J7+L7+N7+P7+R7+T7+V7+X7+Z7 -> 35291602 | AC7: Queda igual - Propuesta subir aquí lo que bajo en Socios nuevos dado que los socios nuevos son renovaciones para el otro año | AD7: Si procede, subir diderencia de Socios Nvos.
B8: 401-003-000-00 | C8: Descuentos por pronto pago | D8: -58995.373 | E8: 0 | F8: -60533.502 | G8: 0 | H8: -61121.491 | I8: 0 | J8: -63495.891 | K8: 0 | L8: -65207.621 | M8: 0 | N8: -66928.691 | O8: 0 | P8: -76090.549 | Q8: 0 | R8: -75702.144 | S8: 0 | T8: -77951.474 | U8: 0 | V8: -49355.411 | W8: 0 | X8: -49807.283 | Y8: 0 | Z8: -49807.283 | AA8: 0 | AB8: =D8+F8+H8+J8+L8+N8+P8+R8+T8+V8+X8+Z8 -> -754996.71 | AC8: Sube a $944 | AD8: No procede
B9: 401-001-004-00 | C9: Socios Nuevos | D9: 902787.74 | E9: 0 | F9: 902787.74 | G9: 0 | H9: 902787.74 | I9: 0 | J9: 902787.74 | K9: 0 | L9: 902787.74 | M9: 0 | N9: 902787.74 | O9: 0 | P9: 902787.74 | Q9: 0 | R9: 902787.74 | S9: 0 | T9: 902787.74 | U9: 0 | V9: 902787.74 | W9: 0 | X9: 902787.74 | Y9: 0 | Z9: 902787.74 | AA9: 0 | AB9: =D9+F9+H9+J9+L9+N9+P9+R9+T9+V9+X9+Z9 -> 10833453 | AC9: Baja a $10.4M | AD9: Si procede
B10: 402-002-000-00 | C10: Cuotas Suscripción | D10: 108640 | E10: 0 | F10: 167440 | G10: 0 | H10: 86240 | I10: 0 | J10: 162848 | K10: 0 | L10: 91280 | M10: 0 | N10: 92960 | O10: 0 | P10: 133000 | Q10: 0 | R10: 131432 | S10: 0 | T10: 152880 | U10: 0 | V10: 158629.8 | W10: 0 | X10: 108520.79 | Y10: 0 | Z10: 108520.79 | AA10: 0 | AB10: =D10+F10+H10+J10+L10+N10+P10+R10+T10+V10+X10+Z10 -> 1502391.4 | AC10: Igual
B11: 408-020-000-00 | C11: Diamond Publicidad en Publicaciones | D11: 188003.2 | E11: 0 | F11: 204977.09 | G11: 0 | H11: 206184.5 | I11: 0 | J11: 297482.08 | K11: 0 | L11: 73237.469 | M11: 0 | N11: 83737.447 | O11: 0 | P11: 59237.441 | Q11: 0 | R11: 646465.68 | S11: 0 | T11: 242968.55 | U11: 0 | V11: 57767.157 | W11: 0 | X11: 125565.32 | Y11: 0 | Z11: 125565.32 | AA11: 0 | AB11: =D11+F11+H11+J11+L11+N11+P11+R11+T11+V11+X11+Z11 -> 2311191.3 | AC11: Igual
C12: Suma de Ingresos Membresía | D12: =SUM(D7:D11) -> 4081402.4 | E12: =SUM(E7:E11) -> 0 | F12: =SUM(F7:F11) -> 4155638.2 | G12: =SUM(G7:G11) -> 0 | H12: =SUM(H7:H11) -> 4075057.6 | I12: =SUM(I7:I11) -> 0 | J12: =SUM(J7:J11) -> 4240588.8 | K12: =SUM(K7:K11) -> 0 | ... AB12: =SUM(AB7:AB11) -> 49183641
C14: Gastos Membresía
B15: 705-002-000-00 | C15: Intercambios membresía-especie | D15: 0 | E15: 0 | F15: 0 | G15: 0 | H15: 0 | I15: 0 | J15: 0 | K15: 0 | L15: 0 | M15: 0 | N15: 0 | O15: 0 | P15: 0 | Q15: 0 | R15: 0 | S15: 0 | T15: 149460 | U15: 0 | V15: 131440 | W15: 0 | X15: 131440 | Y15: 0 | Z15: 371000 | AA15: 0 | AB15: =D15+F15+H15+J15+L15+N15+P15+R15+T15+V15+X15+Z15 -> 783340
B16: 705-003-000-00 | C16: Intercambios membresía | D16: 0 | E16: 0 | F16: 0 | G16: 0 | H16: 0 | I16: 0 | J16: 0 | K16: 0 | L16: 89040 | M16: 0 | N16: 0 | O16: 0 | P16: 0 | Q16: 0 | R16: 0 | S16: 0 | T16: 0 | U16: 0 | V16: 0 | W16: 0 | X16: 0 | Y16: 0 | Z16: 0 | AA16: 0 | AB16: =D16+F16+H16+J16+L16+N16+P16+R16+T16+V16+X16+Z16 -> 89040
B17: 520-000-000-00 | C17: Comisiones KAM´s | D17: 218440.83 | E17: 0 | F17: 185073.02 | G17: 0 | H17: 185935.66 | I17: 0 | J17: 200157 | K17: 0 | L17: 144965.6 | M17: 0 | N17: 178249.6 | O17: 0 | P17: 157205.42 | Q17: 0 | R17: 177013.3 | S17: 0 | T17: 158718.04 | U17: 0 | V17: 151989.81 | W17: 0 | X17: 151989.8 | Y17: 0 | Z17: 151989.8 | AA17: 0 | AB17: =D17+F17+H17+J17+L17+N17+P17+R17+T17+V17+X17+Z17 -> 2061727.9
B18: 705-001-000-00 | C18: Promoción Servicios Membresías (Representación) | D18: 1250 | E18: 0 | F18: 1250 | G18: 1250 | H18: 1250 | I18: 1250 | J18: 1250 | K18: 1250 | L18: 1250 | M18: 1250 | N18: 1250 | O18: 1250 | P18: 1250 | Q18: 1250 | R18: 1250 | S18: 1250 | T18: 1250 | U18: 1250 | V18: 1250 | W18: 1250 | X18: 1250 | Y18: 1250 | Z18: 1250 | AA18: 0 | AB18: =D18+F18+H18+J18+L18+N18+P18+R18+T18+V18+X18+Z18 -> 15000 | AC18: Sube a $24K | AD18: Subir a 15K
B19: 705-004-000-00 | C19: Onboarding | D19: 0 | E19: 0 | F19: 0 | G19: 0 | H19: 0 | I19: 0 | J19: 0 | K19: 0 | L19: 0 | M19: 0 | N19: 0 | O19: 0 | P19: 0 | Q19: 0 | R19: 0 | S19: 0 | T19: 0 | U19: 0 | V19: 0 | W19: 0 | X19: 0 | Y19: 0 | Z19: 0 | AA19: 0 | AB19: =D19+F19+H19+J19+L19+N19+P19+R19+T19+V19+X19+Z19 -> 0
