Workbook
Name Payment_Needed: "Pago necesario"
Name Reimbursement: "Reembolso"

Sheet RESUMEN
C3: Real 2026 | D3: Ppto. 2026 | E3: Real 2025 | F3: Variación Ppto. 2026 vs Real 2026 | G3: Variación Real 2025 vs Real 2026 | H3: Ago 24 | I3: Real 2025 | J3: Ppto. 2026 | K3: Ppto. 2025 | L3: Variación Ppto. 2026 vs Real 2025 | M3: Variación Ppto. 2025 vs Ppto. 2026 | O3: Forecast 2026 | P3: Ppto. 2026 | Q3: Real 2025 | R3: Variación Ppto. 2026 vs Real 2026 | S3: Variación Real 2025 vs Real 2026 | U3: Proyectado 2026 | V3: Diferencia
C5: =SUM(C6,C9,C12,C16,C14) -> 0 | D5: =SUM(D6,D9,D12,D16,D14) -> 0 | E5: =SUM(E6,E9,E12,E16,E14) -> 0 | F5: =IF((IFERROR(C5/D5,0))=0,0,(IFERROR(C5/D5,0)-1)) -> 0 | G5: =IF((IFERROR(C5/E5,0))=0,0,(IFERROR(C5/E5,0)-1)) -> 0 | H5: INCOME | I5: =SUM(I6,I9,I12,I16,I14) -> 14195973 | J5: =SUM(J6,J9,J12,J16,J14) -> 17961606 | K5: =SUM(K6,K9,K12,K16,K14) -> 17294316 | L5: =IF((IFERROR(J5/I5,0))=0,0,(IFERROR(J5/I5,0)-1)) -> 0.26526067 | M5: =IF((IFERROR(J5/K5,0))=0,0,(IFERROR(J5/K5,0)-1)) -> 0.038584369 | O5: =SUM(O6,O9,O12,O16,O14) -> 0 | P5: =SUM(P6,P9,P12,P16,P14) -> 0 | Q5: =SUM(Q6,Q9,Q12,Q16,Q14) -> 0 | R5: =IF((IFERROR(O5/P5,0))=0,0,(IFERROR(O5/P5,0)-1)) -> 0 | S5: =IF((IFERROR(O5/Q5,0))=0,0,(IFERROR(O5/Q5,0)-1)) -> 0 | U5: =SUM(U6,U9,U12,U16,U14) -> 18374706 | V5: =SUM(V6,V9,V12,V16,V14) -> -413100.34 | W5: =J5/U5-1 -> -0.02248201
C6: =C7+C8 -> 0 | D6: =D7+D8 -> 0 | E6: =E7+E8 -> 0 | F6: =IF((IFERROR(C6/D6,0))=0,0,(IFERROR(C6/D6,0)-1)) -> 0 | G6: =IF((IFERROR(C6/E6,0))=0,0,(IFERROR(C6/E6,0)-1)) -> 0 | H6: Membership | I6: =I7+I8 -> 10543077 | J6: =J7+J8 -> 11782798 | K6: =K7+K8 -> 10909089 | L6: =IF((IFERROR(J6/I6,0))=0,0,(IFERROR(J6/I6,0)-1)) -> 0.11758631 | M6: =IF((IFERROR(J6/K6,0))=0,0,(IFERROR(J6/K6,0)-1)) -> 0.080090036 | O6: =O7+O8 -> 0 | P6: =P7+P8 -> 0 | Q6: =Q7+Q8 -> 0 | R6: =IF((IFERROR(O6/P6,0))=0,0,(IFERROR(O6/P6,0)-1)) -> 0 | S6: =IF((IFERROR(O6/Q6,0))=0,0,(IFERROR(O6/Q6,0)-1)) -> 0 | U6: 12277769 | V6: =J6-U6 -> -494970.17 | W6: =J6/U6-1 -> -0.040314343
B7: 4e+20 | C7: 0 | D7: 0 | E7: 0 | F7: =IF((IFERROR(C7/D7,0))=0,0,(IFERROR(C7/D7,0)-1)) -> 0 | G7: =IF((IFERROR(C7/E7,0))=0,0,(IFERROR(C7/E7,0)-1)) -> 0 | H7: Cuotas Netas | I7: 10136402 | J7: =SUMIF('PPvsREal Summary'!$C:$C,RESUMEN!B7,'PPvsREal Summary'!$AC:$AC) -> 11272264 | K7: 10052089 | L7: =IF((IFERROR(J7/I7,0))=0,0,(IFERROR(J7/I7,0)-1)) -> 0.11205776 | M7: =IF((IFERROR(J7/K7,0))=0,0,(IFERROR(J7/K7,0)-1)) -> 0.12138525 | O7: 0 | P7: 0 | Q7: 0 | R7: =IF((IFERROR(O7/P7,0))=0,0,(IFERROR(O7/P7,0)-1)) -> 0 | S7: =IF((IFERROR(O7/Q7,0))=0,0,(IFERROR(O7/Q7,0)-1)) -> 0
B8: 4.01e+20 | C8: 0 | D8: 0 | E8: 0 | F8: =IF((IFERROR(C8/D8,0))=0,0,(IFERROR(C8/D8,0)-1)) -> 0 | G8: =IF((IFERROR(C8/E8,0))=0,0,(IFERROR(C8/E8,0)-1)) -> 0 | H8: Ingresos socios nuevos | I8: 406675 | J8: =SUMIF('PPvsREal Summary'!$C:$C,RESUMEN!B8,'PPvsREal Summary'!$AC:$AC) -> 510534 | K8: 857000 | L8: =IF((IFERROR(J8/I8,0))=0,0,(IFERROR(J8/I8,0)-1)) -> 0.25538575 | M8: =IF((IFERROR(J8/K8,0))=0,0,(IFERROR(J8/K8,0)-1)) -> -0.40427771 | O8: 0 | P8: 0 | Q8: 0 | R8: =IF((IFERROR(O8/P8,0))=0,0,(IFERROR(O8/P8,0)-1)) -> 0 | S8: =IF((IFERROR(O8/Q8,0))=0,0,(IFERROR(O8/Q8,0)-1)) -> 0
C9: =C10+C11 -> 0 | D9: =D10+D11 -> 0 | E9: =E10+E11 -> 0 | F9: =IF((IFERROR(C9/D9,0))=0,0,(IFERROR(C9/D9,0)-1)) -> 0 | G9: =IF((IFERROR(C9/E9,0))=0,0,(IFERROR(C9/E9,0)-1)) -> 0 | H9: Events | I9: =I10+I11 -> 2311332.8 | J9: =J10+J11 -> 3820000 | K9: =K10+K11 -> 4100000 | L9: =IF((IFERROR(J9/I9,0))=0,0,(IFERROR(J9/I9,0)-1)) -> 0.65272611 | M9: =IF((IFERROR(J9/K9,0))=0,0,(IFERROR(J9/K9,0)-1)) -> -0.068292683 | O9: =O10+O11 -> 0 | P9: =P10+P11 -> 0 | Q9: =Q10+Q11 -> 0 | R9: =IF((IFERROR(O9/P9,0))=0,0,(IFERROR(O9/P9,0)-1)) -> 0 | S9: =IF((IFERROR(O9/Q9,0))=0,0,(IFERROR(O9/Q9,0)-1)) -> 0 | U9: 3986161 | V9: =J9-U9 -> -166161.04 | W9: =J9/U9-1 -> -0.041684476
B10: 4.05e+20 | C10: 0 | D10: 0 | E10: 0 | F10: =IF((IFERROR(C10/D10,0))=0,0,(IFERROR(C10/D10,0)-1)) -> 0 | G10: =IF((IFERROR(C10/E10,0))=0,0,(IFERROR(C10/E10,0)-1)) -> 0 | H10: Eventos | I10: 2311332.8 | J10: =SUMIF('PPvsREal Summary'!$C:$C,RESUMEN!B10,'PPvsREal Summary'!$AC:$AC) -> 1190000 | K10: 4100000 | L10: =IF((IFERROR(J10/I10,0))=0,0,(IFERROR(J10/I10,0)-1)) -> -0.48514553 | M10: =IF((IFERROR(J10/K10,0))=0,0,(IFERROR(J10/K10,0)-1)) -> -0.7097561 | O10: 0 | P10: 0 | Q10: 0 | R10: =IF((IFERROR(O10/P10,0))=0,0,(IFERROR(O10/P10,0)-1)) -> 0 | S10: =IF((IFERROR(O10/Q10,0))=0,0,(IFERROR(O10/Q10,0)-1)) -> 0 | V10: =J10-U10 -> 1190000
B11: 4.06e+20 | C11: 0 | D11: 0 | E11: 0 | F11: =IF((IFERROR(C11/D11,0))=0,0,(IFERROR(C11/D11,0)-1)) -> 0 | G11: =IF((IFERROR(C11/E11,0))=0,0,(IFERROR(C11/E11,0)-1)) -> 0 | H11: Patrocinios | I11: 0 | J11: =SUMIF('PPvsREal Summary'!$C:$C,RESUMEN!B11,'PPvsREal Summary'!$AC:$AC) -> 2630000 | K11: 0 | L11: =IF((IFERROR(J11/I11,0))=0,0,(IFERROR(J11/I11,0)-1)) -> 0 | M11: =IF((IFERROR(J11/K11,0))=0,0,(IFERROR(J11/K11,0)-1)) -> 0 | O11: 0 | P11: 0 | Q11: 0 | R11: =IF((IFERROR(O11/P11,0))=0,0,(IFERROR(O11/P11,0)-1)) -> 0 | S11: =IF((IFERROR(O11/Q11,0))=0,0,(IFERROR(O11/Q11,0)-1)) -> 0 | V11: =J11-U11 -> 2630000
C12: =C13 -> 0 | D12: =D13 -> 0 | E12: =E13 -> 0 | F12: =IF((IFERROR(C12/D12,0))=0,0,(IFERROR(C12/D12,0)-1)) -> 0 | G12: =IF((IFERROR(C12/E12,0))=0,0,(IFERROR(C12/E12,0)-1)) -> 0 | H12: Committees | I12: =I13 -> 756663.16 | J12: =J13 -> 1594590.7 | K12: =K13 -> 1718000 | L12: =IF((IFERROR(J12/I12,0))=0,0,(IFERROR(J12/I12,0)-1)) -> 1.1073983 | M12: =IF((IFERROR(J12/K12,0))=0,0,(IFERROR(J12/K12,0)-1)) -> -0.07183313 | O12: =O13 -> 0 | P12: =P13 -> 0 | Q12: =Q13 -> 0 | R12: =IF((IFERROR(O12/P12,0))=0,0,(IFERROR(O12/P12,0)-1)) -> 0 | S12: =IF((IFERROR(O12/Q12,0))=0,0,(IFERROR(O12/Q12,0)-1)) -> 0 | U12: 1394945.1 | V12: =J12-U12 -> 199645.56 | W12: =J12/U12-1 -> 0.14312073
B13: 4.04e+20 | C13: 0 | D13: 0 | E13: 0 | F13: =IF((IFERROR(C13/D13,0))=0,0,(IFERROR(C13/D13,0)-1)) -> 0 | G13: =IF((IFERROR(C13/E13,0))=0,0,(IFERROR(C13/E13,0)-1)) -> 0 | H13: Comités | I13: 756663.16 | J13: =SUMIF('PPvsREal Summary'!$C:$C,RESUMEN!B13,'PPvsREal Summary'!$AC:$AC) -> 1594590.7 | K13: 1718000 | L13: =IF((IFERROR(J13/I13,0))=0,0,(IFERROR(J13/I13,0)-1)) -> 1.1073983 | M13: =IF((IFERROR(J13/K13,0))=0,0,(IFERROR(J13/K13,0)-1)) -> -0.07183313 | O13: 0 | P13: 0 | Q13: 0 | R13: =IF((IFERROR(O13/P13,0))=0,0,(IFERROR(O13/P13,0)-1)) -> 0 | S13: =IF((IFERROR(O13/Q13,0))=0,0,(IFERROR(O13/Q13,0)-1)) -> 0 | V13: =J13-U13 -> 1594590.7
C14: =C15 -> 0 | D14: =D15 -> 0 | E14: =E15 -> 0 | F14: =IF((IFERROR(C14/D14,0))=0,0,(IFERROR(C14/D14,0)-1)) -> 0 | G14: =IF((IFERROR(C14/E14,0))=0,0,(IFERROR(C14/E14,0)-1)) -> 0 | H14: T&IC | I14: =I15 -> 0 | J14: =J15 -> 50000 | K14: =K15 -> 0 | L14: =IF((IFERROR(J14/I14,0))=0,0,(IFERROR(J14/I14,0)-1)) -> 0 | M14: =IF((IFERROR(J14/K14,0))=0,0,(IFERROR(J14/K14,0)-1)) -> 0 | O14: =O15 -> 0 | P14: =P15 -> 0 | Q14: =Q15 -> 0 | R14: =IF((IFERROR(O14/P14,0))=0,0,(IFERROR(O14/P14,0)-1)) -> 0 | S14: =IF((IFERROR(O14/Q14,0))=0,0,(IFERROR(O14/Q14,0)-1)) -> 0 | U14: 0 | V14: =J14-U14 -> 50000 | W14: =J14/U14-1 -> #DIV/0!
B15: 4.07e+20 | C15: 0 | D15: 0 | E15: 0 | F15: =IF((IFERROR(C15/D15,0))=0,0,(IFERROR(C15/D15,0)-1)) -> 0 | G15: =IF((IFERROR(C15/E15,0))=0,0,(IFERROR(C15/E15,0)-1)) -> 0 | H15: Trade & Investment Center | I15: 0 | J15: =SUMIF('PPvsREal Summary'!$C:$C,RESUMEN!B15,'PPvsREal Summary'!$AC:$AC) -> 50000 | K15: 0 | L15: =IF((IFERROR(J15/I15,0))=0,0,(IFERROR(J15/I15,0)-1)) -> 0 | M15: =IF((IFERROR(J15/K15,0))=0,0,(IFERROR(J15/K15,0)-1)) -> 0 | O15: 0 | P15: 0 | Q15: 0 | R15: =IF((IFERROR(O15/P15,0))=0,0,(IFERROR(O15/P15,0)-1)) -> 0 | S15: =IF((IFERROR(O15/Q15,0))=0,0,(IFERROR(O15/Q15,0)-1)) -> 0 | V15: =J15-U15 -> 50000
C16: =C17+C18 -> 0 | D16: =D17+D18 -> 0 | E16: =E17+E18 -> 0 | F16: =IF((IFERROR(C16/D16,0))=0,0,(IFERROR(C16/D16,0)-1)) -> 0 | G16: =IF((IFERROR(C16/E16,0))=0,0,(IFERROR(C16/E16,0)-1)) -> 0 | H16: Services to Members | I16: =I17+I18 -> 584900 | J16: =J17+J18 -> 714217.04 | K16: =K17+K18 -> 567226.8 | L16: =IF((IFERROR(J16/I16,0))=0,0,(IFERROR(J16/I16,0)-1)) -> 0.22109255 | M16: =IF((IFERROR(J16/K16,0))=0,0,(IFERROR(J16/K16,0)-1)) -> 0.25913838 | O16: =O17+O18 -> 0 | P16: =P17+P18 -> 0 | Q16: =Q17+Q18 -> 0 | R16: =IF((IFERROR(O16/P16,0))=0,0,(IFERROR(O16/P16,0)-1)) -> 0 | S16: =IF((IFERROR(O16/Q16,0))=0,0,(IFERROR(O16/Q16,0)-1)) -> 0 | U16: 715831.73 | V16: =J16-U16 -> -1614.69 | W16: =J16/U16-1 -> -0.0022556838
B17: 4.03e+20 | C17: 0 | D17: 0 | E17: 0 | F17: =IF((IFERROR(C17/D17,0))=0,0,(IFERROR(C17/D17,0)-1)) -> 0 | G17: =IF((IFERROR(C17/E17,0))=0,0,(IFERROR(C17/E17,0)-1)) -> 0 | H17: Venta Publicaciones | I17: 584900 | J17: =SUMIF('PPvsREal Summary'!$C:$C,RESUMEN!B17,'PPvsREal Summary'!$AC:$AC) -> 714217.04 | K17: 567226.8 | L17: =IF((IFERROR(J17/I17,0))=0,0,(IFERROR(J17/I17,0)-1)) -> 0.22109255 | M17: =IF((IFERROR(J17/K17,0))=0,0,(IFERROR(J17/K17,0)-1)) -> 0.25913838 | O17: 0 | P17: 0 | Q17: 0 | R17: =IF((IFERROR(O17/P17,0))=0,0,(IFERROR(O17/P17,0)-1)) -> 0 | S17: =IF((IFERROR(O17/Q17,0))=0,0,(IFERROR(O17/Q17,0)-1)) -> 0
B18: 4.08e+20 | C18: 0 | D18: 0 | E18: 0 | F18: =IF((IFERROR(C18/D18,0))=0,0,(IFERROR(C18/D18,0)-1)) -> 0 | G18: =IF((IFERROR(C18/E18,0))=0,0,(IFERROR(C18/E18,0)-1)) -> 0 | H18: Visas | I18: 0 | J18: =SUMIF('PPvsREal Summary'!$C:$C,RESUMEN!B18,'PPvsREal Summary'!$AC:$AC) -> 0 | K18: 0 | L18: =IF((IFERROR(J18/I18,0))=0,0,(IFERROR(J18/I18,0)-1)) -> 0 | M18: =IF((IFERROR(J18/K18,0))=0,0,(IFERROR(J18/K18,0)-1)) -> 0 | O18: 0 | P18: 0 | Q18: 0 | R18: =IF((IFERROR(O18/P18,0))=0,0,(IFERROR(O18/P18,0)-1)) -> 0 | S18: =IF((IFERROR(O18/Q18,0))=0,0,(IFERROR(O18/Q18,0)-1)) -> 0
C19: =C20+C23+C25+C30+C32+C35+C36+C28 -> 0 | D19: =D20+D23+D25+D30+D32+D35+D36+D28 -> 0 | E19: =E20+E23+E25+E30+E32+E35+E36+E28 -> 0 | F19: =IF((IFERROR(C19/D19,0))=0,0,(IFERROR(C19/D19,0)-1)) -> 0 | G19: =IF((IFERROR(C19/E19,0))=0,0,(IFERROR(C19/E19,0)-1)) -> 0 | H19: EXPENSE | I19: =I20+I23+I25+I30+I32+I35+I36+I28 -> 14658996 | J19: =J20+J23+J25+J30+J32+J35+J36+J28 -> 17851585 | K19: =K20+K23+K25+K30+K32+K35+K36+K28 -> 16453320 | L19: =IF((IFERROR(J19/I19,0))=0,0,(IFERROR(J19/I19,0)-1)) -> 0.21779036 | M19: =IF((IFERROR(J19/K19,0))=0,0,(IFERROR(J19/K19,0)-1)) -> 0.084983721 | O19: =O20+O23+O25+O30+O32+O35+O36+O28 -> 0 | P19: =P20+P23+P25+P30+P32+P35+P36+P28 -> 0 | Q19: =Q20+Q23+Q25+Q30+Q32+Q35+Q36+Q28 -> 0 | R19: =IF((IFERROR(O19/P19,0))=0,0,(IFERROR(O19/P19,0)-1)) -> 0 | S19: =IF((IFERROR(O19/Q19,0))=0,0,(IFERROR(O19/Q19,0)-1)) -> 0 | U19: =U20+U23+U25+U30+U32+U35+U36+U28 -> 18216153 | V19: =V20+V23+V25+V30+V32+V35+V36+V28 -> -364568.48 | W19: =J19/U19-1 -> -0.020013473
C20: =C21+C22 -> 0 | D20: =D21+D22 -> 0 | E20: =E21+E22 -> 0 | F20: =IF((IFERROR(C20/D20,0))=0,0,(IFERROR(C20/D20,0)-1)) -> 0 | G20: =IF((IFERROR(C20/E20,0))=0,0,(IFERROR(C20/E20,0)-1)) -> 0 | H20: Membership | I20: =I21+I22 -> 567446.96 | J20: =J21+J22 -> 493042.52 | K20: =K21+K22 -> 675870.6 | L20: =IF((IFERROR(J20/I20,0))=0,0,(IFERROR(J20/I20,0)-1)) -> -0.1311214 | M20: =IF((IFERROR(J20/K20,0))=0,0,(IFERROR(J20/K20,0)-1)) -> -0.27050752 | O20: =O21+O22 -> 0 | P20: =P21+P22 -> 0 | Q20: =Q21+Q22 -> 0 | R20: =IF((IFERROR(O20/P20,0))=0,0,(IFERROR(O20/P20,0)-1)) -> 0 | S20: =IF((IFERROR(O20/Q20,0))=0,0,(IFERROR(O20/Q20,0)-1)) -> 0 | U20: 565172.2 | V20: =J20-U20 -> -72129.681 | W20: =J20/U20-1 -> -0.12762426
B21: 7.02e+20 | C21: 0 | D21: 0 | E21: 0 | F21: =IF((IFERROR(C21/D21,0))=0,0,(IFERROR(C21/D21,0)-1)) -> 0 | G21: =IF((IFERROR(C21/E21,0))=0,0,(IFERROR(C21/E21,0)-1)) -> 0 | H21: Gastos Promoción | I21: 40913.02 | J21: =SUMIF('PPvsREal Summary'!$C:$C,RESUMEN!B21,'PPvsREal Summary'!$AC:$AC) -> 33519.558 | K21: 120000 | L21: =IF((IFERROR(J21/I21,0))=0,0,(IFERROR(J21/I21,0)-1)) -> -0.18071171 | M21: =IF((IFERROR(J21/K21,0))=0,0,(IFERROR(J21/K21,0)-1)) -> -0.72067035 | O21: 0 | P21: 0 | Q21: 0 | R21: =IF((IFERROR(O21/P21,0))=0,0,(IFERROR(O21/P21,0)-1)) -> 0 | S21: =IF((IFERROR(O21/Q21,0))=0,0,(IFERROR(O21/Q21,0)-1)) -> 0 | V21: =J21-U21 -> 33519.558
B22: 5.03e+20 | C22: 0 | D22: 0 | E22: 0 | F22: =IF((IFERROR(C22/D22,0))=0,0,(IFERROR(C22/D22,0)-1)) -> 0 | G22: =IF((IFERROR(C22/E22,0))=0,0,(IFERROR(C22/E22,0)-1)) -> 0 | H22: Comisiones por venta de membresías | I22: 526533.94 | J22: =SUMIF('PPvsREal Summary'!$C:$C,RESUMEN!B22,'PPvsREal Summary'!$AC:$AC) -> 459522.96 | K22: 555870.6 | L22: =IF((IFERROR(J22/I22,0))=0,0,(IFERROR(J22/I22,0)-1)) -> -0.12726811 | M22: =IF((IFERROR(J22/K22,0))=0,0,(IFERROR(J22/K22,0)-1)) -> -0.17332746 | O22: 0 | P22: 0 | Q22: 0 | R22: =IF((IFERROR(O22/P22,0))=0,0,(IFERROR(O22/P22,0)-1)) -> 0 | S22: =IF((IFERROR(O22/Q22,0))=0,0,(IFERROR(O22/Q22,0)-1)) -> 0 | V22: =J22-U22 -> 459522.96
C23: =C24 -> 0 | D23: =D24 -> 0 | E23: =E24 -> 0 | F23: =IF((IFERROR(C23/D23,0))=0,0,(IFERROR(C23/D23,0)-1)) -> 0 | G23: =IF((IFERROR(C23/E23,0))=0,0,(IFERROR(C23/E23,0)-1)) -> 0 | H23: Events | I23: =I24 -> 1496260.2 | J23: =J24 -> 2660000 | K23: =K24 -> 2956045 | L23: =IF((IFERROR(J23/I23,0))=0,0,(IFERROR(J23/I23,0)-1)) -> 0.7777656 | M23: =IF((IFERROR(J23/K23,0))=0,0,(IFERROR(J23/K23,0)-1)) -> -0.10014902 | O23: =O24 -> 0 | P23: =P24 -> 0 | Q23: =Q24 -> 0 | R23: =IF((IFERROR(O23/P23,0))=0,0,(IFERROR(O23/P23,0)-1)) -> 0 | S23: =IF((IFERROR(O23/Q23,0))=0,0,(IFERROR(O23/Q23,0)-1)) -> 0 | U23: 2267032.4 | V23: =J23-U23 -> 392967.64 | W23: =J23/U23-1 -> 0.17334011
B24: 7.01e+20 | C24: 0 | D24: 0 | E24: 0 | F24: =IF((IFERROR(C24/D24,0))=0,0,(IFERROR(C24/D24,0)-1)) -> 0 | G24: =IF((IFERROR(C24/E24,0))=0,0,(IFERROR(C24/E24,0)-1)) -> 0 | H24: Costo Eventos | I24: 1496260.2 | J24: =SUMIF('PPvsREal Summary'!$C:$C,RESUMEN!B24,'PPvsREal Summary'!$AC:$AC) -> 2660000 | K24: 2956045 | L24: =IF((IFERROR(J24/I24,0))=0,0,(IFERROR(J24/I24,0)-1)) -> 0.7777656 | M24: =IF((IFERROR(J24/K24,0))=0,0,(IFERROR(J24/K24,0)-1)) -> -0.10014902 | O24: 0 | P24: 0 | Q24: 0 | R24: =IF((IFERROR(O24/P24,0))=0,0,(IFERROR(O24/P24,0)-1)) -> 0 | S24: =IF((IFERROR(O24/Q24,0))=0,0,(IFERROR(O24/Q24,0)-1)) -> 0 | V24: =J24-U24 -> 2660000
C25: =C26+C27 -> 0 | D25: =D26+D27 -> 0 | E25: =E26+E27 -> 0 | F25: =IF((IFERROR(C25/D25,0))=0,0,(IFERROR(C25/D25,0)-1)) -> 0 | G25: =IF((IFERROR(C25/E25,0))=0,0,(IFERROR(C25/E25,0)-1)) -> 0 | H25: Committees | I25: =I26+I27 -> 644237.57 | J25: =J26+J27 -> 1004784.9 | K25: =K26+K27 -> 896480 | L25: =IF((IFERROR(J25/I25,0))=0,0,(IFERROR(J25/I25,0)-1)) -> 0.55964962 | M25: =IF((IFERROR(J25/K25,0))=0,0,(IFERROR(J25/K25,0)-1)) -> 0.12081126 | O25: =O26 -> 0 | P25: =P26 -> 0 | Q25: =Q26 -> 0 | R25: =IF((IFERROR(O25/P25,0))=0,0,(IFERROR(O25/P25,0)-1)) -> 0 | S25: =IF((IFERROR(O25/Q25,0))=0,0,(IFERROR(O25/Q25,0)-1)) -> 0 | U25: 890349.64 | V25: =J25-U25 -> 114435.24 | W25: =J25/U25-1 -> 0.12852843
B26: 5.02e+20 | C26: 0 | D26: 0 | E26: 0 | F26: =IF((IFERROR(C26/D26,0))=0,0,(IFERROR(C26/D26,0)-1)) -> 0 | G26: =IF((IFERROR(C26/E26,0))=0,0,(IFERROR(C26/E26,0)-1)) -> 0 | H26: Costo comités | I26: 644237.57 | J26: =SUMIF('PPvsREal Summary'!$C:$C,RESUMEN!B26,'PPvsREal Summary'!$AC:$AC) -> 1004784.9 | K26: 896480 | L26: =IF((IFERROR(J26/I26,0))=0,0,(IFERROR(J26/I26,0)-1)) -> 0.55964962 | M26: =IF((IFERROR(J26/K26,0))=0,0,(IFERROR(J26/K26,0)-1)) -> 0.12081126 | O26: 0 | P26: 0 | Q26: 0 | R26: =IF((IFERROR(O26/P26,0))=0,0,(IFERROR(O26/P26,0)-1)) -> 0 | S26: =IF((IFERROR(O26/Q26,0))=0,0,(IFERROR(O26/Q26,0)-1)) -> 0 | V26: =J26-U26 -> 1004784.9
B27: 5.04e+20 | C27: 0 | D27: 0 | E27: 0 | F27: =IF((IFERROR(C27/D27,0))=0,0,(IFERROR(C27/D27,0)-1)) -> 0 | G27: =IF((IFERROR(C27/E27,0))=0,0,(IFERROR(C27/E27,0)-1)) -> 0 | H27: Comisiones EWDP | I27: 0 | J27: =SUMIF('PPvsREal Summary'!$C:$C,RESUMEN!B27,'PPvsREal Summary'!$AC:$AC) -> 0 | K27: 0 | L27: =IF((IFERROR(J27/I27,0))=0,0,(IFERROR(J27/I27,0)-1)) -> 0 | M27: =IF((IFERROR(J27/K27,0))=0,0,(IFERROR(J27/K27,0)-1)) -> 0 | O27: 0 | P27: 0 | Q27: 0 | R27: =IF((IFERROR(O27/P27,0))=0,0,(IFERROR(O27/P27,0)-1)) -> 0 | S27: =IF((IFERROR(O27/Q27,0))=0,0,(IFERROR(O27/Q27,0)-1)) -> 0 | V27: =J27-U27 -> 0
C28: =C29 -> 0 | D28: =D29 -> 0 | E28: =E29 -> 0 | F28: =IF((IFERROR(C28/D28,0))=0,0,(IFERROR(C28/D28,0)-1)) -> 0 | G28: =IF((IFERROR(C28/E28,0))=0,0,(IFERROR(C28/E28,0)-1)) -> 0 | H28: T&IC | I28: =I29 -> 0 | J28: =J29 -> 25000 | K28: =K29 -> 0 | L28: =IF((IFERROR(J28/I28,0))=0,0,(IFERROR(J28/I28,0)-1)) -> 0 | M28: =IF((IFERROR(J28/K28,0))=0,0,(IFERROR(J28/K28,0)-1)) -> 0 | O28: =O29 -> 0 | P28: =P29 -> 0 | Q28: =Q29 -> 0 | R28: =IF((IFERROR(O28/P28,0))=0,0,(IFERROR(O28/P28,0)-1)) -> 0 | S28: =IF((IFERROR(O28/Q28,0))=0,0,(IFERROR(O28/Q28,0)-1)) -> 0 | U28: 0 | V28: =J28-U28 -> 25000 | W28: =J28/U28-1 -> #DIV/0!
B29: 7.03e+20 | C29: 0 | D29: 0 | E29: 0 | F29: =IF((IFERROR(C29/D29,0))=0,0,(IFERROR(C29/D29,0)-1)) -> 0 | G29: =IF((IFERROR(C29/E29,0))=0,0,(IFERROR(C29/E29,0)-1)) -> 0 | H29: Costo Trade & Investment Center | I29: 0 | J29: =SUMIF('PPvsREal Summary'!$C:$C,RESUMEN!B29,'PPvsREal Summary'!$AC:$AC) -> 25000 | K29: 0 | L29: =IF((IFERROR(J29/I29,0))=0,0,(IFERROR(J29/I29,0)-1)) -> 0 | M29: =IF((IFERROR(J29/K29,0))=0,0,(IFERROR(J29/K29,0)-1)) -> 0 | O29: 0 | P29: 0 | Q29: 0 | R29: =IF((IFERROR(O29/P29,0))=0,0,(IFERROR(O29/P29,0)-1)) -> 0 | S29: =IF((IFERROR(O29/Q29,0))=0,0,(IFERROR(O29/Q29,0)-1)) -> 0 | V29: =J29-U29 -> 25000
C30: =C31 -> 0 | D30: =D31 -> 0 | E30: =E31 -> 0 | F30: =IF((IFERROR(C30/D30,0))=0,0,(IFERROR(C30/D30,0)-1)) -> 0 | G30: =IF((IFERROR(C30/E30,0))=0,0,(IFERROR(C30/E30,0)-1)) -> 0 | H30: Services to Members | I30: =I31 -> 292450 | J30: =J31 -> 357108.52 | K30: =K31 -> 283613.4 | L30: =IF((IFERROR(J30/I30,0))=0,0,(IFERROR(J30/I30,0)-1)) -> 0.22109255 | M30: =IF((IFERROR(J30/K30,0))=0,0,(IFERROR(J30/K30,0)-1)) -> 0.25913838 | O30: =O31 -> 0 | P30: =P31 -> 0 | Q30: =Q31 -> 0 | R30: =IF((IFERROR(O30/P30,0))=0,0,(IFERROR(O30/P30,0)-1)) -> 0 | S30: =IF((IFERROR(O30/Q30,0))=0,0,(IFERROR(O30/Q30,0)-1)) -> 0 | U30: 444647.32 | V30: =J30-U30 -> -87538.804 | W30: =J30/U30-1 -> -0.19687244
B31: 6.01e+20 | C31: 0 | D31: 0 | E31: 0 | F31: =IF((IFERROR(C31/D31,0))=0,0,(IFERROR(C31/D31,0)-1)) -> 0 | G31: =IF((IFERROR(C31/E31,0))=0,0,(IFERROR(C31/E31,0)-1)) -> 0 | H31: Gastos Venta Publicaciones | I31: 292450 | J31: =SUMIF('PPvsREal Summary'!$C:$C,RESUMEN!B31,'PPvsREal Summary'!$AC:$AC) -> 357108.52 | K31: 283613.4 | L31: =IF((IFERROR(J31/I31,0))=0,0,(IFERROR(J31/I31,0)-1)) -> 0.22109255 | M31: =IF((IFERROR(J31/K31,0))=0,0,(IFERROR(J31/K31,0)-1)) -> 0.25913838 | O31: 0 | P31: 0 | Q31: 0 | R31: =IF((IFERROR(O31/P31,0))=0,0,(IFERROR(O31/P31,0)-1)) -> 0 | S31: =IF((IFERROR(O31/Q31,0))=0,0,(IFERROR(O31/Q31,0)-1)) -> 0 | V31: =J31-U31 -> 357108.52
C32: =C33+C34 -> 0 | D32: =D33+D34 -> 0 | E32: =E33+E34 -> 0 | F32: =IF((IFERROR(C32/D32,0))=0,0,(IFERROR(C32/D32,0)-1)) -> 0 | G32: =IF((IFERROR(C32/E32,0))=0,0,(IFERROR(C32/E32,0)-1)) -> 0 | H32: Gastos G&A | I32: =I33+I34 -> 1780331.8 | J32: =J33+J34 -> 2270680.8 | K32: =K33+K34 -> 2000217.9 | L32: =IF((IFERROR(J32/I32,0))=0,0,(IFERROR(J32/I32,0)-1)) -> 0.27542565 | M32: =IF((IFERROR(J32/K32,0))=0,0,(IFERROR(J32/K32,0)-1)) -> 0.13521673 | O32: =O33+O34 -> 0 | P32: =P33+P34 -> 0 | Q32: =Q33+Q34 -> 0 | R32: =IF((IFERROR(O32/P32,0))=0,0,(IFERROR(O32/P32,0)-1)) -> 0 | S32: =IF((IFERROR(O32/Q32,0))=0,0,(IFERROR(O32/Q32,0)-1)) -> 0 | U32: 1830574.1 | V32: =J32-U32 -> 440106.68 | W32: =J32/U32-1 -> 0.24042003
B33: 8.01e+20 | C33: 0 | D33: 0 | E33: 0 | F33: =IF((IFERROR(C33/D33,0))=0,0,(IFERROR(C33/D33,0)-1)) -> 0 | G33: =IF((IFERROR(C33/E33,0))=0,0,(IFERROR(C33/E33,0)-1)) -> 0 | H33: Gasto de Administración | I33: 302430.6 | J33: =SUMIF('PPvsREal Summary'!$C:$C,RESUMEN!B33,'PPvsREal Summary'!$AC:$AC) -> 496408.94 | K33: 532937.82 | L33: =IF((IFERROR(J33/I33,0))=0,0,(IFERROR(J33/I33,0)-1)) -> 0.64139788 | M33: =IF((IFERROR(J33/K33,0))=0,0,(IFERROR(J33/K33,0)-1)) -> -0.068542472 | O33: 0 | P33: 0 | Q33: 0 | R33: =IF((IFERROR(O33/P33,0))=0,0,(IFERROR(O33/P33,0)-1)) -> 0 | S33: =IF((IFERROR(O33/Q33,0))=0,0,(IFERROR(O33/Q33,0)-1)) -> 0 | V33: =J33-U33 -> 496408.94
B34: 9.01e+20 | C34: 0 | D34: 0 | E34: 0 | F34: =IF((IFERROR(C34/D34,0))=0,0,(IFERROR(C34/D34,0)-1)) -> 0 | G34: =IF((IFERROR(C34/E34,0))=0,0,(IFERROR(C34/E34,0)-1)) -> 0 | H34: Gastos Generales | I34: 1477901.2 | J34: =SUMIF('PPvsREal Summary'!$C:$C,RESUMEN!B34,'PPvsREal Summary'!$AC:$AC) -> 1774271.9 | K34: 1467280.1 | L34: =IF((IFERROR(J34/I34,0))=0,0,(IFERROR(J34/I34,0)-1)) -> 0.20053485 | M34: =IF((IFERROR(J34/K34,0))=0,0,(IFERROR(J34/K34,0)-1)) -> 0.20922509 | O34: 0 | P34: 0 | Q34: 0 | R34: =IF((IFERROR(O34/P34,0))=0,0,(IFERROR(O34/P34,0)-1)) -> 0 | S34: =IF((IFERROR(O34/Q34,0))=0,0,(IFERROR(O34/Q34,0)-1)) -> 0 | V34: =J34-U34 -> 1774271.9
B35: 5.01e+20 | C35: 0 | D35: 0 | E35: 0 | F35: =IF((IFERROR(C35/D35,0))=0,0,(IFERROR(C35/D35,0)-1)) -> 0 | G35: =IF((IFERROR(C35/E35,0))=0,0,(IFERROR(C35/E35,0)-1)) -> 0 | H35: Nómina | I35: 5850740.2 | J35: =SUMIF('PPvsREal Summary'!$C:$C,RESUMEN!B35,'PPvsREal Summary'!$AC:$AC) -> 6711987.8 | K35: 5720425.7 | L35: =IF((IFERROR(J35/I35,0))=0,0,(IFERROR(J35/I35,0)-1)) -> 0.1472032 | M35: =IF((IFERROR(J35/K35,0))=0,0,(IFERROR(J35/K35,0)-1)) -> 0.17333713 | O35: 0 | P35: 0 | Q35: 0 | R35: =IF((IFERROR(O35/P35,0))=0,0,(IFERROR(O35/P35,0)-1)) -> 0 | S35: =IF((IFERROR(O35/Q35,0))=0,0,(IFERROR(O35/Q35,0)-1)) -> 0 | U35: 7550054.4 | V35: =J35-U35 -> -838066.54 | W35: =J35/U35-1 -> -0.11100139
B36: 9.03e+20 | C36: 0 | D36: 0 | E36: 0 | F36: =IF((IFERROR(C36/D36,0))=0,0,(IFERROR(C36/D36,0)-1)) -> 0 | G36: =IF((IFERROR(C36/E36,0))=0,0,(IFERROR(C36/E36,0)-1)) -> 0 | H36: Gastos Corporativos | I36: 4027529.7 | J36: =SUMIF('PPvsREal Summary'!$C:$C,RESUMEN!B36,'PPvsREal Summary'!$AC:$AC) -> 4328980 | K36: 3920667.6 | L36: =IF((IFERROR(J36/I36,0))=0,0,(IFERROR(J36/I36,0)-1)) -> 0.074847429 | M36: =IF((IFERROR(J36/K36,0))=0,0,(IFERROR(J36/K36,0)-1)) -> 0.10414358 | O36: 0 | P36: 0 | Q36: 0 | R36: =IF((IFERROR(O36/P36,0))=0,0,(IFERROR(O36/P36,0)-1)) -> 0 | S36: =IF((IFERROR(O36/Q36,0))=0,0,(IFERROR(O36/Q36,0)-1)) -> 0 | U36: 4668323 | V36: =J36-U36 -> -339343.01 | W36: =J36/U36-1 -> -0.07269056
B37: 9.03016e+20 | C37: 0 | D37: 0 | E37: 0 | F37: =IF((IFERROR(C37/D37,0))=0,0,(IFERROR(C37/D37,0)-1)) -> 0 | G37: =IF((IFERROR(C37/E37,0))=0,0,(IFERROR(C37/E37,0)-1)) -> 0 | H37: Cargos Administrativos | I37: 3024687.9 | J37: 0 | K37: 0 | L37: =IF((IFERROR(J37/I37,0))=0,0,(IFERROR(J37/I37,0)-1)) -> 0 | M37: =IF((IFERROR(J37/K37,0))=0,0,(IFERROR(J37/K37,0)-1)) -> 0 | O37: 0 | P37: 0 | Q37: 0 | R37: =IF((IFERROR(O37/P37,0))=0,0,(IFERROR(O37/P37,0)-1)) -> 0 | S37: =IF((IFERROR(O37/Q37,0))=0,0,(IFERROR(O37/Q37,0)-1)) -> 0
C38: =+C5-C19 -> 0 | D38: =+D5-D19 -> 0 | E38: =+E5-E19 -> 0 | F38: =IF((IFERROR(C38/D38,0))=0,0,(IFERROR(C38/D38,0)-1)) -> 0 | G38: =IF((IFERROR(C38/E38,0))=0,0,(IFERROR(C38/E38,0)-1)) -> 0 | H38: OPERATING RESULTS | I38: =+I5-I19 -> -463023.6 | J38: =+J5-J19 -> 110021.59 | K38: =+K5-K19 -> 840995.69 | L38: =IF((IFERROR(J38/I38,0))=0,0,(IFERROR(J38/I38,0)-1)) -> -1.2376155 | M38: =IF((IFERROR(J38/K38,0))=0,0,(IFERROR(J38/K38,0)-1)) -> -0.86917699 | O38: =+O5-O19 -> 0 | P38: =+P5-P19 -> 0 | Q38: =+Q5-Q19 -> 0 | R38: =IF((IFERROR(O38/P38,0))=0,0,(IFERROR(O38/P38,0)-1)) -> 0 | S38: =IF((IFERROR(O38/Q38,0))=0,0,(IFERROR(O38/Q38,0)-1)) -> 0 | U38: =+U5-U19 -> 158553.44 | V38: =+V5-V19 -> -48531.857 | W38: =J38/U38-1 -> -0.30609147
B39: 9.04e+20 | C39: 0 | D39: 0 | E39: 0 | F39: =IF((IFERROR(C39/D39,0))=0,0,(IFERROR(C39/D39,0)-1)) -> 0 | G39: =IF((IFERROR(C39/E39,0))=0,0,(IFERROR(C39/E39,0)-1)) -> 0 | H39: Member Centricity | I39: 0 | J39: =SUMIF('PPvsREal Summary'!$C:$C,RESUMEN!B39,'PPvsREal Summary'!$AC:$AC) -> 0 | K39: 0 | L39: =IF((IFERROR(J39/I39,0))=0,0,(IFERROR(J39/I39,0)-1)) -> 0 | M39: =IF((IFERROR(J39/K39,0))=0,0,(IFERROR(J39/K39,0)-1)) -> 0 | O39: 0 | P39: 0 | Q39: 0 | R39: =IF((IFERROR(O39/P39,0))=0,0,(IFERROR(O39/P39,0)-1)) -> 0 | S39: =IF((IFERROR(O39/Q39,0))=0,0,(IFERROR(O39/Q39,0)-1)) -> 0 | U39: 0 | V39: =J39-U39 -> 0 | W39: =J39/U39-1 -> #DIV/0!
C40: =C41+C42 -> 0 | D40: =D41+D42 -> 0 | E40: =E41+E42 -> 0 | F40: =IF((IFERROR(C40/D40,0))=0,0,(IFERROR(C40/D40,0)-1)) -> 0 | G40: =IF((IFERROR(C40/E40,0))=0,0,(IFERROR(C40/E40,0)-1)) -> 0 | H40: Other | I40: =I41+I42 -> 215.81 | J40: =J41+J42 -> 0 | K40: =K41+K42 -> 0 | L40: =IF((IFERROR(J40/I40,0))=0,0,(IFERROR(J40/I40,0)-1)) -> 0 | M40: =IF((IFERROR(J40/K40,0))=0,0,(IFERROR(J40/K40,0)-1)) -> 0 | O40: =O41+O42 -> 0 | P40: =P41+P42 -> 0 | Q40: =Q41+Q42 -> 0 | R40: =IF((IFERROR(O40/P40,0))=0,0,(IFERROR(O40/P40,0)-1)) -> 0 | S40: =IF((IFERROR(O40/Q40,0))=0,0,(IFERROR(O40/Q40,0)-1)) -> 0 | U40: 0 | V40: =J40-U40 -> 0 | W40: =J40/U40-1 -> #DIV/0!
B41: 4.02e+20 | C41: 0 | D41: 0 | E41: 0 | F41: =IF((IFERROR(C41/D41,0))=0,0,(IFERROR(C41/D41,0)-1)) -> 0 | G41: =IF((IFERROR(C41/E41,0))=0,0,(IFERROR(C41/E41,0)-1)) -> 0 | H41: Otros ingresos | I41: 215.81 | J41: =SUMIF('PPvsREal Summary'!$C:$C,RESUMEN!B41,'PPvsREal Summary'!$AC:$AC) -> 0 | K41: 0 | L41: =IF((IFERROR(J41/I41,0))=0,0,(IFERROR(J41/I41,0)-1)) -> 0 | M41: =IF((IFERROR(J41/K41,0))=0,0,(IFERROR(J41/K41,0)-1)) -> 0 | O41: 0 | P41: 0 | Q41: 0 | R41: =IF((IFERROR(O41/P41,0))=0,0,(IFERROR(O41/P41,0)-1)) -> 0 | S41: =IF((IFERROR(O41/Q41,0))=0,0,(IFERROR(O41/Q41,0)-1)) -> 0
B42: 4.1e+20 | C42: 0 | D42: 0 | E42: 0 | F42: =IF((IFERROR(C42/D42,0))=0,0,(IFERROR(C42/D42,0)-1)) -> 0 | G42: =IF((IFERROR(C42/E42,0))=0,0,(IFERROR(C42/E42,0)-1)) -> 0 | H42: Utilidad cambiaria | I42: 0 | J42: =SUMIF('PPvsREal Summary'!$C:$C,RESUMEN!B42,'PPvsREal Summary'!$AC:$AC) -> 0 | K42: 0 | L42: =IF((IFERROR(J42/I42,0))=0,0,(IFERROR(J42/I42,0)-1)) -> 0 | M42: =IF((IFERROR(J42/K42,0))=0,0,(IFERROR(J42/K42,0)-1)) -> 0 | O42: 0 | P42: 0 | Q42: 0 | R42: =IF((IFERROR(O42/P42,0))=0,0,(IFERROR(O42/P42,0)-1)) -> 0 | S42: =IF((IFERROR(O42/Q42,0))=0,0,(IFERROR(O42/Q42,0)-1)) -> 0
C43: =C38-C39+C40 -> 0 | D43: =D38-D39+D40 -> 0 | E43: =E38-E39+E40 -> 0 | F43: =IF((IFERROR(C43/D43,0))=0,0,(IFERROR(C43/D43,0)-1)) -> 0 | G43: =IF((IFERROR(C43/E43,0))=0,0,(IFERROR(C43/E43,0)-1)) -> 0 | H43: NET RESULTS | I43: =I38-I39+I40 -> -462807.79 | J43: =J38-J39+J40 -> 110021.59 | K43: =K38-K39+K40 -> 840995.69 | L43: =IF((IFERROR(J43/I43,0))=0,0,(IFERROR(J43/I43,0)-1)) -> -1.2377263 | M43: =IF((IFERROR(J43/K43,0))=0,0,(IFERROR(J43/K43,0)-1)) -> -0.86917699 | O43: =O38-O39+O40 -> 0 | P43: =P38-P39+P40 -> 0 | Q43: =Q38-Q39+Q40 -> 0 | R43: =IF((IFERROR(O43/P43,0))=0,0,(IFERROR(O43/P43,0)-1)) -> 0 | S43: =IF((IFERROR(O43/Q43,0))=0,0,(IFERROR(O43/Q43,0)-1)) -> 0 | U43: =U38-U39+U40 -> 158553.44 | V43: =V38-V39+V40 -> -48531.857 | W43: =J43/U43-1 -> -0.30609147
H47: Bono 2026 - Sueldos NO Corporativos: | I47: 232522.13
H48: Sueldos Corporativos: | I48: 95324.06
H50: Bono 2026 - Sueldos NO Corporativos: | I50: 157778.27
H51: Sueldos Corporativos: | I51: 61812.64

Sheet Gtos. Corporativos
C1: AMERICAN CHAMBER OF COMMERCE OF MEXICO, A.C.
C3: GASTOS CORPORATIVOS 2026 | D3: Real 2025 | E3: Ppto. 2026 | F3: Var. % | G3: Criterio | H3: Mensual | J3: 46023 | K3: 46023 | L3: 46054 | M3: 46054 | N3: 46082 | O3: 46082 | P3: 46113 | Q3: 46113 | R3: 46143 | S3: 46143 | T3: 46174 | U3: 46174 | V3: 46204 | W3: 46204 | X3: 46235 | Y3: 46235 | Z3: 46266 | AA3: 46266 | AB3: 46296 | AC3: 46296 | AD3: 46327 | AE3: 46327 | AF3: 46357 | AG3: 46357
B4: 903-034-000-00 | C4: Seguro Gtos Médicos Mayores | D4: 448491.96 | E4: 432000 | F4: =IFERROR(((E4/D4)-1),1) -> -0.03677203 | G4: Costo Directo | H4: =E4/12 -> 36000 | J4: =H4 -> 36000 | L4: =J4 -> 36000 | N4: =L4 -> 36000 | P4: =N4 -> 36000 | R4: =P4 -> 36000 | T4: =R4 -> 36000 | V4: =T4 -> 36000 | X4: =V4 -> 36000 | Z4: =X4 -> 36000 | AB4: =Z4 -> 36000 | AD4: =AB4 -> 36000 | AF4: =AD4 -> 36000
B5: 903-033-000-00 | C5: Seguro de Vida | D5: 17797.36 | E5: 19288.343 | F5: =IFERROR(((E5/D5)-1),1) -> 0.083775503 | G5: Costo Directo | H5: =E5/12 -> 1607.3619 | J5: =H5 -> 1607.3619 | L5: =J5 -> 1607.3619 | N5: =L5 -> 1607.3619 | P5: =N5 -> 1607.3619 | R5: =P5 -> 1607.3619 | T5: =R5 -> 1607.3619 | V5: =T5 -> 1607.3619 | X5: =V5 -> 1607.3619 | Z5: =X5 -> 1607.3619 | AB5: =Z5 -> 1607.3619 | AD5: =AB5 -> 1607.3619 | AF5: =AD5 -> 1607.3619
B6: 903-002-000-00 | C6: Seguro Empresarial | D6: 17484 | E6: 18083.344 | F6: =IFERROR(((E6/D6)-1),1) -> 0.034279564 | G6: Costo Directo | H6: =E6/12 -> 1506.9453 | J6: =H6 -> 1506.9453 | L6: =J6 -> 1506.9453 | N6: =L6 -> 1506.9453 | P6: =N6 -> 1506.9453 | R6: =P6 -> 1506.9453 | T6: =R6 -> 1506.9453 | V6: =T6 -> 1506.9453 | X6: =V6 -> 1506.9453 | Z6: =X6 -> 1506.9453 | AB6: =Z6 -> 1506.9453 | AD6: =AB6 -> 1506.9453 | AF6: =AD6 -> 1506.9453
B7: 903-029-000-00 | C7: Seguro Gobierno Corporativo | D7: 0 | E7: 8904 | F7: =IFERROR(((E7/D7)-1),1) -> 1 | G7: 0.12 | H7: =E7/12 -> 742 | J7: =H7 -> 742 | L7: =J7 -> 742 | N7: =L7 -> 742 | P7: =N7 -> 742 | R7: =P7 -> 742 | T7: =R7 -> 742 | V7: =T7 -> 742 | X7: =V7 -> 742 | Z7: =X7 -> 742 | AB7: =Z7 -> 742 | AD7: =AB7 -> 742 | AF7: =AD7 -> 742
B8: 903-003-000-00 | C8: Programa de Asistencia Empresarial (PAE) | D8: 9493.16 | E8: 11414.943 | F8: =IFERROR(((E8/D8)-1),1) -> 0.20243869 | G8: Costo Directo | H8: =E8/12 -> 951.24524 | J8: =H8 -> 951.24524 | L8: =J8 -> 951.24524 | N8: =L8 -> 951.24524 | P8: =N8 -> 951.24524 | R8: =P8 -> 951.24524 | T8: =R8 -> 951.24524 | V8: =T8 -> 951.24524 | X8: =V8 -> 951.24524 | Z8: =X8 -> 951.24524 | AB8: =Z8 -> 951.24524 | AD8: =AB8 -> 951.24524 | AF8: =AD8 -> 951.24524
B9: 903-030-000-00 | C9: Dominios | D9: 250.44 | E9: 245.04826 | F9: =IFERROR(((E9/D9)-1),1) -> -0.021529085 | G9: 0.12 | H9: =E9/12 -> 20.420688 | J9: =H9 -> 20.420688 | L9: =J9 -> 20.420688 | N9: =L9 -> 20.420688 | P9: =N9 -> 20.420688 | R9: =P9 -> 20.420688 | T9: =R9 -> 20.420688 | V9: =T9 -> 20.420688 | X9: =V9 -> 20.420688 | Z9: =X9 -> 20.420688 | AB9: =Z9 -> 20.420688 | AD9: =AB9 -> 20.420688 | AF9: =AD9 -> 20.420688
B10: 903-032-000-00 | C10: CRM | D10: 0 | E10: 57461.328 | F10: =IFERROR(((E10/D10)-1),1) -> 1 | G10: 0.12 | H10: =E10/12 -> 4788.444 | J10: =H10 -> 4788.444 | L10: =J10 -> 4788.444 | N10: =L10 -> 4788.444 | P10: =N10 -> 4788.444 | R10: =P10 -> 4788.444 | T10: =R10 -> 4788.444 | V10: =T10 -> 4788.444 | X10: =V10 -> 4788.444 | Z10: =X10 -> 4788.444 | AB10: =Z10 -> 4788.444 | AD10: =AB10 -> 4788.444 | AF10: =AD10 -> 4788.444
B11: 903-018-000-00 | C11: Servicios de Telecomunicaciones | D11: 95628 | E11: 93568.32 | F11: =IFERROR(((E11/D11)-1),1) -> -0.021538462 | G11: 0.12 | H11: =E11/12 -> 7797.36 | J11: =H11 -> 7797.36 | L11: =J11 -> 7797.36 | N11: =L11 -> 7797.36 | P11: =N11 -> 7797.36 | R11: =P11 -> 7797.36 | T11: =R11 -> 7797.36 | V11: =T11 -> 7797.36 | X11: =V11 -> 7797.36 | Z11: =X11 -> 7797.36 | AB11: =Z11 -> 7797.36 | AD11: =AB11 -> 7797.36 | AF11: =AD11 -> 7797.36
B12: 903-031-000-00 | C12: Licencias Generales | D12: 57882.27 | E12: 87034.851 | F12: =IFERROR(((E12/D12)-1),1) -> 0.50365303 | G12: 0.12 | H12: =E12/12 -> 7252.9042 | J12: =H12 -> 7252.9042 | L12: =J12 -> 7252.9042 | N12: =L12 -> 7252.9042 | P12: =N12 -> 7252.9042 | R12: =P12 -> 7252.9042 | T12: =R12 -> 7252.9042 | V12: =T12 -> 7252.9042 | X12: =V12 -> 7252.9042 | Z12: =X12 -> 7252.9042 | AB12: =Z12 -> 7252.9042 | AD12: =AB12 -> 7252.9042 | AF12: =AD12 -> 7252.9042
B13: 903-028-000-00 | C13: Licencias Correos Corporativos | D13: 49328.96 | E13: 50817.672 | F13: =IFERROR(((E13/D13)-1),1) -> 0.03017927 | G13: 0.12 | H13: =E13/12 -> 4234.806 | J13: =H13 -> 4234.806 | L13: =J13 -> 4234.806 | N13: =L13 -> 4234.806 | P13: =N13 -> 4234.806 | R13: =P13 -> 4234.806 | T13: =R13 -> 4234.806 | V13: =T13 -> 4234.806 | X13: =V13 -> 4234.806 | Z13: =X13 -> 4234.806 | AB13: =Z13 -> 4234.806 | AD13: =AB13 -> 4234.806 | AF13: =AD13 -> 4234.806
B14: 903-011-000-00 | C14: Estudio actuarial | D14: 3230.76 | E14: 3161.1744 | F14: =IFERROR(((E14/D14)-1),1) -> -0.021538462 | G14: 0.12 | H14: =E14/12 -> 263.4312 | J14: =H14 -> 263.4312 | L14: =J14 -> 263.4312 | N14: =L14 -> 263.4312 | P14: =N14 -> 263.4312 | R14: =P14 -> 263.4312 | T14: =R14 -> 263.4312 | V14: =T14 -> 263.4312 | X14: =V14 -> 263.4312 | Z14: =X14 -> 263.4312 | AB14: =Z14 -> 263.4312 | AD14: =AB14 -> 263.4312 | AF14: =AD14 -> 263.4312
B15: 903-012-000-00 | C15: Gtos Notariales | D15: 1608 | E15: 1573.7184 | F15: =IFERROR(((E15/D15)-1),1) -> -0.021319403 | G15: 0.12 | H15: =E15/12 -> 131.1432 | J15: =H15 -> 131.1432 | L15: =J15 -> 131.1432 | N15: =L15 -> 131.1432 | P15: =N15 -> 131.1432 | R15: =P15 -> 131.1432 | T15: =R15 -> 131.1432 | V15: =T15 -> 131.1432 | X15: =V15 -> 131.1432 | Z15: =X15 -> 131.1432 | AB15: =Z15 -> 131.1432 | AD15: =AB15 -> 131.1432 | AF15: =AD15 -> 131.1432
B16: 903-017-000-00 | C16: Auditorías Externas | D16: 65005.2 | E16: 63605.088 | F16: =IFERROR(((E16/D16)-1),1) -> -0.021538462 | G16: 0.12 | H16: =E16/12 -> 5300.424 | J16: =H16 -> 5300.424 | L16: =J16 -> 5300.424 | N16: =L16 -> 5300.424 | P16: =N16 -> 5300.424 | R16: =P16 -> 5300.424 | T16: =R16 -> 5300.424 | V16: =T16 -> 5300.424 | X16: =V16 -> 5300.424 | Z16: =X16 -> 5300.424 | AB16: =Z16 -> 5300.424 | AD16: =AB16 -> 5300.424 | AF16: =AD16 -> 5300.424
B17: 903-014-000-00 | C17: Registro de Marcas | D17: 6348 | E17: 6206.3424 | F17: =IFERROR(((E17/D17)-1),1) -> -0.022315312 | G17: 0.12 | H17: =E17/12 -> 517.1952 | J17: =H17 -> 517.1952 | L17: =J17 -> 517.1952 | N17: =L17 -> 517.1952 | P17: =N17 -> 517.1952 | R17: =P17 -> 517.1952 | T17: =R17 -> 517.1952 | V17: =T17 -> 517.1952 | X17: =V17 -> 517.1952 | Z17: =X17 -> 517.1952 | AB17: =Z17 -> 517.1952 | AD17: =AB17 -> 517.1952 | AF17: =AD17 -> 517.1952
B18: 903-015-000-00 | C18: Membresía AACCLA | D18: 50576.11 | E18: 48967.5 | F18: =IFERROR(((E18/D18)-1),1) -> -0.031805735 | G18: 0.12 | H18: =E18/12 -> 4080.625 | J18: =H18 -> 4080.625 | L18: =J18 -> 4080.625 | N18: =L18 -> 4080.625 | P18: =N18 -> 4080.625 | R18: =P18 -> 4080.625 | T18: =R18 -> 4080.625 | V18: =T18 -> 4080.625 | X18: =V18 -> 4080.625 | Z18: =X18 -> 4080.625 | AB18: =Z18 -> 4080.625 | AD18: =AB18 -> 4080.625 | AF18: =AD18 -> 4080.625
C19: Almacén de Archivos | D19: 6782.23 | E19: 0 | F19: =IFERROR(((E19/D19)-1),1) -> -1 | G19: 0 | H19: =E19/12 -> 0 | J19: =H19 -> 0 | L19: =J19 -> 0 | N19: =L19 -> 0 | P19: =N19 -> 0 | R19: =P19 -> 0 | T19: =R19 -> 0 | V19: =T19 -> 0 | X19: =V19 -> 0 | Z19: =X19 -> 0 | AB19: =Z19 -> 0 | AD19: =AB19 -> 0 | AF19: =AD19 -> 0
B20: 903-024-000-00 | C20: T&IC Licencias | D20: 106629.56 | E20: 119174.12 | F20: =IFERROR(((E20/D20)-1),1) -> 0.11764622 | G20: 0.12 | H20: =E20/12 -> 9931.177 | J20: =H20 -> 9931.177 | L20: =J20 -> 9931.177 | N20: =L20 -> 9931.177 | P20: =N20 -> 9931.177 | R20: =P20 -> 9931.177 | T20: =R20 -> 9931.177 | V20: =T20 -> 9931.177 | X20: =V20 -> 9931.177 | Z20: =X20 -> 9931.177 | AB20: =Z20 -> 9931.177 | AD20: =AB20 -> 9931.177 | AF20: =AD20 -> 9931.177
B21: 903-005-000-00 | C21: LinkedIn Herramienta | D21: 57714.01 | E21: 60362.542 | F21: =IFERROR(((E21/D21)-1),1) -> 0.045890624 | G21: Costo Directo | H21: =E21/12 -> 5030.2118 | J21: =H21 -> 5030.2118 | L21: =J21 -> 5030.2118 | N21: =L21 -> 5030.2118 | P21: =N21 -> 5030.2118 | R21: =P21 -> 5030.2118 | T21: =R21 -> 5030.2118 | V21: =T21 -> 5030.2118 | X21: =V21 -> 5030.2118 | Z21: =X21 -> 5030.2118 | AB21: =Z21 -> 5030.2118 | AD21: =AB21 -> 5030.2118 | AF21: =AD21 -> 5030.2118
B22: 903-008-000-00 | C22: Zoom Herramienta | D22: 8591.83 | E22: 8406.8045 | F22: =IFERROR(((E22/D22)-1),1) -> -0.021535056 | G22: 0.12 | H22: =E22/12 -> 700.56704 | J22: =H22 -> 700.56704 | L22: =J22 -> 700.56704 | N22: =L22 -> 700.56704 | P22: =N22 -> 700.56704 | R22: =P22 -> 700.56704 | T22: =R22 -> 700.56704 | V22: =T22 -> 700.56704 | X22: =V22 -> 700.56704 | Z22: =X22 -> 700.56704 | AB22: =Z22 -> 700.56704 | AD22: =AB22 -> 700.56704 | AF22: =AD22 -> 700.56704
B23: 903-019-000-00 | C23: NarwhalHub Herramienta | D23: 0 | E23: 91932.935 | F23: =IFERROR(((E23/D23)-1),1) -> 1 | G23: 0.12 | H23: =E23/12 -> 7661.0779 | J23: =H23 -> 7661.0779 | L23: =J23 -> 7661.0779 | N23: =L23 -> 7661.0779 | P23: =N23 -> 7661.0779 | R23: =P23 -> 7661.0779 | T23: =R23 -> 7661.0779 | V23: =T23 -> 7661.0779 | X23: =V23 -> 7661.0779 | Z23: =X23 -> 7661.0779 | AB23: =Z23 -> 7661.0779 | AD23: =AB23 -> 7661.0779 | AF23: =AD23 -> 7661.0779
B24: 903-026-000-00 | C24: Posicionamiento | D24: 0 | E24: 108374.4 | F24: =IFERROR(((E24/D24)-1),1) -> 1 | G24: 0.12 | H24: =E24/12 -> 9031.2 | J24: =H24 -> 9031.2 | L24: =J24 -> 9031.2 | N24: =L24 -> 9031.2 | P24: =N24 -> 9031.2 | R24: =P24 -> 9031.2 | T24: =R24 -> 9031.2 | V24: =T24 -> 9031.2 | X24: =V24 -> 9031.2 | Z24: =X24 -> 9031.2 | AB24: =Z24 -> 9031.2 | AD24: =AB24 -> 9031.2 | AF24: =AD24 -> 9031.2
B25: 903-016-000-00 | C25: Sueldos y Salarios VPE/Nacionales | D25: 3024687.9 | E25: 3038397.5 | F25: =IFERROR(((E25/D25)-1),1) -> 0.0045325734 | G25: 0.12 | H25: =E25/12 -> 253199.79 | J25: =H25 -> 253199.79 | L25: =J25 -> 253199.79 | N25: =L25 -> 253199.79 | P25: =N25 -> 253199.79 | R25: =P25 -> 253199.79 | T25: =R25 -> 253199.79 | V25: =T25 -> 253199.79 | X25: =V25 -> 253199.79 | Z25: =X25 -> 253199.79 | AB25: =Z25 -> 253199.79 | AD25: =AB25 -> 253199.79 | AF25: =AD25 -> 253199.79
C26: TOTAL CARGOS CORPORATIVOS | D26: =SUM(D4:D25) -> 4027529.7 | E26: =SUM(E4:E25) -> 4328980 | F26: =IFERROR(((E26/D26)-1),1) -> 0.074847429 | H26: =SUM(H4:H25) -> 360748.33 | J26: =SUM(J4:J25) -> 360748.33 | K26: =SUM(K4:K25) -> 0 | L26: =SUM(L4:L25) -> 360748.33 | M26: =SUM(M4:M25) -> 0 | N26: =SUM(N4:N25) -> 360748.33 | O26: =SUM(O4:O25) -> 0 | P26: =SUM(P4:P25) -> 360748.33 | Q26: =SUM(Q4:Q25) -> 0 | ... AG26: =SUM(AG4:AG25) -> 0

Sheet DN
C2: MEMBRESIA | D2: 46023 | E2: 46023 | F2: 46054 | G2: 46054 | H2: 46082 | I2: 46082 | J2: 46113 | K2: 46113 | L2: 46143 | M2: 46143 | N2: 46174 | O2: 46174 | P2: 46204 | Q2: 46204 | R2: 46235 | S2: 46235 | T2: 46266 | U2: 46266 | V2: 46296 | W2: 46296 | X2: 46327 | Y2: 46327 | Z2: 46357 | AA2: 46357 | AB2: 2026
C4: Ingresos Membresía
B5: 400-001-000-00 | C5: Renovaciones | D5: 695531.68 | E5: 0 | F5: 695531.68 | G5: 0 | H5: 695531.68 | I5: 0 | J5: 695531.68 | K5: 0 | L5: 695531.68 | M5: 0 | N5: 695531.68 | O5: 0 | P5: 695531.68 | Q5: 0 | R5: 695531.68 | S5: 0 | T5: 695531.68 | U5: 0 | V5: 695531.68 | W5: 0 | X5: 695531.68 | Y5: 0 | Z5: 695531.68 | AA5: 0 | AB5: =D5+F5+H5+J5+L5+N5+P5+R5+T5+V5+X5+Z5 -> 8346380.2
B6: 400-002-000-00 | C6: Descuentos | D6: -18444.425 | E6: 0 | F6: -18423.995 | G6: 0 | H6: -18402.897 | I6: 0 | J6: -18493.591 | K6: 0 | L6: -19741.292 | M6: 0 | N6: -18391.145 | O6: 0 | P6: -18402.073 | Q6: 0 | R6: -18545.187 | S6: 0 | T6: -18954.145 | U6: 0 | V6: -12255.603 | W6: 0 | X6: -12255.603 | Y6: 0 | Z6: -12264.267 | AA6: 0 | AB6: =D6+F6+H6+J6+L6+N6+P6+R6+T6+V6+X6+Z6 -> -204574.22
B7: 400-005-000-00 | C7: Socios Nuevos | D7: 260871.54 | E7: 0 | F7: 260871.54 | G7: 0 | H7: 260871.54 | I7: 0 | J7: 260871.54 | K7: 0 | L7: 260871.54 | M7: 0 | N7: 260871.54 | O7: 0 | P7: 260871.54 | Q7: 0 | R7: 260871.54 | S7: 0 | T7: 260871.54 | U7: 0 | V7: 260871.54 | W7: 0 | X7: 260871.54 | Y7: 0 | Z7: 260871.54 | AA7: 0 | AB7: =D7+F7+H7+J7+L7+N7+P7+R7+T7+V7+X7+Z7 -> 3130458.5
B8: 401-001-000-00 | C8: Cuotas Suscripción | D8: 42036 | E8: 0 | F8: 74015 | G8: 0 | H8: 25425 | I8: 0 | J8: 27685 | K8: 0 | L8: 0 | M8: 0 | N8: 33335 | O8: 0 | P8: 33335 | Q8: 0 | R8: 18419 | S8: 0 | T8: 34804 | U8: 0 | V8: 67800 | W8: 0 | X8: 80230 | Y8: 0 | Z8: 73450 | AA8: 0 | AB8: =D8+F8+H8+J8+L8+N8+P8+R8+T8+V8+X8+Z8 -> 510534
C9: Suma de Ingresos Membresía | D9: =SUM(D5:D8) -> 979994.8 | E9: =SUM(E5:E8) -> 0 | F9: =SUM(F5:F8) -> 1011994.2 | G9: =SUM(G5:G8) -> 0 | H9: =SUM(H5:H8) -> 963425.32 | I9: =SUM(I5:I8) -> 0 | J9: =SUM(J5:J8) -> 965594.63 | K9: =SUM(K5:K8) -> 0 | ... AB9: =SUM(AB5:AB8) -> 11782798
C11: Gastos Membresía
B12: 702-002-000-00 | C12: Herramienta Sales Force | D12: 0 | E12: 0 | F12: 0 | G12: 0 | H12: 0 | I12: 0 | J12: 0 | K12: 0 | L12: 0 | M12: 0 | N12: 0 | O12: 0 | P12: 0 | Q12: 0 | R12: 0 | S12: 0 | T12: 0 | U12: 0 | V12: 0 | W12: 0 | X12: 0 | Y12: 0 | Z12: 0 | AA12: 0 | AB12: =D12+F12+H12+J12+L12+N12+P12+R12+T12+V12+X12+Z12 -> 0
B13: 503-000-000-00 | C13: Comisiones KAM´s | D13: 38293.58 | E13: 0 | F13: 38293.58 | G13: 0 | H13: 38293.58 | I13: 0 | J13: 38293.58 | K13: 0 | L13: 38293.58 | M13: 0 | N13: 38293.58 | O13: 0 | P13: 38293.58 | Q13: 0 | R13: 38293.58 | S13: 0 | T13: 38293.58 | U13: 0 | V13: 38293.58 | W13: 0 | X13: 38293.58 | Y13: 0 | Z13: 38293.58 | AA13: 0 | AB13: =D13+F13+H13+J13+L13+N13+P13+R13+T13+V13+X13+Z13 -> 459522.96
B14: 702-001-000-00 | C14: Desayunos promoción - Onboarding | D14: 1657.0026 | E14: 0 | F14: 1923.9636 | G14: 0 | H14: 0 | I14: 0 | J14: 860.031 | K14: 0 | L14: 0 | M14: 0 | N14: 4139.247 | O14: 0 | P14: 0 | Q14: 0 | R14: 0 | S14: 0 | T14: 2339.314 | U14: 0 | V14: 0 | W14: 0 | X14: 22600 | Y14: 0 | Z14: 0 | AA14: 0 | AB14: =D14+F14+H14+J14+L14+N14+P14+R14+T14+V14+X14+Z14 -> 33519.558
C15: Suma de Gastos Membresía | D15: =SUM(D12:D14) -> 39950.583 | E15: =SUM(E12:E14) -> 0 | F15: =SUM(F12:F14) -> 40217.544 | G15: =SUM(G12:G14) -> 0 | H15: =SUM(H12:H14) -> 38293.58 | I15: =SUM(I12:I14) -> 0 | J15: =SUM(J12:J14) -> 39153.611 | K15: =SUM(K12:K14) -> 0 | ... AB15: =SUM(AB12:AB14) -> 493042.52
C18: Resultado Membresía | D18: =+D9-D15 -> 940044.21 | E18: =+E9-E15 -> 0 | F18: =+F9-F15 -> 971776.68 | G18: =+G9-G15 -> 0 | H18: =+H9-H15 -> 925131.74 | I18: =+I9-I15 -> 0 | J18: =+J9-J15 -> 926441.02 | K18: =+K9-K15 -> 0 | ... AB18: =+AB9-AB15 -> 11289756

Sheet Comités
C2: COMITÉS | D2: 46023 | E2: 46023 | F2: 46054 | G2: 46054 | H2: 46082 | I2: 46082 | J2: 46113 | K2: 46113 | L2: 46143 | M2: 46143 | N2: 46174 | O2: 46174 | P2: 46204 | Q2: 46204 | R2: 46235 | S2: 46235 | T2: 46266 | U2: 46266 | V2: 46296 | W2: 46296 | X2: 46327 | Y2: 46327 | Z2: 46357 | AA2: 46357 | AB2: 2026
AC3: Agregan Steering Group en Ig. $0 y Eg. $5K
C4: Ingresos Comités | AC4: Agregan Diversidad e Inclusión en Ig. $0 y Eg. $5K
B5: 404-017-000-00 | C5: Agroindustria | D5: 0 | E5: 0 | F5: 0 | G5: 0 | H5: 0 | I5: 0 | J5: 0 | K5: 0 | L5: 0 | M5: 0 | N5: 0 | O5: 0 | P5: 5000 | Q5: 0 | R5: 0 | S5: 0 | T5: 0 | U5: 0 | V5: 0 | W5: 0 | X5: 0 | Y5: 0 | Z5: 0 | AA5: 0 | AB5: =D5+F5+H5+J5+L5+N5+P5+R5+T5+V5+X5+Z5 -> 5000 | AC5: Ig. Y Eg. $5K anuales
B6: 404-005-000-00 | C6: Asuntos Fiscales | D6: 13500 | E6: 0 | F6: 13500 | G6: 0 | H6: 13500 | I6: 0 | J6: 13500 | K6: 0 | L6: 13500 | M6: 0 | N6: 13500 | O6: 0 | P6: 13500 | Q6: 0 | R6: 13500 | S6: 0 | T6: 13500 | U6: 0 | V6: 13500 | W6: 0 | X6: 13500 | Y6: 0 | Z6: 0 | AA6: 0 | AB6: =D6+F6+H6+J6+L6+N6+P6+R6+T6+V6+X6+Z6 -> 148500 | AC6: Ig. $148.5K y Eg. $132K anuales
B7: 404-001-000-00 | C7: Capital Humano y Asuntos Laborales | D7: 13500 | E7: 0 | F7: 13500 | G7: 0 | H7: 13500 | I7: 0 | J7: 13500 | K7: 0 | L7: 13500 | M7: 0 | N7: 13500 | O7: 0 | P7: 13500 | Q7: 0 | R7: 13500 | S7: 0 | T7: 13500 | U7: 0 | V7: 13500 | W7: 0 | X7: 13500 | Y7: 0 | Z7: 0 | AA7: 0 | AB7: =D7+F7+H7+J7+L7+N7+P7+R7+T7+V7+X7+Z7 -> 148500 | AC7: Ig. $148.5K y Eg. $132K anuales
B8: 404-012-000-00 | C8: Diversidad e Inclusión | D8: 0 | E8: 0 | F8: 0 | G8: 0 | H8: 0 | I8: 0 | J8: 0 | K8: 0 | L8: 0 | M8: 0 | N8: 0 | O8: 0 | P8: 0 | Q8: 0 | R8: 0 | S8: 0 | T8: 0 | U8: 0 | V8: 0 | W8: 0 | X8: 0 | Y8: 0 | Z8: 0 | AA8: 0 | AB8: =D8+F8+H8+J8+L8+N8+P8+R8+T8+V8+X8+Z8 -> 0
B9: 404-003-000-00 | C9: Comercio Exterior y Logística | D9: 13500 | E9: 0 | F9: 13500 | G9: 0 | H9: 13500 | I9: 0 | J9: 13500 | K9: 0 | L9: 13500 | M9: 0 | N9: 13500 | O9: 0 | P9: 13500 | Q9: 0 | R9: 13500 | S9: 0 | T9: 13500 | U9: 0 | V9: 13500 | W9: 0 | X9: 13500 | Y9: 0 | Z9: 0 | AA9: 0 | AB9: =D9+F9+H9+J9+L9+N9+P9+R9+T9+V9+X9+Z9 -> 148500 | AC9: Ig. $148.5K y Eg. $132K anuales
B10: 404-013-000-00 | C10: Innovación y TICs | D10: 0 | E10: 0 | F10: 0 | G10: 0 | H10: 0 | I10: 0 | J10: 0 | K10: 0 | L10: 0 | M10: 0 | N10: 0 | O10: 0 | P10: 0 | Q10: 0 | R10: 0 | S10: 0 | T10: 0 | U10: 0 | V10: 0 | W10: 0 | X10: 0 | Y10: 0 | Z10: 0 | AA10: 0 | AB10: =D10+F10+H10+J10+L10+N10+P10+R10+T10+V10+X10+Z10 -> 0 | AC10: Ig. $0 y Eg. $0 anuales
B11: 404-007-000-00 | C11: Legalidad y Estado de Derecho | D11: 0 | E11: 0 | F11: 0 | G11: 0 | H11: 0 | I11: 0 | J11: 0 | K11: 0 | L11: 0 | M11: 0 | N11: 0 | O11: 0 | P11: 0 | Q11: 0 | R11: 0 | S11: 0 | T11: 0 | U11: 0 | V11: 0 | W11: 0 | X11: 0 | Y11: 0 | Z11: 0 | AA11: 0 | AB11: =D11+F11+H11+J11+L11+N11+P11+R11+T11+V11+X11+Z11 -> 0 | AC11: Ig. $0 y Eg. $0 anuales
B12: 404-016-000-00 | C12: Salud | D12: 0 | E12: 0 | F12: 0 | G12: 0 | H12: 0 | I12: 0 | J12: 0 | K12: 0 | L12: 0 | M12: 0 | N12: 0 | O12: 0 | P12: 0 | Q12: 0 | R12: 0 | S12: 0 | T12: 0 | U12: 0 | V12: 0 | W12: 0 | X12: 0 | Y12: 0 | Z12: 0 | AA12: 0 | AB12: =D12+F12+H12+J12+L12+N12+P12+R12+T12+V12+X12+Z12 -> 0 | AC12: Ig. $0 y Eg. $0 anuales
B13: 404-004-000-00 | C13: Seguridad | D13: 0 | E13: 0 | F13: 0 | G13: 0 | H13: 0 | I13: 0 | J13: 0 | K13: 0 | L13: 0 | M13: 0 | N13: 0 | O13: 0 | P13: 0 | Q13: 0 | R13: 0 | S13: 0 | T13: 0 | U13: 0 | V13: 0 | W13: 0 | X13: 0 | Y13: 0 | Z13: 0 | AA13: 0 | AB13: =D13+F13+H13+J13+L13+N13+P13+R13+T13+V13+X13+Z13 -> 0 | AC13: Ig. $0 y Eg. $0 anuales
B14: 404-008-000-00 | C14: Sustentabilidad y Responsabilidad Social | D14: 0 | E14: 0 | F14: 0 | G14: 0 | H14: 0 | I14: 0 | J14: 0 | K14: 0 | L14: 0 | M14: 0 | N14: 0 | O14: 0 | P14: 0 | Q14: 0 | R14: 0 | S14: 0 | T14: 0 | U14: 0 | V14: 0 | W14: 0 | X14: 0 | Y14: 0 | Z14: 0 | AA14: 0 | AB14: =D14+F14+H14+J14+L14+N14+P14+R14+T14+V14+X14+Z14 -> 0 | AC14: Ig. $0 y Eg. $0 anuales
B15: 404-009-000-00 | C15: Turismo | D15: 0 | E15: 0 | F15: 0 | G15: 0 | H15: 0 | I15: 0 | J15: 0 | K15: 0 | L15: 0 | M15: 0 | N15: 0 | O15: 0 | P15: 0 | Q15: 0 | R15: 0 | S15: 0 | T15: 0 | U15: 0 | V15: 0 | W15: 0 | X15: 0 | Y15: 0 | Z15: 0 | AA15: 0 | AB15: =D15+F15+H15+J15+L15+N15+P15+R15+T15+V15+X15+Z15 -> 0 | AC15: Ig. $0 y Eg. $0 anuales
B16: 404-018-000-00 | C16: Programa de Mentoría (EWDP) | D16: 0 | E16: 0 | F16: 0 | G16: 0 | H16: 0 | I16: 0 | J16: 0 | K16: 0 | L16: =71500+71428.57 -> 142928.57 | M16: 0 | N16: =215416.66+71428.57 -> 286845.23 | O16: 0 | P16: =167749.99+71428.57 -> 239178.56 | Q16: 0 | R16: =11916.66+71428.57+100000 -> 183345.23 | S16: 0 | T16: =11916.66+71428.57 -> 83345.23 | U16: 0 | V16: =0+71428.57 -> 71428.57 | W16: 0 | X16: =0+71428.57 -> 71428.57 | Y16: 0 | Z16: 0 | AA16: 0 | AB16: =D16+F16+H16+J16+L16+N16+P16+R16+T16+V16+X16+Z16 -> 1078500 | AC16: Quedan igual
C17: Suma de Ingresos Comités | D17: =SUM(D5:D16) -> 40500 | E17: =SUM(E5:E16) -> 0 | F17: =SUM(F5:F16) -> 40500 | G17: =SUM(G5:G16) -> 0 | H17: =SUM(H5:H16) -> 40500 | I17: =SUM(I5:I16) -> 0 | J17: =SUM(J5:J16) -> 40500 | K17: =SUM(K5:K16) -> 0 | ... AB17: =SUM(AB5:AB16) -> 1529000
C19: Gastos Comités
B20: 502-014-000-00 | C20: Agroindustria | D20: 0 | E20: 0 | F20: 500 | G20: 0 | H20: 500 | I20: 0 | J20: 500 | K20: 0 | L20: 500 | M20: 0 | N20: 500 | O20: 0 | P20: 500 | Q20: 0 | R20: 500 | S20: 0 | T20: 500 | U20: 0 | V20: 500 | W20: 0 | X20: 500 | Y20: 0 | Z20: 0 | AA20: 0 | AB20: =D20+F20+H20+J20+L20+N20+P20+R20+T20+V20+X20+Z20 -> 5000
B21: 502-005-000-00 | C21: Asuntos Fiscales | D21: 12000 | E21: 0 | F21: 12000 | G21: 0 | H21: 12000 | I21: 0 | J21: 12000 | K21: 0 | L21: 12000 | M21: 0 | N21: 12000 | O21: 0 | P21: 12000 | Q21: 0 | R21: 12000 | S21: 0 | T21: 12000 | U21: 0 | V21: 12000 | W21: 0 | X21: 12000 | Y21: 0 | Z21: 0 | AA21: 0 | AB21: =D21+F21+H21+J21+L21+N21+P21+R21+T21+V21+X21+Z21 -> 132000
B22: 502-001-000-00 | C22: Capital Humano y Asuntos Laborales | D22: 12000 | E22: 0 | F22: 12000 | G22: 0 | H22: 12000 | I22: 0 | J22: 12000 | K22: 0 | L22: 12000 | M22: 0 | N22: 12000 | O22: 0 | P22: 12000 | Q22: 0 | R22: 12000 | S22: 0 | T22: 12000 | U22: 0 | V22: 12000 | W22: 0 | X22: 12000 | Y22: 0 | Z22: 0 | AA22: 0 | AB22: =D22+F22+H22+J22+L22+N22+P22+R22+T22+V22+X22+Z22 -> 132000
B23: 502-008-000-00 | C23: Diversidad e Inclusión | D23: 0 | E23: 0 | F23: 500 | G23: 0 | H23: 500 | I23: 0 | J23: 500 | K23: 0 | L23: 500 | M23: 0 | N23: 500 | O23: 0 | P23: 500 | Q23: 0 | R23: 500 | S23: 0 | T23: 500 | U23: 0 | V23: 500 | W23: 0 | X23: 500 | Y23: 0 | Z23: 0 | AA23: 0 | AB23: =D23+F23+H23+J23+L23+N23+P23+R23+T23+V23+X23+Z23 -> 5000
B24: 502-003-000-00 | C24: Comercio Exterior y Logística | D24: 12000 | E24: 0 | F24: 12000 | G24: 0 | H24: 12000 | I24: 0 | J24: 12000 | K24: 0 | L24: 12000 | M24: 0 | N24: 12000 | O24: 0 | P24: 12000 | Q24: 0 | R24: 12000 | S24: 0 | T24: 12000 | U24: 0 | V24: 12000 | W24: 0 | X24: 12000 | Y24: 0 | Z24: 0 | AA24: 0 | AB24: =D24+F24+H24+J24+L24+N24+P24+R24+T24+V24+X24+Z24 -> 132000
B25: 502-013-000-00 | C25: Innovación y TICs | D25: 0 | E25: 0 | F25: 500 | G25: 0 | H25: 500 | I25: 0 | J25: 500 | K25: 0 | L25: 500 | M25: 0 | N25: 500 | O25: 0 | P25: 500 | Q25: 0 | R25: 500 | S25: 0 | T25: 500 | U25: 0 | V25: 500 | W25: 0 | X25: 500 | Y25: 0 | Z25: 0 | AA25: 0 | AB25: =D25+F25+H25+J25+L25+N25+P25+R25+T25+V25+X25+Z25 -> 5000
B26: 502-007-000-00 | C26: Legalidad y Estado de Derecho | D26: 0 | E26: 0 | F26: 500 | G26: 0 | H26: 500 | I26: 0 | J26: 500 | K26: 0 | L26: 500 | M26: 0 | N26: 500 | O26: 0 | P26: 500 | Q26: 0 | R26: 500 | S26: 0 | T26: 500 | U26: 0 | V26: 500 | W26: 0 | X26: 500 | Y26: 0 | Z26: 0 | AA26: 0 | AB26: =D26+F26+H26+J26+L26+N26+P26+R26+T26+V26+X26+Z26 -> 5000
B27: 502-016-000-00 | C27: Salud | D27: 0 | E27: 0 | F27: 500 | G27: 0 | H27: 500 | I27: 0 | J27: 500 | K27: 0 | L27: 500 | M27: 0 | N27: 500 | O27: 0 | P27: 500 | Q27: 0 | R27: 500 | S27: 0 | T27: 500 | U27: 0 | V27: 500 | W27: 0 | X27: 500 | Y27: 0 | Z27: 0 | AA27: 0 | AB27: =D27+F27+H27+J27+L27+N27+P27+R27+T27+V27+X27+Z27 -> 5000
B28: 502-004-000-00 | C28: Seguridad | D28: 0 | E28: 0 | F28: 500 | G28: 0 | H28: 500 | I28: 0 | J28: 500 | K28: 0 | L28: 500 | M28: 0 | N28: 500 | O28: 0 | P28: 500 | Q28: 0 | R28: 500 | S28: 0 | T28: 500 | U28: 0 | V28: 500 | W28: 0 | X28: 500 | Y28: 0 | Z28: 0 | AA28: 0 | AB28: =D28+F28+H28+J28+L28+N28+P28+R28+T28+V28+X28+Z28 -> 5000
B29: 502-002-000-00 | C29: Sustentabilidad y Responsabilidad Social | D29: 0 | E29: 0 | F29: 500 | G29: 0 | H29: 500 | I29: 0 | J29: 500 | K29: 0 | L29: 500 | M29: 0 | N29: 500 | O29: 0 | P29: 500 | Q29: 0 | R29: 500 | S29: 0 | T29: 500 | U29: 0 | V29: 500 | W29: 0 | X29: 500 | Y29: 0 | Z29: 0 | AA29: 0 | AB29: =D29+F29+H29+J29+L29+N29+P29+R29+T29+V29+X29+Z29 -> 5000
B30: 502-009-000-00 | C30: Turismo | D30: 0 | E30: 0 | F30: 500 | G30: 0 | H30: 500 | I30: 0 | J30: 500 | K30: 0 | L30: 500 | M30: 0 | N30: 500 | O30: 0 | P30: 500 | Q30: 0 | R30: 500 | S30: 0 | T30: 500 | U30: 0 | V30: 500 | W30: 0 | X30: 500 | Y30: 0 | Z30: 0 | AA30: 0 | AB30: =D30+F30+H30+J30+L30+N30+P30+R30+T30+V30+X30+Z30 -> 5000
B31: 502-010-000-00 | C31: Steering Group | D31: 0 | F31: 500 | G31: 0 | H31: 500 | I31: 0 | J31: 500 | K31: 0 | L31: 500 | M31: 0 | N31: 500 | O31: 0 | P31: 500 | Q31: 0 | R31: 500 | S31: 0 | T31: 500 | U31: 0 | V31: 500 | W31: 0 | X31: 500 | Y31: 0 | Z31: 0 | AA31: 0 | AB31: =D31+F31+H31+J31+L31+N31+P31+R31+T31+V31+X31+Z31 -> 5000
B32: 502-017-000-00 | C32: Programa de Mentoría (EWDP) | D32: 0 | E32: 0 | F32: 0 | G32: 0 | H32: 0 | I32: 0 | J32: 0 | K32: 0 | L32: 357564.9 | M32: 0 | N32: 3352.745 | O32: 0 | P32: 4062.531 | Q32: 0 | R32: 72123.964 | S32: 0 | T32: 5170.869 | U32: 0 | V32: 0 | W32: 0 | X32: 0 | Y32: 0 | Z32: 44000 | AA32: 0 | AB32: =D32+F32+H32+J32+L32+N32+P32+R32+T32+V32+X32+Z32 -> 486275.01 | AC32: Quedan igual
C33: Suma de Gastos Comités | D33: =SUM(D20:D32) -> 36000 | E33: =SUM(E20:E32) -> 0 | F33: =SUM(F20:F32) -> 40500 | G33: =SUM(G20:G32) -> 0 | H33: =SUM(H20:H32) -> 40500 | I33: =SUM(I20:I32) -> 0 | J33: =SUM(J20:J32) -> 40500 | K33: =SUM(K20:K32) -> 0 | ... AB33: =SUM(AB20:AB32) -> 927275.01
C35: Resultado Operativo Comités | D35: =+D17-D33 -> 4500 | E35: =+E17-E33 -> 0 | F35: =+F17-F33 -> 0 | G35: =+G17-G33 -> 0 | H35: =+H17-H33 -> 0 | I35: =+I17-I33 -> 0 | J35: =+J17-J33 -> 0 | K35: =+K17-K33 -> 0 | ... AB35: =+AB17-AB33 -> 601724.95
B37: 504-000-000-00 | C37: Comisiones EWDP | D37: 0 | E37: 0 | F37: 0 | G37: 0 | H37: 0 | I37: 0 | J37: 0 | K37: 0 | L37: 0 | M37: 0 | N37: 0 | O37: 0 | P37: 0 | Q37: 0 | R37: 0 | S37: 0 | T37: 0 | U37: 0 | V37: 0 | W37: 0 | X37: 0 | Y37: 0 | Z37: 0 | AA37: 0 | AB37: =D37+F37+H37+J37+L37+N37+P37+R37+T37+V37+X37+Z37 -> 0
C39: Resultado Comités | D39: =D35-D37 -> 4500 | E39: =E35-E37 -> 0 | F39: =F35-F37 -> 0 | G39: =G35-G37 -> 0 | H39: =H35-H37 -> 0 | I39: =I35-I37 -> 0 | J39: =J35-J37 -> 0 | K39: =K35-K37 -> 0 | ... AB39: =AB35-AB37 -> 601724.95 | AC39: $512K
AB41: =AB17+'Dirección'!AB7 -> 1594590.7
C42: Nota: Los eventos y comités deberán presupuestarse al menos en punto de equilibrio. | AB42: =AB33+'Dirección'!AB12 -> 1004784.9

Sheet T&IC
C2: Trade & Investment Center | D2: 46023 | E2: 46023 | F2: 46054 | G2: 46054 | H2: 46082 | I2: 46082 | J2: 46113 | K2: 46113 | L2: 46143 | M2: 46143 | N2: 46174 | O2: 46174 | P2: 46204 | Q2: 46204 | R2: 46235 | S2: 46235 | T2: 46266 | U2: 46266 | V2: 46296 | W2: 46296 | X2: 46327 | Y2: 46327 | Z2: 46357 | AA2: 46357 | AB2: 2026
C4: Ingresos T&IC
AC5: No se considera Selec USA
B6: 407-001-000-00 | C6: SemiconWest | D6: 0 | E6: 0 | F6: 0 | G6: 0 | H6: 0 | I6: 0 | J6: 0 | K6: 0 | L6: 0 | M6: 0 | N6: 0 | O6: 0 | P6: 0 | Q6: 0 | R6: 0 | S6: 0 | T6: 0 | U6: 0 | V6: 50000 | W6: 0 | X6: 0 | Y6: 0 | Z6: 0 | AA6: 0 | AB6: =D6+F6+H6+J6+L6+N6+P6+R6+T6+V6+X6+Z6 -> 50000 | AC6: Cierran en $50K | AE6: No procede
B7: 407-002-000-00 | C7: Ingresos 2 | D7: 0 | E7: 0 | F7: 0 | G7: 0 | H7: 0 | I7: 0 | J7: 0 | K7: 0 | L7: 0 | M7: 0 | N7: 0 | O7: 0 | P7: 0 | Q7: 0 | R7: 0 | S7: 0 | T7: 0 | U7: 0 | V7: 0 | W7: 0 | X7: 0 | Y7: 0 | Z7: 0 | AA7: 0 | AB7: =D7+F7+H7+J7+L7+N7+P7+R7+T7+V7+X7+Z7 -> 0
C8: Suma de Ingresos T&IC | D8: =SUM(D6:D7) -> 0 | E8: =SUM(E6:E7) -> 0 | F8: =SUM(F6:F7) -> 0 | G8: =SUM(G6:G7) -> 0 | H8: =SUM(H6:H7) -> 0 | I8: =SUM(I6:I7) -> 0 | J8: =SUM(J6:J7) -> 0 | K8: =SUM(K6:K7) -> 0 | ... AB8: =SUM(AB6:AB7) -> 50000
C10: Gastos T&IC
B11: 703-001-000-00 | C11: SemiconWest | D11: 0 | E11: 0 | F11: 0 | G11: 0 | H11: 0 | I11: 0 | J11: 0 | K11: 0 | L11: 0 | M11: 0 | N11: 0 | O11: 0 | P11: 0 | Q11: 0 | R11: 0 | S11: 0 | T11: 0 | U11: 0 | V11: 25000 | W11: 0 | X11: 0 | Y11: 0 | Z11: 0 | AA11: 0 | AB11: =D11+F11+H11+J11+L11+N11+P11+R11+T11+V11+X11+Z11 -> 25000 | AC11: Cierran en $25K | AE11: No procede
B12: 703-002-000-00 | C12: Gastos 2 | D12: 0 | E12: 0 | F12: 0 | G12: 0 | H12: 0 | I12: 0 | J12: 0 | K12: 0 | L12: 0 | M12: 0 | N12: 0 | O12: 0 | P12: 0 | Q12: 0 | R12: 0 | S12: 0 | T12: 0 | U12: 0 | V12: 0 | W12: 0 | X12: 0 | Y12: 0 | Z12: 0 | AA12: 0 | AB12: =D12+F12+H12+J12+L12+N12+P12+R12+T12+V12+X12+Z12 -> 0
C13: Suma de Gastos T&IC | D13: =SUM(D11:D12) -> 0 | E13: =SUM(E11:E12) -> 0 | F13: =SUM(F11:F12) -> 0 | G13: =SUM(G11:G12) -> 0 | H13: =SUM(H11:H12) -> 0 | I13: =SUM(I11:I12) -> 0 | J13: =SUM(J11:J12) -> 0 | K13: =SUM(K11:K12) -> 0 | ... AB13: =SUM(AB11:AB12) -> 25000
C16: Resultado T&IC | D16: =D8-D13 -> 0 | E16: =E8-E13 -> 0 | F16: =F8-F13 -> 0 | G16: =G8-G13 -> 0 | H16: =H8-H13 -> 0 | I16: =I8-I13 -> 0 | J16: =J8-J13 -> 0 | K16: =K8-K13 -> 0 | ... AB16: =AB8-AB13 -> 25000 | AC16: $25K

Sheet Eventos
C2: EVENTOS | D2: 46023 | E2: 46023 | F2: 46054 | G2: 46054 | H2: 46082 | I2: 46082 | J2: 46113 | K2: 46113 | L2: 46143 | M2: 46143 | N2: 46174 | O2: 46174 | P2: 46204 | Q2: 46204 | R2: 46235 | S2: 46235 | T2: 46266 | U2: 46266 | V2: 46296 | W2: 46296 | X2: 46327 | Y2: 46327 | Z2: 46357 | AA2: 46357 | AB2: 2026
C4: Ingresos Eventos
C5: Boletaje
B6: 405-002-000-00 | C6: Asamblea Anual | D6: 0 | E6: 0 | F6: 0 | G6: 0 | H6: 220000 | I6: 0 | J6: 30000 | K6: 0 | L6: 0 | M6: 0 | N6: 0 | O6: 0 | P6: 0 | Q6: 0 | R6: 0 | S6: 0 | T6: 0 | U6: 0 | V6: 0 | W6: 0 | X6: 0 | Y6: 0 | Z6: 0 | AA6: 0 | AB6: =D6+F6+H6+J6+L6+N6+P6+R6+T6+V6+X6+Z6 -> 250000 | AD6: =AB6+AB21-AB38 -> 150000
B7: 405-001-000-00 | C7: Torneo Golf | D7: 475000 | E7: 0 | F7: 25000 | G7: 0 | H7: 0 | I7: 0 | J7: 0 | K7: 0 | L7: 0 | M7: 0 | N7: 0 | O7: 0 | P7: 0 | Q7: 0 | R7: 0 | S7: 0 | T7: 0 | U7: 0 | V7: 0 | W7: 0 | X7: 0 | Y7: 0 | Z7: 0 | AA7: 0 | AB7: =D7+F7+H7+J7+L7+N7+P7+R7+T7+V7+X7+Z7 -> 500000 | AD7: =AB7+AB22-AB39 -> 150000
B8: 405-009-000-00 | C8: Cumbre Empresarios | D8: 0 | E8: 0 | F8: 0 | G8: 0 | H8: 0 | I8: 0 | J8: 0 | K8: 0 | L8: 0 | M8: 0 | N8: 0 | O8: 0 | P8: 0 | Q8: 0 | R8: 0 | S8: 0 | T8: 0 | U8: 0 | V8: 90000 | W8: 0 | X8: 10000 | Y8: 0 | Z8: 0 | AA8: 0 | AB8: =D8+F8+H8+J8+L8+N8+P8+R8+T8+V8+X8+Z8 -> 100000 | AD8: =AB8+AB23-AB40 -> 150000
B9: 405-010-000-00 | C9: Foros (Talento) | D9: 0 | E9: 0 | F9: 0 | G9: 0 | H9: 60000 | I9: 0 | J9: 0 | K9: 0 | L9: 0 | M9: 0 | N9: 0 | O9: 0 | P9: 0 | Q9: 0 | R9: 0 | S9: 0 | T9: 0 | U9: 0 | V9: 0 | W9: 0 | X9: 0 | Y9: 0 | Z9: 0 | AA9: 0 | AB9: =D9+F9+H9+J9+L9+N9+P9+R9+T9+V9+X9+Z9 -> 60000 | AD9: =AB9+AB24-AB41 -> 120000
B10: 405-013-000-00 | C10: The North America Week | D10: 0 | E10: 0 | F10: 0 | G10: 0 | H10: 0 | I10: 0 | J10: 0 | K10: 0 | L10: 35000 | M10: 0 | N10: 5000 | O10: 0 | P10: 0 | Q10: 0 | R10: 0 | S10: 0 | T10: 0 | U10: 0 | V10: 0 | W10: 0 | X10: 0 | Y10: 0 | Z10: 0 | AA10: 0 | AB10: =D10+F10+H10+J10+L10+N10+P10+R10+T10+V10+X10+Z10 -> 40000 | AD10: =AB10+AB25-AB42 -> 150000
B11: 405-014-000-00 | C11: Jalisco Travel Fest | D11: 0 | E11: 0 | F11: 0 | G11: 0 | H11: 0 | I11: 0 | J11: 0 | K11: 0 | L11: 40000 | M11: 0 | N11: 0 | O11: 0 | P11: 0 | Q11: 0 | R11: 0 | S11: 0 | T11: 0 | U11: 0 | V11: 0 | W11: 0 | X11: 0 | Y11: 0 | Z11: 0 | AA11: 0 | AB11: =D11+F11+H11+J11+L11+N11+P11+R11+T11+V11+X11+Z11 -> 40000 | AD11: =AB11+AB26-AB43 -> 110000
B12: 405-005-000-00 | C12: Open House | D12: 0 | E12: 0 | F12: 0 | G12: 0 | H12: 0 | I12: 0 | J12: 0 | K12: 0 | L12: 0 | M12: 0 | N12: 0 | O12: 0 | P12: 0 | Q12: 0 | R12: 0 | S12: 0 | T12: 0 | U12: 0 | V12: 0 | W12: 0 | X12: 0 | Y12: 0 | Z12: 0 | AA12: 0 | AB12: =D12+F12+H12+J12+L12+N12+P12+R12+T12+V12+X12+Z12 -> 0 | AD12: =AB12+AB27-AB44 -> 150000
B13: 405-007-000-00 | C13: Extend Our Reach | D13: 0 | E13: 0 | F13: 0 | G13: 0 | H13: 0 | I13: 0 | J13: 0 | K13: 0 | L13: 0 | M13: 0 | N13: 0 | O13: 0 | P13: 0 | Q13: 0 | R13: 0 | S13: 0 | T13: 0 | U13: 0 | V13: 0 | W13: 0 | X13: 0 | Y13: 0 | Z13: 0 | AA13: 0 | AB13: =D13+F13+H13+J13+L13+N13+P13+R13+T13+V13+X13+Z13 -> 0 | AD13: =AB13+AB28-AB45 -> 0
B14: 405-004-000-00 | C14: Cocteles | D14: 0 | E14: 0 | F14: 0 | G14: 0 | H14: 0 | I14: 0 | J14: 0 | K14: 0 | L14: 0 | M14: 0 | N14: 0 | O14: 0 | P14: 0 | Q14: 0 | R14: 0 | S14: 0 | T14: 0 | U14: 0 | V14: 0 | W14: 0 | X14: 0 | Y14: 0 | Z14: 0 | AA14: 0 | AB14: =D14+F14+H14+J14+L14+N14+P14+R14+T14+V14+X14+Z14 -> 0 | AD14: =AB14+AB29-AB46 -> 0
B15: 405-015-000-00 | C15: Cena Gala | D15: 0 | E15: 0 | F15: 0 | G15: 0 | H15: 0 | I15: 0 | J15: 0 | K15: 0 | L15: 0 | M15: 0 | N15: 0 | O15: 0 | P15: 0 | Q15: 0 | R15: 0 | S15: 0 | T15: 0 | U15: 0 | V15: 0 | W15: 0 | X15: 0 | Y15: 0 | Z15: 200000 | AA15: 0 | AB15: =D15+F15+H15+J15+L15+N15+P15+R15+T15+V15+X15+Z15 -> 200000 | AD15: =AB15+AB30-AB47 -> 150000
B16: 405-016-000-00 | C16: Top Circle | D16: 0 | E16: 0 | F16: 0 | G16: 0 | H16: 0 | I16: 0 | J16: 0 | K16: 0 | L16: 0 | M16: 0 | N16: 0 | O16: 0 | P16: 0 | Q16: 0 | R16: 0 | S16: 0 | T16: 0 | U16: 0 | V16: 0 | W16: 0 | X16: 0 | Y16: 0 | Z16: 0 | AA16: 0 | AB16: =D16+F16+H16+J16+L16+N16+P16+R16+T16+V16+X16+Z16 -> 0 | AD16: =AB16+AB31-AB49 -> 50000
B17: 405-012-000-00 | C17: Jornada de Reforestación | D17: 0 | E17: 0 | F17: 0 | G17: 0 | H17: 0 | I17: 0 | J17: 0 | K17: 0 | L17: 0 | M17: 0 | N17: 0 | O17: 0 | P17: 0 | Q17: 0 | R17: 0 | S17: 0 | T17: 0 | U17: 0 | V17: 0 | W17: 0 | X17: 0 | Y17: 0 | Z17: 0 | AA17: 0 | AB17: =D17+F17+H17+J17+L17+N17+P17+R17+T17+V17+X17+Z17 -> 0 | AD17: =AB17+AB32-AB49 -> 0
C18: Ingresos Boletaje | D18: =SUM(D6:D17) -> 475000 | E18: =SUM(E6:E17) -> 0 | F18: =SUM(F6:F17) -> 25000 | G18: =SUM(G6:G17) -> 0 | H18: =SUM(H6:H17) -> 280000 | I18: =SUM(I6:I17) -> 0 | J18: =SUM(J6:J17) -> 30000 | K18: =SUM(K6:K17) -> 0 | ... AB18: =SUM(AB6:AB17) -> 1190000
C20: Patrocinios
B21: 406-002-000-00 | C21: Asamblea Anual | D21: 0 | E21: 0 | F21: 0 | G21: 0 | H21: 300000 | I21: 0 | J21: 50000 | K21: 0 | L21: 0 | M21: 0 | N21: 0 | O21: 0 | P21: 0 | Q21: 0 | R21: 0 | S21: 0 | T21: 0 | U21: 0 | V21: 0 | W21: 0 | X21: 0 | Y21: 0 | Z21: 0 | AA21: 0 | AB21: =D21+F21+H21+J21+L21+N21+P21+R21+T21+V21+X21+Z21 -> 350000
B22: 406-001-000-00 | C22: Torneo Golf | D22: 450000 | E22: 0 | F22: 50000 | G22: 0 | H22: 0 | I22: 0 | J22: 0 | K22: 0 | L22: 0 | M22: 0 | N22: 0 | O22: 0 | P22: 0 | Q22: 0 | R22: 0 | S22: 0 | T22: 0 | U22: 0 | V22: 0 | W22: 0 | X22: 0 | Y22: 0 | Z22: 0 | AA22: 0 | AB22: =D22+F22+H22+J22+L22+N22+P22+R22+T22+V22+X22+Z22 -> 500000
B23: 406-003-000-00 | C23: Cumbre Empresarios | D23: 0 | E23: 0 | F23: 0 | G23: 0 | H23: 0 | I23: 0 | J23: 0 | K23: 0 | L23: 0 | M23: 0 | N23: 0 | O23: 0 | P23: 0 | Q23: 0 | R23: 0 | S23: 0 | T23: 0 | U23: 0 | V23: 300000 | W23: 0 | X23: 50000 | Y23: 0 | Z23: 0 | AA23: 0 | AB23: =D23+F23+H23+J23+L23+N23+P23+R23+T23+V23+X23+Z23 -> 350000
B24: 406-008-000-00 | C24: Foros (Talento) | D24: 0 | E24: 0 | F24: 0 | G24: 0 | H24: 180000 | I24: 0 | J24: 0 | K24: 0 | L24: 0 | M24: 0 | N24: 0 | O24: 0 | P24: 0 | Q24: 0 | R24: 0 | S24: 0 | T24: 0 | U24: 0 | V24: 0 | W24: 0 | X24: 0 | Y24: 0 | Z24: 0 | AA24: 0 | AB24: =D24+F24+H24+J24+L24+N24+P24+R24+T24+V24+X24+Z24 -> 180000
B25: 406-005-000-00 | C25: The North America Week | D25: 0 | E25: 0 | F25: 0 | G25: 0 | H25: 0 | I25: 0 | J25: 0 | K25: 0 | L25: 210000 | M25: 0 | N25: 20000 | O25: 0 | P25: 0 | Q25: 0 | R25: 0 | S25: 0 | T25: 0 | U25: 0 | V25: 0 | W25: 0 | X25: 0 | Y25: 0 | Z25: 0 | AA25: 0 | AB25: =D25+F25+H25+J25+L25+N25+P25+R25+T25+V25+X25+Z25 -> 230000
B26: 406-006-000-00 | C26: Jalisco Travel Fest | D26: 0 | E26: 0 | F26: 0 | G26: 0 | H26: 0 | I26: 0 | J26: 0 | K26: 0 | L26: 170000 | M26: 0 | N26: 0 | O26: 0 | P26: 0 | Q26: 0 | R26: 0 | S26: 0 | T26: 0 | U26: 0 | V26: 0 | W26: 0 | X26: 0 | Y26: 0 | Z26: 0 | AA26: 0 | AB26: =D26+F26+H26+J26+L26+N26+P26+R26+T26+V26+X26+Z26 -> 170000
B27: 406-009-000-00 | C27: Open House | D27: 0 | E27: 0 | F27: 100000 | G27: 0 | H27: 0 | I27: 0 | J27: 0 | K27: 0 | L27: 0 | M27: 0 | N27: 0 | O27: 0 | P27: 100000 | Q27: 0 | R27: 0 | S27: 0 | T27: 0 | U27: 0 | V27: 0 | W27: 0 | X27: 100000 | Y27: 0 | Z27: 0 | AA27: 0 | AB27: =D27+F27+H27+J27+L27+N27+P27+R27+T27+V27+X27+Z27 -> 300000
B28: 406-010-000-00 | C28: Extend Our Reach | D28: 0 | E28: 0 | F28: 0 | G28: 0 | H28: 0 | I28: 0 | J28: 0 | K28: 0 | L28: 0 | M28: 0 | N28: 0 | O28: 0 | P28: 0 | Q28: 0 | R28: 0 | S28: 0 | T28: 0 | U28: 0 | V28: 0 | W28: 0 | X28: 0 | Y28: 0 | Z28: 0 | AA28: 0 | AB28: =D28+F28+H28+J28+L28+N28+P28+R28+T28+V28+X28+Z28 -> 0
B29: 406-011-000-00 | C29: Cocteles | D29: 0 | E29: 0 | F29: 0 | G29: 0 | H29: 0 | I29: 0 | J29: 0 | K29: 0 | L29: 0 | M29: 0 | N29: 0 | O29: 0 | P29: 0 | Q29: 0 | R29: 0 | S29: 0 | T29: 0 | U29: 0 | V29: 0 | W29: 0 | X29: 0 | Y29: 0 | Z29: 0 | AA29: 0 | AB29: =D29+F29+H29+J29+L29+N29+P29+R29+T29+V29+X29+Z29 -> 0
B30: 406-014-000-00 | C30: Cena Gala | D30: 0 | E30: 0 | F30: 0 | G30: 0 | H30: 0 | I30: 0 | J30: 0 | K30: 0 | L30: 0 | M30: 0 | N30: 0 | O30: 0 | P30: 0 | Q30: 0 | R30: 0 | S30: 0 | T30: 0 | U30: 0 | V30: 0 | W30: 0 | X30: 0 | Y30: 0 | Z30: 400000 | AA30: 0 | AB30: =D30+F30+H30+J30+L30+N30+P30+R30+T30+V30+X30+Z30 -> 400000
B31: 406-015-000-00 | C31: Top Circle | D31: 0 | E31: 0 | F31: 0 | G31: 0 | H31: 0 | I31: 0 | J31: 0 | K31: 0 | L31: 0 | M31: 0 | N31: 50000 | O31: 0 | P31: 0 | Q31: 0 | R31: 0 | S31: 0 | T31: 0 | U31: 0 | V31: 50000 | W31: 0 | X31: 0 | Y31: 0 | Z31: 0 | AA31: 0 | AB31: =D31+F31+H31+J31+L31+N31+P31+R31+T31+V31+X31+Z31 -> 100000
B32: 406-013-000-00 | C32: Jornada de Reforestación | D32: 0 | E32: 0 | F32: 0 | G32: 0 | H32: 0 | I32: 0 | J32: 0 | K32: 0 | L32: 0 | M32: 0 | N32: 0 | O32: 0 | P32: 0 | Q32: 0 | R32: 50000 | S32: 0 | T32: 0 | U32: 0 | V32: 0 | W32: 0 | X32: 0 | Y32: 0 | Z32: 0 | AA32: 0 | AB32: =D32+F32+H32+J32+L32+N32+P32+R32+T32+V32+X32+Z32 -> 50000
C33: Ingresos Patrocinios | D33: =SUM(D21:D32) -> 450000 | E33: =SUM(E21:E32) -> 0 | F33: =SUM(F21:F32) -> 150000 | G33: =SUM(G21:G32) -> 0 | H33: =SUM(H21:H32) -> 480000 | I33: =SUM(I21:I32) -> 0 | J33: =SUM(J21:J32) -> 50000 | K33: =SUM(K21:K32) -> 0 | ... AA33: =SUM(AA21:AA32) -> 0 | AB33: =D33+F33+H33+J33+L33+N33+P33+R33+T33+V33+X33+Z33 -> 2630000
C35: Suma Ingresos Eventos | D35: =+D18+D33 -> 925000 | E35: =+E18+E33 -> 0 | F35: =+F18+F33 -> 175000 | G35: =+G18+G33 -> 0 | H35: =+H18+H33 -> 760000 | I35: =+I18+I33 -> 0 | J35: =+J18+J33 -> 80000 | K35: =+K18+K33 -> 0 | ... AB35: =+AB18+AB33 -> 3820000
C37: Costos y Gastos Eventos
B38: 701-002-000-00 | C38: Asamblea Anual | D38: 0 | E38: 0 | F38: 0 | G38: 0 | H38: 400000 | I38: 0 | J38: 50000 | K38: 0 | L38: 0 | M38: 0 | N38: 0 | O38: 0 | P38: 0 | Q38: 0 | R38: 0 | S38: 0 | T38: 0 | U38: 0 | V38: 0 | W38: 0 | X38: 0 | Y38: 0 | Z38: 0 | AA38: 0 | AB38: =D38+F38+H38+J38+L38+N38+P38+R38+T38+V38+X38+Z38 -> 450000
B39: 701-001-000-00 | C39: Torneo Golf | D39: 700000 | E39: 0 | F39: 150000 | G39: 0 | H39: 0 | I39: 0 | J39: 0 | K39: 0 | L39: 0 | M39: 0 | N39: 0 | O39: 0 | P39: 0 | Q39: 0 | R39: 0 | S39: 0 | T39: 0 | U39: 0 | V39: 0 | W39: 0 | X39: 0 | Y39: 0 | Z39: 0 | AA39: 0 | AB39: =D39+F39+H39+J39+L39+N39+P39+R39+T39+V39+X39+Z39 -> 850000
B40: 701-011-000-00 | C40: Cumbre Empresarios | D40: 0 | E40: 0 | F40: 0 | G40: 0 | H40: 0 | I40: 0 | J40: 0 | K40: 0 | L40: 0 | M40: 0 | N40: 0 | O40: 0 | P40: 0 | Q40: 0 | R40: 0 | S40: 0 | T40: 0 | U40: 0 | V40: 285000 | W40: 0 | X40: 15000 | Y40: 0 | Z40: 0 | AA40: 0 | AB40: =D40+F40+H40+J40+L40+N40+P40+R40+T40+V40+X40+Z40 -> 300000
B41: 701-014-000-00 | C41: Foros (Talento) | D41: 0 | E41: 0 | F41: 0 | G41: 0 | H41: 120000 | I41: 0 | J41: 0 | K41: 0 | L41: 0 | M41: 0 | N41: 0 | O41: 0 | P41: 0 | Q41: 0 | R41: 0 | S41: 0 | T41: 0 | U41: 0 | V41: 0 | W41: 0 | X41: 0 | Y41: 0 | Z41: 0 | AA41: 0 | AB41: =D41+F41+H41+J41+L41+N41+P41+R41+T41+V41+X41+Z41 -> 120000
B42: 701-012-000-00 | C42: The North America Week | D42: 0 | E42: 0 | F42: 0 | G42: 0 | H42: 0 | I42: 0 | J42: 0 | K42: 0 | L42: 100000 | M42: 0 | N42: 20000 | O42: 0 | P42: 0 | Q42: 0 | R42: 0 | S42: 0 | T42: 0 | U42: 0 | V42: 0 | W42: 0 | X42: 0 | Y42: 0 | Z42: 0 | AA42: 0 | AB42: =D42+F42+H42+J42+L42+N42+P42+R42+T42+V42+X42+Z42 -> 120000
B43: 701-015-000-00 | C43: Jalisco Travel Fest | D43: 0 | E43: 0 | F43: 0 | G43: 0 | H43: 0 | I43: 0 | J43: 0 | K43: 0 | L43: 100000 | M43: 0 | N43: 0 | O43: 0 | P43: 0 | Q43: 0 | R43: 0 | S43: 0 | T43: 0 | U43: 0 | V43: 0 | W43: 0 | X43: 0 | Y43: 0 | Z43: 0 | AA43: 0 | AB43: =D43+F43+H43+J43+L43+N43+P43+R43+T43+V43+X43+Z43 -> 100000
B44: 701-005-000-00 | C44: Open House | D44: 0 | E44: 0 | F44: 50000 | G44: 0 | H44: 0 | I44: 0 | J44: 0 | K44: 0 | L44: 0 | M44: 0 | N44: 0 | O44: 0 | P44: 50000 | Q44: 0 | R44: 0 | S44: 0 | T44: 0 | U44: 0 | V44: 0 | W44: 0 | X44: 50000 | Y44: 0 | Z44: 0 | AA44: 0 | AB44: =D44+F44+H44+J44+L44+N44+P44+R44+T44+V44+X44+Z44 -> 150000
B45: 701-009-000-00 | C45: Extend Our Reach | D45: 0 | E45: 0 | F45: 0 | G45: 0 | H45: 0 | I45: 0 | J45: 0 | K45: 0 | L45: 0 | M45: 0 | N45: 0 | O45: 0 | P45: 0 | Q45: 0 | R45: 0 | S45: 0 | T45: 0 | U45: 0 | V45: 0 | W45: 0 | X45: 0 | Y45: 0 | Z45: 0 | AA45: 0 | AB45: =D45+F45+H45+J45+L45+N45+P45+R45+T45+V45+X45+Z45 -> 0
B46: 701-004-000-00 | C46: Cocteles | D46: 0 | E46: 0 | F46: 0 | G46: 0 | H46: 0 | I46: 0 | J46: 0 | K46: 0 | L46: 0 | M46: 0 | N46: 0 | O46: 0 | P46: 0 | Q46: 0 | R46: 0 | S46: 0 | T46: 0 | U46: 0 | V46: 0 | W46: 0 | X46: 0 | Y46: 0 | Z46: 0 | AA46: 0 | AB46: =D46+F46+H46+J46+L46+N46+P46+R46+T46+V46+X46+Z46 -> 0
B47: 701-003-000-00 | C47: Cena Gala | D47: 0 | E47: 0 | F47: 0 | G47: 0 | H47: 0 | I47: 0 | J47: 0 | K47: 0 | L47: 0 | M47: 0 | N47: 0 | O47: 0 | P47: 0 | Q47: 0 | R47: 0 | S47: 0 | T47: 0 | U47: 0 | V47: 0 | W47: 0 | X47: 0 | Y47: 0 | Z47: 450000 | AA47: 0 | AB47: =D47+F47+H47+J47+L47+N47+P47+R47+T47+V47+X47+Z47 -> 450000
B48: 701-016-000-00 | C48: Top Circle | D48: 0 | E48: 0 | F48: 0 | G48: 0 | H48: 0 | I48: 0 | J48: 0 | K48: 0 | L48: 0 | M48: 0 | N48: 35000 | O48: 0 | P48: 0 | Q48: 0 | R48: 0 | S48: 0 | T48: 0 | U48: 0 | V48: 35000 | W48: 0 | X48: 0 | Y48: 0 | Z48: 0 | AA48: 0 | AB48: =D48+F48+H48+J48+L48+N48+P48+R48+T48+V48+X48+Z48 -> 70000
B49: 701-010-000-00 | C49: Jornada de Reforestación | D49: 0 | E49: 0 | F49: 0 | G49: 0 | H49: 0 | I49: 0 | J49: 0 | K49: 0 | L49: 0 | M49: 0 | N49: 0 | O49: 0 | P49: 0 | Q49: 0 | R49: 50000 | S49: 0 | T49: 0 | U49: 0 | V49: 0 | W49: 0 | X49: 0 | Y49: 0 | Z49: 0 | AA49: 0 | AB49: =D49+F49+H49+J49+L49+N49+P49+R49+T49+V49+X49+Z49 -> 50000
C50: Suma Costos y Gastos Eventos | D50: =SUM(D38:D49) -> 700000 | E50: =SUM(E38:E49) -> 0 | F50: =SUM(F38:F49) -> 200000 | G50: =SUM(G38:G49) -> 0 | H50: =SUM(H38:H49) -> 520000 | I50: =SUM(I38:I49) -> 0 | J50: =SUM(J38:J49) -> 50000 | K50: =SUM(K38:K49) -> 0 | ... AB50: =SUM(AB38:AB49) -> 2660000
C53: Resultado Eventos | D53: =+D35-D50 -> 225000 | E53: =+E35-E50 -> 0 | F53: =+F35-F50 -> -25000 | G53: =+G35-G50 -> 0 | H53: =+H35-H50 -> 240000 | I53: =+I35-I50 -> 0 | J53: =+J35-J50 -> 30000 | K53: =+K35-K50 -> 0 | ... AB53: =+AB35-AB50 -> 1160000 | AC53: 810000
C56: Nota: Los eventos y comités deberán presupuestarse al menos en punto de equilibrio.

Sheet Serv Membresía
C2: SERV A LA MEMBRESÍA | D2: 46023 | E2: 46023 | F2: 46054 | G2: 46054 | H2: 46082 | I2: 46082 | J2: 46113 | K2: 46113 | L2: 46143 | M2: 46143 | N2: 46174 | O2: 46174 | P2: 46204 | Q2: 46204 | R2: 46235 | S2: 46235 | T2: 46266 | U2: 46266 | V2: 46296 | W2: 46296 | X2: 46327 | Y2: 46327 | Z2: 46357 | AA2: 46357 | AB2: 2026 | AE2: Si aplica
C3: Ingresos Serv a la Membresía | AE3: Nvos.
B4: 403-002-000-00 | C4: Encuesta de Sueldos y Prestaciones | D4: 82530 | E4: 0 | F4: 55020 | G4: 0 | H4: 82530 | I4: 0 | J4: 82530 | K4: 0 | L4: 55020 | M4: 0 | N4: 55020 | O4: 0 | P4: 55020 | Q4: 0 | R4: 16275 | S4: 0 | T4: 81375 | U4: 0 | V4: 49632.345 | W4: 0 | X4: 49632.345 | Y4: 0 | Z4: 49632.345 | AA4: 0 | AB4: =D4+F4+H4+J4+L4+N4+P4+R4+T4+V4+X4+Z4 -> 714217.04 | AC4: 598000 | AD4: =AB4/AC4-1 -> 0.19434287 | AE4: Digital Training | AF4: 312000
C5: Suma de Ingresos Serv a la Membresía | D5: =SUM(D4) -> 82530 | E5: =SUM(E4) -> 0 | F5: =SUM(F4) -> 55020 | G5: =SUM(G4) -> 0 | H5: =SUM(H4) -> 82530 | I5: =SUM(I4) -> 0 | J5: =SUM(J4) -> 82530 | K5: =SUM(K4) -> 0 | ... AB5: =SUM(AB4) -> 714217.04 | AE5: Digital Training | AF5: 156000
AF6: =AF4-AF5 -> 156000
C7: Gastos Serv a la Membresía
B8: 601-003-004-00 | C8: Encuesta de Sueldos y Prestaciones | D8: =D4*0.5 -> 41265 | E8: =E4*0.5 -> 0 | F8: =F4*0.5 -> 27510 | G8: =G4*0.5 -> 0 | H8: =H4*0.5 -> 41265 | I8: =I4*0.5 -> 0 | J8: =J4*0.5 -> 41265 | K8: =K4*0.5 -> 0 | ... AA8: =AA4*0.5 -> 0 | AB8: =D8+F8+H8+J8+L8+N8+P8+R8+T8+V8+X8+Z8 -> 357108.52 | AC8: 299000 | AD8: =AB8/AC8-1 -> 0.19434287
C9: Suma de Gastos Serv a la Membresía | D9: =SUM(D8) -> 41265 | E9: =SUM(E8) -> 0 | F9: =SUM(F8) -> 27510 | G9: =SUM(G8) -> 0 | H9: =SUM(H8) -> 41265 | I9: =SUM(I8) -> 0 | J9: =SUM(J8) -> 41265 | K9: =SUM(K8) -> 0 | ... AB9: =SUM(AB8) -> 357108.52
C12: Resultado Serv Membresía | D12: =D5-D9 -> 41265 | E12: =E5-E9 -> 0 | F12: =F5-F9 -> 27510 | G12: =G5-G9 -> 0 | H12: =H5-H9 -> 41265 | I12: =I5-I9 -> 0 | J12: =J5-J9 -> 41265 | K12: =K5-K9 -> 0 | ... AB12: =AB5-AB9 -> 357108.52 | AC12: 455000

Sheet Comunicación
C3: COMUNICACIÓN | D3: 46023 | E3: 46023 | F3: 46054 | G3: 46054 | H3: 46082 | I3: 46082 | J3: 46113 | K3: 46113 | L3: 46143 | M3: 46143 | N3: 46174 | O3: 46174 | P3: 46204 | Q3: 46204 | R3: 46235 | S3: 46235 | T3: 46266 | U3: 46266 | V3: 46296 | W3: 46296 | X3: 46327 | Y3: 46327 | Z3: 46357 | AA3: 46357 | AB3: 2026
C6: Ingresos Comunicación
C7: Ingresos
C8: Suma de Ingresos Comunicación | D8: 0 | E8: 0 | F8: 0 | G8: 0 | H8: 0 | I8: 0 | J8: 0 | K8: 0 | L8: 0 | M8: 0 | N8: 0 | O8: 0 | P8: 0 | Q8: 0 | R8: 0 | S8: 0 | T8: 0 | U8: 0 | V8: 0 | W8: 0 | X8: 0 | Y8: 0 | Z8: 0 | AA8: 0 | AB8: =SUM(D8:AA8) -> 0
C10: Gastos Comunicación
B11: 901-018-001-00 | C11: Agencias de Comunicación | D11: 13949.9 | E11: 0 | F11: 13949.9 | G11: 0 | H11: 13949.9 | I11: 0 | J11: 13949.9 | K11: 0 | L11: 13949.9 | M11: 0 | N11: 13949.9 | O11: 0 | P11: 13949.9 | Q11: 0 | R11: 13949.9 | S11: 0 | T11: 13949.9 | U11: 0 | V11: 13949.9 | W11: 0 | X11: 13949.9 | Y11: 0 | Z11: 13949.9 | AA11: 0 | AB11: =D11+F11+H11+J11+L11+N11+P11+R11+T11+V11+X11+Z11 -> 167398.8
B12: 901-018-002-00 | C12: Contenidos multimedia | D12: 127.2 | E12: 0 | F12: 127.2 | G12: 0 | H12: 127.2 | I12: 0 | J12: 127.2 | K12: 0 | L12: 127.2 | M12: 0 | N12: 127.2 | O12: 0 | P12: 127.2 | Q12: 0 | R12: 127.2 | S12: 0 | T12: 127.2 | U12: 0 | V12: 127.2 | W12: 0 | X12: 127.2 | Y12: 0 | Z12: 127.2 | AA12: 0 | AB12: =D12+F12+H12+J12+L12+N12+P12+R12+T12+V12+X12+Z12 -> 1526.4
B13: 901-018-003-00 | C13: Marketing Licencias | D13: 954 | E13: 0 | F13: 954 | G13: 0 | H13: 954 | I13: 0 | J13: 954 | K13: 0 | L13: 954 | M13: 0 | N13: 954 | O13: 0 | P13: 954 | Q13: 0 | R13: 954 | S13: 0 | T13: 954 | U13: 0 | V13: 954 | W13: 0 | X13: 954 | Y13: 0 | Z13: 954 | AA13: 0 | AB13: =D13+F13+H13+J13+L13+N13+P13+R13+T13+V13+X13+Z13 -> 11448
B14: 901-018-004-00 | C14: Traductor | D14: 240 | E14: 0 | F14: 240 | G14: 0 | H14: 240 | I14: 0 | J14: 240 | K14: 0 | L14: 240 | M14: 0 | N14: 240 | O14: 0 | P14: 240 | Q14: 0 | R14: 240 | S14: 0 | T14: 240 | U14: 0 | V14: 240 | W14: 0 | X14: 240 | Y14: 0 | Z14: 240 | AA14: 0 | AB14: =D14+F14+H14+J14+L14+N14+P14+R14+T14+V14+X14+Z14 -> 2880
C15: Suma de Gastos Comunicación | D15: =D11+D12+D13+D14 -> 15271.1 | E15: =E11+E12+E13+E14 -> 0 | F15: =F11+F12+F13+F14 -> 15271.1 | G15: =G11+G12+G13+G14 -> 0 | H15: =H11+H12+H13+H14 -> 15271.1 | I15: =I11+I12+I13+I14 -> 0 | J15: =J11+J12+J13+J14 -> 15271.1 | K15: =K11+K12+K13+K14 -> 0 | ... AB15: =AB11+AB12+AB13+AB14 -> 183253.2
C18: Resultado Operativo Comunicación | D18: =+D8-D15 -> -15271.1 | E18: =+E8-E15 -> 0 | F18: =+F8-F15 -> -15271.1 | G18: =+G8-G15 -> 0 | H18: =+H8-H15 -> -15271.1 | I18: =+I8-I15 -> 0 | J18: =+J8-J15 -> -15271.1 | K18: =+K8-K15 -> 0 | ... AB18: =+AB8-AB15 -> -183253.2 | AC18: Sin cambios

Sheet RH
C3: DIRECCIÓN DE TALENTO | D3: 46023 | E3: 46023 | F3: 46054 | G3: 46054 | H3: 46082 | I3: 46082 | J3: 46113 | K3: 46113 | L3: 46143 | M3: 46143 | N3: 46174 | O3: 46174 | P3: 46204 | Q3: 46204 | R3: 46235 | S3: 46235 | T3: 46266 | U3: 46266 | V3: 46296 | W3: 46296 | X3: 46327 | Y3: 46327 | Z3: 46357 | AA3: 46357 | AB3: 2026
C5: Ingresos RH
C6: Ingresos | D6: 0 | E6: 0 | F6: 0 | G6: 0 | H6: 0 | I6: 0 | J6: 0 | K6: 0 | L6: 0 | M6: 0 | N6: 0 | O6: 0 | P6: 0 | Q6: 0 | R6: 0 | S6: 0 | T6: 0 | U6: 0 | V6: 0 | W6: 0 | X6: 0 | Y6: 0 | Z6: 0 | AA6: 0 | AB6: =D6+F6+H6+J6+L6+N6+P6+R6+T6+V6+X6+Z6 -> 0
C7: Suma de Ingresos RH | D7: =SUM(D6) -> 0 | E7: =SUM(E6) -> 0 | F7: =SUM(F6) -> 0 | G7: =SUM(G6) -> 0 | H7: =SUM(H6) -> 0 | I7: =SUM(I6) -> 0 | J7: =SUM(J6) -> 0 | K7: =SUM(K6) -> 0 | ... AB7: =SUM(AB6) -> 0
C9: Gastos RH
B10: 901-017-001-00 | C10: Capacitación, Intercambio de talento y Team building | D10: 11102.5 | E10: 0 | F10: 11102.5 | G10: 8000 | H10: 11102.5 | I10: 8000 | J10: 11102.5 | K10: 8000 | L10: 11102.5 | M10: 8000 | N10: 11102.5 | O10: 8000 | P10: 11102.5 | Q10: 8000 | R10: 11102.5 | S10: 8000 | T10: 11102.5 | U10: 8000 | V10: 11102.5 | W10: 8000 | X10: 11102.5 | Y10: 8000 | Z10: 11102.5 | AA10: 0 | AB10: =D10+F10+H10+J10+L10+N10+P10+R10+T10+V10+X10+Z10 -> 133230
B11: 901-017-002-00 | C11: Programa de reconocimientos, Snacks, Regalos, flores getwell | D11: 910 | E11: 0 | F11: 910 | G11: 0 | H11: 910 | I11: 0 | J11: 910 | K11: 0 | L11: 910 | M11: 0 | N11: 910 | O11: 0 | P11: 910 | Q11: 0 | R11: 910 | S11: 0 | T11: 910 | U11: 0 | V11: 910 | W11: 0 | X11: 910 | Y11: 0 | Z11: 910 | AA11: 0 | AB11: =D11+F11+H11+J11+L11+N11+P11+R11+T11+V11+X11+Z11 -> 10920
B12: 901-017-003-00 | C12: Encuesta NOM035 y Voluntariados corporativos | D12: 987.5 | E12: 0 | F12: 987.5 | G12: 0 | H12: 987.5 | I12: 0 | J12: 987.5 | K12: 0 | L12: 987.5 | M12: 0 | N12: 987.5 | O12: 0 | P12: 987.5 | Q12: 0 | R12: 987.5 | S12: 0 | T12: 987.5 | U12: 0 | V12: 987.5 | W12: 0 | X12: 987.5 | Y12: 0 | Z12: 987.5 | AA12: 0 | AB12: =D12+F12+H12+J12+L12+N12+P12+R12+T12+V12+X12+Z12 -> 11850
C13: Suma de Gastos RH | D13: =SUM(D10:D12) -> 13000 | E13: =SUM(E10:E12) -> 0 | F13: =SUM(F10:F12) -> 13000 | G13: =SUM(G10:G12) -> 8000 | H13: =SUM(H10:H12) -> 13000 | I13: =SUM(I10:I12) -> 8000 | J13: =SUM(J10:J12) -> 13000 | K13: =SUM(K10:K12) -> 8000 | ... AB13: =SUM(AB10:AB12) -> 156000
C16: Resultado Operativo RH | D16: =+D7-D13 -> -13000 | E16: =+E7-E13 -> 0 | F16: =+F7-F13 -> -13000 | G16: =+G7-G13 -> -8000 | H16: =+H7-H13 -> -13000 | I16: =+I7-I13 -> -8000 | J16: =+J7-J13 -> -13000 | K16: =+K7-K13 -> -8000 | ... AB16: =+AB7-AB13 -> -156000

Sheet Dirección
C2: DIRECCIÓN CAPÍTULO | D2: 46023 | E2: 46023 | F2: 46054 | G2: 46054 | H2: 46082 | I2: 46082 | J2: 46113 | K2: 46113 | L2: 46143 | M2: 46143 | N2: 46174 | O2: 46174 | P2: 46204 | Q2: 46204 | R2: 46235 | S2: 46235 | T2: 46266 | U2: 46266 | V2: 46296 | W2: 46296 | X2: 46327 | Y2: 46327 | Z2: 46357 | AA2: 46357 | AB2: 2026
C4: Ingresos CE/Board
B5: 404-006-000-00 | C5: Board Of Directors | D5: 0 | E5: 0 | F5: 0 | G5: 0 | H5: 0 | I5: 0 | J5: 0 | K5: 0 | L5: 0 | M5: 0 | N5: 0 | O5: 0 | P5: 0 | Q5: 0 | R5: 0 | S5: 0 | T5: 0 | U5: 0 | V5: 0 | W5: 0 | X5: 0 | Y5: 0 | Z5: 0 | AA5: 0 | AB5: =D5+F5+H5+J5+L5+N5+P5+R5+T5+V5+X5+Z5 -> 0
B6: 404-011-000-00 | C6: Executive Committee | D6: 0 | E6: 0 | F6: 0 | G6: 0 | H6: 6435 | I6: 0 | J6: 3960 | K6: 0 | L6: 814 | M6: 0 | N6: 6435 | O6: 0 | P6: 7425 | Q6: 0 | R6: 4881.723 | S6: 0 | T6: 3465 | U6: 0 | V6: 10725 | W6: 0 | X6: 10725 | Y6: 0 | Z6: 10725 | AA6: 0 | AB6: =D6+F6+H6+J6+L6+N6+P6+R6+T6+V6+X6+Z6 -> 65590.723
C7: Suma de Ingresos CE/Board | D7: =SUM(D5:D6) -> 0 | E7: =SUM(E5:E6) -> 0 | F7: =SUM(F5:F6) -> 0 | G7: =SUM(G5:G6) -> 0 | H7: =SUM(H5:H6) -> 6435 | I7: =SUM(I5:I6) -> 0 | J7: =SUM(J5:J6) -> 3960 | K7: =SUM(K5:K6) -> 0 | ... AB7: =SUM(AB5:AB6) -> 65590.723
C9: Gastos CE/Board
B10: 502-006-000-00 | C10: Board of Directors | D10: 0 | E10: 0 | F10: 0 | G10: 0 | H10: 0 | I10: 0 | J10: 0 | K10: 0 | L10: 0 | M10: 0 | N10: 0 | O10: 0 | P10: 0 | Q10: 0 | R10: 0 | S10: 0 | T10: 0 | U10: 0 | V10: 0 | W10: 0 | X10: 0 | Y10: 0 | Z10: 0 | AA10: 0 | AB10: =D10+F10+H10+J10+L10+N10+P10+R10+T10+V10+X10+Z10 -> 0
B11: 502-012-000-00 | C11: Executive Committee | D11: 0 | E11: 0 | F11: 0 | G11: 0 | H11: 722.15 | I11: 0 | J11: 9799.636 | K11: 0 | L11: 9799.636 | M11: 0 | N11: 9306.264 | O11: 0 | P11: 2420 | Q11: 0 | R11: 9799.636 | S11: 0 | T11: 9790.55 | U11: 0 | V11: 8624 | W11: 0 | X11: 8624 | Y11: 0 | Z11: 8624 | AA11: 0 | AB11: =D11+F11+H11+J11+L11+N11+P11+R11+T11+V11+X11+Z11 -> 77509.872
C12: Suma de Gastos CE/Board | D12: =SUM(D10:D11) -> 0 | E12: =SUM(E10:E11) -> 0 | F12: =SUM(F10:F11) -> 0 | G12: =SUM(G10:G11) -> 0 | H12: =SUM(H10:H11) -> 722.15 | I12: =SUM(I10:I11) -> 0 | J12: =SUM(J10:J11) -> 9799.636 | K12: =SUM(K10:K11) -> 0 | ... AB12: =SUM(AB10:AB11) -> 77509.872
C14: Resultado Board y Executive | D14: =+D7-D12 -> 0 | E14: =+E7-E12 -> 0 | F14: =+F7-F12 -> 0 | G14: =+G7-G12 -> 0 | H14: =+H7-H12 -> 5712.85 | I14: =+I7-I12 -> 0 | J14: =+J7-J12 -> -5839.636 | K14: =+K7-K12 -> 0 | ... AB14: =+AB7-AB12 -> -11919.149
C17: Gastos de Administración
B19: 801-006-004-00 | C19: Gastos de Viaje | D19: 0 | E19: 0 | F19: 0 | G19: 0 | H19: 4338.7814 | I19: 0 | J19: 0 | K19: 0 | L19: 35492.218 | M19: 0 | N19: 0 | O19: 0 | P19: 11733.596 | Q19: 0 | R19: 3512.8188 | S19: 0 | T19: 1272 | U19: 0 | V19: 0 | W19: 0 | X19: 15370 | Y19: 0 | Z19: 0 | AA19: 0 | AB19: =D19+F19+H19+J19+L19+N19+P19+R19+T19+V19+X19+Z19 -> 71719.414
B20: 901-007-000-00 | C20: Viajes Presidente Capítulo | D20: 0 | E20: 0 | F20: 0 | G20: 0 | H20: 10040.596 | I20: 0 | J20: 0 | K20: 0 | L20: 0 | M20: 0 | N20: 0 | O20: 0 | P20: 10144.359 | Q20: 0 | R20: 0 | S20: 0 | T20: 0 | U20: 0 | V20: 0 | W20: 0 | X20: 0 | Y20: 0 | Z20: 0 | AA20: 0 | AB20: =D20+F20+H20+J20+L20+N20+P20+R20+T20+V20+X20+Z20 -> 20184.955
B21: 801-006-002-00 | C21: Gasolina Administración | D21: 8700 | E21: 0 | F21: 8700 | G21: 0 | H21: 8700 | I21: 0 | J21: 8700 | K21: 0 | L21: 8700 | M21: 0 | N21: 8700 | O21: 0 | P21: 8700 | Q21: 0 | R21: 8700 | S21: 0 | T21: 8700 | U21: 0 | V21: 8700 | W21: 0 | X21: 8700 | Y21: 0 | Z21: 8700 | AA21: 0 | AB21: =D21+F21+H21+J21+L21+N21+P21+R21+T21+V21+X21+Z21 -> 104400
B22: 801-006-005-00 | C22: Mtto. Equipo de Transporte | D22: 0 | E22: 0 | F22: 0 | G22: 0 | H22: 7200 | I22: 0 | J22: 0 | K22: 0 | L22: 0 | M22: 0 | N22: 0 | O22: 0 | P22: 0 | Q22: 0 | R22: 0 | S22: 0 | T22: 7200 | U22: 0 | V22: 0 | W22: 0 | X22: 0 | Y22: 0 | Z22: 0 | AA22: 0 | AB22: =D22+F22+H22+J22+L22+N22+P22+R22+T22+V22+X22+Z22 -> 14400
B23: 801-006-006-00 | C23: Gastos de representacion | D23: 0 | E23: 0 | F23: 1053.6082 | G23: 0 | H23: -271.4024 | I23: 0 | J23: 0 | K23: 0 | L23: 0 | M23: 0 | N23: 456.9024 | O23: 0 | P23: 0 | Q23: 0 | R23: 0 | S23: 0 | T23: 551.2 | U23: 0 | V23: 530 | W23: 0 | X23: 4240 | Y23: 0 | Z23: 530 | AA23: 0 | AB23: =D23+F23+H23+J23+L23+N23+P23+R23+T23+V23+X23+Z23 -> 7090.3082
C24: Suma Gastos Administrativos | D24: =SUM(D19:D23) -> 8700 | E24: =SUM(E19:E23) -> 0 | F24: =SUM(F19:F23) -> 9753.6082 | G24: =SUM(G19:G23) -> 0 | H24: =SUM(H19:H23) -> 30007.975 | I24: =SUM(I19:I23) -> 0 | J24: =SUM(J19:J23) -> 8700 | K24: =SUM(K19:K23) -> 0 | ... AB24: =SUM(AB19:AB23) -> 217794.68
C26: Resultado Director Capítulo | D26: =D14-D24 -> -8700 | E26: =E14-E24 -> 0 | F26: =F14-F24 -> -9753.6082 | G26: =G14-G24 -> 0 | H26: =H14-H24 -> -24295.125 | I26: =I14-I24 -> 0 | J26: =J14-J24 -> -14539.636 | K26: =K14-K24 -> 0 | ... AB26: =AB14-AB24 -> -229713.83
C29: Instrucciones: Favor de llenar solo los espacios en blanco, lo que está sombreado en gris será llenado por AYF

Sheet Gastos Generales
C2: GASTOS GENERALES | D2: 46023 | E2: 46023 | F2: 46054 | G2: 46054 | H2: 46082 | I2: 46082 | J2: 46113 | K2: 46113 | L2: 46143 | M2: 46143 | N2: 46174 | O2: 46174 | P2: 46204 | Q2: 46204 | R2: 46235 | S2: 46235 | T2: 46266 | U2: 46266 | V2: 46296 | W2: 46296 | X2: 46327 | Y2: 46327 | Z2: 46357 | AA2: 46357 | AB2: 2026
C4: Otros ingresos
B5: 402-000-000-00 | C5: Otros Ingresos | D5: 0 | E5: 0 | F5: 0 | G5: 0 | H5: 0 | I5: 0 | J5: 0 | K5: 0 | L5: 0 | M5: 0 | N5: 0 | O5: 0 | P5: 0 | Q5: 0 | R5: 0 | S5: 0 | T5: 0 | U5: 0 | V5: 0 | W5: 0 | X5: 0 | Y5: 0 | Z5: 0 | AA5: 0 | AB5: =D5+F5+H5+J5+L5+N5+P5+R5+T5+V5+X5+Z5 -> 0
C6: Suma Otros Ingresos | D6: =D5 -> 0 | E6: =E5 -> 0 | F6: =F5 -> 0 | G6: =G5 -> 0 | H6: =H5 -> 0 | I6: =I5 -> 0 | J6: =J5 -> 0 | K6: =K5 -> 0 | ... AA6: =AA5 -> 0 | AB6: =D6+F6+H6+J6+L6+N6+P6+R6+T6+V6+X6+Z6 -> 0
C8: Gastos Financieros
B9: 410-000-000-00 | C9: Utilidad Cambiaria | D9: 0 | E9: 0 | F9: 0 | G9: 0 | H9: 0 | I9: 0 | J9: 0 | K9: 0 | L9: 0 | M9: 0 | N9: 0 | O9: 0 | P9: 0 | Q9: 0 | R9: 0 | S9: 0 | T9: 0 | U9: 0 | V9: 0 | W9: 0 | X9: 0 | Y9: 0 | Z9: 0 | AA9: 0 | AB9: =D9+F9+H9+J9+L9+N9+P9+R9+T9+V9+X9+Z9 -> 0
B10: 901-019-000-00 | C10: Perdida Cambiaria | D10: 0 | E10: 0 | F10: 0 | G10: 0 | H10: 0 | I10: 0 | J10: 0 | K10: 0 | L10: 0 | M10: 0 | N10: 0 | O10: 0 | P10: 0 | Q10: 0 | R10: 0 | S10: 0 | T10: 0 | U10: 0 | V10: 0 | W10: 0 | X10: 0 | Y10: 0 | Z10: 0 | AA10: 0 | AB10: =D10+F10+H10+J10+L10+N10+P10+R10+T10+V10+X10+Z10 -> 0
B11: 901-020-000-00 | C11: Gtos Financieros (comisiones) | D11: 6777.7778 | E11: 0 | F11: 1542.3742 | G11: 0 | H11: 1490.0844 | I11: 0 | J11: 4085.1976 | K11: 0 | L11: 3237.9608 | M11: 0 | N11: 7383.9494 | O11: 0 | P11: 3526.2596 | Q11: 0 | R11: 5511.682 | S11: 0 | T11: 2575.1428 | U11: 0 | V11: 3975 | W11: 0 | X11: 3975 | Y11: 0 | Z11: 3975 | AA11: 0 | AB11: =D11+F11+H11+J11+L11+N11+P11+R11+T11+V11+X11+Z11 -> 48055.429
C12: Suma Gastos Financieros | D12: =D11+D10-D9 -> 6777.7778 | E12: =E11+E10-E9 -> 0 | F12: =F11+F10-F9 -> 1542.3742 | G12: =G11+G10-G9 -> 0 | H12: =H11+H10-H9 -> 1490.0844 | I12: =I11+I10-I9 -> 0 | J12: =J11+J10-J9 -> 4085.1976 | K12: =K11+K10-K9 -> 0 | ... AA12: =AA11+AA10-AA9 -> 0 | AB12: =D12+F12+H12+J12+L12+N12+P12+R12+T12+V12+X12+Z12 -> 48055.429
C14: Otros Ingresos vs Gastos | D14: =D6-D12 -> -6777.7778 | E14: =E6-E12 -> 0 | F14: =F6-F12 -> -1542.3742 | G14: =G6-G12 -> 0 | H14: =H6-H12 -> -1490.0844 | I14: =I6-I12 -> 0 | J14: =J6-J12 -> -4085.1976 | K14: =K6-K12 -> 0 | ... AB14: =AB6-AB12 -> -48055.429
C16: Gastos Generales
B17: 901-011-007-00 | C17: MONITOREO ALARMA | D17: 1396.02 | E17: 0 | F17: 477 | G17: 0 | H17: 3177.88 | I17: 0 | J17: 954 | K17: 0 | L17: 477 | M17: 0 | N17: 3113.22 | O17: 0 | P17: 477 | Q17: 0 | R17: 477 | S17: 0 | T17: 477 | U17: 0 | V17: 1119.1056 | W17: 0 | X17: 1119.1056 | Y17: 0 | Z17: 1119.1056 | AA17: 0 | AB17: =D17+F17+H17+J17+L17+N17+P17+R17+T17+V17+X17+Z17 -> 14383.437
B18: 901-016-001-00 | C18: ENERGIA ELECTRICA | D18: 0 | E18: 0 | F18: 4133.9576 | G18: 0 | H18: 0 | I18: 0 | J18: 5319.1648 | K18: 0 | L18: 0 | M18: 0 | N18: 9836.959 | O18: 0 | P18: 0 | Q18: 0 | R18: 7966.4406 | S18: 0 | T18: 0 | U18: 0 | V18: 0 | W18: 0 | X18: 10070 | Y18: 0 | Z18: 0 | AA18: 0 | AB18: =D18+F18+H18+J18+L18+N18+P18+R18+T18+V18+X18+Z18 -> 37326.522
B19: 901-016-002-00 | C19: AGUA POTABLE | D19: 151.58 | E19: 0 | F19: 394.32 | G19: 0 | H19: 208.82 | I19: 0 | J19: 159 | K19: 0 | L19: 178.08 | M19: 0 | N19: 146.28 | O19: 0 | P19: 120.84 | Q19: 0 | R19: 125.08 | S19: 0 | T19: 155.82 | U19: 0 | V19: 848 | W19: 0 | X19: 848 | Y19: 0 | Z19: 848 | AA19: 0 | AB19: =D19+F19+H19+J19+L19+N19+P19+R19+T19+V19+X19+Z19 -> 4183.82
B20: 901-016-003-00 | C20: PREDIAL | D20: 13976.1 | E20: 0 | F20: 0 | G20: 0 | H20: 0 | I20: 0 | J20: 0 | K20: 0 | L20: 0 | M20: 0 | N20: 0 | O20: 0 | P20: 0 | Q20: 0 | R20: 0 | S20: 0 | T20: 0 | U20: 0 | V20: 0 | W20: 0 | X20: 0 | Y20: 0 | Z20: 0 | AA20: 0 | AB20: =D20+F20+H20+J20+L20+N20+P20+R20+T20+V20+X20+Z20 -> 13976.1
B21: 901-011-013-00 | C21: ASEO OFICINAS | D21: =14990*1.06 -> 15889.4 | E21: 0 | F21: =14990*1.06 -> 15889.4 | G21: 0 | H21: =14990*1.06 -> 15889.4 | I21: 0 | J21: =14990*1.06 -> 15889.4 | K21: 0 | L21: =14990*1.06 -> 15889.4 | M21: 0 | N21: 15889.4 | O21: 0 | P21: 15889.4 | Q21: 0 | R21: 15889.4 | S21: 0 | T21: 15889.4 | U21: 0 | V21: =14990*1.06 -> 15889.4 | W21: 0 | X21: =14990*1.06 -> 15889.4 | Y21: 0 | Z21: =14990*1.06 -> 15889.4 | AA21: 0 | AB21: =D21+F21+H21+J21+L21+N21+P21+R21+T21+V21+X21+Z21 -> 190672.8
B22: 901-009-000-00 | C22: DESPENSA, ARTS. CAFETERIA | D22: 1428.9436 | E22: 0 | F22: 2676.5 | G22: 0 | H22: 1876.0092 | I22: 0 | J22: 848.7314 | K22: 0 | L22: 2328.1204 | M22: 0 | N22: 1313.0856 | O22: 0 | P22: 2633.5382 | Q22: 0 | R22: 1538.3568 | S22: 0 | T22: 3699.8028 | U22: 0 | V22: 2154.0366 | W22: 0 | X22: 2154.0366 | Y22: 0 | Z22: 2154.0366 | AA22: 0 | AB22: =D22+F22+H22+J22+L22+N22+P22+R22+T22+V22+X22+Z22 -> 24805.198
B23: 901-011-006-00 | C23: LAVANDERIA, TINTORERIA | D23: 0 | E23: 0 | F23: 690.8656 | G23: 0 | H23: 16430 | I23: 0 | J23: 0 | K23: 0 | L23: 0 | M23: 0 | N23: 0 | O23: 0 | P23: 0 | Q23: 0 | R23: 0 | S23: 0 | T23: 0 | U23: 0 | V23: 1166 | W23: 0 | X23: 0 | Y23: 0 | Z23: 0 | AA23: 0 | AB23: =D23+F23+H23+J23+L23+N23+P23+R23+T23+V23+X23+Z23 -> 18286.866
B24: 901-014-001-00 | C24: MANTENIMIENTO DE OFICINA | D24: 636 | E24: 0 | F24: 4377.111 | G24: 0 | H24: 46996.944 | I24: 0 | J24: 61427 | K24: 0 | L24: 37123.055 | M24: 0 | N24: 32889.68 | O24: 0 | P24: 16324 | Q24: 0 | R24: 2968 | S24: 0 | T24: 36252 | U24: 0 | V24: 15983.74 | W24: 0 | X24: 12444.4 | Y24: 0 | Z24: 12444.4 | AA24: 0 | AB24: =D24+F24+H24+J24+L24+N24+P24+R24+T24+V24+X24+Z24 -> 279866.33
B25: 901-014-002-00 | C25: MANTTO EQ DE COMPUTO | D25: 0 | E25: 0 | F25: 22731.191 | G25: 0 | H25: 4511.5932 | I25: 0 | J25: 2228.1942 | K25: 0 | L25: 0 | M25: 0 | N25: 1510.5 | O25: 0 | P25: 8474.7 | Q25: 0 | R25: 2546.7454 | S25: 0 | T25: 655.186 | U25: 0 | V25: 16960 | W25: 0 | X25: 0 | Y25: 0 | Z25: 0 | AA25: 0 | AB25: =D25+F25+H25+J25+L25+N25+P25+R25+T25+V25+X25+Z25 -> 59618.11
B26: 901-003-000-00 | C26: RENTA IMPRESORAS / COPIADORAS | D26: 1802 | E26: 0 | F26: 1802 | G26: 0 | H26: 1802 | I26: 0 | J26: 1802 | K26: 0 | L26: 1802 | M26: 0 | N26: 1802 | O26: 0 | P26: 1802 | Q26: 0 | R26: 1269.88 | S26: 0 | T26: 1269.88 | U26: 0 | V26: 1910.12 | W26: 0 | X26: 1910.12 | Y26: 0 | Z26: 1910.12 | AA26: 0 | AB26: =D26+F26+H26+J26+L26+N26+P26+R26+T26+V26+X26+Z26 -> 20884.12
B27: 901-006-003-00 | C27: TELEFONOS DE MEXICO | D27: 846.94 | E27: 0 | F27: 846.94 | G27: 0 | H27: 846.94 | I27: 0 | J27: 846.94 | K27: 0 | L27: 846.94 | M27: 0 | N27: 846.94 | O27: 0 | P27: 846.94 | Q27: 0 | R27: 846.94 | S27: 0 | T27: 846.94 | U27: 0 | V27: 931.634 | W27: 0 | X27: 931.634 | Y27: 0 | Z27: 931.634 | AA27: 0 | AB27: =D27+F27+H27+J27+L27+N27+P27+R27+T27+V27+X27+Z27 -> 10417.362
B28: 901-011-002-00 | C28: PAQUETERIA Y MENSAJERIA | D28: 0 | E28: 0 | F28: 0 | G28: 0 | H28: 742.2544 | I28: 0 | J28: 0 | K28: 0 | L28: 1682.7712 | M28: 0 | N28: 566.0188 | O28: 0 | P28: 0 | Q28: 0 | R28: 1712.6844 | S28: 0 | T28: 590.8016 | U28: 0 | V28: 424 | W28: 0 | X28: 530 | Y28: 0 | Z28: 424 | AA28: 0 | AB28: =D28+F28+H28+J28+L28+N28+P28+R28+T28+V28+X28+Z28 -> 6672.5304
B29: 901-002-000-00 | C29: CUOTAS y SUSCRIPCIONES | D29: 2862 | E29: 0 | F29: 0 | G29: 0 | H29: 0 | I29: 0 | J29: 0 | K29: 0 | L29: 0 | M29: 0 | N29: 0 | O29: 0 | P29: 0 | Q29: 0 | R29: 0 | S29: 0 | T29: 0 | U29: 0 | V29: 424 | W29: 0 | X29: 424 | Y29: 0 | Z29: 424 | AA29: 0 | AB29: =D29+F29+H29+J29+L29+N29+P29+R29+T29+V29+X29+Z29 -> 4134
B30: 901-011-011-00 | C30: GTOS EXP PERMISOS | D30: 0 | E30: 0 | F30: 0 | G30: 0 | H30: 0 | I30: 0 | J30: 0 | K30: 0 | L30: 7420 | M30: 0 | N30: 7420 | O30: 0 | P30: 0 | Q30: 0 | R30: 0 | S30: 0 | T30: 0 | U30: 0 | V30: 0 | W30: 0 | X30: 26500 | Y30: 0 | Z30: 0 | AA30: 0 | AB30: =D30+F30+H30+J30+L30+N30+P30+R30+T30+V30+X30+Z30 -> 41340
B31: 901-011-015-00 | C31: ADMINISTRACION DE FIDEICOMISOS | D31: 0 | E31: 0 | F31: 0 | G31: 0 | H31: 0 | I31: 0 | J31: 0 | K31: 0 | L31: 0 | M31: 0 | N31: 0 | O31: 0 | P31: 15903.403 | Q31: 0 | R31: 0 | S31: 0 | T31: 0 | U31: 0 | V31: 0 | W31: 0 | X31: 0 | Y31: 0 | Z31: 0 | AA31: 0 | AB31: =D31+F31+H31+J31+L31+N31+P31+R31+T31+V31+X31+Z31 -> 15903.403
B32: 901-023-000-00 | C32: GASTOS PROMOCIONALES (termos, libretas, plumas) | D32: 0 | E32: 0 | F32: 0 | G32: 0 | H32: 0 | I32: 0 | J32: 0 | K32: 0 | L32: 0 | M32: 0 | N32: 0 | O32: 0 | P32: 10833.931 | Q32: 0 | R32: 0 | S32: 0 | T32: 0 | U32: 0 | V32: 0 | W32: 0 | X32: 0 | Y32: 0 | Z32: 0 | AA32: 0 | AB32: =D32+F32+H32+J32+L32+N32+P32+R32+T32+V32+X32+Z32 -> 10833.931
B33: 901-013-000-00 | C33: SERVICIOS DE CONSULTORIA EN COMUNICACIÓN | D33: 16678.379 | E33: 0 | F33: 16678.379 | G33: 0 | H33: 16678.379 | I33: 0 | J33: 16678.379 | K33: 0 | L33: 16678.379 | M33: 0 | N33: 16678.379 | O33: 0 | P33: 16678.379 | Q33: 0 | R33: 16678.379 | S33: 0 | T33: 16678.379 | U33: 0 | V33: 17512.298 | W33: 0 | X33: 17512.298 | Y33: 0 | Z33: 17512.298 | AA33: 0 | AB33: =D33+F33+H33+J33+L33+N33+P33+R33+T33+V33+X33+Z33 -> 202642.31
B34: 901-011-012-00 | C34: GASTOS EXTRAORDINARIOS | D34: 8220.9148 | E34: 0 | F34: 0 | G34: 0 | H34: -792.9754 | I34: 0 | J34: 743.166 | K34: 0 | L34: =130402.5356-90000 -> 40402.536 | M34: 0 | N34: =98580-53000 -> 45580 | O34: 0 | P34: 0 | Q34: 0 | R34: 1526.4 | S34: 0 | T34: 12284.806 | U34: 0 | V34: 21200 | W34: 0 | X34: 0 | Y34: 0 | Z34: 21200 | AA34: 0 | AB34: =D34+F34+H34+J34+L34+N34+P34+R34+T34+V34+X34+Z34 -> 150364.85
B35: 901-024-000-00 | C35: REUNION FIN DE AÑO | D35: 0 | E35: 0 | F35: 0 | G35: 0 | H35: 0 | I35: 0 | J35: 0 | K35: 0 | L35: 0 | M35: 0 | N35: 0 | O35: 0 | P35: 0 | Q35: 0 | R35: 0 | S35: 0 | T35: 0 | U35: 0 | V35: 0 | W35: 0 | X35: 18815 | Y35: 0 | Z35: 18815 | AA35: 0 | AB35: =D35+F35+H35+J35+L35+N35+P35+R35+T35+V35+X35+Z35 -> 37630
B36: 901-022-000-00 | C36: IVA A PRORRATA NO ACREDITABLE | D36: 10000 | E36: 0 | F36: 15000 | G36: 0 | H36: 7500 | I36: 0 | J36: 7500 | K36: 0 | L36: 7500 | M36: 0 | N36: 7500 | O36: 0 | P36: 7500 | Q36: 0 | R36: 7500 | S36: 0 | T36: 7500 | U36: 0 | V36: 7500 | W36: 0 | X36: 7500 | Y36: 0 | Z36: 7500 | AA36: 0 | AB36: =D36+F36+H36+J36+L36+N36+P36+R36+T36+V36+X36+Z36 -> 100000
B37: 901-099-000-00 | C37: AJUSTES Y DIFERENCIAS | D37: 0 | E37: 0 | F37: 0 | G37: 0 | H37: 0 | I37: 0 | J37: 0 | K37: 0 | L37: 0 | M37: 0 | N37: 0 | O37: 0 | P37: 0 | Q37: 0 | R37: 0 | S37: 0 | T37: 0 | U37: 0 | V37: 0 | W37: 0 | X37: 0 | Y37: 0 | Z37: 0 | AA37: 0 | AB37: =D37+F37+H37+J37+L37+N37+P37+R37+T37+V37+X37+Z37 -> 0
B38: 901-011-004-00 | C38: OTROS GASTOS | D38: 0 | E38: 0 | F38: 0 | G38: 0 | H38: 0 | I38: 0 | J38: 0 | K38: 0 | L38: 0 | M38: 0 | N38: 0 | O38: 0 | P38: 0 | Q38: 0 | R38: 0 | S38: 0 | T38: 0 | U38: 0 | V38: 0 | W38: 0 | X38: 0 | Y38: 0 | Z38: 0 | AA38: 0 | AB38: =D38+F38+H38+J38+L38+N38+P38+R38+T38+V38+X38+Z38 -> 0
B39: 901-011-005-00 | C39: NO DEDUCIBLES | D39: 0 | E39: 0 | F39: 0 | G39: 0 | H39: 0 | I39: 0 | J39: 0 | K39: 0 | L39: 0 | M39: 0 | N39: 0 | O39: 0 | P39: 0 | Q39: 0 | R39: 0 | S39: 0 | T39: 0 | U39: 0 | V39: 0 | W39: 0 | X39: 0 | Y39: 0 | Z39: 0 | AA39: 0 | AB39: =D39+F39+H39+J39+L39+N39+P39+R39+T39+V39+X39+Z39 -> 0
B40: 501-000-000-00 | C40: NOMINA GDL | D40: =551463.32+4799+3070 -> 559332.32 | E40: 0 | F40: =551463.32+4799+3070 -> 559332.32 | G40: =610252.5+4799+3070 -> 618121.5 | H40: =551463.32+4799+3070 -> 559332.32 | I40: =610252.5+4799+3070 -> 618121.5 | J40: =551463.32+4799+3070 -> 559332.32 | K40: =610252.5+4799+3070 -> 618121.5 | L40: =551463.32+4799+3070 -> 559332.32 | M40: =610252.5+4799+3070 -> 618121.5 | N40: =551463.32+4799+3070 -> 559332.32 | O40: =610252.5+4799+3070 -> 618121.5 | P40: =551463.32+4799+3070 -> 559332.32 | Q40: =610252.5+4799+3070 -> 618121.5 | R40: =551463.32+4799+3070 -> 559332.32 | S40: =610252.5+4799+3070 -> 618121.5 | T40: =551463.32+4799+3070 -> 559332.32 | U40: =610252.5+4799+3070 -> 618121.5 | V40: =551463.32+4799+3070 -> 559332.32 | W40: =610252.5+4799+3070 -> 618121.5 | X40: =551463.32+4799+3070 -> 559332.32 | Y40: =610252.5+4799+3070 -> 618121.5 | Z40: =551463.32+4799+3070 -> 559332.32 | AA40: 0 | AB40: =D40+F40+H40+J40+L40+N40+P40+R40+T40+V40+X40+Z40 -> 6711987.8
B41: 801-006-001-00 | C41: REEMBOLSO TELEFONO | D41: =6*800+(3192*1.06) -> 8183.52 | E41: 0 | F41: =6*800 -> 4800 | G41: 0 | H41: =6*800 -> 4800 | I41: 0 | J41: =6*800 -> 4800 | K41: 0 | L41: =6*800 -> 4800 | M41: 0 | N41: =6*800 -> 4800 | O41: 0 | P41: =6*800 -> 4800 | Q41: 0 | R41: =6*800 -> 4800 | S41: 0 | T41: =6*800 -> 4800 | U41: 0 | V41: =6*800 -> 4800 | W41: 0 | X41: =6*800 -> 4800 | Y41: 0 | Z41: =6*800 -> 4800 | AA41: 0 | AB41: =D41+F41+H41+J41+L41+N41+P41+R41+T41+V41+X41+Z41 -> 60983.52
B42: 801-006-003-00 | C42: GASOLINA KAM´S | D42: =2800*3 -> 8400 | E42: 0 | F42: =2800*3 -> 8400 | G42: 0 | H42: =2800*3 -> 8400 | I42: 0 | J42: =2800*3 -> 8400 | K42: 0 | L42: =2800*3 -> 8400 | M42: 0 | N42: =2800*3 -> 8400 | O42: 0 | P42: =2800*3 -> 8400 | Q42: 0 | R42: =2800*3 -> 8400 | S42: 0 | T42: =2800*3 -> 8400 | U42: 0 | V42: =2800*3 -> 8400 | W42: 0 | X42: =2800*3 -> 8400 | Y42: 0 | Z42: =2800*3 -> 8400 | AA42: 0 | AB42: =D42+F42+H42+J42+L42+N42+P42+R42+T42+V42+X42+Z42 -> 100800
B43: 801-006-007-00 | C43: PASAJES y ESTACIONAMIENTOS | D43: 46.64 | E43: 0 | F43: 193.5454 | G43: 0 | H43: 165.36 | I43: 0 | J43: 150.7638 | K43: 0 | L43: 0 | M43: 0 | N43: 0 | O43: 0 | P43: 0 | Q43: 0 | R43: 1555.2638 | S43: 0 | T43: 91.3826 | U43: 0 | V43: 0 | W43: 0 | X43: 1060 | Y43: 0 | Z43: 0 | AA43: 0 | AB43: =D43+F43+H43+J43+L43+N43+P43+R43+T43+V43+X43+Z43 -> 3262.9556
B44: 801-006-008-00 | C44: PAPELERIA Y ARTS OFICINA | D44: 0 | E44: 0 | F44: 0 | G44: 0 | H44: 3021 | I44: 0 | J44: 901 | K44: 0 | L44: 5433.7508 | M44: 0 | N44: 5277.157 | O44: 0 | P44: 2326.5198 | Q44: 0 | R44: 0 | S44: 0 | T44: 0 | U44: 0 | V44: 1766.6702 | W44: 0 | X44: 0 | Y44: 0 | Z44: 1766.649 | AA44: 0 | AB44: =D44+F44+H44+J44+L44+N44+P44+R44+T44+V44+X44+Z44 -> 20492.747
B45: 801-006-009-00 | C45: CONSUMOS REUNIONES DE TRABAJO | D45: 0 | E45: 0 | F45: 0 | G45: 0 | H45: 0 | I45: 0 | J45: 0 | K45: 0 | L45: 0 | M45: 0 | N45: 0 | O45: 0 | P45: 0 | Q45: 0 | R45: 0 | S45: 0 | T45: 0 | U45: 0 | V45: 1060 | W45: 0 | X45: 0 | Y45: 0 | Z45: 0 | AA45: 0 | AB45: =D45+F45+H45+J45+L45+N45+P45+R45+T45+V45+X45+Z45 -> 1060
B46: 801-006-010-00 | C46: HERRAMIENTAS TELE-TRABAJO | D46: =850*11 -> 9350 | E46: 0 | F46: =850*11 -> 9350 | G46: 0 | H46: =850*11 -> 9350 | I46: 0 | J46: =850*11 -> 9350 | K46: 0 | L46: =850*11 -> 9350 | M46: 0 | N46: =850*11 -> 9350 | O46: 0 | P46: =850*11 -> 9350 | Q46: 0 | R46: =850*11 -> 9350 | S46: 0 | T46: =850*11 -> 9350 | U46: 0 | V46: =850*11 -> 9350 | W46: 0 | X46: =850*11 -> 9350 | Y46: 0 | Z46: =850*11 -> 9350 | AA46: 0 | AB46: =D46+F46+H46+J46+L46+N46+P46+R46+T46+V46+X46+Z46 -> 112200
C47: Suma de Gastos Generales | D47: =SUM(D17:D46) -> 659200.76 | E47: =SUM(E17:E46) -> 0 | F47: =SUM(F17:F46) -> 667773.53 | G47: =SUM(G17:G46) -> 618121.5 | H47: =SUM(H17:H46) -> 700935.93 | I47: =SUM(I17:I46) -> 618121.5 | J47: =SUM(J17:J46) -> 697330.06 | K47: =SUM(K17:K46) -> 618121.5 | ... AB47: =SUM(AB17:AB46) -> 8254728.7
C49: Depreciaciones y Amortizaciones
B50: 901-008-000-00 | C50: Depreciaciones de equipo | D50: 6719.717 | E50: 0 | F50: 6719.717 | G50: 0 | H50: 6719.717 | I50: 0 | J50: 6719.717 | K50: 0 | L50: 6719.717 | M50: 0 | N50: 6719.717 | O50: 0 | P50: 6719.717 | Q50: 0 | R50: 6719.717 | S50: 0 | T50: 6719.717 | U50: 0 | V50: 6719.717 | W50: 0 | X50: 6719.717 | Y50: 0 | Z50: 6719.717 | AA50: 0 | AB50: =D50+F50+H50+J50+L50+N50+P50+R50+T50+V50+X50+Z50 -> 80636.604
B51: 901-015-000-00 | C51: Amortizaciones | D51: 3516.6666 | E51: 0 | F51: 3516.6666 | G51: 0 | H51: 3516.6666 | I51: 0 | J51: 3516.6666 | K51: 0 | L51: 3516.6666 | M51: 0 | N51: 3516.6666 | O51: 0 | P51: 3516.6666 | Q51: 0 | R51: 3516.6666 | S51: 0 | T51: 3516.6666 | U51: 0 | V51: 3516.6631 | W51: 0 | X51: 3516.6631 | Y51: 0 | Z51: 3516.6631 | AA51: 0 | AB51: =D51+F51+H51+J51+L51+N51+P51+R51+T51+V51+X51+Z51 -> 42199.989
C52: Suma Depreciaciones y Amortizaciones | D52: =D50+D51 -> 10236.384 | E52: =E50+E51 -> 0 | F52: =F50+F51 -> 10236.384 | G52: =G50+G51 -> 0 | H52: =H50+H51 -> 10236.384 | I52: =I50+I51 -> 0 | J52: =J50+J51 -> 10236.384 | K52: =K50+K51 -> 0 | ... AB52: =AB50+AB51 -> 122836.59
B54: 903-000-000-00 | C54: Gastos Corporativos Gdl | D54: ='Gtos. Corporativos'!H26 -> 360748.33 | E54: 0 | F54: =D54 -> 360748.33 | G54: 0 | H54: =F54 -> 360748.33 | I54: 0 | J54: =H54 -> 360748.33 | K54: 0 | L54: =J54 -> 360748.33 | M54: 0 | N54: =L54 -> 360748.33 | O54: 0 | P54: =N54 -> 360748.33 | Q54: 0 | R54: =P54 -> 360748.33 | S54: 0 | T54: =R54 -> 360748.33 | U54: 0 | V54: =T54 -> 360748.33 | W54: 0 | X54: =V54 -> 360748.33 | Y54: 0 | Z54: =X54 -> 360748.33 | AA54: 0 | AB54: =D54+F54+H54+J54+L54+N54+P54+R54+T54+V54+X54+Z54 -> 4328980
B56: 904-000-000-00 | C56: Member Centricity | D56: 0 | E56: 0 | F56: 0 | G56: 0 | H56: 0 | I56: 0 | J56: 0 | K56: 0 | L56: 0 | M56: 0 | N56: 0 | O56: 0 | P56: 0 | Q56: 0 | R56: 0 | S56: 0 | T56: 0 | U56: 0 | V56: 0 | W56: 0 | X56: 0 | Y56: 0 | Z56: 0 | AA56: 0 | AB56: =D56+F56+H56+J56+L56+N56+P56+R56+T56+V56+X56+Z56 -> 0
C58: Total GA Gdl | D58: =+D14-D47-D52-D54-D56 -> -1036963.3 | E58: =+E14-E47-E52-E54-E56 -> 0 | F58: =+F14-F47-F52-F54-F56 -> -1040300.6 | G58: =+G14-G47-G52-G54-G56 -> -618121.5 | H58: =+H14-H47-H52-H54-H56 -> -1073410.7 | I58: =+I14-I47-I52-I54-I56 -> -618121.5 | J58: =+J14-J47-J52-J54-J56 -> -1072400 | K58: =+K14-K47-K52-K54-K56 -> -618121.5 | ... AB58: =+AB14-AB47-AB52-AB54-AB56 -> -12754601
C63: Nota: Se pueden adicionar conceptos para los gastos generales, en caso de ser necesario.

Sheet PPvsREal
D2: Ppto. | E2: Real | F2: Ppto. | G2: Real | H2: Ppto. | I2: Real | J2: Ppto. | K2: Real | L2: Ppto. | M2: Real | N2: Ppto. | O2: Real | P2: Ppto. | Q2: Real | R2: Ppto. | S2: Real | T2: Ppto. | U2: Real | V2: Ppto. | W2: Real | X2: Ppto. | Y2: Real | Z2: Ppto. | AA2: Real
B3: Departamento | C3: Cta | D3: Ene | E3: Ene | F3: Feb | G3: Feb | H3: Mar | I3: Mar | J3: Abr | K3: Abr | L3: May | M3: May | N3: Jun | O3: Jun | P3: Jul | Q3: Jul | R3: Ago | S3: Ago | T3: Sep | U3: Sep | V3: Oct | W3: Oct | X3: Nov | Y3: Nov | Z3: Dic | AA3: Dic
B4: DN | C4: 400-001-000-00 | D4: =SUMIF(DN!$B:$B,PPvsREal!$C$4,DN!D:D) -> 695531.68 | E4: =SUMIF(DN!$B:$B,PPvsREal!$C$4,DN!E:E) -> 0 | F4: =SUMIF(DN!$B:$B,PPvsREal!$C$4,DN!F:F) -> 695531.68 | G4: =SUMIF(DN!$B:$B,PPvsREal!$C$4,DN!G:G) -> 0 | H4: =SUMIF(DN!$B:$B,PPvsREal!$C$4,DN!H:H) -> 695531.68 | I4: =SUMIF(DN!$B:$B,PPvsREal!$C$4,DN!I:I) -> 0 | J4: =SUMIF(DN!$B:$B,PPvsREal!$C$4,DN!J:J) -> 695531.68 | K4: =SUMIF(DN!$B:$B,PPvsREal!$C$4,DN!K:K) -> 0 | L4: =SUMIF(DN!$B:$B,PPvsREal!$C$4,DN!L:L) -> 695531.68 | M4: =SUMIF(DN!$B:$B,PPvsREal!$C$4,DN!M:M) -> 0 | N4: =SUMIF(DN!$B:$B,PPvsREal!$C$4,DN!N:N) -> 695531.68 | O4: =SUMIF(DN!$B:$B,PPvsREal!$C$4,DN!O:O) -> 0 | P4: =SUMIF(DN!$B:$B,PPvsREal!$C$4,DN!P:P) -> 695531.68 | Q4: =SUMIF(DN!$B:$B,PPvsREal!$C$4,DN!Q:Q) -> 0 | R4: =SUMIF(DN!$B:$B,PPvsREal!$C$4,DN!R:R) -> 695531.68 | S4: =SUMIF(DN!$B:$B,PPvsREal!$C$4,DN!S:S) -> 0 | T4: =SUMIF(DN!$B:$B,PPvsREal!$C$4,DN!T:T) -> 695531.68 | U4: =SUMIF(DN!$B:$B,PPvsREal!$C$4,DN!U:U) -> 0 | V4: =SUMIF(DN!$B:$B,PPvsREal!$C$4,DN!V:V) -> 695531.68 | W4: =SUMIF(DN!$B:$B,PPvsREal!$C$4,DN!W:W) -> 0 | X4: =SUMIF(DN!$B:$B,PPvsREal!$C$4,DN!X:X) -> 695531.68 | Y4: =SUMIF(DN!$B:$B,PPvsREal!$C$4,DN!Y:Y) -> 0 | Z4: =SUMIF(DN!$B:$B,PPvsREal!$C$4,DN!Z:Z) -> 695531.68 | AA4: =SUMIF(DN!$B:$B,PPvsREal!$C$4,DN!AA:AA) -> 0
B5: DN | C5: 400-002-000-00 | D5: =SUMIF(DN!$B:$B,PPvsREal!$C$5,DN!D:D) -> -18444.425 | E5: =SUMIF(DN!$B:$B,PPvsREal!$C$5,DN!E:E) -> 0 | F5: =SUMIF(DN!$B:$B,PPvsREal!$C$5,DN!F:F) -> -18423.995 | G5: =SUMIF(DN!$B:$B,PPvsREal!$C$5,DN!G:G) -> 0 | H5: =SUMIF(DN!$B:$B,PPvsREal!$C$5,DN!H:H) -> -18402.897 | I5: =SUMIF(DN!$B:$B,PPvsREal!$C$5,DN!I:I) -> 0 | J5: =SUMIF(DN!$B:$B,PPvsREal!$C$5,DN!J:J) -> -18493.591 | K5: =SUMIF(DN!$B:$B,PPvsREal!$C$5,DN!K:K) -> 0 | L5: =SUMIF(DN!$B:$B,PPvsREal!$C$5,DN!L:L) -> -19741.292 | M5: =SUMIF(DN!$B:$B,PPvsREal!$C$5,DN!M:M) -> 0 | N5: =SUMIF(DN!$B:$B,PPvsREal!$C$5,DN!N:N) -> -18391.145 | O5: =SUMIF(DN!$B:$B,PPvsREal!$C$5,DN!O:O) -> 0 | P5: =SUMIF(DN!$B:$B,PPvsREal!$C$5,DN!P:P) -> -18402.073 | Q5: =SUMIF(DN!$B:$B,PPvsREal!$C$5,DN!Q:Q) -> 0 | R5: =SUMIF(DN!$B:$B,PPvsREal!$C$5,DN!R:R) -> -18545.187 | S5: =SUMIF(DN!$B:$B,PPvsREal!$C$5,DN!S:S) -> 0 | T5: =SUMIF(DN!$B:$B,PPvsREal!$C$5,DN!T:T) -> -18954.145 | U5: =SUMIF(DN!$B:$B,PPvsREal!$C$5,DN!U:U) -> 0 | V5: =SUMIF(DN!$B:$B,PPvsREal!$C$5,DN!V:V) -> -12255.603 | W5: =SUMIF(DN!$B:$B,PPvsREal!$C$5,DN!W:W) -> 0 | X5: =SUMIF(DN!$B:$B,PPvsREal!$C$5,DN!X:X) -> -12255.603 | Y5: =SUMIF(DN!$B:$B,PPvsREal!$C$5,DN!Y:Y) -> 0 | Z5: =SUMIF(DN!$B:$B,PPvsREal!$C$5,DN!Z:Z) -> -12264.267 | AA5: =SUMIF(DN!$B:$B,PPvsREal!$C$5,DN!AA:AA) -> 0
B6: DN | C6: 400-005-000-00 | D6: =SUMIF(DN!$B:$B,PPvsREal!$C$6,DN!D:D) -> 260871.54 | E6: =SUMIF(DN!$B:$B,PPvsREal!$C$6,DN!E:E) -> 0 | F6: =SUMIF(DN!$B:$B,PPvsREal!$C$6,DN!F:F) -> 260871.54 | G6: =SUMIF(DN!$B:$B,PPvsREal!$C$6,DN!G:G) -> 0 | H6: =SUMIF(DN!$B:$B,PPvsREal!$C$6,DN!H:H) -> 260871.54 | I6: =SUMIF(DN!$B:$B,PPvsREal!$C$6,DN!I:I) -> 0 | J6: =SUMIF(DN!$B:$B,PPvsREal!$C$6,DN!J:J) -> 260871.54 | K6: =SUMIF(DN!$B:$B,PPvsREal!$C$6,DN!K:K) -> 0 | L6: =SUMIF(DN!$B:$B,PPvsREal!$C$6,DN!L:L) -> 260871.54 | M6: =SUMIF(DN!$B:$B,PPvsREal!$C$6,DN!M:M) -> 0 | N6: =SUMIF(DN!$B:$B,PPvsREal!$C$6,DN!N:N) -> 260871.54 | O6: =SUMIF(DN!$B:$B,PPvsREal!$C$6,DN!O:O) -> 0 | P6: =SUMIF(DN!$B:$B,PPvsREal!$C$6,DN!P:P) -> 260871.54 | Q6: =SUMIF(DN!$B:$B,PPvsREal!$C$6,DN!Q:Q) -> 0 | R6: =SUMIF(DN!$B:$B,PPvsREal!$C$6,DN!R:R) -> 260871.54 | S6: =SUMIF(DN!$B:$B,PPvsREal!$C$6,DN!S:S) -> 0 | T6: =SUMIF(DN!$B:$B,PPvsREal!$C$6,DN!T:T) -> 260871.54 | U6: =SUMIF(DN!$B:$B,PPvsREal!$C$6,DN!U:U) -> 0 | V6: =SUMIF(DN!$B:$B,PPvsREal!$C$6,DN!V:V) -> 260871.54 | W6: =SUMIF(DN!$B:$B,PPvsREal!$C$6,DN!W:W) -> 0 | X6: =SUMIF(DN!$B:$B,PPvsREal!$C$6,DN!X:X) -> 260871.54 | Y6: =SUMIF(DN!$B:$B,PPvsREal!$C$6,DN!Y:Y) -> 0 | Z6: =SUMIF(DN!$B:$B,PPvsREal!$C$6,DN!Z:Z) -> 260871.54 | AA6: =SUMIF(DN!$B:$B,PPvsREal!$C$6,DN!AA:AA) -> 0
B7: DN | C7: 401-001-000-00 | D7: =SUMIF(DN!$B:$B,PPvsREal!$C$7,DN!D:D) -> 42036 | E7: =SUMIF(DN!$B:$B,PPvsREal!$C$7,DN!E:E) -> 0 | F7: =SUMIF(DN!$B:$B,PPvsREal!$C$7,DN!F:F) -> 74015 | G7: =SUMIF(DN!$B:$B,PPvsREal!$C$7,DN!G:G) -> 0 | H7: =SUMIF(DN!$B:$B,PPvsREal!$C$7,DN!H:H) -> 25425 | I7: =SUMIF(DN!$B:$B,PPvsREal!$C$7,DN!I:I) -> 0 | J7: =SUMIF(DN!$B:$B,PPvsREal!$C$7,DN!J:J) -> 27685 | K7: =SUMIF(DN!$B:$B,PPvsREal!$C$7,DN!K:K) -> 0 | L7: =SUMIF(DN!$B:$B,PPvsREal!$C$7,DN!L:L) -> 0 | M7: =SUMIF(DN!$B:$B,PPvsREal!$C$7,DN!M:M) -> 0 | N7: =SUMIF(DN!$B:$B,PPvsREal!$C$7,DN!N:N) -> 33335 | O7: =SUMIF(DN!$B:$B,PPvsREal!$C$7,DN!O:O) -> 0 | P7: =SUMIF(DN!$B:$B,PPvsREal!$C$7,DN!P:P) -> 33335 | Q7: =SUMIF(DN!$B:$B,PPvsREal!$C$7,DN!Q:Q) -> 0 | R7: =SUMIF(DN!$B:$B,PPvsREal!$C$7,DN!R:R) -> 18419 | S7: =SUMIF(DN!$B:$B,PPvsREal!$C$7,DN!S:S) -> 0 | T7: =SUMIF(DN!$B:$B,PPvsREal!$C$7,DN!T:T) -> 34804 | U7: =SUMIF(DN!$B:$B,PPvsREal!$C$7,DN!U:U) -> 0 | V7: =SUMIF(DN!$B:$B,PPvsREal!$C$7,DN!V:V) -> 67800 | W7: =SUMIF(DN!$B:$B,PPvsREal!$C$7,DN!W:W) -> 0 | X7: =SUMIF(DN!$B:$B,PPvsREal!$C$7,DN!X:X) -> 80230 | Y7: =SUMIF(DN!$B:$B,PPvsREal!$C$7,DN!Y:Y) -> 0 | Z7: =SUMIF(DN!$B:$B,PPvsREal!$C$7,DN!Z:Z) -> 73450 | AA7: =SUMIF(DN!$B:$B,PPvsREal!$C$7,DN!AA:AA) -> 0
B8: DN | C8: 702-002-000-00 | D8: =SUMIF(DN!$B:$B,$C$8,DN!D:D) -> 0 | E8: =SUMIF(DN!$B:$B,$C$8,DN!E:E) -> 0 | F8: =SUMIF(DN!$B:$B,$C$8,DN!F:F) -> 0 | G8: =SUMIF(DN!$B:$B,$C$8,DN!G:G) -> 0 | H8: =SUMIF(DN!$B:$B,$C$8,DN!H:H) -> 0 | I8: =SUMIF(DN!$B:$B,$C$8,DN!I:I) -> 0 | J8: =SUMIF(DN!$B:$B,$C$8,DN!J:J) -> 0 | K8: =SUMIF(DN!$B:$B,$C$8,DN!K:K) -> 0 | L8: =SUMIF(DN!$B:$B,$C$8,DN!L:L) -> 0 | M8: =SUMIF(DN!$B:$B,$C$8,DN!M:M) -> 0 | N8: =SUMIF(DN!$B:$B,$C$8,DN!N:N) -> 0 | O8: =SUMIF(DN!$B:$B,$C$8,DN!O:O) -> 0 | P8: =SUMIF(DN!$B:$B,$C$8,DN!P:P) -> 0 | Q8: =SUMIF(DN!$B:$B,$C$8,DN!Q:Q) -> 0 | R8: =SUMIF(DN!$B:$B,$C$8,DN!R:R) -> 0 | S8: =SUMIF(DN!$B:$B,$C$8,DN!S:S) -> 0 | T8: =SUMIF(DN!$B:$B,$C$8,DN!T:T) -> 0 | U8: =SUMIF(DN!$B:$B,$C$8,DN!U:U) -> 0 | V8: =SUMIF(DN!$B:$B,$C$8,DN!V:V) -> 0 | W8: =SUMIF(DN!$B:$B,$C$8,DN!W:W) -> 0 | X8: =SUMIF(DN!$B:$B,$C$8,DN!X:X) -> 0 | Y8: =SUMIF(DN!$B:$B,$C$8,DN!Y:Y) -> 0 | Z8: =SUMIF(DN!$B:$B,$C$8,DN!Z:Z) -> 0 | AA8: =SUMIF(DN!$B:$B,$C$8,DN!AA:AA) -> 0
B9: DN | C9: 503-000-000-00 | D9: =SUMIF(DN!$B:$B,$C$9,DN!D:D) -> 38293.58 | E9: =SUMIF(DN!$B:$B,$C$9,DN!E:E) -> 0 | F9: =SUMIF(DN!$B:$B,$C$9,DN!F:F) -> 38293.58 | G9: =SUMIF(DN!$B:$B,$C$9,DN!G:G) -> 0 | H9: =SUMIF(DN!$B:$B,$C$9,DN!H:H) -> 38293.58 | I9: =SUMIF(DN!$B:$B,$C$9,DN!I:I) -> 0 | J9: =SUMIF(DN!$B:$B,$C$9,DN!J:J) -> 38293.58 | K9: =SUMIF(DN!$B:$B,$C$9,DN!K:K) -> 0 | L9: =SUMIF(DN!$B:$B,$C$9,DN!L:L) -> 38293.58 | M9: =SUMIF(DN!$B:$B,$C$9,DN!M:M) -> 0 | N9: =SUMIF(DN!$B:$B,$C$9,DN!N:N) -> 38293.58 | O9: =SUMIF(DN!$B:$B,$C$9,DN!O:O) -> 0 | P9: =SUMIF(DN!$B:$B,$C$9,DN!P:P) -> 38293.58 | Q9: =SUMIF(DN!$B:$B,$C$9,DN!Q:Q) -> 0 | R9: =SUMIF(DN!$B:$B,$C$9,DN!R:R) -> 38293.58 | S9: =SUMIF(DN!$B:$B,$C$9,DN!S:S) -> 0 | T9: =SUMIF(DN!$B:$B,$C$9,DN!T:T) -> 38293.58 | U9: =SUMIF(DN!$B:$B,$C$9,DN!U:U) -> 0 | V9: =SUMIF(DN!$B:$B,$C$9,DN!V:V) -> 38293.58 | W9: =SUMIF(DN!$B:$B,$C$9,DN!W:W) -> 0 | X9: =SUMIF(DN!$B:$B,$C$9,DN!X:X) -> 38293.58 | Y9: =SUMIF(DN!$B:$B,$C$9,DN!Y:Y) -> 0 | Z9: =SUMIF(DN!$B:$B,$C$9,DN!Z:Z) -> 38293.58 | AA9: =SUMIF(DN!$B:$B,$C$9,DN!AA:AA) -> 0
B10: DN | C10: 702-001-000-00 | D10: =SUMIF(DN!$B:$B,PPvsREal!$C$10,DN!D:D) -> 1657.0026 | E10: =SUMIF(DN!$B:$B,PPvsREal!$C$10,DN!E:E) -> 0 | F10: =SUMIF(DN!$B:$B,PPvsREal!$C$10,DN!F:F) -> 1923.9636 | G10: =SUMIF(DN!$B:$B,PPvsREal!$C$10,DN!G:G) -> 0 | H10: =SUMIF(DN!$B:$B,PPvsREal!$C$10,DN!H:H) -> 0 | I10: =SUMIF(DN!$B:$B,PPvsREal!$C$10,DN!I:I) -> 0 | J10: =SUMIF(DN!$B:$B,PPvsREal!$C$10,DN!J:J) -> 860.031 | K10: =SUMIF(DN!$B:$B,PPvsREal!$C$10,DN!K:K) -> 0 | L10: =SUMIF(DN!$B:$B,PPvsREal!$C$10,DN!L:L) -> 0 | M10: =SUMIF(DN!$B:$B,PPvsREal!$C$10,DN!M:M) -> 0 | N10: =SUMIF(DN!$B:$B,PPvsREal!$C$10,DN!N:N) -> 4139.247 | O10: =SUMIF(DN!$B:$B,PPvsREal!$C$10,DN!O:O) -> 0 | P10: =SUMIF(DN!$B:$B,PPvsREal!$C$10,DN!P:P) -> 0 | Q10: =SUMIF(DN!$B:$B,PPvsREal!$C$10,DN!Q:Q) -> 0 | R10: =SUMIF(DN!$B:$B,PPvsREal!$C$10,DN!R:R) -> 0 | S10: =SUMIF(DN!$B:$B,PPvsREal!$C$10,DN!S:S) -> 0 | T10: =SUMIF(DN!$B:$B,PPvsREal!$C$10,DN!T:T) -> 2339.314 | U10: =SUMIF(DN!$B:$B,PPvsREal!$C$10,DN!U:U) -> 0 | V10: =SUMIF(DN!$B:$B,PPvsREal!$C$10,DN!V:V) -> 0 | W10: =SUMIF(DN!$B:$B,PPvsREal!$C$10,DN!W:W) -> 0 | X10: =SUMIF(DN!$B:$B,PPvsREal!$C$10,DN!X:X) -> 22600 | Y10: =SUMIF(DN!$B:$B,PPvsREal!$C$10,DN!Y:Y) -> 0 | Z10: =SUMIF(DN!$B:$B,PPvsREal!$C$10,DN!Z:Z) -> 0 | AA10: =SUMIF(DN!$B:$B,PPvsREal!$C$10,DN!AA:AA) -> 0
B11: Comités | C11: 404-017-000-00 | D11: =SUMIF('Comités'!$B:$B,PPvsREal!$C$11,'Comités'!D:D) -> 0 | E11: =SUMIF('Comités'!$B:$B,PPvsREal!$C$11,'Comités'!E:E) -> 0 | F11: =SUMIF('Comités'!$B:$B,PPvsREal!$C$11,'Comités'!F:F) -> 0 | G11: =SUMIF('Comités'!$B:$B,PPvsREal!$C$11,'Comités'!G:G) -> 0 | H11: =SUMIF('Comités'!$B:$B,PPvsREal!$C$11,'Comités'!H:H) -> 0 | I11: =SUMIF('Comités'!$B:$B,PPvsREal!$C$11,'Comités'!I:I) -> 0 | J11: =SUMIF('Comités'!$B:$B,PPvsREal!$C$11,'Comités'!J:J) -> 0 | K11: =SUMIF('Comités'!$B:$B,PPvsREal!$C$11,'Comités'!K:K) -> 0 | L11: =SUMIF('Comités'!$B:$B,PPvsREal!$C$11,'Comités'!L:L) -> 0 | M11: =SUMIF('Comités'!$B:$B,PPvsREal!$C$11,'Comités'!M:M) -> 0 | N11: =SUMIF('Comités'!$B:$B,PPvsREal!$C$11,'Comités'!N:N) -> 0 | O11: =SUMIF('Comités'!$B:$B,PPvsREal!$C$11,'Comités'!O:O) -> 0 | P11: =SUMIF('Comités'!$B:$B,PPvsREal!$C$11,'Comités'!P:P) -> 5000 | Q11: =SUMIF('Comités'!$B:$B,PPvsREal!$C$11,'Comités'!Q:Q) -> 0 | R11: =SUMIF('Comités'!$B:$B,PPvsREal!$C$11,'Comités'!R:R) -> 0 | S11: =SUMIF('Comités'!$B:$B,PPvsREal!$C$11,'Comités'!S:S) -> 0 | T11: =SUMIF('Comités'!$B:$B,PPvsREal!$C$11,'Comités'!T:T) -> 0 | U11: =SUMIF('Comités'!$B:$B,PPvsREal!$C$11,'Comités'!U:U) -> 0 | V11: =SUMIF('Comités'!$B:$B,PPvsREal!$C$11,'Comités'!V:V) -> 0 | W11: =SUMIF('Comités'!$B:$B,PPvsREal!$C$11,'Comités'!W:W) -> 0 | X11: =SUMIF('Comités'!$B:$B,PPvsREal!$C$11,'Comités'!X:X) -> 0 | Y11: =SUMIF('Comités'!$B:$B,PPvsREal!$C$11,'Comités'!Y:Y) -> 0 | Z11: =SUMIF('Comités'!$B:$B,PPvsREal!$C$11,'Comités'!Z:Z) -> 0 | AA11: =SUMIF('Comités'!$B:$B,PPvsREal!$C$11,'Comités'!AA:AA) -> 0
B12: Comités | C12: 404-005-000-00 | D12: =SUMIF('Comités'!$B:$B,PPvsREal!$C$12,'Comités'!D:D) -> 13500 | E12: =SUMIF('Comités'!$B:$B,PPvsREal!$C$12,'Comités'!E:E) -> 0 | F12: =SUMIF('Comités'!$B:$B,PPvsREal!$C$12,'Comités'!F:F) -> 13500 | G12: =SUMIF('Comités'!$B:$B,PPvsREal!$C$12,'Comités'!G:G) -> 0 | H12: =SUMIF('Comités'!$B:$B,PPvsREal!$C$12,'Comités'!H:H) -> 13500 | I12: =SUMIF('Comités'!$B:$B,PPvsREal!$C$12,'Comités'!I:I) -> 0 | J12: =SUMIF('Comités'!$B:$B,PPvsREal!$C$12,'Comités'!J:J) -> 13500 | K12: =SUMIF('Comités'!$B:$B,PPvsREal!$C$12,'Comités'!K:K) -> 0 | L12: =SUMIF('Comités'!$B:$B,PPvsREal!$C$12,'Comités'!L:L) -> 13500 | M12: =SUMIF('Comités'!$B:$B,PPvsREal!$C$12,'Comités'!M:M) -> 0 | N12: =SUMIF('Comités'!$B:$B,PPvsREal!$C$12,'Comités'!N:N) -> 13500 | O12: =SUMIF('Comités'!$B:$B,PPvsREal!$C$12,'Comités'!O:O) -> 0 | P12: =SUMIF('Comités'!$B:$B,PPvsREal!$C$12,'Comités'!P:P) -> 13500 | Q12: =SUMIF('Comités'!$B:$B,PPvsREal!$C$12,'Comités'!Q:Q) -> 0 | R12: =SUMIF('Comités'!$B:$B,PPvsREal!$C$12,'Comités'!R:R) -> 13500 | S12: =SUMIF('Comités'!$B:$B,PPvsREal!$C$12,'Comités'!S:S) -> 0 | T12: =SUMIF('Comités'!$B:$B,PPvsREal!$C$12,'Comités'!T:T) -> 13500 | U12: =SUMIF('Comités'!$B:$B,PPvsREal!$C$12,'Comités'!U:U) -> 0 | V12: =SUMIF('Comités'!$B:$B,PPvsREal!$C$12,'Comités'!V:V) -> 13500 | W12: =SUMIF('Comités'!$B:$B,PPvsREal!$C$12,'Comités'!W:W) -> 0 | X12: =SUMIF('Comités'!$B:$B,PPvsREal!$C$12,'Comités'!X:X) -> 13500 | Y12: =SUMIF('Comités'!$B:$B,PPvsREal!$C$12,'Comités'!Y:Y) -> 0 | Z12: =SUMIF('Comités'!$B:$B,PPvsREal!$C$12,'Comités'!Z:Z) -> 0 | AA12: =SUMIF('Comités'!$B:$B,PPvsREal!$C$12,'Comités'!AA:AA) -> 0
B13: Comités | C13: 404-001-000-00 | D13: =SUMIF('Comités'!$B:$B,PPvsREal!$C$13,'Comités'!D:D) -> 13500 | E13: =SUMIF('Comités'!$B:$B,PPvsREal!$C$13,'Comités'!E:E) -> 0 | F13: =SUMIF('Comités'!$B:$B,PPvsREal!$C$13,'Comités'!F:F) -> 13500 | G13: =SUMIF('Comités'!$B:$B,PPvsREal!$C$13,'Comités'!G:G) -> 0 | H13: =SUMIF('Comités'!$B:$B,PPvsREal!$C$13,'Comités'!H:H) -> 13500 | I13: =SUMIF('Comités'!$B:$B,PPvsREal!$C$13,'Comités'!I:I) -> 0 | J13: =SUMIF('Comités'!$B:$B,PPvsREal!$C$13,'Comités'!J:J) -> 13500 | K13: =SUMIF('Comités'!$B:$B,PPvsREal!$C$13,'Comités'!K:K) -> 0 | L13: =SUMIF('Comités'!$B:$B,PPvsREal!$C$13,'Comités'!L:L) -> 13500 | M13: =SUMIF('Comités'!$B:$B,PPvsREal!$C$13,'Comités'!M:M) -> 0 | N13: =SUMIF('Comités'!$B:$B,PPvsREal!$C$13,'Comités'!N:N) -> 13500 | O13: =SUMIF('Comités'!$B:$B,PPvsREal!$C$13,'Comités'!O:O) -> 0 | P13: =SUMIF('Comités'!$B:$B,PPvsREal!$C$13,'Comités'!P:P) -> 13500 | Q13: =SUMIF('Comités'!$B:$B,PPvsREal!$C$13,'Comités'!Q:Q) -> 0 | R13: =SUMIF('Comités'!$B:$B,PPvsREal!$C$13,'Comités'!R:R) -> 13500 | S13: =SUMIF('Comités'!$B:$B,PPvsREal!$C$13,'Comités'!S:S) -> 0 | T13: =SUMIF('Comités'!$B:$B,PPvsREal!$C$13,'Comités'!T:T) -> 13500 | U13: =SUMIF('Comités'!$B:$B,PPvsREal!$C$13,'Comités'!U:U) -> 0 | V13: =SUMIF('Comités'!$B:$B,PPvsREal!$C$13,'Comités'!V:V) -> 13500 | W13: =SUMIF('Comités'!$B:$B,PPvsREal!$C$13,'Comités'!W:W) -> 0 | X13: =SUMIF('Comités'!$B:$B,PPvsREal!$C$13,'Comités'!X:X) -> 13500 | Y13: =SUMIF('Comités'!$B:$B,PPvsREal!$C$13,'Comités'!Y:Y) -> 0 | Z13: =SUMIF('Comités'!$B:$B,PPvsREal!$C$13,'Comités'!Z:Z) -> 0 | AA13: =SUMIF('Comités'!$B:$B,PPvsREal!$C$13,'Comités'!AA:AA) -> 0
B14: Comités | C14: 404-012-000-00 | D14: =SUMIF('Comités'!$B:$B,PPvsREal!$C$14,'Comités'!D:D) -> 0 | E14: =SUMIF('Comités'!$B:$B,PPvsREal!$C$14,'Comités'!E:E) -> 0 | F14: =SUMIF('Comités'!$B:$B,PPvsREal!$C$14,'Comités'!F:F) -> 0 | G14: =SUMIF('Comités'!$B:$B,PPvsREal!$C$14,'Comités'!G:G) -> 0 | H14: =SUMIF('Comités'!$B:$B,PPvsREal!$C$14,'Comités'!H:H) -> 0 | I14: =SUMIF('Comités'!$B:$B,PPvsREal!$C$14,'Comités'!I:I) -> 0 | J14: =SUMIF('Comités'!$B:$B,PPvsREal!$C$14,'Comités'!J:J) -> 0 | K14: =SUMIF('Comités'!$B:$B,PPvsREal!$C$14,'Comités'!K:K) -> 0 | L14: =SUMIF('Comités'!$B:$B,PPvsREal!$C$14,'Comités'!L:L) -> 0 | M14: =SUMIF('Comités'!$B:$B,PPvsREal!$C$14,'Comités'!M:M) -> 0 | N14: =SUMIF('Comités'!$B:$B,PPvsREal!$C$14,'Comités'!N:N) -> 0 | O14: =SUMIF('Comités'!$B:$B,PPvsREal!$C$14,'Comités'!O:O) -> 0 | P14: =SUMIF('Comités'!$B:$B,PPvsREal!$C$14,'Comités'!P:P) -> 0 | Q14: =SUMIF('Comités'!$B:$B,PPvsREal!$C$14,'Comités'!Q:Q) -> 0 | R14: =SUMIF('Comités'!$B:$B,PPvsREal!$C$14,'Comités'!R:R) -> 0 | S14: =SUMIF('Comités'!$B:$B,PPvsREal!$C$14,'Comités'!S:S) -> 0 | T14: =SUMIF('Comités'!$B:$B,PPvsREal!$C$14,'Comités'!T:T) -> 0 | U14: =SUMIF('Comités'!$B:$B,PPvsREal!$C$14,'Comités'!U:U) -> 0 | V14: =SUMIF('Comités'!$B:$B,PPvsREal!$C$14,'Comités'!V:V) -> 0 | W14: =SUMIF('Comités'!$B:$B,PPvsREal!$C$14,'Comités'!W:W) -> 0 | X14: =SUMIF('Comités'!$B:$B,PPvsREal!$C$14,'Comités'!X:X) -> 0 | Y14: =SUMIF('Comités'!$B:$B,PPvsREal!$C$14,'Comités'!Y:Y) -> 0 | Z14: =SUMIF('Comités'!$B:$B,PPvsREal!$C$14,'Comités'!Z:Z) -> 0 | AA14: =SUMIF('Comités'!$B:$B,PPvsREal!$C$14,'Comités'!AA:AA) -> 0
B15: Comités | C15: 404-003-000-00 | D15: =SUMIF('Comités'!$B:$B,PPvsREal!$C$15,'Comités'!D:D) -> 13500 | E15: =SUMIF('Comités'!$B:$B,PPvsREal!$C$15,'Comités'!E:E) -> 0 | F15: =SUMIF('Comités'!$B:$B,PPvsREal!$C$15,'Comités'!F:F) -> 13500 | G15: =SUMIF('Comités'!$B:$B,PPvsREal!$C$15,'Comités'!G:G) -> 0 | H15: =SUMIF('Comités'!$B:$B,PPvsREal!$C$15,'Comités'!H:H) -> 13500 | I15: =SUMIF('Comités'!$B:$B,PPvsREal!$C$15,'Comités'!I:I) -> 0 | J15: =SUMIF('Comités'!$B:$B,PPvsREal!$C$15,'Comités'!J:J) -> 13500 | K15: =SUMIF('Comités'!$B:$B,PPvsREal!$C$15,'Comités'!K:K) -> 0 | L15: =SUMIF('Comités'!$B:$B,PPvsREal!$C$15,'Comités'!L:L) -> 13500 | M15: =SUMIF('Comités'!$B:$B,PPvsREal!$C$15,'Comités'!M:M) -> 0 | N15: =SUMIF('Comités'!$B:$B,PPvsREal!$C$15,'Comités'!N:N) -> 13500 | O15: =SUMIF('Comités'!$B:$B,PPvsREal!$C$15,'Comités'!O:O) -> 0 | P15: =SUMIF('Comités'!$B:$B,PPvsREal!$C$15,'Comités'!P:P) -> 13500 | Q15: =SUMIF('Comités'!$B:$B,PPvsREal!$C$15,'Comités'!Q:Q) -> 0 | R15: =SUMIF('Comités'!$B:$B,PPvsREal!$C$15,'Comités'!R:R) -> 13500 | S15: =SUMIF('Comités'!$B:$B,PPvsREal!$C$15,'Comités'!S:S) -> 0 | T15: =SUMIF('Comités'!$B:$B,PPvsREal!$C$15,'Comités'!T:T) -> 13500 | U15: =SUMIF('Comités'!$B:$B,PPvsREal!$C$15,'Comités'!U:U) -> 0 | V15: =SUMIF('Comités'!$B:$B,PPvsREal!$C$15,'Comités'!V:V) -> 13500 | W15: =SUMIF('Comités'!$B:$B,PPvsREal!$C$15,'Comités'!W:W) -> 0 | X15: =SUMIF('Comités'!$B:$B,PPvsREal!$C$15,'Comités'!X:X) -> 13500 | Y15: =SUMIF('Comités'!$B:$B,PPvsREal!$C$15,'Comités'!Y:Y) -> 0 | Z15: =SUMIF('Comités'!$B:$B,PPvsREal!$C$15,'Comités'!Z:Z) -> 0 | AA15: =SUMIF('Comités'!$B:$B,PPvsREal!$C$15,'Comités'!AA:AA) -> 0
B16: Comités | C16: 404-013-000-00 | D16: =SUMIF('Comités'!$B:$B,PPvsREal!$C$16,'Comités'!D:D) -> 0 | E16: =SUMIF('Comités'!$B:$B,PPvsREal!$C$16,'Comités'!E:E) -> 0 | F16: =SUMIF('Comités'!$B:$B,PPvsREal!$C$16,'Comités'!F:F) -> 0 | G16: =SUMIF('Comités'!$B:$B,PPvsREal!$C$16,'Comités'!G:G) -> 0 | H16: =SUMIF('Comités'!$B:$B,PPvsREal!$C$16,'Comités'!H:H) -> 0 | I16: =SUMIF('Comités'!$B:$B,PPvsREal!$C$16,'Comités'!I:I) -> 0 | J16: =SUMIF('Comités'!$B:$B,PPvsREal!$C$16,'Comités'!J:J) -> 0 | K16: =SUMIF('Comités'!$B:$B,PPvsREal!$C$16,'Comités'!K:K) -> 0 | L16: =SUMIF('Comités'!$B:$B,PPvsREal!$C$16,'Comités'!L:L) -> 0 | M16: =SUMIF('Comités'!$B:$B,PPvsREal!$C$16,'Comités'!M:M) -> 0 | N16: =SUMIF('Comités'!$B:$B,PPvsREal!$C$16,'Comités'!N:N) -> 0 | O16: =SUMIF('Comités'!$B:$B,PPvsREal!$C$16,'Comités'!O:O) -> 0 | P16: =SUMIF('Comités'!$B:$B,PPvsREal!$C$16,'Comités'!P:P) -> 0 | Q16: =SUMIF('Comités'!$B:$B,PPvsREal!$C$16,'Comités'!Q:Q) -> 0 | R16: =SUMIF('Comités'!$B:$B,PPvsREal!$C$16,'Comités'!R:R) -> 0 | S16: =SUMIF('Comités'!$B:$B,PPvsREal!$C$16,'Comités'!S:S) -> 0 | T16: =SUMIF('Comités'!$B:$B,PPvsREal!$C$16,'Comités'!T:T) -> 0 | U16: =SUMIF('Comités'!$B:$B,PPvsREal!$C$16,'Comités'!U:U) -> 0 | V16: =SUMIF('Comités'!$B:$B,PPvsREal!$C$16,'Comités'!V:V) -> 0 | W16: =SUMIF('Comités'!$B:$B,PPvsREal!$C$16,'Comités'!W:W) -> 0 | X16: =SUMIF('Comités'!$B:$B,PPvsREal!$C$16,'Comités'!X:X) -> 0 | Y16: =SUMIF('Comités'!$B:$B,PPvsREal!$C$16,'Comités'!Y:Y) -> 0 | Z16: =SUMIF('Comités'!$B:$B,PPvsREal!$C$16,'Comités'!Z:Z) -> 0 | AA16: =SUMIF('Comités'!$B:$B,PPvsREal!$C$16,'Comités'!AA:AA) -> 0
B17: Comités | C17: 404-007-000-00 | D17: =SUMIF('Comités'!$B:$B,PPvsREal!$C$17,'Comités'!D:D) -> 0 | E17: =SUMIF('Comités'!$B:$B,PPvsREal!$C$17,'Comités'!E:E) -> 0 | F17: =SUMIF('Comités'!$B:$B,PPvsREal!$C$17,'Comités'!F:F) -> 0 | G17: =SUMIF('Comités'!$B:$B,PPvsREal!$C$17,'Comités'!G:G) -> 0 | H17: =SUMIF('Comités'!$B:$B,PPvsREal!$C$17,'Comités'!H:H) -> 0 | I17: =SUMIF('Comités'!$B:$B,PPvsREal!$C$17,'Comités'!I:I) -> 0 | J17: =SUMIF('Comités'!$B:$B,PPvsREal!$C$17,'Comités'!J:J) -> 0 | K17: =SUMIF('Comités'!$B:$B,PPvsREal!$C$17,'Comités'!K:K) -> 0 | L17: =SUMIF('Comités'!$B:$B,PPvsREal!$C$17,'Comités'!L:L) -> 0 | M17: =SUMIF('Comités'!$B:$B,PPvsREal!$C$17,'Comités'!M:M) -> 0 | N17: =SUMIF('Comités'!$B:$B,PPvsREal!$C$17,'Comités'!N:N) -> 0 | O17: =SUMIF('Comités'!$B:$B,PPvsREal!$C$17,'Comités'!O:O) -> 0 | P17: =SUMIF('Comités'!$B:$B,PPvsREal!$C$17,'Comités'!P:P) -> 0 | Q17: =SUMIF('Comités'!$B:$B,PPvsREal!$C$17,'Comités'!Q:Q) -> 0 | R17: =SUMIF('Comités'!$B:$B,PPvsREal!$C$17,'Comités'!R:R) -> 0 | S17: =SUMIF('Comités'!$B:$B,PPvsREal!$C$17,'Comités'!S:S) -> 0 | T17: =SUMIF('Comités'!$B:$B,PPvsREal!$C$17,'Comités'!T:T) -> 0 | U17: =SUMIF('Comités'!$B:$B,PPvsREal!$C$17,'Comités'!U:U) -> 0 | V17: =SUMIF('Comités'!$B:$B,PPvsREal!$C$17,'Comités'!V:V) -> 0 | W17: =SUMIF('Comités'!$B:$B,PPvsREal!$C$17,'Comités'!W:W) -> 0 | X17: =SUMIF('Comités'!$B:$B,PPvsREal!$C$17,'Comités'!X:X) -> 0 | Y17: =SUMIF('Comités'!$B:$B,PPvsREal!$C$17,'Comités'!Y:Y) -> 0 | Z17: =SUMIF('Comités'!$B:$B,PPvsREal!$C$17,'Comités'!Z:Z) -> 0 | AA17: =SUMIF('Comités'!$B:$B,PPvsREal!$C$17,'Comités'!AA:AA) -> 0
B18: Comités | C18: 404-016-000-00 | D18: =SUMIF('Comités'!$B:$B,PPvsREal!$C$18,'Comités'!D:D) -> 0 | E18: =SUMIF('Comités'!$B:$B,PPvsREal!$C$18,'Comités'!E:E) -> 0 | F18: =SUMIF('Comités'!$B:$B,PPvsREal!$C$18,'Comités'!F:F) -> 0 | G18: =SUMIF('Comités'!$B:$B,PPvsREal!$C$18,'Comités'!G:G) -> 0 | H18: =SUMIF('Comités'!$B:$B,PPvsREal!$C$18,'Comités'!H:H) -> 0 | I18: =SUMIF('Comités'!$B:$B,PPvsREal!$C$18,'Comités'!I:I) -> 0 | J18: =SUMIF('Comités'!$B:$B,PPvsREal!$C$18,'Comités'!J:J) -> 0 | K18: =SUMIF('Comités'!$B:$B,PPvsREal!$C$18,'Comités'!K:K) -> 0 | L18: =SUMIF('Comités'!$B:$B,PPvsREal!$C$18,'Comités'!L:L) -> 0 | M18: =SUMIF('Comités'!$B:$B,PPvsREal!$C$18,'Comités'!M:M) -> 0 | N18: =SUMIF('Comités'!$B:$B,PPvsREal!$C$18,'Comités'!N:N) -> 0 | O18: =SUMIF('Comités'!$B:$B,PPvsREal!$C$18,'Comités'!O:O) -> 0 | P18: =SUMIF('Comités'!$B:$B,PPvsREal!$C$18,'Comités'!P:P) -> 0 | Q18: =SUMIF('Comités'!$B:$B,PPvsREal!$C$18,'Comités'!Q:Q) -> 0 | R18: =SUMIF('Comités'!$B:$B,PPvsREal!$C$18,'Comités'!R:R) -> 0 | S18: =SUMIF('Comités'!$B:$B,PPvsREal!$C$18,'Comités'!S:S) -> 0 | T18: =SUMIF('Comités'!$B:$B,PPvsREal!$C$18,'Comités'!T:T) -> 0 | U18: =SUMIF('Comités'!$B:$B,PPvsREal!$C$18,'Comités'!U:U) -> 0 | V18: =SUMIF('Comités'!$B:$B,PPvsREal!$C$18,'Comités'!V:V) -> 0 | W18: =SUMIF('Comités'!$B:$B,PPvsREal!$C$18,'Comités'!W:W) -> 0 | X18: =SUMIF('Comités'!$B:$B,PPvsREal!$C$18,'Comités'!X:X) -> 0 | Y18: =SUMIF('Comités'!$B:$B,PPvsREal!$C$18,'Comités'!Y:Y) -> 0 | Z18: =SUMIF('Comités'!$B:$B,PPvsREal!$C$18,'Comités'!Z:Z) -> 0 | AA18: =SUMIF('Comités'!$B:$B,PPvsREal!$C$18,'Comités'!AA:AA) -> 0
B19: Comités | C19: 404-004-000-00 | D19: =SUMIF('Comités'!$B:$B,PPvsREal!$C$19,'Comités'!D:D) -> 0 | E19: =SUMIF('Comités'!$B:$B,PPvsREal!$C$19,'Comités'!E:E) -> 0 | F19: =SUMIF('Comités'!$B:$B,PPvsREal!$C$19,'Comités'!F:F) -> 0 | G19: =SUMIF('Comités'!$B:$B,PPvsREal!$C$19,'Comités'!G:G) -> 0 | H19: =SUMIF('Comités'!$B:$B,PPvsREal!$C$19,'Comités'!H:H) -> 0 | I19: =SUMIF('Comités'!$B:$B,PPvsREal!$C$19,'Comités'!I:I) -> 0 | J19: =SUMIF('Comités'!$B:$B,PPvsREal!$C$19,'Comités'!J:J) -> 0 | K19: =SUMIF('Comités'!$B:$B,PPvsREal!$C$19,'Comités'!K:K) -> 0 | L19: =SUMIF('Comités'!$B:$B,PPvsREal!$C$19,'Comités'!L:L) -> 0 | M19: =SUMIF('Comités'!$B:$B,PPvsREal!$C$19,'Comités'!M:M) -> 0 | N19: =SUMIF('Comités'!$B:$B,PPvsREal!$C$19,'Comités'!N:N) -> 0 | O19: =SUMIF('Comités'!$B:$B,PPvsREal!$C$19,'Comités'!O:O) -> 0 | P19: =SUMIF('Comités'!$B:$B,PPvsREal!$C$19,'Comités'!P:P) -> 0 | Q19: =SUMIF('Comités'!$B:$B,PPvsREal!$C$19,'Comités'!Q:Q) -> 0 | R19: =SUMIF('Comités'!$B:$B,PPvsREal!$C$19,'Comités'!R:R) -> 0 | S19: =SUMIF('Comités'!$B:$B,PPvsREal!$C$19,'Comités'!S:S) -> 0 | T19: =SUMIF('Comités'!$B:$B,PPvsREal!$C$19,'Comités'!T:T) -> 0 | U19: =SUMIF('Comités'!$B:$B,PPvsREal!$C$19,'Comités'!U:U) -> 0 | V19: =SUMIF('Comités'!$B:$B,PPvsREal!$C$19,'Comités'!V:V) -> 0 | W19: =SUMIF('Comités'!$B:$B,PPvsREal!$C$19,'Comités'!W:W) -> 0 | X19: =SUMIF('Comités'!$B:$B,PPvsREal!$C$19,'Comités'!X:X) -> 0 | Y19: =SUMIF('Comités'!$B:$B,PPvsREal!$C$19,'Comités'!Y:Y) -> 0 | Z19: =SUMIF('Comités'!$B:$B,PPvsREal!$C$19,'Comités'!Z:Z) -> 0 | AA19: =SUMIF('Comités'!$B:$B,PPvsREal!$C$19,'Comités'!AA:AA) -> 0
B20: Comités | C20: 404-008-000-00 | D20: =SUMIF('Comités'!$B:$B,PPvsREal!$C$20,'Comités'!D:D) -> 0 | E20: =SUMIF('Comités'!$B:$B,PPvsREal!$C$20,'Comités'!E:E) -> 0 | F20: =SUMIF('Comités'!$B:$B,PPvsREal!$C$20,'Comités'!F:F) -> 0 | G20: =SUMIF('Comités'!$B:$B,PPvsREal!$C$20,'Comités'!G:G) -> 0 | H20: =SUMIF('Comités'!$B:$B,PPvsREal!$C$20,'Comités'!H:H) -> 0 | I20: =SUMIF('Comités'!$B:$B,PPvsREal!$C$20,'Comités'!I:I) -> 0 | J20: =SUMIF('Comités'!$B:$B,PPvsREal!$C$20,'Comités'!J:J) -> 0 | K20: =SUMIF('Comités'!$B:$B,PPvsREal!$C$20,'Comités'!K:K) -> 0 | L20: =SUMIF('Comités'!$B:$B,PPvsREal!$C$20,'Comités'!L:L) -> 0 | M20: =SUMIF('Comités'!$B:$B,PPvsREal!$C$20,'Comités'!M:M) -> 0 | N20: =SUMIF('Comités'!$B:$B,PPvsREal!$C$20,'Comités'!N:N) -> 0 | O20: =SUMIF('Comités'!$B:$B,PPvsREal!$C$20,'Comités'!O:O) -> 0 | P20: =SUMIF('Comités'!$B:$B,PPvsREal!$C$20,'Comités'!P:P) -> 0 | Q20: =SUMIF('Comités'!$B:$B,PPvsREal!$C$20,'Comités'!Q:Q) -> 0 | R20: =SUMIF('Comités'!$B:$B,PPvsREal!$C$20,'Comités'!R:R) -> 0 | S20: =SUMIF('Comités'!$B:$B,PPvsREal!$C$20,'Comités'!S:S) -> 0 | T20: =SUMIF('Comités'!$B:$B,PPvsREal!$C$20,'Comités'!T:T) -> 0 | U20: =SUMIF('Comités'!$B:$B,PPvsREal!$C$20,'Comités'!U:U) -> 0 | V20: =SUMIF('Comités'!$B:$B,PPvsREal!$C$20,'Comités'!V:V) -> 0 | W20: =SUMIF('Comités'!$B:$B,PPvsREal!$C$20,'Comités'!W:W) -> 0 | X20: =SUMIF('Comités'!$B:$B,PPvsREal!$C$20,'Comités'!X:X) -> 0 | Y20: =SUMIF('Comités'!$B:$B,PPvsREal!$C$20,'Comités'!Y:Y) -> 0 | Z20: =SUMIF('Comités'!$B:$B,PPvsREal!$C$20,'Comités'!Z:Z) -> 0 | AA20: =SUMIF('Comités'!$B:$B,PPvsREal!$C$20,'Comités'!AA:AA) -> 0
B21: Comités | C21: 404-009-000-00 | D21: =SUMIF('Comités'!$B:$B,PPvsREal!$C$21,'Comités'!D:D) -> 0 | E21: =SUMIF('Comités'!$B:$B,PPvsREal!$C$21,'Comités'!E:E) -> 0 | F21: =SUMIF('Comités'!$B:$B,PPvsREal!$C$21,'Comités'!F:F) -> 0 | G21: =SUMIF('Comités'!$B:$B,PPvsREal!$C$21,'Comités'!G:G) -> 0 | H21: =SUMIF('Comités'!$B:$B,PPvsREal!$C$21,'Comités'!H:H) -> 0 | I21: =SUMIF('Comités'!$B:$B,PPvsREal!$C$21,'Comités'!I:I) -> 0 | J21: =SUMIF('Comités'!$B:$B,PPvsREal!$C$21,'Comités'!J:J) -> 0 | K21: =SUMIF('Comités'!$B:$B,PPvsREal!$C$21,'Comités'!K:K) -> 0 | L21: =SUMIF('Comités'!$B:$B,PPvsREal!$C$21,'Comités'!L:L) -> 0 | M21: =SUMIF('Comités'!$B:$B,PPvsREal!$C$21,'Comités'!M:M) -> 0 | N21: =SUMIF('Comités'!$B:$B,PPvsREal!$C$21,'Comités'!N:N) -> 0 | O21: =SUMIF('Comités'!$B:$B,PPvsREal!$C$21,'Comités'!O:O) -> 0 | P21: =SUMIF('Comités'!$B:$B,PPvsREal!$C$21,'Comités'!P:P) -> 0 | Q21: =SUMIF('Comités'!$B:$B,PPvsREal!$C$21,'Comités'!Q:Q) -> 0 | R21: =SUMIF('Comités'!$B:$B,PPvsREal!$C$21,'Comités'!R:R) -> 0 | S21: =SUMIF('Comités'!$B:$B,PPvsREal!$C$21,'Comités'!S:S) -> 0 | T21: =SUMIF('Comités'!$B:$B,PPvsREal!$C$21,'Comités'!T:T) -> 0 | U21: =SUMIF('Comités'!$B:$B,PPvsREal!$C$21,'Comités'!U:U) -> 0 | V21: =SUMIF('Comités'!$B:$B,PPvsREal!$C$21,'Comités'!V:V) -> 0 | W21: =SUMIF('Comités'!$B:$B,PPvsREal!$C$21,'Comités'!W:W) -> 0 | X21: =SUMIF('Comités'!$B:$B,PPvsREal!$C$21,'Comités'!X:X) -> 0 | Y21: =SUMIF('Comités'!$B:$B,PPvsREal!$C$21,'Comités'!Y:Y) -> 0 | Z21: =SUMIF('Comités'!$B:$B,PPvsREal!$C$21,'Comités'!Z:Z) -> 0 | AA21: =SUMIF('Comités'!$B:$B,PPvsREal!$C$21,'Comités'!AA:AA) -> 0
B22: Comités | C22: 404-018-000-00 | D22: =SUMIF('Comités'!$B:$B,PPvsREal!$C$22,'Comités'!D:D) -> 0 | E22: =SUMIF('Comités'!$B:$B,PPvsREal!$C$22,'Comités'!E:E) -> 0 | F22: =SUMIF('Comités'!$B:$B,PPvsREal!$C$22,'Comités'!F:F) -> 0 | G22: =SUMIF('Comités'!$B:$B,PPvsREal!$C$22,'Comités'!G:G) -> 0 | H22: =SUMIF('Comités'!$B:$B,PPvsREal!$C$22,'Comités'!H:H) -> 0 | I22: =SUMIF('Comités'!$B:$B,PPvsREal!$C$22,'Comités'!I:I) -> 0 | J22: =SUMIF('Comités'!$B:$B,PPvsREal!$C$22,'Comités'!J:J) -> 0 | K22: =SUMIF('Comités'!$B:$B,PPvsREal!$C$22,'Comités'!K:K) -> 0 | L22: =SUMIF('Comités'!$B:$B,PPvsREal!$C$22,'Comités'!L:L) -> 142928.57 | M22: =SUMIF('Comités'!$B:$B,PPvsREal!$C$22,'Comités'!M:M) -> 0 | N22: =SUMIF('Comités'!$B:$B,PPvsREal!$C$22,'Comités'!N:N) -> 286845.23 | O22: =SUMIF('Comités'!$B:$B,PPvsREal!$C$22,'Comités'!O:O) -> 0 | P22: =SUMIF('Comités'!$B:$B,PPvsREal!$C$22,'Comités'!P:P) -> 239178.56 | Q22: =SUMIF('Comités'!$B:$B,PPvsREal!$C$22,'Comités'!Q:Q) -> 0 | R22: =SUMIF('Comités'!$B:$B,PPvsREal!$C$22,'Comités'!R:R) -> 183345.23 | S22: =SUMIF('Comités'!$B:$B,PPvsREal!$C$22,'Comités'!S:S) -> 0 | T22: =SUMIF('Comités'!$B:$B,PPvsREal!$C$22,'Comités'!T:T) -> 83345.23 | U22: =SUMIF('Comités'!$B:$B,PPvsREal!$C$22,'Comités'!U:U) -> 0 | V22: =SUMIF('Comités'!$B:$B,PPvsREal!$C$22,'Comités'!V:V) -> 71428.57 | W22: =SUMIF('Comités'!$B:$B,PPvsREal!$C$22,'Comités'!W:W) -> 0 | X22: =SUMIF('Comités'!$B:$B,PPvsREal!$C$22,'Comités'!X:X) -> 71428.57 | Y22: =SUMIF('Comités'!$B:$B,PPvsREal!$C$22,'Comités'!Y:Y) -> 0 | Z22: =SUMIF('Comités'!$B:$B,PPvsREal!$C$22,'Comités'!Z:Z) -> 0 | AA22: =SUMIF('Comités'!$B:$B,PPvsREal!$C$22,'Comités'!AA:AA) -> 0
B23: Comités | C23: 502-014-000-00 | D23: =SUMIF('Comités'!$B:$B,PPvsREal!$C$23,'Comités'!D:D) -> 0 | E23: =SUMIF('Comités'!$B:$B,PPvsREal!$C$23,'Comités'!E:E) -> 0 | F23: =SUMIF('Comités'!$B:$B,PPvsREal!$C$23,'Comités'!F:F) -> 500 | G23: =SUMIF('Comités'!$B:$B,PPvsREal!$C$23,'Comités'!G:G) -> 0 | H23: =SUMIF('Comités'!$B:$B,PPvsREal!$C$23,'Comités'!H:H) -> 500 | I23: =SUMIF('Comités'!$B:$B,PPvsREal!$C$23,'Comités'!I:I) -> 0 | J23: =SUMIF('Comités'!$B:$B,PPvsREal!$C$23,'Comités'!J:J) -> 500 | K23: =SUMIF('Comités'!$B:$B,PPvsREal!$C$23,'Comités'!K:K) -> 0 | L23: =SUMIF('Comités'!$B:$B,PPvsREal!$C$23,'Comités'!L:L) -> 500 | M23: =SUMIF('Comités'!$B:$B,PPvsREal!$C$23,'Comités'!M:M) -> 0 | N23: =SUMIF('Comités'!$B:$B,PPvsREal!$C$23,'Comités'!N:N) -> 500 | O23: =SUMIF('Comités'!$B:$B,PPvsREal!$C$23,'Comités'!O:O) -> 0 | P23: =SUMIF('Comités'!$B:$B,PPvsREal!$C$23,'Comités'!P:P) -> 500 | Q23: =SUMIF('Comités'!$B:$B,PPvsREal!$C$23,'Comités'!Q:Q) -> 0 | R23: =SUMIF('Comités'!$B:$B,PPvsREal!$C$23,'Comités'!R:R) -> 500 | S23: =SUMIF('Comités'!$B:$B,PPvsREal!$C$23,'Comités'!S:S) -> 0 | T23: =SUMIF('Comités'!$B:$B,PPvsREal!$C$23,'Comités'!T:T) -> 500 | U23: =SUMIF('Comités'!$B:$B,PPvsREal!$C$23,'Comités'!U:U) -> 0 | V23: =SUMIF('Comités'!$B:$B,PPvsREal!$C$23,'Comités'!V:V) -> 500 | W23: =SUMIF('Comités'!$B:$B,PPvsREal!$C$23,'Comités'!W:W) -> 0 | X23: =SUMIF('Comités'!$B:$B,PPvsREal!$C$23,'Comités'!X:X) -> 500 | Y23: =SUMIF('Comités'!$B:$B,PPvsREal!$C$23,'Comités'!Y:Y) -> 0 | Z23: =SUMIF('Comités'!$B:$B,PPvsREal!$C$23,'Comités'!Z:Z) -> 0 | AA23: =SUMIF('Comités'!$B:$B,PPvsREal!$C$23,'Comités'!AA:AA) -> 0
B24: Comités | C24: 502-005-000-00 | D24: =SUMIF('Comités'!$B:$B,PPvsREal!$C$24,'Comités'!D:D) -> 12000 | E24: =SUMIF('Comités'!$B:$B,PPvsREal!$C$24,'Comités'!E:E) -> 0 | F24: =SUMIF('Comités'!$B:$B,PPvsREal!$C$24,'Comités'!F:F) -> 12000 | G24: =SUMIF('Comités'!$B:$B,PPvsREal!$C$24,'Comités'!G:G) -> 0 | H24: =SUMIF('Comités'!$B:$B,PPvsREal!$C$24,'Comités'!H:H) -> 12000 | I24: =SUMIF('Comités'!$B:$B,PPvsREal!$C$24,'Comités'!I:I) -> 0 | J24: =SUMIF('Comités'!$B:$B,PPvsREal!$C$24,'Comités'!J:J) -> 12000 | K24: =SUMIF('Comités'!$B:$B,PPvsREal!$C$24,'Comités'!K:K) -> 0 | L24: =SUMIF('Comités'!$B:$B,PPvsREal!$C$24,'Comités'!L:L) -> 12000 | M24: =SUMIF('Comités'!$B:$B,PPvsREal!$C$24,'Comités'!M:M) -> 0 | N24: =SUMIF('Comités'!$B:$B,PPvsREal!$C$24,'Comités'!N:N) -> 12000 | O24: =SUMIF('Comités'!$B:$B,PPvsREal!$C$24,'Comités'!O:O) -> 0 | P24: =SUMIF('Comités'!$B:$B,PPvsREal!$C$24,'Comités'!P:P) -> 12000 | Q24: =SUMIF('Comités'!$B:$B,PPvsREal!$C$24,'Comités'!Q:Q) -> 0 | R24: =SUMIF('Comités'!$B:$B,PPvsREal!$C$24,'Comités'!R:R) -> 12000 | S24: =SUMIF('Comités'!$B:$B,PPvsREal!$C$24,'Comités'!S:S) -> 0 | T24: =SUMIF('Comités'!$B:$B,PPvsREal!$C$24,'Comités'!T:T) -> 12000 | U24: =SUMIF('Comités'!$B:$B,PPvsREal!$C$24,'Comités'!U:U) -> 0 | V24: =SUMIF('Comités'!$B:$B,PPvsREal!$C$24,'Comités'!V:V) -> 12000 | W24: =SUMIF('Comités'!$B:$B,PPvsREal!$C$24,'Comités'!W:W) -> 0 | X24: =SUMIF('Comités'!$B:$B,PPvsREal!$C$24,'Comités'!X:X) -> 12000 | Y24: =SUMIF('Comités'!$B:$B,PPvsREal!$C$24,'Comités'!Y:Y) -> 0 | Z24: =SUMIF('Comités'!$B:$B,PPvsREal!$C$24,'Comités'!Z:Z) -> 0 | AA24: =SUMIF('Comités'!$B:$B,PPvsREal!$C$24,'Comités'!AA:AA) -> 0
B25: Comités | C25: 502-001-000-00 | D25: =SUMIF('Comités'!$B:$B,PPvsREal!$C$25,'Comités'!D:D) -> 12000 | E25: =SUMIF('Comités'!$B:$B,PPvsREal!$C$25,'Comités'!E:E) -> 0 | F25: =SUMIF('Comités'!$B:$B,PPvsREal!$C$25,'Comités'!F:F) -> 12000 | G25: =SUMIF('Comités'!$B:$B,PPvsREal!$C$25,'Comités'!G:G) -> 0 | H25: =SUMIF('Comités'!$B:$B,PPvsREal!$C$25,'Comités'!H:H) -> 12000 | I25: =SUMIF('Comités'!$B:$B,PPvsREal!$C$25,'Comités'!I:I) -> 0 | J25: =SUMIF('Comités'!$B:$B,PPvsREal!$C$25,'Comités'!J:J) -> 12000 | K25: =SUMIF('Comités'!$B:$B,PPvsREal!$C$25,'Comités'!K:K) -> 0 | L25: =SUMIF('Comités'!$B:$B,PPvsREal!$C$25,'Comités'!L:L) -> 12000 | M25: =SUMIF('Comités'!$B:$B,PPvsREal!$C$25,'Comités'!M:M) -> 0 | N25: =SUMIF('Comités'!$B:$B,PPvsREal!$C$25,'Comités'!N:N) -> 12000 | O25: =SUMIF('Comités'!$B:$B,PPvsREal!$C$25,'Comités'!O:O) -> 0 | P25: =SUMIF('Comités'!$B:$B,PPvsREal!$C$25,'Comités'!P:P) -> 12000 | Q25: =SUMIF('Comités'!$B:$B,PPvsREal!$C$25,'Comités'!Q:Q) -> 0 | R25: =SUMIF('Comités'!$B:$B,PPvsREal!$C$25,'Comités'!R:R) -> 12000 | S25: =SUMIF('Comités'!$B:$B,PPvsREal!$C$25,'Comités'!S:S) -> 0 | T25: =SUMIF('Comités'!$B:$B,PPvsREal!$C$25,'Comités'!T:T) -> 12000 | U25: =SUMIF('Comités'!$B:$B,PPvsREal!$C$25,'Comités'!U:U) -> 0 | V25: =SUMIF('Comités'!$B:$B,PPvsREal!$C$25,'Comités'!V:V) -> 12000 | W25: =SUMIF('Comités'!$B:$B,PPvsREal!$C$25,'Comités'!W:W) -> 0 | X25: =SUMIF('Comités'!$B:$B,PPvsREal!$C$25,'Comités'!X:X) -> 12000 | Y25: =SUMIF('Comités'!$B:$B,PPvsREal!$C$25,'Comités'!Y:Y) -> 0 | Z25: =SUMIF('Comités'!$B:$B,PPvsREal!$C$25,'Comités'!Z:Z) -> 0 | AA25: =SUMIF('Comités'!$B:$B,PPvsREal!$C$25,'Comités'!AA:AA) -> 0
B26: Comités | C26: 502-008-000-00 | D26: =SUMIF('Comités'!$B:$B,PPvsREal!$C$26,'Comités'!D:D) -> 0 | E26: =SUMIF('Comités'!$B:$B,PPvsREal!$C$26,'Comités'!E:E) -> 0 | F26: =SUMIF('Comités'!$B:$B,PPvsREal!$C$26,'Comités'!F:F) -> 500 | G26: =SUMIF('Comités'!$B:$B,PPvsREal!$C$26,'Comités'!G:G) -> 0 | H26: =SUMIF('Comités'!$B:$B,PPvsREal!$C$26,'Comités'!H:H) -> 500 | I26: =SUMIF('Comités'!$B:$B,PPvsREal!$C$26,'Comités'!I:I) -> 0 | J26: =SUMIF('Comités'!$B:$B,PPvsREal!$C$26,'Comités'!J:J) -> 500 | K26: =SUMIF('Comités'!$B:$B,PPvsREal!$C$26,'Comités'!K:K) -> 0 | L26: =SUMIF('Comités'!$B:$B,PPvsREal!$C$26,'Comités'!L:L) -> 500 | M26: =SUMIF('Comités'!$B:$B,PPvsREal!$C$26,'Comités'!M:M) -> 0 | N26: =SUMIF('Comités'!$B:$B,PPvsREal!$C$26,'Comités'!N:N) -> 500 | O26: =SUMIF('Comités'!$B:$B,PPvsREal!$C$26,'Comités'!O:O) -> 0 | P26: =SUMIF('Comités'!$B:$B,PPvsREal!$C$26,'Comités'!P:P) -> 500 | Q26: =SUMIF('Comités'!$B:$B,PPvsREal!$C$26,'Comités'!Q:Q) -> 0 | R26: =SUMIF('Comités'!$B:$B,PPvsREal!$C$26,'Comités'!R:R) -> 500 | S26: =SUMIF('Comités'!$B:$B,PPvsREal!$C$26,'Comités'!S:S) -> 0 | T26: =SUMIF('Comités'!$B:$B,PPvsREal!$C$26,'Comités'!T:T) -> 500 | U26: =SUMIF('Comités'!$B:$B,PPvsREal!$C$26,'Comités'!U:U) -> 0 | V26: =SUMIF('Comités'!$B:$B,PPvsREal!$C$26,'Comités'!V:V) -> 500 | W26: =SUMIF('Comités'!$B:$B,PPvsREal!$C$26,'Comités'!W:W) -> 0 | X26: =SUMIF('Comités'!$B:$B,PPvsREal!$C$26,'Comités'!X:X) -> 500 | Y26: =SUMIF('Comités'!$B:$B,PPvsREal!$C$26,'Comités'!Y:Y) -> 0 | Z26: =SUMIF('Comités'!$B:$B,PPvsREal!$C$26,'Comités'!Z:Z) -> 0 | AA26: =SUMIF('Comités'!$B:$B,PPvsREal!$C$26,'Comités'!AA:AA) -> 0
B27: Comités | C27: 502-003-000-00 | D27: =SUMIF('Comités'!$B:$B,PPvsREal!$C$27,'Comités'!D:D) -> 12000 | E27: =SUMIF('Comités'!$B:$B,PPvsREal!$C$27,'Comités'!E:E) -> 0 | F27: =SUMIF('Comités'!$B:$B,PPvsREal!$C$27,'Comités'!F:F) -> 12000 | G27: =SUMIF('Comités'!$B:$B,PPvsREal!$C$27,'Comités'!G:G) -> 0 | H27: =SUMIF('Comités'!$B:$B,PPvsREal!$C$27,'Comités'!H:H) -> 12000 | I27: =SUMIF('Comités'!$B:$B,PPvsREal!$C$27,'Comités'!I:I) -> 0 | J27: =SUMIF('Comités'!$B:$B,PPvsREal!$C$27,'Comités'!J:J) -> 12000 | K27: =SUMIF('Comités'!$B:$B,PPvsREal!$C$27,'Comités'!K:K) -> 0 | L27: =SUMIF('Comités'!$B:$B,PPvsREal!$C$27,'Comités'!L:L) -> 12000 | M27: =SUMIF('Comités'!$B:$B,PPvsREal!$C$27,'Comités'!M:M) -> 0 | N27: =SUMIF('Comités'!$B:$B,PPvsREal!$C$27,'Comités'!N:N) -> 12000 | O27: =SUMIF('Comités'!$B:$B,PPvsREal!$C$27,'Comités'!O:O) -> 0 | P27: =SUMIF('Comités'!$B:$B,PPvsREal!$C$27,'Comités'!P:P) -> 12000 | Q27: =SUMIF('Comités'!$B:$B,PPvsREal!$C$27,'Comités'!Q:Q) -> 0 | R27: =SUMIF('Comités'!$B:$B,PPvsREal!$C$27,'Comités'!R:R) -> 12000 | S27: =SUMIF('Comités'!$B:$B,PPvsREal!$C$27,'Comités'!S:S) -> 0 | T27: =SUMIF('Comités'!$B:$B,PPvsREal!$C$27,'Comités'!T:T) -> 12000 | U27: =SUMIF('Comités'!$B:$B,PPvsREal!$C$27,'Comités'!U:U) -> 0 | V27: =SUMIF('Comités'!$B:$B,PPvsREal!$C$27,'Comités'!V:V) -> 12000 | W27: =SUMIF('Comités'!$B:$B,PPvsREal!$C$27,'Comités'!W:W) -> 0 | X27: =SUMIF('Comités'!$B:$B,PPvsREal!$C$27,'Comités'!X:X) -> 12000 | Y27: =SUMIF('Comités'!$B:$B,PPvsREal!$C$27,'Comités'!Y:Y) -> 0 | Z27: =SUMIF('Comités'!$B:$B,PPvsREal!$C$27,'Comités'!Z:Z) -> 0 | AA27: =SUMIF('Comités'!$B:$B,PPvsREal!$C$27,'Comités'!AA:AA) -> 0
B28: Comités | C28: 502-013-000-00 | D28: =SUMIF('Comités'!$B:$B,PPvsREal!$C$28,'Comités'!D:D) -> 0 | E28: =SUMIF('Comités'!$B:$B,PPvsREal!$C$28,'Comités'!E:E) -> 0 | F28: =SUMIF('Comités'!$B:$B,PPvsREal!$C$28,'Comités'!F:F) -> 500 | G28: =SUMIF('Comités'!$B:$B,PPvsREal!$C$28,'Comités'!G:G) -> 0 | H28: =SUMIF('Comités'!$B:$B,PPvsREal!$C$28,'Comités'!H:H) -> 500 | I28: =SUMIF('Comités'!$B:$B,PPvsREal!$C$28,'Comités'!I:I) -> 0 | J28: =SUMIF('Comités'!$B:$B,PPvsREal!$C$28,'Comités'!J:J) -> 500 | K28: =SUMIF('Comités'!$B:$B,PPvsREal!$C$28,'Comités'!K:K) -> 0 | L28: =SUMIF('Comités'!$B:$B,PPvsREal!$C$28,'Comités'!L:L) -> 500 | M28: =SUMIF('Comités'!$B:$B,PPvsREal!$C$28,'Comités'!M:M) -> 0 | N28: =SUMIF('Comités'!$B:$B,PPvsREal!$C$28,'Comités'!N:N) -> 500 | O28: =SUMIF('Comités'!$B:$B,PPvsREal!$C$28,'Comités'!O:O) -> 0 | P28: =SUMIF('Comités'!$B:$B,PPvsREal!$C$28,'Comités'!P:P) -> 500 | Q28: =SUMIF('Comités'!$B:$B,PPvsREal!$C$28,'Comités'!Q:Q) -> 0 | R28: =SUMIF('Comités'!$B:$B,PPvsREal!$C$28,'Comités'!R:R) -> 500 | S28: =SUMIF('Comités'!$B:$B,PPvsREal!$C$28,'Comités'!S:S) -> 0 | T28: =SUMIF('Comités'!$B:$B,PPvsREal!$C$28,'Comités'!T:T) -> 500 | U28: =SUMIF('Comités'!$B:$B,PPvsREal!$C$28,'Comités'!U:U) -> 0 | V28: =SUMIF('Comités'!$B:$B,PPvsREal!$C$28,'Comités'!V:V) -> 500 | W28: =SUMIF('Comités'!$B:$B,PPvsREal!$C$28,'Comités'!W:W) -> 0 | X28: =SUMIF('Comités'!$B:$B,PPvsREal!$C$28,'Comités'!X:X) -> 500 | Y28: =SUMIF('Comités'!$B:$B,PPvsREal!$C$28,'Comités'!Y:Y) -> 0 | Z28: =SUMIF('Comités'!$B:$B,PPvsREal!$C$28,'Comités'!Z:Z) -> 0 | AA28: =SUMIF('Comités'!$B:$B,PPvsREal!$C$28,'Comités'!AA:AA) -> 0
B29: Comités | C29: 502-007-000-00 | D29: =SUMIF('Comités'!$B:$B,PPvsREal!$C$29,'Comités'!D:D) -> 0 | E29: =SUMIF('Comités'!$B:$B,PPvsREal!$C$29,'Comités'!E:E) -> 0 | F29: =SUMIF('Comités'!$B:$B,PPvsREal!$C$29,'Comités'!F:F) -> 500 | G29: =SUMIF('Comités'!$B:$B,PPvsREal!$C$29,'Comités'!G:G) -> 0 | H29: =SUMIF('Comités'!$B:$B,PPvsREal!$C$29,'Comités'!H:H) -> 500 | I29: =SUMIF('Comités'!$B:$B,PPvsREal!$C$29,'Comités'!I:I) -> 0 | J29: =SUMIF('Comités'!$B:$B,PPvsREal!$C$29,'Comités'!J:J) -> 500 | K29: =SUMIF('Comités'!$B:$B,PPvsREal!$C$29,'Comités'!K:K) -> 0 | L29: =SUMIF('Comités'!$B:$B,PPvsREal!$C$29,'Comités'!L:L) -> 500 | M29: =SUMIF('Comités'!$B:$B,PPvsREal!$C$29,'Comités'!M:M) -> 0 | N29: =SUMIF('Comités'!$B:$B,PPvsREal!$C$29,'Comités'!N:N) -> 500 | O29: =SUMIF('Comités'!$B:$B,PPvsREal!$C$29,'Comités'!O:O) -> 0 | P29: =SUMIF('Comités'!$B:$B,PPvsREal!$C$29,'Comités'!P:P) -> 500 | Q29: =SUMIF('Comités'!$B:$B,PPvsREal!$C$29,'Comités'!Q:Q) -> 0 | R29: =SUMIF('Comités'!$B:$B,PPvsREal!$C$29,'Comités'!R:R) -> 500 | S29: =SUMIF('Comités'!$B:$B,PPvsREal!$C$29,'Comités'!S:S) -> 0 | T29: =SUMIF('Comités'!$B:$B,PPvsREal!$C$29,'Comités'!T:T) -> 500 | U29: =SUMIF('Comités'!$B:$B,PPvsREal!$C$29,'Comités'!U:U) -> 0 | V29: =SUMIF('Comités'!$B:$B,PPvsREal!$C$29,'Comités'!V:V) -> 500 | W29: =SUMIF('Comités'!$B:$B,PPvsREal!$C$29,'Comités'!W:W) -> 0 | X29: =SUMIF('Comités'!$B:$B,PPvsREal!$C$29,'Comités'!X:X) -> 500 | Y29: =SUMIF('Comités'!$B:$B,PPvsREal!$C$29,'Comités'!Y:Y) -> 0 | Z29: =SUMIF('Comités'!$B:$B,PPvsREal!$C$29,'Comités'!Z:Z) -> 0 | AA29: =SUMIF('Comités'!$B:$B,PPvsREal!$C$29,'Comités'!AA:AA) -> 0
B30: Comités | C30: 502-016-000-00 | D30: =SUMIF('Comités'!$B:$B,PPvsREal!$C$30,'Comités'!D:D) -> 0 | E30: =SUMIF('Comités'!$B:$B,PPvsREal!$C$30,'Comités'!E:E) -> 0 | F30: =SUMIF('Comités'!$B:$B,PPvsREal!$C$30,'Comités'!F:F) -> 500 | G30: =SUMIF('Comités'!$B:$B,PPvsREal!$C$30,'Comités'!G:G) -> 0 | H30: =SUMIF('Comités'!$B:$B,PPvsREal!$C$30,'Comités'!H:H) -> 500 | I30: =SUMIF('Comités'!$B:$B,PPvsREal!$C$30,'Comités'!I:I) -> 0 | J30: =SUMIF('Comités'!$B:$B,PPvsREal!$C$30,'Comités'!J:J) -> 500 | K30: =SUMIF('Comités'!$B:$B,PPvsREal!$C$30,'Comités'!K:K) -> 0 | L30: =SUMIF('Comités'!$B:$B,PPvsREal!$C$30,'Comités'!L:L) -> 500 | M30: =SUMIF('Comités'!$B:$B,PPvsREal!$C$30,'Comités'!M:M) -> 0 | N30: =SUMIF('Comités'!$B:$B,PPvsREal!$C$30,'Comités'!N:N) -> 500 | O30: =SUMIF('Comités'!$B:$B,PPvsREal!$C$30,'Comités'!O:O) -> 0 | P30: =SUMIF('Comités'!$B:$B,PPvsREal!$C$30,'Comités'!P:P) -> 500 | Q30: =SUMIF('Comités'!$B:$B,PPvsREal!$C$30,'Comités'!Q:Q) -> 0 | R30: =SUMIF('Comités'!$B:$B,PPvsREal!$C$30,'Comités'!R:R) -> 500 | S30: =SUMIF('Comités'!$B:$B,PPvsREal!$C$30,'Comités'!S:S) -> 0 | T30: =SUMIF('Comités'!$B:$B,PPvsREal!$C$30,'Comités'!T:T) -> 500 | U30: =SUMIF('Comités'!$B:$B,PPvsREal!$C$30,'Comités'!U:U) -> 0 | V30: =SUMIF('Comités'!$B:$B,PPvsREal!$C$30,'Comités'!V:V) -> 500 | W30: =SUMIF('Comités'!$B:$B,PPvsREal!$C$30,'Comités'!W:W) -> 0 | X30: =SUMIF('Comités'!$B:$B,PPvsREal!$C$30,'Comités'!X:X) -> 500 | Y30: =SUMIF('Comités'!$B:$B,PPvsREal!$C$30,'Comités'!Y:Y) -> 0 | Z30: =SUMIF('Comités'!$B:$B,PPvsREal!$C$30,'Comités'!Z:Z) -> 0 | AA30: =SUMIF('Comités'!$B:$B,PPvsREal!$C$30,'Comités'!AA:AA) -> 0
B31: Comités | C31: 502-004-000-00 | D31: =SUMIF('Comités'!$B:$B,PPvsREal!$C$31,'Comités'!D:D) -> 0 | E31: =SUMIF('Comités'!$B:$B,PPvsREal!$C$31,'Comités'!E:E) -> 0 | F31: =SUMIF('Comités'!$B:$B,PPvsREal!$C$31,'Comités'!F:F) -> 500 | G31: =SUMIF('Comités'!$B:$B,PPvsREal!$C$31,'Comités'!G:G) -> 0 | H31: =SUMIF('Comités'!$B:$B,PPvsREal!$C$31,'Comités'!H:H) -> 500 | I31: =SUMIF('Comités'!$B:$B,PPvsREal!$C$31,'Comités'!I:I) -> 0 | J31: =SUMIF('Comités'!$B:$B,PPvsREal!$C$31,'Comités'!J:J) -> 500 | K31: =SUMIF('Comités'!$B:$B,PPvsREal!$C$31,'Comités'!K:K) -> 0 | L31: =SUMIF('Comités'!$B:$B,PPvsREal!$C$31,'Comités'!L:L) -> 500 | M31: =SUMIF('Comités'!$B:$B,PPvsREal!$C$31,'Comités'!M:M) -> 0 | N31: =SUMIF('Comités'!$B:$B,PPvsREal!$C$31,'Comités'!N:N) -> 500 | O31: =SUMIF('Comités'!$B:$B,PPvsREal!$C$31,'Comités'!O:O) -> 0 | P31: =SUMIF('Comités'!$B:$B,PPvsREal!$C$31,'Comités'!P:P) -> 500 | Q31: =SUMIF('Comités'!$B:$B,PPvsREal!$C$31,'Comités'!Q:Q) -> 0 | R31: =SUMIF('Comités'!$B:$B,PPvsREal!$C$31,'Comités'!R:R) -> 500 | S31: =SUMIF('Comités'!$B:$B,PPvsREal!$C$31,'Comités'!S:S) -> 0 | T31: =SUMIF('Comités'!$B:$B,PPvsREal!$C$31,'Comités'!T:T) -> 500 | U31: =SUMIF('Comités'!$B:$B,PPvsREal!$C$31,'Comités'!U:U) -> 0 | V31: =SUMIF('Comités'!$B:$B,PPvsREal!$C$31,'Comités'!V:V) -> 500 | W31: =SUMIF('Comités'!$B:$B,PPvsREal!$C$31,'Comités'!W:W) -> 0 | X31: =SUMIF('Comités'!$B:$B,PPvsREal!$C$31,'Comités'!X:X) -> 500 | Y31: =SUMIF('Comités'!$B:$B,PPvsREal!$C$31,'Comités'!Y:Y) -> 0 | Z31: =SUMIF('Comités'!$B:$B,PPvsREal!$C$31,'Comités'!Z:Z) -> 0 | AA31: =SUMIF('Comités'!$B:$B,PPvsREal!$C$31,'Comités'!AA:AA) -> 0
B32: Comités | C32: 502-002-000-00 | D32: =SUMIF('Comités'!$B:$B,PPvsREal!$C$32,'Comités'!D:D) -> 0 | E32: =SUMIF('Comités'!$B:$B,PPvsREal!$C$32,'Comités'!E:E) -> 0 | F32: =SUMIF('Comités'!$B:$B,PPvsREal!$C$32,'Comités'!F:F) -> 500 | G32: =SUMIF('Comités'!$B:$B,PPvsREal!$C$32,'Comités'!G:G) -> 0 | H32: =SUMIF('Comités'!$B:$B,PPvsREal!$C$32,'Comités'!H:H) -> 500 | I32: =SUMIF('Comités'!$B:$B,PPvsREal!$C$32,'Comités'!I:I) -> 0 | J32: =SUMIF('Comités'!$B:$B,PPvsREal!$C$32,'Comités'!J:J) -> 500 | K32: =SUMIF('Comités'!$B:$B,PPvsREal!$C$32,'Comités'!K:K) -> 0 | L32: =SUMIF('Comités'!$B:$B,PPvsREal!$C$32,'Comités'!L:L) -> 500 | M32: =SUMIF('Comités'!$B:$B,PPvsREal!$C$32,'Comités'!M:M) -> 0 | N32: =SUMIF('Comités'!$B:$B,PPvsREal!$C$32,'Comités'!N:N) -> 500 | O32: =SUMIF('Comités'!$B:$B,PPvsREal!$C$32,'Comités'!O:O) -> 0 | P32: =SUMIF('Comités'!$B:$B,PPvsREal!$C$32,'Comités'!P:P) -> 500 | Q32: =SUMIF('Comités'!$B:$B,PPvsREal!$C$32,'Comités'!Q:Q) -> 0 | R32: =SUMIF('Comités'!$B:$B,PPvsREal!$C$32,'Comités'!R:R) -> 500 | S32: =SUMIF('Comités'!$B:$B,PPvsREal!$C$32,'Comités'!S:S) -> 0 | T32: =SUMIF('Comités'!$B:$B,PPvsREal!$C$32,'Comités'!T:T) -> 500 | U32: =SUMIF('Comités'!$B:$B,PPvsREal!$C$32,'Comités'!U:U) -> 0 | V32: =SUMIF('Comités'!$B:$B,PPvsREal!$C$32,'Comités'!V:V) -> 500 | W32: =SUMIF('Comités'!$B:$B,PPvsREal!$C$32,'Comités'!W:W) -> 0 | X32: =SUMIF('Comités'!$B:$B,PPvsREal!$C$32,'Comités'!X:X) -> 500 | Y32: =SUMIF('Comités'!$B:$B,PPvsREal!$C$32,'Comités'!Y:Y) -> 0 | Z32: =SUMIF('Comités'!$B:$B,PPvsREal!$C$32,'Comités'!Z:Z) -> 0 | AA32: =SUMIF('Comités'!$B:$B,PPvsREal!$C$32,'Comités'!AA:AA) -> 0
B33: Comités | C33: 502-009-000-00 | D33: =SUMIF('Comités'!$B:$B,$C$33,'Comités'!D:D) -> 0 | E33: =SUMIF('Comités'!$B:$B,$C$33,'Comités'!E:E) -> 0 | F33: =SUMIF('Comités'!$B:$B,$C$33,'Comités'!F:F) -> 500 | G33: =SUMIF('Comités'!$B:$B,$C$33,'Comités'!G:G) -> 0 | H33: =SUMIF('Comités'!$B:$B,$C$33,'Comités'!H:H) -> 500 | I33: =SUMIF('Comités'!$B:$B,$C$33,'Comités'!I:I) -> 0 | J33: =SUMIF('Comités'!$B:$B,$C$33,'Comités'!J:J) -> 500 | K33: =SUMIF('Comités'!$B:$B,$C$33,'Comités'!K:K) -> 0 | L33: =SUMIF('Comités'!$B:$B,$C$33,'Comités'!L:L) -> 500 | M33: =SUMIF('Comités'!$B:$B,$C$33,'Comités'!M:M) -> 0 | N33: =SUMIF('Comités'!$B:$B,$C$33,'Comités'!N:N) -> 500 | O33: =SUMIF('Comités'!$B:$B,$C$33,'Comités'!O:O) -> 0 | P33: =SUMIF('Comités'!$B:$B,$C$33,'Comités'!P:P) -> 500 | Q33: =SUMIF('Comités'!$B:$B,$C$33,'Comités'!Q:Q) -> 0 | R33: =SUMIF('Comités'!$B:$B,$C$33,'Comités'!R:R) -> 500 | S33: =SUMIF('Comités'!$B:$B,$C$33,'Comités'!S:S) -> 0 | T33: =SUMIF('Comités'!$B:$B,$C$33,'Comités'!T:T) -> 500 | U33: =SUMIF('Comités'!$B:$B,$C$33,'Comités'!U:U) -> 0 | V33: =SUMIF('Comités'!$B:$B,$C$33,'Comités'!V:V) -> 500 | W33: =SUMIF('Comités'!$B:$B,$C$33,'Comités'!W:W) -> 0 | X33: =SUMIF('Comités'!$B:$B,$C$33,'Comités'!X:X) -> 500 | Y33: =SUMIF('Comités'!$B:$B,$C$33,'Comités'!Y:Y) -> 0 | Z33: =SUMIF('Comités'!$B:$B,$C$33,'Comités'!Z:Z) -> 0 | AA33: =SUMIF('Comités'!$B:$B,$C$33,'Comités'!AA:AA) -> 0
B34: Comités | C34: 502-010-000-00 | D34: =SUMIF('Comités'!$B:$B,$C$34,'Comités'!D:D) -> 0 | E34: =SUMIF('Comités'!$B:$B,$C$34,'Comités'!E:E) -> 0 | F34: =SUMIF('Comités'!$B:$B,$C$34,'Comités'!F:F) -> 500 | G34: =SUMIF('Comités'!$B:$B,$C$34,'Comités'!G:G) -> 0 | H34: =SUMIF('Comités'!$B:$B,$C$34,'Comités'!H:H) -> 500 | I34: =SUMIF('Comités'!$B:$B,$C$34,'Comités'!I:I) -> 0 | J34: =SUMIF('Comités'!$B:$B,$C$34,'Comités'!J:J) -> 500 | K34: =SUMIF('Comités'!$B:$B,$C$34,'Comités'!K:K) -> 0 | L34: =SUMIF('Comités'!$B:$B,$C$34,'Comités'!L:L) -> 500 | M34: =SUMIF('Comités'!$B:$B,$C$34,'Comités'!M:M) -> 0 | N34: =SUMIF('Comités'!$B:$B,$C$34,'Comités'!N:N) -> 500 | O34: =SUMIF('Comités'!$B:$B,$C$34,'Comités'!O:O) -> 0 | P34: =SUMIF('Comités'!$B:$B,$C$34,'Comités'!P:P) -> 500 | Q34: =SUMIF('Comités'!$B:$B,$C$34,'Comités'!Q:Q) -> 0 | R34: =SUMIF('Comités'!$B:$B,$C$34,'Comités'!R:R) -> 500 | S34: =SUMIF('Comités'!$B:$B,$C$34,'Comités'!S:S) -> 0 | T34: =SUMIF('Comités'!$B:$B,$C$34,'Comités'!T:T) -> 500 | U34: =SUMIF('Comités'!$B:$B,$C$34,'Comités'!U:U) -> 0 | V34: =SUMIF('Comités'!$B:$B,$C$34,'Comités'!V:V) -> 500 | W34: =SUMIF('Comités'!$B:$B,$C$34,'Comités'!W:W) -> 0 | X34: =SUMIF('Comités'!$B:$B,$C$34,'Comités'!X:X) -> 500 | Y34: =SUMIF('Comités'!$B:$B,$C$34,'Comités'!Y:Y) -> 0 | Z34: =SUMIF('Comités'!$B:$B,$C$34,'Comités'!Z:Z) -> 0 | AA34: =SUMIF('Comités'!$B:$B,$C$34,'Comités'!AA:AA) -> 0
B35: Comités | C35: 502-017-000-00 | D35: =SUMIF('Comités'!$B:$B,$C$35,'Comités'!D:D) -> 0 | E35: =SUMIF('Comités'!$B:$B,$C$35,'Comités'!E:E) -> 0 | F35: =SUMIF('Comités'!$B:$B,$C$35,'Comités'!F:F) -> 0 | G35: =SUMIF('Comités'!$B:$B,$C$35,'Comités'!G:G) -> 0 | H35: =SUMIF('Comités'!$B:$B,$C$35,'Comités'!H:H) -> 0 | I35: =SUMIF('Comités'!$B:$B,$C$35,'Comités'!I:I) -> 0 | J35: =SUMIF('Comités'!$B:$B,$C$35,'Comités'!J:J) -> 0 | K35: =SUMIF('Comités'!$B:$B,$C$35,'Comités'!K:K) -> 0 | L35: =SUMIF('Comités'!$B:$B,$C$35,'Comités'!L:L) -> 357564.9 | M35: =SUMIF('Comités'!$B:$B,$C$35,'Comités'!M:M) -> 0 | N35: =SUMIF('Comités'!$B:$B,$C$35,'Comités'!N:N) -> 3352.745 | O35: =SUMIF('Comités'!$B:$B,$C$35,'Comités'!O:O) -> 0 | P35: =SUMIF('Comités'!$B:$B,$C$35,'Comités'!P:P) -> 4062.531 | Q35: =SUMIF('Comités'!$B:$B,$C$35,'Comités'!Q:Q) -> 0 | R35: =SUMIF('Comités'!$B:$B,$C$35,'Comités'!R:R) -> 72123.964 | S35: =SUMIF('Comités'!$B:$B,$C$35,'Comités'!S:S) -> 0 | T35: =SUMIF('Comités'!$B:$B,$C$35,'Comités'!T:T) -> 5170.869 | U35: =SUMIF('Comités'!$B:$B,$C$35,'Comités'!U:U) -> 0 | V35: =SUMIF('Comités'!$B:$B,$C$35,'Comités'!V:V) -> 0 | W35: =SUMIF('Comités'!$B:$B,$C$35,'Comités'!W:W) -> 0 | X35: =SUMIF('Comités'!$B:$B,$C$35,'Comités'!X:X) -> 0 | Y35: =SUMIF('Comités'!$B:$B,$C$35,'Comités'!Y:Y) -> 0 | Z35: =SUMIF('Comités'!$B:$B,$C$35,'Comités'!Z:Z) -> 44000 | AA35: =SUMIF('Comités'!$B:$B,$C$35,'Comités'!AA:AA) -> 0
B36: Comités | C36: 504-000-000-00 | D36: =SUMIF('Comités'!$B:$B,PPvsREal!$C$36,'Comités'!D:D) -> 0 | E36: =SUMIF('Comités'!$B:$B,PPvsREal!$C$36,'Comités'!E:E) -> 0 | F36: =SUMIF('Comités'!$B:$B,PPvsREal!$C$36,'Comités'!F:F) -> 0 | G36: =SUMIF('Comités'!$B:$B,PPvsREal!$C$36,'Comités'!G:G) -> 0 | H36: =SUMIF('Comités'!$B:$B,PPvsREal!$C$36,'Comités'!H:H) -> 0 | I36: =SUMIF('Comités'!$B:$B,PPvsREal!$C$36,'Comités'!I:I) -> 0 | J36: =SUMIF('Comités'!$B:$B,PPvsREal!$C$36,'Comités'!J:J) -> 0 | K36: =SUMIF('Comités'!$B:$B,PPvsREal!$C$36,'Comités'!K:K) -> 0 | L36: =SUMIF('Comités'!$B:$B,PPvsREal!$C$36,'Comités'!L:L) -> 0 | M36: =SUMIF('Comités'!$B:$B,PPvsREal!$C$36,'Comités'!M:M) -> 0 | N36: =SUMIF('Comités'!$B:$B,PPvsREal!$C$36,'Comités'!N:N) -> 0 | O36: =SUMIF('Comités'!$B:$B,PPvsREal!$C$36,'Comités'!O:O) -> 0 | P36: =SUMIF('Comités'!$B:$B,PPvsREal!$C$36,'Comités'!P:P) -> 0 | Q36: =SUMIF('Comités'!$B:$B,PPvsREal!$C$36,'Comités'!Q:Q) -> 0 | R36: =SUMIF('Comités'!$B:$B,PPvsREal!$C$36,'Comités'!R:R) -> 0 | S36: =SUMIF('Comités'!$B:$B,PPvsREal!$C$36,'Comités'!S:S) -> 0 | T36: =SUMIF('Comités'!$B:$B,PPvsREal!$C$36,'Comités'!T:T) -> 0 | U36: =SUMIF('Comités'!$B:$B,PPvsREal!$C$36,'Comités'!U:U) -> 0 | V36: =SUMIF('Comités'!$B:$B,PPvsREal!$C$36,'Comités'!V:V) -> 0 | W36: =SUMIF('Comités'!$B:$B,PPvsREal!$C$36,'Comités'!W:W) -> 0 | X36: =SUMIF('Comités'!$B:$B,PPvsREal!$C$36,'Comités'!X:X) -> 0 | Y36: =SUMIF('Comités'!$B:$B,PPvsREal!$C$36,'Comités'!Y:Y) -> 0 | Z36: =SUMIF('Comités'!$B:$B,PPvsREal!$C$36,'Comités'!Z:Z) -> 0 | AA36: =SUMIF('Comités'!$B:$B,PPvsREal!$C$36,'Comités'!AA:AA) -> 0
B37: T&IC | C37: 407-001-000-00 | D37: =SUMIF('T&IC'!$B:$B,PPvsREal!$C$37,'T&IC'!D:D) -> 0 | E37: =SUMIF('T&IC'!$B:$B,PPvsREal!$C$37,'T&IC'!E:E) -> 0 | F37: =SUMIF('T&IC'!$B:$B,PPvsREal!$C$37,'T&IC'!F:F) -> 0 | G37: =SUMIF('T&IC'!$B:$B,PPvsREal!$C$37,'T&IC'!G:G) -> 0 | H37: =SUMIF('T&IC'!$B:$B,PPvsREal!$C$37,'T&IC'!H:H) -> 0 | I37: =SUMIF('T&IC'!$B:$B,PPvsREal!$C$37,'T&IC'!I:I) -> 0 | J37: =SUMIF('T&IC'!$B:$B,PPvsREal!$C$37,'T&IC'!J:J) -> 0 | K37: =SUMIF('T&IC'!$B:$B,PPvsREal!$C$37,'T&IC'!K:K) -> 0 | L37: =SUMIF('T&IC'!$B:$B,PPvsREal!$C$37,'T&IC'!L:L) -> 0 | M37: =SUMIF('T&IC'!$B:$B,PPvsREal!$C$37,'T&IC'!M:M) -> 0 | N37: =SUMIF('T&IC'!$B:$B,PPvsREal!$C$37,'T&IC'!N:N) -> 0 | O37: =SUMIF('T&IC'!$B:$B,PPvsREal!$C$37,'T&IC'!O:O) -> 0 | P37: =SUMIF('T&IC'!$B:$B,PPvsREal!$C$37,'T&IC'!P:P) -> 0 | Q37: =SUMIF('T&IC'!$B:$B,PPvsREal!$C$37,'T&IC'!Q:Q) -> 0 | R37: =SUMIF('T&IC'!$B:$B,PPvsREal!$C$37,'T&IC'!R:R) -> 0 | S37: =SUMIF('T&IC'!$B:$B,PPvsREal!$C$37,'T&IC'!S:S) -> 0 | T37: =SUMIF('T&IC'!$B:$B,PPvsREal!$C$37,'T&IC'!T:T) -> 0 | U37: =SUMIF('T&IC'!$B:$B,PPvsREal!$C$37,'T&IC'!U:U) -> 0 | V37: =SUMIF('T&IC'!$B:$B,PPvsREal!$C$37,'T&IC'!V:V) -> 50000 | W37: =SUMIF('T&IC'!$B:$B,PPvsREal!$C$37,'T&IC'!W:W) -> 0 | X37: =SUMIF('T&IC'!$B:$B,PPvsREal!$C$37,'T&IC'!X:X) -> 0 | Y37: =SUMIF('T&IC'!$B:$B,PPvsREal!$C$37,'T&IC'!Y:Y) -> 0 | Z37: =SUMIF('T&IC'!$B:$B,PPvsREal!$C$37,'T&IC'!Z:Z) -> 0 | AA37: =SUMIF('T&IC'!$B:$B,PPvsREal!$C$37,'T&IC'!AA:AA) -> 0
B38: T&IC | C38: 407-002-000-00 | D38: =SUMIF('T&IC'!$B:$B,PPvsREal!$C$38,'T&IC'!D:D) -> 0 | E38: =SUMIF('T&IC'!$B:$B,PPvsREal!$C$38,'T&IC'!E:E) -> 0 | F38: =SUMIF('T&IC'!$B:$B,PPvsREal!$C$38,'T&IC'!F:F) -> 0 | G38: =SUMIF('T&IC'!$B:$B,PPvsREal!$C$38,'T&IC'!G:G) -> 0 | H38: =SUMIF('T&IC'!$B:$B,PPvsREal!$C$38,'T&IC'!H:H) -> 0 | I38: =SUMIF('T&IC'!$B:$B,PPvsREal!$C$38,'T&IC'!I:I) -> 0 | J38: =SUMIF('T&IC'!$B:$B,PPvsREal!$C$38,'T&IC'!J:J) -> 0 | K38: =SUMIF('T&IC'!$B:$B,PPvsREal!$C$38,'T&IC'!K:K) -> 0 | L38: =SUMIF('T&IC'!$B:$B,PPvsREal!$C$38,'T&IC'!L:L) -> 0 | M38: =SUMIF('T&IC'!$B:$B,PPvsREal!$C$38,'T&IC'!M:M) -> 0 | N38: =SUMIF('T&IC'!$B:$B,PPvsREal!$C$38,'T&IC'!N:N) -> 0 | O38: =SUMIF('T&IC'!$B:$B,PPvsREal!$C$38,'T&IC'!O:O) -> 0 | P38: =SUMIF('T&IC'!$B:$B,PPvsREal!$C$38,'T&IC'!P:P) -> 0 | Q38: =SUMIF('T&IC'!$B:$B,PPvsREal!$C$38,'T&IC'!Q:Q) -> 0 | R38: =SUMIF('T&IC'!$B:$B,PPvsREal!$C$38,'T&IC'!R:R) -> 0 | S38: =SUMIF('T&IC'!$B:$B,PPvsREal!$C$38,'T&IC'!S:S) -> 0 | T38: =SUMIF('T&IC'!$B:$B,PPvsREal!$C$38,'T&IC'!T:T) -> 0 | U38: =SUMIF('T&IC'!$B:$B,PPvsREal!$C$38,'T&IC'!U:U) -> 0 | V38: =SUMIF('T&IC'!$B:$B,PPvsREal!$C$38,'T&IC'!V:V) -> 0 | W38: =SUMIF('T&IC'!$B:$B,PPvsREal!$C$38,'T&IC'!W:W) -> 0 | X38: =SUMIF('T&IC'!$B:$B,PPvsREal!$C$38,'T&IC'!X:X) -> 0 | Y38: =SUMIF('T&IC'!$B:$B,PPvsREal!$C$38,'T&IC'!Y:Y) -> 0 | Z38: =SUMIF('T&IC'!$B:$B,PPvsREal!$C$38,'T&IC'!Z:Z) -> 0 | AA38: =SUMIF('T&IC'!$B:$B,PPvsREal!$C$38,'T&IC'!AA:AA) -> 0
B39: T&IC | C39: 703-001-000-00 | D39: =SUMIF('T&IC'!$B:$B,PPvsREal!$C$39,'T&IC'!D:D) -> 0 | E39: =SUMIF('T&IC'!$B:$B,PPvsREal!$C$39,'T&IC'!E:E) -> 0 | F39: =SUMIF('T&IC'!$B:$B,PPvsREal!$C$39,'T&IC'!F:F) -> 0 | G39: =SUMIF('T&IC'!$B:$B,PPvsREal!$C$39,'T&IC'!G:G) -> 0 | H39: =SUMIF('T&IC'!$B:$B,PPvsREal!$C$39,'T&IC'!H:H) -> 0 | I39: =SUMIF('T&IC'!$B:$B,PPvsREal!$C$39,'T&IC'!I:I) -> 0 | J39: =SUMIF('T&IC'!$B:$B,PPvsREal!$C$39,'T&IC'!J:J) -> 0 | K39: =SUMIF('T&IC'!$B:$B,PPvsREal!$C$39,'T&IC'!K:K) -> 0 | L39: =SUMIF('T&IC'!$B:$B,PPvsREal!$C$39,'T&IC'!L:L) -> 0 | M39: =SUMIF('T&IC'!$B:$B,PPvsREal!$C$39,'T&IC'!M:M) -> 0 | N39: =SUMIF('T&IC'!$B:$B,PPvsREal!$C$39,'T&IC'!N:N) -> 0 | O39: =SUMIF('T&IC'!$B:$B,PPvsREal!$C$39,'T&IC'!O:O) -> 0 | P39: =SUMIF('T&IC'!$B:$B,PPvsREal!$C$39,'T&IC'!P:P) -> 0 | Q39: =SUMIF('T&IC'!$B:$B,PPvsREal!$C$39,'T&IC'!Q:Q) -> 0 | R39: =SUMIF('T&IC'!$B:$B,PPvsREal!$C$39,'T&IC'!R:R) -> 0 | S39: =SUMIF('T&IC'!$B:$B,PPvsREal!$C$39,'T&IC'!S:S) -> 0 | T39: =SUMIF('T&IC'!$B:$B,PPvsREal!$C$39,'T&IC'!T:T) -> 0 | U39: =SUMIF('T&IC'!$B:$B,PPvsREal!$C$39,'T&IC'!U:U) -> 0 | V39: =SUMIF('T&IC'!$B:$B,PPvsREal!$C$39,'T&IC'!V:V) -> 25000 | W39: =SUMIF('T&IC'!$B:$B,PPvsREal!$C$39,'T&IC'!W:W) -> 0 | X39: =SUMIF('T&IC'!$B:$B,PPvsREal!$C$39,'T&IC'!X:X) -> 0 | Y39: =SUMIF('T&IC'!$B:$B,PPvsREal!$C$39,'T&IC'!Y:Y) -> 0 | Z39: =SUMIF('T&IC'!$B:$B,PPvsREal!$C$39,'T&IC'!Z:Z) -> 0 | AA39: =SUMIF('T&IC'!$B:$B,PPvsREal!$C$39,'T&IC'!AA:AA) -> 0
B40: T&IC | C40: 703-002-000-00 | D40: =SUMIF('T&IC'!$B:$B,PPvsREal!$C$40,'T&IC'!D:D) -> 0 | E40: =SUMIF('T&IC'!$B:$B,PPvsREal!$C$40,'T&IC'!E:E) -> 0 | F40: =SUMIF('T&IC'!$B:$B,PPvsREal!$C$40,'T&IC'!F:F) -> 0 | G40: =SUMIF('T&IC'!$B:$B,PPvsREal!$C$40,'T&IC'!G:G) -> 0 | H40: =SUMIF('T&IC'!$B:$B,PPvsREal!$C$40,'T&IC'!H:H) -> 0 | I40: =SUMIF('T&IC'!$B:$B,PPvsREal!$C$40,'T&IC'!I:I) -> 0 | J40: =SUMIF('T&IC'!$B:$B,PPvsREal!$C$40,'T&IC'!J:J) -> 0 | K40: =SUMIF('T&IC'!$B:$B,PPvsREal!$C$40,'T&IC'!K:K) -> 0 | L40: =SUMIF('T&IC'!$B:$B,PPvsREal!$C$40,'T&IC'!L:L) -> 0 | M40: =SUMIF('T&IC'!$B:$B,PPvsREal!$C$40,'T&IC'!M:M) -> 0 | N40: =SUMIF('T&IC'!$B:$B,PPvsREal!$C$40,'T&IC'!N:N) -> 0 | O40: =SUMIF('T&IC'!$B:$B,PPvsREal!$C$40,'T&IC'!O:O) -> 0 | P40: =SUMIF('T&IC'!$B:$B,PPvsREal!$C$40,'T&IC'!P:P) -> 0 | Q40: =SUMIF('T&IC'!$B:$B,PPvsREal!$C$40,'T&IC'!Q:Q) -> 0 | R40: =SUMIF('T&IC'!$B:$B,PPvsREal!$C$40,'T&IC'!R:R) -> 0 | S40: =SUMIF('T&IC'!$B:$B,PPvsREal!$C$40,'T&IC'!S:S) -> 0 | T40: =SUMIF('T&IC'!$B:$B,PPvsREal!$C$40,'T&IC'!T:T) -> 0 | U40: =SUMIF('T&IC'!$B:$B,PPvsREal!$C$40,'T&IC'!U:U) -> 0 | V40: =SUMIF('T&IC'!$B:$B,PPvsREal!$C$40,'T&IC'!V:V) -> 0 | W40: =SUMIF('T&IC'!$B:$B,PPvsREal!$C$40,'T&IC'!W:W) -> 0 | X40: =SUMIF('T&IC'!$B:$B,PPvsREal!$C$40,'T&IC'!X:X) -> 0 | Y40: =SUMIF('T&IC'!$B:$B,PPvsREal!$C$40,'T&IC'!Y:Y) -> 0 | Z40: =SUMIF('T&IC'!$B:$B,PPvsREal!$C$40,'T&IC'!Z:Z) -> 0 | AA40: =SUMIF('T&IC'!$B:$B,PPvsREal!$C$40,'T&IC'!AA:AA) -> 0
B41: Eventos | C41: 405-002-000-00 | D41: =SUMIF(Eventos!$B:$B,PPvsREal!$C$41,Eventos!D:D) -> 0 | E41: =SUMIF(Eventos!$B:$B,PPvsREal!$C$41,Eventos!E:E) -> 0 | F41: =SUMIF(Eventos!$B:$B,PPvsREal!$C$41,Eventos!F:F) -> 0 | G41: =SUMIF(Eventos!$B:$B,PPvsREal!$C$41,Eventos!G:G) -> 0 | H41: =SUMIF(Eventos!$B:$B,PPvsREal!$C$41,Eventos!H:H) -> 220000 | I41: =SUMIF(Eventos!$B:$B,PPvsREal!$C$41,Eventos!I:I) -> 0 | J41: =SUMIF(Eventos!$B:$B,PPvsREal!$C$41,Eventos!J:J) -> 30000 | K41: =SUMIF(Eventos!$B:$B,PPvsREal!$C$41,Eventos!K:K) -> 0 | L41: =SUMIF(Eventos!$B:$B,PPvsREal!$C$41,Eventos!L:L) -> 0 | M41: =SUMIF(Eventos!$B:$B,PPvsREal!$C$41,Eventos!M:M) -> 0 | N41: =SUMIF(Eventos!$B:$B,PPvsREal!$C$41,Eventos!N:N) -> 0 | O41: =SUMIF(Eventos!$B:$B,PPvsREal!$C$41,Eventos!O:O) -> 0 | P41: =SUMIF(Eventos!$B:$B,PPvsREal!$C$41,Eventos!P:P) -> 0 | Q41: =SUMIF(Eventos!$B:$B,PPvsREal!$C$41,Eventos!Q:Q) -> 0 | R41: =SUMIF(Eventos!$B:$B,PPvsREal!$C$41,Eventos!R:R) -> 0 | S41: =SUMIF(Eventos!$B:$B,PPvsREal!$C$41,Eventos!S:S) -> 0 | T41: =SUMIF(Eventos!$B:$B,PPvsREal!$C$41,Eventos!T:T) -> 0 | U41: =SUMIF(Eventos!$B:$B,PPvsREal!$C$41,Eventos!U:U) -> 0 | V41: =SUMIF(Eventos!$B:$B,PPvsREal!$C$41,Eventos!V:V) -> 0 | W41: =SUMIF(Eventos!$B:$B,PPvsREal!$C$41,Eventos!W:W) -> 0 | X41: =SUMIF(Eventos!$B:$B,PPvsREal!$C$41,Eventos!X:X) -> 0 | Y41: =SUMIF(Eventos!$B:$B,PPvsREal!$C$41,Eventos!Y:Y) -> 0 | Z41: =SUMIF(Eventos!$B:$B,PPvsREal!$C$41,Eventos!Z:Z) -> 0 | AA41: =SUMIF(Eventos!$B:$B,PPvsREal!$C$41,Eventos!AA:AA) -> 0
B42: Eventos | C42: 405-001-000-00 | D42: =SUMIF(Eventos!$B:$B,PPvsREal!$C$42,Eventos!D:D) -> 475000 | E42: =SUMIF(Eventos!$B:$B,PPvsREal!$C$42,Eventos!E:E) -> 0 | F42: =SUMIF(Eventos!$B:$B,PPvsREal!$C$42,Eventos!F:F) -> 25000 | G42: =SUMIF(Eventos!$B:$B,PPvsREal!$C$42,Eventos!G:G) -> 0 | H42: =SUMIF(Eventos!$B:$B,PPvsREal!$C$42,Eventos!H:H) -> 0 | I42: =SUMIF(Eventos!$B:$B,PPvsREal!$C$42,Eventos!I:I) -> 0 | J42: =SUMIF(Eventos!$B:$B,PPvsREal!$C$42,Eventos!J:J) -> 0 | K42: =SUMIF(Eventos!$B:$B,PPvsREal!$C$42,Eventos!K:K) -> 0 | L42: =SUMIF(Eventos!$B:$B,PPvsREal!$C$42,Eventos!L:L) -> 0 | M42: =SUMIF(Eventos!$B:$B,PPvsREal!$C$42,Eventos!M:M) -> 0 | N42: =SUMIF(Eventos!$B:$B,PPvsREal!$C$42,Eventos!N:N) -> 0 | O42: =SUMIF(Eventos!$B:$B,PPvsREal!$C$42,Eventos!O:O) -> 0 | P42: =SUMIF(Eventos!$B:$B,PPvsREal!$C$42,Eventos!P:P) -> 0 | Q42: =SUMIF(Eventos!$B:$B,PPvsREal!$C$42,Eventos!Q:Q) -> 0 | R42: =SUMIF(Eventos!$B:$B,PPvsREal!$C$42,Eventos!R:R) -> 0 | S42: =SUMIF(Eventos!$B:$B,PPvsREal!$C$42,Eventos!S:S) -> 0 | T42: =SUMIF(Eventos!$B:$B,PPvsREal!$C$42,Eventos!T:T) -> 0 | U42: =SUMIF(Eventos!$B:$B,PPvsREal!$C$42,Eventos!U:U) -> 0 | V42: =SUMIF(Eventos!$B:$B,PPvsREal!$C$42,Eventos!V:V) -> 0 | W42: =SUMIF(Eventos!$B:$B,PPvsREal!$C$42,Eventos!W:W) -> 0 | X42: =SUMIF(Eventos!$B:$B,PPvsREal!$C$42,Eventos!X:X) -> 0 | Y42: =SUMIF(Eventos!$B:$B,PPvsREal!$C$42,Eventos!Y:Y) -> 0 | Z42: =SUMIF(Eventos!$B:$B,PPvsREal!$C$42,Eventos!Z:Z) -> 0 | AA42: =SUMIF(Eventos!$B:$B,PPvsREal!$C$42,Eventos!AA:AA) -> 0
B43: Eventos | C43: 405-009-000-00 | D43: =SUMIF(Eventos!$B:$B,PPvsREal!$C$43,Eventos!D:D) -> 0 | E43: =SUMIF(Eventos!$B:$B,PPvsREal!$C$43,Eventos!E:E) -> 0 | F43: =SUMIF(Eventos!$B:$B,PPvsREal!$C$43,Eventos!F:F) -> 0 | G43: =SUMIF(Eventos!$B:$B,PPvsREal!$C$43,Eventos!G:G) -> 0 | H43: =SUMIF(Eventos!$B:$B,PPvsREal!$C$43,Eventos!H:H) -> 0 | I43: =SUMIF(Eventos!$B:$B,PPvsREal!$C$43,Eventos!I:I) -> 0 | J43: =SUMIF(Eventos!$B:$B,PPvsREal!$C$43,Eventos!J:J) -> 0 | K43: =SUMIF(Eventos!$B:$B,PPvsREal!$C$43,Eventos!K:K) -> 0 | L43: =SUMIF(Eventos!$B:$B,PPvsREal!$C$43,Eventos!L:L) -> 0 | M43: =SUMIF(Eventos!$B:$B,PPvsREal!$C$43,Eventos!M:M) -> 0 | N43: =SUMIF(Eventos!$B:$B,PPvsREal!$C$43,Eventos!N:N) -> 0 | O43: =SUMIF(Eventos!$B:$B,PPvsREal!$C$43,Eventos!O:O) -> 0 | P43: =SUMIF(Eventos!$B:$B,PPvsREal!$C$43,Eventos!P:P) -> 0 | Q43: =SUMIF(Eventos!$B:$B,PPvsREal!$C$43,Eventos!Q:Q) -> 0 | R43: =SUMIF(Eventos!$B:$B,PPvsREal!$C$43,Eventos!R:R) -> 0 | S43: =SUMIF(Eventos!$B:$B,PPvsREal!$C$43,Eventos!S:S) -> 0 | T43: =SUMIF(Eventos!$B:$B,PPvsREal!$C$43,Eventos!T:T) -> 0 | U43: =SUMIF(Eventos!$B:$B,PPvsREal!$C$43,Eventos!U:U) -> 0 | V43: =SUMIF(Eventos!$B:$B,PPvsREal!$C$43,Eventos!V:V) -> 90000 | W43: =SUMIF(Eventos!$B:$B,PPvsREal!$C$43,Eventos!W:W) -> 0 | X43: =SUMIF(Eventos!$B:$B,PPvsREal!$C$43,Eventos!X:X) -> 10000 | Y43: =SUMIF(Eventos!$B:$B,PPvsREal!$C$43,Eventos!Y:Y) -> 0 | Z43: =SUMIF(Eventos!$B:$B,PPvsREal!$C$43,Eventos!Z:Z) -> 0 | AA43: =SUMIF(Eventos!$B:$B,PPvsREal!$C$43,Eventos!AA:AA) -> 0
B44: Eventos | C44: 405-003-000-00 | D44: =SUMIF(Eventos!$B:$B,PPvsREal!$C$44,Eventos!D:D) -> 0 | E44: =SUMIF(Eventos!$B:$B,PPvsREal!$C$44,Eventos!E:E) -> 0 | F44: =SUMIF(Eventos!$B:$B,PPvsREal!$C$44,Eventos!F:F) -> 0 | G44: =SUMIF(Eventos!$B:$B,PPvsREal!$C$44,Eventos!G:G) -> 0 | H44: =SUMIF(Eventos!$B:$B,PPvsREal!$C$44,Eventos!H:H) -> 0 | I44: =SUMIF(Eventos!$B:$B,PPvsREal!$C$44,Eventos!I:I) -> 0 | J44: =SUMIF(Eventos!$B:$B,PPvsREal!$C$44,Eventos!J:J) -> 0 | K44: =SUMIF(Eventos!$B:$B,PPvsREal!$C$44,Eventos!K:K) -> 0 | L44: =SUMIF(Eventos!$B:$B,PPvsREal!$C$44,Eventos!L:L) -> 0 | M44: =SUMIF(Eventos!$B:$B,PPvsREal!$C$44,Eventos!M:M) -> 0 | N44: =SUMIF(Eventos!$B:$B,PPvsREal!$C$44,Eventos!N:N) -> 0 | O44: =SUMIF(Eventos!$B:$B,PPvsREal!$C$44,Eventos!O:O) -> 0 | P44: =SUMIF(Eventos!$B:$B,PPvsREal!$C$44,Eventos!P:P) -> 0 | Q44: =SUMIF(Eventos!$B:$B,PPvsREal!$C$44,Eventos!Q:Q) -> 0 | R44: =SUMIF(Eventos!$B:$B,PPvsREal!$C$44,Eventos!R:R) -> 0 | S44: =SUMIF(Eventos!$B:$B,PPvsREal!$C$44,Eventos!S:S) -> 0 | T44: =SUMIF(Eventos!$B:$B,PPvsREal!$C$44,Eventos!T:T) -> 0 | U44: =SUMIF(Eventos!$B:$B,PPvsREal!$C$44,Eventos!U:U) -> 0 | V44: =SUMIF(Eventos!$B:$B,PPvsREal!$C$44,Eventos!V:V) -> 0 | W44: =SUMIF(Eventos!$B:$B,PPvsREal!$C$44,Eventos!W:W) -> 0 | X44: =SUMIF(Eventos!$B:$B,PPvsREal!$C$44,Eventos!X:X) -> 0 | Y44: =SUMIF(Eventos!$B:$B,PPvsREal!$C$44,Eventos!Y:Y) -> 0 | Z44: =SUMIF(Eventos!$B:$B,PPvsREal!$C$44,Eventos!Z:Z) -> 0 | AA44: =SUMIF(Eventos!$B:$B,PPvsREal!$C$44,Eventos!AA:AA) -> 0
B45: Eventos | C45: 405-013-000-00 | D45: =SUMIF(Eventos!$B:$B,PPvsREal!$C$45,Eventos!D:D) -> 0 | E45: =SUMIF(Eventos!$B:$B,PPvsREal!$C$45,Eventos!E:E) -> 0 | F45: =SUMIF(Eventos!$B:$B,PPvsREal!$C$45,Eventos!F:F) -> 0 | G45: =SUMIF(Eventos!$B:$B,PPvsREal!$C$45,Eventos!G:G) -> 0 | H45: =SUMIF(Eventos!$B:$B,PPvsREal!$C$45,Eventos!H:H) -> 0 | I45: =SUMIF(Eventos!$B:$B,PPvsREal!$C$45,Eventos!I:I) -> 0 | J45: =SUMIF(Eventos!$B:$B,PPvsREal!$C$45,Eventos!J:J) -> 0 | K45: =SUMIF(Eventos!$B:$B,PPvsREal!$C$45,Eventos!K:K) -> 0 | L45: =SUMIF(Eventos!$B:$B,PPvsREal!$C$45,Eventos!L:L) -> 35000 | M45: =SUMIF(Eventos!$B:$B,PPvsREal!$C$45,Eventos!M:M) -> 0 | N45: =SUMIF(Eventos!$B:$B,PPvsREal!$C$45,Eventos!N:N) -> 5000 | O45: =SUMIF(Eventos!$B:$B,PPvsREal!$C$45,Eventos!O:O) -> 0 | P45: =SUMIF(Eventos!$B:$B,PPvsREal!$C$45,Eventos!P:P) -> 0 | Q45: =SUMIF(Eventos!$B:$B,PPvsREal!$C$45,Eventos!Q:Q) -> 0 | R45: =SUMIF(Eventos!$B:$B,PPvsREal!$C$45,Eventos!R:R) -> 0 | S45: =SUMIF(Eventos!$B:$B,PPvsREal!$C$45,Eventos!S:S) -> 0 | T45: =SUMIF(Eventos!$B:$B,PPvsREal!$C$45,Eventos!T:T) -> 0 | U45: =SUMIF(Eventos!$B:$B,PPvsREal!$C$45,Eventos!U:U) -> 0 | V45: =SUMIF(Eventos!$B:$B,PPvsREal!$C$45,Eventos!V:V) -> 0 | W45: =SUMIF(Eventos!$B:$B,PPvsREal!$C$45,Eventos!W:W) -> 0 | X45: =SUMIF(Eventos!$B:$B,PPvsREal!$C$45,Eventos!X:X) -> 0 | Y45: =SUMIF(Eventos!$B:$B,PPvsREal!$C$45,Eventos!Y:Y) -> 0 | Z45: =SUMIF(Eventos!$B:$B,PPvsREal!$C$45,Eventos!Z:Z) -> 0 | AA45: =SUMIF(Eventos!$B:$B,PPvsREal!$C$45,Eventos!AA:AA) -> 0
B46: Eventos | C46: 405-014-000-00 | D46: =SUMIF(Eventos!$B:$B,PPvsREal!$C$46,Eventos!D:D) -> 0 | E46: =SUMIF(Eventos!$B:$B,PPvsREal!$C$46,Eventos!E:E) -> 0 | F46: =SUMIF(Eventos!$B:$B,PPvsREal!$C$46,Eventos!F:F) -> 0 | G46: =SUMIF(Eventos!$B:$B,PPvsREal!$C$46,Eventos!G:G) -> 0 | H46: =SUMIF(Eventos!$B:$B,PPvsREal!$C$46,Eventos!H:H) -> 0 | I46: =SUMIF(Eventos!$B:$B,PPvsREal!$C$46,Eventos!I:I) -> 0 | J46: =SUMIF(Eventos!$B:$B,PPvsREal!$C$46,Eventos!J:J) -> 0 | K46: =SUMIF(Eventos!$B:$B,PPvsREal!$C$46,Eventos!K:K) -> 0 | L46: =SUMIF(Eventos!$B:$B,PPvsREal!$C$46,Eventos!L:L) -> 40000 | M46: =SUMIF(Eventos!$B:$B,PPvsREal!$C$46,Eventos!M:M) -> 0 | N46: =SUMIF(Eventos!$B:$B,PPvsREal!$C$46,Eventos!N:N) -> 0 | O46: =SUMIF(Eventos!$B:$B,PPvsREal!$C$46,Eventos!O:O) -> 0 | P46: =SUMIF(Eventos!$B:$B,PPvsREal!$C$46,Eventos!P:P) -> 0 | Q46: =SUMIF(Eventos!$B:$B,PPvsREal!$C$46,Eventos!Q:Q) -> 0 | R46: =SUMIF(Eventos!$B:$B,PPvsREal!$C$46,Eventos!R:R) -> 0 | S46: =SUMIF(Eventos!$B:$B,PPvsREal!$C$46,Eventos!S:S) -> 0 | T46: =SUMIF(Eventos!$B:$B,PPvsREal!$C$46,Eventos!T:T) -> 0 | U46: =SUMIF(Eventos!$B:$B,PPvsREal!$C$46,Eventos!U:U) -> 0 | V46: =SUMIF(Eventos!$B:$B,PPvsREal!$C$46,Eventos!V:V) -> 0 | W46: =SUMIF(Eventos!$B:$B,PPvsREal!$C$46,Eventos!W:W) -> 0 | X46: =SUMIF(Eventos!$B:$B,PPvsREal!$C$46,Eventos!X:X) -> 0 | Y46: =SUMIF(Eventos!$B:$B,PPvsREal!$C$46,Eventos!Y:Y) -> 0 | Z46: =SUMIF(Eventos!$B:$B,PPvsREal!$C$46,Eventos!Z:Z) -> 0 | AA46: =SUMIF(Eventos!$B:$B,PPvsREal!$C$46,Eventos!AA:AA) -> 0
B47: Eventos | C47: 405-008-000-00 | D47: =SUMIF(Eventos!$B:$B,PPvsREal!$C$47,Eventos!D:D) -> 0 | E47: =SUMIF(Eventos!$B:$B,PPvsREal!$C$47,Eventos!E:E) -> 0 | F47: =SUMIF(Eventos!$B:$B,PPvsREal!$C$47,Eventos!F:F) -> 0 | G47: =SUMIF(Eventos!$B:$B,PPvsREal!$C$47,Eventos!G:G) -> 0 | H47: =SUMIF(Eventos!$B:$B,PPvsREal!$C$47,Eventos!H:H) -> 0 | I47: =SUMIF(Eventos!$B:$B,PPvsREal!$C$47,Eventos!I:I) -> 0 | J47: =SUMIF(Eventos!$B:$B,PPvsREal!$C$47,Eventos!J:J) -> 0 | K47: =SUMIF(Eventos!$B:$B,PPvsREal!$C$47,Eventos!K:K) -> 0 | L47: =SUMIF(Eventos!$B:$B,PPvsREal!$C$47,Eventos!L:L) -> 0 | M47: =SUMIF(Eventos!$B:$B,PPvsREal!$C$47,Eventos!M:M) -> 0 | N47: =SUMIF(Eventos!$B:$B,PPvsREal!$C$47,Eventos!N:N) -> 0 | O47: =SUMIF(Eventos!$B:$B,PPvsREal!$C$47,Eventos!O:O) -> 0 | P47: =SUMIF(Eventos!$B:$B,PPvsREal!$C$47,Eventos!P:P) -> 0 | Q47: =SUMIF(Eventos!$B:$B,PPvsREal!$C$47,Eventos!Q:Q) -> 0 | R47: =SUMIF(Eventos!$B:$B,PPvsREal!$C$47,Eventos!R:R) -> 0 | S47: =SUMIF(Eventos!$B:$B,PPvsREal!$C$47,Eventos!S:S) -> 0 | T47: =SUMIF(Eventos!$B:$B,PPvsREal!$C$47,Eventos!T:T) -> 0 | U47: =SUMIF(Eventos!$B:$B,PPvsREal!$C$47,Eventos!U:U) -> 0 | V47: =SUMIF(Eventos!$B:$B,PPvsREal!$C$47,Eventos!V:V) -> 0 | W47: =SUMIF(Eventos!$B:$B,PPvsREal!$C$47,Eventos!W:W) -> 0 | X47: =SUMIF(Eventos!$B:$B,PPvsREal!$C$47,Eventos!X:X) -> 0 | Y47: =SUMIF(Eventos!$B:$B,PPvsREal!$C$47,Eventos!Y:Y) -> 0 | Z47: =SUMIF(Eventos!$B:$B,PPvsREal!$C$47,Eventos!Z:Z) -> 0 | AA47: =SUMIF(Eventos!$B:$B,PPvsREal!$C$47,Eventos!AA:AA) -> 0
B48: Eventos | C48: 405-010-000-00 | D48: =SUMIF(Eventos!$B:$B,PPvsREal!$C$48,Eventos!D:D) -> 0 | E48: =SUMIF(Eventos!$B:$B,PPvsREal!$C$48,Eventos!E:E) -> 0 | F48: =SUMIF(Eventos!$B:$B,PPvsREal!$C$48,Eventos!F:F) -> 0 | G48: =SUMIF(Eventos!$B:$B,PPvsREal!$C$48,Eventos!G:G) -> 0 | H48: =SUMIF(Eventos!$B:$B,PPvsREal!$C$48,Eventos!H:H) -> 60000 | I48: =SUMIF(Eventos!$B:$B,PPvsREal!$C$48,Eventos!I:I) -> 0 | J48: =SUMIF(Eventos!$B:$B,PPvsREal!$C$48,Eventos!J:J) -> 0 | K48: =SUMIF(Eventos!$B:$B,PPvsREal!$C$48,Eventos!K:K) -> 0 | L48: =SUMIF(Eventos!$B:$B,PPvsREal!$C$48,Eventos!L:L) -> 0 | M48: =SUMIF(Eventos!$B:$B,PPvsREal!$C$48,Eventos!M:M) -> 0 | N48: =SUMIF(Eventos!$B:$B,PPvsREal!$C$48,Eventos!N:N) -> 0 | O48: =SUMIF(Eventos!$B:$B,PPvsREal!$C$48,Eventos!O:O) -> 0 | P48: =SUMIF(Eventos!$B:$B,PPvsREal!$C$48,Eventos!P:P) -> 0 | Q48: =SUMIF(Eventos!$B:$B,PPvsREal!$C$48,Eventos!Q:Q) -> 0 | R48: =SUMIF(Eventos!$B:$B,PPvsREal!$C$48,Eventos!R:R) -> 0 | S48: =SUMIF(Eventos!$B:$B,PPvsREal!$C$48,Eventos!S:S) -> 0 | T48: =SUMIF(Eventos!$B:$B,PPvsREal!$C$48,Eventos!T:T) -> 0 | U48: =SUMIF(Eventos!$B:$B,PPvsREal!$C$48,Eventos!U:U) -> 0 | V48: =SUMIF(Eventos!$B:$B,PPvsREal!$C$48,Eventos!V:V) -> 0 | W48: =SUMIF(Eventos!$B:$B,PPvsREal!$C$48,Eventos!W:W) -> 0 | X48: =SUMIF(Eventos!$B:$B,PPvsREal!$C$48,Eventos!X:X) -> 0 | Y48: =SUMIF(Eventos!$B:$B,PPvsREal!$C$48,Eventos!Y:Y) -> 0 | Z48: =SUMIF(Eventos!$B:$B,PPvsREal!$C$48,Eventos!Z:Z) -> 0 | AA48: =SUMIF(Eventos!$B:$B,PPvsREal!$C$48,Eventos!AA:AA) -> 0
B49: Eventos | C49: 405-005-000-00 | D49: =SUMIF(Eventos!$B:$B,PPvsREal!$C$49,Eventos!D:D) -> 0 | E49: =SUMIF(Eventos!$B:$B,PPvsREal!$C$49,Eventos!E:E) -> 0 | F49: =SUMIF(Eventos!$B:$B,PPvsREal!$C$49,Eventos!F:F) -> 0 | G49: =SUMIF(Eventos!$B:$B,PPvsREal!$C$49,Eventos!G:G) -> 0 | H49: =SUMIF(Eventos!$B:$B,PPvsREal!$C$49,Eventos!H:H) -> 0 | I49: =SUMIF(Eventos!$B:$B,PPvsREal!$C$49,Eventos!I:I) -> 0 | J49: =SUMIF(Eventos!$B:$B,PPvsREal!$C$49,Eventos!J:J) -> 0 | K49: =SUMIF(Eventos!$B:$B,PPvsREal!$C$49,Eventos!K:K) -> 0 | L49: =SUMIF(Eventos!$B:$B,PPvsREal!$C$49,Eventos!L:L) -> 0 | M49: =SUMIF(Eventos!$B:$B,PPvsREal!$C$49,Eventos!M:M) -> 0 | N49: =SUMIF(Eventos!$B:$B,PPvsREal!$C$49,Eventos!N:N) -> 0 | O49: =SUMIF(Eventos!$B:$B,PPvsREal!$C$49,Eventos!O:O) -> 0 | P49: =SUMIF(Eventos!$B:$B,PPvsREal!$C$49,Eventos!P:P) -> 0 | Q49: =SUMIF(Eventos!$B:$B,PPvsREal!$C$49,Eventos!Q:Q) -> 0 | R49: =SUMIF(Eventos!$B:$B,PPvsREal!$C$49,Eventos!R:R) -> 0 | S49: =SUMIF(Eventos!$B:$B,PPvsREal!$C$49,Eventos!S:S) -> 0 | T49: =SUMIF(Eventos!$B:$B,PPvsREal!$C$49,Eventos!T:T) -> 0 | U49: =SUMIF(Eventos!$B:$B,PPvsREal!$C$49,Eventos!U:U) -> 0 | V49: =SUMIF(Eventos!$B:$B,PPvsREal!$C$49,Eventos!V:V) -> 0 | W49: =SUMIF(Eventos!$B:$B,PPvsREal!$C$49,Eventos!W:W) -> 0 | X49: =SUMIF(Eventos!$B:$B,PPvsREal!$C$49,Eventos!X:X) -> 0 | Y49: =SUMIF(Eventos!$B:$B,PPvsREal!$C$49,Eventos!Y:Y) -> 0 | Z49: =SUMIF(Eventos!$B:$B,PPvsREal!$C$49,Eventos!Z:Z) -> 0 | AA49: =SUMIF(Eventos!$B:$B,PPvsREal!$C$49,Eventos!AA:AA) -> 0
B50: Eventos | C50: 405-007-000-00 | D50: =SUMIF(Eventos!$B:$B,PPvsREal!$C$50,Eventos!D:D) -> 0 | E50: =SUMIF(Eventos!$B:$B,PPvsREal!$C$50,Eventos!E:E) -> 0 | F50: =SUMIF(Eventos!$B:$B,PPvsREal!$C$50,Eventos!F:F) -> 0 | G50: =SUMIF(Eventos!$B:$B,PPvsREal!$C$50,Eventos!G:G) -> 0 | H50: =SUMIF(Eventos!$B:$B,PPvsREal!$C$50,Eventos!H:H) -> 0 | I50: =SUMIF(Eventos!$B:$B,PPvsREal!$C$50,Eventos!I:I) -> 0 | J50: =SUMIF(Eventos!$B:$B,PPvsREal!$C$50,Eventos!J:J) -> 0 | K50: =SUMIF(Eventos!$B:$B,PPvsREal!$C$50,Eventos!K:K) -> 0 | L50: =SUMIF(Eventos!$B:$B,PPvsREal!$C$50,Eventos!L:L) -> 0 | M50: =SUMIF(Eventos!$B:$B,PPvsREal!$C$50,Eventos!M:M) -> 0 | N50: =SUMIF(Eventos!$B:$B,PPvsREal!$C$50,Eventos!N:N) -> 0 | O50: =SUMIF(Eventos!$B:$B,PPvsREal!$C$50,Eventos!O:O) -> 0 | P50: =SUMIF(Eventos!$B:$B,PPvsREal!$C$50,Eventos!P:P) -> 0 | Q50: =SUMIF(Eventos!$B:$B,PPvsREal!$C$50,Eventos!Q:Q) -> 0 | R50: =SUMIF(Eventos!$B:$B,PPvsREal!$C$50,Eventos!R:R) -> 0 | S50: =SUMIF(Eventos!$B:$B,PPvsREal!$C$50,Eventos!S:S) -> 0 | T50: =SUMIF(Eventos!$B:$B,PPvsREal!$C$50,Eventos!T:T) -> 0 | U50: =SUMIF(Eventos!$B:$B,PPvsREal!$C$50,Eventos!U:U) -> 0 | V50: =SUMIF(Eventos!$B:$B,PPvsREal!$C$50,Eventos!V:V) -> 0 | W50: =SUMIF(Eventos!$B:$B,PPvsREal!$C$50,Eventos!W:W) -> 0 | X50: =SUMIF(Eventos!$B:$B,PPvsREal!$C$50,Eventos!X:X) -> 0 | Y50: =SUMIF(Eventos!$B:$B,PPvsREal!$C$50,Eventos!Y:Y) -> 0 | Z50: =SUMIF(Eventos!$B:$B,PPvsREal!$C$50,Eventos!Z:Z) -> 0 | AA50: =SUMIF(Eventos!$B:$B,PPvsREal!$C$50,Eventos!AA:AA) -> 0
B51: Eventos | C51: 405-004-000-00 | D51: =SUMIF(Eventos!$B:$B,PPvsREal!$C$51,Eventos!D:D) -> 0 | E51: =SUMIF(Eventos!$B:$B,PPvsREal!$C$51,Eventos!E:E) -> 0 | F51: =SUMIF(Eventos!$B:$B,PPvsREal!$C$51,Eventos!F:F) -> 0 | G51: =SUMIF(Eventos!$B:$B,PPvsREal!$C$51,Eventos!G:G) -> 0 | H51: =SUMIF(Eventos!$B:$B,PPvsREal!$C$51,Eventos!H:H) -> 0 | I51: =SUMIF(Eventos!$B:$B,PPvsREal!$C$51,Eventos!I:I) -> 0 | J51: =SUMIF(Eventos!$B:$B,PPvsREal!$C$51,Eventos!J:J) -> 0 | K51: =SUMIF(Eventos!$B:$B,PPvsREal!$C$51,Eventos!K:K) -> 0 | L51: =SUMIF(Eventos!$B:$B,PPvsREal!$C$51,Eventos!L:L) -> 0 | M51: =SUMIF(Eventos!$B:$B,PPvsREal!$C$51,Eventos!M:M) -> 0 | N51: =SUMIF(Eventos!$B:$B,PPvsREal!$C$51,Eventos!N:N) -> 0 | O51: =SUMIF(Eventos!$B:$B,PPvsREal!$C$51,Eventos!O:O) -> 0 | P51: =SUMIF(Eventos!$B:$B,PPvsREal!$C$51,Eventos!P:P) -> 0 | Q51: =SUMIF(Eventos!$B:$B,PPvsREal!$C$51,Eventos!Q:Q) -> 0 | R51: =SUMIF(Eventos!$B:$B,PPvsREal!$C$51,Eventos!R:R) -> 0 | S51: =SUMIF(Eventos!$B:$B,PPvsREal!$C$51,Eventos!S:S) -> 0 | T51: =SUMIF(Eventos!$B:$B,PPvsREal!$C$51,Eventos!T:T) -> 0 | U51: =SUMIF(Eventos!$B:$B,PPvsREal!$C$51,Eventos!U:U) -> 0 | V51: =SUMIF(Eventos!$B:$B,PPvsREal!$C$51,Eventos!V:V) -> 0 | W51: =SUMIF(Eventos!$B:$B,PPvsREal!$C$51,Eventos!W:W) -> 0 | X51: =SUMIF(Eventos!$B:$B,PPvsREal!$C$51,Eventos!X:X) -> 0 | Y51: =SUMIF(Eventos!$B:$B,PPvsREal!$C$51,Eventos!Y:Y) -> 0 | Z51: =SUMIF(Eventos!$B:$B,PPvsREal!$C$51,Eventos!Z:Z) -> 0 | AA51: =SUMIF(Eventos!$B:$B,PPvsREal!$C$51,Eventos!AA:AA) -> 0
B52: Eventos | C52: 405-015-000-00 | D52: =SUMIF(Eventos!$B:$B,PPvsREal!$C$52,Eventos!D:D) -> 0 | E52: =SUMIF(Eventos!$B:$B,PPvsREal!$C$52,Eventos!E:E) -> 0 | F52: =SUMIF(Eventos!$B:$B,PPvsREal!$C$52,Eventos!F:F) -> 0 | G52: =SUMIF(Eventos!$B:$B,PPvsREal!$C$52,Eventos!G:G) -> 0 | H52: =SUMIF(Eventos!$B:$B,PPvsREal!$C$52,Eventos!H:H) -> 0 | I52: =SUMIF(Eventos!$B:$B,PPvsREal!$C$52,Eventos!I:I) -> 0 | J52: =SUMIF(Eventos!$B:$B,PPvsREal!$C$52,Eventos!J:J) -> 0 | K52: =SUMIF(Eventos!$B:$B,PPvsREal!$C$52,Eventos!K:K) -> 0 | L52: =SUMIF(Eventos!$B:$B,PPvsREal!$C$52,Eventos!L:L) -> 0 | M52: =SUMIF(Eventos!$B:$B,PPvsREal!$C$52,Eventos!M:M) -> 0 | N52: =SUMIF(Eventos!$B:$B,PPvsREal!$C$52,Eventos!N:N) -> 0 | O52: =SUMIF(Eventos!$B:$B,PPvsREal!$C$52,Eventos!O:O) -> 0 | P52: =SUMIF(Eventos!$B:$B,PPvsREal!$C$52,Eventos!P:P) -> 0 | Q52: =SUMIF(Eventos!$B:$B,PPvsREal!$C$52,Eventos!Q:Q) -> 0 | R52: =SUMIF(Eventos!$B:$B,PPvsREal!$C$52,Eventos!R:R) -> 0 | S52: =SUMIF(Eventos!$B:$B,PPvsREal!$C$52,Eventos!S:S) -> 0 | T52: =SUMIF(Eventos!$B:$B,PPvsREal!$C$52,Eventos!T:T) -> 0 | U52: =SUMIF(Eventos!$B:$B,PPvsREal!$C$52,Eventos!U:U) -> 0 | V52: =SUMIF(Eventos!$B:$B,PPvsREal!$C$52,Eventos!V:V) -> 0 | W52: =SUMIF(Eventos!$B:$B,PPvsREal!$C$52,Eventos!W:W) -> 0 | X52: =SUMIF(Eventos!$B:$B,PPvsREal!$C$52,Eventos!X:X) -> 0 | Y52: =SUMIF(Eventos!$B:$B,PPvsREal!$C$52,Eventos!Y:Y) -> 0 | Z52: =SUMIF(Eventos!$B:$B,PPvsREal!$C$52,Eventos!Z:Z) -> 200000 | AA52: =SUMIF(Eventos!$B:$B,PPvsREal!$C$52,Eventos!AA:AA) -> 0
B53: Eventos | C53: 405-016-000-00 | D53: =SUMIF(Eventos!$B:$B,PPvsREal!$C$53,Eventos!D:D) -> 0 | E53: =SUMIF(Eventos!$B:$B,PPvsREal!$C$53,Eventos!E:E) -> 0 | F53: =SUMIF(Eventos!$B:$B,PPvsREal!$C$53,Eventos!F:F) -> 0 | G53: =SUMIF(Eventos!$B:$B,PPvsREal!$C$53,Eventos!G:G) -> 0 | H53: =SUMIF(Eventos!$B:$B,PPvsREal!$C$53,Eventos!H:H) -> 0 | I53: =SUMIF(Eventos!$B:$B,PPvsREal!$C$53,Eventos!I:I) -> 0 | J53: =SUMIF(Eventos!$B:$B,PPvsREal!$C$53,Eventos!J:J) -> 0 | K53: =SUMIF(Eventos!$B:$B,PPvsREal!$C$53,Eventos!K:K) -> 0 | L53: =SUMIF(Eventos!$B:$B,PPvsREal!$C$53,Eventos!L:L) -> 0 | M53: =SUMIF(Eventos!$B:$B,PPvsREal!$C$53,Eventos!M:M) -> 0 | N53: =SUMIF(Eventos!$B:$B,PPvsREal!$C$53,Eventos!N:N) -> 0 | O53: =SUMIF(Eventos!$B:$B,PPvsREal!$C$53,Eventos!O:O) -> 0 | P53: =SUMIF(Eventos!$B:$B,PPvsREal!$C$53,Eventos!P:P) -> 0 | Q53: =SUMIF(Eventos!$B:$B,PPvsREal!$C$53,Eventos!Q:Q) -> 0 | R53: =SUMIF(Eventos!$B:$B,PPvsREal!$C$53,Eventos!R:R) -> 0 | S53: =SUMIF(Eventos!$B:$B,PPvsREal!$C$53,Eventos!S:S) -> 0 | T53: =SUMIF(Eventos!$B:$B,PPvsREal!$C$53,Eventos!T:T) -> 0 | U53: =SUMIF(Eventos!$B:$B,PPvsREal!$C$53,Eventos!U:U) -> 0 | V53: =SUMIF(Eventos!$B:$B,PPvsREal!$C$53,Eventos!V:V) -> 0 | W53: =SUMIF(Eventos!$B:$B,PPvsREal!$C$53,Eventos!W:W) -> 0 | X53: =SUMIF(Eventos!$B:$B,PPvsREal!$C$53,Eventos!X:X) -> 0 | Y53: =SUMIF(Eventos!$B:$B,PPvsREal!$C$53,Eventos!Y:Y) -> 0 | Z53: =SUMIF(Eventos!$B:$B,PPvsREal!$C$53,Eventos!Z:Z) -> 0 | AA53: =SUMIF(Eventos!$B:$B,PPvsREal!$C$53,Eventos!AA:AA) -> 0
B54: Eventos | C54: 405-012-000-00 | D54: =SUMIF(Eventos!$B:$B,PPvsREal!$C$54,Eventos!D:D) -> 0 | E54: =SUMIF(Eventos!$B:$B,PPvsREal!$C$54,Eventos!E:E) -> 0 | F54: =SUMIF(Eventos!$B:$B,PPvsREal!$C$54,Eventos!F:F) -> 0 | G54: =SUMIF(Eventos!$B:$B,PPvsREal!$C$54,Eventos!G:G) -> 0 | H54: =SUMIF(Eventos!$B:$B,PPvsREal!$C$54,Eventos!H:H) -> 0 | I54: =SUMIF(Eventos!$B:$B,PPvsREal!$C$54,Eventos!I:I) -> 0 | J54: =SUMIF(Eventos!$B:$B,PPvsREal!$C$54,Eventos!J:J) -> 0 | K54: =SUMIF(Eventos!$B:$B,PPvsREal!$C$54,Eventos!K:K) -> 0 | L54: =SUMIF(Eventos!$B:$B,PPvsREal!$C$54,Eventos!L:L) -> 0 | M54: =SUMIF(Eventos!$B:$B,PPvsREal!$C$54,Eventos!M:M) -> 0 | N54: =SUMIF(Eventos!$B:$B,PPvsREal!$C$54,Eventos!N:N) -> 0 | O54: =SUMIF(Eventos!$B:$B,PPvsREal!$C$54,Eventos!O:O) -> 0 | P54: =SUMIF(Eventos!$B:$B,PPvsREal!$C$54,Eventos!P:P) -> 0 | Q54: =SUMIF(Eventos!$B:$B,PPvsREal!$C$54,Eventos!Q:Q) -> 0 | R54: =SUMIF(Eventos!$B:$B,PPvsREal!$C$54,Eventos!R:R) -> 0 | S54: =SUMIF(Eventos!$B:$B,PPvsREal!$C$54,Eventos!S:S) -> 0 | T54: =SUMIF(Eventos!$B:$B,PPvsREal!$C$54,Eventos!T:T) -> 0 | U54: =SUMIF(Eventos!$B:$B,PPvsREal!$C$54,Eventos!U:U) -> 0 | V54: =SUMIF(Eventos!$B:$B,PPvsREal!$C$54,Eventos!V:V) -> 0 | W54: =SUMIF(Eventos!$B:$B,PPvsREal!$C$54,Eventos!W:W) -> 0 | X54: =SUMIF(Eventos!$B:$B,PPvsREal!$C$54,Eventos!X:X) -> 0 | Y54: =SUMIF(Eventos!$B:$B,PPvsREal!$C$54,Eventos!Y:Y) -> 0 | Z54: =SUMIF(Eventos!$B:$B,PPvsREal!$C$54,Eventos!Z:Z) -> 0 | AA54: =SUMIF(Eventos!$B:$B,PPvsREal!$C$54,Eventos!AA:AA) -> 0
B55: Eventos | C55: 406-002-000-00 | D55: =SUMIF(Eventos!$B:$B,PPvsREal!$C$55,Eventos!D:D) -> 0 | E55: =SUMIF(Eventos!$B:$B,PPvsREal!$C$55,Eventos!E:E) -> 0 | F55: =SUMIF(Eventos!$B:$B,PPvsREal!$C$55,Eventos!F:F) -> 0 | G55: =SUMIF(Eventos!$B:$B,PPvsREal!$C$55,Eventos!G:G) -> 0 | H55: =SUMIF(Eventos!$B:$B,PPvsREal!$C$55,Eventos!H:H) -> 300000 | I55: =SUMIF(Eventos!$B:$B,PPvsREal!$C$55,Eventos!I:I) -> 0 | J55: =SUMIF(Eventos!$B:$B,PPvsREal!$C$55,Eventos!J:J) -> 50000 | K55: =SUMIF(Eventos!$B:$B,PPvsREal!$C$55,Eventos!K:K) -> 0 | L55: =SUMIF(Eventos!$B:$B,PPvsREal!$C$55,Eventos!L:L) -> 0 | M55: =SUMIF(Eventos!$B:$B,PPvsREal!$C$55,Eventos!M:M) -> 0 | N55: =SUMIF(Eventos!$B:$B,PPvsREal!$C$55,Eventos!N:N) -> 0 | O55: =SUMIF(Eventos!$B:$B,PPvsREal!$C$55,Eventos!O:O) -> 0 | P55: =SUMIF(Eventos!$B:$B,PPvsREal!$C$55,Eventos!P:P) -> 0 | Q55: =SUMIF(Eventos!$B:$B,PPvsREal!$C$55,Eventos!Q:Q) -> 0 | R55: =SUMIF(Eventos!$B:$B,PPvsREal!$C$55,Eventos!R:R) -> 0 | S55: =SUMIF(Eventos!$B:$B,PPvsREal!$C$55,Eventos!S:S) -> 0 | T55: =SUMIF(Eventos!$B:$B,PPvsREal!$C$55,Eventos!T:T) -> 0 | U55: =SUMIF(Eventos!$B:$B,PPvsREal!$C$55,Eventos!U:U) -> 0 | V55: =SUMIF(Eventos!$B:$B,PPvsREal!$C$55,Eventos!V:V) -> 0 | W55: =SUMIF(Eventos!$B:$B,PPvsREal!$C$55,Eventos!W:W) -> 0 | X55: =SUMIF(Eventos!$B:$B,PPvsREal!$C$55,Eventos!X:X) -> 0 | Y55: =SUMIF(Eventos!$B:$B,PPvsREal!$C$55,Eventos!Y:Y) -> 0 | Z55: =SUMIF(Eventos!$B:$B,PPvsREal!$C$55,Eventos!Z:Z) -> 0 | AA55: =SUMIF(Eventos!$B:$B,PPvsREal!$C$55,Eventos!AA:AA) -> 0
B56: Eventos | C56: 406-001-000-00 | D56: =SUMIF(Eventos!$B:$B,PPvsREal!$C$56,Eventos!D:D) -> 450000 | E56: =SUMIF(Eventos!$B:$B,PPvsREal!$C$56,Eventos!E:E) -> 0 | F56: =SUMIF(Eventos!$B:$B,PPvsREal!$C$56,Eventos!F:F) -> 50000 | G56: =SUMIF(Eventos!$B:$B,PPvsREal!$C$56,Eventos!G:G) -> 0 | H56: =SUMIF(Eventos!$B:$B,PPvsREal!$C$56,Eventos!H:H) -> 0 | I56: =SUMIF(Eventos!$B:$B,PPvsREal!$C$56,Eventos!I:I) -> 0 | J56: =SUMIF(Eventos!$B:$B,PPvsREal!$C$56,Eventos!J:J) -> 0 | K56: =SUMIF(Eventos!$B:$B,PPvsREal!$C$56,Eventos!K:K) -> 0 | L56: =SUMIF(Eventos!$B:$B,PPvsREal!$C$56,Eventos!L:L) -> 0 | M56: =SUMIF(Eventos!$B:$B,PPvsREal!$C$56,Eventos!M:M) -> 0 | N56: =SUMIF(Eventos!$B:$B,PPvsREal!$C$56,Eventos!N:N) -> 0 | O56: =SUMIF(Eventos!$B:$B,PPvsREal!$C$56,Eventos!O:O) -> 0 | P56: =SUMIF(Eventos!$B:$B,PPvsREal!$C$56,Eventos!P:P) -> 0 | Q56: =SUMIF(Eventos!$B:$B,PPvsREal!$C$56,Eventos!Q:Q) -> 0 | R56: =SUMIF(Eventos!$B:$B,PPvsREal!$C$56,Eventos!R:R) -> 0 | S56: =SUMIF(Eventos!$B:$B,PPvsREal!$C$56,Eventos!S:S) -> 0 | T56: =SUMIF(Eventos!$B:$B,PPvsREal!$C$56,Eventos!T:T) -> 0 | U56: =SUMIF(Eventos!$B:$B,PPvsREal!$C$56,Eventos!U:U) -> 0 | V56: =SUMIF(Eventos!$B:$B,PPvsREal!$C$56,Eventos!V:V) -> 0 | W56: =SUMIF(Eventos!$B:$B,PPvsREal!$C$56,Eventos!W:W) -> 0 | X56: =SUMIF(Eventos!$B:$B,PPvsREal!$C$56,Eventos!X:X) -> 0 | Y56: =SUMIF(Eventos!$B:$B,PPvsREal!$C$56,Eventos!Y:Y) -> 0 | Z56: =SUMIF(Eventos!$B:$B,PPvsREal!$C$56,Eventos!Z:Z) -> 0 | AA56: =SUMIF(Eventos!$B:$B,PPvsREal!$C$56,Eventos!AA:AA) -> 0
B57: Eventos | C57: 406-003-000-00 | D57: =SUMIF(Eventos!$B:$B,PPvsREal!$C$57,Eventos!D:D) -> 0 | E57: =SUMIF(Eventos!$B:$B,PPvsREal!$C$57,Eventos!E:E) -> 0 | F57: =SUMIF(Eventos!$B:$B,PPvsREal!$C$57,Eventos!F:F) -> 0 | G57: =SUMIF(Eventos!$B:$B,PPvsREal!$C$57,Eventos!G:G) -> 0 | H57: =SUMIF(Eventos!$B:$B,PPvsREal!$C$57,Eventos!H:H) -> 0 | I57: =SUMIF(Eventos!$B:$B,PPvsREal!$C$57,Eventos!I:I) -> 0 | J57: =SUMIF(Eventos!$B:$B,PPvsREal!$C$57,Eventos!J:J) -> 0 | K57: =SUMIF(Eventos!$B:$B,PPvsREal!$C$57,Eventos!K:K) -> 0 | L57: =SUMIF(Eventos!$B:$B,PPvsREal!$C$57,Eventos!L:L) -> 0 | M57: =SUMIF(Eventos!$B:$B,PPvsREal!$C$57,Eventos!M:M) -> 0 | N57: =SUMIF(Eventos!$B:$B,PPvsREal!$C$57,Eventos!N:N) -> 0 | O57: =SUMIF(Eventos!$B:$B,PPvsREal!$C$57,Eventos!O:O) -> 0 | P57: =SUMIF(Eventos!$B:$B,PPvsREal!$C$57,Eventos!P:P) -> 0 | Q57: =SUMIF(Eventos!$B:$B,PPvsREal!$C$57,Eventos!Q:Q) -> 0 | R57: =SUMIF(Eventos!$B:$B,PPvsREal!$C$57,Eventos!R:R) -> 0 | S57: =SUMIF(Eventos!$B:$B,PPvsREal!$C$57,Eventos!S:S) -> 0 | T57: =SUMIF(Eventos!$B:$B,PPvsREal!$C$57,Eventos!T:T) -> 0 | U57: =SUMIF(Eventos!$B:$B,PPvsREal!$C$57,Eventos!U:U) -> 0 | V57: =SUMIF(Eventos!$B:$B,PPvsREal!$C$57,Eventos!V:V) -> 300000 | W57: =SUMIF(Eventos!$B:$B,PPvsREal!$C$57,Eventos!W:W) -> 0 | X57: =SUMIF(Eventos!$B:$B,PPvsREal!$C$57,Eventos!X:X) -> 50000 | Y57: =SUMIF(Eventos!$B:$B,PPvsREal!$C$57,Eventos!Y:Y) -> 0 | Z57: =SUMIF(Eventos!$B:$B,PPvsREal!$C$57,Eventos!Z:Z) -> 0 | AA57: =SUMIF(Eventos!$B:$B,PPvsREal!$C$57,Eventos!AA:AA) -> 0
B58: Eventos | C58: 406-004-000-00 | D58: =SUMIF(Eventos!$B:$B,PPvsREal!$C$58,Eventos!D:D) -> 0 | E58: =SUMIF(Eventos!$B:$B,PPvsREal!$C$58,Eventos!E:E) -> 0 | F58: =SUMIF(Eventos!$B:$B,PPvsREal!$C$58,Eventos!F:F) -> 0 | G58: =SUMIF(Eventos!$B:$B,PPvsREal!$C$58,Eventos!G:G) -> 0 | H58: =SUMIF(Eventos!$B:$B,PPvsREal!$C$58,Eventos!H:H) -> 0 | I58: =SUMIF(Eventos!$B:$B,PPvsREal!$C$58,Eventos!I:I) -> 0 | J58: =SUMIF(Eventos!$B:$B,PPvsREal!$C$58,Eventos!J:J) -> 0 | K58: =SUMIF(Eventos!$B:$B,PPvsREal!$C$58,Eventos!K:K) -> 0 | L58: =SUMIF(Eventos!$B:$B,PPvsREal!$C$58,Eventos!L:L) -> 0 | M58: =SUMIF(Eventos!$B:$B,PPvsREal!$C$58,Eventos!M:M) -> 0 | N58: =SUMIF(Eventos!$B:$B,PPvsREal!$C$58,Eventos!N:N) -> 0 | O58: =SUMIF(Eventos!$B:$B,PPvsREal!$C$58,Eventos!O:O) -> 0 | P58: =SUMIF(Eventos!$B:$B,PPvsREal!$C$58,Eventos!P:P) -> 0 | Q58: =SUMIF(Eventos!$B:$B,PPvsREal!$C$58,Eventos!Q:Q) -> 0 | R58: =SUMIF(Eventos!$B:$B,PPvsREal!$C$58,Eventos!R:R) -> 0 | S58: =SUMIF(Eventos!$B:$B,PPvsREal!$C$58,Eventos!S:S) -> 0 | T58: =SUMIF(Eventos!$B:$B,PPvsREal!$C$58,Eventos!T:T) -> 0 | U58: =SUMIF(Eventos!$B:$B,PPvsREal!$C$58,Eventos!U:U) -> 0 | V58: =SUMIF(Eventos!$B:$B,PPvsREal!$C$58,Eventos!V:V) -> 0 | W58: =SUMIF(Eventos!$B:$B,PPvsREal!$C$58,Eventos!W:W) -> 0 | X58: =SUMIF(Eventos!$B:$B,PPvsREal!$C$58,Eventos!X:X) -> 0 | Y58: =SUMIF(Eventos!$B:$B,PPvsREal!$C$58,Eventos!Y:Y) -> 0 | Z58: =SUMIF(Eventos!$B:$B,PPvsREal!$C$58,Eventos!Z:Z) -> 0 | AA58: =SUMIF(Eventos!$B:$B,PPvsREal!$C$58,Eventos!AA:AA) -> 0
B59: Eventos | C59: 406-005-000-00 | D59: =SUMIF(Eventos!$B:$B,PPvsREal!$C$59,Eventos!D:D) -> 0 | E59: =SUMIF(Eventos!$B:$B,PPvsREal!$C$59,Eventos!E:E) -> 0 | F59: =SUMIF(Eventos!$B:$B,PPvsREal!$C$59,Eventos!F:F) -> 0 | G59: =SUMIF(Eventos!$B:$B,PPvsREal!$C$59,Eventos!G:G) -> 0 | H59: =SUMIF(Eventos!$B:$B,PPvsREal!$C$59,Eventos!H:H) -> 0 | I59: =SUMIF(Eventos!$B:$B,PPvsREal!$C$59,Eventos!I:I) -> 0 | J59: =SUMIF(Eventos!$B:$B,PPvsREal!$C$59,Eventos!J:J) -> 0 | K59: =SUMIF(Eventos!$B:$B,PPvsREal!$C$59,Eventos!K:K) -> 0 | L59: =SUMIF(Eventos!$B:$B,PPvsREal!$C$59,Eventos!L:L) -> 210000 | M59: =SUMIF(Eventos!$B:$B,PPvsREal!$C$59,Eventos!M:M) -> 0 | N59: =SUMIF(Eventos!$B:$B,PPvsREal!$C$59,Eventos!N:N) -> 20000 | O59: =SUMIF(Eventos!$B:$B,PPvsREal!$C$59,Eventos!O:O) -> 0 | P59: =SUMIF(Eventos!$B:$B,PPvsREal!$C$59,Eventos!P:P) -> 0 | Q59: =SUMIF(Eventos!$B:$B,PPvsREal!$C$59,Eventos!Q:Q) -> 0 | R59: =SUMIF(Eventos!$B:$B,PPvsREal!$C$59,Eventos!R:R) -> 0 | S59: =SUMIF(Eventos!$B:$B,PPvsREal!$C$59,Eventos!S:S) -> 0 | T59: =SUMIF(Eventos!$B:$B,PPvsREal!$C$59,Eventos!T:T) -> 0 | U59: =SUMIF(Eventos!$B:$B,PPvsREal!$C$59,Eventos!U:U) -> 0 | V59: =SUMIF(Eventos!$B:$B,PPvsREal!$C$59,Eventos!V:V) -> 0 | W59: =SUMIF(Eventos!$B:$B,PPvsREal!$C$59,Eventos!W:W) -> 0 | X59: =SUMIF(Eventos!$B:$B,PPvsREal!$C$59,Eventos!X:X) -> 0 | Y59: =SUMIF(Eventos!$B:$B,PPvsREal!$C$59,Eventos!Y:Y) -> 0 | Z59: =SUMIF(Eventos!$B:$B,PPvsREal!$C$59,Eventos!Z:Z) -> 0 | AA59: =SUMIF(Eventos!$B:$B,PPvsREal!$C$59,Eventos!AA:AA) -> 0
B60: Eventos | C60: 406-006-000-00 | D60: =SUMIF(Eventos!$B:$B,PPvsREal!$C$60,Eventos!D:D) -> 0 | E60: =SUMIF(Eventos!$B:$B,PPvsREal!$C$60,Eventos!E:E) -> 0 | F60: =SUMIF(Eventos!$B:$B,PPvsREal!$C$60,Eventos!F:F) -> 0 | G60: =SUMIF(Eventos!$B:$B,PPvsREal!$C$60,Eventos!G:G) -> 0 | H60: =SUMIF(Eventos!$B:$B,PPvsREal!$C$60,Eventos!H:H) -> 0 | I60: =SUMIF(Eventos!$B:$B,PPvsREal!$C$60,Eventos!I:I) -> 0 | J60: =SUMIF(Eventos!$B:$B,PPvsREal!$C$60,Eventos!J:J) -> 0 | K60: =SUMIF(Eventos!$B:$B,PPvsREal!$C$60,Eventos!K:K) -> 0 | L60: =SUMIF(Eventos!$B:$B,PPvsREal!$C$60,Eventos!L:L) -> 170000 | M60: =SUMIF(Eventos!$B:$B,PPvsREal!$C$60,Eventos!M:M) -> 0 | N60: =SUMIF(Eventos!$B:$B,PPvsREal!$C$60,Eventos!N:N) -> 0 | O60: =SUMIF(Eventos!$B:$B,PPvsREal!$C$60,Eventos!O:O) -> 0 | P60: =SUMIF(Eventos!$B:$B,PPvsREal!$C$60,Eventos!P:P) -> 0 | Q60: =SUMIF(Eventos!$B:$B,PPvsREal!$C$60,Eventos!Q:Q) -> 0 | R60: =SUMIF(Eventos!$B:$B,PPvsREal!$C$60,Eventos!R:R) -> 0 | S60: =SUMIF(Eventos!$B:$B,PPvsREal!$C$60,Eventos!S:S) -> 0 | T60: =SUMIF(Eventos!$B:$B,PPvsREal!$C$60,Eventos!T:T) -> 0 | U60: =SUMIF(Eventos!$B:$B,PPvsREal!$C$60,Eventos!U:U) -> 0 | V60: =SUMIF(Eventos!$B:$B,PPvsREal!$C$60,Eventos!V:V) -> 0 | W60: =SUMIF(Eventos!$B:$B,PPvsREal!$C$60,Eventos!W:W) -> 0 | X60: =SUMIF(Eventos!$B:$B,PPvsREal!$C$60,Eventos!X:X) -> 0 | Y60: =SUMIF(Eventos!$B:$B,PPvsREal!$C$60,Eventos!Y:Y) -> 0 | Z60: =SUMIF(Eventos!$B:$B,PPvsREal!$C$60,Eventos!Z:Z) -> 0 | AA60: =SUMIF(Eventos!$B:$B,PPvsREal!$C$60,Eventos!AA:AA) -> 0
B61: Eventos | C61: 406-007-000-00 | D61: =SUMIF(Eventos!$B:$B,PPvsREal!$C$61,Eventos!D:D) -> 0 | E61: =SUMIF(Eventos!$B:$B,PPvsREal!$C$61,Eventos!E:E) -> 0 | F61: =SUMIF(Eventos!$B:$B,PPvsREal!$C$61,Eventos!F:F) -> 0 | G61: =SUMIF(Eventos!$B:$B,PPvsREal!$C$61,Eventos!G:G) -> 0 | H61: =SUMIF(Eventos!$B:$B,PPvsREal!$C$61,Eventos!H:H) -> 0 | I61: =SUMIF(Eventos!$B:$B,PPvsREal!$C$61,Eventos!I:I) -> 0 | J61: =SUMIF(Eventos!$B:$B,PPvsREal!$C$61,Eventos!J:J) -> 0 | K61: =SUMIF(Eventos!$B:$B,PPvsREal!$C$61,Eventos!K:K) -> 0 | L61: =SUMIF(Eventos!$B:$B,PPvsREal!$C$61,Eventos!L:L) -> 0 | M61: =SUMIF(Eventos!$B:$B,PPvsREal!$C$61,Eventos!M:M) -> 0 | N61: =SUMIF(Eventos!$B:$B,PPvsREal!$C$61,Eventos!N:N) -> 0 | O61: =SUMIF(Eventos!$B:$B,PPvsREal!$C$61,Eventos!O:O) -> 0 | P61: =SUMIF(Eventos!$B:$B,PPvsREal!$C$61,Eventos!P:P) -> 0 | Q61: =SUMIF(Eventos!$B:$B,PPvsREal!$C$61,Eventos!Q:Q) -> 0 | R61: =SUMIF(Eventos!$B:$B,PPvsREal!$C$61,Eventos!R:R) -> 0 | S61: =SUMIF(Eventos!$B:$B,PPvsREal!$C$61,Eventos!S:S) -> 0 | T61: =SUMIF(Eventos!$B:$B,PPvsREal!$C$61,Eventos!T:T) -> 0 | U61: =SUMIF(Eventos!$B:$B,PPvsREal!$C$61,Eventos!U:U) -> 0 | V61: =SUMIF(Eventos!$B:$B,PPvsREal!$C$61,Eventos!V:V) -> 0 | W61: =SUMIF(Eventos!$B:$B,PPvsREal!$C$61,Eventos!W:W) -> 0 | X61: =SUMIF(Eventos!$B:$B,PPvsREal!$C$61,Eventos!X:X) -> 0 | Y61: =SUMIF(Eventos!$B:$B,PPvsREal!$C$61,Eventos!Y:Y) -> 0 | Z61: =SUMIF(Eventos!$B:$B,PPvsREal!$C$61,Eventos!Z:Z) -> 0 | AA61: =SUMIF(Eventos!$B:$B,PPvsREal!$C$61,Eventos!AA:AA) -> 0
B62: Eventos | C62: 406-008-000-00 | D62: =SUMIF(Eventos!$B:$B,PPvsREal!$C$62,Eventos!D:D) -> 0 | E62: =SUMIF(Eventos!$B:$B,PPvsREal!$C$62,Eventos!E:E) -> 0 | F62: =SUMIF(Eventos!$B:$B,PPvsREal!$C$62,Eventos!F:F) -> 0 | G62: =SUMIF(Eventos!$B:$B,PPvsREal!$C$62,Eventos!G:G) -> 0 | H62: =SUMIF(Eventos!$B:$B,PPvsREal!$C$62,Eventos!H:H) -> 180000 | I62: =SUMIF(Eventos!$B:$B,PPvsREal!$C$62,Eventos!I:I) -> 0 | J62: =SUMIF(Eventos!$B:$B,PPvsREal!$C$62,Eventos!J:J) -> 0 | K62: =SUMIF(Eventos!$B:$B,PPvsREal!$C$62,Eventos!K:K) -> 0 | L62: =SUMIF(Eventos!$B:$B,PPvsREal!$C$62,Eventos!L:L) -> 0 | M62: =SUMIF(Eventos!$B:$B,PPvsREal!$C$62,Eventos!M:M) -> 0 | N62: =SUMIF(Eventos!$B:$B,PPvsREal!$C$62,Eventos!N:N) -> 0 | O62: =SUMIF(Eventos!$B:$B,PPvsREal!$C$62,Eventos!O:O) -> 0 | P62: =SUMIF(Eventos!$B:$B,PPvsREal!$C$62,Eventos!P:P) -> 0 | Q62: =SUMIF(Eventos!$B:$B,PPvsREal!$C$62,Eventos!Q:Q) -> 0 | R62: =SUMIF(Eventos!$B:$B,PPvsREal!$C$62,Eventos!R:R) -> 0 | S62: =SUMIF(Eventos!$B:$B,PPvsREal!$C$62,Eventos!S:S) -> 0 | T62: =SUMIF(Eventos!$B:$B,PPvsREal!$C$62,Eventos!T:T) -> 0 | U62: =SUMIF(Eventos!$B:$B,PPvsREal!$C$62,Eventos!U:U) -> 0 | V62: =SUMIF(Eventos!$B:$B,PPvsREal!$C$62,Eventos!V:V) -> 0 | W62: =SUMIF(Eventos!$B:$B,PPvsREal!$C$62,Eventos!W:W) -> 0 | X62: =SUMIF(Eventos!$B:$B,PPvsREal!$C$62,Eventos!X:X) -> 0 | Y62: =SUMIF(Eventos!$B:$B,PPvsREal!$C$62,Eventos!Y:Y) -> 0 | Z62: =SUMIF(Eventos!$B:$B,PPvsREal!$C$62,Eventos!Z:Z) -> 0 | AA62: =SUMIF(Eventos!$B:$B,PPvsREal!$C$62,Eventos!AA:AA) -> 0
B63: Eventos | C63: 406-009-000-00 | D63: =SUMIF(Eventos!$B:$B,PPvsREal!$C$63,Eventos!D:D) -> 0 | E63: =SUMIF(Eventos!$B:$B,PPvsREal!$C$63,Eventos!E:E) -> 0 | F63: =SUMIF(Eventos!$B:$B,PPvsREal!$C$63,Eventos!F:F) -> 100000 | G63: =SUMIF(Eventos!$B:$B,PPvsREal!$C$63,Eventos!G:G) -> 0 | H63: =SUMIF(Eventos!$B:$B,PPvsREal!$C$63,Eventos!H:H) -> 0 | I63: =SUMIF(Eventos!$B:$B,PPvsREal!$C$63,Eventos!I:I) -> 0 | J63: =SUMIF(Eventos!$B:$B,PPvsREal!$C$63,Eventos!J:J) -> 0 | K63: =SUMIF(Eventos!$B:$B,PPvsREal!$C$63,Eventos!K:K) -> 0 | L63: =SUMIF(Eventos!$B:$B,PPvsREal!$C$63,Eventos!L:L) -> 0 | M63: =SUMIF(Eventos!$B:$B,PPvsREal!$C$63,Eventos!M:M) -> 0 | N63: =SUMIF(Eventos!$B:$B,PPvsREal!$C$63,Eventos!N:N) -> 0 | O63: =SUMIF(Eventos!$B:$B,PPvsREal!$C$63,Eventos!O:O) -> 0 | P63: =SUMIF(Eventos!$B:$B,PPvsREal!$C$63,Eventos!P:P) -> 100000 | Q63: =SUMIF(Eventos!$B:$B,PPvsREal!$C$63,Eventos!Q:Q) -> 0 | R63: =SUMIF(Eventos!$B:$B,PPvsREal!$C$63,Eventos!R:R) -> 0 | S63: =SUMIF(Eventos!$B:$B,PPvsREal!$C$63,Eventos!S:S) -> 0 | T63: =SUMIF(Eventos!$B:$B,PPvsREal!$C$63,Eventos!T:T) -> 0 | U63: =SUMIF(Eventos!$B:$B,PPvsREal!$C$63,Eventos!U:U) -> 0 | V63: =SUMIF(Eventos!$B:$B,PPvsREal!$C$63,Eventos!V:V) -> 0 | W63: =SUMIF(Eventos!$B:$B,PPvsREal!$C$63,Eventos!W:W) -> 0 | X63: =SUMIF(Eventos!$B:$B,PPvsREal!$C$63,Eventos!X:X) -> 100000 | Y63: =SUMIF(Eventos!$B:$B,PPvsREal!$C$63,Eventos!Y:Y) -> 0 | Z63: =SUMIF(Eventos!$B:$B,PPvsREal!$C$63,Eventos!Z:Z) -> 0 | AA63: =SUMIF(Eventos!$B:$B,PPvsREal!$C$63,Eventos!AA:AA) -> 0
B64: Eventos | C64: 406-010-000-00 | D64: =SUMIF(Eventos!$B:$B,PPvsREal!$C$64,Eventos!D:D) -> 0 | E64: =SUMIF(Eventos!$B:$B,PPvsREal!$C$64,Eventos!E:E) -> 0 | F64: =SUMIF(Eventos!$B:$B,PPvsREal!$C$64,Eventos!F:F) -> 0 | G64: =SUMIF(Eventos!$B:$B,PPvsREal!$C$64,Eventos!G:G) -> 0 | H64: =SUMIF(Eventos!$B:$B,PPvsREal!$C$64,Eventos!H:H) -> 0 | I64: =SUMIF(Eventos!$B:$B,PPvsREal!$C$64,Eventos!I:I) -> 0 | J64: =SUMIF(Eventos!$B:$B,PPvsREal!$C$64,Eventos!J:J) -> 0 | K64: =SUMIF(Eventos!$B:$B,PPvsREal!$C$64,Eventos!K:K) -> 0 | L64: =SUMIF(Eventos!$B:$B,PPvsREal!$C$64,Eventos!L:L) -> 0 | M64: =SUMIF(Eventos!$B:$B,PPvsREal!$C$64,Eventos!M:M) -> 0 | N64: =SUMIF(Eventos!$B:$B,PPvsREal!$C$64,Eventos!N:N) -> 0 | O64: =SUMIF(Eventos!$B:$B,PPvsREal!$C$64,Eventos!O:O) -> 0 | P64: =SUMIF(Eventos!$B:$B,PPvsREal!$C$64,Eventos!P:P) -> 0 | Q64: =SUMIF(Eventos!$B:$B,PPvsREal!$C$64,Eventos!Q:Q) -> 0 | R64: =SUMIF(Eventos!$B:$B,PPvsREal!$C$64,Eventos!R:R) -> 0 | S64: =SUMIF(Eventos!$B:$B,PPvsREal!$C$64,Eventos!S:S) -> 0 | T64: =SUMIF(Eventos!$B:$B,PPvsREal!$C$64,Eventos!T:T) -> 0 | U64: =SUMIF(Eventos!$B:$B,PPvsREal!$C$64,Eventos!U:U) -> 0 | V64: =SUMIF(Eventos!$B:$B,PPvsREal!$C$64,Eventos!V:V) -> 0 | W64: =SUMIF(Eventos!$B:$B,PPvsREal!$C$64,Eventos!W:W) -> 0 | X64: =SUMIF(Eventos!$B:$B,PPvsREal!$C$64,Eventos!X:X) -> 0 | Y64: =SUMIF(Eventos!$B:$B,PPvsREal!$C$64,Eventos!Y:Y) -> 0 | Z64: =SUMIF(Eventos!$B:$B,PPvsREal!$C$64,Eventos!Z:Z) -> 0 | AA64: =SUMIF(Eventos!$B:$B,PPvsREal!$C$64,Eventos!AA:AA) -> 0
B65: Eventos | C65: 406-011-000-00 | D65: =SUMIF(Eventos!$B:$B,PPvsREal!$C$65,Eventos!D:D) -> 0 | E65: =SUMIF(Eventos!$B:$B,PPvsREal!$C$65,Eventos!E:E) -> 0 | F65: =SUMIF(Eventos!$B:$B,PPvsREal!$C$65,Eventos!F:F) -> 0 | G65: =SUMIF(Eventos!$B:$B,PPvsREal!$C$65,Eventos!G:G) -> 0 | H65: =SUMIF(Eventos!$B:$B,PPvsREal!$C$65,Eventos!H:H) -> 0 | I65: =SUMIF(Eventos!$B:$B,PPvsREal!$C$65,Eventos!I:I) -> 0 | J65: =SUMIF(Eventos!$B:$B,PPvsREal!$C$65,Eventos!J:J) -> 0 | K65: =SUMIF(Eventos!$B:$B,PPvsREal!$C$65,Eventos!K:K) -> 0 | L65: =SUMIF(Eventos!$B:$B,PPvsREal!$C$65,Eventos!L:L) -> 0 | M65: =SUMIF(Eventos!$B:$B,PPvsREal!$C$65,Eventos!M:M) -> 0 | N65: =SUMIF(Eventos!$B:$B,PPvsREal!$C$65,Eventos!N:N) -> 0 | O65: =SUMIF(Eventos!$B:$B,PPvsREal!$C$65,Eventos!O:O) -> 0 | P65: =SUMIF(Eventos!$B:$B,PPvsREal!$C$65,Eventos!P:P) -> 0 | Q65: =SUMIF(Eventos!$B:$B,PPvsREal!$C$65,Eventos!Q:Q) -> 0 | R65: =SUMIF(Eventos!$B:$B,PPvsREal!$C$65,Eventos!R:R) -> 0 | S65: =SUMIF(Eventos!$B:$B,PPvsREal!$C$65,Eventos!S:S) -> 0 | T65: =SUMIF(Eventos!$B:$B,PPvsREal!$C$65,Eventos!T:T) -> 0 | U65: =SUMIF(Eventos!$B:$B,PPvsREal!$C$65,Eventos!U:U) -> 0 | V65: =SUMIF(Eventos!$B:$B,PPvsREal!$C$65,Eventos!V:V) -> 0 | W65: =SUMIF(Eventos!$B:$B,PPvsREal!$C$65,Eventos!W:W) -> 0 | X65: =SUMIF(Eventos!$B:$B,PPvsREal!$C$65,Eventos!X:X) -> 0 | Y65: =SUMIF(Eventos!$B:$B,PPvsREal!$C$65,Eventos!Y:Y) -> 0 | Z65: =SUMIF(Eventos!$B:$B,PPvsREal!$C$65,Eventos!Z:Z) -> 0 | AA65: =SUMIF(Eventos!$B:$B,PPvsREal!$C$65,Eventos!AA:AA) -> 0
B66: Eventos | C66: 406-014-000-00 | D66: =SUMIF(Eventos!$B:$B,$C$66,Eventos!D:D) -> 0 | E66: =SUMIF(Eventos!$B:$B,$C$66,Eventos!E:E) -> 0 | F66: =SUMIF(Eventos!$B:$B,$C$66,Eventos!F:F) -> 0 | G66: =SUMIF(Eventos!$B:$B,$C$66,Eventos!G:G) -> 0 | H66: =SUMIF(Eventos!$B:$B,$C$66,Eventos!H:H) -> 0 | I66: =SUMIF(Eventos!$B:$B,$C$66,Eventos!I:I) -> 0 | J66: =SUMIF(Eventos!$B:$B,$C$66,Eventos!J:J) -> 0 | K66: =SUMIF(Eventos!$B:$B,$C$66,Eventos!K:K) -> 0 | L66: =SUMIF(Eventos!$B:$B,$C$66,Eventos!L:L) -> 0 | M66: =SUMIF(Eventos!$B:$B,$C$66,Eventos!M:M) -> 0 | N66: =SUMIF(Eventos!$B:$B,$C$66,Eventos!N:N) -> 0 | O66: =SUMIF(Eventos!$B:$B,$C$66,Eventos!O:O) -> 0 | P66: =SUMIF(Eventos!$B:$B,$C$66,Eventos!P:P) -> 0 | Q66: =SUMIF(Eventos!$B:$B,$C$66,Eventos!Q:Q) -> 0 | R66: =SUMIF(Eventos!$B:$B,$C$66,Eventos!R:R) -> 0 | S66: =SUMIF(Eventos!$B:$B,$C$66,Eventos!S:S) -> 0 | T66: =SUMIF(Eventos!$B:$B,$C$66,Eventos!T:T) -> 0 | U66: =SUMIF(Eventos!$B:$B,$C$66,Eventos!U:U) -> 0 | V66: =SUMIF(Eventos!$B:$B,$C$66,Eventos!V:V) -> 0 | W66: =SUMIF(Eventos!$B:$B,$C$66,Eventos!W:W) -> 0 | X66: =SUMIF(Eventos!$B:$B,$C$66,Eventos!X:X) -> 0 | Y66: =SUMIF(Eventos!$B:$B,$C$66,Eventos!Y:Y) -> 0 | Z66: =SUMIF(Eventos!$B:$B,$C$66,Eventos!Z:Z) -> 400000 | AA66: =SUMIF(Eventos!$B:$B,$C$66,Eventos!AA:AA) -> 0
B67: Eventos | C67: 406-015-000-00 | D67: =SUMIF(Eventos!$B:$B,$C$67,Eventos!D:D) -> 0 | E67: =SUMIF(Eventos!$B:$B,$C$67,Eventos!E:E) -> 0 | F67: =SUMIF(Eventos!$B:$B,$C$67,Eventos!F:F) -> 0 | G67: =SUMIF(Eventos!$B:$B,$C$67,Eventos!G:G) -> 0 | H67: =SUMIF(Eventos!$B:$B,$C$67,Eventos!H:H) -> 0 | I67: =SUMIF(Eventos!$B:$B,$C$67,Eventos!I:I) -> 0 | J67: =SUMIF(Eventos!$B:$B,$C$67,Eventos!J:J) -> 0 | K67: =SUMIF(Eventos!$B:$B,$C$67,Eventos!K:K) -> 0 | L67: =SUMIF(Eventos!$B:$B,$C$67,Eventos!L:L) -> 0 | M67: =SUMIF(Eventos!$B:$B,$C$67,Eventos!M:M) -> 0 | N67: =SUMIF(Eventos!$B:$B,$C$67,Eventos!N:N) -> 50000 | O67: =SUMIF(Eventos!$B:$B,$C$67,Eventos!O:O) -> 0 | P67: =SUMIF(Eventos!$B:$B,$C$67,Eventos!P:P) -> 0 | Q67: =SUMIF(Eventos!$B:$B,$C$67,Eventos!Q:Q) -> 0 | R67: =SUMIF(Eventos!$B:$B,$C$67,Eventos!R:R) -> 0 | S67: =SUMIF(Eventos!$B:$B,$C$67,Eventos!S:S) -> 0 | T67: =SUMIF(Eventos!$B:$B,$C$67,Eventos!T:T) -> 0 | U67: =SUMIF(Eventos!$B:$B,$C$67,Eventos!U:U) -> 0 | V67: =SUMIF(Eventos!$B:$B,$C$67,Eventos!V:V) -> 50000 | W67: =SUMIF(Eventos!$B:$B,$C$67,Eventos!W:W) -> 0 | X67: =SUMIF(Eventos!$B:$B,$C$67,Eventos!X:X) -> 0 | Y67: =SUMIF(Eventos!$B:$B,$C$67,Eventos!Y:Y) -> 0 | Z67: =SUMIF(Eventos!$B:$B,$C$67,Eventos!Z:Z) -> 0 | AA67: =SUMIF(Eventos!$B:$B,$C$67,Eventos!AA:AA) -> 0
B68: Eventos | C68: 406-013-000-00 | D68: =SUMIF(Eventos!$B:$B,$C$68,Eventos!D:D) -> 0 | E68: =SUMIF(Eventos!$B:$B,$C$68,Eventos!E:E) -> 0 | F68: =SUMIF(Eventos!$B:$B,$C$68,Eventos!F:F) -> 0 | G68: =SUMIF(Eventos!$B:$B,$C$68,Eventos!G:G) -> 0 | H68: =SUMIF(Eventos!$B:$B,$C$68,Eventos!H:H) -> 0 | I68: =SUMIF(Eventos!$B:$B,$C$68,Eventos!I:I) -> 0 | J68: =SUMIF(Eventos!$B:$B,$C$68,Eventos!J:J) -> 0 | K68: =SUMIF(Eventos!$B:$B,$C$68,Eventos!K:K) -> 0 | L68: =SUMIF(Eventos!$B:$B,$C$68,Eventos!L:L) -> 0 | M68: =SUMIF(Eventos!$B:$B,$C$68,Eventos!M:M) -> 0 | N68: =SUMIF(Eventos!$B:$B,$C$68,Eventos!N:N) -> 0 | O68: =SUMIF(Eventos!$B:$B,$C$68,Eventos!O:O) -> 0 | P68: =SUMIF(Eventos!$B:$B,$C$68,Eventos!P:P) -> 0 | Q68: =SUMIF(Eventos!$B:$B,$C$68,Eventos!Q:Q) -> 0 | R68: =SUMIF(Eventos!$B:$B,$C$68,Eventos!R:R) -> 50000 | S68: =SUMIF(Eventos!$B:$B,$C$68,Eventos!S:S) -> 0 | T68: =SUMIF(Eventos!$B:$B,$C$68,Eventos!T:T) -> 0 | U68: =SUMIF(Eventos!$B:$B,$C$68,Eventos!U:U) -> 0 | V68: =SUMIF(Eventos!$B:$B,$C$68,Eventos!V:V) -> 0 | W68: =SUMIF(Eventos!$B:$B,$C$68,Eventos!W:W) -> 0 | X68: =SUMIF(Eventos!$B:$B,$C$68,Eventos!X:X) -> 0 | Y68: =SUMIF(Eventos!$B:$B,$C$68,Eventos!Y:Y) -> 0 | Z68: =SUMIF(Eventos!$B:$B,$C$68,Eventos!Z:Z) -> 0 | AA68: =SUMIF(Eventos!$B:$B,$C$68,Eventos!AA:AA) -> 0
B69: Eventos | C69: 701-002-000-00 | D69: =SUMIF(Eventos!$B:$B,$C$69,Eventos!D:D) -> 0 | E69: =SUMIF(Eventos!$B:$B,$C$69,Eventos!E:E) -> 0 | F69: =SUMIF(Eventos!$B:$B,$C$69,Eventos!F:F) -> 0 | G69: =SUMIF(Eventos!$B:$B,$C$69,Eventos!G:G) -> 0 | H69: =SUMIF(Eventos!$B:$B,$C$69,Eventos!H:H) -> 400000 | I69: =SUMIF(Eventos!$B:$B,$C$69,Eventos!I:I) -> 0 | J69: =SUMIF(Eventos!$B:$B,$C$69,Eventos!J:J) -> 50000 | K69: =SUMIF(Eventos!$B:$B,$C$69,Eventos!K:K) -> 0 | L69: =SUMIF(Eventos!$B:$B,$C$69,Eventos!L:L) -> 0 | M69: =SUMIF(Eventos!$B:$B,$C$69,Eventos!M:M) -> 0 | N69: =SUMIF(Eventos!$B:$B,$C$69,Eventos!N:N) -> 0 | O69: =SUMIF(Eventos!$B:$B,$C$69,Eventos!O:O) -> 0 | P69: =SUMIF(Eventos!$B:$B,$C$69,Eventos!P:P) -> 0 | Q69: =SUMIF(Eventos!$B:$B,$C$69,Eventos!Q:Q) -> 0 | R69: =SUMIF(Eventos!$B:$B,$C$69,Eventos!R:R) -> 0 | S69: =SUMIF(Eventos!$B:$B,$C$69,Eventos!S:S) -> 0 | T69: =SUMIF(Eventos!$B:$B,$C$69,Eventos!T:T) -> 0 | U69: =SUMIF(Eventos!$B:$B,$C$69,Eventos!U:U) -> 0 | V69: =SUMIF(Eventos!$B:$B,$C$69,Eventos!V:V) -> 0 | W69: =SUMIF(Eventos!$B:$B,$C$69,Eventos!W:W) -> 0 | X69: =SUMIF(Eventos!$B:$B,$C$69,Eventos!X:X) -> 0 | Y69: =SUMIF(Eventos!$B:$B,$C$69,Eventos!Y:Y) -> 0 | Z69: =SUMIF(Eventos!$B:$B,$C$69,Eventos!Z:Z) -> 0 | AA69: =SUMIF(Eventos!$B:$B,$C$69,Eventos!AA:AA) -> 0
B70: Eventos | C70: 701-001-000-00 | D70: =SUMIF(Eventos!$B:$B,$C$70,Eventos!D:D) -> 700000 | E70: =SUMIF(Eventos!$B:$B,$C$70,Eventos!E:E) -> 0 | F70: =SUMIF(Eventos!$B:$B,$C$70,Eventos!F:F) -> 150000 | G70: =SUMIF(Eventos!$B:$B,$C$70,Eventos!G:G) -> 0 | H70: =SUMIF(Eventos!$B:$B,$C$70,Eventos!H:H) -> 0 | I70: =SUMIF(Eventos!$B:$B,$C$70,Eventos!I:I) -> 0 | J70: =SUMIF(Eventos!$B:$B,$C$70,Eventos!J:J) -> 0 | K70: =SUMIF(Eventos!$B:$B,$C$70,Eventos!K:K) -> 0 | L70: =SUMIF(Eventos!$B:$B,$C$70,Eventos!L:L) -> 0 | M70: =SUMIF(Eventos!$B:$B,$C$70,Eventos!M:M) -> 0 | N70: =SUMIF(Eventos!$B:$B,$C$70,Eventos!N:N) -> 0 | O70: =SUMIF(Eventos!$B:$B,$C$70,Eventos!O:O) -> 0 | P70: =SUMIF(Eventos!$B:$B,$C$70,Eventos!P:P) -> 0 | Q70: =SUMIF(Eventos!$B:$B,$C$70,Eventos!Q:Q) -> 0 | R70: =SUMIF(Eventos!$B:$B,$C$70,Eventos!R:R) -> 0 | S70: =SUMIF(Eventos!$B:$B,$C$70,Eventos!S:S) -> 0 | T70: =SUMIF(Eventos!$B:$B,$C$70,Eventos!T:T) -> 0 | U70: =SUMIF(Eventos!$B:$B,$C$70,Eventos!U:U) -> 0 | V70: =SUMIF(Eventos!$B:$B,$C$70,Eventos!V:V) -> 0 | W70: =SUMIF(Eventos!$B:$B,$C$70,Eventos!W:W) -> 0 | X70: =SUMIF(Eventos!$B:$B,$C$70,Eventos!X:X) -> 0 | Y70: =SUMIF(Eventos!$B:$B,$C$70,Eventos!Y:Y) -> 0 | Z70: =SUMIF(Eventos!$B:$B,$C$70,Eventos!Z:Z) -> 0 | AA70: =SUMIF(Eventos!$B:$B,$C$70,Eventos!AA:AA) -> 0
